public class AEw extends VHz {
  static {
  
  }
  
  protected float zGp() {
    return -20.0F;
  }
  
  protected void Dne(wHH paramwHH) {
    // Byte code:
    //   0: aload_0
    //   1: getfield Dne : LQnq;
    //   4: getfield aFZ : Z
    //   7: ifne -> 123
    //   10: aload_0
    //   11: getfield Dne : LQnq;
    //   14: sipush #2002
    //   17: aload_0
    //   18: getfield div : D
    //   21: invokestatic round : (D)J
    //   24: l2i
    //   25: aload_0
    //   26: getfield IjH : D
    //   29: invokestatic round : (D)J
    //   32: l2i
    //   33: aload_0
    //   34: getfield mrb : D
    //   37: invokestatic round : (D)J
    //   40: l2i
    //   41: iconst_0
    //   42: invokevirtual Qnq : (IIIII)V
    //   45: iconst_3
    //   46: aload_0
    //   47: getfield Dne : LQnq;
    //   50: getfield Dne : Ljava/util/Random;
    //   53: iconst_5
    //   54: invokevirtual nextInt : (I)I
    //   57: iadd
    //   58: aload_0
    //   59: getfield Dne : LQnq;
    //   62: getfield Dne : Ljava/util/Random;
    //   65: iconst_5
    //   66: invokevirtual nextInt : (I)I
    //   69: iadd
    //   70: istore_2
    //   71: iload_2
    //   72: ifle -> 119
    //   75: iload_2
    //   76: invokestatic Dne : (I)I
    //   79: istore_3
    //   80: iload_2
    //   81: iload_3
    //   82: isub
    //   83: istore_2
    //   84: aload_0
    //   85: getfield Dne : LQnq;
    //   88: new alg
    //   91: dup
    //   92: aload_0
    //   93: getfield Dne : LQnq;
    //   96: aload_0
    //   97: getfield div : D
    //   100: aload_0
    //   101: getfield IjH : D
    //   104: aload_0
    //   105: getfield mrb : D
    //   108: iload_3
    //   109: invokespecial <init> : (LQnq;DDDI)V
    //   112: invokevirtual FWm : (LsMa;)Z
    //   115: pop
    //   116: goto -> 71
    //   119: aload_0
    //   120: invokevirtual g_ : ()V
    //   123: return
  }
  
  public AEw(Qnq paramQnq, FUH paramFUH) {
    super(paramQnq, paramFUH);
  }
  
  protected float DyG() {
    return 0.07F;
  }
  
  public AEw(Qnq paramQnq) {
    super(paramQnq);
  }
  
  public AEw(Qnq paramQnq, double paramDouble1, double paramDouble2, double paramDouble3) {
    super(paramQnq, paramDouble1, paramDouble2, paramDouble3);
  }
  
  protected float bzF() {
    return 0.7F;
  }
}


/* Location:              C:\Users\fract\Downloads\ERROR422.jar!\AEw.class
 * Java compiler version: 8 (52.0)
 * JD-Core Version:       1.1.3
 */