public class AmF extends ZOO {
  Class Dne;
  
  private Wtm Dne;
  
  FUH Dne;
  
  int Dne;
  
  private final pUe Dne;
  
  public AmF(FUH paramFUH, Class paramClass, float paramFloat, int paramInt, boolean paramBoolean1, boolean paramBoolean2) {
    this(paramFUH, paramClass, paramFloat, paramInt, paramBoolean1, paramBoolean2, (pUe)null);
  }
  
  public boolean Dne() {
    // Byte code:
    //   0: aload_0
    //   1: getfield Dne : I
    //   4: ifle -> 26
    //   7: aload_0
    //   8: getfield FWm : LFUH;
    //   11: invokevirtual Dne : ()Ljava/util/Random;
    //   14: aload_0
    //   15: getfield Dne : I
    //   18: invokevirtual nextInt : (I)I
    //   21: ifeq -> 26
    //   24: iconst_0
    //   25: ireturn
    //   26: aload_0
    //   27: getfield Dne : Ljava/lang/Class;
    //   30: ldc FiG
    //   32: if_acmpne -> 74
    //   35: aload_0
    //   36: getfield FWm : LFUH;
    //   39: getfield Dne : LQnq;
    //   42: aload_0
    //   43: getfield FWm : LFUH;
    //   46: aload_0
    //   47: getfield Dne : F
    //   50: f2d
    //   51: invokevirtual FWm : (LsMa;D)LFiG;
    //   54: astore_1
    //   55: aload_0
    //   56: aload_1
    //   57: iconst_0
    //   58: invokevirtual Dne : (LFUH;Z)Z
    //   61: ifeq -> 71
    //   64: aload_0
    //   65: aload_1
    //   66: putfield Dne : LFUH;
    //   69: iconst_1
    //   70: ireturn
    //   71: goto -> 177
    //   74: aload_0
    //   75: getfield FWm : LFUH;
    //   78: getfield Dne : LQnq;
    //   81: aload_0
    //   82: getfield Dne : Ljava/lang/Class;
    //   85: aload_0
    //   86: getfield FWm : LFUH;
    //   89: getfield Dne : LbSp;
    //   92: aload_0
    //   93: getfield Dne : F
    //   96: f2d
    //   97: ldc2_w 4.0
    //   100: aload_0
    //   101: getfield Dne : F
    //   104: f2d
    //   105: invokevirtual FWm : (DDD)LbSp;
    //   108: aload_0
    //   109: getfield Dne : LpUe;
    //   112: invokevirtual Dne : (Ljava/lang/Class;LbSp;LpUe;)Ljava/util/List;
    //   115: astore_1
    //   116: aload_1
    //   117: aload_0
    //   118: getfield Dne : LWtm;
    //   121: invokestatic sort : (Ljava/util/List;Ljava/util/Comparator;)V
    //   124: aload_1
    //   125: invokeinterface iterator : ()Ljava/util/Iterator;
    //   130: astore_2
    //   131: aload_2
    //   132: invokeinterface hasNext : ()Z
    //   137: ifeq -> 177
    //   140: aload_2
    //   141: invokeinterface next : ()Ljava/lang/Object;
    //   146: checkcast sMa
    //   149: astore_3
    //   150: aload_3
    //   151: checkcast FUH
    //   154: astore #4
    //   156: aload_0
    //   157: aload #4
    //   159: iconst_0
    //   160: invokevirtual Dne : (LFUH;Z)Z
    //   163: ifeq -> 174
    //   166: aload_0
    //   167: aload #4
    //   169: putfield Dne : LFUH;
    //   172: iconst_1
    //   173: ireturn
    //   174: goto -> 131
    //   177: iconst_0
    //   178: ireturn
  }
  
  public AmF(FUH paramFUH, Class paramClass, float paramFloat, int paramInt, boolean paramBoolean) {
    this(paramFUH, paramClass, paramFloat, paramInt, paramBoolean, false);
  }
  
  public AmF(FUH paramFUH, Class paramClass, float paramFloat, int paramInt, boolean paramBoolean1, boolean paramBoolean2, pUe parampUe) {
    super(paramFUH, paramFloat, paramBoolean1, paramBoolean2);
    this.Dne = (pUe)paramClass;
    this.Dne = paramFloat;
    this.Dne = paramInt;
    this.Dne = (pUe)new Wtm(this, paramFUH);
    this.Dne = parampUe;
    Dne(1);
  }
  
  public void Dne() {
    // Byte code:
    //   0: aload_0
    //   1: getfield FWm : LFUH;
    //   4: aload_0
    //   5: getfield Dne : LFUH;
    //   8: invokevirtual FWm : (LFUH;)V
    //   11: aload_0
    //   12: invokespecial Dne : ()V
    //   15: return
  }
}


/* Location:              C:\Users\fract\Downloads\ERROR422.jar!\AmF.class
 * Java compiler version: 8 (52.0)
 * JD-Core Version:       1.1.3
 */