public class AOl {
  long Dne;
  
  long zGp;
  
  int DyG;
  
  int XHL;
  
  float[] Dne;
  
  int kGO;
  
  Object[][] Dne;
  
  int Qnq;
  
  byte[] bzF;
  
  long bzF;
  
  Object[] Dne;
  
  int zGp;
  
  byte[] Dne;
  
  int bzF;
  
  int aFZ;
  
  float[][] Dne;
  
  zbP[] Dne;
  
  byte[] FWm;
  
  int div;
  
  int Zpi;
  
  int udO;
  
  float[][][][][] Dne;
  
  long FWm;
  
  int mrb;
  
  Lth Dne = (Lth)new Object[2][];
  
  long aFZ;
  
  long Qnq;
  
  static final int FWm;
  
  static final float Dne = 3.1415927F;
  
  static final int Dne = 1;
  
  int IjH;
  
  public AOl() {
    this.Dne = new float[2][][][][];
    this.Dne[0] = new float[2][][][];
    this.Dne[0][0] = new float[2][][];
    this.Dne[0][1] = new float[2][][];
    this.Dne[0][0][0] = new float[2][];
    this.Dne[0][0][1] = new float[2][];
    this.Dne[0][1][0] = new float[2][];
    this.Dne[0][1][1] = new float[2][];
    this.Dne[1] = new float[2][][][];
    this.Dne[1][0] = new float[2][][];
    this.Dne[1][1] = new float[2][][];
    this.Dne[1][0][0] = new float[2][];
    this.Dne[1][0][1] = new float[2][];
    this.Dne[1][1][0] = new float[2][];
    this.Dne[1][1][1] = new float[2][];
  }
  
  public void Dne() {}
  
  public int Dne(int paramInt) {
    if (paramInt != 0 && this.DyG + paramInt > this.udO)
      return -1; 
    this.DyG += paramInt;
    return 0;
  }
  
  public int Dne(float[][][] paramArrayOffloat, int[] paramArrayOfint) {
    if (this.DyG < this.udO) {
      if (paramArrayOffloat != null) {
        for (byte b = 0; b < this.Dne.FWm; b++)
          paramArrayOfint[b] = this.DyG; 
        paramArrayOffloat[0] = this.Dne;
      } 
      return this.udO - this.DyG;
    } 
    return 0;
  }
  
  int Dne(Lth paramLth, boolean paramBoolean) {
    // Byte code:
    //   0: aload_0
    //   1: aload_1
    //   2: putfield Dne : LLth;
    //   5: aload_0
    //   6: aload_1
    //   7: getfield DyG : I
    //   10: invokestatic FWm : (I)I
    //   13: putfield Qnq : I
    //   16: aload_0
    //   17: getfield Dne : [[Ljava/lang/Object;
    //   20: iconst_0
    //   21: iconst_1
    //   22: anewarray java/lang/Object
    //   25: aastore
    //   26: aload_0
    //   27: getfield Dne : [[Ljava/lang/Object;
    //   30: iconst_1
    //   31: iconst_1
    //   32: anewarray java/lang/Object
    //   35: aastore
    //   36: aload_0
    //   37: getfield Dne : [[Ljava/lang/Object;
    //   40: iconst_0
    //   41: aaload
    //   42: iconst_0
    //   43: new Sti
    //   46: dup
    //   47: invokespecial <init> : ()V
    //   50: aastore
    //   51: aload_0
    //   52: getfield Dne : [[Ljava/lang/Object;
    //   55: iconst_1
    //   56: aaload
    //   57: iconst_0
    //   58: new Sti
    //   61: dup
    //   62: invokespecial <init> : ()V
    //   65: aastore
    //   66: aload_0
    //   67: getfield Dne : [[Ljava/lang/Object;
    //   70: iconst_0
    //   71: aaload
    //   72: iconst_0
    //   73: aaload
    //   74: checkcast Sti
    //   77: aload_1
    //   78: getfield Dne : [I
    //   81: iconst_0
    //   82: iaload
    //   83: invokevirtual Dne : (I)V
    //   86: aload_0
    //   87: getfield Dne : [[Ljava/lang/Object;
    //   90: iconst_1
    //   91: aaload
    //   92: iconst_0
    //   93: aaload
    //   94: checkcast Sti
    //   97: aload_1
    //   98: getfield Dne : [I
    //   101: iconst_1
    //   102: iaload
    //   103: invokevirtual Dne : (I)V
    //   106: aload_0
    //   107: getfield Dne : [[[[[F
    //   110: iconst_0
    //   111: aaload
    //   112: iconst_0
    //   113: aaload
    //   114: iconst_0
    //   115: iconst_1
    //   116: anewarray [F
    //   119: aastore
    //   120: aload_0
    //   121: getfield Dne : [[[[[F
    //   124: iconst_0
    //   125: aaload
    //   126: iconst_0
    //   127: aaload
    //   128: iconst_1
    //   129: aload_0
    //   130: getfield Dne : [[[[[F
    //   133: iconst_0
    //   134: aaload
    //   135: iconst_0
    //   136: aaload
    //   137: iconst_0
    //   138: aaload
    //   139: aastore
    //   140: aload_0
    //   141: getfield Dne : [[[[[F
    //   144: iconst_0
    //   145: aaload
    //   146: iconst_1
    //   147: aaload
    //   148: iconst_0
    //   149: aload_0
    //   150: getfield Dne : [[[[[F
    //   153: iconst_0
    //   154: aaload
    //   155: iconst_0
    //   156: aaload
    //   157: iconst_0
    //   158: aaload
    //   159: aastore
    //   160: aload_0
    //   161: getfield Dne : [[[[[F
    //   164: iconst_0
    //   165: aaload
    //   166: iconst_1
    //   167: aaload
    //   168: iconst_1
    //   169: aload_0
    //   170: getfield Dne : [[[[[F
    //   173: iconst_0
    //   174: aaload
    //   175: iconst_0
    //   176: aaload
    //   177: iconst_0
    //   178: aaload
    //   179: aastore
    //   180: aload_0
    //   181: getfield Dne : [[[[[F
    //   184: iconst_1
    //   185: aaload
    //   186: iconst_0
    //   187: aaload
    //   188: iconst_0
    //   189: iconst_1
    //   190: anewarray [F
    //   193: aastore
    //   194: aload_0
    //   195: getfield Dne : [[[[[F
    //   198: iconst_1
    //   199: aaload
    //   200: iconst_0
    //   201: aaload
    //   202: iconst_1
    //   203: iconst_1
    //   204: anewarray [F
    //   207: aastore
    //   208: aload_0
    //   209: getfield Dne : [[[[[F
    //   212: iconst_1
    //   213: aaload
    //   214: iconst_1
    //   215: aaload
    //   216: iconst_0
    //   217: iconst_1
    //   218: anewarray [F
    //   221: aastore
    //   222: aload_0
    //   223: getfield Dne : [[[[[F
    //   226: iconst_1
    //   227: aaload
    //   228: iconst_1
    //   229: aaload
    //   230: iconst_1
    //   231: iconst_1
    //   232: anewarray [F
    //   235: aastore
    //   236: iconst_0
    //   237: istore_3
    //   238: iload_3
    //   239: iconst_1
    //   240: if_icmpge -> 439
    //   243: aload_0
    //   244: getfield Dne : [[[[[F
    //   247: iconst_0
    //   248: aaload
    //   249: iconst_0
    //   250: aaload
    //   251: iconst_0
    //   252: aaload
    //   253: iload_3
    //   254: iload_3
    //   255: aload_1
    //   256: getfield Dne : [I
    //   259: iconst_0
    //   260: iaload
    //   261: aload_1
    //   262: getfield Dne : [I
    //   265: iconst_0
    //   266: iaload
    //   267: iconst_2
    //   268: idiv
    //   269: aload_1
    //   270: getfield Dne : [I
    //   273: iconst_0
    //   274: iaload
    //   275: iconst_2
    //   276: idiv
    //   277: invokestatic Dne : (IIII)[F
    //   280: aastore
    //   281: aload_0
    //   282: getfield Dne : [[[[[F
    //   285: iconst_1
    //   286: aaload
    //   287: iconst_0
    //   288: aaload
    //   289: iconst_0
    //   290: aaload
    //   291: iload_3
    //   292: iload_3
    //   293: aload_1
    //   294: getfield Dne : [I
    //   297: iconst_1
    //   298: iaload
    //   299: aload_1
    //   300: getfield Dne : [I
    //   303: iconst_0
    //   304: iaload
    //   305: iconst_2
    //   306: idiv
    //   307: aload_1
    //   308: getfield Dne : [I
    //   311: iconst_0
    //   312: iaload
    //   313: iconst_2
    //   314: idiv
    //   315: invokestatic Dne : (IIII)[F
    //   318: aastore
    //   319: aload_0
    //   320: getfield Dne : [[[[[F
    //   323: iconst_1
    //   324: aaload
    //   325: iconst_0
    //   326: aaload
    //   327: iconst_1
    //   328: aaload
    //   329: iload_3
    //   330: iload_3
    //   331: aload_1
    //   332: getfield Dne : [I
    //   335: iconst_1
    //   336: iaload
    //   337: aload_1
    //   338: getfield Dne : [I
    //   341: iconst_0
    //   342: iaload
    //   343: iconst_2
    //   344: idiv
    //   345: aload_1
    //   346: getfield Dne : [I
    //   349: iconst_1
    //   350: iaload
    //   351: iconst_2
    //   352: idiv
    //   353: invokestatic Dne : (IIII)[F
    //   356: aastore
    //   357: aload_0
    //   358: getfield Dne : [[[[[F
    //   361: iconst_1
    //   362: aaload
    //   363: iconst_1
    //   364: aaload
    //   365: iconst_0
    //   366: aaload
    //   367: iload_3
    //   368: iload_3
    //   369: aload_1
    //   370: getfield Dne : [I
    //   373: iconst_1
    //   374: iaload
    //   375: aload_1
    //   376: getfield Dne : [I
    //   379: iconst_1
    //   380: iaload
    //   381: iconst_2
    //   382: idiv
    //   383: aload_1
    //   384: getfield Dne : [I
    //   387: iconst_0
    //   388: iaload
    //   389: iconst_2
    //   390: idiv
    //   391: invokestatic Dne : (IIII)[F
    //   394: aastore
    //   395: aload_0
    //   396: getfield Dne : [[[[[F
    //   399: iconst_1
    //   400: aaload
    //   401: iconst_1
    //   402: aaload
    //   403: iconst_1
    //   404: aaload
    //   405: iload_3
    //   406: iload_3
    //   407: aload_1
    //   408: getfield Dne : [I
    //   411: iconst_1
    //   412: iaload
    //   413: aload_1
    //   414: getfield Dne : [I
    //   417: iconst_1
    //   418: iaload
    //   419: iconst_2
    //   420: idiv
    //   421: aload_1
    //   422: getfield Dne : [I
    //   425: iconst_1
    //   426: iaload
    //   427: iconst_2
    //   428: idiv
    //   429: invokestatic Dne : (IIII)[F
    //   432: aastore
    //   433: iinc #3, 1
    //   436: goto -> 238
    //   439: aload_0
    //   440: aload_1
    //   441: getfield Zpi : I
    //   444: anewarray zbP
    //   447: putfield Dne : [LzbP;
    //   450: iconst_0
    //   451: istore_3
    //   452: iload_3
    //   453: aload_1
    //   454: getfield Zpi : I
    //   457: if_icmpge -> 495
    //   460: aload_0
    //   461: getfield Dne : [LzbP;
    //   464: iload_3
    //   465: new zbP
    //   468: dup
    //   469: invokespecial <init> : ()V
    //   472: aastore
    //   473: aload_0
    //   474: getfield Dne : [LzbP;
    //   477: iload_3
    //   478: aaload
    //   479: aload_1
    //   480: getfield Dne : [LVey;
    //   483: iload_3
    //   484: aaload
    //   485: invokevirtual Dne : (LVey;)I
    //   488: pop
    //   489: iinc #3, 1
    //   492: goto -> 452
    //   495: aload_0
    //   496: sipush #8192
    //   499: putfield aFZ : I
    //   502: aload_0
    //   503: aload_1
    //   504: getfield FWm : I
    //   507: anewarray [F
    //   510: putfield Dne : [[F
    //   513: iconst_0
    //   514: istore_3
    //   515: iload_3
    //   516: aload_1
    //   517: getfield FWm : I
    //   520: if_icmpge -> 541
    //   523: aload_0
    //   524: getfield Dne : [[F
    //   527: iload_3
    //   528: aload_0
    //   529: getfield aFZ : I
    //   532: newarray float
    //   534: aastore
    //   535: iinc #3, 1
    //   538: goto -> 515
    //   541: aload_0
    //   542: iconst_0
    //   543: putfield XHL : I
    //   546: aload_0
    //   547: iconst_0
    //   548: putfield Zpi : I
    //   551: aload_0
    //   552: aload_1
    //   553: getfield Dne : [I
    //   556: iconst_1
    //   557: iaload
    //   558: iconst_2
    //   559: idiv
    //   560: putfield udO : I
    //   563: aload_0
    //   564: aload_0
    //   565: getfield udO : I
    //   568: putfield zGp : I
    //   571: aload_0
    //   572: aload_1
    //   573: getfield DyG : I
    //   576: anewarray java/lang/Object
    //   579: putfield Dne : [Ljava/lang/Object;
    //   582: iconst_0
    //   583: istore_3
    //   584: iload_3
    //   585: aload_1
    //   586: getfield DyG : I
    //   589: if_icmpge -> 647
    //   592: aload_1
    //   593: getfield Dne : [LXEH;
    //   596: iload_3
    //   597: aaload
    //   598: getfield Qnq : I
    //   601: istore #4
    //   603: aload_1
    //   604: getfield FWm : [I
    //   607: iload #4
    //   609: iaload
    //   610: istore #5
    //   612: aload_0
    //   613: getfield Dne : [Ljava/lang/Object;
    //   616: iload_3
    //   617: getstatic ghN.Dne : [LghN;
    //   620: iload #5
    //   622: aaload
    //   623: aload_0
    //   624: aload_1
    //   625: getfield Dne : [LXEH;
    //   628: iload_3
    //   629: aaload
    //   630: aload_1
    //   631: getfield Dne : [Ljava/lang/Object;
    //   634: iload #4
    //   636: aaload
    //   637: invokevirtual Dne : (LAOl;LXEH;Ljava/lang/Object;)Ljava/lang/Object;
    //   640: aastore
    //   641: iinc #3, 1
    //   644: goto -> 584
    //   647: iconst_0
    //   648: ireturn
  }
  
  static {
    FWm = 1;
  }
  
  public int Dne(MOU paramMOU) {
    if (this.udO > this.Dne.Dne[1] / 2 && this.DyG > 8192) {
      int i2 = this.udO - this.Dne.Dne[1] / 2;
      i2 = (this.DyG < i2) ? this.DyG : i2;
      this.zGp -= i2;
      this.udO -= i2;
      this.DyG -= i2;
      if (i2 != 0)
        for (byte b1 = 0; b1 < this.Dne.FWm; b1++)
          System.arraycopy(this.Dne[b1], i2, this.Dne[b1], 0, this.zGp);  
    } 
    this.XHL = this.Zpi;
    this.Zpi = paramMOU.FWm;
    this.kGO = -1;
    this.bzF += paramMOU.DyG;
    this.Qnq += paramMOU.div;
    this.aFZ += paramMOU.IjH;
    this.zGp += paramMOU.mrb;
    if (this.FWm + 1L != paramMOU.FWm)
      this.Dne = -1L; 
    this.FWm = paramMOU.FWm;
    int i = this.Dne.Dne[this.Zpi];
    int j = this.udO + this.Dne.Dne[this.XHL] / 4 + i / 4;
    int k = j - i / 2;
    int m = k + i;
    int n = 0;
    int i1 = 0;
    if (m > this.aFZ) {
      this.aFZ = m + this.Dne.Dne[1];
      for (byte b1 = 0; b1 < this.Dne.FWm; b1++) {
        float[] arrayOfFloat = new float[this.aFZ];
        System.arraycopy(this.Dne[b1], 0, arrayOfFloat, 0, (this.Dne[b1]).length);
        this.Dne[b1] = arrayOfFloat;
      } 
    } 
    switch (this.Zpi) {
      case 0:
        n = 0;
        i1 = this.Dne.Dne[0] / 2;
        break;
      case 1:
        n = this.Dne.Dne[1] / 4 - this.Dne.Dne[this.XHL] / 4;
        i1 = n + this.Dne.Dne[this.XHL] / 2;
        break;
    } 
    for (byte b = 0; b < this.Dne.FWm; b++) {
      int i2 = k;
      int i3 = 0;
      for (i3 = n; i3 < i1; i3++)
        this.Dne[b][i2 + i3] = this.Dne[b][i2 + i3] + paramMOU.Dne[b][i3]; 
      while (i3 < i) {
        this.Dne[b][i2 + i3] = paramMOU.Dne[b][i3];
        i3++;
      } 
    } 
    if (this.Dne == -1L) {
      this.Dne = paramMOU.Dne;
    } else {
      this.Dne += (j - this.udO);
      if (paramMOU.Dne != -1L && this.Dne != paramMOU.Dne) {
        if (this.Dne > paramMOU.Dne && paramMOU.zGp != 0)
          j = (int)(j - this.Dne - paramMOU.Dne); 
        this.Dne = paramMOU.Dne;
      } 
    } 
    this.udO = j;
    this.zGp = m;
    if (paramMOU.zGp != 0)
      this.mrb = 1; 
    return 0;
  }
  
  public int Dne(Lth paramLth) {
    Dne(paramLth, false);
    this.DyG = this.udO;
    this.udO -= paramLth.Dne[this.Zpi] / 4 + paramLth.Dne[this.XHL] / 4;
    this.Dne = -1L;
    this.FWm = -1L;
    return 0;
  }
  
  static float[] Dne(int paramInt1, int paramInt2, int paramInt3, int paramInt4) {
    int i;
    int j;
    int k;
    float[] arrayOfFloat = new float[paramInt2];
    switch (paramInt1) {
      case 0:
        i = paramInt2 / 4 - paramInt3 / 2;
        j = paramInt2 - paramInt2 / 4 - paramInt4 / 2;
        for (k = 0; k < paramInt3; k++) {
          float f = (float)((k + 0.5D) / paramInt3 * 3.1415927410125732D / 2.0D);
          f = (float)Math.sin(f);
          f *= f;
          f = (float)(f * 1.5707963705062866D);
          f = (float)Math.sin(f);
          arrayOfFloat[k + i] = f;
        } 
        for (k = i + paramInt3; k < j; k++)
          arrayOfFloat[k] = 1.0F; 
        for (k = 0; k < paramInt4; k++) {
          float f = (float)(((paramInt4 - k) - 0.5D) / paramInt4 * 3.1415927410125732D / 2.0D);
          f = (float)Math.sin(f);
          f *= f;
          f = (float)(f * 1.5707963705062866D);
          f = (float)Math.sin(f);
          arrayOfFloat[k + j] = f;
        } 
        return arrayOfFloat;
    } 
    return null;
  }
  
  AOl(Lth paramLth) {
    this();
    Dne(paramLth, false);
    this.DyG = this.udO;
    this.udO -= paramLth.Dne[this.Zpi] / 4 + paramLth.Dne[this.XHL] / 4;
    this.Dne = -1L;
    this.FWm = -1L;
  }
}


/* Location:              C:\Users\fract\Downloads\ERROR422.jar!\AOl.class
 * Java compiler version: 5 (49.0)
 * JD-Core Version:       1.1.3
 */