public class bcj extends qVZ {
  private fzy Dne;
  
  private int Dne = 0;
  
  public bcj(fzy paramfzy) {
    this.Dne = paramfzy;
  }
  
  public void Dne() {
    // Byte code:
    //   0: aload_0
    //   1: getfield Dne : Ljava/util/List;
    //   4: invokeinterface clear : ()V
    //   9: return
  }
  
  public void Dne(int paramInt1, int paramInt2, float paramFloat) {
    bzF(0);
    irb irb = irb.Dne();
    Dne(this.Dne, irb.Dne("multiplayer.downloadingTerrain"), this.FWm / 2, this.bzF / 2 - 50, 16777215);
    super.Dne(paramInt1, paramInt2, paramFloat);
  }
  
  protected void Dne(char paramChar, int paramInt) {}
  
  public void bzF() {
    // Byte code:
    //   0: aload_0
    //   1: dup
    //   2: getfield Dne : I
    //   5: iconst_1
    //   6: iadd
    //   7: putfield Dne : I
    //   10: aload_0
    //   11: getfield Dne : I
    //   14: bipush #20
    //   16: irem
    //   17: ifne -> 34
    //   20: aload_0
    //   21: getfield Dne : Lfzy;
    //   24: new Phv
    //   27: dup
    //   28: invokespecial <init> : ()V
    //   31: invokevirtual FWm : (LNER;)V
    //   34: aload_0
    //   35: getfield Dne : Lfzy;
    //   38: ifnull -> 48
    //   41: aload_0
    //   42: getfield Dne : Lfzy;
    //   45: invokevirtual FWm : ()V
    //   48: return
  }
}


/* Location:              C:\Users\fract\Downloads\ERROR422.jar!\bcj.class
 * Java compiler version: 8 (52.0)
 * JD-Core Version:       1.1.3
 */