import java.util.ArrayList;
import java.util.Iterator;
import java.util.List;

public class cBP extends cMv {
  private yQQ Dne;
  
  private kSJ Dne;
  
  private List Dne;
  
  private float Dne;
  
  private boolean Dne;
  
  private wdG Dne = (wdG)new ArrayList();
  
  public boolean FWm() {
    if (this.Dne.Dne().bzF())
      return false; 
    float f = ((kSJ)this.Dne).ooe + 4.0F;
    return (this.Dne.Dne(((yQQ)this.Dne).Dne, ((yQQ)this.Dne).FWm, ((yQQ)this.Dne).bzF) > (f * f));
  }
  
  private boolean Dne(yQQ paramyQQ) {
    Iterator<yQQ> iterator = this.Dne.iterator();
    while (true) {
      if (!iterator.hasNext())
        return false; 
      yQQ yQQ1 = iterator.next();
      if (paramyQQ.Dne == yQQ1.Dne && paramyQQ.FWm == yQQ1.FWm && paramyQQ.bzF == yQQ1.bzF)
        return true; 
    } 
  }
  
  public void Dne() {
    this.Dne.Dne().Dne(this.Dne, this.Dne);
  }
  
  public boolean Dne() {
    // Byte code:
    //   0: aload_0
    //   1: invokespecial Qnq : ()V
    //   4: aload_0
    //   5: getfield Dne : Z
    //   8: ifeq -> 26
    //   11: aload_0
    //   12: getfield Dne : LkSJ;
    //   15: getfield Dne : LQnq;
    //   18: invokevirtual Dne : ()Z
    //   21: ifeq -> 26
    //   24: iconst_0
    //   25: ireturn
    //   26: aload_0
    //   27: getfield Dne : LkSJ;
    //   30: getfield Dne : LQnq;
    //   33: getfield Dne : LPrX;
    //   36: aload_0
    //   37: getfield Dne : LkSJ;
    //   40: getfield div : D
    //   43: invokestatic FWm : (D)I
    //   46: aload_0
    //   47: getfield Dne : LkSJ;
    //   50: getfield IjH : D
    //   53: invokestatic FWm : (D)I
    //   56: aload_0
    //   57: getfield Dne : LkSJ;
    //   60: getfield mrb : D
    //   63: invokestatic FWm : (D)I
    //   66: iconst_0
    //   67: invokevirtual Dne : (IIII)LuQr;
    //   70: astore_1
    //   71: aload_1
    //   72: ifnonnull -> 77
    //   75: iconst_0
    //   76: ireturn
    //   77: aload_0
    //   78: aload_0
    //   79: aload_1
    //   80: invokespecial Dne : (LuQr;)LyQQ;
    //   83: putfield Dne : LyQQ;
    //   86: aload_0
    //   87: getfield Dne : LyQQ;
    //   90: ifnonnull -> 95
    //   93: iconst_0
    //   94: ireturn
    //   95: aload_0
    //   96: getfield Dne : LkSJ;
    //   99: invokevirtual Dne : ()LKFZ;
    //   102: invokevirtual FWm : ()Z
    //   105: istore_2
    //   106: aload_0
    //   107: getfield Dne : LkSJ;
    //   110: invokevirtual Dne : ()LKFZ;
    //   113: iconst_0
    //   114: invokevirtual FWm : (Z)V
    //   117: aload_0
    //   118: aload_0
    //   119: getfield Dne : LkSJ;
    //   122: invokevirtual Dne : ()LKFZ;
    //   125: aload_0
    //   126: getfield Dne : LyQQ;
    //   129: getfield Dne : I
    //   132: i2d
    //   133: aload_0
    //   134: getfield Dne : LyQQ;
    //   137: getfield FWm : I
    //   140: i2d
    //   141: aload_0
    //   142: getfield Dne : LyQQ;
    //   145: getfield bzF : I
    //   148: i2d
    //   149: invokevirtual Dne : (DDD)LwdG;
    //   152: putfield Dne : LwdG;
    //   155: aload_0
    //   156: getfield Dne : LkSJ;
    //   159: invokevirtual Dne : ()LKFZ;
    //   162: iload_2
    //   163: invokevirtual FWm : (Z)V
    //   166: aload_0
    //   167: getfield Dne : LwdG;
    //   170: ifnull -> 175
    //   173: iconst_1
    //   174: ireturn
    //   175: aload_0
    //   176: getfield Dne : LkSJ;
    //   179: bipush #10
    //   181: bipush #7
    //   183: aload_0
    //   184: getfield Dne : LkSJ;
    //   187: getfield Dne : LQnq;
    //   190: invokevirtual Dne : ()LziS;
    //   193: aload_0
    //   194: getfield Dne : LyQQ;
    //   197: getfield Dne : I
    //   200: i2d
    //   201: aload_0
    //   202: getfield Dne : LyQQ;
    //   205: getfield FWm : I
    //   208: i2d
    //   209: aload_0
    //   210: getfield Dne : LyQQ;
    //   213: getfield bzF : I
    //   216: i2d
    //   217: invokevirtual Dne : (DDD)LchN;
    //   220: invokestatic Dne : (LkSJ;IILchN;)LchN;
    //   223: astore_3
    //   224: aload_3
    //   225: ifnonnull -> 230
    //   228: iconst_0
    //   229: ireturn
    //   230: aload_0
    //   231: getfield Dne : LkSJ;
    //   234: invokevirtual Dne : ()LKFZ;
    //   237: iconst_0
    //   238: invokevirtual FWm : (Z)V
    //   241: aload_0
    //   242: aload_0
    //   243: getfield Dne : LkSJ;
    //   246: invokevirtual Dne : ()LKFZ;
    //   249: aload_3
    //   250: getfield Dne : D
    //   253: aload_3
    //   254: getfield FWm : D
    //   257: aload_3
    //   258: getfield bzF : D
    //   261: invokevirtual Dne : (DDD)LwdG;
    //   264: putfield Dne : LwdG;
    //   267: aload_0
    //   268: getfield Dne : LkSJ;
    //   271: invokevirtual Dne : ()LKFZ;
    //   274: iload_2
    //   275: invokevirtual FWm : (Z)V
    //   278: aload_0
    //   279: getfield Dne : LwdG;
    //   282: ifnull -> 289
    //   285: iconst_1
    //   286: goto -> 290
    //   289: iconst_0
    //   290: ireturn
  }
  
  private yQQ Dne(uQr paramuQr) {
    yQQ yQQ1 = null;
    int i = Integer.MAX_VALUE;
    List list = paramuQr.Dne();
    for (yQQ yQQ2 : list) {
      int j = yQQ2.Dne(geR.FWm(((kSJ)this.Dne).div), geR.FWm(((kSJ)this.Dne).IjH), geR.FWm(((kSJ)this.Dne).mrb));
      if (j < i && !Dne(yQQ2)) {
        yQQ1 = yQQ2;
        i = j;
      } 
    } 
    return yQQ1;
  }
  
  public cBP(kSJ paramkSJ, float paramFloat, boolean paramBoolean) {
    this.Dne = (wdG)paramkSJ;
    this.Dne = paramFloat;
    this.Dne = paramBoolean;
    Dne(1);
  }
  
  public void FWm() {
    if (this.Dne.Dne().bzF() || this.Dne.Dne(((yQQ)this.Dne).Dne, ((yQQ)this.Dne).FWm, ((yQQ)this.Dne).bzF) < 16.0D)
      this.Dne.add(this.Dne); 
  }
  
  private void Qnq() {
    if (this.Dne.size() > 15)
      this.Dne.remove(0); 
  }
}


/* Location:              C:\Users\fract\Downloads\ERROR422.jar!\cBP.class
 * Java compiler version: 8 (52.0)
 * JD-Core Version:       1.1.3
 */