public class CDE extends tkl {
  private int One;
  
  private int ZgS;
  
  private int FWm;
  
  uQr Dne;
  
  public boolean tgc() {
    return true;
  }
  
  public CDE(Qnq paramQnq) {
    // Byte code:
    //   0: aload_0
    //   1: aload_1
    //   2: invokespecial <init> : (LQnq;)V
    //   5: aload_0
    //   6: iconst_0
    //   7: putfield FWm : I
    //   10: aload_0
    //   11: aconst_null
    //   12: putfield Dne : LuQr;
    //   15: aload_0
    //   16: ldc '/mob/villager_golem.png'
    //   18: putfield bzF : Ljava/lang/String;
    //   21: aload_0
    //   22: ldc 1.4
    //   24: ldc 2.9
    //   26: invokevirtual Dne : (FF)V
    //   29: aload_0
    //   30: invokevirtual Dne : ()LKFZ;
    //   33: iconst_1
    //   34: invokevirtual Dne : (Z)V
    //   37: aload_0
    //   38: getfield Dne : LOKo;
    //   41: iconst_1
    //   42: new etz
    //   45: dup
    //   46: aload_0
    //   47: ldc 0.25
    //   49: iconst_1
    //   50: invokespecial <init> : (LFUH;FZ)V
    //   53: invokevirtual Dne : (ILcMv;)V
    //   56: aload_0
    //   57: getfield Dne : LOKo;
    //   60: iconst_2
    //   61: new quK
    //   64: dup
    //   65: aload_0
    //   66: ldc 0.22
    //   68: ldc 32.0
    //   70: invokespecial <init> : (LkSJ;FF)V
    //   73: invokevirtual Dne : (ILcMv;)V
    //   76: aload_0
    //   77: getfield Dne : LOKo;
    //   80: iconst_3
    //   81: new cBP
    //   84: dup
    //   85: aload_0
    //   86: ldc 0.16
    //   88: iconst_1
    //   89: invokespecial <init> : (LkSJ;FZ)V
    //   92: invokevirtual Dne : (ILcMv;)V
    //   95: aload_0
    //   96: getfield Dne : LOKo;
    //   99: iconst_4
    //   100: new ZWx
    //   103: dup
    //   104: aload_0
    //   105: ldc 0.16
    //   107: invokespecial <init> : (LkSJ;F)V
    //   110: invokevirtual Dne : (ILcMv;)V
    //   113: aload_0
    //   114: getfield Dne : LOKo;
    //   117: iconst_5
    //   118: new Ydw
    //   121: dup
    //   122: aload_0
    //   123: invokespecial <init> : (LCDE;)V
    //   126: invokevirtual Dne : (ILcMv;)V
    //   129: aload_0
    //   130: getfield Dne : LOKo;
    //   133: bipush #6
    //   135: new IBw
    //   138: dup
    //   139: aload_0
    //   140: ldc 0.16
    //   142: invokespecial <init> : (LkSJ;F)V
    //   145: invokevirtual Dne : (ILcMv;)V
    //   148: aload_0
    //   149: getfield Dne : LOKo;
    //   152: bipush #7
    //   154: new yws
    //   157: dup
    //   158: aload_0
    //   159: ldc FiG
    //   161: ldc 6.0
    //   163: invokespecial <init> : (LFUH;Ljava/lang/Class;F)V
    //   166: invokevirtual Dne : (ILcMv;)V
    //   169: aload_0
    //   170: getfield Dne : LOKo;
    //   173: bipush #8
    //   175: new cHg
    //   178: dup
    //   179: aload_0
    //   180: invokespecial <init> : (LFUH;)V
    //   183: invokevirtual Dne : (ILcMv;)V
    //   186: aload_0
    //   187: getfield FWm : LOKo;
    //   190: iconst_1
    //   191: new ZkF
    //   194: dup
    //   195: aload_0
    //   196: invokespecial <init> : (LCDE;)V
    //   199: invokevirtual Dne : (ILcMv;)V
    //   202: aload_0
    //   203: getfield FWm : LOKo;
    //   206: iconst_2
    //   207: new QRF
    //   210: dup
    //   211: aload_0
    //   212: iconst_0
    //   213: invokespecial <init> : (LFUH;Z)V
    //   216: invokevirtual Dne : (ILcMv;)V
    //   219: aload_0
    //   220: getfield FWm : LOKo;
    //   223: iconst_3
    //   224: new AmF
    //   227: dup
    //   228: aload_0
    //   229: ldc FUH
    //   231: ldc 16.0
    //   233: iconst_0
    //   234: iconst_0
    //   235: iconst_1
    //   236: getstatic ZFz.Dne : LpUe;
    //   239: invokespecial <init> : (LFUH;Ljava/lang/Class;FIZZLpUe;)V
    //   242: invokevirtual Dne : (ILcMv;)V
    //   245: return
  }
  
  protected void Dne(boolean paramBoolean, int paramInt) {
    int i = this.Dne.nextInt(3);
    int j;
    for (j = 0; j < i; j++)
      Dne(zKP.FWm.FWm, 1); 
    j = 3 + this.Dne.nextInt(3);
    for (byte b = 0; b < j; b++)
      Dne(dEr.IjH.Qnq, 1); 
  }
  
  public void IjH(boolean paramBoolean) {
    byte b = this.Dne.Dne(16);
    if (paramBoolean) {
      this.Dne.FWm(16, Byte.valueOf((byte)(b | 0x1)));
    } else {
      this.Dne.FWm(16, Byte.valueOf((byte)(b & 0xFFFFFFFE)));
    } 
  }
  
  public int qLR() {
    return this.ZgS;
  }
  
  public void Dne(WkD paramWkD) {
    super.Dne(paramWkD);
    paramWkD.Dne("PlayerCreated", LVR());
  }
  
  public int bzF() {
    return this.One;
  }
  
  public int Dne() {
    return 100;
  }
  
  public void Dne(zBn paramzBn) {
    if (!LVR() && this.Dne != null && this.Dne != null)
      this.Dne.Dne(this.Dne.a_(), -5); 
    super.Dne(paramzBn);
  }
  
  public void IjH() {
    super.IjH();
    if (this.One > 0)
      this.One--; 
    if (this.ZgS > 0)
      this.ZgS--; 
    if (this.XHL * this.XHL + this.kGO * this.kGO > 2.500000277905201E-7D && this.Dne.nextInt(5) == 0) {
      int i = geR.FWm(this.div);
      int j = geR.FWm(this.IjH - 0.20000000298023224D - this.udO);
      int k = geR.FWm(this.mrb);
      int m = this.Dne.Dne(i, j, k);
      if (m > 0)
        this.Dne.Dne("tilecrack_" + m + "_" + this.Dne.bzF(i, j, k), this.div + (this.Dne.nextFloat() - 0.5D) * this.ooe, ((bSp)this.Dne).FWm + 0.1D, this.mrb + (this.Dne.nextFloat() - 0.5D) * this.ooe, 4.0D * (this.Dne.nextFloat() - 0.5D), 0.5D, (this.Dne.nextFloat() - 0.5D) * 4.0D); 
    } 
  }
  
  protected void mlD() {
    if (--this.FWm <= 0) {
      this.FWm = 70 + this.Dne.nextInt(50);
      this.Dne = ((Qnq)this.Dne).Dne.Dne(geR.FWm(this.div), geR.FWm(this.IjH), geR.FWm(this.mrb), 32);
      if (this.Dne == null) {
        AgF();
      } else {
        iSh iSh = this.Dne.Dne();
        FWm(iSh.Dne, iSh.FWm, iSh.bzF, (int)(this.Dne.Dne() * 0.6F));
      } 
    } 
    super.mlD();
  }
  
  protected void FWm() {
    super.FWm();
    this.Dne.Dne(16, Byte.valueOf((byte)0));
  }
  
  protected void div(sMa paramsMa) {
    if (paramsMa instanceof ZFz && Dne().nextInt(20) == 0)
      FWm((FUH)paramsMa); 
    super.div(paramsMa);
  }
  
  public boolean bzF(sMa paramsMa) {
    this.One = 10;
    this.Dne.Dne(this, (byte)4);
    boolean bool = paramsMa.Dne(zBn.Dne(this), 7 + this.Dne.nextInt(15));
    if (bool)
      paramsMa.Zpi += 0.4000000059604645D; 
    Dne("mob.irongolem.throw", 1.0F, 1.0F);
    return bool;
  }
  
  protected String zGp() {
    return "none";
  }
  
  protected String DyG() {
    return "mob.irongolem.hit";
  }
  
  public void Dne(byte paramByte) {
    if (paramByte == 4) {
      this.One = 10;
      Dne("mob.irongolem.throw", 1.0F, 1.0F);
    } else if (paramByte == 11) {
      this.ZgS = 400;
    } else {
      super.Dne(paramByte);
    } 
  }
  
  public boolean LVR() {
    return ((this.Dne.Dne(16) & 0x1) != 0);
  }
  
  protected int Dne(int paramInt) {
    return paramInt;
  }
  
  public void FWm(WkD paramWkD) {
    super.FWm(paramWkD);
    IjH(paramWkD.FWm("PlayerCreated"));
  }
  
  public boolean Dne(Class<?> paramClass) {
    return (LVR() && FiG.class.isAssignableFrom(paramClass)) ? false : super.Dne(paramClass);
  }
  
  public void FWm(boolean paramBoolean) {
    this.ZgS = paramBoolean ? 400 : 0;
    this.Dne.Dne(this, (byte)11);
  }
  
  public uQr Dne() {
    return this.Dne;
  }
  
  protected void Dne(int paramInt1, int paramInt2, int paramInt3, int paramInt4) {
    Dne("mob.irongolem.walk", 1.0F, 1.0F);
  }
  
  protected String div() {
    return "mob.irongolem.death";
  }
}


/* Location:              C:\Users\fract\Downloads\ERROR422.jar!\CDE.class
 * Java compiler version: 8 (52.0)
 * JD-Core Version:       1.1.3
 */