public class cnh extends cMv {
  private int FWm;
  
  private FiG Dne;
  
  private boolean FWm;
  
  private boolean bzF;
  
  private float Dne;
  
  private double Dne;
  
  private double Qnq;
  
  private int Dne;
  
  private double FWm;
  
  private double aFZ;
  
  private double bzF;
  
  private boolean Dne;
  
  private kSJ Dne = false;
  
  public void bzF() {
    this.Dne.Dne().Dne(this.Dne, 30.0F, this.Dne.udO());
    if (this.Dne.Dne(this.Dne) < 6.25D) {
      this.Dne.Dne().FWm();
    } else {
      this.Dne.Dne().Dne(this.Dne, this.Dne);
    } 
  }
  
  public boolean FWm() {
    if (this.FWm != 0.0D) {
      if (this.Dne.Dne(this.Dne) < 36.0D) {
        if (this.Dne.Dne(this.Dne, this.FWm, this.bzF) > 0.010000000000000002D)
          return false; 
        if (Math.abs(((FiG)this.Dne).XHL - this.Qnq) > 5.0D || Math.abs(((FiG)this.Dne).mrb - this.aFZ) > 5.0D)
          return false; 
      } else {
        this.Dne = ((FiG)this.Dne).div;
        this.FWm = ((FiG)this.Dne).IjH;
        this.bzF = ((FiG)this.Dne).mrb;
      } 
      this.Qnq = ((FiG)this.Dne).XHL;
      this.aFZ = ((FiG)this.Dne).mrb;
    } 
    return Dne();
  }
  
  public boolean bzF() {
    return this.Dne;
  }
  
  public void Dne() {
    this.Dne = ((FiG)this.Dne).div;
    this.FWm = ((FiG)this.Dne).IjH;
    this.bzF = ((FiG)this.Dne).mrb;
    this.Dne = true;
    this.bzF = this.Dne.Dne().Dne();
    this.Dne.Dne().Dne(false);
  }
  
  public boolean Dne() {
    // Byte code:
    //   0: aload_0
    //   1: getfield Dne : I
    //   4: ifle -> 19
    //   7: aload_0
    //   8: dup
    //   9: getfield Dne : I
    //   12: iconst_1
    //   13: isub
    //   14: putfield Dne : I
    //   17: iconst_0
    //   18: ireturn
    //   19: aload_0
    //   20: aload_0
    //   21: getfield Dne : LkSJ;
    //   24: getfield Dne : LQnq;
    //   27: aload_0
    //   28: getfield Dne : LkSJ;
    //   31: ldc2_w 10.0
    //   34: invokevirtual Dne : (LsMa;D)LFiG;
    //   37: putfield Dne : LFiG;
    //   40: aload_0
    //   41: getfield Dne : LFiG;
    //   44: ifnonnull -> 49
    //   47: iconst_0
    //   48: ireturn
    //   49: aload_0
    //   50: getfield Dne : LFiG;
    //   53: invokevirtual bzF : ()LNMq;
    //   56: astore_1
    //   57: aload_1
    //   58: ifnonnull -> 65
    //   61: iconst_0
    //   62: goto -> 81
    //   65: aload_1
    //   66: getfield bzF : I
    //   69: aload_0
    //   70: getfield FWm : I
    //   73: if_icmpne -> 80
    //   76: iconst_1
    //   77: goto -> 81
    //   80: iconst_0
    //   81: ireturn
  }
  
  public cnh(kSJ paramkSJ, float paramFloat, int paramInt, boolean paramBoolean) {
    this.Dne = paramkSJ;
    this.Dne = paramFloat;
    this.FWm = paramInt;
    this.FWm = paramBoolean;
    Dne(3);
  }
  
  public void FWm() {
    this.Dne = null;
    this.Dne.Dne().FWm();
    this.Dne = 100;
    this.Dne = false;
    this.Dne.Dne().Dne(this.bzF);
  }
}


/* Location:              C:\Users\fract\Downloads\ERROR422.jar!\cnh.class
 * Java compiler version: 8 (52.0)
 * JD-Core Version:       1.1.3
 */