public class csP {
  private double FWm;
  
  private FUH Dne;
  
  private boolean Dne;
  
  private double bzF;
  
  private float Dne;
  
  private double Dne = false;
  
  public void Dne() {
    // Byte code:
    //   0: aload_0
    //   1: getfield Dne : LFUH;
    //   4: fconst_0
    //   5: invokevirtual Qnq : (F)V
    //   8: aload_0
    //   9: getfield Dne : Z
    //   12: ifeq -> 192
    //   15: aload_0
    //   16: iconst_0
    //   17: putfield Dne : Z
    //   20: aload_0
    //   21: getfield Dne : LFUH;
    //   24: getfield Dne : LbSp;
    //   27: getfield FWm : D
    //   30: ldc2_w 0.5
    //   33: dadd
    //   34: invokestatic FWm : (D)I
    //   37: istore_1
    //   38: aload_0
    //   39: getfield Dne : D
    //   42: aload_0
    //   43: getfield Dne : LFUH;
    //   46: getfield div : D
    //   49: dsub
    //   50: dstore_2
    //   51: aload_0
    //   52: getfield bzF : D
    //   55: aload_0
    //   56: getfield Dne : LFUH;
    //   59: getfield mrb : D
    //   62: dsub
    //   63: dstore #4
    //   65: aload_0
    //   66: getfield FWm : D
    //   69: iload_1
    //   70: i2d
    //   71: dsub
    //   72: dstore #6
    //   74: dload_2
    //   75: dload_2
    //   76: dmul
    //   77: dload #6
    //   79: dload #6
    //   81: dmul
    //   82: dadd
    //   83: dload #4
    //   85: dload #4
    //   87: dmul
    //   88: dadd
    //   89: dstore #8
    //   91: dload #8
    //   93: ldc2_w 2.500000277905201E-7
    //   96: dcmpl
    //   97: iflt -> 192
    //   100: dload #4
    //   102: dload_2
    //   103: invokestatic atan2 : (DD)D
    //   106: ldc2_w 180.0
    //   109: dmul
    //   110: ldc2_w 3.141592653589793
    //   113: ddiv
    //   114: d2f
    //   115: ldc 90.0
    //   117: fsub
    //   118: fstore #10
    //   120: aload_0
    //   121: getfield Dne : LFUH;
    //   124: aload_0
    //   125: aload_0
    //   126: getfield Dne : LFUH;
    //   129: getfield mrb : F
    //   132: fload #10
    //   134: ldc 30.0
    //   136: invokespecial Dne : (FFF)F
    //   139: putfield mrb : F
    //   142: aload_0
    //   143: getfield Dne : LFUH;
    //   146: aload_0
    //   147: getfield Dne : F
    //   150: aload_0
    //   151: getfield Dne : LFUH;
    //   154: invokevirtual mrb : ()F
    //   157: fmul
    //   158: invokevirtual bzF : (F)V
    //   161: dload #6
    //   163: dconst_0
    //   164: dcmpl
    //   165: ifle -> 192
    //   168: dload_2
    //   169: dload_2
    //   170: dmul
    //   171: dload #4
    //   173: dload #4
    //   175: dmul
    //   176: dadd
    //   177: dconst_1
    //   178: dcmpg
    //   179: ifge -> 192
    //   182: aload_0
    //   183: getfield Dne : LFUH;
    //   186: invokevirtual Dne : ()Lqgb;
    //   189: invokevirtual Dne : ()V
    //   192: return
  }
  
  public csP(FUH paramFUH) {
    this.Dne = paramFUH;
    this.Dne = paramFUH.div;
    this.FWm = paramFUH.IjH;
    this.bzF = paramFUH.mrb;
  }
  
  public void Dne(double paramDouble1, double paramDouble2, double paramDouble3, float paramFloat) {
    this.Dne = paramDouble1;
    this.FWm = paramDouble2;
    this.bzF = paramDouble3;
    this.Dne = paramFloat;
    this.Dne = true;
  }
  
  public float Dne() {
    return this.Dne;
  }
  
  private float Dne(float paramFloat1, float paramFloat2, float paramFloat3) {
    float f = geR.aFZ(paramFloat2 - paramFloat1);
    if (f > paramFloat3)
      f = paramFloat3; 
    if (f < -paramFloat3)
      f = -paramFloat3; 
    return paramFloat1 + f;
  }
  
  public boolean Dne() {
    return this.Dne;
  }
}


/* Location:              C:\Users\fract\Downloads\ERROR422.jar!\csP.class
 * Java compiler version: 8 (52.0)
 * JD-Core Version:       1.1.3
 */