public class dyC {
  public PJQ Dne;
  
  private int bzF;
  
  private int aFZ;
  
  private XHL Dne;
  
  public Qnq Dne;
  
  private int Qnq;
  
  private int FWm;
  
  private int mrb = -1;
  
  private int Dne;
  
  private int DyG;
  
  private boolean FWm;
  
  private boolean Dne = XHL.Dne;
  
  private int div;
  
  private int IjH;
  
  private int zGp;
  
  public void FWm(XHL paramXHL) {
    if (this.Dne == XHL.Dne)
      this.Dne = paramXHL; 
    Dne(this.Dne);
  }
  
  public boolean Dne(int paramInt1, int paramInt2, int paramInt3) {
    // Byte code:
    //   0: aload_0
    //   1: getfield Dne : LXHL;
    //   4: invokevirtual Dne : ()Z
    //   7: ifeq -> 25
    //   10: aload_0
    //   11: getfield Dne : LPJQ;
    //   14: iload_1
    //   15: iload_2
    //   16: iload_3
    //   17: invokevirtual FWm : (III)Z
    //   20: ifne -> 25
    //   23: iconst_0
    //   24: ireturn
    //   25: aload_0
    //   26: getfield Dne : LQnq;
    //   29: iload_1
    //   30: iload_2
    //   31: iload_3
    //   32: invokevirtual Dne : (III)I
    //   35: istore #4
    //   37: aload_0
    //   38: getfield Dne : LQnq;
    //   41: iload_1
    //   42: iload_2
    //   43: iload_3
    //   44: invokevirtual bzF : (III)I
    //   47: istore #5
    //   49: aload_0
    //   50: getfield Dne : LQnq;
    //   53: aload_0
    //   54: getfield Dne : LPJQ;
    //   57: sipush #2001
    //   60: iload_1
    //   61: iload_2
    //   62: iload_3
    //   63: iload #4
    //   65: aload_0
    //   66: getfield Dne : LQnq;
    //   69: iload_1
    //   70: iload_2
    //   71: iload_3
    //   72: invokevirtual bzF : (III)I
    //   75: bipush #12
    //   77: ishl
    //   78: iadd
    //   79: invokevirtual Dne : (LFiG;IIIII)V
    //   82: aload_0
    //   83: iload_1
    //   84: iload_2
    //   85: iload_3
    //   86: invokespecial FWm : (III)Z
    //   89: istore #6
    //   91: aload_0
    //   92: invokevirtual Dne : ()Z
    //   95: ifeq -> 125
    //   98: aload_0
    //   99: getfield Dne : LPJQ;
    //   102: getfield Dne : LTnv;
    //   105: new cSs
    //   108: dup
    //   109: iload_1
    //   110: iload_2
    //   111: iload_3
    //   112: aload_0
    //   113: getfield Dne : LQnq;
    //   116: invokespecial <init> : (IIILQnq;)V
    //   119: invokevirtual Dne : (LNER;)V
    //   122: goto -> 219
    //   125: aload_0
    //   126: getfield Dne : LPJQ;
    //   129: invokevirtual bzF : ()LNMq;
    //   132: astore #7
    //   134: aload_0
    //   135: getfield Dne : LPJQ;
    //   138: getstatic zKP.Dne : [LzKP;
    //   141: iload #4
    //   143: aaload
    //   144: invokevirtual Dne : (LzKP;)Z
    //   147: istore #8
    //   149: aload #7
    //   151: ifnull -> 187
    //   154: aload #7
    //   156: aload_0
    //   157: getfield Dne : LQnq;
    //   160: iload #4
    //   162: iload_1
    //   163: iload_2
    //   164: iload_3
    //   165: aload_0
    //   166: getfield Dne : LPJQ;
    //   169: invokevirtual Dne : (LQnq;IIIILFiG;)V
    //   172: aload #7
    //   174: getfield Dne : I
    //   177: ifne -> 187
    //   180: aload_0
    //   181: getfield Dne : LPJQ;
    //   184: invokevirtual BJH : ()V
    //   187: iload #6
    //   189: ifeq -> 219
    //   192: iload #8
    //   194: ifeq -> 219
    //   197: getstatic zKP.Dne : [LzKP;
    //   200: iload #4
    //   202: aaload
    //   203: aload_0
    //   204: getfield Dne : LQnq;
    //   207: aload_0
    //   208: getfield Dne : LPJQ;
    //   211: iload_1
    //   212: iload_2
    //   213: iload_3
    //   214: iload #5
    //   216: invokevirtual Dne : (LQnq;LFiG;IIII)V
    //   219: iload #6
    //   221: ireturn
  }
  
  public boolean Dne() {
    // Byte code:
    //   0: aload_0
    //   1: getfield Dne : LXHL;
    //   4: invokevirtual FWm : ()Z
    //   7: ireturn
  }
  
  public dyC(Qnq paramQnq) {
    this.Dne = paramQnq;
  }
  
  public void Dne(int paramInt1, int paramInt2, int paramInt3) {
    // Byte code:
    //   0: iload_1
    //   1: aload_0
    //   2: getfield FWm : I
    //   5: if_icmpne -> 169
    //   8: iload_2
    //   9: aload_0
    //   10: getfield bzF : I
    //   13: if_icmpne -> 169
    //   16: iload_3
    //   17: aload_0
    //   18: getfield Qnq : I
    //   21: if_icmpne -> 169
    //   24: aload_0
    //   25: getfield aFZ : I
    //   28: aload_0
    //   29: getfield Dne : I
    //   32: isub
    //   33: istore #4
    //   35: aload_0
    //   36: getfield Dne : LQnq;
    //   39: iload_1
    //   40: iload_2
    //   41: iload_3
    //   42: invokevirtual Dne : (III)I
    //   45: istore #5
    //   47: iload #5
    //   49: ifeq -> 169
    //   52: getstatic zKP.Dne : [LzKP;
    //   55: iload #5
    //   57: aaload
    //   58: astore #6
    //   60: aload #6
    //   62: aload_0
    //   63: getfield Dne : LPJQ;
    //   66: aload_0
    //   67: getfield Dne : LPJQ;
    //   70: getfield Dne : LQnq;
    //   73: iload_1
    //   74: iload_2
    //   75: iload_3
    //   76: invokevirtual Dne : (LFiG;LQnq;III)F
    //   79: iload #4
    //   81: iconst_1
    //   82: iadd
    //   83: i2f
    //   84: fmul
    //   85: fstore #7
    //   87: fload #7
    //   89: ldc 0.7
    //   91: fcmpl
    //   92: iflt -> 129
    //   95: aload_0
    //   96: iconst_0
    //   97: putfield Dne : Z
    //   100: aload_0
    //   101: getfield Dne : LQnq;
    //   104: aload_0
    //   105: getfield Dne : LPJQ;
    //   108: getfield aFZ : I
    //   111: iload_1
    //   112: iload_2
    //   113: iload_3
    //   114: iconst_m1
    //   115: invokevirtual aFZ : (IIIII)V
    //   118: aload_0
    //   119: iload_1
    //   120: iload_2
    //   121: iload_3
    //   122: invokevirtual Dne : (III)Z
    //   125: pop
    //   126: goto -> 169
    //   129: aload_0
    //   130: getfield FWm : Z
    //   133: ifne -> 169
    //   136: aload_0
    //   137: iconst_0
    //   138: putfield Dne : Z
    //   141: aload_0
    //   142: iconst_1
    //   143: putfield FWm : Z
    //   146: aload_0
    //   147: iload_1
    //   148: putfield zGp : I
    //   151: aload_0
    //   152: iload_2
    //   153: putfield DyG : I
    //   156: aload_0
    //   157: iload_3
    //   158: putfield div : I
    //   161: aload_0
    //   162: aload_0
    //   163: getfield Dne : I
    //   166: putfield IjH : I
    //   169: return
  }
  
  public boolean Dne(FiG paramFiG, Qnq paramQnq, NMq paramNMq, int paramInt1, int paramInt2, int paramInt3, int paramInt4, float paramFloat1, float paramFloat2, float paramFloat3) {
    if (!paramFiG.aFZ() || paramFiG.Dne() == null) {
      int i = paramQnq.Dne(paramInt1, paramInt2, paramInt3);
      if (i > 0 && zKP.Dne[i].Dne(paramQnq, paramInt1, paramInt2, paramInt3, paramFiG, paramInt4, paramFloat1, paramFloat2, paramFloat3))
        return true; 
    } 
    if (paramNMq == null)
      return false; 
    if (Dne()) {
      int i = paramNMq.Qnq();
      int j = paramNMq.Dne;
      boolean bool = paramNMq.Dne(paramFiG, paramQnq, paramInt1, paramInt2, paramInt3, paramInt4, paramFloat1, paramFloat2, paramFloat3);
      paramNMq.Dne(i);
      paramNMq.Dne = j;
      return bool;
    } 
    return paramNMq.Dne(paramFiG, paramQnq, paramInt1, paramInt2, paramInt3, paramInt4, paramFloat1, paramFloat2, paramFloat3);
  }
  
  public boolean Dne(FiG paramFiG, Qnq paramQnq, NMq paramNMq) {
    int i = paramNMq.Dne;
    int j = paramNMq.Qnq();
    NMq nMq = paramNMq.Dne(paramQnq, paramFiG);
    if (nMq == paramNMq && (nMq == null || (nMq.Dne == i && nMq.zGp() <= 0 && nMq.Qnq() == j)))
      return false; 
    ((MOS)paramFiG.Dne).Dne[((MOS)paramFiG.Dne).Dne] = nMq;
    if (Dne()) {
      nMq.Dne = i;
      if (nMq.FWm())
        nMq.Dne(j); 
    } 
    if (nMq.Dne == 0)
      ((MOS)paramFiG.Dne).Dne[((MOS)paramFiG.Dne).Dne] = null; 
    if (!paramFiG.haP())
      ((PJQ)paramFiG).Dne(paramFiG.Dne); 
    return true;
  }
  
  public XHL Dne() {
    return this.Dne;
  }
  
  public void Dne() {
    // Byte code:
    //   0: aload_0
    //   1: dup
    //   2: getfield aFZ : I
    //   5: iconst_1
    //   6: iadd
    //   7: putfield aFZ : I
    //   10: aload_0
    //   11: getfield FWm : Z
    //   14: ifeq -> 180
    //   17: aload_0
    //   18: getfield aFZ : I
    //   21: aload_0
    //   22: getfield IjH : I
    //   25: isub
    //   26: istore_1
    //   27: aload_0
    //   28: getfield Dne : LQnq;
    //   31: aload_0
    //   32: getfield zGp : I
    //   35: aload_0
    //   36: getfield DyG : I
    //   39: aload_0
    //   40: getfield div : I
    //   43: invokevirtual Dne : (III)I
    //   46: istore #4
    //   48: iload #4
    //   50: ifne -> 61
    //   53: aload_0
    //   54: iconst_0
    //   55: putfield FWm : Z
    //   58: goto -> 177
    //   61: getstatic zKP.Dne : [LzKP;
    //   64: iload #4
    //   66: aaload
    //   67: astore #5
    //   69: aload #5
    //   71: aload_0
    //   72: getfield Dne : LPJQ;
    //   75: aload_0
    //   76: getfield Dne : LPJQ;
    //   79: getfield Dne : LQnq;
    //   82: aload_0
    //   83: getfield zGp : I
    //   86: aload_0
    //   87: getfield DyG : I
    //   90: aload_0
    //   91: getfield div : I
    //   94: invokevirtual Dne : (LFiG;LQnq;III)F
    //   97: iload_1
    //   98: iconst_1
    //   99: iadd
    //   100: i2f
    //   101: fmul
    //   102: fstore_2
    //   103: fload_2
    //   104: ldc 10.0
    //   106: fmul
    //   107: f2i
    //   108: istore_3
    //   109: iload_3
    //   110: aload_0
    //   111: getfield mrb : I
    //   114: if_icmpeq -> 149
    //   117: aload_0
    //   118: getfield Dne : LQnq;
    //   121: aload_0
    //   122: getfield Dne : LPJQ;
    //   125: getfield aFZ : I
    //   128: aload_0
    //   129: getfield zGp : I
    //   132: aload_0
    //   133: getfield DyG : I
    //   136: aload_0
    //   137: getfield div : I
    //   140: iload_3
    //   141: invokevirtual aFZ : (IIIII)V
    //   144: aload_0
    //   145: iload_3
    //   146: putfield mrb : I
    //   149: fload_2
    //   150: fconst_1
    //   151: fcmpl
    //   152: iflt -> 177
    //   155: aload_0
    //   156: iconst_0
    //   157: putfield FWm : Z
    //   160: aload_0
    //   161: aload_0
    //   162: getfield zGp : I
    //   165: aload_0
    //   166: getfield DyG : I
    //   169: aload_0
    //   170: getfield div : I
    //   173: invokevirtual Dne : (III)Z
    //   176: pop
    //   177: goto -> 351
    //   180: aload_0
    //   181: getfield Dne : Z
    //   184: ifeq -> 351
    //   187: aload_0
    //   188: getfield Dne : LQnq;
    //   191: aload_0
    //   192: getfield FWm : I
    //   195: aload_0
    //   196: getfield bzF : I
    //   199: aload_0
    //   200: getfield Qnq : I
    //   203: invokevirtual Dne : (III)I
    //   206: istore_1
    //   207: getstatic zKP.Dne : [LzKP;
    //   210: iload_1
    //   211: aaload
    //   212: astore #4
    //   214: aload #4
    //   216: ifnonnull -> 259
    //   219: aload_0
    //   220: getfield Dne : LQnq;
    //   223: aload_0
    //   224: getfield Dne : LPJQ;
    //   227: getfield aFZ : I
    //   230: aload_0
    //   231: getfield FWm : I
    //   234: aload_0
    //   235: getfield bzF : I
    //   238: aload_0
    //   239: getfield Qnq : I
    //   242: iconst_m1
    //   243: invokevirtual aFZ : (IIIII)V
    //   246: aload_0
    //   247: iconst_m1
    //   248: putfield mrb : I
    //   251: aload_0
    //   252: iconst_0
    //   253: putfield Dne : Z
    //   256: goto -> 351
    //   259: aload_0
    //   260: getfield aFZ : I
    //   263: aload_0
    //   264: getfield Dne : I
    //   267: isub
    //   268: istore #5
    //   270: aload #4
    //   272: aload_0
    //   273: getfield Dne : LPJQ;
    //   276: aload_0
    //   277: getfield Dne : LPJQ;
    //   280: getfield Dne : LQnq;
    //   283: aload_0
    //   284: getfield FWm : I
    //   287: aload_0
    //   288: getfield bzF : I
    //   291: aload_0
    //   292: getfield Qnq : I
    //   295: invokevirtual Dne : (LFiG;LQnq;III)F
    //   298: iload #5
    //   300: iconst_1
    //   301: iadd
    //   302: i2f
    //   303: fmul
    //   304: fstore_2
    //   305: fload_2
    //   306: ldc 10.0
    //   308: fmul
    //   309: f2i
    //   310: istore_3
    //   311: iload_3
    //   312: aload_0
    //   313: getfield mrb : I
    //   316: if_icmpeq -> 351
    //   319: aload_0
    //   320: getfield Dne : LQnq;
    //   323: aload_0
    //   324: getfield Dne : LPJQ;
    //   327: getfield aFZ : I
    //   330: aload_0
    //   331: getfield FWm : I
    //   334: aload_0
    //   335: getfield bzF : I
    //   338: aload_0
    //   339: getfield Qnq : I
    //   342: iload_3
    //   343: invokevirtual aFZ : (IIIII)V
    //   346: aload_0
    //   347: iload_3
    //   348: putfield mrb : I
    //   351: return
  }
  
  public void Dne(XHL paramXHL) {
    // Byte code:
    //   0: aload_0
    //   1: aload_1
    //   2: putfield Dne : LXHL;
    //   5: aload_1
    //   6: aload_0
    //   7: getfield Dne : LPJQ;
    //   10: getfield Dne : Luqg;
    //   13: invokevirtual Dne : (Luqg;)V
    //   16: aload_0
    //   17: getfield Dne : LPJQ;
    //   20: invokevirtual DyG : ()V
    //   23: return
  }
  
  public void Dne(int paramInt1, int paramInt2, int paramInt3, int paramInt4) {
    // Byte code:
    //   0: aload_0
    //   1: getfield Dne : LXHL;
    //   4: invokevirtual Dne : ()Z
    //   7: ifeq -> 23
    //   10: aload_0
    //   11: getfield Dne : LPJQ;
    //   14: iload_1
    //   15: iload_2
    //   16: iload_3
    //   17: invokevirtual FWm : (III)Z
    //   20: ifeq -> 226
    //   23: aload_0
    //   24: invokevirtual Dne : ()Z
    //   27: ifeq -> 60
    //   30: aload_0
    //   31: getfield Dne : LQnq;
    //   34: aconst_null
    //   35: checkcast FiG
    //   38: iload_1
    //   39: iload_2
    //   40: iload_3
    //   41: iload #4
    //   43: invokevirtual Dne : (LFiG;IIII)Z
    //   46: ifne -> 226
    //   49: aload_0
    //   50: iload_1
    //   51: iload_2
    //   52: iload_3
    //   53: invokevirtual Dne : (III)Z
    //   56: pop
    //   57: goto -> 226
    //   60: aload_0
    //   61: getfield Dne : LQnq;
    //   64: aconst_null
    //   65: checkcast FiG
    //   68: iload_1
    //   69: iload_2
    //   70: iload_3
    //   71: iload #4
    //   73: invokevirtual Dne : (LFiG;IIII)Z
    //   76: pop
    //   77: aload_0
    //   78: aload_0
    //   79: getfield aFZ : I
    //   82: putfield Dne : I
    //   85: fconst_1
    //   86: fstore #5
    //   88: aload_0
    //   89: getfield Dne : LQnq;
    //   92: iload_1
    //   93: iload_2
    //   94: iload_3
    //   95: invokevirtual Dne : (III)I
    //   98: istore #6
    //   100: iload #6
    //   102: ifle -> 150
    //   105: getstatic zKP.Dne : [LzKP;
    //   108: iload #6
    //   110: aaload
    //   111: aload_0
    //   112: getfield Dne : LQnq;
    //   115: iload_1
    //   116: iload_2
    //   117: iload_3
    //   118: aload_0
    //   119: getfield Dne : LPJQ;
    //   122: invokevirtual Dne : (LQnq;IIILFiG;)V
    //   125: getstatic zKP.Dne : [LzKP;
    //   128: iload #6
    //   130: aaload
    //   131: aload_0
    //   132: getfield Dne : LPJQ;
    //   135: aload_0
    //   136: getfield Dne : LPJQ;
    //   139: getfield Dne : LQnq;
    //   142: iload_1
    //   143: iload_2
    //   144: iload_3
    //   145: invokevirtual Dne : (LFiG;LQnq;III)F
    //   148: fstore #5
    //   150: iload #6
    //   152: ifle -> 173
    //   155: fload #5
    //   157: fconst_1
    //   158: fcmpl
    //   159: iflt -> 173
    //   162: aload_0
    //   163: iload_1
    //   164: iload_2
    //   165: iload_3
    //   166: invokevirtual Dne : (III)Z
    //   169: pop
    //   170: goto -> 226
    //   173: aload_0
    //   174: iconst_1
    //   175: putfield Dne : Z
    //   178: aload_0
    //   179: iload_1
    //   180: putfield FWm : I
    //   183: aload_0
    //   184: iload_2
    //   185: putfield bzF : I
    //   188: aload_0
    //   189: iload_3
    //   190: putfield Qnq : I
    //   193: fload #5
    //   195: ldc 10.0
    //   197: fmul
    //   198: f2i
    //   199: istore #7
    //   201: aload_0
    //   202: getfield Dne : LQnq;
    //   205: aload_0
    //   206: getfield Dne : LPJQ;
    //   209: getfield aFZ : I
    //   212: iload_1
    //   213: iload_2
    //   214: iload_3
    //   215: iload #7
    //   217: invokevirtual aFZ : (IIIII)V
    //   220: aload_0
    //   221: iload #7
    //   223: putfield mrb : I
    //   226: return
  }
  
  public void Dne(RAN paramRAN) {
    this.Dne = paramRAN;
  }
  
  private boolean FWm(int paramInt1, int paramInt2, int paramInt3) {
    // Byte code:
    //   0: getstatic zKP.Dne : [LzKP;
    //   3: aload_0
    //   4: getfield Dne : LQnq;
    //   7: iload_1
    //   8: iload_2
    //   9: iload_3
    //   10: invokevirtual Dne : (III)I
    //   13: aaload
    //   14: astore #4
    //   16: aload_0
    //   17: getfield Dne : LQnq;
    //   20: iload_1
    //   21: iload_2
    //   22: iload_3
    //   23: invokevirtual bzF : (III)I
    //   26: istore #5
    //   28: aload #4
    //   30: ifnull -> 51
    //   33: aload #4
    //   35: aload_0
    //   36: getfield Dne : LQnq;
    //   39: iload_1
    //   40: iload_2
    //   41: iload_3
    //   42: iload #5
    //   44: aload_0
    //   45: getfield Dne : LPJQ;
    //   48: invokevirtual Dne : (LQnq;IIIILFiG;)V
    //   51: aload_0
    //   52: getfield Dne : LQnq;
    //   55: iload_1
    //   56: iload_2
    //   57: iload_3
    //   58: invokevirtual Qnq : (III)Z
    //   61: istore #6
    //   63: aload #4
    //   65: ifnull -> 87
    //   68: iload #6
    //   70: ifeq -> 87
    //   73: aload #4
    //   75: aload_0
    //   76: getfield Dne : LQnq;
    //   79: iload_1
    //   80: iload_2
    //   81: iload_3
    //   82: iload #5
    //   84: invokevirtual bzF : (LQnq;IIII)V
    //   87: iload #6
    //   89: ireturn
  }
  
  public void FWm(int paramInt1, int paramInt2, int paramInt3) {
    // Byte code:
    //   0: aload_0
    //   1: iconst_0
    //   2: putfield Dne : Z
    //   5: aload_0
    //   6: getfield Dne : LQnq;
    //   9: aload_0
    //   10: getfield Dne : LPJQ;
    //   13: getfield aFZ : I
    //   16: aload_0
    //   17: getfield FWm : I
    //   20: aload_0
    //   21: getfield bzF : I
    //   24: aload_0
    //   25: getfield Qnq : I
    //   28: iconst_m1
    //   29: invokevirtual aFZ : (IIIII)V
    //   32: return
  }
}


/* Location:              C:\Users\fract\Downloads\ERROR422.jar!\dyC.class
 * Java compiler version: 8 (52.0)
 * JD-Core Version:       1.1.3
 */