import java.net.SocketAddress;
import java.text.SimpleDateFormat;
import java.util.ArrayList;
import java.util.Iterator;
import java.util.List;
import java.util.Map;
import java.util.Set;

public abstract class dzN {
  private AAC Dne;
  
  private XHL Dne;
  
  private final bkM FWm;
  
  private final bkM Dne;
  
  protected int Dne;
  
  private int bzF;
  
  private Set FWm;
  
  private Set Dne;
  
  private final Jwh Dne;
  
  private boolean Dne;
  
  private boolean FWm;
  
  protected int FWm;
  
  public final List Dne;
  
  private static final SimpleDateFormat Dne = new SimpleDateFormat("yyyy-MM-dd 'at' HH:mm:ss z");
  
  public int bzF() {
    return this.Dne;
  }
  
  public void Qnq() {
    // Byte code:
    //   0: aload_0
    //   1: getfield Dne : Ljava/util/List;
    //   4: invokeinterface isEmpty : ()Z
    //   9: ifne -> 36
    //   12: aload_0
    //   13: getfield Dne : Ljava/util/List;
    //   16: iconst_0
    //   17: invokeinterface get : (I)Ljava/lang/Object;
    //   22: checkcast PJQ
    //   25: getfield Dne : LTnv;
    //   28: ldc 'Server closed'
    //   30: invokevirtual Dne : (Ljava/lang/String;)V
    //   33: goto -> 0
    //   36: return
  }
  
  public boolean Dne() {
    return this.Dne;
  }
  
  public void bzF(String paramString) {
    // Byte code:
    //   0: aload_0
    //   1: getfield FWm : Ljava/util/Set;
    //   4: aload_1
    //   5: invokeinterface add : (Ljava/lang/Object;)Z
    //   10: pop
    //   11: return
  }
  
  public void Dne(NER paramNER, int paramInt) {
    // Byte code:
    //   0: iconst_0
    //   1: istore_3
    //   2: iload_3
    //   3: aload_0
    //   4: getfield Dne : Ljava/util/List;
    //   7: invokeinterface size : ()I
    //   12: if_icmpge -> 54
    //   15: aload_0
    //   16: getfield Dne : Ljava/util/List;
    //   19: iload_3
    //   20: invokeinterface get : (I)Ljava/lang/Object;
    //   25: checkcast PJQ
    //   28: astore #4
    //   30: aload #4
    //   32: getfield qLR : I
    //   35: iload_2
    //   36: if_icmpne -> 48
    //   39: aload #4
    //   41: getfield Dne : LTnv;
    //   44: aload_1
    //   45: invokevirtual Dne : (LNER;)V
    //   48: iinc #3, 1
    //   51: goto -> 2
    //   54: return
  }
  
  public PJQ Dne(PJQ paramPJQ, int paramInt, boolean paramBoolean) {
    // Byte code:
    //   0: aload_1
    //   1: invokevirtual Dne : ()LRAN;
    //   4: invokevirtual Dne : ()Lclp;
    //   7: aload_1
    //   8: invokevirtual Dne : (LPJQ;)V
    //   11: aload_1
    //   12: invokevirtual Dne : ()LRAN;
    //   15: invokevirtual Dne : ()Lclp;
    //   18: aload_1
    //   19: invokevirtual FWm : (LsMa;)V
    //   22: aload_1
    //   23: invokevirtual Dne : ()LRAN;
    //   26: invokevirtual Dne : ()Lwrs;
    //   29: aload_1
    //   30: invokevirtual bzF : (LPJQ;)V
    //   33: aload_0
    //   34: getfield Dne : Ljava/util/List;
    //   37: aload_1
    //   38: invokeinterface remove : (Ljava/lang/Object;)Z
    //   43: pop
    //   44: aload_0
    //   45: getfield Dne : LJwh;
    //   48: aload_1
    //   49: getfield qLR : I
    //   52: invokevirtual Dne : (I)LRAN;
    //   55: aload_1
    //   56: invokevirtual Qnq : (LsMa;)V
    //   59: aload_1
    //   60: invokevirtual bzF : ()LiSh;
    //   63: astore #4
    //   65: aload_1
    //   66: invokevirtual LVR : ()Z
    //   69: istore #5
    //   71: aload_1
    //   72: iload_2
    //   73: putfield qLR : I
    //   76: aload_0
    //   77: getfield Dne : LJwh;
    //   80: invokevirtual kGO : ()Z
    //   83: ifeq -> 109
    //   86: new OzV
    //   89: dup
    //   90: aload_0
    //   91: getfield Dne : LJwh;
    //   94: aload_1
    //   95: getfield qLR : I
    //   98: invokevirtual Dne : (I)LRAN;
    //   101: invokespecial <init> : (LQnq;)V
    //   104: astore #6
    //   106: goto -> 129
    //   109: new dyC
    //   112: dup
    //   113: aload_0
    //   114: getfield Dne : LJwh;
    //   117: aload_1
    //   118: getfield qLR : I
    //   121: invokevirtual Dne : (I)LRAN;
    //   124: invokespecial <init> : (LQnq;)V
    //   127: astore #6
    //   129: new PJQ
    //   132: dup
    //   133: aload_0
    //   134: getfield Dne : LJwh;
    //   137: aload_0
    //   138: getfield Dne : LJwh;
    //   141: aload_1
    //   142: getfield qLR : I
    //   145: invokevirtual Dne : (I)LRAN;
    //   148: aload_1
    //   149: getfield aFZ : Ljava/lang/String;
    //   152: aload #6
    //   154: checkcast dyC
    //   157: invokespecial <init> : (LJwh;LQnq;Ljava/lang/String;LdyC;)V
    //   160: astore #7
    //   162: aload #7
    //   164: aload_1
    //   165: getfield Dne : LTnv;
    //   168: putfield Dne : LTnv;
    //   171: aload #7
    //   173: aload_1
    //   174: iload_3
    //   175: invokevirtual Dne : (LFiG;Z)V
    //   178: aload #7
    //   180: aload_1
    //   181: getfield aFZ : I
    //   184: putfield aFZ : I
    //   187: aload_0
    //   188: getfield Dne : LJwh;
    //   191: aload_1
    //   192: getfield qLR : I
    //   195: invokevirtual Dne : (I)LRAN;
    //   198: astore #8
    //   200: aload_0
    //   201: aload #7
    //   203: aload_1
    //   204: aload #8
    //   206: invokespecial Dne : (LPJQ;LPJQ;LQnq;)V
    //   209: aload #4
    //   211: ifnull -> 305
    //   214: aload_0
    //   215: getfield Dne : LJwh;
    //   218: aload_1
    //   219: getfield qLR : I
    //   222: invokevirtual Dne : (I)LRAN;
    //   225: aload #4
    //   227: iload #5
    //   229: invokestatic Dne : (LQnq;LiSh;Z)LiSh;
    //   232: astore #9
    //   234: aload #9
    //   236: ifnull -> 288
    //   239: aload #7
    //   241: aload #9
    //   243: getfield Dne : I
    //   246: i2f
    //   247: ldc 0.5
    //   249: fadd
    //   250: f2d
    //   251: aload #9
    //   253: getfield FWm : I
    //   256: i2f
    //   257: ldc 0.1
    //   259: fadd
    //   260: f2d
    //   261: aload #9
    //   263: getfield bzF : I
    //   266: i2f
    //   267: ldc 0.5
    //   269: fadd
    //   270: f2d
    //   271: fconst_0
    //   272: fconst_0
    //   273: invokevirtual FWm : (DDDFF)V
    //   276: aload #7
    //   278: aload #4
    //   280: iload #5
    //   282: invokevirtual Dne : (LiSh;Z)V
    //   285: goto -> 305
    //   288: aload #7
    //   290: getfield Dne : LTnv;
    //   293: new Tnn
    //   296: dup
    //   297: iconst_0
    //   298: iconst_0
    //   299: invokespecial <init> : (II)V
    //   302: invokevirtual Dne : (LNER;)V
    //   305: aload #8
    //   307: getfield Dne : LEnH;
    //   310: aload #7
    //   312: getfield div : D
    //   315: d2i
    //   316: iconst_4
    //   317: ishr
    //   318: aload #7
    //   320: getfield mrb : D
    //   323: d2i
    //   324: iconst_4
    //   325: ishr
    //   326: invokevirtual FWm : (II)LqMV;
    //   329: pop
    //   330: aload #8
    //   332: aload #7
    //   334: aload #7
    //   336: getfield Dne : LbSp;
    //   339: invokevirtual Dne : (LsMa;LbSp;)Ljava/util/List;
    //   342: invokeinterface isEmpty : ()Z
    //   347: ifne -> 375
    //   350: aload #7
    //   352: aload #7
    //   354: getfield div : D
    //   357: aload #7
    //   359: getfield IjH : D
    //   362: dconst_1
    //   363: dadd
    //   364: aload #7
    //   366: getfield mrb : D
    //   369: invokevirtual bzF : (DDD)V
    //   372: goto -> 330
    //   375: aload #7
    //   377: getfield Dne : LTnv;
    //   380: new fmA
    //   383: dup
    //   384: aload #7
    //   386: getfield qLR : I
    //   389: aload #7
    //   391: getfield Dne : LQnq;
    //   394: getfield aFZ : I
    //   397: i2b
    //   398: aload #7
    //   400: getfield Dne : LQnq;
    //   403: invokevirtual Dne : ()LxoY;
    //   406: invokevirtual Dne : ()LkGO;
    //   409: aload #7
    //   411: getfield Dne : LQnq;
    //   414: invokevirtual FWm : ()I
    //   417: aload #7
    //   419: getfield Dne : LdyC;
    //   422: invokevirtual Dne : ()LXHL;
    //   425: invokespecial <init> : (IBLkGO;ILXHL;)V
    //   428: invokevirtual Dne : (LNER;)V
    //   431: aload #8
    //   433: invokevirtual Dne : ()LiSh;
    //   436: astore #9
    //   438: aload #7
    //   440: getfield Dne : LTnv;
    //   443: aload #7
    //   445: getfield div : D
    //   448: aload #7
    //   450: getfield IjH : D
    //   453: aload #7
    //   455: getfield mrb : D
    //   458: aload #7
    //   460: getfield mrb : F
    //   463: aload #7
    //   465: getfield XHL : F
    //   468: invokevirtual Dne : (DDDFF)V
    //   471: aload #7
    //   473: getfield Dne : LTnv;
    //   476: new ROw
    //   479: dup
    //   480: aload #9
    //   482: getfield Dne : I
    //   485: aload #9
    //   487: getfield FWm : I
    //   490: aload #9
    //   492: getfield bzF : I
    //   495: invokespecial <init> : (III)V
    //   498: invokevirtual Dne : (LNER;)V
    //   501: aload #7
    //   503: getfield Dne : LTnv;
    //   506: new WXC
    //   509: dup
    //   510: aload #7
    //   512: getfield iNQ : F
    //   515: aload #7
    //   517: getfield mlD : I
    //   520: aload #7
    //   522: getfield eHV : I
    //   525: invokespecial <init> : (FII)V
    //   528: invokevirtual Dne : (LNER;)V
    //   531: aload_0
    //   532: aload #7
    //   534: aload #8
    //   536: invokevirtual FWm : (LPJQ;LRAN;)V
    //   539: aload #8
    //   541: invokevirtual Dne : ()Lwrs;
    //   544: aload #7
    //   546: invokevirtual Dne : (LPJQ;)V
    //   549: aload #8
    //   551: aload #7
    //   553: invokevirtual FWm : (LsMa;)Z
    //   556: pop
    //   557: aload_0
    //   558: getfield Dne : Ljava/util/List;
    //   561: aload #7
    //   563: invokeinterface add : (Ljava/lang/Object;)Z
    //   568: pop
    //   569: aload #7
    //   571: invokevirtual XHL : ()V
    //   574: aload #7
    //   576: aload #7
    //   578: invokevirtual XHL : ()I
    //   581: invokevirtual bzF : (I)V
    //   584: aload #7
    //   586: areturn
  }
  
  private void Dne(PJQ paramPJQ1, PJQ paramPJQ2, Qnq paramQnq) {
    // Byte code:
    //   0: aload_2
    //   1: ifnull -> 21
    //   4: aload_1
    //   5: getfield Dne : LdyC;
    //   8: aload_2
    //   9: getfield Dne : LdyC;
    //   12: invokevirtual Dne : ()LXHL;
    //   15: invokevirtual Dne : (LXHL;)V
    //   18: goto -> 39
    //   21: aload_0
    //   22: getfield Dne : LXHL;
    //   25: ifnull -> 39
    //   28: aload_1
    //   29: getfield Dne : LdyC;
    //   32: aload_0
    //   33: getfield Dne : LXHL;
    //   36: invokevirtual Dne : (LXHL;)V
    //   39: aload_1
    //   40: getfield Dne : LdyC;
    //   43: aload_3
    //   44: invokevirtual Dne : ()LxoY;
    //   47: invokevirtual Dne : ()LXHL;
    //   50: invokevirtual FWm : (LXHL;)V
    //   53: return
  }
  
  public int Dne() {
    return wrs.Dne(Qnq());
  }
  
  public void Dne(RAN[] paramArrayOfRAN) {
    this.Dne = (SimpleDateFormat)paramArrayOfRAN[0].Dne().Dne();
  }
  
  public void Dne(PJQ paramPJQ, int paramInt) {
    // Byte code:
    //   0: aload_1
    //   1: getfield qLR : I
    //   4: istore_3
    //   5: aload_0
    //   6: getfield Dne : LJwh;
    //   9: aload_1
    //   10: getfield qLR : I
    //   13: invokevirtual Dne : (I)LRAN;
    //   16: astore #4
    //   18: aload_1
    //   19: iload_2
    //   20: putfield qLR : I
    //   23: aload_0
    //   24: getfield Dne : LJwh;
    //   27: aload_1
    //   28: getfield qLR : I
    //   31: invokevirtual Dne : (I)LRAN;
    //   34: astore #5
    //   36: aload_1
    //   37: getfield Dne : LTnv;
    //   40: new fmA
    //   43: dup
    //   44: aload_1
    //   45: getfield qLR : I
    //   48: aload_1
    //   49: getfield Dne : LQnq;
    //   52: getfield aFZ : I
    //   55: i2b
    //   56: aload #5
    //   58: invokevirtual Dne : ()LxoY;
    //   61: invokevirtual Dne : ()LkGO;
    //   64: aload #5
    //   66: invokevirtual FWm : ()I
    //   69: aload_1
    //   70: getfield Dne : LdyC;
    //   73: invokevirtual Dne : ()LXHL;
    //   76: invokespecial <init> : (IBLkGO;ILXHL;)V
    //   79: invokevirtual Dne : (LNER;)V
    //   82: aload #4
    //   84: aload_1
    //   85: invokevirtual Qnq : (LsMa;)V
    //   88: aload_1
    //   89: iconst_0
    //   90: putfield Zpi : Z
    //   93: aload_0
    //   94: aload_1
    //   95: iload_3
    //   96: aload #4
    //   98: aload #5
    //   100: invokevirtual Dne : (LsMa;ILRAN;LRAN;)V
    //   103: aload_0
    //   104: aload_1
    //   105: aload #4
    //   107: invokevirtual Dne : (LPJQ;LRAN;)V
    //   110: aload_1
    //   111: getfield Dne : LTnv;
    //   114: aload_1
    //   115: getfield div : D
    //   118: aload_1
    //   119: getfield IjH : D
    //   122: aload_1
    //   123: getfield mrb : D
    //   126: aload_1
    //   127: getfield mrb : F
    //   130: aload_1
    //   131: getfield XHL : F
    //   134: invokevirtual Dne : (DDDFF)V
    //   137: aload_1
    //   138: getfield Dne : LdyC;
    //   141: aload #5
    //   143: invokevirtual Dne : (LRAN;)V
    //   146: aload_0
    //   147: aload_1
    //   148: aload #5
    //   150: invokevirtual FWm : (LPJQ;LRAN;)V
    //   153: aload_0
    //   154: aload_1
    //   155: invokevirtual aFZ : (LPJQ;)V
    //   158: aload_1
    //   159: invokevirtual Dne : ()Ljava/util/Collection;
    //   162: invokeinterface iterator : ()Ljava/util/Iterator;
    //   167: astore #6
    //   169: aload #6
    //   171: invokeinterface hasNext : ()Z
    //   176: ifeq -> 214
    //   179: aload #6
    //   181: invokeinterface next : ()Ljava/lang/Object;
    //   186: checkcast NAx
    //   189: astore #7
    //   191: aload_1
    //   192: getfield Dne : LTnv;
    //   195: new ziQ
    //   198: dup
    //   199: aload_1
    //   200: getfield aFZ : I
    //   203: aload #7
    //   205: invokespecial <init> : (ILNAx;)V
    //   208: invokevirtual Dne : (LNER;)V
    //   211: goto -> 169
    //   214: return
  }
  
  public void Dne(String paramString) {
    this.Dne.add(paramString.toLowerCase());
  }
  
  public int Qnq() {
    return this.FWm;
  }
  
  protected void Dne(PJQ paramPJQ) {
    this.Dne.Dne(paramPJQ);
  }
  
  public void FWm() {
    for (byte b = 0; b < this.Dne.size(); b++)
      Dne(this.Dne.get(b)); 
  }
  
  public bkM FWm() {
    return this.FWm;
  }
  
  public boolean FWm(String paramString) {
    // Byte code:
    //   0: aload_0
    //   1: getfield Dne : Ljava/util/Set;
    //   4: aload_1
    //   5: invokevirtual trim : ()Ljava/lang/String;
    //   8: invokevirtual toLowerCase : ()Ljava/lang/String;
    //   11: invokeinterface contains : (Ljava/lang/Object;)Z
    //   16: ifne -> 68
    //   19: aload_0
    //   20: getfield Dne : LJwh;
    //   23: invokevirtual Zpi : ()Z
    //   26: ifeq -> 61
    //   29: aload_0
    //   30: getfield Dne : LJwh;
    //   33: getfield Dne : [LRAN;
    //   36: iconst_0
    //   37: aaload
    //   38: invokevirtual Dne : ()LxoY;
    //   41: invokevirtual aFZ : ()Z
    //   44: ifeq -> 61
    //   47: aload_0
    //   48: getfield Dne : LJwh;
    //   51: invokevirtual mrb : ()Ljava/lang/String;
    //   54: aload_1
    //   55: invokevirtual equalsIgnoreCase : (Ljava/lang/String;)Z
    //   58: ifne -> 68
    //   61: aload_0
    //   62: getfield FWm : Z
    //   65: ifeq -> 72
    //   68: iconst_1
    //   69: goto -> 73
    //   72: iconst_0
    //   73: ireturn
  }
  
  public String[] FWm() {
    // Byte code:
    //   0: aload_0
    //   1: getfield Dne : LJwh;
    //   4: getfield Dne : [LRAN;
    //   7: iconst_0
    //   8: aaload
    //   9: invokevirtual Dne : ()LiDE;
    //   12: invokeinterface Dne : ()LAAC;
    //   17: invokeinterface Dne : ()[Ljava/lang/String;
    //   22: areturn
  }
  
  public List Dne(String paramString) {
    ArrayList<PJQ> arrayList = new ArrayList();
    for (PJQ pJQ : this.Dne) {
      if (pJQ.FWm().equals(paramString))
        arrayList.add(pJQ); 
    } 
    return arrayList;
  }
  
  public List Dne(iSh paramiSh, int paramInt1, int paramInt2, int paramInt3, int paramInt4, int paramInt5, int paramInt6, Map paramMap, String paramString1, String paramString2) {
    // Byte code:
    //   0: aload_0
    //   1: getfield Dne : Ljava/util/List;
    //   4: invokeinterface isEmpty : ()Z
    //   9: ifeq -> 14
    //   12: aconst_null
    //   13: areturn
    //   14: new java/util/ArrayList
    //   17: dup
    //   18: invokespecial <init> : ()V
    //   21: astore #11
    //   23: iload #4
    //   25: ifge -> 32
    //   28: iconst_1
    //   29: goto -> 33
    //   32: iconst_0
    //   33: istore #12
    //   35: iload_2
    //   36: iload_2
    //   37: imul
    //   38: istore #13
    //   40: iload_3
    //   41: iload_3
    //   42: imul
    //   43: istore #14
    //   45: iload #4
    //   47: invokestatic Dne : (I)I
    //   50: istore #4
    //   52: iconst_0
    //   53: istore #15
    //   55: iload #15
    //   57: aload_0
    //   58: getfield Dne : Ljava/util/List;
    //   61: invokeinterface size : ()I
    //   66: if_icmpge -> 333
    //   69: aload_0
    //   70: getfield Dne : Ljava/util/List;
    //   73: iload #15
    //   75: invokeinterface get : (I)Ljava/lang/Object;
    //   80: checkcast PJQ
    //   83: astore #16
    //   85: aload #9
    //   87: ifnull -> 131
    //   90: aload #9
    //   92: ldc_w '!'
    //   95: invokevirtual startsWith : (Ljava/lang/String;)Z
    //   98: istore #17
    //   100: iload #17
    //   102: ifeq -> 113
    //   105: aload #9
    //   107: iconst_1
    //   108: invokevirtual substring : (I)Ljava/lang/String;
    //   111: astore #9
    //   113: iload #17
    //   115: aload #9
    //   117: aload #16
    //   119: invokevirtual Dne : ()Ljava/lang/String;
    //   122: invokevirtual equalsIgnoreCase : (Ljava/lang/String;)Z
    //   125: if_icmpne -> 131
    //   128: goto -> 327
    //   131: aload #10
    //   133: ifnull -> 199
    //   136: aload #10
    //   138: ldc_w '!'
    //   141: invokevirtual startsWith : (Ljava/lang/String;)Z
    //   144: istore #17
    //   146: iload #17
    //   148: ifeq -> 159
    //   151: aload #10
    //   153: iconst_1
    //   154: invokevirtual substring : (I)Ljava/lang/String;
    //   157: astore #10
    //   159: aload #16
    //   161: invokevirtual Dne : ()LYGE;
    //   164: astore #18
    //   166: aload #18
    //   168: ifnonnull -> 177
    //   171: ldc_w ''
    //   174: goto -> 182
    //   177: aload #18
    //   179: invokevirtual Dne : ()Ljava/lang/String;
    //   182: astore #19
    //   184: iload #17
    //   186: aload #10
    //   188: aload #19
    //   190: invokevirtual equalsIgnoreCase : (Ljava/lang/String;)Z
    //   193: if_icmpne -> 199
    //   196: goto -> 327
    //   199: aload_1
    //   200: ifnull -> 251
    //   203: iload_2
    //   204: ifgt -> 211
    //   207: iload_3
    //   208: ifle -> 251
    //   211: aload_1
    //   212: aload #16
    //   214: invokevirtual Dne : ()LiSh;
    //   217: invokevirtual Dne : (LiSh;)F
    //   220: fstore #18
    //   222: iload_2
    //   223: ifle -> 235
    //   226: fload #18
    //   228: iload #13
    //   230: i2f
    //   231: fcmpg
    //   232: iflt -> 327
    //   235: iload_3
    //   236: ifle -> 251
    //   239: fload #18
    //   241: iload #14
    //   243: i2f
    //   244: fcmpl
    //   245: ifle -> 251
    //   248: goto -> 327
    //   251: aload_0
    //   252: aload #16
    //   254: aload #8
    //   256: invokespecial Dne : (LFiG;Ljava/util/Map;)Z
    //   259: ifeq -> 327
    //   262: iload #5
    //   264: getstatic XHL.Dne : LXHL;
    //   267: invokevirtual Dne : ()I
    //   270: if_icmpeq -> 289
    //   273: iload #5
    //   275: aload #16
    //   277: getfield Dne : LdyC;
    //   280: invokevirtual Dne : ()LXHL;
    //   283: invokevirtual Dne : ()I
    //   286: if_icmpne -> 327
    //   289: iload #6
    //   291: ifle -> 304
    //   294: aload #16
    //   296: getfield eHV : I
    //   299: iload #6
    //   301: if_icmplt -> 327
    //   304: aload #16
    //   306: getfield eHV : I
    //   309: iload #7
    //   311: if_icmpgt -> 327
    //   314: aload #11
    //   316: checkcast java/util/List
    //   319: aload #16
    //   321: invokeinterface add : (Ljava/lang/Object;)Z
    //   326: pop
    //   327: iinc #15, 1
    //   330: goto -> 55
    //   333: aload_1
    //   334: ifnull -> 353
    //   337: aload #11
    //   339: checkcast java/util/List
    //   342: new dTr
    //   345: dup
    //   346: aload_1
    //   347: invokespecial <init> : (LiSh;)V
    //   350: invokestatic sort : (Ljava/util/List;Ljava/util/Comparator;)V
    //   353: iload #12
    //   355: ifeq -> 366
    //   358: aload #11
    //   360: checkcast java/util/List
    //   363: invokestatic reverse : (Ljava/util/List;)V
    //   366: iload #4
    //   368: ifle -> 399
    //   371: aload #11
    //   373: checkcast java/util/List
    //   376: iconst_0
    //   377: iload #4
    //   379: aload #11
    //   381: checkcast java/util/List
    //   384: invokeinterface size : ()I
    //   389: invokestatic min : (II)I
    //   392: invokeinterface subList : (II)Ljava/util/List;
    //   397: astore #11
    //   399: aload #11
    //   401: checkcast java/util/List
    //   404: areturn
  }
  
  public Set Dne() {
    return this.FWm;
  }
  
  public void Dne(PJQ paramPJQ, RAN paramRAN) {
    RAN rAN = paramPJQ.Dne();
    if (paramRAN != null)
      paramRAN.Dne().bzF(paramPJQ); 
    rAN.Dne().Dne(paramPJQ);
    rAN.Dne.FWm((int)paramPJQ.div >> 4, (int)paramPJQ.mrb >> 4);
  }
  
  public void FWm(PJQ paramPJQ, RAN paramRAN) {
    // Byte code:
    //   0: aload_1
    //   1: getfield Dne : LTnv;
    //   4: new uYm
    //   7: dup
    //   8: aload_2
    //   9: invokevirtual FWm : ()J
    //   12: aload_2
    //   13: invokevirtual bzF : ()J
    //   16: invokespecial <init> : (JJ)V
    //   19: invokevirtual Dne : (LNER;)V
    //   22: aload_2
    //   23: invokevirtual bzF : ()Z
    //   26: ifeq -> 45
    //   29: aload_1
    //   30: getfield Dne : LTnv;
    //   33: new Tnn
    //   36: dup
    //   37: iconst_1
    //   38: iconst_0
    //   39: invokespecial <init> : (II)V
    //   42: invokevirtual Dne : (LNER;)V
    //   45: return
  }
  
  public void Qnq(String paramString) {
    // Byte code:
    //   0: aload_0
    //   1: getfield FWm : Ljava/util/Set;
    //   4: aload_1
    //   5: invokeinterface remove : (Ljava/lang/Object;)Z
    //   10: pop
    //   11: return
  }
  
  public void Dne(NER paramNER) {
    // Byte code:
    //   0: iconst_0
    //   1: istore_2
    //   2: iload_2
    //   3: aload_0
    //   4: getfield Dne : Ljava/util/List;
    //   7: invokeinterface size : ()I
    //   12: if_icmpge -> 41
    //   15: aload_0
    //   16: getfield Dne : Ljava/util/List;
    //   19: iload_2
    //   20: invokeinterface get : (I)Ljava/lang/Object;
    //   25: checkcast PJQ
    //   28: getfield Dne : LTnv;
    //   31: aload_1
    //   32: invokevirtual Dne : (LNER;)V
    //   35: iinc #2, 1
    //   38: goto -> 2
    //   41: return
  }
  
  public int FWm() {
    return this.Dne.size();
  }
  
  public String[] Dne() {
    String[] arrayOfString = new String[this.Dne.size()];
    for (byte b = 0; b < this.Dne.size(); b++)
      arrayOfString[b] = ((PJQ)this.Dne.get(b)).aFZ; 
    return arrayOfString;
  }
  
  public PJQ Dne(String paramString) {
    // Byte code:
    //   0: new java/util/ArrayList
    //   3: dup
    //   4: invokespecial <init> : ()V
    //   7: astore_2
    //   8: iconst_0
    //   9: istore #4
    //   11: iload #4
    //   13: aload_0
    //   14: getfield Dne : Ljava/util/List;
    //   17: invokeinterface size : ()I
    //   22: if_icmpge -> 63
    //   25: aload_0
    //   26: getfield Dne : Ljava/util/List;
    //   29: iload #4
    //   31: invokeinterface get : (I)Ljava/lang/Object;
    //   36: checkcast PJQ
    //   39: astore_3
    //   40: aload_3
    //   41: getfield aFZ : Ljava/lang/String;
    //   44: aload_1
    //   45: invokevirtual equalsIgnoreCase : (Ljava/lang/String;)Z
    //   48: ifeq -> 57
    //   51: aload_2
    //   52: aload_3
    //   53: invokevirtual add : (Ljava/lang/Object;)Z
    //   56: pop
    //   57: iinc #4, 1
    //   60: goto -> 11
    //   63: aload_2
    //   64: invokevirtual iterator : ()Ljava/util/Iterator;
    //   67: astore #4
    //   69: aload #4
    //   71: invokeinterface hasNext : ()Z
    //   76: ifeq -> 103
    //   79: aload #4
    //   81: invokeinterface next : ()Ljava/lang/Object;
    //   86: checkcast PJQ
    //   89: astore_3
    //   90: aload_3
    //   91: getfield Dne : LTnv;
    //   94: ldc_w 'You logged in from another location'
    //   97: invokevirtual Dne : (Ljava/lang/String;)V
    //   100: goto -> 69
    //   103: aload_0
    //   104: getfield Dne : LJwh;
    //   107: invokevirtual kGO : ()Z
    //   110: ifeq -> 133
    //   113: new OzV
    //   116: dup
    //   117: aload_0
    //   118: getfield Dne : LJwh;
    //   121: iconst_0
    //   122: invokevirtual Dne : (I)LRAN;
    //   125: invokespecial <init> : (LQnq;)V
    //   128: astore #5
    //   130: goto -> 150
    //   133: new dyC
    //   136: dup
    //   137: aload_0
    //   138: getfield Dne : LJwh;
    //   141: iconst_0
    //   142: invokevirtual Dne : (I)LRAN;
    //   145: invokespecial <init> : (LQnq;)V
    //   148: astore #5
    //   150: new PJQ
    //   153: dup
    //   154: aload_0
    //   155: getfield Dne : LJwh;
    //   158: aload_0
    //   159: getfield Dne : LJwh;
    //   162: iconst_0
    //   163: invokevirtual Dne : (I)LRAN;
    //   166: aload_1
    //   167: aload #5
    //   169: checkcast dyC
    //   172: invokespecial <init> : (LJwh;LQnq;Ljava/lang/String;LdyC;)V
    //   175: areturn
  }
  
  public WkD Dne() {
    return null;
  }
  
  public dzN(Jwh paramJwh) {
    // Byte code:
    //   0: aload_0
    //   1: invokespecial <init> : ()V
    //   4: aload_0
    //   5: new java/util/ArrayList
    //   8: dup
    //   9: invokespecial <init> : ()V
    //   12: putfield Dne : Ljava/util/List;
    //   15: aload_0
    //   16: new bkM
    //   19: dup
    //   20: new java/io/File
    //   23: dup
    //   24: ldc_w 'banned-players.txt'
    //   27: invokespecial <init> : (Ljava/lang/String;)V
    //   30: invokespecial <init> : (Ljava/io/File;)V
    //   33: putfield Dne : LbkM;
    //   36: aload_0
    //   37: new bkM
    //   40: dup
    //   41: new java/io/File
    //   44: dup
    //   45: ldc_w 'banned-ips.txt'
    //   48: invokespecial <init> : (Ljava/lang/String;)V
    //   51: invokespecial <init> : (Ljava/io/File;)V
    //   54: putfield FWm : LbkM;
    //   57: aload_0
    //   58: new java/util/HashSet
    //   61: dup
    //   62: invokespecial <init> : ()V
    //   65: putfield Dne : Ljava/util/Set;
    //   68: aload_0
    //   69: new java/util/HashSet
    //   72: dup
    //   73: invokespecial <init> : ()V
    //   76: putfield FWm : Ljava/util/Set;
    //   79: aload_0
    //   80: iconst_0
    //   81: putfield bzF : I
    //   84: aload_0
    //   85: aload_1
    //   86: putfield Dne : LJwh;
    //   89: aload_0
    //   90: getfield Dne : LbkM;
    //   93: iconst_0
    //   94: invokevirtual Dne : (Z)V
    //   97: aload_0
    //   98: getfield FWm : LbkM;
    //   101: iconst_0
    //   102: invokevirtual Dne : (Z)V
    //   105: aload_0
    //   106: bipush #8
    //   108: putfield Dne : I
    //   111: return
  }
  
  public void Dne(FiG paramFiG, double paramDouble1, double paramDouble2, double paramDouble3, double paramDouble4, int paramInt, NER paramNER) {
    // Byte code:
    //   0: iconst_0
    //   1: istore #12
    //   3: iload #12
    //   5: aload_0
    //   6: getfield Dne : Ljava/util/List;
    //   9: invokeinterface size : ()I
    //   14: if_icmpge -> 120
    //   17: aload_0
    //   18: getfield Dne : Ljava/util/List;
    //   21: iload #12
    //   23: invokeinterface get : (I)Ljava/lang/Object;
    //   28: checkcast PJQ
    //   31: astore #13
    //   33: aload #13
    //   35: aload_1
    //   36: if_acmpeq -> 114
    //   39: aload #13
    //   41: getfield qLR : I
    //   44: iload #10
    //   46: if_icmpne -> 114
    //   49: dload_2
    //   50: aload #13
    //   52: getfield div : D
    //   55: dsub
    //   56: dstore #14
    //   58: dload #4
    //   60: aload #13
    //   62: getfield IjH : D
    //   65: dsub
    //   66: dstore #16
    //   68: dload #6
    //   70: aload #13
    //   72: getfield mrb : D
    //   75: dsub
    //   76: dstore #18
    //   78: dload #14
    //   80: dload #14
    //   82: dmul
    //   83: dload #16
    //   85: dload #16
    //   87: dmul
    //   88: dadd
    //   89: dload #18
    //   91: dload #18
    //   93: dmul
    //   94: dadd
    //   95: dload #8
    //   97: dload #8
    //   99: dmul
    //   100: dcmpg
    //   101: ifge -> 114
    //   104: aload #13
    //   106: getfield Dne : LTnv;
    //   109: aload #11
    //   111: invokevirtual Dne : (LNER;)V
    //   114: iinc #12, 1
    //   117: goto -> 3
    //   120: return
  }
  
  private boolean Dne(FiG paramFiG, Map paramMap) {
    if (paramMap != null && paramMap.size() != 0) {
      Iterator<Map.Entry> iterator = paramMap.entrySet().iterator();
      while (true) {
        if (!iterator.hasNext())
          return true; 
        Map.Entry entry = iterator.next();
        String str = (String)entry.getKey();
        boolean bool = false;
        if (str.endsWith("_min") && str.length() > 4) {
          bool = true;
          str = str.substring(0, str.length() - 4);
        } 
        SFA sFA = paramFiG.Dne();
        vfE vfE = sFA.Dne(str);
        if (vfE == null)
          return false; 
        OHz oHz = paramFiG.Dne().Dne(paramFiG.Dne(), vfE);
        int i = oHz.Dne();
        if (i < ((Integer)entry.getValue()).intValue() && bool)
          return false; 
        if (i > ((Integer)entry.getValue()).intValue() && !bool)
          return false; 
      } 
    } 
    return true;
  }
  
  protected void Dne(kXX paramkXX, PJQ paramPJQ) {
    // Byte code:
    //   0: new java/util/HashSet
    //   3: dup
    //   4: invokespecial <init> : ()V
    //   7: astore_3
    //   8: aload_1
    //   9: invokevirtual aFZ : ()Ljava/util/Collection;
    //   12: invokeinterface iterator : ()Ljava/util/Iterator;
    //   17: astore #4
    //   19: aload #4
    //   21: invokeinterface hasNext : ()Z
    //   26: ifeq -> 61
    //   29: aload #4
    //   31: invokeinterface next : ()Ljava/lang/Object;
    //   36: checkcast YGE
    //   39: astore #5
    //   41: aload_2
    //   42: getfield Dne : LTnv;
    //   45: new SPR
    //   48: dup
    //   49: aload #5
    //   51: iconst_0
    //   52: invokespecial <init> : (LYGE;I)V
    //   55: invokevirtual Dne : (LNER;)V
    //   58: goto -> 19
    //   61: iconst_0
    //   62: istore #5
    //   64: iload #5
    //   66: iconst_3
    //   67: if_icmpge -> 156
    //   70: aload_1
    //   71: iload #5
    //   73: invokevirtual Dne : (I)LvfE;
    //   76: astore #6
    //   78: aload #6
    //   80: ifnull -> 150
    //   83: aload_3
    //   84: aload #6
    //   86: invokevirtual contains : (Ljava/lang/Object;)Z
    //   89: ifne -> 150
    //   92: aload_1
    //   93: aload #6
    //   95: invokevirtual Dne : (LvfE;)Ljava/util/List;
    //   98: astore #7
    //   100: aload #7
    //   102: invokeinterface iterator : ()Ljava/util/Iterator;
    //   107: astore #8
    //   109: aload #8
    //   111: invokeinterface hasNext : ()Z
    //   116: ifeq -> 143
    //   119: aload #8
    //   121: invokeinterface next : ()Ljava/lang/Object;
    //   126: checkcast NER
    //   129: astore #9
    //   131: aload_2
    //   132: getfield Dne : LTnv;
    //   135: aload #9
    //   137: invokevirtual Dne : (LNER;)V
    //   140: goto -> 109
    //   143: aload_3
    //   144: aload #6
    //   146: invokevirtual add : (Ljava/lang/Object;)Z
    //   149: pop
    //   150: iinc #5, 1
    //   153: goto -> 64
    //   156: return
  }
  
  public bkM Dne() {
    return (bkM)this.Dne;
  }
  
  public void Qnq(PJQ paramPJQ) {
    Dne(paramPJQ);
    RAN rAN = paramPJQ.Dne();
    if (paramPJQ.FWm != null) {
      rAN.bzF((sMa)paramPJQ.FWm);
      System.out.println("removing player mount");
    } 
    rAN.bzF(paramPJQ);
    rAN.Dne().bzF(paramPJQ);
    this.Dne.remove(paramPJQ);
    Dne(new fPl(paramPJQ.aFZ, false, 9999));
  }
  
  public void Dne(sMa paramsMa, int paramInt, RAN paramRAN1, RAN paramRAN2) {
    double d1;
    double d2;
    boolean bool1 = paramsMa.div;
    float f1 = paramsMa.mrb;
    double d3 = 8.0D;
    boolean bool2 = paramsMa.div;
    double d4 = paramsMa.IjH;
    float f2 = paramsMa.mrb;
    float f3 = paramsMa.mrb;
    paramRAN1.Dne.Dne("moving");
    if (paramsMa.qLR == -1) {
      d1 = bool1 / d3;
      d2 = f1 / d3;
      paramsMa.FWm(d1, paramsMa.IjH, d2, paramsMa.mrb, paramsMa.XHL);
      if (paramsMa.udO())
        paramRAN1.Dne(paramsMa, false); 
    } else if (paramsMa.qLR == 0.0F) {
      d1 *= d3;
      d2 *= d3;
      paramsMa.FWm(d1, paramsMa.IjH, d2, paramsMa.mrb, paramsMa.XHL);
      if (paramsMa.udO())
        paramRAN1.Dne(paramsMa, false); 
    } else {
      iSh iSh;
      if (paramInt == 1) {
        iSh = paramRAN2.Dne();
      } else {
        iSh = paramRAN2.FWm();
      } 
      d1 = iSh.Dne;
      paramsMa.IjH = iSh.FWm;
      d2 = iSh.bzF;
      paramsMa.FWm(d1, paramsMa.IjH, d2, 90.0F, 0.0F);
      if (paramsMa.udO())
        paramRAN1.Dne(paramsMa, false); 
    } 
    paramRAN1.Dne.FWm();
    if (paramInt != 1) {
      paramRAN1.Dne.Dne("placing");
      d1 = geR.Dne((int)d1, -29999872, 29999872);
      d2 = geR.Dne((int)d2, -29999872, 29999872);
      if (paramsMa.udO()) {
        paramRAN2.FWm(paramsMa);
        paramsMa.FWm(d1, paramsMa.IjH, d2, paramsMa.mrb, paramsMa.XHL);
        paramRAN2.Dne(paramsMa, false);
        paramRAN2.Dne().Dne(paramsMa, bool2, d4, f2, f3);
      } 
      paramRAN1.Dne.FWm();
    } 
    paramsMa.Dne(paramRAN2);
  }
  
  public void Dne() {
    if (++this.bzF > 600)
      this.bzF = 0; 
    if (this.bzF < this.Dne.size()) {
      PJQ pJQ = this.Dne.get(this.bzF);
      Dne(new fPl(pJQ.aFZ, true, pJQ.Dne));
    } 
  }
  
  public void FWm(PJQ paramPJQ) {
    // Byte code:
    //   0: aload_0
    //   1: new fPl
    //   4: dup
    //   5: aload_1
    //   6: getfield aFZ : Ljava/lang/String;
    //   9: iconst_1
    //   10: sipush #1000
    //   13: invokespecial <init> : (Ljava/lang/String;ZI)V
    //   16: invokevirtual Dne : (LNER;)V
    //   19: aload_0
    //   20: getfield Dne : Ljava/util/List;
    //   23: aload_1
    //   24: invokeinterface add : (Ljava/lang/Object;)Z
    //   29: pop
    //   30: aload_0
    //   31: getfield Dne : LJwh;
    //   34: aload_1
    //   35: getfield qLR : I
    //   38: invokevirtual Dne : (I)LRAN;
    //   41: astore_2
    //   42: aload_2
    //   43: aload_1
    //   44: invokevirtual FWm : (LsMa;)Z
    //   47: pop
    //   48: aload_0
    //   49: aload_1
    //   50: aconst_null
    //   51: checkcast RAN
    //   54: invokevirtual Dne : (LPJQ;LRAN;)V
    //   57: iconst_0
    //   58: istore_3
    //   59: iload_3
    //   60: aload_0
    //   61: getfield Dne : Ljava/util/List;
    //   64: invokeinterface size : ()I
    //   69: if_icmpge -> 118
    //   72: aload_0
    //   73: getfield Dne : Ljava/util/List;
    //   76: iload_3
    //   77: invokeinterface get : (I)Ljava/lang/Object;
    //   82: checkcast PJQ
    //   85: astore #4
    //   87: aload_1
    //   88: getfield Dne : LTnv;
    //   91: new fPl
    //   94: dup
    //   95: aload #4
    //   97: getfield aFZ : Ljava/lang/String;
    //   100: iconst_1
    //   101: aload #4
    //   103: getfield Dne : I
    //   106: invokespecial <init> : (Ljava/lang/String;ZI)V
    //   109: invokevirtual Dne : (LNER;)V
    //   112: iinc #3, 1
    //   115: goto -> 59
    //   118: return
  }
  
  public void FWm(String paramString) {
    this.Dne.remove(paramString.toLowerCase());
  }
  
  public void Dne(XHL paramXHL) {
    this.Dne = (SimpleDateFormat)paramXHL;
  }
  
  public void Dne(double paramDouble1, double paramDouble2, double paramDouble3, double paramDouble4, int paramInt, NER paramNER) {
    Dne((FiG)null, paramDouble1, paramDouble2, paramDouble3, paramDouble4, paramInt, paramNER);
  }
  
  public Set FWm() {
    return (Set)this.Dne;
  }
  
  public String Dne(SocketAddress paramSocketAddress, String paramString) {
    // Byte code:
    //   0: aload_0
    //   1: getfield Dne : LbkM;
    //   4: aload_2
    //   5: invokevirtual Dne : (Ljava/lang/String;)Z
    //   8: ifeq -> 99
    //   11: aload_0
    //   12: getfield Dne : LbkM;
    //   15: invokevirtual Dne : ()Ljava/util/Map;
    //   18: aload_2
    //   19: invokeinterface get : (Ljava/lang/Object;)Ljava/lang/Object;
    //   24: checkcast eHI
    //   27: astore_3
    //   28: new java/lang/StringBuilder
    //   31: dup
    //   32: invokespecial <init> : ()V
    //   35: ldc_w 'You are banned from this server!\\nReason: '
    //   38: invokevirtual append : (Ljava/lang/String;)Ljava/lang/StringBuilder;
    //   41: aload_3
    //   42: invokevirtual bzF : ()Ljava/lang/String;
    //   45: invokevirtual append : (Ljava/lang/String;)Ljava/lang/StringBuilder;
    //   48: invokevirtual toString : ()Ljava/lang/String;
    //   51: astore #4
    //   53: aload_3
    //   54: invokevirtual FWm : ()Ljava/util/Date;
    //   57: ifnull -> 96
    //   60: new java/lang/StringBuilder
    //   63: dup
    //   64: invokespecial <init> : ()V
    //   67: aload #4
    //   69: invokevirtual append : (Ljava/lang/String;)Ljava/lang/StringBuilder;
    //   72: ldc_w '\\nYour ban will be removed on '
    //   75: invokevirtual append : (Ljava/lang/String;)Ljava/lang/StringBuilder;
    //   78: getstatic dzN.Dne : Ljava/text/SimpleDateFormat;
    //   81: aload_3
    //   82: invokevirtual FWm : ()Ljava/util/Date;
    //   85: invokevirtual format : (Ljava/util/Date;)Ljava/lang/String;
    //   88: invokevirtual append : (Ljava/lang/String;)Ljava/lang/StringBuilder;
    //   91: invokevirtual toString : ()Ljava/lang/String;
    //   94: astore #4
    //   96: aload #4
    //   98: areturn
    //   99: aload_0
    //   100: aload_2
    //   101: invokevirtual Dne : (Ljava/lang/String;)Z
    //   104: ifne -> 111
    //   107: ldc_w 'You are not white-listed on this server!'
    //   110: areturn
    //   111: aload_1
    //   112: invokevirtual toString : ()Ljava/lang/String;
    //   115: astore_3
    //   116: aload_3
    //   117: aload_3
    //   118: ldc_w '/'
    //   121: invokevirtual indexOf : (Ljava/lang/String;)I
    //   124: iconst_1
    //   125: iadd
    //   126: invokevirtual substring : (I)Ljava/lang/String;
    //   129: astore_3
    //   130: aload_3
    //   131: iconst_0
    //   132: aload_3
    //   133: ldc_w ':'
    //   136: invokevirtual indexOf : (Ljava/lang/String;)I
    //   139: invokevirtual substring : (II)Ljava/lang/String;
    //   142: astore_3
    //   143: aload_0
    //   144: getfield FWm : LbkM;
    //   147: aload_3
    //   148: invokevirtual Dne : (Ljava/lang/String;)Z
    //   151: ifeq -> 246
    //   154: aload_0
    //   155: getfield FWm : LbkM;
    //   158: invokevirtual Dne : ()Ljava/util/Map;
    //   161: aload_3
    //   162: invokeinterface get : (Ljava/lang/Object;)Ljava/lang/Object;
    //   167: checkcast eHI
    //   170: astore #4
    //   172: new java/lang/StringBuilder
    //   175: dup
    //   176: invokespecial <init> : ()V
    //   179: ldc_w 'Your IP address is banned from this server!\\nReason: '
    //   182: invokevirtual append : (Ljava/lang/String;)Ljava/lang/StringBuilder;
    //   185: aload #4
    //   187: invokevirtual bzF : ()Ljava/lang/String;
    //   190: invokevirtual append : (Ljava/lang/String;)Ljava/lang/StringBuilder;
    //   193: invokevirtual toString : ()Ljava/lang/String;
    //   196: astore #5
    //   198: aload #4
    //   200: invokevirtual FWm : ()Ljava/util/Date;
    //   203: ifnull -> 243
    //   206: new java/lang/StringBuilder
    //   209: dup
    //   210: invokespecial <init> : ()V
    //   213: aload #5
    //   215: invokevirtual append : (Ljava/lang/String;)Ljava/lang/StringBuilder;
    //   218: ldc_w '\\nYour ban will be removed on '
    //   221: invokevirtual append : (Ljava/lang/String;)Ljava/lang/StringBuilder;
    //   224: getstatic dzN.Dne : Ljava/text/SimpleDateFormat;
    //   227: aload #4
    //   229: invokevirtual FWm : ()Ljava/util/Date;
    //   232: invokevirtual format : (Ljava/util/Date;)Ljava/lang/String;
    //   235: invokevirtual append : (Ljava/lang/String;)Ljava/lang/StringBuilder;
    //   238: invokevirtual toString : ()Ljava/lang/String;
    //   241: astore #5
    //   243: aload #5
    //   245: areturn
    //   246: aload_0
    //   247: getfield Dne : Ljava/util/List;
    //   250: invokeinterface size : ()I
    //   255: aload_0
    //   256: getfield Dne : I
    //   259: if_icmplt -> 268
    //   262: ldc_w 'The server is full!'
    //   265: goto -> 269
    //   268: aconst_null
    //   269: areturn
  }
  
  public void FWm(boolean paramBoolean) {
    this.FWm = paramBoolean;
  }
  
  public void bzF() {}
  
  public void bzF(PJQ paramPJQ) {
    paramPJQ.Dne().Dne().Qnq(paramPJQ);
  }
  
  public void Dne(boolean paramBoolean) {
    this.Dne = paramBoolean;
  }
  
  public PJQ FWm(String paramString) {
    Iterator<PJQ> iterator = this.Dne.iterator();
    while (true) {
      if (!iterator.hasNext())
        return null; 
      PJQ pJQ = iterator.next();
      if (pJQ.aFZ.equalsIgnoreCase(paramString))
        return pJQ; 
    } 
  }
  
  public void aFZ(String paramString) {
    this.Dne.a_(paramString);
    Dne(new rXx(paramString));
  }
  
  public String Dne() {
    String str = "";
    for (byte b = 0; b < this.Dne.size(); b++) {
      if (b > 0)
        str = str + ", "; 
      str = str + ((PJQ)this.Dne.get(b)).aFZ;
    } 
    return str;
  }
  
  public void Dne(RXf paramRXf, PJQ paramPJQ) {
    // Byte code:
    //   0: aload_0
    //   1: aload_2
    //   2: invokevirtual Dne : (LPJQ;)LWkD;
    //   5: astore_3
    //   6: aload_2
    //   7: aload_0
    //   8: getfield Dne : LJwh;
    //   11: aload_2
    //   12: getfield qLR : I
    //   15: invokevirtual Dne : (I)LRAN;
    //   18: invokevirtual Dne : (LQnq;)V
    //   21: aload_2
    //   22: getfield Dne : LdyC;
    //   25: aload_2
    //   26: getfield Dne : LQnq;
    //   29: checkcast RAN
    //   32: invokevirtual Dne : (LRAN;)V
    //   35: ldc_w 'local'
    //   38: astore #4
    //   40: aload_1
    //   41: invokeinterface Dne : ()Ljava/net/SocketAddress;
    //   46: ifnull -> 60
    //   49: aload_1
    //   50: invokeinterface Dne : ()Ljava/net/SocketAddress;
    //   55: invokevirtual toString : ()Ljava/lang/String;
    //   58: astore #4
    //   60: aload_0
    //   61: getfield Dne : LJwh;
    //   64: invokevirtual Dne : ()LdLs;
    //   67: new java/lang/StringBuilder
    //   70: dup
    //   71: invokespecial <init> : ()V
    //   74: aload_2
    //   75: getfield aFZ : Ljava/lang/String;
    //   78: invokevirtual append : (Ljava/lang/String;)Ljava/lang/StringBuilder;
    //   81: ldc_w '['
    //   84: invokevirtual append : (Ljava/lang/String;)Ljava/lang/StringBuilder;
    //   87: aload #4
    //   89: invokevirtual append : (Ljava/lang/String;)Ljava/lang/StringBuilder;
    //   92: ldc_w '] logged in with entity id '
    //   95: invokevirtual append : (Ljava/lang/String;)Ljava/lang/StringBuilder;
    //   98: aload_2
    //   99: getfield aFZ : I
    //   102: invokevirtual append : (I)Ljava/lang/StringBuilder;
    //   105: ldc_w ' at ('
    //   108: invokevirtual append : (Ljava/lang/String;)Ljava/lang/StringBuilder;
    //   111: aload_2
    //   112: getfield div : D
    //   115: invokevirtual append : (D)Ljava/lang/StringBuilder;
    //   118: ldc_w ', '
    //   121: invokevirtual append : (Ljava/lang/String;)Ljava/lang/StringBuilder;
    //   124: aload_2
    //   125: getfield IjH : D
    //   128: invokevirtual append : (D)Ljava/lang/StringBuilder;
    //   131: ldc_w ', '
    //   134: invokevirtual append : (Ljava/lang/String;)Ljava/lang/StringBuilder;
    //   137: aload_2
    //   138: getfield mrb : D
    //   141: invokevirtual append : (D)Ljava/lang/StringBuilder;
    //   144: ldc_w ')'
    //   147: invokevirtual append : (Ljava/lang/String;)Ljava/lang/StringBuilder;
    //   150: invokevirtual toString : ()Ljava/lang/String;
    //   153: invokeinterface Dne : (Ljava/lang/String;)V
    //   158: aload_0
    //   159: getfield Dne : LJwh;
    //   162: aload_2
    //   163: getfield qLR : I
    //   166: invokevirtual Dne : (I)LRAN;
    //   169: astore #5
    //   171: aload #5
    //   173: invokevirtual Dne : ()LiSh;
    //   176: astore #6
    //   178: aload_0
    //   179: aload_2
    //   180: aconst_null
    //   181: checkcast PJQ
    //   184: aload #5
    //   186: invokespecial Dne : (LPJQ;LPJQ;LQnq;)V
    //   189: new Tnv
    //   192: dup
    //   193: aload_0
    //   194: getfield Dne : LJwh;
    //   197: aload_1
    //   198: aload_2
    //   199: invokespecial <init> : (LJwh;LRXf;LPJQ;)V
    //   202: astore #7
    //   204: aload #7
    //   206: new VPw
    //   209: dup
    //   210: aload_2
    //   211: getfield aFZ : I
    //   214: aload #5
    //   216: invokevirtual Dne : ()LxoY;
    //   219: invokevirtual Dne : ()LkGO;
    //   222: aload_2
    //   223: getfield Dne : LdyC;
    //   226: invokevirtual Dne : ()LXHL;
    //   229: aload #5
    //   231: invokevirtual Dne : ()LxoY;
    //   234: invokevirtual Qnq : ()Z
    //   237: aload #5
    //   239: getfield Dne : LJik;
    //   242: getfield Dne : I
    //   245: aload #5
    //   247: getfield aFZ : I
    //   250: aload #5
    //   252: invokevirtual FWm : ()I
    //   255: aload_0
    //   256: invokevirtual bzF : ()I
    //   259: invokespecial <init> : (ILkGO;LXHL;ZIIII)V
    //   262: invokevirtual Dne : (LNER;)V
    //   265: aload #7
    //   267: new ROw
    //   270: dup
    //   271: aload #6
    //   273: getfield Dne : I
    //   276: aload #6
    //   278: getfield FWm : I
    //   281: aload #6
    //   283: getfield bzF : I
    //   286: invokespecial <init> : (III)V
    //   289: invokevirtual Dne : (LNER;)V
    //   292: aload #7
    //   294: new pSe
    //   297: dup
    //   298: aload_2
    //   299: getfield Dne : Luqg;
    //   302: invokespecial <init> : (Luqg;)V
    //   305: invokevirtual Dne : (LNER;)V
    //   308: aload #7
    //   310: new aig
    //   313: dup
    //   314: aload_2
    //   315: getfield Dne : LMOS;
    //   318: getfield Dne : I
    //   321: invokespecial <init> : (I)V
    //   324: invokevirtual Dne : (LNER;)V
    //   327: aload_0
    //   328: aload #5
    //   330: invokevirtual Dne : ()LSFA;
    //   333: checkcast kXX
    //   336: aload_2
    //   337: invokevirtual Dne : (LkXX;LPJQ;)V
    //   340: aload_0
    //   341: aload_2
    //   342: aload #5
    //   344: invokevirtual FWm : (LPJQ;LRAN;)V
    //   347: aload_0
    //   348: new rXx
    //   351: dup
    //   352: new java/lang/StringBuilder
    //   355: dup
    //   356: invokespecial <init> : ()V
    //   359: getstatic Dne.ooe : LDne;
    //   362: invokevirtual append : (Ljava/lang/Object;)Ljava/lang/StringBuilder;
    //   365: aload_2
    //   366: invokevirtual aFZ : ()Ljava/lang/String;
    //   369: invokevirtual append : (Ljava/lang/String;)Ljava/lang/StringBuilder;
    //   372: getstatic Dne.ooe : LDne;
    //   375: invokevirtual append : (Ljava/lang/Object;)Ljava/lang/StringBuilder;
    //   378: ldc_w ' joined the game.'
    //   381: invokevirtual append : (Ljava/lang/String;)Ljava/lang/StringBuilder;
    //   384: invokevirtual toString : ()Ljava/lang/String;
    //   387: invokespecial <init> : (Ljava/lang/String;)V
    //   390: invokevirtual Dne : (LNER;)V
    //   393: aload_0
    //   394: aload_2
    //   395: invokevirtual FWm : (LPJQ;)V
    //   398: aload #7
    //   400: aload_2
    //   401: getfield div : D
    //   404: aload_2
    //   405: getfield IjH : D
    //   408: aload_2
    //   409: getfield mrb : D
    //   412: aload_2
    //   413: getfield mrb : F
    //   416: aload_2
    //   417: getfield XHL : F
    //   420: invokevirtual Dne : (DDDFF)V
    //   423: aload_0
    //   424: getfield Dne : LJwh;
    //   427: invokevirtual Dne : ()LNuQ;
    //   430: aload #7
    //   432: invokevirtual Dne : (LTnv;)V
    //   435: aload #7
    //   437: new uYm
    //   440: dup
    //   441: aload #5
    //   443: invokevirtual FWm : ()J
    //   446: aload #5
    //   448: invokevirtual bzF : ()J
    //   451: invokespecial <init> : (JJ)V
    //   454: invokevirtual Dne : (LNER;)V
    //   457: aload_0
    //   458: getfield Dne : LJwh;
    //   461: invokevirtual Zpi : ()Ljava/lang/String;
    //   464: invokevirtual length : ()I
    //   467: ifle -> 488
    //   470: aload_2
    //   471: aload_0
    //   472: getfield Dne : LJwh;
    //   475: invokevirtual Zpi : ()Ljava/lang/String;
    //   478: aload_0
    //   479: getfield Dne : LJwh;
    //   482: invokevirtual DyG : ()I
    //   485: invokevirtual Dne : (Ljava/lang/String;I)V
    //   488: aload_2
    //   489: invokevirtual Dne : ()Ljava/util/Collection;
    //   492: invokeinterface iterator : ()Ljava/util/Iterator;
    //   497: astore #8
    //   499: aload #8
    //   501: invokeinterface hasNext : ()Z
    //   506: ifeq -> 542
    //   509: aload #8
    //   511: invokeinterface next : ()Ljava/lang/Object;
    //   516: checkcast NAx
    //   519: astore #9
    //   521: aload #7
    //   523: new ziQ
    //   526: dup
    //   527: aload_2
    //   528: getfield aFZ : I
    //   531: aload #9
    //   533: invokespecial <init> : (ILNAx;)V
    //   536: invokevirtual Dne : (LNER;)V
    //   539: goto -> 499
    //   542: aload_2
    //   543: invokevirtual XHL : ()V
    //   546: aload_3
    //   547: ifnull -> 605
    //   550: aload_3
    //   551: ldc_w 'Riding'
    //   554: invokevirtual Dne : (Ljava/lang/String;)Z
    //   557: ifeq -> 605
    //   560: aload_3
    //   561: ldc_w 'Riding'
    //   564: invokevirtual Dne : (Ljava/lang/String;)LWkD;
    //   567: aload #5
    //   569: invokestatic Dne : (LWkD;LQnq;)LsMa;
    //   572: astore #9
    //   574: aload #9
    //   576: ifnull -> 605
    //   579: aload #9
    //   581: iconst_1
    //   582: putfield Qnq : Z
    //   585: aload #5
    //   587: aload #9
    //   589: invokevirtual FWm : (LsMa;)Z
    //   592: pop
    //   593: aload_2
    //   594: aload #9
    //   596: invokevirtual bzF : (LsMa;)V
    //   599: aload #9
    //   601: iconst_0
    //   602: putfield Qnq : Z
    //   605: return
  }
  
  public void aFZ(PJQ paramPJQ) {
    // Byte code:
    //   0: aload_1
    //   1: aload_1
    //   2: getfield Dne : LPdb;
    //   5: invokevirtual Dne : (LPdb;)V
    //   8: aload_1
    //   9: invokevirtual trS : ()V
    //   12: aload_1
    //   13: getfield Dne : LTnv;
    //   16: new aig
    //   19: dup
    //   20: aload_1
    //   21: getfield Dne : LMOS;
    //   24: getfield Dne : I
    //   27: invokespecial <init> : (I)V
    //   30: invokevirtual Dne : (LNER;)V
    //   33: return
  }
  
  public boolean Dne(String paramString) {
    // Byte code:
    //   0: aload_1
    //   1: invokevirtual trim : ()Ljava/lang/String;
    //   4: invokevirtual toLowerCase : ()Ljava/lang/String;
    //   7: astore_1
    //   8: aload_0
    //   9: getfield Dne : Z
    //   12: ifeq -> 41
    //   15: aload_0
    //   16: getfield Dne : Ljava/util/Set;
    //   19: aload_1
    //   20: invokeinterface contains : (Ljava/lang/Object;)Z
    //   25: ifne -> 41
    //   28: aload_0
    //   29: getfield FWm : Ljava/util/Set;
    //   32: aload_1
    //   33: invokeinterface contains : (Ljava/lang/Object;)Z
    //   38: ifeq -> 45
    //   41: iconst_1
    //   42: goto -> 46
    //   45: iconst_0
    //   46: ireturn
  }
  
  public Jwh Dne() {
    return (Jwh)this.Dne;
  }
  
  public WkD Dne(PJQ paramPJQ) {
    // Byte code:
    //   0: aload_0
    //   1: getfield Dne : LJwh;
    //   4: getfield Dne : [LRAN;
    //   7: iconst_0
    //   8: aaload
    //   9: invokevirtual Dne : ()LxoY;
    //   12: invokevirtual FWm : ()LWkD;
    //   15: astore_2
    //   16: aload_1
    //   17: invokevirtual a_ : ()Ljava/lang/String;
    //   20: aload_0
    //   21: getfield Dne : LJwh;
    //   24: invokevirtual mrb : ()Ljava/lang/String;
    //   27: invokevirtual equals : (Ljava/lang/Object;)Z
    //   30: ifeq -> 56
    //   33: aload_2
    //   34: ifnull -> 56
    //   37: aload_1
    //   38: aload_2
    //   39: invokevirtual Qnq : (LWkD;)V
    //   42: aload_2
    //   43: astore_3
    //   44: getstatic java/lang/System.out : Ljava/io/PrintStream;
    //   47: ldc_w 'loading single player'
    //   50: invokevirtual println : (Ljava/lang/String;)V
    //   53: goto -> 67
    //   56: aload_0
    //   57: getfield Dne : LAAC;
    //   60: aload_1
    //   61: invokeinterface Dne : (LFiG;)LWkD;
    //   66: astore_3
    //   67: aload_3
    //   68: areturn
  }
}


/* Location:              C:\Users\fract\Downloads\ERROR422.jar!\dzN.class
 * Java compiler version: 8 (52.0)
 * JD-Core Version:       1.1.3
 */