public class ePu extends xZE {
  public int Dne() {
    return 2;
  }
  
  protected void Dne() {
    // Byte code:
    //   0: invokestatic Dne : ()LJwh;
    //   3: getfield Dne : [LRAN;
    //   6: iconst_0
    //   7: aaload
    //   8: invokevirtual zGp : ()V
    //   11: invokestatic Dne : ()LJwh;
    //   14: getfield Dne : [LRAN;
    //   17: iconst_0
    //   18: aaload
    //   19: invokevirtual Dne : ()LxoY;
    //   22: iconst_1
    //   23: invokevirtual Dne : (Z)V
    //   26: return
  }
  
  static {
  
  }
  
  public void Dne(gnI paramgnI, String[] paramArrayOfString) {
    Dne();
    Dne(paramgnI, "commands.downfall.success", new Object[0]);
  }
  
  public String Dne() {
    return "toggledownfall";
  }
}


/* Location:              C:\Users\fract\Downloads\ERROR422.jar!\ePu.class
 * Java compiler version: 8 (52.0)
 * JD-Core Version:       1.1.3
 */