public class etz extends cMv {
  private int FWm;
  
  Class Dne;
  
  float Dne;
  
  FUH Dne;
  
  wdG Dne;
  
  Qnq Dne;
  
  int Dne;
  
  boolean Dne = false;
  
  FUH FWm;
  
  public void Dne() {
    // Byte code:
    //   0: aload_0
    //   1: getfield Dne : LFUH;
    //   4: invokevirtual Dne : ()LKFZ;
    //   7: aload_0
    //   8: getfield Dne : LwdG;
    //   11: aload_0
    //   12: getfield Dne : F
    //   15: invokevirtual Dne : (LwdG;F)Z
    //   18: pop
    //   19: aload_0
    //   20: iconst_0
    //   21: putfield FWm : I
    //   24: return
  }
  
  public etz(FUH paramFUH, Class paramClass, float paramFloat, boolean paramBoolean) {
    this(paramFUH, paramFloat, paramBoolean);
    this.Dne = paramClass;
  }
  
  public void FWm() {
    // Byte code:
    //   0: aload_0
    //   1: aconst_null
    //   2: putfield FWm : LFUH;
    //   5: aload_0
    //   6: getfield Dne : LFUH;
    //   9: invokevirtual Dne : ()LKFZ;
    //   12: invokevirtual FWm : ()V
    //   15: return
  }
  
  public boolean Dne() {
    // Byte code:
    //   0: aload_0
    //   1: getfield Dne : LFUH;
    //   4: invokevirtual bzF : ()LFUH;
    //   7: astore_1
    //   8: aload_1
    //   9: ifnonnull -> 14
    //   12: iconst_0
    //   13: ireturn
    //   14: aload_0
    //   15: getfield Dne : Ljava/lang/Class;
    //   18: ifnull -> 37
    //   21: aload_0
    //   22: getfield Dne : Ljava/lang/Class;
    //   25: aload_1
    //   26: invokevirtual getClass : ()Ljava/lang/Class;
    //   29: invokevirtual isAssignableFrom : (Ljava/lang/Class;)Z
    //   32: ifne -> 37
    //   35: iconst_0
    //   36: ireturn
    //   37: aload_0
    //   38: aload_1
    //   39: putfield FWm : LFUH;
    //   42: aload_0
    //   43: aload_0
    //   44: getfield Dne : LFUH;
    //   47: invokevirtual Dne : ()LKFZ;
    //   50: aload_0
    //   51: getfield FWm : LFUH;
    //   54: invokevirtual Dne : (LFUH;)LwdG;
    //   57: putfield Dne : LwdG;
    //   60: aload_0
    //   61: getfield Dne : LwdG;
    //   64: ifnull -> 71
    //   67: iconst_1
    //   68: goto -> 72
    //   71: iconst_0
    //   72: ireturn
  }
  
  public boolean FWm() {
    // Byte code:
    //   0: aload_0
    //   1: getfield Dne : LFUH;
    //   4: invokevirtual bzF : ()LFUH;
    //   7: astore_1
    //   8: aload_1
    //   9: ifnonnull -> 16
    //   12: iconst_0
    //   13: goto -> 95
    //   16: aload_0
    //   17: getfield FWm : LFUH;
    //   20: invokevirtual udO : ()Z
    //   23: ifne -> 30
    //   26: iconst_0
    //   27: goto -> 95
    //   30: aload_0
    //   31: getfield Dne : Z
    //   34: ifne -> 58
    //   37: aload_0
    //   38: getfield Dne : LFUH;
    //   41: invokevirtual Dne : ()LKFZ;
    //   44: invokevirtual bzF : ()Z
    //   47: ifne -> 54
    //   50: iconst_1
    //   51: goto -> 95
    //   54: iconst_0
    //   55: goto -> 95
    //   58: aload_0
    //   59: getfield Dne : LFUH;
    //   62: aload_0
    //   63: getfield FWm : LFUH;
    //   66: getfield div : D
    //   69: invokestatic FWm : (D)I
    //   72: aload_0
    //   73: getfield FWm : LFUH;
    //   76: getfield IjH : D
    //   79: invokestatic FWm : (D)I
    //   82: aload_0
    //   83: getfield FWm : LFUH;
    //   86: getfield mrb : D
    //   89: invokestatic FWm : (D)I
    //   92: invokevirtual Dne : (III)Z
    //   95: ireturn
  }
  
  public etz(FUH paramFUH, float paramFloat, boolean paramBoolean) {
    this.Dne = paramFUH;
    this.Dne = paramFUH.Dne;
    this.Dne = paramFloat;
    this.Dne = paramBoolean;
    Dne(3);
  }
  
  public void bzF() {
    // Byte code:
    //   0: aload_0
    //   1: getfield Dne : LFUH;
    //   4: invokevirtual Dne : ()LbvU;
    //   7: aload_0
    //   8: getfield FWm : LFUH;
    //   11: ldc 30.0
    //   13: ldc 30.0
    //   15: invokevirtual Dne : (LsMa;FF)V
    //   18: aload_0
    //   19: getfield Dne : Z
    //   22: ifne -> 42
    //   25: aload_0
    //   26: getfield Dne : LFUH;
    //   29: invokevirtual Dne : ()LEEb;
    //   32: aload_0
    //   33: getfield FWm : LFUH;
    //   36: invokevirtual Dne : (LsMa;)Z
    //   39: ifeq -> 93
    //   42: aload_0
    //   43: dup
    //   44: getfield FWm : I
    //   47: iconst_1
    //   48: isub
    //   49: dup_x1
    //   50: putfield FWm : I
    //   53: ifgt -> 93
    //   56: aload_0
    //   57: iconst_4
    //   58: aload_0
    //   59: getfield Dne : LFUH;
    //   62: invokevirtual Dne : ()Ljava/util/Random;
    //   65: bipush #7
    //   67: invokevirtual nextInt : (I)I
    //   70: iadd
    //   71: putfield FWm : I
    //   74: aload_0
    //   75: getfield Dne : LFUH;
    //   78: invokevirtual Dne : ()LKFZ;
    //   81: aload_0
    //   82: getfield FWm : LFUH;
    //   85: aload_0
    //   86: getfield Dne : F
    //   89: invokevirtual Dne : (LFUH;F)Z
    //   92: pop
    //   93: aload_0
    //   94: aload_0
    //   95: getfield Dne : I
    //   98: iconst_1
    //   99: isub
    //   100: iconst_0
    //   101: invokestatic max : (II)I
    //   104: putfield Dne : I
    //   107: aload_0
    //   108: getfield Dne : LFUH;
    //   111: getfield ooe : F
    //   114: fconst_2
    //   115: fmul
    //   116: aload_0
    //   117: getfield Dne : LFUH;
    //   120: getfield ooe : F
    //   123: fmul
    //   124: fconst_2
    //   125: fmul
    //   126: f2d
    //   127: dstore_1
    //   128: aload_0
    //   129: getfield Dne : LFUH;
    //   132: aload_0
    //   133: getfield FWm : LFUH;
    //   136: getfield div : D
    //   139: aload_0
    //   140: getfield FWm : LFUH;
    //   143: getfield Dne : LbSp;
    //   146: getfield FWm : D
    //   149: aload_0
    //   150: getfield FWm : LFUH;
    //   153: getfield mrb : D
    //   156: invokevirtual Dne : (DDD)D
    //   159: dload_1
    //   160: dcmpg
    //   161: ifgt -> 206
    //   164: aload_0
    //   165: getfield Dne : I
    //   168: ifgt -> 206
    //   171: aload_0
    //   172: bipush #20
    //   174: putfield Dne : I
    //   177: aload_0
    //   178: getfield Dne : LFUH;
    //   181: invokevirtual Dne : ()LNMq;
    //   184: ifnull -> 194
    //   187: aload_0
    //   188: getfield Dne : LFUH;
    //   191: invokevirtual bzF : ()V
    //   194: aload_0
    //   195: getfield Dne : LFUH;
    //   198: aload_0
    //   199: getfield FWm : LFUH;
    //   202: invokevirtual bzF : (LsMa;)Z
    //   205: pop
    //   206: return
  }
}


/* Location:              C:\Users\fract\Downloads\ERROR422.jar!\etz.class
 * Java compiler version: 8 (52.0)
 * JD-Core Version:       1.1.3
 */