public class gNt extends cMv {
  private int FWm = -1;
  
  private kSJ Dne;
  
  private int Dne;
  
  private yQQ Dne = -1;
  
  public boolean Dne() {
    // Byte code:
    //   0: aload_0
    //   1: getfield Dne : LkSJ;
    //   4: getfield Dne : LQnq;
    //   7: invokevirtual Dne : ()Z
    //   10: ifeq -> 26
    //   13: aload_0
    //   14: getfield Dne : LkSJ;
    //   17: getfield Dne : LQnq;
    //   20: invokevirtual bzF : ()Z
    //   23: ifeq -> 203
    //   26: aload_0
    //   27: getfield Dne : LkSJ;
    //   30: getfield Dne : LQnq;
    //   33: getfield Dne : LJik;
    //   36: getfield FWm : Z
    //   39: ifne -> 203
    //   42: aload_0
    //   43: getfield Dne : LkSJ;
    //   46: invokevirtual Dne : ()Ljava/util/Random;
    //   49: bipush #50
    //   51: invokevirtual nextInt : (I)I
    //   54: ifeq -> 59
    //   57: iconst_0
    //   58: ireturn
    //   59: aload_0
    //   60: getfield Dne : I
    //   63: iconst_m1
    //   64: if_icmpeq -> 100
    //   67: aload_0
    //   68: getfield Dne : LkSJ;
    //   71: aload_0
    //   72: getfield Dne : I
    //   75: i2d
    //   76: aload_0
    //   77: getfield Dne : LkSJ;
    //   80: getfield IjH : D
    //   83: aload_0
    //   84: getfield FWm : I
    //   87: i2d
    //   88: invokevirtual Dne : (DDD)D
    //   91: ldc2_w 4.0
    //   94: dcmpg
    //   95: ifge -> 100
    //   98: iconst_0
    //   99: ireturn
    //   100: aload_0
    //   101: getfield Dne : LkSJ;
    //   104: getfield Dne : LQnq;
    //   107: getfield Dne : LPrX;
    //   110: aload_0
    //   111: getfield Dne : LkSJ;
    //   114: getfield div : D
    //   117: invokestatic FWm : (D)I
    //   120: aload_0
    //   121: getfield Dne : LkSJ;
    //   124: getfield IjH : D
    //   127: invokestatic FWm : (D)I
    //   130: aload_0
    //   131: getfield Dne : LkSJ;
    //   134: getfield mrb : D
    //   137: invokestatic FWm : (D)I
    //   140: bipush #14
    //   142: invokevirtual Dne : (IIII)LuQr;
    //   145: astore_1
    //   146: aload_1
    //   147: ifnonnull -> 152
    //   150: iconst_0
    //   151: ireturn
    //   152: aload_0
    //   153: aload_1
    //   154: aload_0
    //   155: getfield Dne : LkSJ;
    //   158: getfield div : D
    //   161: invokestatic FWm : (D)I
    //   164: aload_0
    //   165: getfield Dne : LkSJ;
    //   168: getfield IjH : D
    //   171: invokestatic FWm : (D)I
    //   174: aload_0
    //   175: getfield Dne : LkSJ;
    //   178: getfield mrb : D
    //   181: invokestatic FWm : (D)I
    //   184: invokevirtual FWm : (III)LyQQ;
    //   187: putfield Dne : LyQQ;
    //   190: aload_0
    //   191: getfield Dne : LyQQ;
    //   194: ifnull -> 201
    //   197: iconst_1
    //   198: goto -> 202
    //   201: iconst_0
    //   202: ireturn
    //   203: iconst_0
    //   204: ireturn
  }
  
  public gNt(kSJ paramkSJ) {
    this.Dne = (yQQ)paramkSJ;
    Dne(1);
  }
  
  public boolean FWm() {
    return !this.Dne.Dne().bzF();
  }
  
  public void FWm() {
    this.Dne = this.Dne.Dne();
    this.FWm = this.Dne.bzF();
    this.Dne = null;
  }
  
  public void Dne() {
    // Byte code:
    //   0: aload_0
    //   1: iconst_m1
    //   2: putfield Dne : I
    //   5: aload_0
    //   6: getfield Dne : LkSJ;
    //   9: aload_0
    //   10: getfield Dne : LyQQ;
    //   13: invokevirtual Dne : ()I
    //   16: i2d
    //   17: aload_0
    //   18: getfield Dne : LyQQ;
    //   21: getfield FWm : I
    //   24: i2d
    //   25: aload_0
    //   26: getfield Dne : LyQQ;
    //   29: invokevirtual bzF : ()I
    //   32: i2d
    //   33: invokevirtual Dne : (DDD)D
    //   36: ldc2_w 256.0
    //   39: dcmpl
    //   40: ifle -> 131
    //   43: aload_0
    //   44: getfield Dne : LkSJ;
    //   47: bipush #14
    //   49: iconst_3
    //   50: aload_0
    //   51: getfield Dne : LkSJ;
    //   54: getfield Dne : LQnq;
    //   57: invokevirtual Dne : ()LziS;
    //   60: aload_0
    //   61: getfield Dne : LyQQ;
    //   64: invokevirtual Dne : ()I
    //   67: i2d
    //   68: ldc2_w 0.5
    //   71: dadd
    //   72: aload_0
    //   73: getfield Dne : LyQQ;
    //   76: invokevirtual FWm : ()I
    //   79: i2d
    //   80: aload_0
    //   81: getfield Dne : LyQQ;
    //   84: invokevirtual bzF : ()I
    //   87: i2d
    //   88: ldc2_w 0.5
    //   91: dadd
    //   92: invokevirtual Dne : (DDD)LchN;
    //   95: invokestatic Dne : (LkSJ;IILchN;)LchN;
    //   98: astore_1
    //   99: aload_1
    //   100: ifnull -> 128
    //   103: aload_0
    //   104: getfield Dne : LkSJ;
    //   107: invokevirtual Dne : ()LKFZ;
    //   110: aload_1
    //   111: getfield Dne : D
    //   114: aload_1
    //   115: getfield FWm : D
    //   118: aload_1
    //   119: getfield bzF : D
    //   122: ldc 0.3
    //   124: invokevirtual Dne : (DDDF)Z
    //   127: pop
    //   128: goto -> 176
    //   131: aload_0
    //   132: getfield Dne : LkSJ;
    //   135: invokevirtual Dne : ()LKFZ;
    //   138: aload_0
    //   139: getfield Dne : LyQQ;
    //   142: invokevirtual Dne : ()I
    //   145: i2d
    //   146: ldc2_w 0.5
    //   149: dadd
    //   150: aload_0
    //   151: getfield Dne : LyQQ;
    //   154: invokevirtual FWm : ()I
    //   157: i2d
    //   158: aload_0
    //   159: getfield Dne : LyQQ;
    //   162: invokevirtual bzF : ()I
    //   165: i2d
    //   166: ldc2_w 0.5
    //   169: dadd
    //   170: ldc 0.3
    //   172: invokevirtual Dne : (DDDF)Z
    //   175: pop
    //   176: return
  }
}


/* Location:              C:\Users\fract\Downloads\ERROR422.jar!\gNt.class
 * Java compiler version: 8 (52.0)
 * JD-Core Version:       1.1.3
 */