import java.util.ArrayList;
import java.util.HashMap;
import java.util.List;
import java.util.Map;
import java.util.Random;

public abstract class Gor {
  public boolean zGp = false;
  
  public List Dne;
  
  private Map Dne;
  
  public int bzF;
  
  public boolean DyG = true;
  
  public float Dne = new ArrayList();
  
  public int Qnq;
  
  public EZg Dne(String paramString) {
    // Byte code:
    //   0: aload_0
    //   1: getfield Dne : Ljava/util/Map;
    //   4: aload_1
    //   5: invokeinterface get : (Ljava/lang/Object;)Ljava/lang/Object;
    //   10: checkcast EZg
    //   13: areturn
  }
  
  public void Dne(float paramFloat1, float paramFloat2, float paramFloat3, float paramFloat4, float paramFloat5, float paramFloat6, sMa paramsMa) {}
  
  public Gor() {
    this.Dne = new HashMap<>();
    this.bzF = 64;
    this.Qnq = 32;
  }
  
  protected void Dne(String paramString, int paramInt1, int paramInt2) {
    // Byte code:
    //   0: aload_0
    //   1: getfield Dne : Ljava/util/Map;
    //   4: aload_1
    //   5: new EZg
    //   8: dup
    //   9: iload_2
    //   10: iload_3
    //   11: invokespecial <init> : (II)V
    //   14: invokeinterface put : (Ljava/lang/Object;Ljava/lang/Object;)Ljava/lang/Object;
    //   19: pop
    //   20: return
  }
  
  public void Dne(sMa paramsMa, float paramFloat1, float paramFloat2, float paramFloat3, float paramFloat4, float paramFloat5, float paramFloat6) {}
  
  public void Dne(FUH paramFUH, float paramFloat1, float paramFloat2, float paramFloat3) {}
  
  public rxL Dne(Random paramRandom) {
    // Byte code:
    //   0: aload_0
    //   1: getfield Dne : Ljava/util/List;
    //   4: aload_1
    //   5: aload_0
    //   6: getfield Dne : Ljava/util/List;
    //   9: invokeinterface size : ()I
    //   14: invokevirtual nextInt : (I)I
    //   17: invokeinterface get : (I)Ljava/lang/Object;
    //   22: checkcast rxL
    //   25: areturn
  }
}


/* Location:              C:\Users\fract\Downloads\ERROR422.jar!\Gor.class
 * Java compiler version: 8 (52.0)
 * JD-Core Version:       1.1.3
 */