public class gwo extends CAZ {
  public void Dne(WAR paramWAR, float paramFloat1, float paramFloat2, float paramFloat3, float paramFloat4, float paramFloat5, float paramFloat6) {
    // Byte code:
    //   0: aload_0
    //   1: getfield Dne : I
    //   4: i2f
    //   5: aload_0
    //   6: getfield FWm : F
    //   9: ldc 4.0
    //   11: fdiv
    //   12: fadd
    //   13: ldc 16.0
    //   15: fdiv
    //   16: fstore #8
    //   18: fload #8
    //   20: ldc 0.015609375
    //   22: fadd
    //   23: fstore #9
    //   25: aload_0
    //   26: getfield FWm : I
    //   29: i2f
    //   30: aload_0
    //   31: getfield bzF : F
    //   34: ldc 4.0
    //   36: fdiv
    //   37: fadd
    //   38: ldc 16.0
    //   40: fdiv
    //   41: fstore #10
    //   43: fload #10
    //   45: ldc 0.015609375
    //   47: fadd
    //   48: fstore #11
    //   50: ldc 0.1
    //   52: aload_0
    //   53: getfield Qnq : F
    //   56: fmul
    //   57: fstore #12
    //   59: aload_0
    //   60: getfield Dne : LgDn;
    //   63: ifnull -> 158
    //   66: aload_0
    //   67: getfield Dne : LgDn;
    //   70: aload_0
    //   71: getfield FWm : F
    //   74: ldc 4.0
    //   76: fdiv
    //   77: ldc 16.0
    //   79: fmul
    //   80: f2d
    //   81: invokeinterface Dne : (D)F
    //   86: fstore #8
    //   88: aload_0
    //   89: getfield Dne : LgDn;
    //   92: aload_0
    //   93: getfield FWm : F
    //   96: fconst_1
    //   97: fadd
    //   98: ldc 4.0
    //   100: fdiv
    //   101: ldc 16.0
    //   103: fmul
    //   104: f2d
    //   105: invokeinterface Dne : (D)F
    //   110: fstore #9
    //   112: aload_0
    //   113: getfield Dne : LgDn;
    //   116: aload_0
    //   117: getfield bzF : F
    //   120: ldc 4.0
    //   122: fdiv
    //   123: ldc 16.0
    //   125: fmul
    //   126: f2d
    //   127: invokeinterface FWm : (D)F
    //   132: fstore #10
    //   134: aload_0
    //   135: getfield Dne : LgDn;
    //   138: aload_0
    //   139: getfield bzF : F
    //   142: fconst_1
    //   143: fadd
    //   144: ldc 4.0
    //   146: fdiv
    //   147: ldc 16.0
    //   149: fmul
    //   150: f2d
    //   151: invokeinterface FWm : (D)F
    //   156: fstore #11
    //   158: aload_0
    //   159: getfield aFZ : D
    //   162: aload_0
    //   163: getfield div : D
    //   166: aload_0
    //   167: getfield aFZ : D
    //   170: dsub
    //   171: fload_2
    //   172: f2d
    //   173: dmul
    //   174: dadd
    //   175: getstatic gwo.Dne : D
    //   178: dsub
    //   179: d2f
    //   180: fstore #13
    //   182: aload_0
    //   183: getfield zGp : D
    //   186: aload_0
    //   187: getfield IjH : D
    //   190: aload_0
    //   191: getfield zGp : D
    //   194: dsub
    //   195: fload_2
    //   196: f2d
    //   197: dmul
    //   198: dadd
    //   199: getstatic gwo.FWm : D
    //   202: dsub
    //   203: d2f
    //   204: fstore #14
    //   206: aload_0
    //   207: getfield DyG : D
    //   210: aload_0
    //   211: getfield mrb : D
    //   214: aload_0
    //   215: getfield DyG : D
    //   218: dsub
    //   219: fload_2
    //   220: f2d
    //   221: dmul
    //   222: dadd
    //   223: getstatic gwo.bzF : D
    //   226: dsub
    //   227: d2f
    //   228: fstore #15
    //   230: fconst_1
    //   231: fstore #16
    //   233: aload_1
    //   234: fload #16
    //   236: aload_0
    //   237: getfield zGp : F
    //   240: fmul
    //   241: fload #16
    //   243: aload_0
    //   244: getfield DyG : F
    //   247: fmul
    //   248: fload #16
    //   250: aload_0
    //   251: getfield div : F
    //   254: fmul
    //   255: invokevirtual Dne : (FFF)V
    //   258: aload_1
    //   259: fload #13
    //   261: fload_3
    //   262: fload #12
    //   264: fmul
    //   265: fsub
    //   266: fload #6
    //   268: fload #12
    //   270: fmul
    //   271: fsub
    //   272: f2d
    //   273: fload #14
    //   275: fload #4
    //   277: fload #12
    //   279: fmul
    //   280: fsub
    //   281: f2d
    //   282: fload #15
    //   284: fload #5
    //   286: fload #12
    //   288: fmul
    //   289: fsub
    //   290: fload #7
    //   292: fload #12
    //   294: fmul
    //   295: fsub
    //   296: f2d
    //   297: fload #8
    //   299: f2d
    //   300: fload #11
    //   302: f2d
    //   303: invokevirtual Dne : (DDDDD)V
    //   306: aload_1
    //   307: fload #13
    //   309: fload_3
    //   310: fload #12
    //   312: fmul
    //   313: fsub
    //   314: fload #6
    //   316: fload #12
    //   318: fmul
    //   319: fadd
    //   320: f2d
    //   321: fload #14
    //   323: fload #4
    //   325: fload #12
    //   327: fmul
    //   328: fadd
    //   329: f2d
    //   330: fload #15
    //   332: fload #5
    //   334: fload #12
    //   336: fmul
    //   337: fsub
    //   338: fload #7
    //   340: fload #12
    //   342: fmul
    //   343: fadd
    //   344: f2d
    //   345: fload #8
    //   347: f2d
    //   348: fload #10
    //   350: f2d
    //   351: invokevirtual Dne : (DDDDD)V
    //   354: aload_1
    //   355: fload #13
    //   357: fload_3
    //   358: fload #12
    //   360: fmul
    //   361: fadd
    //   362: fload #6
    //   364: fload #12
    //   366: fmul
    //   367: fadd
    //   368: f2d
    //   369: fload #14
    //   371: fload #4
    //   373: fload #12
    //   375: fmul
    //   376: fadd
    //   377: f2d
    //   378: fload #15
    //   380: fload #5
    //   382: fload #12
    //   384: fmul
    //   385: fadd
    //   386: fload #7
    //   388: fload #12
    //   390: fmul
    //   391: fadd
    //   392: f2d
    //   393: fload #9
    //   395: f2d
    //   396: fload #10
    //   398: f2d
    //   399: invokevirtual Dne : (DDDDD)V
    //   402: aload_1
    //   403: fload #13
    //   405: fload_3
    //   406: fload #12
    //   408: fmul
    //   409: fadd
    //   410: fload #6
    //   412: fload #12
    //   414: fmul
    //   415: fsub
    //   416: f2d
    //   417: fload #14
    //   419: fload #4
    //   421: fload #12
    //   423: fmul
    //   424: fsub
    //   425: f2d
    //   426: fload #15
    //   428: fload #5
    //   430: fload #12
    //   432: fmul
    //   433: fadd
    //   434: fload #7
    //   436: fload #12
    //   438: fmul
    //   439: fsub
    //   440: f2d
    //   441: fload #9
    //   443: f2d
    //   444: fload #11
    //   446: f2d
    //   447: invokevirtual Dne : (DDDDD)V
    //   450: return
  }
  
  public gwo(Qnq paramQnq, double paramDouble1, double paramDouble2, double paramDouble3, dEr paramdEr, Snh paramSnh) {
    super(paramQnq, paramDouble1, paramDouble2, paramDouble3, 0.0D, 0.0D, 0.0D);
    Dne(paramSnh, paramdEr.Dne(0));
    this.zGp = this.DyG = this.div = 1.0F;
    this.aFZ = zKP.Jik.bzF;
    this.Qnq /= 2.0F;
  }
  
  public int Dne() {
    return 2;
  }
  
  public gwo(Qnq paramQnq, double paramDouble1, double paramDouble2, double paramDouble3, double paramDouble4, double paramDouble5, double paramDouble6, dEr paramdEr, Snh paramSnh) {
    this(paramQnq, paramDouble1, paramDouble2, paramDouble3, paramdEr, paramSnh);
    this.XHL *= 0.10000000149011612D;
    this.Zpi *= 0.10000000149011612D;
    this.kGO *= 0.10000000149011612D;
    this.XHL += paramDouble4;
    this.Zpi += paramDouble5;
    this.kGO += paramDouble6;
  }
  
  static {
  
  }
}


/* Location:              C:\Users\fract\Downloads\ERROR422.jar!\gwo.class
 * Java compiler version: 8 (52.0)
 * JD-Core Version:       1.1.3
 */