public class Hhj extends VHz {
  public Hhj(Qnq paramQnq, double paramDouble1, double paramDouble2, double paramDouble3) {
    super(paramQnq, paramDouble1, paramDouble2, paramDouble3);
  }
  
  static {
  
  }
  
  public Hhj(Qnq paramQnq, FUH paramFUH) {
    super(paramQnq, paramFUH);
  }
  
  public Hhj(Qnq paramQnq) {
    super(paramQnq);
  }
  
  protected void Dne(wHH paramwHH) {
    // Byte code:
    //   0: aload_1
    //   1: getfield Dne : LsMa;
    //   4: ifnull -> 24
    //   7: aload_1
    //   8: getfield Dne : LsMa;
    //   11: aload_0
    //   12: aload_0
    //   13: invokevirtual Dne : ()LFUH;
    //   16: invokestatic Dne : (LsMa;LsMa;)LzBn;
    //   19: iconst_0
    //   20: invokevirtual Dne : (LzBn;I)Z
    //   23: pop
    //   24: iconst_0
    //   25: istore_2
    //   26: iload_2
    //   27: bipush #32
    //   29: if_icmpge -> 86
    //   32: aload_0
    //   33: getfield Dne : LQnq;
    //   36: ldc 'portal'
    //   38: aload_0
    //   39: getfield div : D
    //   42: aload_0
    //   43: getfield IjH : D
    //   46: aload_0
    //   47: getfield Dne : Ljava/util/Random;
    //   50: invokevirtual nextDouble : ()D
    //   53: ldc2_w 2.0
    //   56: dmul
    //   57: dadd
    //   58: aload_0
    //   59: getfield mrb : D
    //   62: aload_0
    //   63: getfield Dne : Ljava/util/Random;
    //   66: invokevirtual nextGaussian : ()D
    //   69: dconst_0
    //   70: aload_0
    //   71: getfield Dne : Ljava/util/Random;
    //   74: invokevirtual nextGaussian : ()D
    //   77: invokevirtual Dne : (Ljava/lang/String;DDDDDD)V
    //   80: iinc #2, 1
    //   83: goto -> 26
    //   86: aload_0
    //   87: getfield Dne : LQnq;
    //   90: getfield aFZ : Z
    //   93: ifne -> 185
    //   96: aload_0
    //   97: invokevirtual Dne : ()LFUH;
    //   100: ifnull -> 181
    //   103: aload_0
    //   104: invokevirtual Dne : ()LFUH;
    //   107: instanceof PJQ
    //   110: ifeq -> 181
    //   113: aload_0
    //   114: invokevirtual Dne : ()LFUH;
    //   117: checkcast PJQ
    //   120: astore_2
    //   121: aload_2
    //   122: getfield Dne : LTnv;
    //   125: getfield Dne : Z
    //   128: ifne -> 181
    //   131: aload_2
    //   132: getfield Dne : LQnq;
    //   135: aload_0
    //   136: getfield Dne : LQnq;
    //   139: if_acmpne -> 181
    //   142: aload_0
    //   143: invokevirtual Dne : ()LFUH;
    //   146: aload_0
    //   147: getfield div : D
    //   150: aload_0
    //   151: getfield IjH : D
    //   154: aload_0
    //   155: getfield mrb : D
    //   158: invokevirtual FWm : (DDD)V
    //   161: aload_0
    //   162: invokevirtual Dne : ()LFUH;
    //   165: fconst_0
    //   166: putfield ceE : F
    //   169: aload_0
    //   170: invokevirtual Dne : ()LFUH;
    //   173: getstatic zBn.div : LzBn;
    //   176: iconst_5
    //   177: invokevirtual Dne : (LzBn;I)Z
    //   180: pop
    //   181: aload_0
    //   182: invokevirtual g_ : ()V
    //   185: return
  }
}


/* Location:              C:\Users\fract\Downloads\ERROR422.jar!\Hhj.class
 * Java compiler version: 8 (52.0)
 * JD-Core Version:       1.1.3
 */