import java.util.Random;

public class HhP extends Pdb {
  private Qnq Dne;
  
  public MqS Dne;
  
  private Random Dne;
  
  private int FWm;
  
  public int[] Dne;
  
  private int bzF;
  
  public long Dne = new NPS(this, "Enchant", true, 1);
  
  private int Qnq;
  
  public NMq Dne(FiG paramFiG, int paramInt) {
    // Byte code:
    //   0: aconst_null
    //   1: astore_3
    //   2: aload_0
    //   3: getfield bzF : Ljava/util/List;
    //   6: iload_2
    //   7: invokeinterface get : (I)Ljava/lang/Object;
    //   12: checkcast onZ
    //   15: astore #4
    //   17: aload #4
    //   19: ifnull -> 252
    //   22: aload #4
    //   24: invokevirtual Dne : ()Z
    //   27: ifeq -> 252
    //   30: aload #4
    //   32: invokevirtual Dne : ()LNMq;
    //   35: astore #5
    //   37: aload #5
    //   39: invokevirtual Dne : ()LNMq;
    //   42: astore_3
    //   43: iload_2
    //   44: ifne -> 62
    //   47: aload_0
    //   48: aload #5
    //   50: iconst_1
    //   51: bipush #37
    //   53: iconst_1
    //   54: invokevirtual Dne : (LNMq;IIZ)Z
    //   57: ifne -> 205
    //   60: aconst_null
    //   61: areturn
    //   62: aload_0
    //   63: getfield bzF : Ljava/util/List;
    //   66: iconst_0
    //   67: invokeinterface get : (I)Ljava/lang/Object;
    //   72: checkcast onZ
    //   75: invokevirtual Dne : ()Z
    //   78: ifne -> 102
    //   81: aload_0
    //   82: getfield bzF : Ljava/util/List;
    //   85: iconst_0
    //   86: invokeinterface get : (I)Ljava/lang/Object;
    //   91: checkcast onZ
    //   94: aload #5
    //   96: invokevirtual Dne : (LNMq;)Z
    //   99: ifne -> 104
    //   102: aconst_null
    //   103: areturn
    //   104: aload #5
    //   106: invokevirtual aFZ : ()Z
    //   109: ifeq -> 151
    //   112: aload #5
    //   114: getfield Dne : I
    //   117: iconst_1
    //   118: if_icmpne -> 151
    //   121: aload_0
    //   122: getfield bzF : Ljava/util/List;
    //   125: iconst_0
    //   126: invokeinterface get : (I)Ljava/lang/Object;
    //   131: checkcast onZ
    //   134: aload #5
    //   136: invokevirtual Dne : ()LNMq;
    //   139: invokevirtual Dne : (LNMq;)V
    //   142: aload #5
    //   144: iconst_0
    //   145: putfield Dne : I
    //   148: goto -> 205
    //   151: aload #5
    //   153: getfield Dne : I
    //   156: iconst_1
    //   157: if_icmplt -> 205
    //   160: aload_0
    //   161: getfield bzF : Ljava/util/List;
    //   164: iconst_0
    //   165: invokeinterface get : (I)Ljava/lang/Object;
    //   170: checkcast onZ
    //   173: new NMq
    //   176: dup
    //   177: aload #5
    //   179: getfield bzF : I
    //   182: iconst_1
    //   183: aload #5
    //   185: invokevirtual Qnq : ()I
    //   188: invokespecial <init> : (III)V
    //   191: invokevirtual Dne : (LNMq;)V
    //   194: aload #5
    //   196: dup
    //   197: getfield Dne : I
    //   200: iconst_1
    //   201: isub
    //   202: putfield Dne : I
    //   205: aload #5
    //   207: getfield Dne : I
    //   210: ifne -> 225
    //   213: aload #4
    //   215: aconst_null
    //   216: checkcast NMq
    //   219: invokevirtual Dne : (LNMq;)V
    //   222: goto -> 230
    //   225: aload #4
    //   227: invokevirtual Dne : ()V
    //   230: aload #5
    //   232: getfield Dne : I
    //   235: aload_3
    //   236: getfield Dne : I
    //   239: if_icmpne -> 244
    //   242: aconst_null
    //   243: areturn
    //   244: aload #4
    //   246: aload_1
    //   247: aload #5
    //   249: invokevirtual Dne : (LFiG;LNMq;)V
    //   252: aload_3
    //   253: areturn
  }
  
  public boolean Dne(FiG paramFiG, int paramInt) {
    // Byte code:
    //   0: aload_0
    //   1: getfield Dne : LMqS;
    //   4: iconst_0
    //   5: invokeinterface Dne : (I)LNMq;
    //   10: astore_3
    //   11: aload_0
    //   12: getfield Dne : [I
    //   15: iload_2
    //   16: iaload
    //   17: ifle -> 237
    //   20: aload_3
    //   21: ifnull -> 237
    //   24: aload_1
    //   25: getfield eHV : I
    //   28: aload_0
    //   29: getfield Dne : [I
    //   32: iload_2
    //   33: iaload
    //   34: if_icmpge -> 47
    //   37: aload_1
    //   38: getfield Dne : Luqg;
    //   41: getfield Qnq : Z
    //   44: ifeq -> 237
    //   47: aload_0
    //   48: getfield Dne : LQnq;
    //   51: getfield aFZ : Z
    //   54: ifne -> 235
    //   57: aload_0
    //   58: getfield Dne : Ljava/util/Random;
    //   61: aload_3
    //   62: aload_0
    //   63: getfield Dne : [I
    //   66: iload_2
    //   67: iaload
    //   68: invokestatic Dne : (Ljava/util/Random;LNMq;I)Ljava/util/List;
    //   71: astore #4
    //   73: aload_3
    //   74: getfield bzF : I
    //   77: getstatic dEr.TKg : LdEr;
    //   80: getfield Qnq : I
    //   83: if_icmpne -> 90
    //   86: iconst_1
    //   87: goto -> 91
    //   90: iconst_0
    //   91: istore #5
    //   93: aload #4
    //   95: ifnull -> 235
    //   98: aload_1
    //   99: aload_0
    //   100: getfield Dne : [I
    //   103: iload_2
    //   104: iaload
    //   105: ineg
    //   106: invokevirtual FWm : (I)V
    //   109: iload #5
    //   111: ifeq -> 124
    //   114: aload_3
    //   115: getstatic dEr.Dne : LdpS;
    //   118: getfield Qnq : I
    //   121: putfield bzF : I
    //   124: iload #5
    //   126: ifeq -> 146
    //   129: aload_0
    //   130: getfield Dne : Ljava/util/Random;
    //   133: aload #4
    //   135: invokeinterface size : ()I
    //   140: invokevirtual nextInt : (I)I
    //   143: goto -> 147
    //   146: iconst_m1
    //   147: istore #6
    //   149: iconst_0
    //   150: istore #7
    //   152: iload #7
    //   154: aload #4
    //   156: invokeinterface size : ()I
    //   161: if_icmpge -> 227
    //   164: aload #4
    //   166: iload #7
    //   168: invokeinterface get : (I)Ljava/lang/Object;
    //   173: checkcast RmG
    //   176: astore #8
    //   178: iload #5
    //   180: ifeq -> 190
    //   183: iload #7
    //   185: iload #6
    //   187: if_icmpne -> 221
    //   190: iload #5
    //   192: ifeq -> 207
    //   195: getstatic dEr.Dne : LdpS;
    //   198: aload_3
    //   199: aload #8
    //   201: invokevirtual Dne : (LNMq;LRmG;)V
    //   204: goto -> 221
    //   207: aload_3
    //   208: aload #8
    //   210: getfield Dne : Lycv;
    //   213: aload #8
    //   215: getfield Dne : I
    //   218: invokevirtual Dne : (Lycv;I)V
    //   221: iinc #7, 1
    //   224: goto -> 152
    //   227: aload_0
    //   228: aload_0
    //   229: getfield Dne : LMqS;
    //   232: invokevirtual Dne : (LMqS;)V
    //   235: iconst_1
    //   236: ireturn
    //   237: iconst_0
    //   238: ireturn
  }
  
  public boolean Dne(FiG paramFiG) {
    // Byte code:
    //   0: aload_0
    //   1: getfield Dne : LQnq;
    //   4: aload_0
    //   5: getfield FWm : I
    //   8: aload_0
    //   9: getfield bzF : I
    //   12: aload_0
    //   13: getfield Qnq : I
    //   16: invokevirtual Dne : (III)I
    //   19: getstatic zKP.KkE : LzKP;
    //   22: getfield FWm : I
    //   25: if_icmpeq -> 32
    //   28: iconst_0
    //   29: goto -> 75
    //   32: aload_1
    //   33: aload_0
    //   34: getfield FWm : I
    //   37: i2d
    //   38: ldc2_w 0.5
    //   41: dadd
    //   42: aload_0
    //   43: getfield bzF : I
    //   46: i2d
    //   47: ldc2_w 0.5
    //   50: dadd
    //   51: aload_0
    //   52: getfield Qnq : I
    //   55: i2d
    //   56: ldc2_w 0.5
    //   59: dadd
    //   60: invokevirtual Dne : (DDD)D
    //   63: ldc2_w 64.0
    //   66: dcmpg
    //   67: ifgt -> 74
    //   70: iconst_1
    //   71: goto -> 75
    //   74: iconst_0
    //   75: ireturn
  }
  
  public HhP(MOS paramMOS, Qnq paramQnq, int paramInt1, int paramInt2, int paramInt3) {
    this.Dne = new Random();
    this.Dne = new int[3];
    this.Dne = paramQnq;
    this.FWm = paramInt1;
    this.bzF = paramInt2;
    this.Qnq = paramInt3;
    Dne(new fKk(this, this.Dne, 0, 25, 47));
    byte b;
    for (b = 0; b < 3; b++) {
      for (byte b1 = 0; b1 < 9; b1++)
        Dne(new onZ(paramMOS, b1 + b * 9 + 9, 8 + b1 * 18, 84 + b * 18)); 
    } 
    for (b = 0; b < 9; b++)
      Dne(new onZ(paramMOS, b, 8 + b * 18, 142)); 
  }
  
  public void Dne(mXX parammXX) {
    super.Dne(parammXX);
    parammXX.Dne(this, 0, this.Dne[0]);
    parammXX.Dne(this, 1, this.Dne[1]);
    parammXX.Dne(this, 2, this.Dne[2]);
  }
  
  public void Dne() {
    // Byte code:
    //   0: aload_0
    //   1: invokespecial Dne : ()V
    //   4: iconst_0
    //   5: istore_1
    //   6: iload_1
    //   7: aload_0
    //   8: getfield Qnq : Ljava/util/List;
    //   11: invokeinterface size : ()I
    //   16: if_icmpge -> 81
    //   19: aload_0
    //   20: getfield Qnq : Ljava/util/List;
    //   23: iload_1
    //   24: invokeinterface get : (I)Ljava/lang/Object;
    //   29: checkcast mXX
    //   32: astore_2
    //   33: aload_2
    //   34: aload_0
    //   35: iconst_0
    //   36: aload_0
    //   37: getfield Dne : [I
    //   40: iconst_0
    //   41: iaload
    //   42: invokeinterface Dne : (LPdb;II)V
    //   47: aload_2
    //   48: aload_0
    //   49: iconst_1
    //   50: aload_0
    //   51: getfield Dne : [I
    //   54: iconst_1
    //   55: iaload
    //   56: invokeinterface Dne : (LPdb;II)V
    //   61: aload_2
    //   62: aload_0
    //   63: iconst_2
    //   64: aload_0
    //   65: getfield Dne : [I
    //   68: iconst_2
    //   69: iaload
    //   70: invokeinterface Dne : (LPdb;II)V
    //   75: iinc #1, 1
    //   78: goto -> 6
    //   81: return
  }
  
  public void Dne(FiG paramFiG) {
    // Byte code:
    //   0: aload_0
    //   1: aload_1
    //   2: invokespecial Dne : (LFiG;)V
    //   5: aload_0
    //   6: getfield Dne : LQnq;
    //   9: getfield aFZ : Z
    //   12: ifne -> 36
    //   15: aload_0
    //   16: getfield Dne : LMqS;
    //   19: iconst_0
    //   20: invokeinterface FWm : (I)LNMq;
    //   25: astore_2
    //   26: aload_2
    //   27: ifnull -> 36
    //   30: aload_1
    //   31: aload_2
    //   32: invokevirtual Dne : (LNMq;)LJiM;
    //   35: pop
    //   36: return
  }
  
  public void Dne(MqS paramMqS) {
    // Byte code:
    //   0: aload_1
    //   1: aload_0
    //   2: getfield Dne : LMqS;
    //   5: if_acmpne -> 462
    //   8: aload_1
    //   9: iconst_0
    //   10: invokeinterface Dne : (I)LNMq;
    //   15: astore_2
    //   16: aload_2
    //   17: ifnull -> 442
    //   20: aload_2
    //   21: invokevirtual div : ()Z
    //   24: ifeq -> 442
    //   27: aload_0
    //   28: aload_0
    //   29: getfield Dne : Ljava/util/Random;
    //   32: invokevirtual nextLong : ()J
    //   35: putfield Dne : J
    //   38: aload_0
    //   39: getfield Dne : LQnq;
    //   42: getfield aFZ : Z
    //   45: ifne -> 462
    //   48: iconst_0
    //   49: istore_3
    //   50: iconst_m1
    //   51: istore #4
    //   53: iload #4
    //   55: iconst_1
    //   56: if_icmpgt -> 402
    //   59: iconst_m1
    //   60: istore #5
    //   62: iload #5
    //   64: iconst_1
    //   65: if_icmpgt -> 396
    //   68: iload #4
    //   70: ifne -> 78
    //   73: iload #5
    //   75: ifeq -> 390
    //   78: aload_0
    //   79: getfield Dne : LQnq;
    //   82: aload_0
    //   83: getfield FWm : I
    //   86: iload #5
    //   88: iadd
    //   89: aload_0
    //   90: getfield bzF : I
    //   93: aload_0
    //   94: getfield Qnq : I
    //   97: iload #4
    //   99: iadd
    //   100: invokevirtual Dne : (III)Z
    //   103: ifeq -> 390
    //   106: aload_0
    //   107: getfield Dne : LQnq;
    //   110: aload_0
    //   111: getfield FWm : I
    //   114: iload #5
    //   116: iadd
    //   117: aload_0
    //   118: getfield bzF : I
    //   121: iconst_1
    //   122: iadd
    //   123: aload_0
    //   124: getfield Qnq : I
    //   127: iload #4
    //   129: iadd
    //   130: invokevirtual Dne : (III)Z
    //   133: ifeq -> 390
    //   136: aload_0
    //   137: getfield Dne : LQnq;
    //   140: aload_0
    //   141: getfield FWm : I
    //   144: iload #5
    //   146: iconst_2
    //   147: imul
    //   148: iadd
    //   149: aload_0
    //   150: getfield bzF : I
    //   153: aload_0
    //   154: getfield Qnq : I
    //   157: iload #4
    //   159: iconst_2
    //   160: imul
    //   161: iadd
    //   162: invokevirtual Dne : (III)I
    //   165: getstatic zKP.AgF : LzKP;
    //   168: getfield FWm : I
    //   171: if_icmpne -> 177
    //   174: iinc #3, 1
    //   177: aload_0
    //   178: getfield Dne : LQnq;
    //   181: aload_0
    //   182: getfield FWm : I
    //   185: iload #5
    //   187: iconst_2
    //   188: imul
    //   189: iadd
    //   190: aload_0
    //   191: getfield bzF : I
    //   194: iconst_1
    //   195: iadd
    //   196: aload_0
    //   197: getfield Qnq : I
    //   200: iload #4
    //   202: iconst_2
    //   203: imul
    //   204: iadd
    //   205: invokevirtual Dne : (III)I
    //   208: getstatic zKP.AgF : LzKP;
    //   211: getfield FWm : I
    //   214: if_icmpne -> 220
    //   217: iinc #3, 1
    //   220: iload #5
    //   222: ifeq -> 390
    //   225: iload #4
    //   227: ifeq -> 390
    //   230: aload_0
    //   231: getfield Dne : LQnq;
    //   234: aload_0
    //   235: getfield FWm : I
    //   238: iload #5
    //   240: iconst_2
    //   241: imul
    //   242: iadd
    //   243: aload_0
    //   244: getfield bzF : I
    //   247: aload_0
    //   248: getfield Qnq : I
    //   251: iload #4
    //   253: iadd
    //   254: invokevirtual Dne : (III)I
    //   257: getstatic zKP.AgF : LzKP;
    //   260: getfield FWm : I
    //   263: if_icmpne -> 269
    //   266: iinc #3, 1
    //   269: aload_0
    //   270: getfield Dne : LQnq;
    //   273: aload_0
    //   274: getfield FWm : I
    //   277: iload #5
    //   279: iconst_2
    //   280: imul
    //   281: iadd
    //   282: aload_0
    //   283: getfield bzF : I
    //   286: iconst_1
    //   287: iadd
    //   288: aload_0
    //   289: getfield Qnq : I
    //   292: iload #4
    //   294: iadd
    //   295: invokevirtual Dne : (III)I
    //   298: getstatic zKP.AgF : LzKP;
    //   301: getfield FWm : I
    //   304: if_icmpne -> 310
    //   307: iinc #3, 1
    //   310: aload_0
    //   311: getfield Dne : LQnq;
    //   314: aload_0
    //   315: getfield FWm : I
    //   318: iload #5
    //   320: iadd
    //   321: aload_0
    //   322: getfield bzF : I
    //   325: aload_0
    //   326: getfield Qnq : I
    //   329: iload #4
    //   331: iconst_2
    //   332: imul
    //   333: iadd
    //   334: invokevirtual Dne : (III)I
    //   337: getstatic zKP.AgF : LzKP;
    //   340: getfield FWm : I
    //   343: if_icmpne -> 349
    //   346: iinc #3, 1
    //   349: aload_0
    //   350: getfield Dne : LQnq;
    //   353: aload_0
    //   354: getfield FWm : I
    //   357: iload #5
    //   359: iadd
    //   360: aload_0
    //   361: getfield bzF : I
    //   364: iconst_1
    //   365: iadd
    //   366: aload_0
    //   367: getfield Qnq : I
    //   370: iload #4
    //   372: iconst_2
    //   373: imul
    //   374: iadd
    //   375: invokevirtual Dne : (III)I
    //   378: getstatic zKP.AgF : LzKP;
    //   381: getfield FWm : I
    //   384: if_icmpne -> 390
    //   387: iinc #3, 1
    //   390: iinc #5, 1
    //   393: goto -> 62
    //   396: iinc #4, 1
    //   399: goto -> 53
    //   402: iconst_0
    //   403: istore #4
    //   405: iload #4
    //   407: iconst_3
    //   408: if_icmpge -> 435
    //   411: aload_0
    //   412: getfield Dne : [I
    //   415: iload #4
    //   417: aload_0
    //   418: getfield Dne : Ljava/util/Random;
    //   421: iload #4
    //   423: iload_3
    //   424: aload_2
    //   425: invokestatic Dne : (Ljava/util/Random;IILNMq;)I
    //   428: iastore
    //   429: iinc #4, 1
    //   432: goto -> 405
    //   435: aload_0
    //   436: invokevirtual Dne : ()V
    //   439: goto -> 462
    //   442: iconst_0
    //   443: istore_3
    //   444: iload_3
    //   445: iconst_3
    //   446: if_icmpge -> 462
    //   449: aload_0
    //   450: getfield Dne : [I
    //   453: iload_3
    //   454: iconst_0
    //   455: iastore
    //   456: iinc #3, 1
    //   459: goto -> 444
    //   462: return
  }
  
  public void Dne(int paramInt1, int paramInt2) {
    // Byte code:
    //   0: iload_1
    //   1: iflt -> 19
    //   4: iload_1
    //   5: iconst_2
    //   6: if_icmpgt -> 19
    //   9: aload_0
    //   10: getfield Dne : [I
    //   13: iload_1
    //   14: iload_2
    //   15: iastore
    //   16: goto -> 25
    //   19: aload_0
    //   20: iload_1
    //   21: iload_2
    //   22: invokespecial Dne : (II)V
    //   25: return
  }
}


/* Location:              C:\Users\fract\Downloads\ERROR422.jar!\HhP.class
 * Java compiler version: 8 (52.0)
 * JD-Core Version:       1.1.3
 */