public class IBw extends cMv {
  private float Dne;
  
  private kSJ Dne;
  
  private double FWm;
  
  private double bzF;
  
  private double Dne;
  
  public void Dne() {
    // Byte code:
    //   0: aload_0
    //   1: getfield Dne : LkSJ;
    //   4: invokevirtual Dne : ()LKFZ;
    //   7: aload_0
    //   8: getfield Dne : D
    //   11: aload_0
    //   12: getfield FWm : D
    //   15: aload_0
    //   16: getfield bzF : D
    //   19: aload_0
    //   20: getfield Dne : F
    //   23: invokevirtual Dne : (DDDF)Z
    //   26: pop
    //   27: return
  }
  
  public boolean Dne() {
    // Byte code:
    //   0: aload_0
    //   1: getfield Dne : LkSJ;
    //   4: invokevirtual aFZ : ()I
    //   7: bipush #100
    //   9: if_icmplt -> 14
    //   12: iconst_0
    //   13: ireturn
    //   14: aload_0
    //   15: getfield Dne : LkSJ;
    //   18: invokevirtual Dne : ()Ljava/util/Random;
    //   21: bipush #120
    //   23: invokevirtual nextInt : (I)I
    //   26: ifeq -> 31
    //   29: iconst_0
    //   30: ireturn
    //   31: aload_0
    //   32: getfield Dne : LkSJ;
    //   35: bipush #10
    //   37: bipush #7
    //   39: invokestatic Dne : (LkSJ;II)LchN;
    //   42: astore_1
    //   43: aload_1
    //   44: ifnonnull -> 49
    //   47: iconst_0
    //   48: ireturn
    //   49: aload_0
    //   50: aload_1
    //   51: getfield Dne : D
    //   54: putfield Dne : D
    //   57: aload_0
    //   58: aload_1
    //   59: getfield FWm : D
    //   62: putfield FWm : D
    //   65: aload_0
    //   66: aload_1
    //   67: getfield bzF : D
    //   70: putfield bzF : D
    //   73: iconst_1
    //   74: ireturn
  }
  
  public boolean FWm() {
    // Byte code:
    //   0: aload_0
    //   1: getfield Dne : LkSJ;
    //   4: invokevirtual Dne : ()LKFZ;
    //   7: invokevirtual bzF : ()Z
    //   10: ifne -> 17
    //   13: iconst_1
    //   14: goto -> 18
    //   17: iconst_0
    //   18: ireturn
  }
  
  public IBw(kSJ paramkSJ, float paramFloat) {
    this.Dne = paramkSJ;
    this.Dne = paramFloat;
    Dne(1);
  }
}


/* Location:              C:\Users\fract\Downloads\ERROR422.jar!\IBw.class
 * Java compiler version: 8 (52.0)
 * JD-Core Version:       1.1.3
 */