public class iqS extends RNA {
  protected Sgm Qnq;
  
  protected Sgm zGp;
  
  protected Sgm DyG;
  
  private kGJ Dne;
  
  private Sgm div = this.Dne;
  
  protected Sgm aFZ;
  
  private int Dne = 1;
  
  protected void Dne(zxd paramzxd, float paramFloat1, float paramFloat2, float paramFloat3) {
    if (paramzxd.ZfC())
      paramFloat2 += (float)(Math.cos(paramzxd.zGp * 3.25D) * Math.PI * 0.25D); 
    super.Dne(paramzxd, paramFloat1, paramFloat2, paramFloat3);
  }
  
  protected void FWm(FUH paramFUH, float paramFloat) {
    Dne((zxd)paramFUH, paramFloat);
  }
  
  protected void Dne() {
    this.FWm = new fsj(1.0F, true);
    this.bzF = new fsj(0.5F, true);
    this.Qnq = this.FWm;
    this.aFZ = this.bzF;
    this.zGp = new kGJ(1.0F, 0.0F, true);
    this.DyG = new kGJ(0.5F, 0.0F, true);
  }
  
  protected int Dne(FUH paramFUH, int paramInt, float paramFloat) {
    return Dne((zxd)paramFUH, paramInt, paramFloat);
  }
  
  private void Dne(zxd paramzxd) {
    // Byte code:
    //   0: aload_1
    //   1: invokevirtual LVR : ()Z
    //   4: ifeq -> 99
    //   7: aload_0
    //   8: getfield Dne : I
    //   11: aload_0
    //   12: getfield Dne : LkGJ;
    //   15: invokevirtual Dne : ()I
    //   18: if_icmpeq -> 72
    //   21: aload_0
    //   22: new kGJ
    //   25: dup
    //   26: invokespecial <init> : ()V
    //   29: putfield Dne : LkGJ;
    //   32: aload_0
    //   33: aload_0
    //   34: getfield Dne : LkGJ;
    //   37: invokevirtual Dne : ()I
    //   40: putfield Dne : I
    //   43: aload_0
    //   44: new kGJ
    //   47: dup
    //   48: fconst_1
    //   49: fconst_0
    //   50: iconst_1
    //   51: invokespecial <init> : (FFZ)V
    //   54: putfield zGp : LSgm;
    //   57: aload_0
    //   58: new kGJ
    //   61: dup
    //   62: ldc 0.5
    //   64: fconst_0
    //   65: iconst_1
    //   66: invokespecial <init> : (FFZ)V
    //   69: putfield DyG : LSgm;
    //   72: aload_0
    //   73: aload_0
    //   74: getfield Dne : LkGJ;
    //   77: putfield Dne : LGor;
    //   80: aload_0
    //   81: aload_0
    //   82: getfield zGp : LSgm;
    //   85: putfield FWm : LSgm;
    //   88: aload_0
    //   89: aload_0
    //   90: getfield DyG : LSgm;
    //   93: putfield bzF : LSgm;
    //   96: goto -> 123
    //   99: aload_0
    //   100: aload_0
    //   101: getfield div : LSgm;
    //   104: putfield Dne : LGor;
    //   107: aload_0
    //   108: aload_0
    //   109: getfield Qnq : LSgm;
    //   112: putfield FWm : LSgm;
    //   115: aload_0
    //   116: aload_0
    //   117: getfield aFZ : LSgm;
    //   120: putfield bzF : LSgm;
    //   123: aload_0
    //   124: aload_0
    //   125: getfield Dne : LGor;
    //   128: checkcast Sgm
    //   131: putfield Dne : LSgm;
    //   134: return
  }
  
  public void Dne(zxd paramzxd, double paramDouble1, double paramDouble2, double paramDouble3, float paramFloat1, float paramFloat2) {
    Dne(paramzxd);
    super.Dne(paramzxd, paramDouble1, paramDouble2, paramDouble3, paramFloat1, paramFloat2);
  }
  
  protected void Dne(zxd paramzxd, float paramFloat) {
    Dne(paramzxd);
    super.FWm(paramzxd, paramFloat);
  }
  
  protected void Dne(FUH paramFUH, float paramFloat1, float paramFloat2, float paramFloat3) {
    Dne((zxd)paramFUH, paramFloat1, paramFloat2, paramFloat3);
  }
  
  public iqS() {
    super(new fsj(), 0.5F, 1.0F);
    this.Dne = new kGJ();
  }
  
  public void Dne(sMa paramsMa, double paramDouble1, double paramDouble2, double paramDouble3, float paramFloat1, float paramFloat2) {
    Dne((zxd)paramsMa, paramDouble1, paramDouble2, paramDouble3, paramFloat1, paramFloat2);
  }
  
  protected int Dne(zxd paramzxd, int paramInt, float paramFloat) {
    Dne(paramzxd);
    return super.Dne(paramzxd, paramInt, paramFloat);
  }
  
  public void Dne(FUH paramFUH, double paramDouble1, double paramDouble2, double paramDouble3, float paramFloat1, float paramFloat2) {
    Dne((zxd)paramFUH, paramDouble1, paramDouble2, paramDouble3, paramFloat1, paramFloat2);
  }
}


/* Location:              C:\Users\fract\Downloads\ERROR422.jar!\iqS.class
 * Java compiler version: 8 (52.0)
 * JD-Core Version:       1.1.3
 */