public class ITf extends cMv {
  private double Dne;
  
  private kSJ Dne;
  
  private double bzF;
  
  private double FWm;
  
  private Qnq Dne;
  
  private float Dne;
  
  public void Dne() {
    // Byte code:
    //   0: aload_0
    //   1: getfield Dne : LkSJ;
    //   4: invokevirtual Dne : ()LKFZ;
    //   7: aload_0
    //   8: getfield Dne : D
    //   11: aload_0
    //   12: getfield FWm : D
    //   15: aload_0
    //   16: getfield bzF : D
    //   19: aload_0
    //   20: getfield Dne : F
    //   23: invokevirtual Dne : (DDDF)Z
    //   26: pop
    //   27: return
  }
  
  public boolean FWm() {
    // Byte code:
    //   0: aload_0
    //   1: getfield Dne : LkSJ;
    //   4: invokevirtual Dne : ()LKFZ;
    //   7: invokevirtual bzF : ()Z
    //   10: ifne -> 17
    //   13: iconst_1
    //   14: goto -> 18
    //   17: iconst_0
    //   18: ireturn
  }
  
  public ITf(kSJ paramkSJ, float paramFloat) {
    this.Dne = paramkSJ;
    this.Dne = paramFloat;
    this.Dne = paramkSJ.Dne;
    Dne(1);
  }
  
  private chN Dne() {
    // Byte code:
    //   0: aload_0
    //   1: getfield Dne : LkSJ;
    //   4: invokevirtual Dne : ()Ljava/util/Random;
    //   7: astore_1
    //   8: iconst_0
    //   9: istore_2
    //   10: iload_2
    //   11: bipush #10
    //   13: if_icmpge -> 147
    //   16: aload_0
    //   17: getfield Dne : LkSJ;
    //   20: getfield div : D
    //   23: aload_1
    //   24: bipush #20
    //   26: invokevirtual nextInt : (I)I
    //   29: i2d
    //   30: dadd
    //   31: ldc2_w 10.0
    //   34: dsub
    //   35: invokestatic FWm : (D)I
    //   38: istore_3
    //   39: aload_0
    //   40: getfield Dne : LkSJ;
    //   43: getfield Dne : LbSp;
    //   46: getfield FWm : D
    //   49: aload_1
    //   50: bipush #6
    //   52: invokevirtual nextInt : (I)I
    //   55: i2d
    //   56: dadd
    //   57: ldc2_w 3.0
    //   60: dsub
    //   61: invokestatic FWm : (D)I
    //   64: istore #4
    //   66: aload_0
    //   67: getfield Dne : LkSJ;
    //   70: getfield mrb : D
    //   73: aload_1
    //   74: bipush #20
    //   76: invokevirtual nextInt : (I)I
    //   79: i2d
    //   80: dadd
    //   81: ldc2_w 10.0
    //   84: dsub
    //   85: invokestatic FWm : (D)I
    //   88: istore #5
    //   90: aload_0
    //   91: getfield Dne : LQnq;
    //   94: iload_3
    //   95: iload #4
    //   97: iload #5
    //   99: invokevirtual aFZ : (III)Z
    //   102: ifne -> 141
    //   105: aload_0
    //   106: getfield Dne : LkSJ;
    //   109: iload_3
    //   110: iload #4
    //   112: iload #5
    //   114: invokevirtual Dne : (III)F
    //   117: fconst_0
    //   118: fcmpg
    //   119: ifge -> 141
    //   122: aload_0
    //   123: getfield Dne : LQnq;
    //   126: invokevirtual Dne : ()LziS;
    //   129: iload_3
    //   130: i2d
    //   131: iload #4
    //   133: i2d
    //   134: iload #5
    //   136: i2d
    //   137: invokevirtual Dne : (DDD)LchN;
    //   140: areturn
    //   141: iinc #2, 1
    //   144: goto -> 10
    //   147: aconst_null
    //   148: areturn
  }
  
  public boolean Dne() {
    // Byte code:
    //   0: aload_0
    //   1: getfield Dne : LQnq;
    //   4: invokevirtual Dne : ()Z
    //   7: ifne -> 12
    //   10: iconst_0
    //   11: ireturn
    //   12: aload_0
    //   13: getfield Dne : LkSJ;
    //   16: invokevirtual trS : ()Z
    //   19: ifne -> 24
    //   22: iconst_0
    //   23: ireturn
    //   24: aload_0
    //   25: getfield Dne : LQnq;
    //   28: aload_0
    //   29: getfield Dne : LkSJ;
    //   32: getfield div : D
    //   35: invokestatic FWm : (D)I
    //   38: aload_0
    //   39: getfield Dne : LkSJ;
    //   42: getfield Dne : LbSp;
    //   45: getfield FWm : D
    //   48: d2i
    //   49: aload_0
    //   50: getfield Dne : LkSJ;
    //   53: getfield mrb : D
    //   56: invokestatic FWm : (D)I
    //   59: invokevirtual aFZ : (III)Z
    //   62: ifne -> 67
    //   65: iconst_0
    //   66: ireturn
    //   67: aload_0
    //   68: invokespecial Dne : ()LchN;
    //   71: astore_1
    //   72: aload_1
    //   73: ifnonnull -> 78
    //   76: iconst_0
    //   77: ireturn
    //   78: aload_0
    //   79: aload_1
    //   80: getfield Dne : D
    //   83: putfield Dne : D
    //   86: aload_0
    //   87: aload_1
    //   88: getfield FWm : D
    //   91: putfield FWm : D
    //   94: aload_0
    //   95: aload_1
    //   96: getfield bzF : D
    //   99: putfield bzF : D
    //   102: iconst_1
    //   103: ireturn
  }
}


/* Location:              C:\Users\fract\Downloads\ERROR422.jar!\ITf.class
 * Java compiler version: 8 (52.0)
 * JD-Core Version:       1.1.3
 */