public abstract class Jik {
  public boolean Dne;
  
  public String Dne;
  
  public Qnq Dne;
  
  public float[] Dne;
  
  private float[] FWm;
  
  public kGO Dne;
  
  public tgc Dne;
  
  public int Dne = 0;
  
  public boolean FWm = false;
  
  public int Dne() {
    return (this.Dne == kGO.FWm) ? 4 : 64;
  }
  
  public ZfC Dne() {
    // Byte code:
    //   0: aload_0
    //   1: getfield Dne : LkGO;
    //   4: getstatic kGO.FWm : LkGO;
    //   7: if_acmpne -> 45
    //   10: new sly
    //   13: dup
    //   14: aload_0
    //   15: getfield Dne : LQnq;
    //   18: aload_0
    //   19: getfield Dne : LQnq;
    //   22: invokevirtual Dne : ()J
    //   25: aload_0
    //   26: getfield Dne : LQnq;
    //   29: invokevirtual Dne : ()LxoY;
    //   32: invokevirtual bzF : ()Z
    //   35: aload_0
    //   36: getfield Dne : Ljava/lang/String;
    //   39: invokespecial <init> : (LQnq;JZLjava/lang/String;)V
    //   42: goto -> 73
    //   45: new XwR
    //   48: dup
    //   49: aload_0
    //   50: getfield Dne : LQnq;
    //   53: aload_0
    //   54: getfield Dne : LQnq;
    //   57: invokevirtual Dne : ()J
    //   60: aload_0
    //   61: getfield Dne : LQnq;
    //   64: invokevirtual Dne : ()LxoY;
    //   67: invokevirtual bzF : ()Z
    //   70: invokespecial <init> : (LQnq;JZ)V
    //   73: areturn
  }
  
  public boolean Qnq() {
    return (this.Dne != kGO.FWm && !this.FWm);
  }
  
  public boolean Dne() {
    return true;
  }
  
  public float[] Dne(float paramFloat1, float paramFloat2) {
    float f1 = 0.4F;
    float f2 = geR.FWm(paramFloat1 * 3.1415927F * 2.0F) - 0.0F;
    float f3 = -0.0F;
    if (f2 >= f3 - f1 && f2 <= f3 + f1) {
      float f4 = (f2 - f3) / f1 * 0.5F + 0.5F;
      float f5 = 1.0F - (1.0F - geR.Dne(f4 * 3.1415927F)) * 0.99F;
      f5 *= f5;
      this.FWm[0] = f4 * 0.3F + 0.7F;
      this.FWm[1] = f4 * f4 * 0.7F + 0.2F;
      this.FWm[2] = f4 * f4 * 0.0F + 0.2F;
      this.FWm[3] = f5;
      return this.FWm;
    } 
    return null;
  }
  
  public boolean FWm() {
    return true;
  }
  
  public double Dne() {
    return (this.Dne == kGO.FWm) ? 1.0D : 0.03125D;
  }
  
  public boolean FWm(int paramInt1, int paramInt2) {
    return false;
  }
  
  public boolean Dne(int paramInt1, int paramInt2) {
    // Byte code:
    //   0: aload_0
    //   1: getfield Dne : LQnq;
    //   4: iload_1
    //   5: iload_2
    //   6: invokevirtual Dne : (II)I
    //   9: istore_3
    //   10: iload_3
    //   11: getstatic zKP.Dne : LZQN;
    //   14: getfield FWm : I
    //   17: if_icmpne -> 24
    //   20: iconst_1
    //   21: goto -> 25
    //   24: iconst_0
    //   25: ireturn
  }
  
  public chN Dne(float paramFloat1, float paramFloat2) {
    // Byte code:
    //   0: fload_1
    //   1: ldc 3.1415927
    //   3: fmul
    //   4: fconst_2
    //   5: fmul
    //   6: invokestatic FWm : (F)F
    //   9: fconst_2
    //   10: fmul
    //   11: ldc 0.5
    //   13: fadd
    //   14: fstore_3
    //   15: fload_3
    //   16: fconst_0
    //   17: fcmpg
    //   18: ifge -> 23
    //   21: fconst_0
    //   22: fstore_3
    //   23: fload_3
    //   24: fconst_1
    //   25: fcmpl
    //   26: ifle -> 31
    //   29: fconst_1
    //   30: fstore_3
    //   31: ldc 0.7529412
    //   33: fstore #4
    //   35: ldc 0.84705883
    //   37: fstore #5
    //   39: fconst_1
    //   40: fstore #6
    //   42: fload #4
    //   44: fload_3
    //   45: ldc 0.94
    //   47: fmul
    //   48: ldc 0.06
    //   50: fadd
    //   51: fmul
    //   52: fstore #4
    //   54: fload #5
    //   56: fload_3
    //   57: ldc 0.94
    //   59: fmul
    //   60: ldc 0.06
    //   62: fadd
    //   63: fmul
    //   64: fstore #5
    //   66: fload #6
    //   68: fload_3
    //   69: ldc 0.91
    //   71: fmul
    //   72: ldc 0.09
    //   74: fadd
    //   75: fmul
    //   76: fstore #6
    //   78: aload_0
    //   79: getfield Dne : LQnq;
    //   82: invokevirtual Dne : ()LziS;
    //   85: fload #4
    //   87: f2d
    //   88: fload #5
    //   90: f2d
    //   91: fload #6
    //   93: f2d
    //   94: invokevirtual Dne : (DDD)LchN;
    //   97: areturn
  }
  
  public static Jik Dne(int paramInt) {
    return (paramInt == -1) ? new XjO() : ((paramInt == 0) ? new lMz() : ((paramInt == 1) ? new TKg() : null));
  }
  
  public boolean bzF() {
    return true;
  }
  
  public abstract String Dne();
  
  public float Dne(long paramLong, float paramFloat) {
    int i = (int)(paramLong % 24000L);
    null = (i + paramFloat) / 24000.0F - 0.25F;
    if (null < 0.0F)
      null++; 
    if (null > 1.0F)
      null--; 
    float f = null;
    null = 1.0F - (float)((Math.cos(null * Math.PI) + 1.0D) / 2.0D);
    return f + (null - f) / 3.0F;
  }
  
  public final void Dne(Qnq paramQnq) {
    this.Dne = paramQnq;
    this.Dne = paramQnq.Dne().Dne();
    this.Dne = paramQnq.Dne().FWm();
    FWm();
    Dne();
  }
  
  public float Dne() {
    return 128.0F;
  }
  
  protected void Dne() {
    float f = 0.0F;
    for (byte b = 0; b <= 15; b++) {
      float f1 = 1.0F - b / 15.0F;
      this.Dne[b] = (1.0F - f1) / (f1 * 3.0F + 1.0F) * (1.0F - f) + f;
    } 
  }
  
  public Jik() {
    this.Dne = new float[16];
    this.Dne = 0;
    this.FWm = new float[4];
  }
  
  public int Dne(long paramLong) {
    return (int)(paramLong / 24000L) % 8;
  }
  
  protected void FWm() {
    // Byte code:
    //   0: aload_0
    //   1: getfield Dne : LQnq;
    //   4: invokevirtual Dne : ()LxoY;
    //   7: invokevirtual Dne : ()LkGO;
    //   10: getstatic kGO.FWm : LkGO;
    //   13: if_acmpne -> 56
    //   16: aload_0
    //   17: getfield Dne : LQnq;
    //   20: invokevirtual Dne : ()LxoY;
    //   23: invokevirtual FWm : ()Ljava/lang/String;
    //   26: invokestatic Dne : (Ljava/lang/String;)LlDk;
    //   29: astore_1
    //   30: aload_0
    //   31: new yMz
    //   34: dup
    //   35: getstatic OdI.Dne : [LOdI;
    //   38: aload_1
    //   39: invokevirtual Dne : ()I
    //   42: aaload
    //   43: ldc 0.5
    //   45: ldc 0.5
    //   47: invokespecial <init> : (LOdI;FF)V
    //   50: putfield Dne : Ltgc;
    //   53: goto -> 71
    //   56: aload_0
    //   57: new tgc
    //   60: dup
    //   61: aload_0
    //   62: getfield Dne : LQnq;
    //   65: invokespecial <init> : (LQnq;)V
    //   68: putfield Dne : Ltgc;
    //   71: return
  }
  
  public iSh Dne() {
    return null;
  }
}


/* Location:              C:\Users\fract\Downloads\ERROR422.jar!\Jik.class
 * Java compiler version: 8 (52.0)
 * JD-Core Version:       1.1.3
 */