public abstract class Jte {
  protected XWr Dne;
  
  protected void Dne(String paramString1, String paramString2) {
    // Byte code:
    //   0: aload_0
    //   1: getfield Dne : LXWr;
    //   4: getfield Dne : LSnh;
    //   7: astore_3
    //   8: aload_3
    //   9: ifnull -> 24
    //   12: sipush #3553
    //   15: aload_3
    //   16: aload_1
    //   17: aload_2
    //   18: invokevirtual Dne : (Ljava/lang/String;Ljava/lang/String;)I
    //   21: invokestatic glBindTexture : (II)V
    //   24: aload_3
    //   25: invokevirtual Dne : ()V
    //   28: return
  }
  
  protected void Dne(String paramString) {
    // Byte code:
    //   0: aload_0
    //   1: getfield Dne : LXWr;
    //   4: getfield Dne : LSnh;
    //   7: astore_2
    //   8: aload_2
    //   9: ifnull -> 17
    //   12: aload_2
    //   13: aload_1
    //   14: invokevirtual Dne : (Ljava/lang/String;)V
    //   17: return
  }
  
  public msA Dne() {
    return this.Dne.Dne();
  }
  
  public void Dne(Qnq paramQnq) {}
  
  public void Dne(XWr paramXWr) {
    this.Dne = paramXWr;
  }
  
  public abstract void Dne(ipD paramipD, double paramDouble1, double paramDouble2, double paramDouble3, float paramFloat);
}


/* Location:              C:\Users\fract\Downloads\ERROR422.jar!\Jte.class
 * Java compiler version: 8 (52.0)
 * JD-Core Version:       1.1.3
 */