public class kfK extends dEr {
  static {
  
  }
  
  public kfK(int paramInt) {
    super(paramInt);
    Dne(JcN.Qnq);
  }
  
  public NMq Dne(NMq paramNMq, Qnq paramQnq, FiG paramFiG) {
    // Byte code:
    //   0: fconst_1
    //   1: fstore #4
    //   3: aload_3
    //   4: getfield kGO : F
    //   7: aload_3
    //   8: getfield XHL : F
    //   11: aload_3
    //   12: getfield kGO : F
    //   15: fsub
    //   16: fload #4
    //   18: fmul
    //   19: fadd
    //   20: fstore #5
    //   22: aload_3
    //   23: getfield Zpi : F
    //   26: aload_3
    //   27: getfield mrb : F
    //   30: aload_3
    //   31: getfield Zpi : F
    //   34: fsub
    //   35: fload #4
    //   37: fmul
    //   38: fadd
    //   39: fstore #6
    //   41: aload_3
    //   42: getfield aFZ : D
    //   45: aload_3
    //   46: getfield div : D
    //   49: aload_3
    //   50: getfield aFZ : D
    //   53: dsub
    //   54: fload #4
    //   56: f2d
    //   57: dmul
    //   58: dadd
    //   59: dstore #7
    //   61: aload_3
    //   62: getfield zGp : D
    //   65: aload_3
    //   66: getfield IjH : D
    //   69: aload_3
    //   70: getfield zGp : D
    //   73: dsub
    //   74: fload #4
    //   76: f2d
    //   77: dmul
    //   78: dadd
    //   79: ldc2_w 1.62
    //   82: dadd
    //   83: aload_3
    //   84: getfield udO : F
    //   87: f2d
    //   88: dsub
    //   89: dstore #9
    //   91: aload_3
    //   92: getfield DyG : D
    //   95: aload_3
    //   96: getfield mrb : D
    //   99: aload_3
    //   100: getfield DyG : D
    //   103: dsub
    //   104: fload #4
    //   106: f2d
    //   107: dmul
    //   108: dadd
    //   109: dstore #11
    //   111: aload_2
    //   112: invokevirtual Dne : ()LziS;
    //   115: dload #7
    //   117: dload #9
    //   119: dload #11
    //   121: invokevirtual Dne : (DDD)LchN;
    //   124: astore #13
    //   126: fload #6
    //   128: fneg
    //   129: ldc 0.017453292
    //   131: fmul
    //   132: ldc 3.1415927
    //   134: fsub
    //   135: invokestatic FWm : (F)F
    //   138: fstore #14
    //   140: fload #6
    //   142: fneg
    //   143: ldc 0.017453292
    //   145: fmul
    //   146: ldc 3.1415927
    //   148: fsub
    //   149: invokestatic Dne : (F)F
    //   152: fstore #15
    //   154: fload #5
    //   156: fneg
    //   157: ldc 0.017453292
    //   159: fmul
    //   160: invokestatic FWm : (F)F
    //   163: fneg
    //   164: fstore #16
    //   166: fload #5
    //   168: fneg
    //   169: ldc 0.017453292
    //   171: fmul
    //   172: invokestatic Dne : (F)F
    //   175: fstore #17
    //   177: fload #15
    //   179: fload #16
    //   181: fmul
    //   182: fstore #18
    //   184: fload #14
    //   186: fload #16
    //   188: fmul
    //   189: fstore #19
    //   191: ldc2_w 5.0
    //   194: dstore #20
    //   196: aload #13
    //   198: fload #18
    //   200: f2d
    //   201: dload #20
    //   203: dmul
    //   204: fload #17
    //   206: f2d
    //   207: dload #20
    //   209: dmul
    //   210: fload #19
    //   212: f2d
    //   213: dload #20
    //   215: dmul
    //   216: invokevirtual bzF : (DDD)LchN;
    //   219: astore #22
    //   221: aload_2
    //   222: aload #13
    //   224: aload #22
    //   226: iconst_1
    //   227: invokevirtual Dne : (LchN;LchN;Z)LwHH;
    //   230: astore #23
    //   232: aload #23
    //   234: ifnonnull -> 239
    //   237: aload_1
    //   238: areturn
    //   239: aload_3
    //   240: fload #4
    //   242: invokevirtual FWm : (F)LchN;
    //   245: astore #24
    //   247: iconst_0
    //   248: istore #25
    //   250: fconst_1
    //   251: fstore #26
    //   253: aload_2
    //   254: aload_3
    //   255: aload_3
    //   256: getfield Dne : LbSp;
    //   259: aload #24
    //   261: getfield Dne : D
    //   264: dload #20
    //   266: dmul
    //   267: aload #24
    //   269: getfield FWm : D
    //   272: dload #20
    //   274: dmul
    //   275: aload #24
    //   277: getfield bzF : D
    //   280: dload #20
    //   282: dmul
    //   283: invokevirtual Dne : (DDD)LbSp;
    //   286: fload #26
    //   288: f2d
    //   289: fload #26
    //   291: f2d
    //   292: fload #26
    //   294: f2d
    //   295: invokevirtual FWm : (DDD)LbSp;
    //   298: invokevirtual FWm : (LsMa;LbSp;)Ljava/util/List;
    //   301: astore #27
    //   303: iconst_0
    //   304: istore #28
    //   306: iload #28
    //   308: aload #27
    //   310: invokeinterface size : ()I
    //   315: if_icmpge -> 385
    //   318: aload #27
    //   320: iload #28
    //   322: invokeinterface get : (I)Ljava/lang/Object;
    //   327: checkcast sMa
    //   330: astore #29
    //   332: aload #29
    //   334: invokevirtual kGO : ()Z
    //   337: ifeq -> 379
    //   340: aload #29
    //   342: invokevirtual Qnq : ()F
    //   345: fstore #30
    //   347: aload #29
    //   349: getfield Dne : LbSp;
    //   352: fload #30
    //   354: f2d
    //   355: fload #30
    //   357: f2d
    //   358: fload #30
    //   360: f2d
    //   361: invokevirtual FWm : (DDD)LbSp;
    //   364: astore #31
    //   366: aload #31
    //   368: aload #13
    //   370: invokevirtual Dne : (LchN;)Z
    //   373: ifeq -> 379
    //   376: iconst_1
    //   377: istore #25
    //   379: iinc #28, 1
    //   382: goto -> 306
    //   385: iload #25
    //   387: ifeq -> 392
    //   390: aload_1
    //   391: areturn
    //   392: aload #23
    //   394: getfield Dne : Lgks;
    //   397: getstatic gks.Dne : Lgks;
    //   400: if_acmpne -> 574
    //   403: aload #23
    //   405: getfield Dne : I
    //   408: istore #28
    //   410: aload #23
    //   412: getfield FWm : I
    //   415: istore #29
    //   417: aload #23
    //   419: getfield bzF : I
    //   422: istore #30
    //   424: aload_2
    //   425: iload #28
    //   427: iload #29
    //   429: iload #30
    //   431: invokevirtual Dne : (III)I
    //   434: getstatic zKP.EwP : LzKP;
    //   437: getfield FWm : I
    //   440: if_icmpne -> 446
    //   443: iinc #29, -1
    //   446: new iMX
    //   449: dup
    //   450: aload_2
    //   451: iload #28
    //   453: i2f
    //   454: ldc 0.5
    //   456: fadd
    //   457: f2d
    //   458: iload #29
    //   460: i2f
    //   461: fconst_1
    //   462: fadd
    //   463: f2d
    //   464: iload #30
    //   466: i2f
    //   467: ldc 0.5
    //   469: fadd
    //   470: f2d
    //   471: invokespecial <init> : (LQnq;DDD)V
    //   474: astore #31
    //   476: aload #31
    //   478: aload_3
    //   479: getfield mrb : F
    //   482: ldc 4.0
    //   484: fmul
    //   485: ldc 360.0
    //   487: fdiv
    //   488: f2d
    //   489: ldc2_w 0.5
    //   492: dadd
    //   493: invokestatic FWm : (D)I
    //   496: iconst_3
    //   497: iand
    //   498: iconst_1
    //   499: isub
    //   500: bipush #90
    //   502: imul
    //   503: i2f
    //   504: putfield mrb : F
    //   507: aload_2
    //   508: aload #31
    //   510: aload #31
    //   512: getfield Dne : LbSp;
    //   515: ldc2_w -0.1
    //   518: ldc2_w -0.1
    //   521: ldc2_w -0.1
    //   524: invokevirtual FWm : (DDD)LbSp;
    //   527: invokevirtual Dne : (LsMa;LbSp;)Ljava/util/List;
    //   530: invokeinterface isEmpty : ()Z
    //   535: ifne -> 540
    //   538: aload_1
    //   539: areturn
    //   540: aload_2
    //   541: getfield aFZ : Z
    //   544: ifne -> 554
    //   547: aload_2
    //   548: aload #31
    //   550: invokevirtual FWm : (LsMa;)Z
    //   553: pop
    //   554: aload_3
    //   555: getfield Dne : Luqg;
    //   558: getfield Qnq : Z
    //   561: ifne -> 574
    //   564: aload_1
    //   565: dup
    //   566: getfield Dne : I
    //   569: iconst_1
    //   570: isub
    //   571: putfield Dne : I
    //   574: aload_1
    //   575: areturn
  }
}


/* Location:              C:\Users\fract\Downloads\ERROR422.jar!\kfK.class
 * Java compiler version: 8 (52.0)
 * JD-Core Version:       1.1.3
 */