public abstract class lIg extends FUH {
  static {
  
  }
  
  public boolean div() {
    return false;
  }
  
  protected void Dne(float paramFloat) {}
  
  public lIg(Qnq paramQnq) {
    super(paramQnq);
  }
  
  protected void Dne(double paramDouble, boolean paramBoolean) {}
  
  public void Qnq(float paramFloat1, float paramFloat2) {
    // Byte code:
    //   0: aload_0
    //   1: invokevirtual Zpi : ()Z
    //   4: ifeq -> 70
    //   7: aload_0
    //   8: fload_1
    //   9: fload_2
    //   10: ldc 0.02
    //   12: invokevirtual FWm : (FFF)V
    //   15: aload_0
    //   16: aload_0
    //   17: getfield XHL : D
    //   20: aload_0
    //   21: getfield Zpi : D
    //   24: aload_0
    //   25: getfield kGO : D
    //   28: invokevirtual Dne : (DDD)V
    //   31: aload_0
    //   32: dup
    //   33: getfield XHL : D
    //   36: ldc2_w 0.800000011920929
    //   39: dmul
    //   40: putfield XHL : D
    //   43: aload_0
    //   44: dup
    //   45: getfield Zpi : D
    //   48: ldc2_w 0.800000011920929
    //   51: dmul
    //   52: putfield Zpi : D
    //   55: aload_0
    //   56: dup
    //   57: getfield kGO : D
    //   60: ldc2_w 0.800000011920929
    //   63: dmul
    //   64: putfield kGO : D
    //   67: goto -> 354
    //   70: aload_0
    //   71: invokevirtual DyG : ()Z
    //   74: ifeq -> 140
    //   77: aload_0
    //   78: fload_1
    //   79: fload_2
    //   80: ldc 0.02
    //   82: invokevirtual FWm : (FFF)V
    //   85: aload_0
    //   86: aload_0
    //   87: getfield XHL : D
    //   90: aload_0
    //   91: getfield Zpi : D
    //   94: aload_0
    //   95: getfield kGO : D
    //   98: invokevirtual Dne : (DDD)V
    //   101: aload_0
    //   102: dup
    //   103: getfield XHL : D
    //   106: ldc2_w 0.5
    //   109: dmul
    //   110: putfield XHL : D
    //   113: aload_0
    //   114: dup
    //   115: getfield Zpi : D
    //   118: ldc2_w 0.5
    //   121: dmul
    //   122: putfield Zpi : D
    //   125: aload_0
    //   126: dup
    //   127: getfield kGO : D
    //   130: ldc2_w 0.5
    //   133: dmul
    //   134: putfield kGO : D
    //   137: goto -> 354
    //   140: ldc 0.91
    //   142: fstore_3
    //   143: aload_0
    //   144: getfield aFZ : Z
    //   147: ifeq -> 206
    //   150: ldc 0.54600006
    //   152: fstore_3
    //   153: aload_0
    //   154: getfield Dne : LQnq;
    //   157: aload_0
    //   158: getfield div : D
    //   161: invokestatic FWm : (D)I
    //   164: aload_0
    //   165: getfield Dne : LbSp;
    //   168: getfield FWm : D
    //   171: invokestatic FWm : (D)I
    //   174: iconst_1
    //   175: isub
    //   176: aload_0
    //   177: getfield mrb : D
    //   180: invokestatic FWm : (D)I
    //   183: invokevirtual Dne : (III)I
    //   186: istore #4
    //   188: iload #4
    //   190: ifle -> 206
    //   193: getstatic zKP.Dne : [LzKP;
    //   196: iload #4
    //   198: aaload
    //   199: getfield Qnq : F
    //   202: ldc 0.91
    //   204: fmul
    //   205: fstore_3
    //   206: ldc 0.16277136
    //   208: fload_3
    //   209: fload_3
    //   210: fmul
    //   211: fload_3
    //   212: fmul
    //   213: fdiv
    //   214: fstore #4
    //   216: aload_0
    //   217: fload_1
    //   218: fload_2
    //   219: aload_0
    //   220: getfield aFZ : Z
    //   223: ifeq -> 234
    //   226: ldc 0.1
    //   228: fload #4
    //   230: fmul
    //   231: goto -> 236
    //   234: ldc 0.02
    //   236: invokevirtual FWm : (FFF)V
    //   239: ldc 0.91
    //   241: fstore_3
    //   242: aload_0
    //   243: getfield aFZ : Z
    //   246: ifeq -> 305
    //   249: ldc 0.54600006
    //   251: fstore_3
    //   252: aload_0
    //   253: getfield Dne : LQnq;
    //   256: aload_0
    //   257: getfield div : D
    //   260: invokestatic FWm : (D)I
    //   263: aload_0
    //   264: getfield Dne : LbSp;
    //   267: getfield FWm : D
    //   270: invokestatic FWm : (D)I
    //   273: iconst_1
    //   274: isub
    //   275: aload_0
    //   276: getfield mrb : D
    //   279: invokestatic FWm : (D)I
    //   282: invokevirtual Dne : (III)I
    //   285: istore #5
    //   287: iload #5
    //   289: ifle -> 305
    //   292: getstatic zKP.Dne : [LzKP;
    //   295: iload #5
    //   297: aaload
    //   298: getfield Qnq : F
    //   301: ldc 0.91
    //   303: fmul
    //   304: fstore_3
    //   305: aload_0
    //   306: aload_0
    //   307: getfield XHL : D
    //   310: aload_0
    //   311: getfield Zpi : D
    //   314: aload_0
    //   315: getfield kGO : D
    //   318: invokevirtual Dne : (DDD)V
    //   321: aload_0
    //   322: dup
    //   323: getfield XHL : D
    //   326: fload_3
    //   327: f2d
    //   328: dmul
    //   329: putfield XHL : D
    //   332: aload_0
    //   333: dup
    //   334: getfield Zpi : D
    //   337: fload_3
    //   338: f2d
    //   339: dmul
    //   340: putfield Zpi : D
    //   343: aload_0
    //   344: dup
    //   345: getfield kGO : D
    //   348: fload_3
    //   349: f2d
    //   350: dmul
    //   351: putfield kGO : D
    //   354: aload_0
    //   355: aload_0
    //   356: getfield qrB : F
    //   359: putfield haP : F
    //   362: aload_0
    //   363: getfield div : D
    //   366: aload_0
    //   367: getfield aFZ : D
    //   370: dsub
    //   371: dstore_3
    //   372: aload_0
    //   373: getfield mrb : D
    //   376: aload_0
    //   377: getfield DyG : D
    //   380: dsub
    //   381: dstore #5
    //   383: dload_3
    //   384: dload_3
    //   385: dmul
    //   386: dload #5
    //   388: dload #5
    //   390: dmul
    //   391: dadd
    //   392: invokestatic Dne : (D)F
    //   395: ldc 4.0
    //   397: fmul
    //   398: fstore #7
    //   400: fload #7
    //   402: fconst_1
    //   403: fcmpl
    //   404: ifle -> 410
    //   407: fconst_1
    //   408: fstore #7
    //   410: aload_0
    //   411: dup
    //   412: getfield qrB : F
    //   415: fload #7
    //   417: aload_0
    //   418: getfield qrB : F
    //   421: fsub
    //   422: ldc 0.4
    //   424: fmul
    //   425: fadd
    //   426: putfield qrB : F
    //   429: aload_0
    //   430: dup
    //   431: getfield LVR : F
    //   434: aload_0
    //   435: getfield qrB : F
    //   438: fadd
    //   439: putfield LVR : F
    //   442: return
  }
}


/* Location:              C:\Users\fract\Downloads\ERROR422.jar!\lIg.class
 * Java compiler version: 8 (52.0)
 * JD-Core Version:       1.1.3
 */