import java.util.List;

public class lOW extends xZE {
  public int Dne() {
    return 3;
  }
  
  public List Dne(gnI paramgnI, String[] paramArrayOfString) {
    return (paramArrayOfString.length >= 1) ? Dne(paramArrayOfString, Jwh.Dne().Dne()) : null;
  }
  
  static {
  
  }
  
  public String Dne() {
    return "ban";
  }
  
  public boolean Dne(gnI paramgnI) {
    return (Jwh.Dne().Dne().Dne().Dne() && super.Dne(paramgnI));
  }
  
  public void Dne(gnI paramgnI, String[] paramArrayOfString) {
    // Byte code:
    //   0: aload_2
    //   1: arraylength
    //   2: iconst_1
    //   3: if_icmplt -> 114
    //   6: aload_2
    //   7: iconst_0
    //   8: aaload
    //   9: invokevirtual length : ()I
    //   12: ifle -> 114
    //   15: invokestatic Dne : ()LJwh;
    //   18: invokevirtual Dne : ()LdzN;
    //   21: aload_2
    //   22: iconst_0
    //   23: aaload
    //   24: invokevirtual FWm : (Ljava/lang/String;)LPJQ;
    //   27: astore_3
    //   28: new eHI
    //   31: dup
    //   32: aload_2
    //   33: iconst_0
    //   34: aaload
    //   35: invokespecial <init> : (Ljava/lang/String;)V
    //   38: astore #4
    //   40: aload #4
    //   42: aload_1
    //   43: invokeinterface a_ : ()Ljava/lang/String;
    //   48: invokevirtual Dne : (Ljava/lang/String;)V
    //   51: aload_2
    //   52: arraylength
    //   53: iconst_2
    //   54: if_icmplt -> 68
    //   57: aload #4
    //   59: aload_1
    //   60: aload_2
    //   61: iconst_1
    //   62: invokestatic Dne : (LgnI;[Ljava/lang/String;I)Ljava/lang/String;
    //   65: invokevirtual FWm : (Ljava/lang/String;)V
    //   68: invokestatic Dne : ()LJwh;
    //   71: invokevirtual Dne : ()LdzN;
    //   74: invokevirtual Dne : ()LbkM;
    //   77: aload #4
    //   79: invokevirtual Dne : (LeHI;)V
    //   82: aload_3
    //   83: ifnull -> 95
    //   86: aload_3
    //   87: getfield Dne : LTnv;
    //   90: ldc 'You are banned from this server.'
    //   92: invokevirtual Dne : (Ljava/lang/String;)V
    //   95: aload_1
    //   96: ldc 'commands.ban.success'
    //   98: iconst_1
    //   99: anewarray java/lang/Object
    //   102: dup
    //   103: iconst_0
    //   104: aload_2
    //   105: iconst_0
    //   106: aaload
    //   107: aastore
    //   108: invokestatic Dne : (LgnI;Ljava/lang/String;[Ljava/lang/Object;)V
    //   111: goto -> 128
    //   114: new fxw
    //   117: dup
    //   118: ldc 'commands.ban.usage'
    //   120: iconst_0
    //   121: anewarray java/lang/Object
    //   124: invokespecial <init> : (Ljava/lang/String;[Ljava/lang/Object;)V
    //   127: athrow
    //   128: return
  }
  
  public String Dne(gnI paramgnI) {
    return paramgnI.Dne("commands.ban.usage", new Object[0]);
  }
}


/* Location:              C:\Users\fract\Downloads\ERROR422.jar!\lOW.class
 * Java compiler version: 8 (52.0)
 * JD-Core Version:       1.1.3
 */