public class LVR extends Fnk {
  protected gwq ceE = new sJS(zKP.dNY.FWm);
  
  protected void Dne() {
    // Byte code:
    //   0: aload_0
    //   1: invokevirtual FWm : ()V
    //   4: aload_0
    //   5: getfield Dne : Ljava/util/Random;
    //   8: iconst_5
    //   9: invokevirtual nextInt : (I)I
    //   12: ifne -> 84
    //   15: aload_0
    //   16: getfield Dne : I
    //   19: aload_0
    //   20: getfield Dne : Ljava/util/Random;
    //   23: bipush #16
    //   25: invokevirtual nextInt : (I)I
    //   28: iadd
    //   29: bipush #8
    //   31: iadd
    //   32: istore_1
    //   33: aload_0
    //   34: getfield FWm : I
    //   37: aload_0
    //   38: getfield Dne : Ljava/util/Random;
    //   41: bipush #16
    //   43: invokevirtual nextInt : (I)I
    //   46: iadd
    //   47: bipush #8
    //   49: iadd
    //   50: istore_2
    //   51: aload_0
    //   52: getfield Dne : LQnq;
    //   55: iload_1
    //   56: iload_2
    //   57: invokevirtual aFZ : (II)I
    //   60: istore_3
    //   61: iload_3
    //   62: ifle -> 65
    //   65: aload_0
    //   66: getfield ceE : Lgwq;
    //   69: aload_0
    //   70: getfield Dne : LQnq;
    //   73: aload_0
    //   74: getfield Dne : Ljava/util/Random;
    //   77: iload_1
    //   78: iload_3
    //   79: iload_2
    //   80: invokevirtual Dne : (LQnq;Ljava/util/Random;III)Z
    //   83: pop
    //   84: aload_0
    //   85: getfield Dne : I
    //   88: ifne -> 139
    //   91: aload_0
    //   92: getfield FWm : I
    //   95: ifne -> 139
    //   98: new WSC
    //   101: dup
    //   102: aload_0
    //   103: getfield Dne : LQnq;
    //   106: invokespecial <init> : (LQnq;)V
    //   109: astore_1
    //   110: aload_1
    //   111: dconst_0
    //   112: ldc2_w 128.0
    //   115: dconst_0
    //   116: aload_0
    //   117: getfield Dne : Ljava/util/Random;
    //   120: invokevirtual nextFloat : ()F
    //   123: ldc 360.0
    //   125: fmul
    //   126: fconst_0
    //   127: invokevirtual FWm : (DDDFF)V
    //   130: aload_0
    //   131: getfield Dne : LQnq;
    //   134: aload_1
    //   135: invokevirtual FWm : (LsMa;)Z
    //   138: pop
    //   139: return
  }
  
  public LVR(OdI paramOdI) {
    super(paramOdI);
  }
}


/* Location:              C:\Users\fract\Downloads\ERROR422.jar!\LVR.class
 * Java compiler version: 8 (52.0)
 * JD-Core Version:       1.1.3
 */