public class ocu {
  protected float FWm = 0.0F;
  
  public void Dne(int paramInt1, int paramInt2, gDn paramgDn, int paramInt3, int paramInt4) {
    // Byte code:
    //   0: getstatic WAR.Dne : LWAR;
    //   3: astore #6
    //   5: aload #6
    //   7: invokevirtual Dne : ()V
    //   10: aload #6
    //   12: iload_1
    //   13: iconst_0
    //   14: iadd
    //   15: i2d
    //   16: iload_2
    //   17: iload #5
    //   19: iadd
    //   20: i2d
    //   21: aload_0
    //   22: getfield FWm : F
    //   25: f2d
    //   26: aload_3
    //   27: invokeinterface Dne : ()F
    //   32: f2d
    //   33: aload_3
    //   34: invokeinterface Qnq : ()F
    //   39: f2d
    //   40: invokevirtual Dne : (DDDDD)V
    //   43: aload #6
    //   45: iload_1
    //   46: iload #4
    //   48: iadd
    //   49: i2d
    //   50: iload_2
    //   51: iload #5
    //   53: iadd
    //   54: i2d
    //   55: aload_0
    //   56: getfield FWm : F
    //   59: f2d
    //   60: aload_3
    //   61: invokeinterface FWm : ()F
    //   66: f2d
    //   67: aload_3
    //   68: invokeinterface Qnq : ()F
    //   73: f2d
    //   74: invokevirtual Dne : (DDDDD)V
    //   77: aload #6
    //   79: iload_1
    //   80: iload #4
    //   82: iadd
    //   83: i2d
    //   84: iload_2
    //   85: iconst_0
    //   86: iadd
    //   87: i2d
    //   88: aload_0
    //   89: getfield FWm : F
    //   92: f2d
    //   93: aload_3
    //   94: invokeinterface FWm : ()F
    //   99: f2d
    //   100: aload_3
    //   101: invokeinterface bzF : ()F
    //   106: f2d
    //   107: invokevirtual Dne : (DDDDD)V
    //   110: aload #6
    //   112: iload_1
    //   113: iconst_0
    //   114: iadd
    //   115: i2d
    //   116: iload_2
    //   117: iconst_0
    //   118: iadd
    //   119: i2d
    //   120: aload_0
    //   121: getfield FWm : F
    //   124: f2d
    //   125: aload_3
    //   126: invokeinterface Dne : ()F
    //   131: f2d
    //   132: aload_3
    //   133: invokeinterface bzF : ()F
    //   138: f2d
    //   139: invokevirtual Dne : (DDDDD)V
    //   142: aload #6
    //   144: invokevirtual Dne : ()I
    //   147: pop
    //   148: return
  }
  
  protected void Dne(int paramInt1, int paramInt2, int paramInt3, int paramInt4, int paramInt5, int paramInt6) {
    // Byte code:
    //   0: iload #5
    //   2: bipush #24
    //   4: ishr
    //   5: sipush #255
    //   8: iand
    //   9: i2f
    //   10: ldc 255.0
    //   12: fdiv
    //   13: fstore #7
    //   15: iload #5
    //   17: bipush #16
    //   19: ishr
    //   20: sipush #255
    //   23: iand
    //   24: i2f
    //   25: ldc 255.0
    //   27: fdiv
    //   28: fstore #8
    //   30: iload #5
    //   32: bipush #8
    //   34: ishr
    //   35: sipush #255
    //   38: iand
    //   39: i2f
    //   40: ldc 255.0
    //   42: fdiv
    //   43: fstore #9
    //   45: iload #5
    //   47: sipush #255
    //   50: iand
    //   51: i2f
    //   52: ldc 255.0
    //   54: fdiv
    //   55: fstore #10
    //   57: iload #6
    //   59: bipush #24
    //   61: ishr
    //   62: sipush #255
    //   65: iand
    //   66: i2f
    //   67: ldc 255.0
    //   69: fdiv
    //   70: fstore #11
    //   72: iload #6
    //   74: bipush #16
    //   76: ishr
    //   77: sipush #255
    //   80: iand
    //   81: i2f
    //   82: ldc 255.0
    //   84: fdiv
    //   85: fstore #12
    //   87: iload #6
    //   89: bipush #8
    //   91: ishr
    //   92: sipush #255
    //   95: iand
    //   96: i2f
    //   97: ldc 255.0
    //   99: fdiv
    //   100: fstore #13
    //   102: iload #6
    //   104: sipush #255
    //   107: iand
    //   108: i2f
    //   109: ldc 255.0
    //   111: fdiv
    //   112: fstore #14
    //   114: sipush #3553
    //   117: invokestatic glDisable : (I)V
    //   120: sipush #3042
    //   123: invokestatic glEnable : (I)V
    //   126: sipush #3008
    //   129: invokestatic glDisable : (I)V
    //   132: sipush #770
    //   135: sipush #771
    //   138: invokestatic glBlendFunc : (II)V
    //   141: sipush #7425
    //   144: invokestatic glShadeModel : (I)V
    //   147: getstatic WAR.Dne : LWAR;
    //   150: astore #15
    //   152: aload #15
    //   154: invokevirtual Dne : ()V
    //   157: aload #15
    //   159: fload #8
    //   161: fload #9
    //   163: fload #10
    //   165: fload #7
    //   167: invokevirtual Dne : (FFFF)V
    //   170: aload #15
    //   172: iload_3
    //   173: i2d
    //   174: iload_2
    //   175: i2d
    //   176: aload_0
    //   177: getfield FWm : F
    //   180: f2d
    //   181: invokevirtual Dne : (DDD)V
    //   184: aload #15
    //   186: iload_1
    //   187: i2d
    //   188: iload_2
    //   189: i2d
    //   190: aload_0
    //   191: getfield FWm : F
    //   194: f2d
    //   195: invokevirtual Dne : (DDD)V
    //   198: aload #15
    //   200: fload #12
    //   202: fload #13
    //   204: fload #14
    //   206: fload #11
    //   208: invokevirtual Dne : (FFFF)V
    //   211: aload #15
    //   213: iload_1
    //   214: i2d
    //   215: iload #4
    //   217: i2d
    //   218: aload_0
    //   219: getfield FWm : F
    //   222: f2d
    //   223: invokevirtual Dne : (DDD)V
    //   226: aload #15
    //   228: iload_3
    //   229: i2d
    //   230: iload #4
    //   232: i2d
    //   233: aload_0
    //   234: getfield FWm : F
    //   237: f2d
    //   238: invokevirtual Dne : (DDD)V
    //   241: aload #15
    //   243: invokevirtual Dne : ()I
    //   246: pop
    //   247: sipush #7424
    //   250: invokestatic glShadeModel : (I)V
    //   253: sipush #3042
    //   256: invokestatic glDisable : (I)V
    //   259: sipush #3008
    //   262: invokestatic glEnable : (I)V
    //   265: sipush #3553
    //   268: invokestatic glEnable : (I)V
    //   271: return
  }
  
  protected void FWm(int paramInt1, int paramInt2, int paramInt3, int paramInt4) {
    if (paramInt3 < paramInt2) {
      int i = paramInt2;
      paramInt2 = paramInt3;
      paramInt3 = i;
    } 
    Dne(paramInt1, paramInt2 + 1, paramInt1 + 1, paramInt3, paramInt4);
  }
  
  public static void Dne(int paramInt1, int paramInt2, int paramInt3, int paramInt4, int paramInt5) {
    // Byte code:
    //   0: iload_0
    //   1: iload_2
    //   2: if_icmpge -> 13
    //   5: iload_0
    //   6: istore #5
    //   8: iload_2
    //   9: istore_0
    //   10: iload #5
    //   12: istore_2
    //   13: iload_1
    //   14: iload_3
    //   15: if_icmpge -> 26
    //   18: iload_1
    //   19: istore #5
    //   21: iload_3
    //   22: istore_1
    //   23: iload #5
    //   25: istore_3
    //   26: iload #4
    //   28: bipush #24
    //   30: ishr
    //   31: sipush #255
    //   34: iand
    //   35: i2f
    //   36: ldc 255.0
    //   38: fdiv
    //   39: fstore #6
    //   41: iload #4
    //   43: bipush #16
    //   45: ishr
    //   46: sipush #255
    //   49: iand
    //   50: i2f
    //   51: ldc 255.0
    //   53: fdiv
    //   54: fstore #7
    //   56: iload #4
    //   58: bipush #8
    //   60: ishr
    //   61: sipush #255
    //   64: iand
    //   65: i2f
    //   66: ldc 255.0
    //   68: fdiv
    //   69: fstore #8
    //   71: iload #4
    //   73: sipush #255
    //   76: iand
    //   77: i2f
    //   78: ldc 255.0
    //   80: fdiv
    //   81: fstore #9
    //   83: getstatic WAR.Dne : LWAR;
    //   86: astore #10
    //   88: sipush #3042
    //   91: invokestatic glEnable : (I)V
    //   94: sipush #3553
    //   97: invokestatic glDisable : (I)V
    //   100: sipush #770
    //   103: sipush #771
    //   106: invokestatic glBlendFunc : (II)V
    //   109: fload #7
    //   111: fload #8
    //   113: fload #9
    //   115: fload #6
    //   117: invokestatic glColor4f : (FFFF)V
    //   120: aload #10
    //   122: invokevirtual Dne : ()V
    //   125: aload #10
    //   127: iload_0
    //   128: i2d
    //   129: iload_3
    //   130: i2d
    //   131: dconst_0
    //   132: invokevirtual Dne : (DDD)V
    //   135: aload #10
    //   137: iload_2
    //   138: i2d
    //   139: iload_3
    //   140: i2d
    //   141: dconst_0
    //   142: invokevirtual Dne : (DDD)V
    //   145: aload #10
    //   147: iload_2
    //   148: i2d
    //   149: iload_1
    //   150: i2d
    //   151: dconst_0
    //   152: invokevirtual Dne : (DDD)V
    //   155: aload #10
    //   157: iload_0
    //   158: i2d
    //   159: iload_1
    //   160: i2d
    //   161: dconst_0
    //   162: invokevirtual Dne : (DDD)V
    //   165: aload #10
    //   167: invokevirtual Dne : ()I
    //   170: pop
    //   171: sipush #3553
    //   174: invokestatic glEnable : (I)V
    //   177: sipush #3042
    //   180: invokestatic glDisable : (I)V
    //   183: return
  }
  
  protected void Dne(int paramInt1, int paramInt2, int paramInt3, int paramInt4) {
    if (paramInt2 < paramInt1) {
      int i = paramInt1;
      paramInt1 = paramInt2;
      paramInt2 = i;
    } 
    Dne(paramInt1, paramInt3, paramInt2 + 1, paramInt3 + 1, paramInt4);
  }
  
  public void FWm(msA parammsA, String paramString, int paramInt1, int paramInt2, int paramInt3) {
    parammsA.Dne(paramString, paramInt1, paramInt2, paramInt3);
  }
  
  public void FWm(int paramInt1, int paramInt2, int paramInt3, int paramInt4, int paramInt5, int paramInt6) {
    // Byte code:
    //   0: ldc 0.00390625
    //   2: fstore #7
    //   4: ldc 0.00390625
    //   6: fstore #8
    //   8: getstatic WAR.Dne : LWAR;
    //   11: astore #9
    //   13: aload #9
    //   15: invokevirtual Dne : ()V
    //   18: aload #9
    //   20: iload_1
    //   21: iconst_0
    //   22: iadd
    //   23: i2d
    //   24: iload_2
    //   25: iload #6
    //   27: iadd
    //   28: i2d
    //   29: aload_0
    //   30: getfield FWm : F
    //   33: f2d
    //   34: iload_3
    //   35: iconst_0
    //   36: iadd
    //   37: i2f
    //   38: fload #7
    //   40: fmul
    //   41: f2d
    //   42: iload #4
    //   44: iload #6
    //   46: iadd
    //   47: i2f
    //   48: fload #8
    //   50: fmul
    //   51: f2d
    //   52: invokevirtual Dne : (DDDDD)V
    //   55: aload #9
    //   57: iload_1
    //   58: iload #5
    //   60: iadd
    //   61: i2d
    //   62: iload_2
    //   63: iload #6
    //   65: iadd
    //   66: i2d
    //   67: aload_0
    //   68: getfield FWm : F
    //   71: f2d
    //   72: iload_3
    //   73: iload #5
    //   75: iadd
    //   76: i2f
    //   77: fload #7
    //   79: fmul
    //   80: f2d
    //   81: iload #4
    //   83: iload #6
    //   85: iadd
    //   86: i2f
    //   87: fload #8
    //   89: fmul
    //   90: f2d
    //   91: invokevirtual Dne : (DDDDD)V
    //   94: aload #9
    //   96: iload_1
    //   97: iload #5
    //   99: iadd
    //   100: i2d
    //   101: iload_2
    //   102: iconst_0
    //   103: iadd
    //   104: i2d
    //   105: aload_0
    //   106: getfield FWm : F
    //   109: f2d
    //   110: iload_3
    //   111: iload #5
    //   113: iadd
    //   114: i2f
    //   115: fload #7
    //   117: fmul
    //   118: f2d
    //   119: iload #4
    //   121: iconst_0
    //   122: iadd
    //   123: i2f
    //   124: fload #8
    //   126: fmul
    //   127: f2d
    //   128: invokevirtual Dne : (DDDDD)V
    //   131: aload #9
    //   133: iload_1
    //   134: iconst_0
    //   135: iadd
    //   136: i2d
    //   137: iload_2
    //   138: iconst_0
    //   139: iadd
    //   140: i2d
    //   141: aload_0
    //   142: getfield FWm : F
    //   145: f2d
    //   146: iload_3
    //   147: iconst_0
    //   148: iadd
    //   149: i2f
    //   150: fload #7
    //   152: fmul
    //   153: f2d
    //   154: iload #4
    //   156: iconst_0
    //   157: iadd
    //   158: i2f
    //   159: fload #8
    //   161: fmul
    //   162: f2d
    //   163: invokevirtual Dne : (DDDDD)V
    //   166: aload #9
    //   168: invokevirtual Dne : ()I
    //   171: pop
    //   172: return
  }
  
  public void Dne(msA parammsA, String paramString, int paramInt1, int paramInt2, int paramInt3) {
    parammsA.Dne(paramString, paramInt1 - parammsA.Dne(paramString) / 2, paramInt2, paramInt3);
  }
}


/* Location:              C:\Users\fract\Downloads\ERROR422.jar!\ocu.class
 * Java compiler version: 8 (52.0)
 * JD-Core Version:       1.1.3
 */