import java.awt.Color;
import java.util.List;
import java.util.Random;

public abstract class OdI {
  protected List bzF;
  
  protected tIz Dne;
  
  public int Dne;
  
  public static final OdI aFZ;
  
  protected edi Dne;
  
  public static final OdI div;
  
  public static final OdI mrb;
  
  protected Woy Dne;
  
  private boolean FWm;
  
  public static final OdI OdI;
  
  public static final OdI ATE;
  
  protected List Qnq;
  
  public byte FWm;
  
  public int FWm;
  
  public static final OdI qLR;
  
  public static final OdI XHL;
  
  public static final OdI ceE;
  
  public float FWm;
  
  public float Qnq;
  
  public float bzF;
  
  public static final OdI kGO;
  
  public static final OdI bzF;
  
  public Fnk Dne;
  
  public static final OdI Dne;
  
  public float Dne;
  
  protected ghu Dne;
  
  public static final OdI FfS;
  
  public static final OdI Vxn;
  
  public static final OdI DyG;
  
  public static final OdI Zpi;
  
  public String Dne;
  
  public static final OdI trS;
  
  public byte Dne;
  
  public static final OdI ooe;
  
  public int bzF;
  
  protected List FWm;
  
  public static final OdI FWm;
  
  public static final OdI udO;
  
  public static final OdI[] Dne = new OdI[256];
  
  public final int Qnq;
  
  protected List Dne;
  
  public static final OdI zGp;
  
  public static final OdI IjH;
  
  public static final OdI EyB;
  
  public static final OdI Qnq;
  
  private boolean Dne;
  
  protected OdI Dne(int paramInt) {
    this.FWm = paramInt;
    return this;
  }
  
  public int Qnq() {
    double d1 = geR.Dne(bzF(), 0.0F, 1.0F);
    double d2 = geR.Dne(FWm(), 0.0F, 1.0F);
    return QFY.Dne(d1, d2);
  }
  
  public boolean bzF() {
    return (this.Qnq > 0.85F);
  }
  
  private OdI FWm() {
    this.FWm = false;
    return this;
  }
  
  public boolean Dne() {
    return this.Dne;
  }
  
  public void Dne(Qnq paramQnq, Random paramRandom, int paramInt1, int paramInt2) {
    // Byte code:
    //   0: aload_0
    //   1: getfield Dne : LFnk;
    //   4: aload_1
    //   5: aload_2
    //   6: iload_3
    //   7: iload #4
    //   9: invokevirtual Dne : (LQnq;Ljava/util/Random;II)V
    //   12: return
  }
  
  public int bzF() {
    double d1 = geR.Dne(bzF(), 0.0F, 1.0F);
    double d2 = geR.Dne(FWm(), 0.0F, 1.0F);
    return bzF.Dne(d1, d2);
  }
  
  static {
    Dne = (new eHV(0)).FWm(112).Dne("Ocean").FWm(-1.0F, 0.4F);
    FWm = (new mlD(1)).FWm(9286496).Dne("Plains").Dne(0.8F, 0.4F);
    bzF = (new qXo(2)).FWm(16421912).Dne("Desert").FWm().Dne(2.0F, 0.0F).FWm(0.1F, 0.2F);
    Qnq = (new AgF(3)).FWm(6316128).Dne("Extreme Hills").FWm(0.3F, 1.5F).Dne(0.2F, 0.3F);
    aFZ = (new cot(4)).FWm(353825).Dne("Forest").Dne(5159473).Dne(0.7F, 0.8F);
    zGp = (new haP(5)).FWm(747097).Dne("Taiga").Dne(5159473).Dne().Dne(0.05F, 0.8F).FWm(0.1F, 0.4F);
    DyG = (new rPc(6)).FWm(522674).Dne("Swampland").Dne(9154376).FWm(-0.2F, 0.1F).Dne(0.8F, 0.9F);
    div = (new EWz(7)).FWm(255).Dne("River").FWm(-0.5F, 0.0F);
    IjH = (new Wwe(8)).FWm(16711680).Dne("Hell").FWm().Dne(2.0F, 0.0F);
    mrb = (new qrB(9)).FWm(8421631).Dne("Sky").FWm();
    XHL = (new eHV(10)).FWm(9474208).Dne("FrozenOcean").Dne().FWm(-1.0F, 0.5F).Dne(0.0F, 0.5F);
    Zpi = (new EWz(11)).FWm(10526975).Dne("FrozenRiver").Dne().FWm(-0.5F, 0.0F).Dne(0.0F, 0.5F);
    kGO = (new eJi(12)).FWm(16777215).Dne("Ice Plains").Dne().Dne(0.0F, 0.5F);
    udO = (new eJi(13)).FWm(10526880).Dne("Ice Mountains").Dne().FWm(0.3F, 1.3F).Dne(0.0F, 0.5F);
    ooe = (new ZgS(14)).FWm(16711935).Dne("MushroomIsland").Dne(0.9F, 1.0F).FWm(0.2F, 1.0F);
    trS = (new ZgS(15)).FWm(10486015).Dne("MushroomIslandShore").Dne(0.9F, 1.0F).FWm(-1.0F, 0.1F);
    qLR = (new FfS(16)).FWm(16440917).Dne("Beach").Dne(0.8F, 0.4F).FWm(0.0F, 0.1F);
    ATE = (new qXo(17)).FWm(13786898).Dne("DesertHills").FWm().Dne(2.0F, 0.0F).FWm(0.3F, 0.8F);
    Vxn = (new cot(18)).FWm(2250012).Dne("ForestHills").Dne(5159473).Dne(0.7F, 0.8F).FWm(0.3F, 0.7F);
    ceE = (new haP(19)).FWm(1456435).Dne("TaigaHills").Dne().Dne(5159473).Dne(0.05F, 0.8F).FWm(0.3F, 0.8F);
    EyB = (new AgF(20)).FWm(7501978).Dne("Extreme Hills Edge").FWm(0.2F, 0.8F).Dne(0.2F, 0.3F);
    FfS = (new One(21)).FWm(5470985).Dne("Jungle").Dne(5470985).Dne(1.2F, 0.9F).FWm(0.2F, 0.4F);
    OdI = (new One(22)).FWm(2900485).Dne("JungleHills").Dne(5470985).Dne(1.2F, 0.9F).FWm(1.8F, 0.5F);
  }
  
  public final float FWm() {
    return this.Qnq;
  }
  
  public final float bzF() {
    return this.bzF;
  }
  
  public int Dne(float paramFloat) {
    paramFloat /= 3.0F;
    if (paramFloat < -1.0F)
      paramFloat = -1.0F; 
    if (paramFloat > 1.0F)
      paramFloat = 1.0F; 
    return Color.getHSBColor(0.62222224F - paramFloat * 0.05F, 0.5F + paramFloat * 0.1F, 1.0F).getRGB();
  }
  
  public boolean FWm() {
    return this.Dne ? false : this.FWm;
  }
  
  public float Dne() {
    return 0.1F;
  }
  
  public final int FWm() {
    return (int)(this.bzF * 65536.0F);
  }
  
  public gwq Dne(Random paramRandom) {
    return (paramRandom.nextInt(10) == 0) ? this.Dne : this.Dne;
  }
  
  public gwq FWm(Random paramRandom) {
    return new Wnd(((Tte)zKP.Dne).FWm, 1);
  }
  
  public final int Dne() {
    return (int)(this.Qnq * 65536.0F);
  }
  
  public List Dne(Icc paramIcc) {
    return (paramIcc == Icc.Dne) ? this.Dne : ((paramIcc == Icc.FWm) ? (List)this.FWm : ((paramIcc == Icc.Qnq) ? this.bzF : ((paramIcc == Icc.bzF) ? (List)this.Qnq : null)));
  }
  
  protected OdI Dne() {
    this.Dne = true;
    return this;
  }
  
  private OdI FWm(float paramFloat1, float paramFloat2) {
    this.Dne = paramFloat1;
    this.FWm = paramFloat2;
    return this;
  }
  
  private OdI Dne(float paramFloat1, float paramFloat2) {
    if (paramFloat1 > 0.1F && paramFloat1 < 0.2F)
      throw new IllegalArgumentException("Please avoid temperatures in the range 0.1 - 0.2 because of snow"); 
    this.bzF = paramFloat1;
    this.Qnq = paramFloat2;
    return this;
  }
  
  protected OdI FWm(int paramInt) {
    this.Dne = paramInt;
    return this;
  }
  
  protected Fnk Dne() {
    return new Fnk(this);
  }
  
  protected OdI Dne(String paramString) {
    this.Dne = paramString;
    return this;
  }
  
  protected OdI(int paramInt) {
    // Byte code:
    //   0: aload_0
    //   1: invokespecial <init> : ()V
    //   4: aload_0
    //   5: getstatic zKP.Dne : LZQN;
    //   8: getfield FWm : I
    //   11: i2b
    //   12: putfield Dne : B
    //   15: aload_0
    //   16: getstatic zKP.FWm : LzKP;
    //   19: getfield FWm : I
    //   22: i2b
    //   23: putfield FWm : B
    //   26: aload_0
    //   27: ldc_w 5169201
    //   30: putfield FWm : I
    //   33: aload_0
    //   34: ldc 0.1
    //   36: putfield Dne : F
    //   39: aload_0
    //   40: ldc 0.3
    //   42: putfield FWm : F
    //   45: aload_0
    //   46: ldc 0.5
    //   48: putfield bzF : F
    //   51: aload_0
    //   52: ldc 0.5
    //   54: putfield Qnq : F
    //   57: aload_0
    //   58: ldc 16777215
    //   60: putfield bzF : I
    //   63: aload_0
    //   64: new java/util/ArrayList
    //   67: dup
    //   68: invokespecial <init> : ()V
    //   71: putfield Dne : Ljava/util/List;
    //   74: aload_0
    //   75: new java/util/ArrayList
    //   78: dup
    //   79: invokespecial <init> : ()V
    //   82: putfield FWm : Ljava/util/List;
    //   85: aload_0
    //   86: new java/util/ArrayList
    //   89: dup
    //   90: invokespecial <init> : ()V
    //   93: putfield bzF : Ljava/util/List;
    //   96: aload_0
    //   97: new java/util/ArrayList
    //   100: dup
    //   101: invokespecial <init> : ()V
    //   104: putfield Qnq : Ljava/util/List;
    //   107: aload_0
    //   108: iconst_1
    //   109: putfield FWm : Z
    //   112: aload_0
    //   113: new ghu
    //   116: dup
    //   117: iconst_0
    //   118: invokespecial <init> : (Z)V
    //   121: putfield Dne : Lghu;
    //   124: aload_0
    //   125: new edi
    //   128: dup
    //   129: iconst_0
    //   130: invokespecial <init> : (Z)V
    //   133: putfield Dne : Ledi;
    //   136: aload_0
    //   137: new tIz
    //   140: dup
    //   141: iconst_0
    //   142: invokespecial <init> : (Z)V
    //   145: putfield Dne : LtIz;
    //   148: aload_0
    //   149: new Woy
    //   152: dup
    //   153: invokespecial <init> : ()V
    //   156: putfield Dne : LWoy;
    //   159: aload_0
    //   160: iload_1
    //   161: putfield Qnq : I
    //   164: getstatic OdI.Dne : [LOdI;
    //   167: iload_1
    //   168: aload_0
    //   169: aastore
    //   170: aload_0
    //   171: aload_0
    //   172: invokevirtual Dne : ()LFnk;
    //   175: putfield Dne : LFnk;
    //   178: aload_0
    //   179: getfield FWm : Ljava/util/List;
    //   182: new oIf
    //   185: dup
    //   186: ldc_w Pvd
    //   189: bipush #12
    //   191: iconst_4
    //   192: iconst_4
    //   193: invokespecial <init> : (Ljava/lang/Class;III)V
    //   196: invokeinterface add : (Ljava/lang/Object;)Z
    //   201: pop
    //   202: aload_0
    //   203: getfield FWm : Ljava/util/List;
    //   206: new oIf
    //   209: dup
    //   210: ldc_w fNv
    //   213: bipush #10
    //   215: iconst_4
    //   216: iconst_4
    //   217: invokespecial <init> : (Ljava/lang/Class;III)V
    //   220: invokeinterface add : (Ljava/lang/Object;)Z
    //   225: pop
    //   226: aload_0
    //   227: getfield FWm : Ljava/util/List;
    //   230: new oIf
    //   233: dup
    //   234: ldc_w GRq
    //   237: bipush #10
    //   239: iconst_4
    //   240: iconst_4
    //   241: invokespecial <init> : (Ljava/lang/Class;III)V
    //   244: invokeinterface add : (Ljava/lang/Object;)Z
    //   249: pop
    //   250: aload_0
    //   251: getfield FWm : Ljava/util/List;
    //   254: new oIf
    //   257: dup
    //   258: ldc_w wBN
    //   261: bipush #8
    //   263: iconst_4
    //   264: iconst_4
    //   265: invokespecial <init> : (Ljava/lang/Class;III)V
    //   268: invokeinterface add : (Ljava/lang/Object;)Z
    //   273: pop
    //   274: aload_0
    //   275: getfield Dne : Ljava/util/List;
    //   278: new oIf
    //   281: dup
    //   282: ldc_w osi
    //   285: bipush #10
    //   287: iconst_4
    //   288: iconst_4
    //   289: invokespecial <init> : (Ljava/lang/Class;III)V
    //   292: invokeinterface add : (Ljava/lang/Object;)Z
    //   297: pop
    //   298: aload_0
    //   299: getfield Dne : Ljava/util/List;
    //   302: new oIf
    //   305: dup
    //   306: ldc_w zxd
    //   309: bipush #10
    //   311: iconst_4
    //   312: iconst_4
    //   313: invokespecial <init> : (Ljava/lang/Class;III)V
    //   316: invokeinterface add : (Ljava/lang/Object;)Z
    //   321: pop
    //   322: aload_0
    //   323: getfield Dne : Ljava/util/List;
    //   326: new oIf
    //   329: dup
    //   330: ldc_w yXX
    //   333: bipush #10
    //   335: iconst_4
    //   336: iconst_4
    //   337: invokespecial <init> : (Ljava/lang/Class;III)V
    //   340: invokeinterface add : (Ljava/lang/Object;)Z
    //   345: pop
    //   346: aload_0
    //   347: getfield Dne : Ljava/util/List;
    //   350: new oIf
    //   353: dup
    //   354: ldc_w gls
    //   357: bipush #10
    //   359: iconst_4
    //   360: iconst_4
    //   361: invokespecial <init> : (Ljava/lang/Class;III)V
    //   364: invokeinterface add : (Ljava/lang/Object;)Z
    //   369: pop
    //   370: aload_0
    //   371: getfield Dne : Ljava/util/List;
    //   374: new oIf
    //   377: dup
    //   378: ldc_w Tgj
    //   381: bipush #10
    //   383: iconst_4
    //   384: iconst_4
    //   385: invokespecial <init> : (Ljava/lang/Class;III)V
    //   388: invokeinterface add : (Ljava/lang/Object;)Z
    //   393: pop
    //   394: aload_0
    //   395: getfield Dne : Ljava/util/List;
    //   398: new oIf
    //   401: dup
    //   402: ldc_w iGp
    //   405: iconst_1
    //   406: iconst_1
    //   407: iconst_4
    //   408: invokespecial <init> : (Ljava/lang/Class;III)V
    //   411: invokeinterface add : (Ljava/lang/Object;)Z
    //   416: pop
    //   417: aload_0
    //   418: getfield bzF : Ljava/util/List;
    //   421: new oIf
    //   424: dup
    //   425: ldc_w Xxe
    //   428: bipush #10
    //   430: iconst_4
    //   431: iconst_4
    //   432: invokespecial <init> : (Ljava/lang/Class;III)V
    //   435: invokeinterface add : (Ljava/lang/Object;)Z
    //   440: pop
    //   441: aload_0
    //   442: getfield Qnq : Ljava/util/List;
    //   445: new oIf
    //   448: dup
    //   449: ldc_w oaw
    //   452: bipush #10
    //   454: bipush #8
    //   456: bipush #8
    //   458: invokespecial <init> : (Ljava/lang/Class;III)V
    //   461: invokeinterface add : (Ljava/lang/Object;)Z
    //   466: pop
    //   467: return
  }
}


/* Location:              C:\Users\fract\Downloads\ERROR422.jar!\OdI.class
 * Java compiler version: 8 (52.0)
 * JD-Core Version:       1.1.3
 */