import java.util.ArrayList;

public class OEk {
  static int bzF;
  
  public static int FWm;
  
  public static ArrayList Dne = new ArrayList();
  
  public static ArrayList FWm = new ArrayList();
  
  public static int Dne;
  
  public static void FWm() {
    // Byte code:
    //   0: getstatic OEk.bzF : I
    //   3: bipush #13
    //   5: if_icmpne -> 18
    //   8: invokestatic Dne : ()V
    //   11: iconst_0
    //   12: putstatic OEk.bzF : I
    //   15: goto -> 26
    //   18: getstatic OEk.bzF : I
    //   21: iconst_1
    //   22: iadd
    //   23: putstatic OEk.bzF : I
    //   26: iconst_0
    //   27: istore_0
    //   28: iconst_0
    //   29: istore_1
    //   30: iconst_0
    //   31: istore_2
    //   32: iconst_0
    //   33: istore_3
    //   34: iload_3
    //   35: getstatic OEk.FWm : I
    //   38: bipush #6
    //   40: idiv
    //   41: iconst_1
    //   42: iadd
    //   43: if_icmpge -> 118
    //   46: iconst_0
    //   47: istore #4
    //   49: iload #4
    //   51: getstatic OEk.Dne : I
    //   54: bipush #10
    //   56: idiv
    //   57: if_icmpge -> 107
    //   60: getstatic QXI.Dne : Lnet/minecraft/client/Minecraft;
    //   63: getfield Dne : LmsA;
    //   66: getstatic OEk.Dne : Ljava/util/ArrayList;
    //   69: iload_2
    //   70: invokevirtual get : (I)Ljava/lang/Object;
    //   73: checkcast java/lang/String
    //   76: iload_0
    //   77: iload_1
    //   78: getstatic OEk.FWm : Ljava/util/ArrayList;
    //   81: iload_2
    //   82: invokevirtual get : (I)Ljava/lang/Object;
    //   85: checkcast java/lang/Integer
    //   88: invokevirtual intValue : ()I
    //   91: invokevirtual FWm : (Ljava/lang/String;III)I
    //   94: pop
    //   95: iinc #1, 11
    //   98: iinc #2, 1
    //   101: iinc #4, 1
    //   104: goto -> 49
    //   107: iinc #0, 6
    //   110: iconst_0
    //   111: istore_1
    //   112: iinc #3, 1
    //   115: goto -> 34
    //   118: return
  }
  
  public static void Dne() {
    // Byte code:
    //   0: getstatic OEk.Dne : Ljava/util/ArrayList;
    //   3: invokevirtual clear : ()V
    //   6: getstatic OEk.FWm : Ljava/util/ArrayList;
    //   9: invokevirtual clear : ()V
    //   12: getstatic QXI.Dne : Lnet/minecraft/client/Minecraft;
    //   15: getfield Dne : LqVZ;
    //   18: getfield FWm : I
    //   21: putstatic OEk.FWm : I
    //   24: getstatic QXI.Dne : Lnet/minecraft/client/Minecraft;
    //   27: getfield Dne : LqVZ;
    //   30: getfield bzF : I
    //   33: putstatic OEk.Dne : I
    //   36: iconst_0
    //   37: istore_0
    //   38: iload_0
    //   39: getstatic OEk.FWm : I
    //   42: bipush #6
    //   44: idiv
    //   45: iconst_1
    //   46: iadd
    //   47: getstatic OEk.Dne : I
    //   50: bipush #10
    //   52: idiv
    //   53: imul
    //   54: if_icmpge -> 99
    //   57: getstatic OEk.Dne : Ljava/util/ArrayList;
    //   60: getstatic QXI.Dne : [C
    //   63: getstatic QXI.Dne : [C
    //   66: arraylength
    //   67: invokestatic Dne : (I)I
    //   70: caload
    //   71: invokestatic toString : (C)Ljava/lang/String;
    //   74: invokevirtual add : (Ljava/lang/Object;)Z
    //   77: pop
    //   78: getstatic OEk.FWm : Ljava/util/ArrayList;
    //   81: ldc 16777215
    //   83: invokestatic Dne : (I)I
    //   86: invokestatic valueOf : (I)Ljava/lang/Integer;
    //   89: invokevirtual add : (Ljava/lang/Object;)Z
    //   92: pop
    //   93: iinc #0, 1
    //   96: goto -> 38
    //   99: return
  }
}


/* Location:              C:\Users\fract\Downloads\ERROR422.jar!\OEk.class
 * Java compiler version: 8 (52.0)
 * JD-Core Version:       1.1.3
 */