public class onZ {
  public final MqS Dne;
  
  public int aFZ;
  
  private final int Dne;
  
  public int zGp;
  
  public int Qnq;
  
  public void Dne(NMq paramNMq) {
    // Byte code:
    //   0: aload_0
    //   1: getfield Dne : LMqS;
    //   4: aload_0
    //   5: getfield Dne : I
    //   8: aload_1
    //   9: invokeinterface Dne : (ILNMq;)V
    //   14: aload_0
    //   15: invokevirtual Dne : ()V
    //   18: return
  }
  
  public NMq Dne(int paramInt) {
    // Byte code:
    //   0: aload_0
    //   1: getfield Dne : LMqS;
    //   4: aload_0
    //   5: getfield Dne : I
    //   8: iload_1
    //   9: invokeinterface Dne : (II)LNMq;
    //   14: areturn
  }
  
  public boolean Dne(MqS paramMqS, int paramInt) {
    return (paramMqS == this.Dne && paramInt == this.Dne);
  }
  
  public int Dne() {
    // Byte code:
    //   0: aload_0
    //   1: getfield Dne : LMqS;
    //   4: invokeinterface aFZ : ()I
    //   9: ireturn
  }
  
  public void Dne(NMq paramNMq1, NMq paramNMq2) {
    if (paramNMq1 != null && paramNMq2 != null && paramNMq1.bzF == paramNMq2.bzF) {
      int i = paramNMq2.Dne - paramNMq1.Dne;
      if (i > 0)
        Dne(paramNMq1, i); 
    } 
  }
  
  protected void FWm(NMq paramNMq) {}
  
  public boolean Dne(NMq paramNMq) {
    return true;
  }
  
  public gDn Dne() {
    return null;
  }
  
  public NMq Dne() {
    // Byte code:
    //   0: aload_0
    //   1: getfield Dne : LMqS;
    //   4: aload_0
    //   5: getfield Dne : I
    //   8: invokeinterface Dne : (I)LNMq;
    //   13: areturn
  }
  
  public void Dne(FiG paramFiG, NMq paramNMq) {
    Dne();
  }
  
  public onZ(MqS paramMqS, int paramInt1, int paramInt2, int paramInt3) {
    this.Dne = paramMqS;
    this.Dne = paramInt1;
    this.aFZ = paramInt2;
    this.zGp = paramInt3;
  }
  
  public boolean Dne(FiG paramFiG) {
    return true;
  }
  
  public void Dne() {
    // Byte code:
    //   0: aload_0
    //   1: getfield Dne : LMqS;
    //   4: invokeinterface a_ : ()V
    //   9: return
  }
  
  protected void Dne(NMq paramNMq, int paramInt) {}
  
  public boolean Dne() {
    return (Dne() != null);
  }
}


/* Location:              C:\Users\fract\Downloads\ERROR422.jar!\onZ.class
 * Java compiler version: 8 (52.0)
 * JD-Core Version:       1.1.3
 */