import java.util.Arrays;
import java.util.Collection;
import java.util.List;

public class PJQ extends FiG implements mXX {
  private int EWz;
  
  private irb Dne;
  
  public boolean Dne;
  
  public int Dne;
  
  public double FWm;
  
  private int ICU;
  
  private boolean Fnk;
  
  public final List Dne;
  
  public Jwh Dne;
  
  private int FWm;
  
  private int LVR;
  
  private int rPc;
  
  private int haP;
  
  public dyC Dne;
  
  private boolean RPx;
  
  public Tnv Dne;
  
  public boolean FWm;
  
  public final List FWm;
  
  public double Dne;
  
  private int qrB;
  
  public void Dne(MqS paramMqS) {
    // Byte code:
    //   0: aload_0
    //   1: getfield FWm : LPdb;
    //   4: aload_0
    //   5: getfield Dne : LPdb;
    //   8: if_acmpeq -> 15
    //   11: aload_0
    //   12: invokevirtual aFZ : ()V
    //   15: aload_0
    //   16: invokespecial qMV : ()V
    //   19: aload_0
    //   20: getfield Dne : LTnv;
    //   23: new XGq
    //   26: dup
    //   27: aload_0
    //   28: getfield ICU : I
    //   31: iconst_0
    //   32: aload_1
    //   33: invokeinterface b_ : ()Ljava/lang/String;
    //   38: aload_1
    //   39: invokeinterface Qnq : ()I
    //   44: aload_1
    //   45: invokeinterface d_ : ()Z
    //   50: invokespecial <init> : (IILjava/lang/String;IZ)V
    //   53: invokevirtual Dne : (LNER;)V
    //   56: aload_0
    //   57: new ZqW
    //   60: dup
    //   61: aload_0
    //   62: getfield Dne : LMOS;
    //   65: aload_1
    //   66: invokespecial <init> : (LMqS;LMqS;)V
    //   69: putfield FWm : LPdb;
    //   72: aload_0
    //   73: getfield FWm : LPdb;
    //   76: aload_0
    //   77: getfield ICU : I
    //   80: putfield Dne : I
    //   83: aload_0
    //   84: getfield FWm : LPdb;
    //   87: aload_0
    //   88: invokevirtual Dne : (LmXX;)V
    //   91: return
  }
  
  public void FWm(sMa paramsMa) {
    Dne().Dne().FWm(this, new UVb(paramsMa, 7));
  }
  
  public void DyG() {
    // Byte code:
    //   0: aload_0
    //   1: getfield Dne : LTnv;
    //   4: ifnull -> 25
    //   7: aload_0
    //   8: getfield Dne : LTnv;
    //   11: new pSe
    //   14: dup
    //   15: aload_0
    //   16: getfield Dne : Luqg;
    //   19: invokespecial <init> : (Luqg;)V
    //   22: invokevirtual Dne : (LNER;)V
    //   25: return
  }
  
  protected void Dne(NAx paramNAx) {
    // Byte code:
    //   0: aload_0
    //   1: aload_1
    //   2: invokespecial Dne : (LNAx;)V
    //   5: aload_0
    //   6: getfield Dne : LTnv;
    //   9: new ziQ
    //   12: dup
    //   13: aload_0
    //   14: getfield aFZ : I
    //   17: aload_1
    //   18: invokespecial <init> : (ILNAx;)V
    //   21: invokevirtual Dne : (LNER;)V
    //   24: return
  }
  
  public void Dne(FiG paramFiG, boolean paramBoolean) {
    super.Dne(paramFiG, paramBoolean);
    this.rPc = -1;
    this.FWm = -1;
    this.EWz = -1;
    this.FWm.addAll(((PJQ)paramFiG).FWm);
  }
  
  public void Dne(Pdb paramPdb, int paramInt1, int paramInt2) {
    // Byte code:
    //   0: aload_0
    //   1: getfield Dne : LTnv;
    //   4: new QKM
    //   7: dup
    //   8: aload_1
    //   9: getfield Dne : I
    //   12: iload_2
    //   13: iload_3
    //   14: invokespecial <init> : (III)V
    //   17: invokevirtual Dne : (LNER;)V
    //   20: return
  }
  
  public boolean Dne(zBn paramzBn, int paramInt) {
    // Byte code:
    //   0: aload_0
    //   1: invokevirtual EyB : ()Z
    //   4: ifeq -> 9
    //   7: iconst_0
    //   8: ireturn
    //   9: aload_0
    //   10: getfield Dne : LJwh;
    //   13: invokevirtual Qnq : ()Z
    //   16: ifeq -> 45
    //   19: aload_0
    //   20: getfield Dne : LJwh;
    //   23: invokevirtual qLR : ()Z
    //   26: ifeq -> 45
    //   29: ldc 'fall'
    //   31: aload_1
    //   32: getfield Dne : Ljava/lang/String;
    //   35: invokevirtual equals : (Ljava/lang/Object;)Z
    //   38: ifeq -> 45
    //   41: iconst_1
    //   42: goto -> 46
    //   45: iconst_0
    //   46: istore_3
    //   47: iload_3
    //   48: ifne -> 67
    //   51: aload_0
    //   52: getfield haP : I
    //   55: ifle -> 67
    //   58: aload_1
    //   59: getstatic zBn.IjH : LzBn;
    //   62: if_acmpeq -> 67
    //   65: iconst_0
    //   66: ireturn
    //   67: aload_1
    //   68: instanceof Kgw
    //   71: ifeq -> 145
    //   74: aload_1
    //   75: invokevirtual FWm : ()LsMa;
    //   78: astore #4
    //   80: aload #4
    //   82: instanceof FiG
    //   85: ifeq -> 102
    //   88: aload_0
    //   89: aload #4
    //   91: checkcast FiG
    //   94: invokevirtual Dne : (LFiG;)Z
    //   97: ifne -> 102
    //   100: iconst_0
    //   101: ireturn
    //   102: aload #4
    //   104: instanceof hhc
    //   107: ifeq -> 145
    //   110: aload #4
    //   112: checkcast hhc
    //   115: astore #5
    //   117: aload #5
    //   119: getfield bzF : LsMa;
    //   122: instanceof FiG
    //   125: ifeq -> 145
    //   128: aload_0
    //   129: aload #5
    //   131: getfield bzF : LsMa;
    //   134: checkcast FiG
    //   137: invokevirtual Dne : (LFiG;)Z
    //   140: ifne -> 145
    //   143: iconst_0
    //   144: ireturn
    //   145: aload_0
    //   146: aload_1
    //   147: iload_2
    //   148: invokespecial Dne : (LzBn;I)Z
    //   151: ireturn
  }
  
  public boolean Dne(FiG paramFiG) {
    // Byte code:
    //   0: aload_0
    //   1: getfield Dne : LJwh;
    //   4: invokevirtual qLR : ()Z
    //   7: ifne -> 14
    //   10: iconst_0
    //   11: goto -> 19
    //   14: aload_0
    //   15: aload_1
    //   16: invokespecial Dne : (LFiG;)Z
    //   19: ireturn
  }
  
  public void bzF(sMa paramsMa) {
    // Byte code:
    //   0: aload_0
    //   1: aload_1
    //   2: invokespecial bzF : (LsMa;)V
    //   5: aload_0
    //   6: getfield Dne : LTnv;
    //   9: new YVz
    //   12: dup
    //   13: aload_0
    //   14: aload_0
    //   15: getfield FWm : LsMa;
    //   18: invokespecial <init> : (LsMa;LsMa;)V
    //   21: invokevirtual Dne : (LNER;)V
    //   24: aload_0
    //   25: getfield Dne : LTnv;
    //   28: aload_0
    //   29: getfield div : D
    //   32: aload_0
    //   33: getfield IjH : D
    //   36: aload_0
    //   37: getfield mrb : D
    //   40: aload_0
    //   41: getfield mrb : F
    //   44: aload_0
    //   45: getfield XHL : F
    //   48: invokevirtual Dne : (DDDFF)V
    //   51: return
  }
  
  public NSR Dne(int paramInt1, int paramInt2, int paramInt3) {
    // Byte code:
    //   0: aload_0
    //   1: iload_1
    //   2: iload_2
    //   3: iload_3
    //   4: invokespecial Dne : (III)LNSR;
    //   7: astore #4
    //   9: aload #4
    //   11: getstatic NSR.Dne : LNSR;
    //   14: if_acmpne -> 80
    //   17: new kwp
    //   20: dup
    //   21: aload_0
    //   22: iconst_0
    //   23: iload_1
    //   24: iload_2
    //   25: iload_3
    //   26: invokespecial <init> : (LsMa;IIII)V
    //   29: astore #5
    //   31: aload_0
    //   32: invokevirtual Dne : ()LRAN;
    //   35: invokevirtual Dne : ()Lclp;
    //   38: aload_0
    //   39: aload #5
    //   41: invokevirtual Dne : (LsMa;LNER;)V
    //   44: aload_0
    //   45: getfield Dne : LTnv;
    //   48: aload_0
    //   49: getfield div : D
    //   52: aload_0
    //   53: getfield IjH : D
    //   56: aload_0
    //   57: getfield mrb : D
    //   60: aload_0
    //   61: getfield mrb : F
    //   64: aload_0
    //   65: getfield XHL : F
    //   68: invokevirtual Dne : (DDDFF)V
    //   71: aload_0
    //   72: getfield Dne : LTnv;
    //   75: aload #5
    //   77: invokevirtual Dne : (LNER;)V
    //   80: aload #4
    //   82: areturn
  }
  
  public void Qnq(int paramInt) {
    // Byte code:
    //   0: aload_0
    //   1: getfield qLR : I
    //   4: iconst_1
    //   5: if_icmpne -> 52
    //   8: iload_1
    //   9: iconst_1
    //   10: if_icmpne -> 52
    //   13: aload_0
    //   14: getstatic qlg.oIf : LAuk;
    //   17: invokevirtual Dne : (LRLC;)V
    //   20: aload_0
    //   21: getfield Dne : LQnq;
    //   24: aload_0
    //   25: invokevirtual bzF : (LsMa;)V
    //   28: aload_0
    //   29: iconst_1
    //   30: putfield FWm : Z
    //   33: aload_0
    //   34: getfield Dne : LTnv;
    //   37: new Tnn
    //   40: dup
    //   41: iconst_4
    //   42: iconst_0
    //   43: invokespecial <init> : (II)V
    //   46: invokevirtual Dne : (LNER;)V
    //   49: goto -> 150
    //   52: aload_0
    //   53: getfield qLR : I
    //   56: iconst_1
    //   57: if_icmpne -> 116
    //   60: iload_1
    //   61: ifne -> 116
    //   64: aload_0
    //   65: getstatic qlg.OdI : LAuk;
    //   68: invokevirtual Dne : (LRLC;)V
    //   71: aload_0
    //   72: getfield Dne : LJwh;
    //   75: iload_1
    //   76: invokevirtual Dne : (I)LRAN;
    //   79: invokevirtual FWm : ()LiSh;
    //   82: astore_2
    //   83: aload_2
    //   84: ifnull -> 111
    //   87: aload_0
    //   88: getfield Dne : LTnv;
    //   91: aload_2
    //   92: getfield Dne : I
    //   95: i2d
    //   96: aload_2
    //   97: getfield FWm : I
    //   100: i2d
    //   101: aload_2
    //   102: getfield bzF : I
    //   105: i2d
    //   106: fconst_0
    //   107: fconst_0
    //   108: invokevirtual Dne : (DDDFF)V
    //   111: iconst_1
    //   112: istore_1
    //   113: goto -> 123
    //   116: aload_0
    //   117: getstatic qlg.Vxn : LAuk;
    //   120: invokevirtual Dne : (LRLC;)V
    //   123: aload_0
    //   124: getfield Dne : LJwh;
    //   127: invokevirtual Dne : ()LdzN;
    //   130: aload_0
    //   131: iload_1
    //   132: invokevirtual Dne : (LPJQ;I)V
    //   135: aload_0
    //   136: iconst_m1
    //   137: putfield rPc : I
    //   140: aload_0
    //   141: iconst_m1
    //   142: putfield FWm : I
    //   145: aload_0
    //   146: iconst_m1
    //   147: putfield EWz : I
    //   150: return
  }
  
  public void Dne(YzO paramYzO, String paramString) {
    // Byte code:
    //   0: aload_0
    //   1: invokespecial qMV : ()V
    //   4: aload_0
    //   5: new ema
    //   8: dup
    //   9: aload_0
    //   10: getfield Dne : LMOS;
    //   13: aload_1
    //   14: aload_0
    //   15: getfield Dne : LQnq;
    //   18: invokespecial <init> : (LMOS;LYzO;LQnq;)V
    //   21: putfield FWm : LPdb;
    //   24: aload_0
    //   25: getfield FWm : LPdb;
    //   28: aload_0
    //   29: getfield ICU : I
    //   32: putfield Dne : I
    //   35: aload_0
    //   36: getfield FWm : LPdb;
    //   39: aload_0
    //   40: invokevirtual Dne : (LmXX;)V
    //   43: aload_0
    //   44: getfield FWm : LPdb;
    //   47: checkcast ema
    //   50: invokevirtual Dne : ()LJmn;
    //   53: astore_3
    //   54: aload_0
    //   55: getfield Dne : LTnv;
    //   58: new XGq
    //   61: dup
    //   62: aload_0
    //   63: getfield ICU : I
    //   66: bipush #6
    //   68: aload_2
    //   69: ifnonnull -> 78
    //   72: ldc_w ''
    //   75: goto -> 79
    //   78: aload_2
    //   79: aload_3
    //   80: invokevirtual Qnq : ()I
    //   83: aload_2
    //   84: ifnull -> 91
    //   87: iconst_1
    //   88: goto -> 92
    //   91: iconst_0
    //   92: invokespecial <init> : (IILjava/lang/String;IZ)V
    //   95: invokevirtual Dne : (LNER;)V
    //   98: aload_1
    //   99: aload_0
    //   100: invokeinterface Dne : (LFiG;)LybO;
    //   105: astore #4
    //   107: aload #4
    //   109: ifnull -> 180
    //   112: new java/io/ByteArrayOutputStream
    //   115: dup
    //   116: invokespecial <init> : ()V
    //   119: astore #5
    //   121: new java/io/DataOutputStream
    //   124: dup
    //   125: aload #5
    //   127: invokespecial <init> : (Ljava/io/OutputStream;)V
    //   130: astore #6
    //   132: aload #6
    //   134: aload_0
    //   135: getfield ICU : I
    //   138: invokevirtual writeInt : (I)V
    //   141: aload #4
    //   143: aload #6
    //   145: invokevirtual Dne : (Ljava/io/DataOutputStream;)V
    //   148: aload_0
    //   149: getfield Dne : LTnv;
    //   152: new FaB
    //   155: dup
    //   156: ldc_w 'MC|TrList'
    //   159: aload #5
    //   161: invokevirtual toByteArray : ()[B
    //   164: invokespecial <init> : (Ljava/lang/String;[B)V
    //   167: invokevirtual Dne : (LNER;)V
    //   170: goto -> 180
    //   173: astore #5
    //   175: aload #5
    //   177: invokevirtual printStackTrace : ()V
    //   180: return
    // Exception table:
    //   from	to	target	type
    //   112	170	173	java/io/IOException
  }
  
  public void Dne(yUQ paramyUQ) {
    // Byte code:
    //   0: aload_0
    //   1: getfield Dne : Lirb;
    //   4: invokevirtual Dne : ()Ljava/util/TreeMap;
    //   7: aload_1
    //   8: invokevirtual Dne : ()Ljava/lang/String;
    //   11: invokevirtual containsKey : (Ljava/lang/Object;)Z
    //   14: ifeq -> 29
    //   17: aload_0
    //   18: getfield Dne : Lirb;
    //   21: aload_1
    //   22: invokevirtual Dne : ()Ljava/lang/String;
    //   25: iconst_0
    //   26: invokevirtual Dne : (Ljava/lang/String;Z)V
    //   29: sipush #256
    //   32: aload_1
    //   33: invokevirtual FWm : ()I
    //   36: ishr
    //   37: istore_2
    //   38: iload_2
    //   39: iconst_3
    //   40: if_icmple -> 54
    //   43: iload_2
    //   44: bipush #15
    //   46: if_icmpge -> 54
    //   49: aload_0
    //   50: iload_2
    //   51: putfield qrB : I
    //   54: aload_0
    //   55: aload_1
    //   56: invokevirtual bzF : ()I
    //   59: putfield LVR : I
    //   62: aload_0
    //   63: aload_1
    //   64: invokevirtual bzF : ()Z
    //   67: putfield Fnk : Z
    //   70: aload_0
    //   71: getfield Dne : LJwh;
    //   74: invokevirtual Zpi : ()Z
    //   77: ifeq -> 108
    //   80: aload_0
    //   81: getfield Dne : LJwh;
    //   84: invokevirtual mrb : ()Ljava/lang/String;
    //   87: aload_0
    //   88: getfield aFZ : Ljava/lang/String;
    //   91: invokevirtual equals : (Ljava/lang/Object;)Z
    //   94: ifeq -> 108
    //   97: aload_0
    //   98: getfield Dne : LJwh;
    //   101: aload_1
    //   102: invokevirtual Qnq : ()I
    //   105: invokevirtual FWm : (I)V
    //   108: aload_0
    //   109: iconst_1
    //   110: aload_1
    //   111: invokevirtual Qnq : ()Z
    //   114: ifne -> 121
    //   117: iconst_1
    //   118: goto -> 122
    //   121: iconst_0
    //   122: invokevirtual FWm : (IZ)V
    //   125: return
  }
  
  protected void Dne(double paramDouble, boolean paramBoolean) {}
  
  public void udO() {
    this.FWm.Dne(this);
    this.FWm = this.Dne;
  }
  
  public PJQ(Jwh paramJwh, Qnq paramQnq, String paramString, dyC paramdyC) {
    // Byte code:
    //   0: aload_0
    //   1: aload_2
    //   2: invokespecial <init> : (LQnq;)V
    //   5: aload_0
    //   6: new irb
    //   9: dup
    //   10: ldc_w 'en_US'
    //   13: invokespecial <init> : (Ljava/lang/String;)V
    //   16: putfield Dne : Lirb;
    //   19: aload_0
    //   20: new java/util/LinkedList
    //   23: dup
    //   24: invokespecial <init> : ()V
    //   27: putfield Dne : Ljava/util/List;
    //   30: aload_0
    //   31: new java/util/LinkedList
    //   34: dup
    //   35: invokespecial <init> : ()V
    //   38: putfield FWm : Ljava/util/List;
    //   41: aload_0
    //   42: ldc_w -99999999
    //   45: putfield FWm : I
    //   48: aload_0
    //   49: ldc_w -99999999
    //   52: putfield EWz : I
    //   55: aload_0
    //   56: iconst_1
    //   57: putfield RPx : Z
    //   60: aload_0
    //   61: ldc_w -99999999
    //   64: putfield rPc : I
    //   67: aload_0
    //   68: bipush #60
    //   70: putfield haP : I
    //   73: aload_0
    //   74: iconst_0
    //   75: putfield qrB : I
    //   78: aload_0
    //   79: iconst_0
    //   80: putfield LVR : I
    //   83: aload_0
    //   84: iconst_1
    //   85: putfield Fnk : Z
    //   88: aload_0
    //   89: iconst_0
    //   90: putfield ICU : I
    //   93: aload_0
    //   94: iconst_0
    //   95: putfield FWm : Z
    //   98: aload #4
    //   100: aload_0
    //   101: putfield Dne : LPJQ;
    //   104: aload_0
    //   105: aload #4
    //   107: putfield Dne : LdyC;
    //   110: aload_0
    //   111: aload_1
    //   112: invokevirtual Dne : ()LdzN;
    //   115: invokevirtual Qnq : ()I
    //   118: putfield qrB : I
    //   121: aload_2
    //   122: invokevirtual Dne : ()LiSh;
    //   125: astore #5
    //   127: aload #5
    //   129: getfield Dne : I
    //   132: istore #6
    //   134: aload #5
    //   136: getfield bzF : I
    //   139: istore #7
    //   141: aload #5
    //   143: getfield FWm : I
    //   146: istore #8
    //   148: aload_2
    //   149: getfield Dne : LJik;
    //   152: getfield FWm : Z
    //   155: ifne -> 232
    //   158: aload_2
    //   159: invokevirtual Dne : ()LxoY;
    //   162: invokevirtual Dne : ()LXHL;
    //   165: getstatic XHL.Qnq : LXHL;
    //   168: if_acmpeq -> 232
    //   171: iconst_5
    //   172: aload_1
    //   173: invokevirtual aFZ : ()I
    //   176: bipush #6
    //   178: isub
    //   179: invokestatic max : (II)I
    //   182: istore #9
    //   184: iload #6
    //   186: aload_0
    //   187: getfield Dne : Ljava/util/Random;
    //   190: iload #9
    //   192: iconst_2
    //   193: imul
    //   194: invokevirtual nextInt : (I)I
    //   197: iload #9
    //   199: isub
    //   200: iadd
    //   201: istore #6
    //   203: iload #7
    //   205: aload_0
    //   206: getfield Dne : Ljava/util/Random;
    //   209: iload #9
    //   211: iconst_2
    //   212: imul
    //   213: invokevirtual nextInt : (I)I
    //   216: iload #9
    //   218: isub
    //   219: iadd
    //   220: istore #7
    //   222: aload_2
    //   223: iload #6
    //   225: iload #7
    //   227: invokevirtual aFZ : (II)I
    //   230: istore #8
    //   232: aload_0
    //   233: aload_1
    //   234: putfield Dne : LJwh;
    //   237: aload_0
    //   238: fconst_0
    //   239: putfield FfS : F
    //   242: aload_0
    //   243: aload_3
    //   244: putfield aFZ : Ljava/lang/String;
    //   247: aload_0
    //   248: fconst_0
    //   249: putfield udO : F
    //   252: aload_0
    //   253: iload #6
    //   255: i2d
    //   256: ldc2_w 0.5
    //   259: dadd
    //   260: iload #8
    //   262: i2d
    //   263: iload #7
    //   265: i2d
    //   266: ldc2_w 0.5
    //   269: dadd
    //   270: fconst_0
    //   271: fconst_0
    //   272: invokevirtual FWm : (DDDFF)V
    //   275: aload_2
    //   276: aload_0
    //   277: aload_0
    //   278: getfield Dne : LbSp;
    //   281: invokevirtual Dne : (LsMa;LbSp;)Ljava/util/List;
    //   284: invokeinterface isEmpty : ()Z
    //   289: ifne -> 313
    //   292: aload_0
    //   293: aload_0
    //   294: getfield div : D
    //   297: aload_0
    //   298: getfield IjH : D
    //   301: dconst_1
    //   302: dadd
    //   303: aload_0
    //   304: getfield mrb : D
    //   307: invokevirtual bzF : (DDD)V
    //   310: goto -> 275
    //   313: return
  }
  
  public void Dne(String paramString, int paramInt) {
    // Byte code:
    //   0: new java/lang/StringBuilder
    //   3: dup
    //   4: invokespecial <init> : ()V
    //   7: aload_1
    //   8: invokevirtual append : (Ljava/lang/String;)Ljava/lang/StringBuilder;
    //   11: ldc_w ' '
    //   14: invokevirtual append : (Ljava/lang/String;)Ljava/lang/StringBuilder;
    //   17: iload_2
    //   18: invokevirtual append : (I)Ljava/lang/StringBuilder;
    //   21: invokevirtual toString : ()Ljava/lang/String;
    //   24: astore_3
    //   25: aload_0
    //   26: getfield Dne : LTnv;
    //   29: new FaB
    //   32: dup
    //   33: ldc_w 'MC|TPack'
    //   36: aload_3
    //   37: invokevirtual getBytes : ()[B
    //   40: invokespecial <init> : (Ljava/lang/String;[B)V
    //   43: invokevirtual Dne : (LNER;)V
    //   46: return
  }
  
  public void FWm(int paramInt) {
    super.FWm(paramInt);
    this.rPc = -1;
  }
  
  public String FWm() {
    null = this.Dne.Dne.Dne().toString();
    null = null.substring(null.indexOf("/") + 1);
    return null.substring(0, null.indexOf(":"));
  }
  
  public void Zpi() {
    // Byte code:
    //   0: aload_0
    //   1: invokespecial Dne : ()V
    //   4: iconst_0
    //   5: istore_1
    //   6: iload_1
    //   7: aload_0
    //   8: getfield Dne : LMOS;
    //   11: invokevirtual Qnq : ()I
    //   14: if_icmpge -> 94
    //   17: aload_0
    //   18: getfield Dne : LMOS;
    //   21: iload_1
    //   22: invokevirtual Dne : (I)LNMq;
    //   25: astore_2
    //   26: aload_2
    //   27: ifnull -> 88
    //   30: getstatic dEr.Dne : [LdEr;
    //   33: aload_2
    //   34: getfield bzF : I
    //   37: aaload
    //   38: invokevirtual Qnq : ()Z
    //   41: ifeq -> 88
    //   44: aload_0
    //   45: getfield Dne : LTnv;
    //   48: invokevirtual Dne : ()I
    //   51: iconst_5
    //   52: if_icmpgt -> 88
    //   55: getstatic dEr.Dne : [LdEr;
    //   58: aload_2
    //   59: getfield bzF : I
    //   62: aaload
    //   63: checkcast wJb
    //   66: aload_2
    //   67: aload_0
    //   68: getfield Dne : LQnq;
    //   71: aload_0
    //   72: invokevirtual Dne : (LNMq;LQnq;LFiG;)LNER;
    //   75: astore_3
    //   76: aload_3
    //   77: ifnull -> 88
    //   80: aload_0
    //   81: getfield Dne : LTnv;
    //   84: aload_3
    //   85: invokevirtual Dne : (LNER;)V
    //   88: iinc #1, 1
    //   91: goto -> 6
    //   94: aload_0
    //   95: invokevirtual XHL : ()I
    //   98: aload_0
    //   99: getfield FWm : I
    //   102: if_icmpne -> 143
    //   105: aload_0
    //   106: getfield EWz : I
    //   109: aload_0
    //   110: getfield Dne : LSCY;
    //   113: invokevirtual Dne : ()I
    //   116: if_icmpne -> 143
    //   119: aload_0
    //   120: getfield Dne : LSCY;
    //   123: invokevirtual Dne : ()F
    //   126: fconst_0
    //   127: fcmpl
    //   128: ifne -> 135
    //   131: iconst_1
    //   132: goto -> 136
    //   135: iconst_0
    //   136: aload_0
    //   137: getfield RPx : Z
    //   140: if_icmpeq -> 215
    //   143: aload_0
    //   144: getfield Dne : LTnv;
    //   147: new zqT
    //   150: dup
    //   151: aload_0
    //   152: invokevirtual XHL : ()I
    //   155: aload_0
    //   156: getfield Dne : LSCY;
    //   159: invokevirtual Dne : ()I
    //   162: aload_0
    //   163: getfield Dne : LSCY;
    //   166: invokevirtual Dne : ()F
    //   169: invokespecial <init> : (IIF)V
    //   172: invokevirtual Dne : (LNER;)V
    //   175: aload_0
    //   176: aload_0
    //   177: invokevirtual XHL : ()I
    //   180: putfield FWm : I
    //   183: aload_0
    //   184: aload_0
    //   185: getfield Dne : LSCY;
    //   188: invokevirtual Dne : ()I
    //   191: putfield EWz : I
    //   194: aload_0
    //   195: aload_0
    //   196: getfield Dne : LSCY;
    //   199: invokevirtual Dne : ()F
    //   202: fconst_0
    //   203: fcmpl
    //   204: ifne -> 211
    //   207: iconst_1
    //   208: goto -> 212
    //   211: iconst_0
    //   212: putfield RPx : Z
    //   215: aload_0
    //   216: getfield mlD : I
    //   219: aload_0
    //   220: getfield rPc : I
    //   223: if_icmpeq -> 260
    //   226: aload_0
    //   227: aload_0
    //   228: getfield mlD : I
    //   231: putfield rPc : I
    //   234: aload_0
    //   235: getfield Dne : LTnv;
    //   238: new WXC
    //   241: dup
    //   242: aload_0
    //   243: getfield iNQ : F
    //   246: aload_0
    //   247: getfield mlD : I
    //   250: aload_0
    //   251: getfield eHV : I
    //   254: invokespecial <init> : (FII)V
    //   257: invokevirtual Dne : (LNER;)V
    //   260: goto -> 294
    //   263: astore_1
    //   264: aload_1
    //   265: ldc_w 'Ticking player'
    //   268: invokestatic Dne : (Ljava/lang/Throwable;Ljava/lang/String;)LMcM;
    //   271: astore_2
    //   272: aload_2
    //   273: ldc_w 'Player being ticked'
    //   276: invokevirtual Dne : (Ljava/lang/String;)LNoo;
    //   279: astore_3
    //   280: aload_0
    //   281: aload_3
    //   282: invokevirtual Dne : (LNoo;)V
    //   285: new kaJ
    //   288: dup
    //   289: aload_2
    //   290: invokespecial <init> : (LMcM;)V
    //   293: athrow
    //   294: return
    // Exception table:
    //   from	to	target	type
    //   0	260	263	java/lang/Throwable
  }
  
  public void bzF(int paramInt) {
    super.bzF(paramInt);
    Collection collection = Dne().Dne(PAf.aFZ);
    for (vfE vfE : collection) {
      Dne().Dne(Dne(), vfE).Dne(Arrays.asList(new FiG[] { this }));
    } 
  }
  
  public void ooe() {
    // Byte code:
    //   0: aload_0
    //   1: getfield Dne : LsMa;
    //   4: ifnull -> 15
    //   7: aload_0
    //   8: getfield Dne : LsMa;
    //   11: aload_0
    //   12: invokevirtual bzF : (LsMa;)V
    //   15: aload_0
    //   16: getfield vSL : Z
    //   19: ifeq -> 29
    //   22: aload_0
    //   23: iconst_1
    //   24: iconst_0
    //   25: iconst_0
    //   26: invokevirtual Dne : (ZZZ)V
    //   29: return
  }
  
  public void Dne(TpA paramTpA) {
    // Byte code:
    //   0: aload_0
    //   1: invokespecial qMV : ()V
    //   4: aload_0
    //   5: getfield Dne : LTnv;
    //   8: new XGq
    //   11: dup
    //   12: aload_0
    //   13: getfield ICU : I
    //   16: bipush #7
    //   18: aload_1
    //   19: invokevirtual b_ : ()Ljava/lang/String;
    //   22: aload_1
    //   23: invokevirtual Qnq : ()I
    //   26: aload_1
    //   27: invokevirtual d_ : ()Z
    //   30: invokespecial <init> : (IILjava/lang/String;IZ)V
    //   33: invokevirtual Dne : (LNER;)V
    //   36: aload_0
    //   37: new eSp
    //   40: dup
    //   41: aload_0
    //   42: getfield Dne : LMOS;
    //   45: aload_1
    //   46: invokespecial <init> : (LMOS;LTpA;)V
    //   49: putfield FWm : LPdb;
    //   52: aload_0
    //   53: getfield FWm : LPdb;
    //   56: aload_0
    //   57: getfield ICU : I
    //   60: putfield Dne : I
    //   63: aload_0
    //   64: getfield FWm : LPdb;
    //   67: aload_0
    //   68: invokevirtual Dne : (LmXX;)V
    //   71: return
  }
  
  public irb Dne() {
    return this.Dne;
  }
  
  public void trS() {
    this.FWm = -99999999;
  }
  
  public void Dne(RLC paramRLC, int paramInt) {
    // Byte code:
    //   0: aload_1
    //   1: ifnull -> 62
    //   4: aload_1
    //   5: getfield Dne : Z
    //   8: ifne -> 62
    //   11: iload_2
    //   12: bipush #100
    //   14: if_icmple -> 43
    //   17: aload_0
    //   18: getfield Dne : LTnv;
    //   21: new Raa
    //   24: dup
    //   25: aload_1
    //   26: getfield bzF : I
    //   29: bipush #100
    //   31: invokespecial <init> : (II)V
    //   34: invokevirtual Dne : (LNER;)V
    //   37: iinc #2, -100
    //   40: goto -> 11
    //   43: aload_0
    //   44: getfield Dne : LTnv;
    //   47: new Raa
    //   50: dup
    //   51: aload_1
    //   52: getfield bzF : I
    //   55: iload_2
    //   56: invokespecial <init> : (II)V
    //   59: invokevirtual Dne : (LNER;)V
    //   62: return
  }
  
  public void Dne() {
    // Byte code:
    //   0: aload_0
    //   1: getfield Dne : LdyC;
    //   4: invokevirtual Dne : ()V
    //   7: aload_0
    //   8: dup
    //   9: getfield haP : I
    //   12: iconst_1
    //   13: isub
    //   14: putfield haP : I
    //   17: aload_0
    //   18: getfield FWm : LPdb;
    //   21: invokevirtual Dne : ()V
    //   24: aload_0
    //   25: getfield FWm : Ljava/util/List;
    //   28: invokeinterface isEmpty : ()Z
    //   33: ifne -> 129
    //   36: aload_0
    //   37: getfield FWm : Ljava/util/List;
    //   40: invokeinterface size : ()I
    //   45: bipush #127
    //   47: invokestatic min : (II)I
    //   50: istore_1
    //   51: iload_1
    //   52: newarray int
    //   54: astore_2
    //   55: aload_0
    //   56: getfield FWm : Ljava/util/List;
    //   59: invokeinterface iterator : ()Ljava/util/Iterator;
    //   64: astore_3
    //   65: iconst_0
    //   66: istore #4
    //   68: aload_3
    //   69: invokeinterface hasNext : ()Z
    //   74: ifeq -> 111
    //   77: iload #4
    //   79: iload_1
    //   80: if_icmpge -> 111
    //   83: aload_2
    //   84: iload #4
    //   86: iinc #4, 1
    //   89: aload_3
    //   90: invokeinterface next : ()Ljava/lang/Object;
    //   95: checkcast java/lang/Integer
    //   98: invokevirtual intValue : ()I
    //   101: iastore
    //   102: aload_3
    //   103: invokeinterface remove : ()V
    //   108: goto -> 68
    //   111: aload_0
    //   112: getfield Dne : LTnv;
    //   115: new tXK
    //   118: dup
    //   119: aload_2
    //   120: invokespecial <init> : ([I)V
    //   123: invokevirtual Dne : (LNER;)V
    //   126: goto -> 24
    //   129: aload_0
    //   130: getfield Dne : Ljava/util/List;
    //   133: invokeinterface isEmpty : ()Z
    //   138: ifne -> 416
    //   141: new java/util/ArrayList
    //   144: dup
    //   145: invokespecial <init> : ()V
    //   148: astore_1
    //   149: aload_0
    //   150: getfield Dne : Ljava/util/List;
    //   153: invokeinterface iterator : ()Ljava/util/Iterator;
    //   158: astore_2
    //   159: new java/util/ArrayList
    //   162: dup
    //   163: invokespecial <init> : ()V
    //   166: astore_3
    //   167: aload_2
    //   168: invokeinterface hasNext : ()Z
    //   173: ifeq -> 313
    //   176: aload_1
    //   177: invokevirtual size : ()I
    //   180: iconst_5
    //   181: if_icmpge -> 313
    //   184: aload_2
    //   185: invokeinterface next : ()Ljava/lang/Object;
    //   190: checkcast Sxs
    //   193: astore #4
    //   195: aload_2
    //   196: invokeinterface remove : ()V
    //   201: aload #4
    //   203: ifnull -> 310
    //   206: aload_0
    //   207: getfield Dne : LQnq;
    //   210: aload #4
    //   212: getfield Dne : I
    //   215: iconst_4
    //   216: ishl
    //   217: iconst_0
    //   218: aload #4
    //   220: getfield FWm : I
    //   223: iconst_4
    //   224: ishl
    //   225: invokevirtual bzF : (III)Z
    //   228: ifeq -> 310
    //   231: aload_1
    //   232: aload_0
    //   233: getfield Dne : LQnq;
    //   236: aload #4
    //   238: getfield Dne : I
    //   241: aload #4
    //   243: getfield FWm : I
    //   246: invokevirtual FWm : (II)LqMV;
    //   249: invokevirtual add : (Ljava/lang/Object;)Z
    //   252: pop
    //   253: aload_3
    //   254: aload_0
    //   255: getfield Dne : LQnq;
    //   258: checkcast RAN
    //   261: aload #4
    //   263: getfield Dne : I
    //   266: bipush #16
    //   268: imul
    //   269: iconst_0
    //   270: aload #4
    //   272: getfield FWm : I
    //   275: bipush #16
    //   277: imul
    //   278: aload #4
    //   280: getfield Dne : I
    //   283: bipush #16
    //   285: imul
    //   286: bipush #16
    //   288: iadd
    //   289: sipush #256
    //   292: aload #4
    //   294: getfield FWm : I
    //   297: bipush #16
    //   299: imul
    //   300: bipush #16
    //   302: iadd
    //   303: invokevirtual Dne : (IIIIII)Ljava/util/List;
    //   306: invokevirtual addAll : (Ljava/util/Collection;)Z
    //   309: pop
    //   310: goto -> 167
    //   313: aload_1
    //   314: invokevirtual isEmpty : ()Z
    //   317: ifne -> 416
    //   320: aload_0
    //   321: getfield Dne : LTnv;
    //   324: new nPC
    //   327: dup
    //   328: aload_1
    //   329: invokespecial <init> : (Ljava/util/List;)V
    //   332: invokevirtual Dne : (LNER;)V
    //   335: aload_3
    //   336: invokevirtual iterator : ()Ljava/util/Iterator;
    //   339: astore #4
    //   341: aload #4
    //   343: invokeinterface hasNext : ()Z
    //   348: ifeq -> 372
    //   351: aload #4
    //   353: invokeinterface next : ()Ljava/lang/Object;
    //   358: checkcast ipD
    //   361: astore #5
    //   363: aload_0
    //   364: aload #5
    //   366: invokespecial FWm : (LipD;)V
    //   369: goto -> 341
    //   372: aload_1
    //   373: invokevirtual iterator : ()Ljava/util/Iterator;
    //   376: astore #4
    //   378: aload #4
    //   380: invokeinterface hasNext : ()Z
    //   385: ifeq -> 416
    //   388: aload #4
    //   390: invokeinterface next : ()Ljava/lang/Object;
    //   395: checkcast qMV
    //   398: astore #5
    //   400: aload_0
    //   401: invokevirtual Dne : ()LRAN;
    //   404: invokevirtual Dne : ()Lclp;
    //   407: aload_0
    //   408: aload #5
    //   410: invokevirtual Dne : (LPJQ;LqMV;)V
    //   413: goto -> 378
    //   416: return
  }
  
  public void Dne(zBn paramzBn) {
    // Byte code:
    //   0: aload_0
    //   1: getfield Dne : LJwh;
    //   4: invokevirtual Dne : ()LdzN;
    //   7: aload_0
    //   8: getfield Dne : LpFT;
    //   11: invokevirtual Dne : ()Ljava/lang/String;
    //   14: invokevirtual aFZ : (Ljava/lang/String;)V
    //   17: aload_0
    //   18: getfield Dne : LQnq;
    //   21: invokevirtual Dne : ()LaSc;
    //   24: ldc_w 'keepInventory'
    //   27: invokevirtual Dne : (Ljava/lang/String;)Z
    //   30: ifne -> 40
    //   33: aload_0
    //   34: getfield Dne : LMOS;
    //   37: invokevirtual Qnq : ()V
    //   40: aload_0
    //   41: getfield Dne : LQnq;
    //   44: invokevirtual Dne : ()LSFA;
    //   47: getstatic PAf.FWm : LPAf;
    //   50: invokevirtual Dne : (LPAf;)Ljava/util/Collection;
    //   53: astore_2
    //   54: aload_2
    //   55: invokeinterface iterator : ()Ljava/util/Iterator;
    //   60: astore_3
    //   61: aload_3
    //   62: invokeinterface hasNext : ()Z
    //   67: ifeq -> 104
    //   70: aload_3
    //   71: invokeinterface next : ()Ljava/lang/Object;
    //   76: checkcast vfE
    //   79: astore #4
    //   81: aload_0
    //   82: invokevirtual Dne : ()LSFA;
    //   85: aload_0
    //   86: invokevirtual Dne : ()Ljava/lang/String;
    //   89: aload #4
    //   91: invokevirtual Dne : (Ljava/lang/String;LvfE;)LOHz;
    //   94: astore #5
    //   96: aload #5
    //   98: invokevirtual Dne : ()V
    //   101: goto -> 61
    //   104: aload_0
    //   105: invokevirtual Qnq : ()LFUH;
    //   108: astore #4
    //   110: aload #4
    //   112: ifnull -> 125
    //   115: aload #4
    //   117: aload_0
    //   118: aload_0
    //   119: getfield Qnq : I
    //   122: invokevirtual FWm : (LsMa;I)V
    //   125: return
  }
  
  public void Dne(String paramString) {
    // Byte code:
    //   0: aload_0
    //   1: getfield Dne : LTnv;
    //   4: new rXx
    //   7: dup
    //   8: aload_1
    //   9: invokespecial <init> : (Ljava/lang/String;)V
    //   12: invokevirtual Dne : (LNER;)V
    //   15: return
  }
  
  public void FWm(double paramDouble, boolean paramBoolean) {
    super.Dne(paramDouble, paramBoolean);
  }
  
  public void bzF(String paramString) {
    // Byte code:
    //   0: invokestatic Dne : ()Lirb;
    //   3: astore_2
    //   4: aload_2
    //   5: aload_1
    //   6: invokevirtual Dne : (Ljava/lang/String;)Ljava/lang/String;
    //   9: astore_3
    //   10: aload_0
    //   11: getfield Dne : LTnv;
    //   14: new rXx
    //   17: dup
    //   18: aload_3
    //   19: invokespecial <init> : (Ljava/lang/String;)V
    //   22: invokevirtual Dne : (LNER;)V
    //   25: return
  }
  
  protected void zGp() {
    this.udO = 0.0F;
  }
  
  public iSh Dne() {
    return new iSh(geR.FWm(this.div), geR.FWm(this.IjH + 0.5D), geR.FWm(this.mrb));
  }
  
  private void FWm(ipD paramipD) {
    // Byte code:
    //   0: aload_1
    //   1: ifnull -> 21
    //   4: aload_1
    //   5: invokevirtual Dne : ()LNER;
    //   8: astore_2
    //   9: aload_2
    //   10: ifnull -> 21
    //   13: aload_0
    //   14: getfield Dne : LTnv;
    //   17: aload_2
    //   18: invokevirtual Dne : (LNER;)V
    //   21: return
  }
  
  public void Dne(lqs paramlqs) {
    // Byte code:
    //   0: aload_0
    //   1: invokespecial qMV : ()V
    //   4: aload_0
    //   5: getfield Dne : LTnv;
    //   8: new XGq
    //   11: dup
    //   12: aload_0
    //   13: getfield ICU : I
    //   16: iconst_2
    //   17: aload_1
    //   18: invokevirtual b_ : ()Ljava/lang/String;
    //   21: aload_1
    //   22: invokevirtual Qnq : ()I
    //   25: aload_1
    //   26: invokevirtual d_ : ()Z
    //   29: invokespecial <init> : (IILjava/lang/String;IZ)V
    //   32: invokevirtual Dne : (LNER;)V
    //   35: aload_0
    //   36: new bhy
    //   39: dup
    //   40: aload_0
    //   41: getfield Dne : LMOS;
    //   44: aload_1
    //   45: invokespecial <init> : (LMOS;Llqs;)V
    //   48: putfield FWm : LPdb;
    //   51: aload_0
    //   52: getfield FWm : LPdb;
    //   55: aload_0
    //   56: getfield ICU : I
    //   59: putfield Dne : I
    //   62: aload_0
    //   63: getfield FWm : LPdb;
    //   66: aload_0
    //   67: invokevirtual Dne : (LmXX;)V
    //   70: return
  }
  
  public void Dne(NMq paramNMq, int paramInt) {
    super.Dne(paramNMq, paramInt);
    if (paramNMq != null && paramNMq.Dne() != null && paramNMq.Dne().Dne(paramNMq) == een.FWm)
      Dne().Dne().FWm(this, new UVb(this, 5)); 
  }
  
  public void Dne(UTs paramUTs) {
    // Byte code:
    //   0: aload_0
    //   1: invokespecial qMV : ()V
    //   4: aload_0
    //   5: getfield Dne : LTnv;
    //   8: new XGq
    //   11: dup
    //   12: aload_0
    //   13: getfield ICU : I
    //   16: aload_1
    //   17: instanceof BDA
    //   20: ifeq -> 28
    //   23: bipush #10
    //   25: goto -> 29
    //   28: iconst_3
    //   29: aload_1
    //   30: invokevirtual b_ : ()Ljava/lang/String;
    //   33: aload_1
    //   34: invokevirtual Qnq : ()I
    //   37: aload_1
    //   38: invokevirtual d_ : ()Z
    //   41: invokespecial <init> : (IILjava/lang/String;IZ)V
    //   44: invokevirtual Dne : (LNER;)V
    //   47: aload_0
    //   48: new HnX
    //   51: dup
    //   52: aload_0
    //   53: getfield Dne : LMOS;
    //   56: aload_1
    //   57: invokespecial <init> : (LMqS;LUTs;)V
    //   60: putfield FWm : LPdb;
    //   63: aload_0
    //   64: getfield FWm : LPdb;
    //   67: aload_0
    //   68: getfield ICU : I
    //   71: putfield Dne : I
    //   74: aload_0
    //   75: getfield FWm : LPdb;
    //   78: aload_0
    //   79: invokevirtual Dne : (LmXX;)V
    //   82: return
  }
  
  public void kGO() {
    // Byte code:
    //   0: aload_0
    //   1: getfield Dne : Z
    //   4: ifne -> 30
    //   7: aload_0
    //   8: getfield Dne : LTnv;
    //   11: new RZL
    //   14: dup
    //   15: iconst_m1
    //   16: iconst_m1
    //   17: aload_0
    //   18: getfield Dne : LMOS;
    //   21: invokevirtual FWm : ()LNMq;
    //   24: invokespecial <init> : (IILNMq;)V
    //   27: invokevirtual Dne : (LNER;)V
    //   30: return
  }
  
  public void Dne(int paramInt1, int paramInt2, int paramInt3) {
    // Byte code:
    //   0: aload_0
    //   1: invokespecial qMV : ()V
    //   4: aload_0
    //   5: getfield Dne : LTnv;
    //   8: new XGq
    //   11: dup
    //   12: aload_0
    //   13: getfield ICU : I
    //   16: iconst_1
    //   17: ldc_w 'Crafting'
    //   20: bipush #9
    //   22: iconst_1
    //   23: invokespecial <init> : (IILjava/lang/String;IZ)V
    //   26: invokevirtual Dne : (LNER;)V
    //   29: aload_0
    //   30: new uxW
    //   33: dup
    //   34: aload_0
    //   35: getfield Dne : LMOS;
    //   38: aload_0
    //   39: getfield Dne : LQnq;
    //   42: iload_1
    //   43: iload_2
    //   44: iload_3
    //   45: invokespecial <init> : (LMOS;LQnq;III)V
    //   48: putfield FWm : LPdb;
    //   51: aload_0
    //   52: getfield FWm : LPdb;
    //   55: aload_0
    //   56: getfield ICU : I
    //   59: putfield Dne : I
    //   62: aload_0
    //   63: getfield FWm : LPdb;
    //   66: aload_0
    //   67: invokevirtual Dne : (LmXX;)V
    //   70: return
  }
  
  public void Dne(sMa paramsMa, int paramInt) {
    super.Dne(paramsMa, paramInt);
    this.FWm.Dne();
  }
  
  private void qMV() {
    this.ICU = this.ICU % 100 + 1;
  }
  
  public boolean Dne(int paramInt, String paramString) {
    // Byte code:
    //   0: ldc_w 'seed'
    //   3: aload_2
    //   4: invokevirtual equals : (Ljava/lang/Object;)Z
    //   7: ifeq -> 24
    //   10: aload_0
    //   11: getfield Dne : LJwh;
    //   14: invokevirtual Qnq : ()Z
    //   17: ifne -> 24
    //   20: iconst_1
    //   21: goto -> 72
    //   24: ldc_w 'tell'
    //   27: aload_2
    //   28: invokevirtual equals : (Ljava/lang/Object;)Z
    //   31: ifne -> 71
    //   34: ldc_w 'help'
    //   37: aload_2
    //   38: invokevirtual equals : (Ljava/lang/Object;)Z
    //   41: ifne -> 71
    //   44: ldc_w 'me'
    //   47: aload_2
    //   48: invokevirtual equals : (Ljava/lang/Object;)Z
    //   51: ifne -> 71
    //   54: aload_0
    //   55: getfield Dne : LJwh;
    //   58: invokevirtual Dne : ()LdzN;
    //   61: aload_0
    //   62: getfield aFZ : Ljava/lang/String;
    //   65: invokevirtual FWm : (Ljava/lang/String;)Z
    //   68: goto -> 72
    //   71: iconst_1
    //   72: ireturn
  }
  
  protected void qLR() {
    // Byte code:
    //   0: aload_0
    //   1: getfield Dne : LTnv;
    //   4: new JGj
    //   7: dup
    //   8: aload_0
    //   9: getfield aFZ : I
    //   12: bipush #9
    //   14: invokespecial <init> : (IB)V
    //   17: invokevirtual Dne : (LNER;)V
    //   20: aload_0
    //   21: invokespecial qLR : ()V
    //   24: return
  }
  
  public void FWm(int paramInt1, int paramInt2, int paramInt3) {
    // Byte code:
    //   0: aload_0
    //   1: invokespecial qMV : ()V
    //   4: aload_0
    //   5: getfield Dne : LTnv;
    //   8: new XGq
    //   11: dup
    //   12: aload_0
    //   13: getfield ICU : I
    //   16: bipush #8
    //   18: ldc_w 'Repairing'
    //   21: bipush #9
    //   23: iconst_1
    //   24: invokespecial <init> : (IILjava/lang/String;IZ)V
    //   27: invokevirtual Dne : (LNER;)V
    //   30: aload_0
    //   31: new sZS
    //   34: dup
    //   35: aload_0
    //   36: getfield Dne : LMOS;
    //   39: aload_0
    //   40: getfield Dne : LQnq;
    //   43: iload_1
    //   44: iload_2
    //   45: iload_3
    //   46: aload_0
    //   47: invokespecial <init> : (LMOS;LQnq;IIILFiG;)V
    //   50: putfield FWm : LPdb;
    //   53: aload_0
    //   54: getfield FWm : LPdb;
    //   57: aload_0
    //   58: getfield ICU : I
    //   61: putfield Dne : I
    //   64: aload_0
    //   65: getfield FWm : LPdb;
    //   68: aload_0
    //   69: invokevirtual Dne : (LmXX;)V
    //   72: return
  }
  
  public void Dne(sMa paramsMa) {
    Dne().Dne().FWm(this, new UVb(paramsMa, 6));
  }
  
  public void Dne(Pdb paramPdb) {
    Dne(paramPdb, paramPdb.Dne());
  }
  
  public void Dne(klq paramklq) {
    // Byte code:
    //   0: aload_0
    //   1: invokespecial qMV : ()V
    //   4: aload_0
    //   5: getfield Dne : LTnv;
    //   8: new XGq
    //   11: dup
    //   12: aload_0
    //   13: getfield ICU : I
    //   16: bipush #9
    //   18: aload_1
    //   19: invokevirtual b_ : ()Ljava/lang/String;
    //   22: aload_1
    //   23: invokevirtual Qnq : ()I
    //   26: aload_1
    //   27: invokevirtual d_ : ()Z
    //   30: invokespecial <init> : (IILjava/lang/String;IZ)V
    //   33: invokevirtual Dne : (LNER;)V
    //   36: aload_0
    //   37: new Fed
    //   40: dup
    //   41: aload_0
    //   42: getfield Dne : LMOS;
    //   45: aload_1
    //   46: invokespecial <init> : (LMOS;LMqS;)V
    //   49: putfield FWm : LPdb;
    //   52: aload_0
    //   53: getfield FWm : LPdb;
    //   56: aload_0
    //   57: getfield ICU : I
    //   60: putfield Dne : I
    //   63: aload_0
    //   64: getfield FWm : LPdb;
    //   67: aload_0
    //   68: invokevirtual Dne : (LmXX;)V
    //   71: return
  }
  
  public void Dne(int paramInt1, int paramInt2, int paramInt3, String paramString) {
    // Byte code:
    //   0: aload_0
    //   1: invokespecial qMV : ()V
    //   4: aload_0
    //   5: getfield Dne : LTnv;
    //   8: new XGq
    //   11: dup
    //   12: aload_0
    //   13: getfield ICU : I
    //   16: iconst_4
    //   17: aload #4
    //   19: ifnonnull -> 28
    //   22: ldc_w ''
    //   25: goto -> 30
    //   28: aload #4
    //   30: bipush #9
    //   32: aload #4
    //   34: ifnull -> 41
    //   37: iconst_1
    //   38: goto -> 42
    //   41: iconst_0
    //   42: invokespecial <init> : (IILjava/lang/String;IZ)V
    //   45: invokevirtual Dne : (LNER;)V
    //   48: aload_0
    //   49: new HhP
    //   52: dup
    //   53: aload_0
    //   54: getfield Dne : LMOS;
    //   57: aload_0
    //   58: getfield Dne : LQnq;
    //   61: iload_1
    //   62: iload_2
    //   63: iload_3
    //   64: invokespecial <init> : (LMOS;LQnq;III)V
    //   67: putfield FWm : LPdb;
    //   70: aload_0
    //   71: getfield FWm : LPdb;
    //   74: aload_0
    //   75: getfield ICU : I
    //   78: putfield Dne : I
    //   81: aload_0
    //   82: getfield FWm : LPdb;
    //   85: aload_0
    //   86: invokevirtual Dne : (LmXX;)V
    //   89: return
  }
  
  protected void bzF(NAx paramNAx) {
    // Byte code:
    //   0: aload_0
    //   1: aload_1
    //   2: invokespecial bzF : (LNAx;)V
    //   5: aload_0
    //   6: getfield Dne : LTnv;
    //   9: new gzk
    //   12: dup
    //   13: aload_0
    //   14: getfield aFZ : I
    //   17: aload_1
    //   18: invokespecial <init> : (ILNAx;)V
    //   21: invokevirtual Dne : (LNER;)V
    //   24: return
  }
  
  public void Dne(XHL paramXHL) {
    // Byte code:
    //   0: aload_0
    //   1: getfield Dne : LdyC;
    //   4: aload_1
    //   5: invokevirtual Dne : (LXHL;)V
    //   8: aload_0
    //   9: getfield Dne : LTnv;
    //   12: new Tnn
    //   15: dup
    //   16: iconst_3
    //   17: aload_1
    //   18: invokevirtual Dne : ()I
    //   21: invokespecial <init> : (II)V
    //   24: invokevirtual Dne : (LNER;)V
    //   27: return
  }
  
  protected void FWm(NAx paramNAx) {
    // Byte code:
    //   0: aload_0
    //   1: aload_1
    //   2: invokespecial FWm : (LNAx;)V
    //   5: aload_0
    //   6: getfield Dne : LTnv;
    //   9: new ziQ
    //   12: dup
    //   13: aload_0
    //   14: getfield aFZ : I
    //   17: aload_1
    //   18: invokespecial <init> : (ILNAx;)V
    //   21: invokevirtual Dne : (LNER;)V
    //   24: return
  }
  
  public RAN Dne() {
    return (RAN)this.Dne;
  }
  
  public void Dne(zio paramzio) {
    // Byte code:
    //   0: aload_0
    //   1: invokespecial qMV : ()V
    //   4: aload_0
    //   5: getfield Dne : LTnv;
    //   8: new XGq
    //   11: dup
    //   12: aload_0
    //   13: getfield ICU : I
    //   16: iconst_5
    //   17: aload_1
    //   18: invokevirtual b_ : ()Ljava/lang/String;
    //   21: aload_1
    //   22: invokevirtual Qnq : ()I
    //   25: aload_1
    //   26: invokevirtual d_ : ()Z
    //   29: invokespecial <init> : (IILjava/lang/String;IZ)V
    //   32: invokevirtual Dne : (LNER;)V
    //   35: aload_0
    //   36: new oss
    //   39: dup
    //   40: aload_0
    //   41: getfield Dne : LMOS;
    //   44: aload_1
    //   45: invokespecial <init> : (LMOS;Lzio;)V
    //   48: putfield FWm : LPdb;
    //   51: aload_0
    //   52: getfield FWm : LPdb;
    //   55: aload_0
    //   56: getfield ICU : I
    //   59: putfield Dne : I
    //   62: aload_0
    //   63: getfield FWm : LPdb;
    //   66: aload_0
    //   67: invokevirtual Dne : (LmXX;)V
    //   70: return
  }
  
  public void Dne(Pdb paramPdb, List paramList) {
    // Byte code:
    //   0: aload_0
    //   1: getfield Dne : LTnv;
    //   4: new Pwq
    //   7: dup
    //   8: aload_1
    //   9: getfield Dne : I
    //   12: aload_2
    //   13: invokespecial <init> : (ILjava/util/List;)V
    //   16: invokevirtual Dne : (LNER;)V
    //   19: aload_0
    //   20: getfield Dne : LTnv;
    //   23: new RZL
    //   26: dup
    //   27: iconst_m1
    //   28: iconst_m1
    //   29: aload_0
    //   30: getfield Dne : LMOS;
    //   33: invokevirtual FWm : ()LNMq;
    //   36: invokespecial <init> : (IILNMq;)V
    //   39: invokevirtual Dne : (LNER;)V
    //   42: return
  }
  
  public void Dne(Pdb paramPdb, int paramInt, NMq paramNMq) {
    // Byte code:
    //   0: aload_1
    //   1: iload_2
    //   2: invokevirtual Dne : (I)LonZ;
    //   5: instanceof wEm
    //   8: ifne -> 38
    //   11: aload_0
    //   12: getfield Dne : Z
    //   15: ifne -> 38
    //   18: aload_0
    //   19: getfield Dne : LTnv;
    //   22: new RZL
    //   25: dup
    //   26: aload_1
    //   27: getfield Dne : I
    //   30: iload_2
    //   31: aload_3
    //   32: invokespecial <init> : (IILNMq;)V
    //   35: invokevirtual Dne : (LNER;)V
    //   38: return
  }
  
  public void FWm(WkD paramWkD) {
    // Byte code:
    //   0: aload_0
    //   1: aload_1
    //   2: invokespecial FWm : (LWkD;)V
    //   5: aload_1
    //   6: ldc_w 'playerGameType'
    //   9: invokevirtual Dne : (Ljava/lang/String;)Z
    //   12: ifeq -> 57
    //   15: invokestatic Dne : ()LJwh;
    //   18: invokevirtual EyB : ()Z
    //   21: ifeq -> 40
    //   24: aload_0
    //   25: getfield Dne : LdyC;
    //   28: invokestatic Dne : ()LJwh;
    //   31: invokevirtual Dne : ()LXHL;
    //   34: invokevirtual Dne : (LXHL;)V
    //   37: goto -> 57
    //   40: aload_0
    //   41: getfield Dne : LdyC;
    //   44: aload_1
    //   45: ldc_w 'playerGameType'
    //   48: invokevirtual Dne : (Ljava/lang/String;)I
    //   51: invokestatic Dne : (I)LXHL;
    //   54: invokevirtual Dne : (LXHL;)V
    //   57: return
  }
  
  public void XHL() {
    this.FWm.Dne(this);
  }
  
  public void FWm(double paramDouble1, double paramDouble2, double paramDouble3) {
    // Byte code:
    //   0: aload_0
    //   1: getfield Dne : LTnv;
    //   4: dload_1
    //   5: dload_3
    //   6: dload #5
    //   8: aload_0
    //   9: getfield mrb : F
    //   12: aload_0
    //   13: getfield XHL : F
    //   16: invokevirtual Dne : (DDDFF)V
    //   19: return
  }
  
  public void aFZ() {
    // Byte code:
    //   0: aload_0
    //   1: getfield Dne : LTnv;
    //   4: new Krr
    //   7: dup
    //   8: aload_0
    //   9: getfield FWm : LPdb;
    //   12: getfield Dne : I
    //   15: invokespecial <init> : (I)V
    //   18: invokevirtual Dne : (LNER;)V
    //   21: aload_0
    //   22: invokevirtual udO : ()V
    //   25: return
  }
  
  public int bzF() {
    return this.LVR;
  }
  
  public void Dne(Aem paramAem) {
    // Byte code:
    //   0: aload_0
    //   1: invokespecial qMV : ()V
    //   4: aload_0
    //   5: getfield Dne : LTnv;
    //   8: new XGq
    //   11: dup
    //   12: aload_0
    //   13: getfield ICU : I
    //   16: bipush #9
    //   18: aload_1
    //   19: invokevirtual b_ : ()Ljava/lang/String;
    //   22: aload_1
    //   23: invokevirtual Qnq : ()I
    //   26: aload_1
    //   27: invokevirtual d_ : ()Z
    //   30: invokespecial <init> : (IILjava/lang/String;IZ)V
    //   33: invokevirtual Dne : (LNER;)V
    //   36: aload_0
    //   37: new Fed
    //   40: dup
    //   41: aload_0
    //   42: getfield Dne : LMOS;
    //   45: aload_1
    //   46: invokespecial <init> : (LMOS;LMqS;)V
    //   49: putfield FWm : LPdb;
    //   52: aload_0
    //   53: getfield FWm : LPdb;
    //   56: aload_0
    //   57: getfield ICU : I
    //   60: putfield Dne : I
    //   63: aload_0
    //   64: getfield FWm : LPdb;
    //   67: aload_0
    //   68: invokevirtual Dne : (LmXX;)V
    //   71: return
  }
  
  public void Dne(WkD paramWkD) {
    // Byte code:
    //   0: aload_0
    //   1: aload_1
    //   2: invokespecial Dne : (LWkD;)V
    //   5: aload_1
    //   6: ldc_w 'playerGameType'
    //   9: aload_0
    //   10: getfield Dne : LdyC;
    //   13: invokevirtual Dne : ()LXHL;
    //   16: invokevirtual Dne : ()I
    //   19: invokevirtual Dne : (Ljava/lang/String;I)V
    //   22: return
  }
  
  public void Dne(boolean paramBoolean1, boolean paramBoolean2, boolean paramBoolean3) {
    // Byte code:
    //   0: aload_0
    //   1: invokevirtual Wwe : ()Z
    //   4: ifeq -> 27
    //   7: aload_0
    //   8: invokevirtual Dne : ()LRAN;
    //   11: invokevirtual Dne : ()Lclp;
    //   14: aload_0
    //   15: new UVb
    //   18: dup
    //   19: aload_0
    //   20: iconst_3
    //   21: invokespecial <init> : (LsMa;I)V
    //   24: invokevirtual FWm : (LsMa;LNER;)V
    //   27: aload_0
    //   28: iload_1
    //   29: iload_2
    //   30: iload_3
    //   31: invokespecial Dne : (ZZZ)V
    //   34: aload_0
    //   35: getfield Dne : LTnv;
    //   38: ifnull -> 68
    //   41: aload_0
    //   42: getfield Dne : LTnv;
    //   45: aload_0
    //   46: getfield div : D
    //   49: aload_0
    //   50: getfield IjH : D
    //   53: aload_0
    //   54: getfield mrb : D
    //   57: aload_0
    //   58: getfield mrb : F
    //   61: aload_0
    //   62: getfield XHL : F
    //   65: invokevirtual Dne : (DDDFF)V
    //   68: return
  }
  
  public float c_() {
    return 1.62F;
  }
}


/* Location:              C:\Users\fract\Downloads\ERROR422.jar!\PJQ.class
 * Java compiler version: 8 (52.0)
 * JD-Core Version:       1.1.3
 */