public class pnN implements OTl {
  private int aFZ;
  
  private boolean Dne;
  
  private int Qnq;
  
  private static final byte[] Dne = new byte[] { 
      99, 124, 119, 123, -14, 107, 111, -59, 48, 1, 
      103, 43, -2, -41, -85, 118, -54, -126, -55, 125, 
      -6, 89, 71, -16, -83, -44, -94, -81, -100, -92, 
      114, -64, -73, -3, -109, 38, 54, 63, -9, -52, 
      52, -91, -27, -15, 113, -40, 49, 21, 4, -57, 
      35, -61, 24, -106, 5, -102, 7, 18, Byte.MIN_VALUE, -30, 
      -21, 39, -78, 117, 9, -125, 44, 26, 27, 110, 
      90, -96, 82, 59, -42, -77, 41, -29, 47, -124, 
      83, -47, 0, -19, 32, -4, -79, 91, 106, -53, 
      -66, 57, 74, 76, 88, -49, -48, -17, -86, -5, 
      67, 77, 51, -123, 69, -7, 2, Byte.MAX_VALUE, 80, 60, 
      -97, -88, 81, -93, 64, -113, -110, -99, 56, -11, 
      -68, -74, -38, 33, 16, -1, -13, -46, -51, 12, 
      19, -20, 95, -105, 68, 23, -60, -89, 126, 61, 
      100, 93, 25, 115, 96, -127, 79, -36, 34, 42, 
      -112, -120, 70, -18, -72, 20, -34, 94, 11, -37, 
      -32, 50, 58, 10, 73, 6, 36, 92, -62, -45, 
      -84, 98, -111, -107, -28, 121, -25, -56, 55, 109, 
      -115, -43, 78, -87, 108, 86, -12, -22, 101, 122, 
      -82, 8, -70, 120, 37, 46, 28, -90, -76, -58, 
      -24, -35, 116, 31, 75, -67, -117, -118, 112, 62, 
      -75, 102, 72, 3, -10, 14, 97, 53, 87, -71, 
      -122, -63, 29, -98, -31, -8, -104, 17, 105, -39, 
      -114, -108, -101, 30, -121, -23, -50, 85, 40, -33, 
      -116, -95, -119, 13, -65, -26, 66, 104, 65, -103, 
      45, 15, -80, 84, -69, 22 };
  
  private static final int[] aFZ;
  
  private static final int[] DyG;
  
  private static final int[] Dne;
  
  private static final int[] zGp;
  
  private static final int[] IjH;
  
  private int[][] Dne;
  
  private int FWm;
  
  private static final int[] div;
  
  private int bzF;
  
  private static final int[] bzF;
  
  private static final int[] Qnq;
  
  private static final byte[] FWm = new byte[] { 
      82, 9, 106, -43, 48, 54, -91, 56, -65, 64, 
      -93, -98, -127, -13, -41, -5, 124, -29, 57, -126, 
      -101, 47, -1, -121, 52, -114, 67, 68, -60, -34, 
      -23, -53, 84, 123, -108, 50, -90, -62, 35, 61, 
      -18, 76, -107, 11, 66, -6, -61, 78, 8, 46, 
      -95, 102, 40, -39, 36, -78, 118, 91, -94, 73, 
      109, -117, -47, 37, 114, -8, -10, 100, -122, 104, 
      -104, 22, -44, -92, 92, -52, 93, 101, -74, -110, 
      108, 112, 72, 80, -3, -19, -71, -38, 94, 21, 
      70, 87, -89, -115, -99, -124, -112, -40, -85, 0, 
      -116, -68, -45, 10, -9, -28, 88, 5, -72, -77, 
      69, 6, -48, 44, 30, -113, -54, 63, 15, 2, 
      -63, -81, -67, 3, 1, 19, -118, 107, 58, -111, 
      17, 65, 79, 103, -36, -22, -105, -14, -49, -50, 
      -16, -76, -26, 115, -106, -84, 116, 34, -25, -83, 
      53, -123, -30, -7, 55, -24, 28, 117, -33, 110, 
      71, -15, 26, 113, 29, 41, -59, -119, 111, -73, 
      98, 14, -86, 24, -66, 27, -4, 86, 62, 75, 
      -58, -46, 121, 32, -102, -37, -64, -2, 120, -51, 
      90, -12, 31, -35, -88, 51, -120, 7, -57, 49, 
      -79, 18, 16, 89, 39, Byte.MIN_VALUE, -20, 95, 96, 81, 
      Byte.MAX_VALUE, -87, 25, -75, 74, 13, 45, -27, 122, -97, 
      -109, -55, -100, -17, -96, -32, 59, 77, -82, 42, 
      -11, -80, -56, -21, -69, 60, -125, 83, -103, 97, 
      23, 43, 4, 126, -70, 119, -42, 38, -31, 105, 
      20, 99, 85, 33, 12, 125 };
  
  private static final int[] FWm;
  
  private int Dne = (int[][])null;
  
  private void Dne(int[][] paramArrayOfint) {
    // Byte code:
    //   0: aload_0
    //   1: dup
    //   2: getfield FWm : I
    //   5: aload_1
    //   6: iconst_0
    //   7: aaload
    //   8: iconst_0
    //   9: iaload
    //   10: ixor
    //   11: putfield FWm : I
    //   14: aload_0
    //   15: dup
    //   16: getfield bzF : I
    //   19: aload_1
    //   20: iconst_0
    //   21: aaload
    //   22: iconst_1
    //   23: iaload
    //   24: ixor
    //   25: putfield bzF : I
    //   28: aload_0
    //   29: dup
    //   30: getfield Qnq : I
    //   33: aload_1
    //   34: iconst_0
    //   35: aaload
    //   36: iconst_2
    //   37: iaload
    //   38: ixor
    //   39: putfield Qnq : I
    //   42: aload_0
    //   43: dup
    //   44: getfield aFZ : I
    //   47: aload_1
    //   48: iconst_0
    //   49: aaload
    //   50: iconst_3
    //   51: iaload
    //   52: ixor
    //   53: putfield aFZ : I
    //   56: iconst_1
    //   57: istore_2
    //   58: iload_2
    //   59: aload_0
    //   60: getfield Dne : I
    //   63: iconst_1
    //   64: isub
    //   65: if_icmpge -> 592
    //   68: getstatic pnN.FWm : [I
    //   71: aload_0
    //   72: getfield FWm : I
    //   75: sipush #255
    //   78: iand
    //   79: iaload
    //   80: getstatic pnN.bzF : [I
    //   83: aload_0
    //   84: getfield bzF : I
    //   87: bipush #8
    //   89: ishr
    //   90: sipush #255
    //   93: iand
    //   94: iaload
    //   95: ixor
    //   96: getstatic pnN.Qnq : [I
    //   99: aload_0
    //   100: getfield Qnq : I
    //   103: bipush #16
    //   105: ishr
    //   106: sipush #255
    //   109: iand
    //   110: iaload
    //   111: ixor
    //   112: getstatic pnN.aFZ : [I
    //   115: aload_0
    //   116: getfield aFZ : I
    //   119: bipush #24
    //   121: ishr
    //   122: sipush #255
    //   125: iand
    //   126: iaload
    //   127: ixor
    //   128: aload_1
    //   129: iload_2
    //   130: aaload
    //   131: iconst_0
    //   132: iaload
    //   133: ixor
    //   134: istore_3
    //   135: getstatic pnN.FWm : [I
    //   138: aload_0
    //   139: getfield bzF : I
    //   142: sipush #255
    //   145: iand
    //   146: iaload
    //   147: getstatic pnN.bzF : [I
    //   150: aload_0
    //   151: getfield Qnq : I
    //   154: bipush #8
    //   156: ishr
    //   157: sipush #255
    //   160: iand
    //   161: iaload
    //   162: ixor
    //   163: getstatic pnN.Qnq : [I
    //   166: aload_0
    //   167: getfield aFZ : I
    //   170: bipush #16
    //   172: ishr
    //   173: sipush #255
    //   176: iand
    //   177: iaload
    //   178: ixor
    //   179: getstatic pnN.aFZ : [I
    //   182: aload_0
    //   183: getfield FWm : I
    //   186: bipush #24
    //   188: ishr
    //   189: sipush #255
    //   192: iand
    //   193: iaload
    //   194: ixor
    //   195: aload_1
    //   196: iload_2
    //   197: aaload
    //   198: iconst_1
    //   199: iaload
    //   200: ixor
    //   201: istore #4
    //   203: getstatic pnN.FWm : [I
    //   206: aload_0
    //   207: getfield Qnq : I
    //   210: sipush #255
    //   213: iand
    //   214: iaload
    //   215: getstatic pnN.bzF : [I
    //   218: aload_0
    //   219: getfield aFZ : I
    //   222: bipush #8
    //   224: ishr
    //   225: sipush #255
    //   228: iand
    //   229: iaload
    //   230: ixor
    //   231: getstatic pnN.Qnq : [I
    //   234: aload_0
    //   235: getfield FWm : I
    //   238: bipush #16
    //   240: ishr
    //   241: sipush #255
    //   244: iand
    //   245: iaload
    //   246: ixor
    //   247: getstatic pnN.aFZ : [I
    //   250: aload_0
    //   251: getfield bzF : I
    //   254: bipush #24
    //   256: ishr
    //   257: sipush #255
    //   260: iand
    //   261: iaload
    //   262: ixor
    //   263: aload_1
    //   264: iload_2
    //   265: aaload
    //   266: iconst_2
    //   267: iaload
    //   268: ixor
    //   269: istore #5
    //   271: getstatic pnN.FWm : [I
    //   274: aload_0
    //   275: getfield aFZ : I
    //   278: sipush #255
    //   281: iand
    //   282: iaload
    //   283: getstatic pnN.bzF : [I
    //   286: aload_0
    //   287: getfield FWm : I
    //   290: bipush #8
    //   292: ishr
    //   293: sipush #255
    //   296: iand
    //   297: iaload
    //   298: ixor
    //   299: getstatic pnN.Qnq : [I
    //   302: aload_0
    //   303: getfield bzF : I
    //   306: bipush #16
    //   308: ishr
    //   309: sipush #255
    //   312: iand
    //   313: iaload
    //   314: ixor
    //   315: getstatic pnN.aFZ : [I
    //   318: aload_0
    //   319: getfield Qnq : I
    //   322: bipush #24
    //   324: ishr
    //   325: sipush #255
    //   328: iand
    //   329: iaload
    //   330: ixor
    //   331: aload_1
    //   332: iload_2
    //   333: iinc #2, 1
    //   336: aaload
    //   337: iconst_3
    //   338: iaload
    //   339: ixor
    //   340: istore #6
    //   342: aload_0
    //   343: getstatic pnN.FWm : [I
    //   346: iload_3
    //   347: sipush #255
    //   350: iand
    //   351: iaload
    //   352: getstatic pnN.bzF : [I
    //   355: iload #4
    //   357: bipush #8
    //   359: ishr
    //   360: sipush #255
    //   363: iand
    //   364: iaload
    //   365: ixor
    //   366: getstatic pnN.Qnq : [I
    //   369: iload #5
    //   371: bipush #16
    //   373: ishr
    //   374: sipush #255
    //   377: iand
    //   378: iaload
    //   379: ixor
    //   380: getstatic pnN.aFZ : [I
    //   383: iload #6
    //   385: bipush #24
    //   387: ishr
    //   388: sipush #255
    //   391: iand
    //   392: iaload
    //   393: ixor
    //   394: aload_1
    //   395: iload_2
    //   396: aaload
    //   397: iconst_0
    //   398: iaload
    //   399: ixor
    //   400: putfield FWm : I
    //   403: aload_0
    //   404: getstatic pnN.FWm : [I
    //   407: iload #4
    //   409: sipush #255
    //   412: iand
    //   413: iaload
    //   414: getstatic pnN.bzF : [I
    //   417: iload #5
    //   419: bipush #8
    //   421: ishr
    //   422: sipush #255
    //   425: iand
    //   426: iaload
    //   427: ixor
    //   428: getstatic pnN.Qnq : [I
    //   431: iload #6
    //   433: bipush #16
    //   435: ishr
    //   436: sipush #255
    //   439: iand
    //   440: iaload
    //   441: ixor
    //   442: getstatic pnN.aFZ : [I
    //   445: iload_3
    //   446: bipush #24
    //   448: ishr
    //   449: sipush #255
    //   452: iand
    //   453: iaload
    //   454: ixor
    //   455: aload_1
    //   456: iload_2
    //   457: aaload
    //   458: iconst_1
    //   459: iaload
    //   460: ixor
    //   461: putfield bzF : I
    //   464: aload_0
    //   465: getstatic pnN.FWm : [I
    //   468: iload #5
    //   470: sipush #255
    //   473: iand
    //   474: iaload
    //   475: getstatic pnN.bzF : [I
    //   478: iload #6
    //   480: bipush #8
    //   482: ishr
    //   483: sipush #255
    //   486: iand
    //   487: iaload
    //   488: ixor
    //   489: getstatic pnN.Qnq : [I
    //   492: iload_3
    //   493: bipush #16
    //   495: ishr
    //   496: sipush #255
    //   499: iand
    //   500: iaload
    //   501: ixor
    //   502: getstatic pnN.aFZ : [I
    //   505: iload #4
    //   507: bipush #24
    //   509: ishr
    //   510: sipush #255
    //   513: iand
    //   514: iaload
    //   515: ixor
    //   516: aload_1
    //   517: iload_2
    //   518: aaload
    //   519: iconst_2
    //   520: iaload
    //   521: ixor
    //   522: putfield Qnq : I
    //   525: aload_0
    //   526: getstatic pnN.FWm : [I
    //   529: iload #6
    //   531: sipush #255
    //   534: iand
    //   535: iaload
    //   536: getstatic pnN.bzF : [I
    //   539: iload_3
    //   540: bipush #8
    //   542: ishr
    //   543: sipush #255
    //   546: iand
    //   547: iaload
    //   548: ixor
    //   549: getstatic pnN.Qnq : [I
    //   552: iload #4
    //   554: bipush #16
    //   556: ishr
    //   557: sipush #255
    //   560: iand
    //   561: iaload
    //   562: ixor
    //   563: getstatic pnN.aFZ : [I
    //   566: iload #5
    //   568: bipush #24
    //   570: ishr
    //   571: sipush #255
    //   574: iand
    //   575: iaload
    //   576: ixor
    //   577: aload_1
    //   578: iload_2
    //   579: iinc #2, 1
    //   582: aaload
    //   583: iconst_3
    //   584: iaload
    //   585: ixor
    //   586: putfield aFZ : I
    //   589: goto -> 58
    //   592: getstatic pnN.FWm : [I
    //   595: aload_0
    //   596: getfield FWm : I
    //   599: sipush #255
    //   602: iand
    //   603: iaload
    //   604: getstatic pnN.bzF : [I
    //   607: aload_0
    //   608: getfield bzF : I
    //   611: bipush #8
    //   613: ishr
    //   614: sipush #255
    //   617: iand
    //   618: iaload
    //   619: ixor
    //   620: getstatic pnN.Qnq : [I
    //   623: aload_0
    //   624: getfield Qnq : I
    //   627: bipush #16
    //   629: ishr
    //   630: sipush #255
    //   633: iand
    //   634: iaload
    //   635: ixor
    //   636: getstatic pnN.aFZ : [I
    //   639: aload_0
    //   640: getfield aFZ : I
    //   643: bipush #24
    //   645: ishr
    //   646: sipush #255
    //   649: iand
    //   650: iaload
    //   651: ixor
    //   652: aload_1
    //   653: iload_2
    //   654: aaload
    //   655: iconst_0
    //   656: iaload
    //   657: ixor
    //   658: istore_3
    //   659: getstatic pnN.FWm : [I
    //   662: aload_0
    //   663: getfield bzF : I
    //   666: sipush #255
    //   669: iand
    //   670: iaload
    //   671: getstatic pnN.bzF : [I
    //   674: aload_0
    //   675: getfield Qnq : I
    //   678: bipush #8
    //   680: ishr
    //   681: sipush #255
    //   684: iand
    //   685: iaload
    //   686: ixor
    //   687: getstatic pnN.Qnq : [I
    //   690: aload_0
    //   691: getfield aFZ : I
    //   694: bipush #16
    //   696: ishr
    //   697: sipush #255
    //   700: iand
    //   701: iaload
    //   702: ixor
    //   703: getstatic pnN.aFZ : [I
    //   706: aload_0
    //   707: getfield FWm : I
    //   710: bipush #24
    //   712: ishr
    //   713: sipush #255
    //   716: iand
    //   717: iaload
    //   718: ixor
    //   719: aload_1
    //   720: iload_2
    //   721: aaload
    //   722: iconst_1
    //   723: iaload
    //   724: ixor
    //   725: istore #4
    //   727: getstatic pnN.FWm : [I
    //   730: aload_0
    //   731: getfield Qnq : I
    //   734: sipush #255
    //   737: iand
    //   738: iaload
    //   739: getstatic pnN.bzF : [I
    //   742: aload_0
    //   743: getfield aFZ : I
    //   746: bipush #8
    //   748: ishr
    //   749: sipush #255
    //   752: iand
    //   753: iaload
    //   754: ixor
    //   755: getstatic pnN.Qnq : [I
    //   758: aload_0
    //   759: getfield FWm : I
    //   762: bipush #16
    //   764: ishr
    //   765: sipush #255
    //   768: iand
    //   769: iaload
    //   770: ixor
    //   771: getstatic pnN.aFZ : [I
    //   774: aload_0
    //   775: getfield bzF : I
    //   778: bipush #24
    //   780: ishr
    //   781: sipush #255
    //   784: iand
    //   785: iaload
    //   786: ixor
    //   787: aload_1
    //   788: iload_2
    //   789: aaload
    //   790: iconst_2
    //   791: iaload
    //   792: ixor
    //   793: istore #5
    //   795: getstatic pnN.FWm : [I
    //   798: aload_0
    //   799: getfield aFZ : I
    //   802: sipush #255
    //   805: iand
    //   806: iaload
    //   807: getstatic pnN.bzF : [I
    //   810: aload_0
    //   811: getfield FWm : I
    //   814: bipush #8
    //   816: ishr
    //   817: sipush #255
    //   820: iand
    //   821: iaload
    //   822: ixor
    //   823: getstatic pnN.Qnq : [I
    //   826: aload_0
    //   827: getfield bzF : I
    //   830: bipush #16
    //   832: ishr
    //   833: sipush #255
    //   836: iand
    //   837: iaload
    //   838: ixor
    //   839: getstatic pnN.aFZ : [I
    //   842: aload_0
    //   843: getfield Qnq : I
    //   846: bipush #24
    //   848: ishr
    //   849: sipush #255
    //   852: iand
    //   853: iaload
    //   854: ixor
    //   855: aload_1
    //   856: iload_2
    //   857: iinc #2, 1
    //   860: aaload
    //   861: iconst_3
    //   862: iaload
    //   863: ixor
    //   864: istore #6
    //   866: aload_0
    //   867: getstatic pnN.Dne : [B
    //   870: iload_3
    //   871: sipush #255
    //   874: iand
    //   875: baload
    //   876: sipush #255
    //   879: iand
    //   880: getstatic pnN.Dne : [B
    //   883: iload #4
    //   885: bipush #8
    //   887: ishr
    //   888: sipush #255
    //   891: iand
    //   892: baload
    //   893: sipush #255
    //   896: iand
    //   897: bipush #8
    //   899: ishl
    //   900: ixor
    //   901: getstatic pnN.Dne : [B
    //   904: iload #5
    //   906: bipush #16
    //   908: ishr
    //   909: sipush #255
    //   912: iand
    //   913: baload
    //   914: sipush #255
    //   917: iand
    //   918: bipush #16
    //   920: ishl
    //   921: ixor
    //   922: getstatic pnN.Dne : [B
    //   925: iload #6
    //   927: bipush #24
    //   929: ishr
    //   930: sipush #255
    //   933: iand
    //   934: baload
    //   935: bipush #24
    //   937: ishl
    //   938: ixor
    //   939: aload_1
    //   940: iload_2
    //   941: aaload
    //   942: iconst_0
    //   943: iaload
    //   944: ixor
    //   945: putfield FWm : I
    //   948: aload_0
    //   949: getstatic pnN.Dne : [B
    //   952: iload #4
    //   954: sipush #255
    //   957: iand
    //   958: baload
    //   959: sipush #255
    //   962: iand
    //   963: getstatic pnN.Dne : [B
    //   966: iload #5
    //   968: bipush #8
    //   970: ishr
    //   971: sipush #255
    //   974: iand
    //   975: baload
    //   976: sipush #255
    //   979: iand
    //   980: bipush #8
    //   982: ishl
    //   983: ixor
    //   984: getstatic pnN.Dne : [B
    //   987: iload #6
    //   989: bipush #16
    //   991: ishr
    //   992: sipush #255
    //   995: iand
    //   996: baload
    //   997: sipush #255
    //   1000: iand
    //   1001: bipush #16
    //   1003: ishl
    //   1004: ixor
    //   1005: getstatic pnN.Dne : [B
    //   1008: iload_3
    //   1009: bipush #24
    //   1011: ishr
    //   1012: sipush #255
    //   1015: iand
    //   1016: baload
    //   1017: bipush #24
    //   1019: ishl
    //   1020: ixor
    //   1021: aload_1
    //   1022: iload_2
    //   1023: aaload
    //   1024: iconst_1
    //   1025: iaload
    //   1026: ixor
    //   1027: putfield bzF : I
    //   1030: aload_0
    //   1031: getstatic pnN.Dne : [B
    //   1034: iload #5
    //   1036: sipush #255
    //   1039: iand
    //   1040: baload
    //   1041: sipush #255
    //   1044: iand
    //   1045: getstatic pnN.Dne : [B
    //   1048: iload #6
    //   1050: bipush #8
    //   1052: ishr
    //   1053: sipush #255
    //   1056: iand
    //   1057: baload
    //   1058: sipush #255
    //   1061: iand
    //   1062: bipush #8
    //   1064: ishl
    //   1065: ixor
    //   1066: getstatic pnN.Dne : [B
    //   1069: iload_3
    //   1070: bipush #16
    //   1072: ishr
    //   1073: sipush #255
    //   1076: iand
    //   1077: baload
    //   1078: sipush #255
    //   1081: iand
    //   1082: bipush #16
    //   1084: ishl
    //   1085: ixor
    //   1086: getstatic pnN.Dne : [B
    //   1089: iload #4
    //   1091: bipush #24
    //   1093: ishr
    //   1094: sipush #255
    //   1097: iand
    //   1098: baload
    //   1099: bipush #24
    //   1101: ishl
    //   1102: ixor
    //   1103: aload_1
    //   1104: iload_2
    //   1105: aaload
    //   1106: iconst_2
    //   1107: iaload
    //   1108: ixor
    //   1109: putfield Qnq : I
    //   1112: aload_0
    //   1113: getstatic pnN.Dne : [B
    //   1116: iload #6
    //   1118: sipush #255
    //   1121: iand
    //   1122: baload
    //   1123: sipush #255
    //   1126: iand
    //   1127: getstatic pnN.Dne : [B
    //   1130: iload_3
    //   1131: bipush #8
    //   1133: ishr
    //   1134: sipush #255
    //   1137: iand
    //   1138: baload
    //   1139: sipush #255
    //   1142: iand
    //   1143: bipush #8
    //   1145: ishl
    //   1146: ixor
    //   1147: getstatic pnN.Dne : [B
    //   1150: iload #4
    //   1152: bipush #16
    //   1154: ishr
    //   1155: sipush #255
    //   1158: iand
    //   1159: baload
    //   1160: sipush #255
    //   1163: iand
    //   1164: bipush #16
    //   1166: ishl
    //   1167: ixor
    //   1168: getstatic pnN.Dne : [B
    //   1171: iload #5
    //   1173: bipush #24
    //   1175: ishr
    //   1176: sipush #255
    //   1179: iand
    //   1180: baload
    //   1181: bipush #24
    //   1183: ishl
    //   1184: ixor
    //   1185: aload_1
    //   1186: iload_2
    //   1187: aaload
    //   1188: iconst_3
    //   1189: iaload
    //   1190: ixor
    //   1191: putfield aFZ : I
    //   1194: return
  }
  
  public void Dne() {}
  
  private int FWm(int paramInt) {
    int i = Dne(paramInt);
    int j = Dne(i);
    int k = Dne(j);
    int m = paramInt ^ k;
    return i ^ j ^ k ^ Dne(i ^ m, 8) ^ Dne(j ^ m, 16) ^ Dne(m, 24);
  }
  
  public String Dne() {
    return "AES";
  }
  
  public int Dne() {
    return 16;
  }
  
  private void FWm(byte[] paramArrayOfbyte, int paramInt) {
    int i = paramInt + 1;
    paramArrayOfbyte[paramInt] = (byte)this.FWm;
    paramArrayOfbyte[i++] = (byte)(this.FWm >> 8);
    paramArrayOfbyte[i++] = (byte)(this.FWm >> 16);
    paramArrayOfbyte[i++] = (byte)(this.FWm >> 24);
    paramArrayOfbyte[i++] = (byte)this.bzF;
    paramArrayOfbyte[i++] = (byte)(this.bzF >> 8);
    paramArrayOfbyte[i++] = (byte)(this.bzF >> 16);
    paramArrayOfbyte[i++] = (byte)(this.bzF >> 24);
    paramArrayOfbyte[i++] = (byte)this.Qnq;
    paramArrayOfbyte[i++] = (byte)(this.Qnq >> 8);
    paramArrayOfbyte[i++] = (byte)(this.Qnq >> 16);
    paramArrayOfbyte[i++] = (byte)(this.Qnq >> 24);
    paramArrayOfbyte[i++] = (byte)this.aFZ;
    paramArrayOfbyte[i++] = (byte)(this.aFZ >> 8);
    paramArrayOfbyte[i++] = (byte)(this.aFZ >> 16);
    paramArrayOfbyte[i++] = (byte)(this.aFZ >> 24);
  }
  
  private void FWm(int[][] paramArrayOfint) {
    // Byte code:
    //   0: aload_0
    //   1: dup
    //   2: getfield FWm : I
    //   5: aload_1
    //   6: aload_0
    //   7: getfield Dne : I
    //   10: aaload
    //   11: iconst_0
    //   12: iaload
    //   13: ixor
    //   14: putfield FWm : I
    //   17: aload_0
    //   18: dup
    //   19: getfield bzF : I
    //   22: aload_1
    //   23: aload_0
    //   24: getfield Dne : I
    //   27: aaload
    //   28: iconst_1
    //   29: iaload
    //   30: ixor
    //   31: putfield bzF : I
    //   34: aload_0
    //   35: dup
    //   36: getfield Qnq : I
    //   39: aload_1
    //   40: aload_0
    //   41: getfield Dne : I
    //   44: aaload
    //   45: iconst_2
    //   46: iaload
    //   47: ixor
    //   48: putfield Qnq : I
    //   51: aload_0
    //   52: dup
    //   53: getfield aFZ : I
    //   56: aload_1
    //   57: aload_0
    //   58: getfield Dne : I
    //   61: aaload
    //   62: iconst_3
    //   63: iaload
    //   64: ixor
    //   65: putfield aFZ : I
    //   68: aload_0
    //   69: getfield Dne : I
    //   72: iconst_1
    //   73: isub
    //   74: istore #6
    //   76: iload #6
    //   78: iconst_1
    //   79: if_icmple -> 609
    //   82: getstatic pnN.zGp : [I
    //   85: aload_0
    //   86: getfield FWm : I
    //   89: sipush #255
    //   92: iand
    //   93: iaload
    //   94: getstatic pnN.DyG : [I
    //   97: aload_0
    //   98: getfield aFZ : I
    //   101: bipush #8
    //   103: ishr
    //   104: sipush #255
    //   107: iand
    //   108: iaload
    //   109: ixor
    //   110: getstatic pnN.div : [I
    //   113: aload_0
    //   114: getfield Qnq : I
    //   117: bipush #16
    //   119: ishr
    //   120: sipush #255
    //   123: iand
    //   124: iaload
    //   125: ixor
    //   126: getstatic pnN.IjH : [I
    //   129: aload_0
    //   130: getfield bzF : I
    //   133: bipush #24
    //   135: ishr
    //   136: sipush #255
    //   139: iand
    //   140: iaload
    //   141: ixor
    //   142: aload_1
    //   143: iload #6
    //   145: aaload
    //   146: iconst_0
    //   147: iaload
    //   148: ixor
    //   149: istore_2
    //   150: getstatic pnN.zGp : [I
    //   153: aload_0
    //   154: getfield bzF : I
    //   157: sipush #255
    //   160: iand
    //   161: iaload
    //   162: getstatic pnN.DyG : [I
    //   165: aload_0
    //   166: getfield FWm : I
    //   169: bipush #8
    //   171: ishr
    //   172: sipush #255
    //   175: iand
    //   176: iaload
    //   177: ixor
    //   178: getstatic pnN.div : [I
    //   181: aload_0
    //   182: getfield aFZ : I
    //   185: bipush #16
    //   187: ishr
    //   188: sipush #255
    //   191: iand
    //   192: iaload
    //   193: ixor
    //   194: getstatic pnN.IjH : [I
    //   197: aload_0
    //   198: getfield Qnq : I
    //   201: bipush #24
    //   203: ishr
    //   204: sipush #255
    //   207: iand
    //   208: iaload
    //   209: ixor
    //   210: aload_1
    //   211: iload #6
    //   213: aaload
    //   214: iconst_1
    //   215: iaload
    //   216: ixor
    //   217: istore_3
    //   218: getstatic pnN.zGp : [I
    //   221: aload_0
    //   222: getfield Qnq : I
    //   225: sipush #255
    //   228: iand
    //   229: iaload
    //   230: getstatic pnN.DyG : [I
    //   233: aload_0
    //   234: getfield bzF : I
    //   237: bipush #8
    //   239: ishr
    //   240: sipush #255
    //   243: iand
    //   244: iaload
    //   245: ixor
    //   246: getstatic pnN.div : [I
    //   249: aload_0
    //   250: getfield FWm : I
    //   253: bipush #16
    //   255: ishr
    //   256: sipush #255
    //   259: iand
    //   260: iaload
    //   261: ixor
    //   262: getstatic pnN.IjH : [I
    //   265: aload_0
    //   266: getfield aFZ : I
    //   269: bipush #24
    //   271: ishr
    //   272: sipush #255
    //   275: iand
    //   276: iaload
    //   277: ixor
    //   278: aload_1
    //   279: iload #6
    //   281: aaload
    //   282: iconst_2
    //   283: iaload
    //   284: ixor
    //   285: istore #4
    //   287: getstatic pnN.zGp : [I
    //   290: aload_0
    //   291: getfield aFZ : I
    //   294: sipush #255
    //   297: iand
    //   298: iaload
    //   299: getstatic pnN.DyG : [I
    //   302: aload_0
    //   303: getfield Qnq : I
    //   306: bipush #8
    //   308: ishr
    //   309: sipush #255
    //   312: iand
    //   313: iaload
    //   314: ixor
    //   315: getstatic pnN.div : [I
    //   318: aload_0
    //   319: getfield bzF : I
    //   322: bipush #16
    //   324: ishr
    //   325: sipush #255
    //   328: iand
    //   329: iaload
    //   330: ixor
    //   331: getstatic pnN.IjH : [I
    //   334: aload_0
    //   335: getfield FWm : I
    //   338: bipush #24
    //   340: ishr
    //   341: sipush #255
    //   344: iand
    //   345: iaload
    //   346: ixor
    //   347: aload_1
    //   348: iload #6
    //   350: iinc #6, -1
    //   353: aaload
    //   354: iconst_3
    //   355: iaload
    //   356: ixor
    //   357: istore #5
    //   359: aload_0
    //   360: getstatic pnN.zGp : [I
    //   363: iload_2
    //   364: sipush #255
    //   367: iand
    //   368: iaload
    //   369: getstatic pnN.DyG : [I
    //   372: iload #5
    //   374: bipush #8
    //   376: ishr
    //   377: sipush #255
    //   380: iand
    //   381: iaload
    //   382: ixor
    //   383: getstatic pnN.div : [I
    //   386: iload #4
    //   388: bipush #16
    //   390: ishr
    //   391: sipush #255
    //   394: iand
    //   395: iaload
    //   396: ixor
    //   397: getstatic pnN.IjH : [I
    //   400: iload_3
    //   401: bipush #24
    //   403: ishr
    //   404: sipush #255
    //   407: iand
    //   408: iaload
    //   409: ixor
    //   410: aload_1
    //   411: iload #6
    //   413: aaload
    //   414: iconst_0
    //   415: iaload
    //   416: ixor
    //   417: putfield FWm : I
    //   420: aload_0
    //   421: getstatic pnN.zGp : [I
    //   424: iload_3
    //   425: sipush #255
    //   428: iand
    //   429: iaload
    //   430: getstatic pnN.DyG : [I
    //   433: iload_2
    //   434: bipush #8
    //   436: ishr
    //   437: sipush #255
    //   440: iand
    //   441: iaload
    //   442: ixor
    //   443: getstatic pnN.div : [I
    //   446: iload #5
    //   448: bipush #16
    //   450: ishr
    //   451: sipush #255
    //   454: iand
    //   455: iaload
    //   456: ixor
    //   457: getstatic pnN.IjH : [I
    //   460: iload #4
    //   462: bipush #24
    //   464: ishr
    //   465: sipush #255
    //   468: iand
    //   469: iaload
    //   470: ixor
    //   471: aload_1
    //   472: iload #6
    //   474: aaload
    //   475: iconst_1
    //   476: iaload
    //   477: ixor
    //   478: putfield bzF : I
    //   481: aload_0
    //   482: getstatic pnN.zGp : [I
    //   485: iload #4
    //   487: sipush #255
    //   490: iand
    //   491: iaload
    //   492: getstatic pnN.DyG : [I
    //   495: iload_3
    //   496: bipush #8
    //   498: ishr
    //   499: sipush #255
    //   502: iand
    //   503: iaload
    //   504: ixor
    //   505: getstatic pnN.div : [I
    //   508: iload_2
    //   509: bipush #16
    //   511: ishr
    //   512: sipush #255
    //   515: iand
    //   516: iaload
    //   517: ixor
    //   518: getstatic pnN.IjH : [I
    //   521: iload #5
    //   523: bipush #24
    //   525: ishr
    //   526: sipush #255
    //   529: iand
    //   530: iaload
    //   531: ixor
    //   532: aload_1
    //   533: iload #6
    //   535: aaload
    //   536: iconst_2
    //   537: iaload
    //   538: ixor
    //   539: putfield Qnq : I
    //   542: aload_0
    //   543: getstatic pnN.zGp : [I
    //   546: iload #5
    //   548: sipush #255
    //   551: iand
    //   552: iaload
    //   553: getstatic pnN.DyG : [I
    //   556: iload #4
    //   558: bipush #8
    //   560: ishr
    //   561: sipush #255
    //   564: iand
    //   565: iaload
    //   566: ixor
    //   567: getstatic pnN.div : [I
    //   570: iload_3
    //   571: bipush #16
    //   573: ishr
    //   574: sipush #255
    //   577: iand
    //   578: iaload
    //   579: ixor
    //   580: getstatic pnN.IjH : [I
    //   583: iload_2
    //   584: bipush #24
    //   586: ishr
    //   587: sipush #255
    //   590: iand
    //   591: iaload
    //   592: ixor
    //   593: aload_1
    //   594: iload #6
    //   596: iinc #6, -1
    //   599: aaload
    //   600: iconst_3
    //   601: iaload
    //   602: ixor
    //   603: putfield aFZ : I
    //   606: goto -> 76
    //   609: getstatic pnN.zGp : [I
    //   612: aload_0
    //   613: getfield FWm : I
    //   616: sipush #255
    //   619: iand
    //   620: iaload
    //   621: getstatic pnN.DyG : [I
    //   624: aload_0
    //   625: getfield aFZ : I
    //   628: bipush #8
    //   630: ishr
    //   631: sipush #255
    //   634: iand
    //   635: iaload
    //   636: ixor
    //   637: getstatic pnN.div : [I
    //   640: aload_0
    //   641: getfield Qnq : I
    //   644: bipush #16
    //   646: ishr
    //   647: sipush #255
    //   650: iand
    //   651: iaload
    //   652: ixor
    //   653: getstatic pnN.IjH : [I
    //   656: aload_0
    //   657: getfield bzF : I
    //   660: bipush #24
    //   662: ishr
    //   663: sipush #255
    //   666: iand
    //   667: iaload
    //   668: ixor
    //   669: aload_1
    //   670: iload #6
    //   672: aaload
    //   673: iconst_0
    //   674: iaload
    //   675: ixor
    //   676: istore_2
    //   677: getstatic pnN.zGp : [I
    //   680: aload_0
    //   681: getfield bzF : I
    //   684: sipush #255
    //   687: iand
    //   688: iaload
    //   689: getstatic pnN.DyG : [I
    //   692: aload_0
    //   693: getfield FWm : I
    //   696: bipush #8
    //   698: ishr
    //   699: sipush #255
    //   702: iand
    //   703: iaload
    //   704: ixor
    //   705: getstatic pnN.div : [I
    //   708: aload_0
    //   709: getfield aFZ : I
    //   712: bipush #16
    //   714: ishr
    //   715: sipush #255
    //   718: iand
    //   719: iaload
    //   720: ixor
    //   721: getstatic pnN.IjH : [I
    //   724: aload_0
    //   725: getfield Qnq : I
    //   728: bipush #24
    //   730: ishr
    //   731: sipush #255
    //   734: iand
    //   735: iaload
    //   736: ixor
    //   737: aload_1
    //   738: iload #6
    //   740: aaload
    //   741: iconst_1
    //   742: iaload
    //   743: ixor
    //   744: istore_3
    //   745: getstatic pnN.zGp : [I
    //   748: aload_0
    //   749: getfield Qnq : I
    //   752: sipush #255
    //   755: iand
    //   756: iaload
    //   757: getstatic pnN.DyG : [I
    //   760: aload_0
    //   761: getfield bzF : I
    //   764: bipush #8
    //   766: ishr
    //   767: sipush #255
    //   770: iand
    //   771: iaload
    //   772: ixor
    //   773: getstatic pnN.div : [I
    //   776: aload_0
    //   777: getfield FWm : I
    //   780: bipush #16
    //   782: ishr
    //   783: sipush #255
    //   786: iand
    //   787: iaload
    //   788: ixor
    //   789: getstatic pnN.IjH : [I
    //   792: aload_0
    //   793: getfield aFZ : I
    //   796: bipush #24
    //   798: ishr
    //   799: sipush #255
    //   802: iand
    //   803: iaload
    //   804: ixor
    //   805: aload_1
    //   806: iload #6
    //   808: aaload
    //   809: iconst_2
    //   810: iaload
    //   811: ixor
    //   812: istore #4
    //   814: getstatic pnN.zGp : [I
    //   817: aload_0
    //   818: getfield aFZ : I
    //   821: sipush #255
    //   824: iand
    //   825: iaload
    //   826: getstatic pnN.DyG : [I
    //   829: aload_0
    //   830: getfield Qnq : I
    //   833: bipush #8
    //   835: ishr
    //   836: sipush #255
    //   839: iand
    //   840: iaload
    //   841: ixor
    //   842: getstatic pnN.div : [I
    //   845: aload_0
    //   846: getfield bzF : I
    //   849: bipush #16
    //   851: ishr
    //   852: sipush #255
    //   855: iand
    //   856: iaload
    //   857: ixor
    //   858: getstatic pnN.IjH : [I
    //   861: aload_0
    //   862: getfield FWm : I
    //   865: bipush #24
    //   867: ishr
    //   868: sipush #255
    //   871: iand
    //   872: iaload
    //   873: ixor
    //   874: aload_1
    //   875: iload #6
    //   877: aaload
    //   878: iconst_3
    //   879: iaload
    //   880: ixor
    //   881: istore #5
    //   883: aload_0
    //   884: getstatic pnN.FWm : [B
    //   887: iload_2
    //   888: sipush #255
    //   891: iand
    //   892: baload
    //   893: sipush #255
    //   896: iand
    //   897: getstatic pnN.FWm : [B
    //   900: iload #5
    //   902: bipush #8
    //   904: ishr
    //   905: sipush #255
    //   908: iand
    //   909: baload
    //   910: sipush #255
    //   913: iand
    //   914: bipush #8
    //   916: ishl
    //   917: ixor
    //   918: getstatic pnN.FWm : [B
    //   921: iload #4
    //   923: bipush #16
    //   925: ishr
    //   926: sipush #255
    //   929: iand
    //   930: baload
    //   931: sipush #255
    //   934: iand
    //   935: bipush #16
    //   937: ishl
    //   938: ixor
    //   939: getstatic pnN.FWm : [B
    //   942: iload_3
    //   943: bipush #24
    //   945: ishr
    //   946: sipush #255
    //   949: iand
    //   950: baload
    //   951: bipush #24
    //   953: ishl
    //   954: ixor
    //   955: aload_1
    //   956: iconst_0
    //   957: aaload
    //   958: iconst_0
    //   959: iaload
    //   960: ixor
    //   961: putfield FWm : I
    //   964: aload_0
    //   965: getstatic pnN.FWm : [B
    //   968: iload_3
    //   969: sipush #255
    //   972: iand
    //   973: baload
    //   974: sipush #255
    //   977: iand
    //   978: getstatic pnN.FWm : [B
    //   981: iload_2
    //   982: bipush #8
    //   984: ishr
    //   985: sipush #255
    //   988: iand
    //   989: baload
    //   990: sipush #255
    //   993: iand
    //   994: bipush #8
    //   996: ishl
    //   997: ixor
    //   998: getstatic pnN.FWm : [B
    //   1001: iload #5
    //   1003: bipush #16
    //   1005: ishr
    //   1006: sipush #255
    //   1009: iand
    //   1010: baload
    //   1011: sipush #255
    //   1014: iand
    //   1015: bipush #16
    //   1017: ishl
    //   1018: ixor
    //   1019: getstatic pnN.FWm : [B
    //   1022: iload #4
    //   1024: bipush #24
    //   1026: ishr
    //   1027: sipush #255
    //   1030: iand
    //   1031: baload
    //   1032: bipush #24
    //   1034: ishl
    //   1035: ixor
    //   1036: aload_1
    //   1037: iconst_0
    //   1038: aaload
    //   1039: iconst_1
    //   1040: iaload
    //   1041: ixor
    //   1042: putfield bzF : I
    //   1045: aload_0
    //   1046: getstatic pnN.FWm : [B
    //   1049: iload #4
    //   1051: sipush #255
    //   1054: iand
    //   1055: baload
    //   1056: sipush #255
    //   1059: iand
    //   1060: getstatic pnN.FWm : [B
    //   1063: iload_3
    //   1064: bipush #8
    //   1066: ishr
    //   1067: sipush #255
    //   1070: iand
    //   1071: baload
    //   1072: sipush #255
    //   1075: iand
    //   1076: bipush #8
    //   1078: ishl
    //   1079: ixor
    //   1080: getstatic pnN.FWm : [B
    //   1083: iload_2
    //   1084: bipush #16
    //   1086: ishr
    //   1087: sipush #255
    //   1090: iand
    //   1091: baload
    //   1092: sipush #255
    //   1095: iand
    //   1096: bipush #16
    //   1098: ishl
    //   1099: ixor
    //   1100: getstatic pnN.FWm : [B
    //   1103: iload #5
    //   1105: bipush #24
    //   1107: ishr
    //   1108: sipush #255
    //   1111: iand
    //   1112: baload
    //   1113: bipush #24
    //   1115: ishl
    //   1116: ixor
    //   1117: aload_1
    //   1118: iconst_0
    //   1119: aaload
    //   1120: iconst_2
    //   1121: iaload
    //   1122: ixor
    //   1123: putfield Qnq : I
    //   1126: aload_0
    //   1127: getstatic pnN.FWm : [B
    //   1130: iload #5
    //   1132: sipush #255
    //   1135: iand
    //   1136: baload
    //   1137: sipush #255
    //   1140: iand
    //   1141: getstatic pnN.FWm : [B
    //   1144: iload #4
    //   1146: bipush #8
    //   1148: ishr
    //   1149: sipush #255
    //   1152: iand
    //   1153: baload
    //   1154: sipush #255
    //   1157: iand
    //   1158: bipush #8
    //   1160: ishl
    //   1161: ixor
    //   1162: getstatic pnN.FWm : [B
    //   1165: iload_3
    //   1166: bipush #16
    //   1168: ishr
    //   1169: sipush #255
    //   1172: iand
    //   1173: baload
    //   1174: sipush #255
    //   1177: iand
    //   1178: bipush #16
    //   1180: ishl
    //   1181: ixor
    //   1182: getstatic pnN.FWm : [B
    //   1185: iload_2
    //   1186: bipush #24
    //   1188: ishr
    //   1189: sipush #255
    //   1192: iand
    //   1193: baload
    //   1194: bipush #24
    //   1196: ishl
    //   1197: ixor
    //   1198: aload_1
    //   1199: iconst_0
    //   1200: aaload
    //   1201: iconst_3
    //   1202: iaload
    //   1203: ixor
    //   1204: putfield aFZ : I
    //   1207: return
  }
  
  private int bzF(int paramInt) {
    return Dne[paramInt & 0xFF] & 0xFF | (Dne[paramInt >> 8 & 0xFF] & 0xFF) << 8 | (Dne[paramInt >> 16 & 0xFF] & 0xFF) << 16 | Dne[paramInt >> 24 & 0xFF] << 24;
  }
  
  private int Dne(int paramInt1, int paramInt2) {
    return paramInt1 >>> paramInt2 | paramInt1 << -paramInt2;
  }
  
  public int Dne(byte[] paramArrayOfbyte1, int paramInt1, byte[] paramArrayOfbyte2, int paramInt2) {
    if (this.Dne == null)
      throw new IllegalStateException("AES engine not initialised"); 
    if (paramInt1 + 16 > paramArrayOfbyte1.length)
      throw new Gtk("input buffer too short"); 
    if (paramInt2 + 16 > paramArrayOfbyte2.length)
      throw new Gtk("output buffer too short"); 
    if (this.Dne != 0) {
      Dne(paramArrayOfbyte1, paramInt1);
      Dne(this.Dne);
      FWm(paramArrayOfbyte2, paramInt2);
    } else {
      Dne(paramArrayOfbyte1, paramInt1);
      FWm(this.Dne);
      FWm(paramArrayOfbyte2, paramInt2);
    } 
    return 16;
  }
  
  public void Dne(boolean paramBoolean, ePy paramePy) {
    if (paramePy instanceof Sst) {
      this.Dne = Dne(((Sst)paramePy).Dne(), paramBoolean);
      this.Dne = paramBoolean;
    } else {
      throw new IllegalArgumentException("invalid parameter passed to AES init - " + paramePy.getClass().getName());
    } 
  }
  
  private int Dne(int paramInt) {
    return (paramInt & 0x7F7F7F7F) << 1 ^ ((paramInt & 0x80808080) >>> 7) * 27;
  }
  
  private void Dne(byte[] paramArrayOfbyte, int paramInt) {
    int i = paramInt + 1;
    this.FWm = paramArrayOfbyte[paramInt] & 0xFF;
    this.FWm |= (paramArrayOfbyte[i++] & 0xFF) << 8;
    this.FWm |= (paramArrayOfbyte[i++] & 0xFF) << 16;
    this.FWm |= paramArrayOfbyte[i++] << 24;
    this.bzF = paramArrayOfbyte[i++] & 0xFF;
    this.bzF |= (paramArrayOfbyte[i++] & 0xFF) << 8;
    this.bzF |= (paramArrayOfbyte[i++] & 0xFF) << 16;
    this.bzF |= paramArrayOfbyte[i++] << 24;
    this.Qnq = paramArrayOfbyte[i++] & 0xFF;
    this.Qnq |= (paramArrayOfbyte[i++] & 0xFF) << 8;
    this.Qnq |= (paramArrayOfbyte[i++] & 0xFF) << 16;
    this.Qnq |= paramArrayOfbyte[i++] << 24;
    this.aFZ = paramArrayOfbyte[i++] & 0xFF;
    this.aFZ |= (paramArrayOfbyte[i++] & 0xFF) << 8;
    this.aFZ |= (paramArrayOfbyte[i++] & 0xFF) << 16;
    this.aFZ |= paramArrayOfbyte[i++] << 24;
  }
  
  static {
    Dne = new int[] { 
        1, 2, 4, 8, 16, 32, 64, 128, 27, 54, 
        108, 216, 171, 77, 154, 47, 94, 188, 99, 198, 
        151, 53, 106, 212, 179, 125, 250, 239, 197, 145 };
    FWm = new int[] { 
        -1520213050, -2072216328, -1720223762, -1921287178, 234025727, -1117033514, -1318096930, 1422247313, 1345335392, 50397442, 
        -1452841010, 2099981142, 436141799, 1658312629, -424957107, -1703512340, 1170918031, -1652391393, 1086966153, -2021818886, 
        368769775, -346465870, -918075506, 200339707, -324162239, 1742001331, -39673249, -357585083, -1080255453, -140204973, 
        -1770884380, 1539358875, -1028147339, 486407649, -1366060227, 1780885068, 1513502316, 1094664062, 49805301, 1338821763, 
        1546925160, -190470831, 887481809, 150073849, -1821281822, 1943591083, 1395732834, 1058346282, 201589768, 1388824469, 
        1696801606, 1589887901, 672667696, -1583966665, 251987210, -1248159185, 151455502, 907153956, -1686077413, 1038279391, 
        652995533, 1764173646, -843926913, -1619692054, 453576978, -1635548387, 1949051992, 773462580, 756751158, -1301385508, 
        -296068428, -73359269, -162377052, 1295727478, 1641469623, -827083907, 2066295122, 1055122397, 1898917726, -1752923117, 
        -179088474, 1758581177, 0, 753790401, 1612718144, 536673507, -927878791, -312779850, -1100322092, 1187761037, 
        -641810841, 1262041458, -565556588, -733197160, -396863312, 1255133061, 1808847035, 720367557, -441800113, 385612781, 
        -985447546, -682799718, 1429418854, -1803188975, -817543798, 284817897, 100794884, -2122350594, -263171936, 1144798328, 
        -1163944155, -475486133, -212774494, -22830243, -1069531008, -1970303227, -1382903233, -1130521311, 1211644016, 83228145, 
        -541279133, -1044990345, 1977277103, 1663115586, 806359072, 452984805, 250868733, 1842533055, 1288555905, 336333848, 
        890442534, 804056259, -513843266, -1567123659, -867941240, 957814574, 1472513171, -223893675, -2105639172, 1195195770, 
        -1402706744, -413311558, 723065138, -1787595802, -1604296512, -1736343271, -783331426, 2145180835, 1713513028, 2116692564, 
        -1416589253, -2088204277, -901364084, 703524551, -742868885, 1007948840, 2044649127, -497131844, 487262998, 1994120109, 
        1004593371, 1446130276, 1312438900, 503974420, -615954030, 168166924, 1814307912, -463709000, 1573044895, 1859376061, 
        -273896381, -1503501628, -1466855111, -1533700815, 937747667, -1954973198, 854058965, 1137232011, 1496790894, -1217565222, 
        -1936880383, 1691735473, -766620004, -525751991, -1267962664, -95005012, 133494003, 636152527, -1352309302, -1904575756, 
        -374428089, 403179536, -709182865, -2005370640, 1864705354, 1915629148, 605822008, -240736681, -944458637, 1371981463, 
        602466507, 2094914977, -1670089496, 555687742, -582268010, -591544991, -2037675251, -2054518257, -1871679264, 1111375484, 
        -994724495, -1436129588, -666351472, 84083462, 32962295, 302911004, -1553899070, 1597322602, -111716434, -793134743, 
        -1853454825, 1489093017, 656219450, -1180787161, 954327513, 335083755, -1281845205, 856756514, -1150719534, 1893325225, 
        -1987146233, -1483434957, -1231316179, 572399164, -1836611819, 552200649, 1238290055, -11184726, 2015897680, 2061492133, 
        -1886614525, -123625127, -2138470135, 386731290, -624967835, 837215959, -968736124, -1201116976, -1019133566, -1332111063, 
        1999449434, 286199582, -877612933, -61582168, -692339859, 974525996 };
    bzF = new int[] { 
        1667483301, 2088564868, 2004348569, 2071721613, -218956019, 1802229437, 1869602481, -976907948, 808476752, 16843267, 
        1734856361, 724260477, -16849127, -673729182, -1414836762, 1987505306, -892694715, -2105401443, -909539008, 2105408135, 
        -84218091, 1499050731, 1195871945, -252642549, -1381154324, -724257945, -1566416899, -1347467798, -1667488833, -1532734473, 
        1920132246, -1061119141, -1212713534, -33693412, -1819066962, 640044138, 909536346, 1061125697, -134744830, -859012273, 
        875849820, -1515892236, -437923532, -235800312, 1903288979, -656888973, 825320019, 353708607, 67373068, -943221422, 
        589514341, -1010590370, 404238376, -1768540255, 84216335, -1701171275, 117902857, 303178806, -2139087973, -488448195, 
        -336868058, 656887401, -1296924723, 1970662047, 151589403, -2088559202, 741103732, 437924910, 454768173, 1852759218, 
        1515893998, -1600103429, 1381147894, 993752653, -690571423, -1280082482, 690573947, -471605954, 791633521, -2071719017, 
        1397991157, -774784664, 0, -303185620, 538984544, -50535649, -1313769016, 1532737261, 1785386174, -875852474, 
        -1094817831, 960066123, 1246401758, 1280088276, 1482207464, -808483510, -791626901, -269499094, -1431679003, -67375850, 
        1128498885, 1296931543, 859006549, -2054876780, 1162185423, -101062384, 33686534, 2139094657, 1347461360, 1010595908, 
        -1616960070, -1465365533, 1364304627, -1549574658, 1077969088, -1886452342, -1835909203, -1650646596, 943222856, -168431356, 
        -1128504353, -1229555775, -623202443, 555827811, 269492272, -6886, -202113778, -757940371, -842170036, 202119188, 
        320022069, -320027857, 1600110305, -1751698014, 1145342156, 387395129, -993750185, -1482205710, 2122251394, 1027439175, 
        1684326572, 1566423783, 421081643, 1936975509, 1616953504, -2122245736, 1330618065, -589520001, 572671078, 707417214, 
        -1869595733, -2004350077, 1179028682, -286341335, -1195873325, 336865340, -555833479, 1583267042, 185275933, -606360202, 
        -522134725, 842163286, 976909390, 168432670, 1229558491, 101059594, 606357612, 1549580516, -1027432611, -741098130, 
        -1397996561, 1650640038, -1852753496, -1785384540, -454765769, 2038035083, -404237006, -926381245, 926379609, 1835915959, 
        -1920138868, -707415708, 1313774802, -1448523296, 1819072692, 1448520954, -185273593, -353710299, 1701169839, 2054878350, 
        -1364310039, 134746136, -1162186795, 2021191816, 623200879, 774790258, 471611428, -1499047951, -1263242297, -960063663, 
        -387396829, -572677764, 1953818780, 522141217, 1263245021, -1111662116, -1953821306, -1970663547, 1886445712, 1044282434, 
        -1246400060, 1718013098, 1212715224, 50529797, -151587071, 235805714, 1633796771, 892693087, 1465364217, -1179031088, 
        -2038032495, -1044276904, 488454695, -1633802311, -505292488, -117904621, -1734857805, 286335539, 1768542907, -640046736, 
        -1903294583, -1802226777, -1684329034, 505297954, -2021190254, -370554592, -825325751, 1431677695, 673730680, -538991238, 
        -1936981105, -1583261192, -1987507840, 218962455, -1077975590, -421079247, 1111655622, 1751699640, 1094812355, -1718015568, 
        757946999, 252648977, -1330611253, 1414834428, -1145344554, 370551866 };
    Qnq = new int[] { 
        1673962851, 2096661628, 2012125559, 2079755643, -218165774, 1809235307, 1876865391, -980331323, 811618352, 16909057, 
        1741597031, 727088427, -18408962, -675978537, -1420958037, 1995217526, -896580150, -2111857278, -913751863, 2113570685, 
        -84994566, 1504897881, 1200539975, -251982864, -1388188499, -726439980, -1570767454, -1354372433, -1675378788, -1538000988, 
        1927583346, -1063560256, -1217019209, -35578627, -1824674157, 642542118, 913070646, 1065238847, -134937865, -863809588, 
        879254580, -1521355611, -439274267, -235337487, 1910674289, -659852328, 828527409, 355090197, 67636228, -946515257, 
        591815971, -1013096765, 405809176, -1774739050, 84545285, -1708149350, 118360327, 304363026, -2145674368, -488686110, 
        -338876693, 659450151, -1300247118, 1978310517, 152181513, -2095210877, 743994412, 439627290, 456535323, 1859957358, 
        1521806938, -1604584544, 1386542674, 997608763, -692624938, -1283600717, 693271337, -472039709, 794718511, -2079090812, 
        1403450707, -776378159, 0, -306107155, 541089824, -52224004, -1317418831, 1538714971, 1792327274, -879933749, 
        -1100490306, 963791673, 1251270218, 1285084236, 1487988824, -813348145, -793023536, -272291089, -1437604438, -68348165, 
        1132905795, 1301993293, 862344499, -2062445435, 1166724933, -102166279, 33818114, 2147385727, 1352724560, 1014514748, 
        -1624917345, -1471421528, 1369633617, -1554121053, 1082179648, -1895462257, -1841320558, -1658733411, 946882616, -168753931, 
        -1134305348, -1233665610, -626035238, 557998881, 270544912, -1762561, -201519373, -759206446, -847164211, 202904588, 
        321271059, -322752532, 1606345055, -1758092649, 1149815876, 388905239, -996976700, -1487539545, 2130477694, 1031423805, 
        1690872932, 1572530013, 422718233, 1944491379, 1623236704, -2129028991, 1335808335, -593264676, 574907938, 710180394, 
        -1875137648, -2012511352, 1183631942, -288937490, -1200893000, 338181140, -559449634, 1589437022, 185998603, -609388837, 
        -522503200, 845436466, 980700730, 169090570, 1234361161, 101452294, 608726052, 1555620956, -1029743166, -742560045, 
        -1404833876, 1657054818, -1858492271, -1791908715, -455919644, 2045938553, -405458201, -930397240, 929978679, 1843050349, 
        -1929278323, -709794603, 1318900302, -1454776151, 1826141292, 1454176854, -185399308, -355523094, 1707781989, 2062847610, 
        -1371018834, 135272456, -1167075910, 2029029496, 625635109, 777810478, 473441308, -1504185946, -1267480652, -963161658, 
        -389340184, -576619299, 1961401460, 524165407, 1268178251, -1117659971, -1962047861, -1978694262, 1893765232, 1048330814, 
        -1250835275, 1724688998, 1217452104, 50726147, -151584266, 236720654, 1640145761, 896163637, 1471084887, -1184247623, 
        -2045275770, -1046914879, 490350365, -1641563746, -505857823, -118811656, -1741966440, 287453969, 1775418217, -643206951, 
        -1912108658, -1808554092, -1691502949, 507257374, -2028629369, -372694807, -829994546, 1437269845, 676362280, -542803233, 
        -1945923700, -1587939167, -1995865975, 219813645, -1083843905, -422104602, 1115997762, 1758509160, 1099088705, -1725321063, 
        760903469, 253628687, -1334064208, 1420360788, -1150429509, 371997206 };
    aFZ = new int[] { 
        -962239645, -125535108, -291932297, -158499973, -15863054, -692229269, -558796945, -1856715323, 1615867952, 33751297, 
        -827758745, 1451043627, -417726722, -1251813417, 1306962859, -325421450, -1891251510, 530416258, -1992242743, -91783811, 
        -283772166, -1293199015, -1899411641, -83103504, 1106029997, -1285040940, 1610457762, 1173008303, 599760028, 1408738468, 
        -459902350, -1688485696, 1975695287, -518193667, 1034851219, 1282024998, 1817851446, 2118205247, -184354825, -2091922228, 
        1750873140, 1374987685, -785062427, -116854287, -493653647, -1418471208, 1649619249, 708777237, 135005188, -1789737017, 
        1181033251, -1654733885, 807933976, 933336726, 168756485, 800430746, 235472647, 607523346, 463175808, -549592350, 
        -853087253, 1315514151, 2144187058, -358648459, 303761673, 496927619, 1484008492, 875436570, 908925723, -592286098, 
        -1259447718, 1543217312, -1527360942, 1984772923, -1218324778, 2110698419, 1383803177, -583080989, 1584475951, 328696964, 
        -1493871789, -1184312879, 0, -1054020115, 1080041504, -484442884, 2043195825, -1225958565, -725718422, -1924740149, 
        1742323390, 1917532473, -1797371318, -1730917300, -1326950312, -2058694705, -1150562096, -987041809, 1340451498, -317260805, 
        -2033892541, -1697166003, 1716859699, 294946181, -1966127803, -384763399, 67502594, -25067649, -1594863536, 2017737788, 
        632987551, 1273211048, -1561112239, 1576969123, -2134884288, 92966799, 1068339858, 566009245, 1883781176, -251333131, 
        1675607228, 2009183926, -1351230758, 1113792801, 540020752, -451215361, -49351693, -1083321646, -2125673011, 403966988, 
        641012499, -1020269332, -1092526241, 899848087, -1999879100, 775493399, -1822964540, 1441965991, -58556802, 2051489085, 
        -928226204, -1159242403, 841685273, -426413197, -1063231392, 429425025, -1630449841, -1551901476, 1147544098, 1417554474, 
        1001099408, 193169544, -1932900794, -953553170, 1809037496, 675025940, -1485185314, -1126015394, 371002123, -1384719397, 
        -616832800, 1683370546, 1951283770, 337512970, -1831122615, 201983494, 1215046692, -1192993700, -1621245246, -1116810285, 
        1139780780, -995728798, 967348625, 832869781, -751311644, -225740423, -718084121, -1958491960, 1851340599, -625513107, 
        25988493, -1318791723, -1663938994, 1239460265, -659264404, -1392880042, -217582348, -819598614, -894474907, -191989126, 
        1206496942, 270010376, 1876277946, -259491720, 1248797989, 1550986798, 941890588, 1475454630, 1942467764, -1756248378, 
        -886839064, -1585652259, -392399756, 1042358047, -1763882165, 1641856445, 226921355, 260409994, -527404944, 2084716094, 
        1908716981, -861247898, -1864873912, 100991747, -150866186, 470945294, -1029480095, 1784624437, -1359390889, 1775286713, 
        395413126, -1722236479, 975641885, 666476190, -650583583, -351012616, 733190296, 573772049, -759469719, -1452221991, 
        126455438, 866620564, 766942107, 1008868894, 361924487, -920589847, -2025206066, -1426107051, 1350051880, -1518673953, 
        59739276, 1509466529, 159418761, 437718285, 1708834751, -684595482, -2067381694, -793221016, -2101132991, 699439513, 
        1517759789, 504434447, 2076946608, -1459858348, 1842789307, 742004246 };
    zGp = new int[] { 
        1353184337, 1399144830, -1012656358, -1772214470, -882136261, -247096033, -1420232020, -1828461749, 1442459680, -160598355, 
        -1854485368, 625738485, -52959921, -674551099, -2143013594, -1885117771, 1230680542, 1729870373, -1743852987, -507445667, 
        41234371, 317738113, -1550367091, -956705941, -413167869, -1784901099, -344298049, -631680363, 763608788, -752782248, 
        694804553, 1154009486, 1787413109, 2021232372, 1799248025, -579749593, -1236278850, 397248752, 1722556617, -1271214467, 
        407560035, -2110711067, 1613975959, 1165972322, -529046351, -2068943941, 480281086, -1809118983, 1483229296, 436028815, 
        -2022908268, -1208452270, 601060267, -503166094, 1468997603, 715871590, 120122290, 63092015, -1703164538, -1526188077, 
        -226023376, -1297760477, -1167457534, 1552029421, 723308426, -1833666137, -252573709, -1578997426, -839591323, -708967162, 
        526529745, -1963022652, -1655493068, -1604979806, 853641733, 1978398372, 971801355, -1427152832, 111112542, 1360031421, 
        -108388034, 1023860118, -1375387939, 1186850381, -1249028975, 90031217, 1876166148, -15380384, 620468249, -1746289194, 
        -868007799, 2006899047, -1119688528, -2004121337, 945494503, -605108103, 1191869601, -384875908, -920746760, 0, 
        -2088337399, 1223502642, -1401941730, 1316117100, -67170563, 1446544655, 517320253, 658058550, 1691946762, 564550760, 
        -783000677, 976107044, -1318647284, 266819475, -761860428, -1634624741, 1338359936, -1574904735, 1766553434, 370807324, 
        179999714, -450191168, 1138762300, 488053522, 185403662, -1379431438, -1180125651, -928440812, -2061897385, 1275557295, 
        -1143105042, -44007517, -1624899081, -1124765092, -985962940, 880737115, 1982415755, -590994485, 1761406390, 1676797112, 
        -891538985, 277177154, 1076008723, 538035844, 2099530373, -130171950, 288553390, 1839278535, 1261411869, -214912292, 
        -330136051, -790380169, 1813426987, -1715900247, -95906799, 577038663, -997393240, 440397984, -668172970, -275762398, 
        -951170681, -1043253031, -22885748, 906744984, -813566554, 685669029, 646887386, -1530942145, -459458004, 227702864, 
        -1681105046, 1648787028, -1038905866, -390539120, 1593260334, -173030526, -1098883681, 2090061929, -1456614033, -1290656305, 
        999926984, -1484974064, 1852021992, 2075868123, 158869197, -199730834, 28809964, -1466282109, 1701746150, 2129067946, 
        147831841, -420997649, -644094022, -835293366, -737566742, -696471511, -1347247055, 824393514, 815048134, -1067015627, 
        935087732, -1496677636, -1328508704, 366520115, 1251476721, -136647615, 240176511, 804688151, -1915335306, 1303441219, 
        1414376140, -553347356, -474623586, 461924940, -1205916479, 2136040774, 82468509, 1563790337, 1937016826, 776014843, 
        1511876531, 1389550482, 861278441, 323475053, -1939744870, 2047648055, -1911228327, -1992551445, -299390514, 902390199, 
        -303751967, 1018251130, 1507840668, 1064563285, 2043548696, -1086863501, -355600557, 1537932639, 342834655, -2032450440, 
        -2114736182, 1053059257, 741614648, 1598071746, 1925389590, 203809468, -1958134744, 1100287487, 1895934009, -558691320, 
        -1662733096, -1866377628, 1636092795, 1890988757, 1952214088, 1113045200 };
    DyG = new int[] { 
        -1477160624, 1698790995, -1541989693, 1579629206, 1806384075, 1167925233, 1492823211, 65227667, -97509291, 1836494326, 
        1993115793, 1275262245, -672837636, -886389289, 1144333952, -1553812081, 1521606217, 465184103, 250234264, -1057071647, 
        1966064386, -263421678, -1756983901, -103584826, 1603208167, -1668147819, 2054012907, 1498584538, -2084645843, 561273043, 
        1776306473, -926314940, -1983744662, 2039411832, 1045993835, 1907959773, 1340194486, -1383534569, -1407137434, 986611124, 
        1256153880, 823846274, 860985184, 2136171077, 2003087840, -1368671356, -1602093540, 722008468, 1749577816, -45773031, 
        1826526343, -126135625, -747394269, 38499042, -1893735593, -1420466646, 686535175, -1028313341, 2076542618, 137876389, 
        -2027409166, -1514200142, 1778582202, -2112426660, 483363371, -1267095662, -234359824, -496415071, -187013683, -1106966827, 
        1647628575, -22625142, 1395537053, 1442030240, -511048398, -336157579, -326956231, -278904662, -1619960314, 275692881, 
        -1977532679, 115185213, 88006062, -1108980410, -1923837515, 1573155077, -737803153, 357589247, -73918172, -373434729, 
        1128303052, -1629919369, 1122545853, -1953953912, 1528424248, -288851493, 175939911, 256015593, 512030921, 0, 
        -2038429309, -315936184, 1880170156, 1918528590, -15794693, 948244310, -710001378, 959264295, -653325724, -1503893471, 
        1415289809, 775300154, 1728711857, -413691121, -1762741038, -1852105826, -977239985, 551313826, 1266113129, 437394454, 
        -1164713462, 715178213, -534627261, 387650077, 218697227, -947129683, -1464455751, -1457646392, 435246981, 125153100, 
        -577114437, 1618977789, 637663135, -177054532, 996558021, 2130402100, 692292470, -970732580, -51530136, -236668829, 
        -600713270, -2057092592, 580326208, 298222624, 608863613, 1035719416, 855223825, -1591097491, 798891339, 817028339, 
        1384517100, -473860144, 380840812, -1183798887, 1217663482, 1693009698, -1929598780, 1072734234, 746411736, -1875696913, 
        1313441735, -784803391, -1563783938, 198481974, -2114607409, -562387672, -1900553690, -1079165020, -1657131804, -1837608947, 
        -866162021, 1182684258, 328070850, -1193766680, -147247522, -1346141451, -2141347906, -1815058052, 768962473, 304467891, 
        -1716729797, 2098729127, 1671227502, -1153705093, 2015808777, 408514292, -1214583807, -1706064984, 1855317605, -419452290, 
        -809754360, -401215514, -1679312167, 913263310, 161475284, 2091919830, -1297862225, 591342129, -1801075152, 1721906624, 
        -1135709129, -897385306, -795811664, -660131051, -1744506550, -622050825, 1355644686, -158263505, -699566451, -1326496947, 
        1303039060, 76997855, -1244553501, -2006299621, 523026872, 1365591679, -362898172, 898367837, 1955068531, 1091304238, 
        493335386, -757362094, 1443948851, 1205234963, 1641519756, 211892090, 351820174, 1007938441, 665439982, -916342987, 
        -451091987, -1320715716, -539845543, 1945261375, -837543815, 935818175, -839429142, -1426235557, 1866325780, -616269690, 
        -206583167, -999769794, 874788908, 1084473951, -1021503886, 635616268, 1228679307, -1794244799, 27801969, -1291056930, 
        -457910116, -1051302768, -2067039391, -1238182544, 1550600308, 1471729730 };
    div = new int[] { 
        -195997529, 1098797925, 387629988, 658151006, -1422144661, -1658851003, -89347240, -481586429, 807425530, 1991112301, 
        -863465098, 49620300, -447742761, 717608907, 891715652, 1656065955, -1310832294, -1171953893, -364537842, -27401792, 
        801309301, 1283527408, 1183687575, -747911431, -1895569569, -1844079204, 1841294202, 1385552473, -1093390973, 1951978273, 
        -532076183, -913423160, -1032492407, -1896580999, 1486449470, -1188569743, -507595185, -1997531219, 550069932, -830622662, 
        -547153846, 451248689, 1368875059, 1398949247, 1689378935, 1807451310, -2114052960, 150574123, 1215322216, 1167006205, 
        -560691348, 2069018616, 1940595667, 1265820162, 534992783, 1432758955, -340654296, -1255210046, -981034373, 936617224, 
        674296455, -1088179547, 50510442, 384654466, -813028580, 2041025204, 133427442, 1766760930, -630862348, 84334014, 
        886120290, -1497068802, 775200083, -207445931, -1979370783, -156994069, -2096416276, 1614850799, 1901987487, 1857900816, 
        557775242, -577356538, 1054715397, -431143235, 1418835341, -999226019, 100954068, 1348534037, -1743182597, -1110009879, 
        1082772547, -647530594, -391070398, -1995994997, 434583643, -931537938, 2090944266, 1115482383, -2064070370, 0, 
        -2146860154, 724715757, 287222896, 1517047410, 251526143, -2062592456, -1371726123, 758523705, 252339417, 1550328230, 
        1536938324, 908343854, 168604007, 1469255655, -290139498, -1692688751, -1065332795, -597581280, 2002413899, 303830554, 
        -1813902662, -1597971158, 574374880, 454171927, 151915277, -1947030073, -1238517336, 504678569, -245922535, 1974422535, 
        -1712407587, 2141453664, 33005350, 1918680309, 1715782971, -77908866, 1133213225, 600562886, -306812676, -457677839, 
        836225756, 1665273989, -1760346078, -964419567, 1250262308, -1143801795, -106032846, 700935585, -1642247377, -1294142672, 
        -2045907886, -1049112349, -1288999914, 1890163129, -1810761144, -381214108, -56048500, -257942977, 2102843436, 857927568, 
        1233635150, 953795025, -896729438, -728222197, -173617279, 2057644254, -1210440050, -1388337985, 976020637, 2018512274, 
        1600822220, 2119459398, -1913208301, -661591880, 959340279, -1014827601, 1570750080, -798393197, -714102483, 634368786, 
        -1396163687, 403744637, -1662488989, 1004239803, 650971512, 1500443672, -1695809097, 1334028442, -1780062866, -5603610, 
        -1138685745, 368043752, -407184997, 1867173430, -1612000247, -1339435396, -1540247630, 1059729699, -1513738092, -1573535642, 
        1316239292, -2097371446, -1864322864, -1489824296, 82922136, -331221030, -847311280, -1860751370, 1299615190, -280801872, 
        -1429449651, -1763385596, -778116171, 1783372680, 750893087, 1699118929, 1587348714, -1946067659, -2013629580, 201010753, 
        1739807261, -611167534, 283718486, -697494713, -677737375, -1590199796, -128348652, 334203196, -1446056409, 1639396809, 
        484568549, 1199193265, -761505313, -229294221, 337148366, -948715721, -145495347, -44082262, 1038029935, 1148749531, 
        -1345682957, 1756970692, 607661108, -1547542720, 488010435, -490992603, 1009290057, 234832277, -1472630527, 201907891, 
        -1260872476, 1449431233, -881106556, 852848822, 1816687708, -1194311081 };
    IjH = new int[] { 
        1364240372, 2119394625, 449029143, 982933031, 1003187115, 535905693, -1398056710, 1267925987, 542505520, -1376359050, 
        -2003732788, -182105086, 1341970405, -975713494, 645940277, -1248877726, -565617999, 627514298, 1167593194, 1575076094, 
        -1023249105, -2129465268, -1918658746, 1808202195, 65494927, 362126482, -1075086739, -1780852398, -735214658, 1490231668, 
        1227450848, -1908094775, 1969916354, -193431154, -1721024936, 668823993, -1095348255, -266883704, -916018144, 2108963534, 
        1662536415, -444452582, -1755303087, 1648721747, -1310689436, -1148932501, -31678335, -107730168, 1884842056, -1894122171, 
        -1803064098, 1387788411, -1423715469, 1927414347, -480800993, 1714072405, -1308153621, 788775605, -2036696123, -744159177, 
        821200680, 598910399, 45771267, -312704490, -1976886065, -1483557767, -202313209, 1319232105, 1707996378, 114671109, 
        -786472396, -997523802, 882725678, -1566550541, 87220618, -1535775754, 188345475, 1084944224, 1577492337, -1118760850, 
        1056541217, -1774385443, -575797954, 1296481766, -1850372780, 1896177092, 74437638, 1627329872, 421854104, -694687299, 
        -1983102144, 1735892697, -1329773848, 126389129, -415737063, 2044456648, -1589179780, 2095648578, -121037180, 0, 
        159614592, 843640107, 514617361, 1817080410, -33816818, 257308805, 1025430958, 908540205, 174381327, 1747035740, 
        -1680780197, 607792694, 212952842, -1827674281, -1261267218, 463376795, -2142255680, 1638015196, 1516850039, 471210514, 
        -502613357, -1058723168, 1011081250, 303896347, 235605257, -223492213, 767142070, 348694814, 1468340721, -1353971851, 
        -289677927, -1543675777, -140564991, 1555887474, 1153776486, 1530167035, -1955190461, -874723805, -1234633491, -1201409564, 
        -674571215, 1108378979, 322970263, -2078273082, -2055396278, -755483205, -1374604551, -949116631, 491466654, -588042062, 
        233591430, 2010178497, 728503987, -1449543312, 301615252, 1193436393, -1463513860, -1608892432, 1457007741, 586125363, 
        -2016981431, -641609416, -1929469238, -1741288492, -1496350219, -1524048262, -635007305, 1067761581, 753179962, 1343066744, 
        1788595295, 1415726718, -155053171, -1863796520, 777975609, -2097827901, -1614905251, 1769771984, 1873358293, -810347995, 
        -935618132, 279411992, -395418724, -612648133, -855017434, 1861490777, -335431782, -2086102449, -429560171, -1434523905, 
        554225596, -270079979, -1160143897, 1255028335, -355202657, 701922480, 833598116, 707863359, -969894747, 901801634, 
        1949809742, -56178046, -525283184, 857069735, -246769660, 1106762476, 2131644621, 389019281, 1989006925, 1129165039, 
        -866890326, -455146346, -1629243951, 1276872810, -1044898004, 1182749029, -1660622242, 22885772, -93096825, -80854773, 
        -1285939865, -1840065829, -382511600, 1829980118, -1702075945, 930745505, 1502483704, -343327725, -823253079, -1221211807, 
        -504503012, 2050797895, -1671831598, 1430221810, 410635796, 1941911495, 1407897079, 1599843069, -552308931, 2022103876, 
        -897453137, -1187068824, 942421028, -1033944925, 376619805, -1140054558, 680216892, -12479219, 963707304, 148812556, 
        -660806476, 1687208278, 2069988555, -714033614, 1215585388, -800958536 };
  }
  
  private int[][] Dne(byte[] paramArrayOfbyte, boolean paramBoolean) {
    int i = paramArrayOfbyte.length / 4;
    if ((i == 4 || i == 6 || i == 8) && i * 4 == paramArrayOfbyte.length) {
      this.Dne = i + 6;
      int[][] arrayOfInt = new int[this.Dne + 1][4];
      byte b = 0;
      int j = 0;
      while (j < paramArrayOfbyte.length) {
        arrayOfInt[b >> 2][b & 0x3] = paramArrayOfbyte[j] & 0xFF | (paramArrayOfbyte[j + 1] & 0xFF) << 8 | (paramArrayOfbyte[j + 2] & 0xFF) << 16 | paramArrayOfbyte[j + 3] << 24;
        j += 4;
        b++;
      } 
      int k = this.Dne + 1 << 2;
      for (j = i; j < k; j++) {
        int m = arrayOfInt[j - 1 >> 2][j - 1 & 0x3];
        if (j % i == 0) {
          m = bzF(Dne(m, 8)) ^ Dne[j / i - 1];
        } else if (i > 6 && j % i == 4) {
          m = bzF(m);
        } 
        arrayOfInt[j >> 2][j & 0x3] = arrayOfInt[j - i >> 2][j - i & 0x3] ^ m;
      } 
      if (!paramBoolean)
        for (byte b1 = 1; b1 < this.Dne; b1++) {
          for (j = 0; j < 4; j++)
            arrayOfInt[b1][j] = FWm(arrayOfInt[b1][j]); 
        }  
      return arrayOfInt;
    } 
    throw new IllegalArgumentException("Key length not 128/192/256 bits.");
  }
}


/* Location:              C:\Users\fract\Downloads\ERROR422.jar!\pnN.class
 * Java compiler version: 8 (52.0)
 * JD-Core Version:       1.1.3
 */