public class pOO implements gDn {
  private final boolean FWm;
  
  private final gDn Dne;
  
  private final boolean Dne;
  
  public float Dne(double paramDouble) {
    float f = FWm() - Dne();
    return Dne() + f * (float)paramDouble / 16.0F;
  }
  
  public int bzF() {
    // Byte code:
    //   0: aload_0
    //   1: getfield Dne : LgDn;
    //   4: invokeinterface bzF : ()I
    //   9: ireturn
  }
  
  public int FWm() {
    // Byte code:
    //   0: aload_0
    //   1: getfield Dne : LgDn;
    //   4: invokeinterface FWm : ()I
    //   9: ireturn
  }
  
  public float Dne() {
    // Byte code:
    //   0: aload_0
    //   1: getfield Dne : Z
    //   4: ifeq -> 19
    //   7: aload_0
    //   8: getfield Dne : LgDn;
    //   11: invokeinterface FWm : ()F
    //   16: goto -> 28
    //   19: aload_0
    //   20: getfield Dne : LgDn;
    //   23: invokeinterface Dne : ()F
    //   28: freturn
  }
  
  public float FWm() {
    // Byte code:
    //   0: aload_0
    //   1: getfield Dne : Z
    //   4: ifeq -> 19
    //   7: aload_0
    //   8: getfield Dne : LgDn;
    //   11: invokeinterface Dne : ()F
    //   16: goto -> 28
    //   19: aload_0
    //   20: getfield Dne : LgDn;
    //   23: invokeinterface FWm : ()F
    //   28: freturn
  }
  
  public float bzF() {
    // Byte code:
    //   0: aload_0
    //   1: getfield FWm : Z
    //   4: ifeq -> 19
    //   7: aload_0
    //   8: getfield Dne : LgDn;
    //   11: invokeinterface bzF : ()F
    //   16: goto -> 28
    //   19: aload_0
    //   20: getfield Dne : LgDn;
    //   23: invokeinterface bzF : ()F
    //   28: freturn
  }
  
  public float Qnq() {
    // Byte code:
    //   0: aload_0
    //   1: getfield FWm : Z
    //   4: ifeq -> 19
    //   7: aload_0
    //   8: getfield Dne : LgDn;
    //   11: invokeinterface bzF : ()F
    //   16: goto -> 28
    //   19: aload_0
    //   20: getfield Dne : LgDn;
    //   23: invokeinterface Qnq : ()F
    //   28: freturn
  }
  
  public String Dne() {
    // Byte code:
    //   0: aload_0
    //   1: getfield Dne : LgDn;
    //   4: invokeinterface Dne : ()Ljava/lang/String;
    //   9: areturn
  }
  
  public int Dne() {
    // Byte code:
    //   0: aload_0
    //   1: getfield Dne : LgDn;
    //   4: invokeinterface Dne : ()I
    //   9: ireturn
  }
  
  public int Qnq() {
    // Byte code:
    //   0: aload_0
    //   1: getfield Dne : LgDn;
    //   4: invokeinterface Qnq : ()I
    //   9: ireturn
  }
  
  public pOO(gDn paramgDn, boolean paramBoolean1, boolean paramBoolean2) {
    this.Dne = paramgDn;
    this.Dne = paramBoolean1;
    this.FWm = paramBoolean2;
  }
  
  public float FWm(double paramDouble) {
    float f = Qnq() - bzF();
    return bzF() + f * (float)paramDouble / 16.0F;
  }
}


/* Location:              C:\Users\fract\Downloads\ERROR422.jar!\pOO.class
 * Java compiler version: 8 (52.0)
 * JD-Core Version:       1.1.3
 */