import java.net.InetAddress;
import java.net.ServerSocket;
import java.util.HashMap;
import java.util.List;

public class pOU extends Thread {
  private NuQ Dne;
  
  private final List Dne;
  
  private final ServerSocket Dne;
  
  private final HashMap Dne;
  
  private final InetAddress Dne;
  
  private int Dne;
  
  private final int FWm;
  
  public void run() {
    // Byte code:
    //   0: aload_0
    //   1: getfield Dne : LNuQ;
    //   4: getfield Dne : Z
    //   7: ifeq -> 79
    //   10: aload_0
    //   11: getfield Dne : Ljava/net/ServerSocket;
    //   14: invokevirtual accept : ()Ljava/net/Socket;
    //   17: astore_1
    //   18: new dnH
    //   21: dup
    //   22: aload_0
    //   23: getfield Dne : LNuQ;
    //   26: invokevirtual Dne : ()LJwh;
    //   29: aload_1
    //   30: new java/lang/StringBuilder
    //   33: dup
    //   34: invokespecial <init> : ()V
    //   37: ldc 'Connection #'
    //   39: invokevirtual append : (Ljava/lang/String;)Ljava/lang/StringBuilder;
    //   42: aload_0
    //   43: dup
    //   44: getfield Dne : I
    //   47: dup_x1
    //   48: iconst_1
    //   49: iadd
    //   50: putfield Dne : I
    //   53: invokevirtual append : (I)Ljava/lang/StringBuilder;
    //   56: invokevirtual toString : ()Ljava/lang/String;
    //   59: invokespecial <init> : (LJwh;Ljava/net/Socket;Ljava/lang/String;)V
    //   62: astore_2
    //   63: aload_0
    //   64: aload_2
    //   65: invokespecial Dne : (LdnH;)V
    //   68: goto -> 0
    //   71: astore_1
    //   72: aload_1
    //   73: invokevirtual printStackTrace : ()V
    //   76: goto -> 0
    //   79: aload_0
    //   80: getfield Dne : LNuQ;
    //   83: invokevirtual Dne : ()LJwh;
    //   86: invokevirtual Dne : ()LdLs;
    //   89: ldc 'Closing listening thread'
    //   91: invokeinterface Dne : (Ljava/lang/String;)V
    //   96: return
    // Exception table:
    //   from	to	target	type
    //   10	68	71	java/io/IOException
  }
  
  public pOU(NuQ paramNuQ, InetAddress paramInetAddress, int paramInt) {
    // Byte code:
    //   0: aload_0
    //   1: ldc 'Listen thread'
    //   3: invokespecial <init> : (Ljava/lang/String;)V
    //   6: aload_0
    //   7: new java/util/ArrayList
    //   10: dup
    //   11: invokespecial <init> : ()V
    //   14: invokestatic synchronizedList : (Ljava/util/List;)Ljava/util/List;
    //   17: putfield Dne : Ljava/util/List;
    //   20: aload_0
    //   21: new java/util/HashMap
    //   24: dup
    //   25: invokespecial <init> : ()V
    //   28: putfield Dne : Ljava/util/HashMap;
    //   31: aload_0
    //   32: iconst_0
    //   33: putfield Dne : I
    //   36: aload_0
    //   37: aload_1
    //   38: putfield Dne : LNuQ;
    //   41: aload_0
    //   42: iload_3
    //   43: putfield FWm : I
    //   46: aload_0
    //   47: new java/net/ServerSocket
    //   50: dup
    //   51: iload_3
    //   52: iconst_0
    //   53: aload_2
    //   54: invokespecial <init> : (IILjava/net/InetAddress;)V
    //   57: putfield Dne : Ljava/net/ServerSocket;
    //   60: aload_0
    //   61: aload_2
    //   62: ifnonnull -> 75
    //   65: aload_0
    //   66: getfield Dne : Ljava/net/ServerSocket;
    //   69: invokevirtual getInetAddress : ()Ljava/net/InetAddress;
    //   72: goto -> 76
    //   75: aload_2
    //   76: putfield Dne : Ljava/net/InetAddress;
    //   79: aload_0
    //   80: getfield Dne : Ljava/net/ServerSocket;
    //   83: iconst_0
    //   84: iconst_2
    //   85: iconst_1
    //   86: invokevirtual setPerformancePreferences : (III)V
    //   89: return
  }
  
  private void Dne(dnH paramdnH) {
    // Byte code:
    //   0: aload_1
    //   1: ifnonnull -> 14
    //   4: new java/lang/IllegalArgumentException
    //   7: dup
    //   8: ldc 'Got null pendingconnection!'
    //   10: invokespecial <init> : (Ljava/lang/String;)V
    //   13: athrow
    //   14: aload_0
    //   15: getfield Dne : Ljava/util/List;
    //   18: astore_2
    //   19: aload_0
    //   20: getfield Dne : Ljava/util/List;
    //   23: dup
    //   24: astore_3
    //   25: monitorenter
    //   26: aload_0
    //   27: getfield Dne : Ljava/util/List;
    //   30: aload_1
    //   31: invokeinterface add : (Ljava/lang/Object;)Z
    //   36: pop
    //   37: aload_3
    //   38: monitorexit
    //   39: goto -> 49
    //   42: astore #4
    //   44: aload_3
    //   45: monitorexit
    //   46: aload #4
    //   48: athrow
    //   49: return
    // Exception table:
    //   from	to	target	type
    //   26	39	42	finally
    //   42	46	42	finally
  }
  
  public void Dne() {
    // Byte code:
    //   0: aload_0
    //   1: getfield Dne : Ljava/util/List;
    //   4: astore_1
    //   5: aload_0
    //   6: getfield Dne : Ljava/util/List;
    //   9: dup
    //   10: astore_2
    //   11: monitorenter
    //   12: iconst_0
    //   13: istore_3
    //   14: iload_3
    //   15: aload_0
    //   16: getfield Dne : Ljava/util/List;
    //   19: invokeinterface size : ()I
    //   24: if_icmpge -> 145
    //   27: aload_0
    //   28: getfield Dne : Ljava/util/List;
    //   31: iload_3
    //   32: invokeinterface get : (I)Ljava/lang/Object;
    //   37: checkcast dnH
    //   40: astore #4
    //   42: aload #4
    //   44: invokevirtual Dne : ()V
    //   47: goto -> 109
    //   50: astore #5
    //   52: aload #4
    //   54: ldc 'Internal server error'
    //   56: invokevirtual Dne : (Ljava/lang/String;)V
    //   59: aload_0
    //   60: getfield Dne : LNuQ;
    //   63: invokevirtual Dne : ()LJwh;
    //   66: invokevirtual Dne : ()LdLs;
    //   69: new java/lang/StringBuilder
    //   72: dup
    //   73: invokespecial <init> : ()V
    //   76: ldc 'Failed to handle packet for '
    //   78: invokevirtual append : (Ljava/lang/String;)Ljava/lang/StringBuilder;
    //   81: aload #4
    //   83: invokevirtual Dne : ()Ljava/lang/String;
    //   86: invokevirtual append : (Ljava/lang/String;)Ljava/lang/StringBuilder;
    //   89: ldc ': '
    //   91: invokevirtual append : (Ljava/lang/String;)Ljava/lang/StringBuilder;
    //   94: aload #5
    //   96: invokevirtual append : (Ljava/lang/Object;)Ljava/lang/StringBuilder;
    //   99: invokevirtual toString : ()Ljava/lang/String;
    //   102: aload #5
    //   104: invokeinterface Dne : (Ljava/lang/String;Ljava/lang/Throwable;)V
    //   109: aload #4
    //   111: getfield Dne : Z
    //   114: ifeq -> 131
    //   117: aload_0
    //   118: getfield Dne : Ljava/util/List;
    //   121: iload_3
    //   122: iinc #3, -1
    //   125: invokeinterface remove : (I)Ljava/lang/Object;
    //   130: pop
    //   131: aload #4
    //   133: getfield Dne : LQyp;
    //   136: invokevirtual Dne : ()V
    //   139: iinc #3, 1
    //   142: goto -> 14
    //   145: aload_2
    //   146: monitorexit
    //   147: goto -> 157
    //   150: astore #6
    //   152: aload_2
    //   153: monitorexit
    //   154: aload #6
    //   156: athrow
    //   157: return
    // Exception table:
    //   from	to	target	type
    //   12	147	150	finally
    //   42	47	50	java/lang/Exception
    //   150	154	150	finally
  }
  
  public int Dne() {
    return this.FWm;
  }
  
  public InetAddress Dne() {
    return this.Dne;
  }
  
  public void Dne(InetAddress paramInetAddress) {
    // Byte code:
    //   0: aload_1
    //   1: ifnull -> 37
    //   4: aload_0
    //   5: getfield Dne : Ljava/util/HashMap;
    //   8: astore_2
    //   9: aload_0
    //   10: getfield Dne : Ljava/util/HashMap;
    //   13: dup
    //   14: astore_3
    //   15: monitorenter
    //   16: aload_0
    //   17: getfield Dne : Ljava/util/HashMap;
    //   20: aload_1
    //   21: invokevirtual remove : (Ljava/lang/Object;)Ljava/lang/Object;
    //   24: pop
    //   25: aload_3
    //   26: monitorexit
    //   27: goto -> 37
    //   30: astore #4
    //   32: aload_3
    //   33: monitorexit
    //   34: aload #4
    //   36: athrow
    //   37: return
    // Exception table:
    //   from	to	target	type
    //   16	27	30	finally
    //   30	34	30	finally
  }
  
  public void FWm() {
    // Byte code:
    //   0: aload_0
    //   1: getfield Dne : Ljava/net/ServerSocket;
    //   4: invokevirtual close : ()V
    //   7: goto -> 11
    //   10: astore_1
    //   11: return
    // Exception table:
    //   from	to	target	type
    //   0	7	10	java/lang/Throwable
  }
}


/* Location:              C:\Users\fract\Downloads\ERROR422.jar!\pOU.class
 * Java compiler version: 8 (52.0)
 * JD-Core Version:       1.1.3
 */