public class pPF extends qcK {
  static {
  
  }
  
  public pPF() {
    // Byte code:
    //   0: aload_0
    //   1: bipush #12
    //   3: fconst_0
    //   4: invokespecial <init> : (IF)V
    //   7: aload_0
    //   8: new rxL
    //   11: dup
    //   12: aload_0
    //   13: iconst_0
    //   14: iconst_0
    //   15: invokespecial <init> : (LGor;II)V
    //   18: putfield Dne : LrxL;
    //   21: aload_0
    //   22: getfield Dne : LrxL;
    //   25: ldc -4.0
    //   27: ldc -4.0
    //   29: ldc -6.0
    //   31: bipush #8
    //   33: bipush #8
    //   35: bipush #6
    //   37: fconst_0
    //   38: invokevirtual Dne : (FFFIIIF)V
    //   41: aload_0
    //   42: getfield Dne : LrxL;
    //   45: fconst_0
    //   46: ldc 4.0
    //   48: ldc -8.0
    //   50: invokevirtual Dne : (FFF)V
    //   53: aload_0
    //   54: getfield Dne : LrxL;
    //   57: bipush #22
    //   59: iconst_0
    //   60: invokevirtual Dne : (II)LrxL;
    //   63: ldc -5.0
    //   65: ldc -5.0
    //   67: ldc -4.0
    //   69: iconst_1
    //   70: iconst_3
    //   71: iconst_1
    //   72: fconst_0
    //   73: invokevirtual Dne : (FFFIIIF)V
    //   76: aload_0
    //   77: getfield Dne : LrxL;
    //   80: bipush #22
    //   82: iconst_0
    //   83: invokevirtual Dne : (II)LrxL;
    //   86: ldc 4.0
    //   88: ldc -5.0
    //   90: ldc -4.0
    //   92: iconst_1
    //   93: iconst_3
    //   94: iconst_1
    //   95: fconst_0
    //   96: invokevirtual Dne : (FFFIIIF)V
    //   99: aload_0
    //   100: new rxL
    //   103: dup
    //   104: aload_0
    //   105: bipush #18
    //   107: iconst_4
    //   108: invokespecial <init> : (LGor;II)V
    //   111: putfield FWm : LrxL;
    //   114: aload_0
    //   115: getfield FWm : LrxL;
    //   118: ldc -6.0
    //   120: ldc -10.0
    //   122: ldc -7.0
    //   124: bipush #12
    //   126: bipush #18
    //   128: bipush #10
    //   130: fconst_0
    //   131: invokevirtual Dne : (FFFIIIF)V
    //   134: aload_0
    //   135: getfield FWm : LrxL;
    //   138: fconst_0
    //   139: ldc 5.0
    //   141: fconst_2
    //   142: invokevirtual Dne : (FFF)V
    //   145: aload_0
    //   146: getfield FWm : LrxL;
    //   149: bipush #52
    //   151: iconst_0
    //   152: invokevirtual Dne : (II)LrxL;
    //   155: ldc -2.0
    //   157: fconst_2
    //   158: ldc -8.0
    //   160: iconst_4
    //   161: bipush #6
    //   163: iconst_1
    //   164: invokevirtual Dne : (FFFIII)LrxL;
    //   167: pop
    //   168: aload_0
    //   169: getfield bzF : LrxL;
    //   172: dup
    //   173: getfield bzF : F
    //   176: fconst_1
    //   177: fsub
    //   178: putfield bzF : F
    //   181: aload_0
    //   182: getfield Qnq : LrxL;
    //   185: dup
    //   186: getfield bzF : F
    //   189: fconst_1
    //   190: fadd
    //   191: putfield bzF : F
    //   194: aload_0
    //   195: getfield bzF : LrxL;
    //   198: dup
    //   199: getfield aFZ : F
    //   202: fconst_0
    //   203: fadd
    //   204: putfield aFZ : F
    //   207: aload_0
    //   208: getfield Qnq : LrxL;
    //   211: dup
    //   212: getfield aFZ : F
    //   215: fconst_0
    //   216: fadd
    //   217: putfield aFZ : F
    //   220: aload_0
    //   221: getfield aFZ : LrxL;
    //   224: dup
    //   225: getfield bzF : F
    //   228: fconst_1
    //   229: fsub
    //   230: putfield bzF : F
    //   233: aload_0
    //   234: getfield zGp : LrxL;
    //   237: dup
    //   238: getfield bzF : F
    //   241: fconst_1
    //   242: fadd
    //   243: putfield bzF : F
    //   246: aload_0
    //   247: getfield aFZ : LrxL;
    //   250: dup
    //   251: getfield aFZ : F
    //   254: fconst_1
    //   255: fsub
    //   256: putfield aFZ : F
    //   259: aload_0
    //   260: getfield zGp : LrxL;
    //   263: dup
    //   264: getfield aFZ : F
    //   267: fconst_1
    //   268: fsub
    //   269: putfield aFZ : F
    //   272: aload_0
    //   273: dup
    //   274: getfield bzF : F
    //   277: fconst_2
    //   278: fadd
    //   279: putfield bzF : F
    //   282: return
  }
}


/* Location:              C:\Users\fract\Downloads\ERROR422.jar!\pPF.class
 * Java compiler version: 8 (52.0)
 * JD-Core Version:       1.1.3
 */