import java.text.DateFormat;
import java.text.SimpleDateFormat;
import java.util.Collections;
import java.util.List;

public class PRD extends qVZ {
  private String bzF;
  
  private String[] Dne;
  
  private Pee Dne;
  
  private Pee FWm;
  
  private final DateFormat Dne;
  
  protected String Dne;
  
  private SWj Dne;
  
  protected qVZ Dne;
  
  private List FWm;
  
  private Pee Qnq;
  
  private int Dne = new SimpleDateFormat();
  
  private boolean Qnq;
  
  private boolean bzF;
  
  private String FWm;
  
  private Pee bzF;
  
  static String[] Dne(PRD paramPRD) {
    return paramPRD.Dne;
  }
  
  protected String FWm(int paramInt) {
    String str = ((pQP)this.FWm.get(paramInt)).FWm();
    if (str == null || geR.Dne(str)) {
      irb irb = irb.Dne();
      str = irb.Dne("selectWorld.world") + " " + (paramInt + 1);
    } 
    return str;
  }
  
  public PRD(qVZ paramqVZ) {
    this.Dne = "Select world";
    this.bzF = false;
    this.Dne = new String[3];
    this.Dne = paramqVZ;
  }
  
  static List Dne(PRD paramPRD) {
    return (List)paramPRD.FWm;
  }
  
  protected String Dne(int paramInt) {
    return ((pQP)this.FWm.get(paramInt)).Dne();
  }
  
  public void Dne(boolean paramBoolean, int paramInt) {
    if (this.Qnq) {
      this.Qnq = false;
      if (paramBoolean) {
        YiY yiY = this.Dne.Dne();
        yiY.Dne();
        yiY.FWm(Dne(paramInt));
        try {
          IjH();
        } catch (Ipl ipl) {
          ipl.printStackTrace();
        } 
      } 
      this.Dne.Dne(this);
    } 
  }
  
  static Pee bzF(PRD paramPRD) {
    return paramPRD.bzF;
  }
  
  public static sHC Dne(qVZ paramqVZ, String paramString, int paramInt) {
    irb irb = irb.Dne();
    String str1 = irb.Dne("selectWorld.deleteQuestion");
    String str2 = "'" + paramString + "' " + irb.Dne("selectWorld.deleteWarning");
    String str3 = irb.Dne("selectWorld.deleteButton");
    String str4 = irb.Dne("gui.cancel");
    return new sHC(paramqVZ, str1, str2, str3, str4, paramInt);
  }
  
  static DateFormat Dne(PRD paramPRD) {
    return paramPRD.Dne;
  }
  
  public void zGp() {
    // Byte code:
    //   0: invokestatic Dne : ()Lirb;
    //   3: astore_1
    //   4: aload_0
    //   5: getfield Dne : Ljava/util/List;
    //   8: aload_0
    //   9: new Pee
    //   12: dup
    //   13: iconst_1
    //   14: aload_0
    //   15: getfield FWm : I
    //   18: iconst_2
    //   19: idiv
    //   20: sipush #154
    //   23: isub
    //   24: aload_0
    //   25: getfield bzF : I
    //   28: bipush #52
    //   30: isub
    //   31: sipush #150
    //   34: bipush #20
    //   36: aload_1
    //   37: ldc 'selectWorld.select'
    //   39: invokevirtual Dne : (Ljava/lang/String;)Ljava/lang/String;
    //   42: invokespecial <init> : (IIIIILjava/lang/String;)V
    //   45: dup_x1
    //   46: putfield FWm : LPee;
    //   49: invokeinterface add : (Ljava/lang/Object;)Z
    //   54: pop
    //   55: aload_0
    //   56: getfield Dne : Ljava/util/List;
    //   59: new Pee
    //   62: dup
    //   63: iconst_3
    //   64: aload_0
    //   65: getfield FWm : I
    //   68: iconst_2
    //   69: idiv
    //   70: iconst_4
    //   71: iadd
    //   72: aload_0
    //   73: getfield bzF : I
    //   76: bipush #52
    //   78: isub
    //   79: sipush #150
    //   82: bipush #20
    //   84: aload_1
    //   85: ldc 'selectWorld.create'
    //   87: invokevirtual Dne : (Ljava/lang/String;)Ljava/lang/String;
    //   90: invokespecial <init> : (IIIIILjava/lang/String;)V
    //   93: invokeinterface add : (Ljava/lang/Object;)Z
    //   98: pop
    //   99: aload_0
    //   100: getfield Dne : Ljava/util/List;
    //   103: aload_0
    //   104: new Pee
    //   107: dup
    //   108: bipush #6
    //   110: aload_0
    //   111: getfield FWm : I
    //   114: iconst_2
    //   115: idiv
    //   116: sipush #154
    //   119: isub
    //   120: aload_0
    //   121: getfield bzF : I
    //   124: bipush #28
    //   126: isub
    //   127: bipush #72
    //   129: bipush #20
    //   131: aload_1
    //   132: ldc 'selectWorld.rename'
    //   134: invokevirtual Dne : (Ljava/lang/String;)Ljava/lang/String;
    //   137: invokespecial <init> : (IIIIILjava/lang/String;)V
    //   140: dup_x1
    //   141: putfield bzF : LPee;
    //   144: invokeinterface add : (Ljava/lang/Object;)Z
    //   149: pop
    //   150: aload_0
    //   151: getfield Dne : Ljava/util/List;
    //   154: aload_0
    //   155: new Pee
    //   158: dup
    //   159: iconst_2
    //   160: aload_0
    //   161: getfield FWm : I
    //   164: iconst_2
    //   165: idiv
    //   166: bipush #76
    //   168: isub
    //   169: aload_0
    //   170: getfield bzF : I
    //   173: bipush #28
    //   175: isub
    //   176: bipush #72
    //   178: bipush #20
    //   180: aload_1
    //   181: ldc 'selectWorld.delete'
    //   183: invokevirtual Dne : (Ljava/lang/String;)Ljava/lang/String;
    //   186: invokespecial <init> : (IIIIILjava/lang/String;)V
    //   189: dup_x1
    //   190: putfield Dne : LPee;
    //   193: invokeinterface add : (Ljava/lang/Object;)Z
    //   198: pop
    //   199: aload_0
    //   200: getfield Dne : Ljava/util/List;
    //   203: aload_0
    //   204: new Pee
    //   207: dup
    //   208: bipush #7
    //   210: aload_0
    //   211: getfield FWm : I
    //   214: iconst_2
    //   215: idiv
    //   216: iconst_4
    //   217: iadd
    //   218: aload_0
    //   219: getfield bzF : I
    //   222: bipush #28
    //   224: isub
    //   225: bipush #72
    //   227: bipush #20
    //   229: aload_1
    //   230: ldc 'selectWorld.recreate'
    //   232: invokevirtual Dne : (Ljava/lang/String;)Ljava/lang/String;
    //   235: invokespecial <init> : (IIIIILjava/lang/String;)V
    //   238: dup_x1
    //   239: putfield Qnq : LPee;
    //   242: invokeinterface add : (Ljava/lang/Object;)Z
    //   247: pop
    //   248: aload_0
    //   249: getfield Dne : Ljava/util/List;
    //   252: new Pee
    //   255: dup
    //   256: iconst_0
    //   257: aload_0
    //   258: getfield FWm : I
    //   261: iconst_2
    //   262: idiv
    //   263: bipush #82
    //   265: iadd
    //   266: aload_0
    //   267: getfield bzF : I
    //   270: bipush #28
    //   272: isub
    //   273: bipush #72
    //   275: bipush #20
    //   277: aload_1
    //   278: ldc 'gui.cancel'
    //   280: invokevirtual Dne : (Ljava/lang/String;)Ljava/lang/String;
    //   283: invokespecial <init> : (IIIIILjava/lang/String;)V
    //   286: invokeinterface add : (Ljava/lang/Object;)Z
    //   291: pop
    //   292: aload_0
    //   293: getfield FWm : LPee;
    //   296: iconst_0
    //   297: putfield Dne : Z
    //   300: aload_0
    //   301: getfield Dne : LPee;
    //   304: iconst_0
    //   305: putfield Dne : Z
    //   308: aload_0
    //   309: getfield bzF : LPee;
    //   312: iconst_0
    //   313: putfield Dne : Z
    //   316: aload_0
    //   317: getfield Qnq : LPee;
    //   320: iconst_0
    //   321: putfield Dne : Z
    //   324: return
  }
  
  static int Dne(PRD paramPRD, int paramInt) {
    return paramPRD.Dne = paramInt;
  }
  
  static String Dne(PRD paramPRD) {
    return paramPRD.FWm;
  }
  
  protected void Dne(Pee paramPee) {
    // Byte code:
    //   0: aload_1
    //   1: getfield Dne : Z
    //   4: ifeq -> 234
    //   7: aload_1
    //   8: getfield aFZ : I
    //   11: iconst_2
    //   12: if_icmpne -> 54
    //   15: aload_0
    //   16: aload_0
    //   17: getfield Dne : I
    //   20: invokevirtual FWm : (I)Ljava/lang/String;
    //   23: astore_2
    //   24: aload_2
    //   25: ifnull -> 51
    //   28: aload_0
    //   29: iconst_1
    //   30: putfield Qnq : Z
    //   33: aload_0
    //   34: aload_2
    //   35: aload_0
    //   36: getfield Dne : I
    //   39: invokestatic Dne : (LqVZ;Ljava/lang/String;I)LsHC;
    //   42: astore_3
    //   43: aload_0
    //   44: getfield Dne : Lnet/minecraft/client/Minecraft;
    //   47: aload_3
    //   48: invokevirtual Dne : (LqVZ;)V
    //   51: goto -> 234
    //   54: aload_1
    //   55: getfield aFZ : I
    //   58: iconst_1
    //   59: if_icmpne -> 73
    //   62: aload_0
    //   63: aload_0
    //   64: getfield Dne : I
    //   67: invokevirtual Dne : (I)V
    //   70: goto -> 234
    //   73: aload_1
    //   74: getfield aFZ : I
    //   77: iconst_3
    //   78: if_icmpne -> 99
    //   81: aload_0
    //   82: getfield Dne : Lnet/minecraft/client/Minecraft;
    //   85: new Lbd
    //   88: dup
    //   89: aload_0
    //   90: invokespecial <init> : (LqVZ;)V
    //   93: invokevirtual Dne : (LqVZ;)V
    //   96: goto -> 234
    //   99: aload_1
    //   100: getfield aFZ : I
    //   103: bipush #6
    //   105: if_icmpne -> 134
    //   108: aload_0
    //   109: getfield Dne : Lnet/minecraft/client/Minecraft;
    //   112: new CkO
    //   115: dup
    //   116: aload_0
    //   117: aload_0
    //   118: aload_0
    //   119: getfield Dne : I
    //   122: invokevirtual Dne : (I)Ljava/lang/String;
    //   125: invokespecial <init> : (LqVZ;Ljava/lang/String;)V
    //   128: invokevirtual Dne : (LqVZ;)V
    //   131: goto -> 234
    //   134: aload_1
    //   135: getfield aFZ : I
    //   138: ifne -> 155
    //   141: aload_0
    //   142: getfield Dne : Lnet/minecraft/client/Minecraft;
    //   145: aload_0
    //   146: getfield Dne : LqVZ;
    //   149: invokevirtual Dne : (LqVZ;)V
    //   152: goto -> 234
    //   155: aload_1
    //   156: getfield aFZ : I
    //   159: bipush #7
    //   161: if_icmpne -> 226
    //   164: new Lbd
    //   167: dup
    //   168: aload_0
    //   169: invokespecial <init> : (LqVZ;)V
    //   172: astore_2
    //   173: aload_0
    //   174: getfield Dne : Lnet/minecraft/client/Minecraft;
    //   177: invokevirtual Dne : ()LYiY;
    //   180: aload_0
    //   181: aload_0
    //   182: getfield Dne : I
    //   185: invokevirtual Dne : (I)Ljava/lang/String;
    //   188: iconst_0
    //   189: invokeinterface Dne : (Ljava/lang/String;Z)LiDE;
    //   194: astore_3
    //   195: aload_3
    //   196: invokeinterface Dne : ()LxoY;
    //   201: astore #4
    //   203: aload_3
    //   204: invokeinterface Dne : ()V
    //   209: aload_2
    //   210: aload #4
    //   212: invokevirtual Dne : (LxoY;)V
    //   215: aload_0
    //   216: getfield Dne : Lnet/minecraft/client/Minecraft;
    //   219: aload_2
    //   220: invokevirtual Dne : (LqVZ;)V
    //   223: goto -> 234
    //   226: aload_0
    //   227: getfield Dne : LSWj;
    //   230: aload_1
    //   231: invokevirtual Dne : (LPee;)V
    //   234: return
  }
  
  static Pee FWm(PRD paramPRD) {
    return paramPRD.Dne;
  }
  
  static int Dne(PRD paramPRD) {
    return paramPRD.Dne;
  }
  
  private void IjH() {
    YiY yiY = this.Dne.Dne();
    this.FWm = (String)yiY.Dne();
    Collections.sort((List<Comparable>)this.FWm);
    this.Dne = -1;
  }
  
  static String FWm(PRD paramPRD) {
    return (String)paramPRD.bzF;
  }
  
  public void Dne(int paramInt) {
    this.Dne.Dne((qVZ)null);
    if (this.bzF == null) {
      this.bzF = true;
      String str1 = Dne(paramInt);
      if (str1 == null)
        str1 = "World" + paramInt; 
      String str2 = FWm(paramInt);
      if (str2 == null)
        str2 = "World" + paramInt; 
      if (this.Dne.Dne().bzF(str1))
        this.Dne.Dne(str1, str2, (mrb)null); 
    } 
  }
  
  static Pee Qnq(PRD paramPRD) {
    return paramPRD.Qnq;
  }
  
  public void Dne() {
    // Byte code:
    //   0: invokestatic Dne : ()Lirb;
    //   3: astore_1
    //   4: aload_0
    //   5: aload_1
    //   6: ldc 'selectWorld.title'
    //   8: invokevirtual Dne : (Ljava/lang/String;)Ljava/lang/String;
    //   11: putfield Dne : Ljava/lang/String;
    //   14: aload_0
    //   15: invokespecial IjH : ()V
    //   18: goto -> 47
    //   21: astore_2
    //   22: aload_2
    //   23: invokevirtual printStackTrace : ()V
    //   26: aload_0
    //   27: getfield Dne : Lnet/minecraft/client/Minecraft;
    //   30: new qtV
    //   33: dup
    //   34: ldc 'Unable to load words'
    //   36: aload_2
    //   37: invokevirtual getMessage : ()Ljava/lang/String;
    //   40: invokespecial <init> : (Ljava/lang/String;Ljava/lang/String;)V
    //   43: invokevirtual Dne : (LqVZ;)V
    //   46: return
    //   47: aload_0
    //   48: aload_1
    //   49: ldc 'selectWorld.world'
    //   51: invokevirtual Dne : (Ljava/lang/String;)Ljava/lang/String;
    //   54: putfield FWm : Ljava/lang/String;
    //   57: aload_0
    //   58: aload_1
    //   59: ldc 'selectWorld.conversion'
    //   61: invokevirtual Dne : (Ljava/lang/String;)Ljava/lang/String;
    //   64: putfield bzF : Ljava/lang/String;
    //   67: aload_0
    //   68: getfield Dne : [Ljava/lang/String;
    //   71: getstatic XHL.FWm : LXHL;
    //   74: invokevirtual Dne : ()I
    //   77: aload_1
    //   78: ldc_w 'gameMode.survival'
    //   81: invokevirtual Dne : (Ljava/lang/String;)Ljava/lang/String;
    //   84: aastore
    //   85: aload_0
    //   86: getfield Dne : [Ljava/lang/String;
    //   89: getstatic XHL.bzF : LXHL;
    //   92: invokevirtual Dne : ()I
    //   95: aload_1
    //   96: ldc_w 'gameMode.creative'
    //   99: invokevirtual Dne : (Ljava/lang/String;)Ljava/lang/String;
    //   102: aastore
    //   103: aload_0
    //   104: getfield Dne : [Ljava/lang/String;
    //   107: getstatic XHL.Qnq : LXHL;
    //   110: invokevirtual Dne : ()I
    //   113: aload_1
    //   114: ldc_w 'gameMode.adventure'
    //   117: invokevirtual Dne : (Ljava/lang/String;)Ljava/lang/String;
    //   120: aastore
    //   121: aload_0
    //   122: new SWj
    //   125: dup
    //   126: aload_0
    //   127: invokespecial <init> : (LPRD;)V
    //   130: putfield Dne : LSWj;
    //   133: aload_0
    //   134: getfield Dne : LSWj;
    //   137: aload_0
    //   138: getfield Dne : Ljava/util/List;
    //   141: iconst_4
    //   142: iconst_5
    //   143: invokevirtual Dne : (Ljava/util/List;II)V
    //   146: aload_0
    //   147: invokevirtual zGp : ()V
    //   150: return
    // Exception table:
    //   from	to	target	type
    //   14	18	21	Ipl
  }
  
  static Pee Dne(PRD paramPRD) {
    return (Pee)paramPRD.FWm;
  }
  
  public void Dne(int paramInt1, int paramInt2, float paramFloat) {
    // Byte code:
    //   0: aload_0
    //   1: getfield Dne : LSWj;
    //   4: iload_1
    //   5: iload_2
    //   6: fload_3
    //   7: invokevirtual Dne : (IIF)V
    //   10: aload_0
    //   11: aload_0
    //   12: getfield Dne : LmsA;
    //   15: aload_0
    //   16: getfield Dne : Ljava/lang/String;
    //   19: aload_0
    //   20: getfield FWm : I
    //   23: iconst_2
    //   24: idiv
    //   25: bipush #20
    //   27: ldc_w 16777215
    //   30: invokevirtual Dne : (LmsA;Ljava/lang/String;III)V
    //   33: aload_0
    //   34: iload_1
    //   35: iload_2
    //   36: fload_3
    //   37: invokespecial Dne : (IIF)V
    //   40: return
  }
}


/* Location:              C:\Users\fract\Downloads\ERROR422.jar!\PRD.class
 * Java compiler version: 8 (52.0)
 * JD-Core Version:       1.1.3
 */