public class qgb {
  private FUH Dne;
  
  private boolean Dne = false;
  
  public qgb(FUH paramFUH) {
    this.Dne = paramFUH;
  }
  
  public void FWm() {
    // Byte code:
    //   0: aload_0
    //   1: getfield Dne : LFUH;
    //   4: aload_0
    //   5: getfield Dne : Z
    //   8: invokevirtual zGp : (Z)V
    //   11: aload_0
    //   12: iconst_0
    //   13: putfield Dne : Z
    //   16: return
  }
  
  public void Dne() {
    this.Dne = true;
  }
}


/* Location:              C:\Users\fract\Downloads\ERROR422.jar!\qgb.class
 * Java compiler version: 8 (52.0)
 * JD-Core Version:       1.1.3
 */