import java.util.List;

public class qlg {
  public static List Dne;
  
  public static Auk qLR;
  
  public static Auk oIf;
  
  public static Auk udO;
  
  public static Auk EyB;
  
  public static Auk Vxn;
  
  public static Auk trS;
  
  public static Auk zGp;
  
  public static Auk aFZ;
  
  public static Auk ooe;
  
  public static Auk OdI;
  
  public static Auk Fnk;
  
  public static Auk Dne;
  
  public static Auk kGO;
  
  public static Auk FWm;
  
  public static int bzF;
  
  public static Auk bzF;
  
  public static Auk vSL;
  
  public static int FWm;
  
  public static Auk FfS;
  
  public static Auk Zpi;
  
  public static Auk ceE;
  
  public static int Qnq;
  
  public static Auk RPx;
  
  public static Auk XHL;
  
  public static int Dne;
  
  public static Auk IjH;
  
  public static Auk div;
  
  public static Auk Qnq;
  
  public static Auk ATE;
  
  public static Auk DyG;
  
  public static Auk mrb;
  
  public static void Dne() {}
  
  static {
    // Byte code:
    //   0: new java/util/ArrayList
    //   3: dup
    //   4: invokespecial <init> : ()V
    //   7: putstatic qlg.Dne : Ljava/util/List;
    //   10: new Auk
    //   13: dup
    //   14: iconst_0
    //   15: ldc 'openInventory'
    //   17: iconst_0
    //   18: iconst_0
    //   19: getstatic dEr.TKg : LdEr;
    //   22: aconst_null
    //   23: checkcast Auk
    //   26: invokespecial <init> : (ILjava/lang/String;IILdEr;LAuk;)V
    //   29: invokevirtual Dne : ()LAuk;
    //   32: invokevirtual bzF : ()LAuk;
    //   35: putstatic qlg.Dne : LAuk;
    //   38: new Auk
    //   41: dup
    //   42: iconst_1
    //   43: ldc 'mineWood'
    //   45: iconst_2
    //   46: iconst_1
    //   47: getstatic zKP.udO : LzKP;
    //   50: getstatic qlg.Dne : LAuk;
    //   53: invokespecial <init> : (ILjava/lang/String;IILzKP;LAuk;)V
    //   56: invokevirtual bzF : ()LAuk;
    //   59: putstatic qlg.FWm : LAuk;
    //   62: new Auk
    //   65: dup
    //   66: iconst_2
    //   67: ldc 'buildWorkBench'
    //   69: iconst_4
    //   70: iconst_m1
    //   71: getstatic zKP.mlD : LzKP;
    //   74: getstatic qlg.FWm : LAuk;
    //   77: invokespecial <init> : (ILjava/lang/String;IILzKP;LAuk;)V
    //   80: invokevirtual bzF : ()LAuk;
    //   83: putstatic qlg.bzF : LAuk;
    //   86: new Auk
    //   89: dup
    //   90: iconst_3
    //   91: ldc 'buildPickaxe'
    //   93: iconst_4
    //   94: iconst_2
    //   95: getstatic dEr.udO : LdEr;
    //   98: getstatic qlg.bzF : LAuk;
    //   101: invokespecial <init> : (ILjava/lang/String;IILdEr;LAuk;)V
    //   104: invokevirtual bzF : ()LAuk;
    //   107: putstatic qlg.Qnq : LAuk;
    //   110: new Auk
    //   113: dup
    //   114: iconst_4
    //   115: ldc 'buildFurnace'
    //   117: iconst_3
    //   118: iconst_4
    //   119: getstatic zKP.haP : LzKP;
    //   122: getstatic qlg.Qnq : LAuk;
    //   125: invokespecial <init> : (ILjava/lang/String;IILzKP;LAuk;)V
    //   128: invokevirtual bzF : ()LAuk;
    //   131: putstatic qlg.aFZ : LAuk;
    //   134: new Auk
    //   137: dup
    //   138: iconst_5
    //   139: ldc 'acquireIron'
    //   141: iconst_1
    //   142: iconst_4
    //   143: getstatic dEr.IjH : LdEr;
    //   146: getstatic qlg.aFZ : LAuk;
    //   149: invokespecial <init> : (ILjava/lang/String;IILdEr;LAuk;)V
    //   152: invokevirtual bzF : ()LAuk;
    //   155: putstatic qlg.zGp : LAuk;
    //   158: new Auk
    //   161: dup
    //   162: bipush #6
    //   164: ldc 'buildHoe'
    //   166: iconst_2
    //   167: bipush #-3
    //   169: getstatic dEr.Wwe : LdEr;
    //   172: getstatic qlg.bzF : LAuk;
    //   175: invokespecial <init> : (ILjava/lang/String;IILdEr;LAuk;)V
    //   178: invokevirtual bzF : ()LAuk;
    //   181: putstatic qlg.DyG : LAuk;
    //   184: new Auk
    //   187: dup
    //   188: bipush #7
    //   190: ldc 'makeBread'
    //   192: iconst_m1
    //   193: bipush #-3
    //   195: getstatic dEr.rPc : LdEr;
    //   198: getstatic qlg.DyG : LAuk;
    //   201: invokespecial <init> : (ILjava/lang/String;IILdEr;LAuk;)V
    //   204: invokevirtual bzF : ()LAuk;
    //   207: putstatic qlg.div : LAuk;
    //   210: new Auk
    //   213: dup
    //   214: bipush #8
    //   216: ldc 'bakeCake'
    //   218: iconst_0
    //   219: bipush #-5
    //   221: getstatic dEr.iXU : LdEr;
    //   224: getstatic qlg.DyG : LAuk;
    //   227: invokespecial <init> : (ILjava/lang/String;IILdEr;LAuk;)V
    //   230: invokevirtual bzF : ()LAuk;
    //   233: putstatic qlg.IjH : LAuk;
    //   236: new Auk
    //   239: dup
    //   240: bipush #9
    //   242: ldc 'buildBetterPickaxe'
    //   244: bipush #6
    //   246: iconst_2
    //   247: getstatic dEr.ATE : LdEr;
    //   250: getstatic qlg.Qnq : LAuk;
    //   253: invokespecial <init> : (ILjava/lang/String;IILdEr;LAuk;)V
    //   256: invokevirtual bzF : ()LAuk;
    //   259: putstatic qlg.mrb : LAuk;
    //   262: new Auk
    //   265: dup
    //   266: bipush #10
    //   268: ldc 'cookFish'
    //   270: iconst_2
    //   271: bipush #6
    //   273: getstatic dEr.kSP : LdEr;
    //   276: getstatic qlg.aFZ : LAuk;
    //   279: invokespecial <init> : (ILjava/lang/String;IILdEr;LAuk;)V
    //   282: invokevirtual bzF : ()LAuk;
    //   285: putstatic qlg.XHL : LAuk;
    //   288: new Auk
    //   291: dup
    //   292: bipush #11
    //   294: ldc 'onARail'
    //   296: iconst_2
    //   297: iconst_3
    //   298: getstatic zKP.FYZ : LzKP;
    //   301: getstatic qlg.zGp : LAuk;
    //   304: invokespecial <init> : (ILjava/lang/String;IILzKP;LAuk;)V
    //   307: invokevirtual FWm : ()LAuk;
    //   310: invokevirtual bzF : ()LAuk;
    //   313: putstatic qlg.Zpi : LAuk;
    //   316: new Auk
    //   319: dup
    //   320: bipush #12
    //   322: ldc 'buildSword'
    //   324: bipush #6
    //   326: iconst_m1
    //   327: getstatic dEr.Zpi : LdEr;
    //   330: getstatic qlg.bzF : LAuk;
    //   333: invokespecial <init> : (ILjava/lang/String;IILdEr;LAuk;)V
    //   336: invokevirtual bzF : ()LAuk;
    //   339: putstatic qlg.kGO : LAuk;
    //   342: new Auk
    //   345: dup
    //   346: bipush #13
    //   348: ldc 'killEnemy'
    //   350: bipush #8
    //   352: iconst_m1
    //   353: getstatic dEr.tIz : LdEr;
    //   356: getstatic qlg.kGO : LAuk;
    //   359: invokespecial <init> : (ILjava/lang/String;IILdEr;LAuk;)V
    //   362: invokevirtual bzF : ()LAuk;
    //   365: putstatic qlg.udO : LAuk;
    //   368: new Auk
    //   371: dup
    //   372: bipush #14
    //   374: ldc 'killCow'
    //   376: bipush #7
    //   378: bipush #-3
    //   380: getstatic dEr.LoG : LdEr;
    //   383: getstatic qlg.kGO : LAuk;
    //   386: invokespecial <init> : (ILjava/lang/String;IILdEr;LAuk;)V
    //   389: invokevirtual bzF : ()LAuk;
    //   392: putstatic qlg.ooe : LAuk;
    //   395: new Auk
    //   398: dup
    //   399: bipush #15
    //   401: ldc 'flyPig'
    //   403: bipush #8
    //   405: bipush #-4
    //   407: getstatic dEr.YHU : LdEr;
    //   410: getstatic qlg.ooe : LAuk;
    //   413: invokespecial <init> : (ILjava/lang/String;IILdEr;LAuk;)V
    //   416: invokevirtual FWm : ()LAuk;
    //   419: invokevirtual bzF : ()LAuk;
    //   422: putstatic qlg.trS : LAuk;
    //   425: new Auk
    //   428: dup
    //   429: bipush #16
    //   431: ldc 'snipeSkeleton'
    //   433: bipush #7
    //   435: iconst_0
    //   436: getstatic dEr.Dne : LDsI;
    //   439: getstatic qlg.udO : LAuk;
    //   442: invokespecial <init> : (ILjava/lang/String;IILdEr;LAuk;)V
    //   445: invokevirtual FWm : ()LAuk;
    //   448: invokevirtual bzF : ()LAuk;
    //   451: putstatic qlg.qLR : LAuk;
    //   454: new Auk
    //   457: dup
    //   458: bipush #17
    //   460: ldc 'diamonds'
    //   462: iconst_m1
    //   463: iconst_5
    //   464: getstatic dEr.div : LdEr;
    //   467: getstatic qlg.zGp : LAuk;
    //   470: invokespecial <init> : (ILjava/lang/String;IILdEr;LAuk;)V
    //   473: invokevirtual bzF : ()LAuk;
    //   476: putstatic qlg.ATE : LAuk;
    //   479: new Auk
    //   482: dup
    //   483: bipush #18
    //   485: ldc 'portal'
    //   487: iconst_m1
    //   488: bipush #7
    //   490: getstatic zKP.cot : LzKP;
    //   493: getstatic qlg.ATE : LAuk;
    //   496: invokespecial <init> : (ILjava/lang/String;IILzKP;LAuk;)V
    //   499: invokevirtual bzF : ()LAuk;
    //   502: putstatic qlg.Vxn : LAuk;
    //   505: new Auk
    //   508: dup
    //   509: bipush #19
    //   511: ldc 'ghast'
    //   513: bipush #-4
    //   515: bipush #8
    //   517: getstatic dEr.ivB : LdEr;
    //   520: getstatic qlg.Vxn : LAuk;
    //   523: invokespecial <init> : (ILjava/lang/String;IILdEr;LAuk;)V
    //   526: invokevirtual FWm : ()LAuk;
    //   529: invokevirtual bzF : ()LAuk;
    //   532: putstatic qlg.ceE : LAuk;
    //   535: new Auk
    //   538: dup
    //   539: bipush #20
    //   541: ldc 'blazeRod'
    //   543: iconst_0
    //   544: bipush #9
    //   546: getstatic dEr.TpV : LdEr;
    //   549: getstatic qlg.Vxn : LAuk;
    //   552: invokespecial <init> : (ILjava/lang/String;IILdEr;LAuk;)V
    //   555: invokevirtual bzF : ()LAuk;
    //   558: putstatic qlg.EyB : LAuk;
    //   561: new Auk
    //   564: dup
    //   565: bipush #21
    //   567: ldc 'potion'
    //   569: iconst_2
    //   570: bipush #8
    //   572: getstatic dEr.Dne : LIJk;
    //   575: getstatic qlg.EyB : LAuk;
    //   578: invokespecial <init> : (ILjava/lang/String;IILdEr;LAuk;)V
    //   581: invokevirtual bzF : ()LAuk;
    //   584: putstatic qlg.FfS : LAuk;
    //   587: new Auk
    //   590: dup
    //   591: bipush #22
    //   593: ldc 'theEnd'
    //   595: iconst_3
    //   596: bipush #10
    //   598: getstatic dEr.Woy : LdEr;
    //   601: getstatic qlg.EyB : LAuk;
    //   604: invokespecial <init> : (ILjava/lang/String;IILdEr;LAuk;)V
    //   607: invokevirtual FWm : ()LAuk;
    //   610: invokevirtual bzF : ()LAuk;
    //   613: putstatic qlg.OdI : LAuk;
    //   616: new Auk
    //   619: dup
    //   620: bipush #23
    //   622: ldc 'theEnd2'
    //   624: iconst_4
    //   625: bipush #13
    //   627: getstatic zKP.sJS : LzKP;
    //   630: getstatic qlg.OdI : LAuk;
    //   633: invokespecial <init> : (ILjava/lang/String;IILzKP;LAuk;)V
    //   636: invokevirtual FWm : ()LAuk;
    //   639: invokevirtual bzF : ()LAuk;
    //   642: putstatic qlg.oIf : LAuk;
    //   645: new Auk
    //   648: dup
    //   649: bipush #24
    //   651: ldc 'enchantments'
    //   653: bipush #-4
    //   655: iconst_4
    //   656: getstatic zKP.KkE : LzKP;
    //   659: getstatic qlg.ATE : LAuk;
    //   662: invokespecial <init> : (ILjava/lang/String;IILzKP;LAuk;)V
    //   665: invokevirtual bzF : ()LAuk;
    //   668: putstatic qlg.vSL : LAuk;
    //   671: new Auk
    //   674: dup
    //   675: bipush #25
    //   677: ldc 'overkill'
    //   679: bipush #-4
    //   681: iconst_1
    //   682: getstatic dEr.ceE : LdEr;
    //   685: getstatic qlg.vSL : LAuk;
    //   688: invokespecial <init> : (ILjava/lang/String;IILdEr;LAuk;)V
    //   691: invokevirtual FWm : ()LAuk;
    //   694: invokevirtual bzF : ()LAuk;
    //   697: putstatic qlg.RPx : LAuk;
    //   700: new Auk
    //   703: dup
    //   704: bipush #26
    //   706: ldc 'bookcase'
    //   708: bipush #-3
    //   710: bipush #6
    //   712: getstatic zKP.AgF : LzKP;
    //   715: getstatic qlg.vSL : LAuk;
    //   718: invokespecial <init> : (ILjava/lang/String;IILzKP;LAuk;)V
    //   721: invokevirtual bzF : ()LAuk;
    //   724: putstatic qlg.Fnk : LAuk;
    //   727: getstatic java/lang/System.out : Ljava/io/PrintStream;
    //   730: new java/lang/StringBuilder
    //   733: dup
    //   734: invokespecial <init> : ()V
    //   737: getstatic qlg.Dne : Ljava/util/List;
    //   740: invokeinterface size : ()I
    //   745: invokevirtual append : (I)Ljava/lang/StringBuilder;
    //   748: ldc_w ' achievements'
    //   751: invokevirtual append : (Ljava/lang/String;)Ljava/lang/StringBuilder;
    //   754: invokevirtual toString : ()Ljava/lang/String;
    //   757: invokevirtual println : (Ljava/lang/String;)V
    //   760: return
  }
}


/* Location:              C:\Users\fract\Downloads\ERROR422.jar!\qlg.class
 * Java compiler version: 8 (52.0)
 * JD-Core Version:       1.1.3
 */