import java.util.ArrayList;
import java.util.Arrays;
import java.util.HashMap;
import java.util.List;
import java.util.Map;
import java.util.Random;

public class qMV {
  private int Qnq;
  
  public static boolean Dne;
  
  public int[] FWm;
  
  public boolean aFZ;
  
  public int[] Dne;
  
  public final int Dne;
  
  public final int FWm;
  
  public List[] Dne;
  
  public Qnq Dne;
  
  private byte[] Dne;
  
  private boolean div;
  
  public boolean[] Dne;
  
  public Map Dne;
  
  public boolean Qnq;
  
  public boolean zGp;
  
  public int bzF;
  
  public boolean FWm;
  
  private cHy[] Dne;
  
  boolean DyG;
  
  public boolean bzF;
  
  public long Dne = new cHy[16];
  
  public Random Dne(long paramLong) {
    // Byte code:
    //   0: new java/util/Random
    //   3: dup
    //   4: aload_0
    //   5: getfield Dne : LQnq;
    //   8: invokevirtual Dne : ()J
    //   11: aload_0
    //   12: getfield Dne : I
    //   15: aload_0
    //   16: getfield Dne : I
    //   19: imul
    //   20: ldc 4987142
    //   22: imul
    //   23: i2l
    //   24: ladd
    //   25: aload_0
    //   26: getfield Dne : I
    //   29: ldc 5947611
    //   31: imul
    //   32: i2l
    //   33: ladd
    //   34: aload_0
    //   35: getfield FWm : I
    //   38: aload_0
    //   39: getfield FWm : I
    //   42: imul
    //   43: i2l
    //   44: ldc2_w 4392871
    //   47: lmul
    //   48: ladd
    //   49: aload_0
    //   50: getfield FWm : I
    //   53: ldc 389711
    //   55: imul
    //   56: i2l
    //   57: ladd
    //   58: lload_1
    //   59: lxor
    //   60: invokespecial <init> : (J)V
    //   63: areturn
  }
  
  private void FWm(int paramInt1, int paramInt2, int paramInt3) {
    // Byte code:
    //   0: aload_0
    //   1: getfield Dne : LQnq;
    //   4: iload_1
    //   5: iload_2
    //   6: invokevirtual FWm : (II)I
    //   9: istore #4
    //   11: iload #4
    //   13: iload_3
    //   14: if_icmple -> 31
    //   17: aload_0
    //   18: iload_1
    //   19: iload_2
    //   20: iload_3
    //   21: iload #4
    //   23: iconst_1
    //   24: iadd
    //   25: invokespecial Dne : (IIII)V
    //   28: goto -> 48
    //   31: iload #4
    //   33: iload_3
    //   34: if_icmpge -> 48
    //   37: aload_0
    //   38: iload_1
    //   39: iload_2
    //   40: iload #4
    //   42: iload_3
    //   43: iconst_1
    //   44: iadd
    //   45: invokespecial Dne : (IIII)V
    //   48: return
  }
  
  public qMV(Qnq paramQnq, int paramInt1, int paramInt2) {
    this.Dne = new byte[256];
    this.Dne = new int[256];
    this.Dne = new boolean[256];
    this.div = false;
    this.Dne = new HashMap<>();
    this.bzF = false;
    this.Qnq = false;
    this.aFZ = false;
    this.Dne = 0L;
    this.zGp = false;
    this.bzF = false;
    this.Qnq = true;
    this.DyG = false;
    this.Dne = new List[16];
    this.Dne = paramQnq;
    this.Dne = paramInt1;
    this.FWm = paramInt2;
    this.FWm = new int[256];
    for (byte b = 0; b < this.Dne.length; b++)
      this.Dne[b] = new ArrayList(); 
    Arrays.fill(this.Dne, -999);
    Arrays.fill(this.Dne, (byte)-1);
  }
  
  public void Dne() {
    // Byte code:
    //   0: aload_0
    //   1: invokevirtual Dne : ()I
    //   4: istore_1
    //   5: iconst_0
    //   6: istore_2
    //   7: iload_2
    //   8: bipush #16
    //   10: if_icmpge -> 101
    //   13: iconst_0
    //   14: istore_3
    //   15: iload_3
    //   16: bipush #16
    //   18: if_icmpge -> 95
    //   21: aload_0
    //   22: getfield Dne : [I
    //   25: iload_2
    //   26: iload_3
    //   27: iconst_4
    //   28: ishl
    //   29: iadd
    //   30: sipush #-999
    //   33: iastore
    //   34: iload_1
    //   35: bipush #16
    //   37: iadd
    //   38: iconst_1
    //   39: isub
    //   40: istore #4
    //   42: iload #4
    //   44: ifle -> 86
    //   47: aload_0
    //   48: iload_2
    //   49: iload #4
    //   51: iconst_1
    //   52: isub
    //   53: iload_3
    //   54: invokevirtual Dne : (III)I
    //   57: istore #5
    //   59: getstatic zKP.FWm : [I
    //   62: iload #5
    //   64: iaload
    //   65: ifne -> 74
    //   68: iinc #4, -1
    //   71: goto -> 42
    //   74: aload_0
    //   75: getfield FWm : [I
    //   78: iload_3
    //   79: iconst_4
    //   80: ishl
    //   81: iload_2
    //   82: ior
    //   83: iload #4
    //   85: iastore
    //   86: iinc #3, 1
    //   89: goto -> 92
    //   92: goto -> 15
    //   95: iinc #2, 1
    //   98: goto -> 7
    //   101: aload_0
    //   102: iconst_1
    //   103: putfield Qnq : Z
    //   106: return
  }
  
  public void Dne(sMa paramsMa, bSp parambSp, List paramList, pUe parampUe) {
    // Byte code:
    //   0: aload_2
    //   1: getfield FWm : D
    //   4: ldc2_w 2.0
    //   7: dsub
    //   8: ldc2_w 16.0
    //   11: ddiv
    //   12: invokestatic FWm : (D)I
    //   15: istore #5
    //   17: aload_2
    //   18: getfield aFZ : D
    //   21: ldc2_w 2.0
    //   24: dadd
    //   25: ldc2_w 16.0
    //   28: ddiv
    //   29: invokestatic FWm : (D)I
    //   32: istore #6
    //   34: iload #5
    //   36: ifge -> 51
    //   39: iconst_0
    //   40: istore #5
    //   42: iload #5
    //   44: iload #6
    //   46: invokestatic max : (II)I
    //   49: istore #6
    //   51: iload #6
    //   53: aload_0
    //   54: getfield Dne : [Ljava/util/List;
    //   57: arraylength
    //   58: if_icmplt -> 79
    //   61: aload_0
    //   62: getfield Dne : [Ljava/util/List;
    //   65: arraylength
    //   66: iconst_1
    //   67: isub
    //   68: istore #6
    //   70: iload #5
    //   72: iload #6
    //   74: invokestatic min : (II)I
    //   77: istore #5
    //   79: iload #5
    //   81: istore #7
    //   83: iload #7
    //   85: iload #6
    //   87: if_icmpgt -> 264
    //   90: aload_0
    //   91: getfield Dne : [Ljava/util/List;
    //   94: iload #7
    //   96: aaload
    //   97: astore #8
    //   99: iconst_0
    //   100: istore #9
    //   102: iload #9
    //   104: aload #8
    //   106: invokeinterface size : ()I
    //   111: if_icmpge -> 258
    //   114: aload #8
    //   116: iload #9
    //   118: invokeinterface get : (I)Ljava/lang/Object;
    //   123: checkcast sMa
    //   126: astore #10
    //   128: aload #10
    //   130: aload_1
    //   131: if_acmpeq -> 252
    //   134: aload #10
    //   136: getfield Dne : LbSp;
    //   139: aload_2
    //   140: invokevirtual Dne : (LbSp;)Z
    //   143: ifeq -> 252
    //   146: aload #4
    //   148: ifnull -> 163
    //   151: aload #4
    //   153: aload #10
    //   155: invokeinterface Dne : (LsMa;)Z
    //   160: ifeq -> 252
    //   163: aload_3
    //   164: aload #10
    //   166: invokeinterface add : (Ljava/lang/Object;)Z
    //   171: pop
    //   172: aload #10
    //   174: invokevirtual Dne : ()[LsMa;
    //   177: astore #11
    //   179: aload #11
    //   181: ifnull -> 252
    //   184: iconst_0
    //   185: istore #12
    //   187: iload #12
    //   189: aload #11
    //   191: arraylength
    //   192: if_icmpge -> 252
    //   195: aload #11
    //   197: iload #12
    //   199: aaload
    //   200: astore #10
    //   202: aload #10
    //   204: aload_1
    //   205: if_acmpeq -> 246
    //   208: aload #10
    //   210: getfield Dne : LbSp;
    //   213: aload_2
    //   214: invokevirtual Dne : (LbSp;)Z
    //   217: ifeq -> 246
    //   220: aload #4
    //   222: ifnull -> 237
    //   225: aload #4
    //   227: aload #10
    //   229: invokeinterface Dne : (LsMa;)Z
    //   234: ifeq -> 246
    //   237: aload_3
    //   238: aload #10
    //   240: invokeinterface add : (Ljava/lang/Object;)Z
    //   245: pop
    //   246: iinc #12, 1
    //   249: goto -> 187
    //   252: iinc #9, 1
    //   255: goto -> 102
    //   258: iinc #7, 1
    //   261: goto -> 83
    //   264: return
  }
  
  public void Dne(sMa paramsMa, int paramInt) {
    // Byte code:
    //   0: iload_2
    //   1: ifge -> 6
    //   4: iconst_0
    //   5: istore_2
    //   6: iload_2
    //   7: aload_0
    //   8: getfield Dne : [Ljava/util/List;
    //   11: arraylength
    //   12: if_icmplt -> 23
    //   15: aload_0
    //   16: getfield Dne : [Ljava/util/List;
    //   19: arraylength
    //   20: iconst_1
    //   21: isub
    //   22: istore_2
    //   23: aload_0
    //   24: getfield Dne : [Ljava/util/List;
    //   27: iload_2
    //   28: aaload
    //   29: aload_1
    //   30: invokeinterface remove : (Ljava/lang/Object;)Z
    //   35: pop
    //   36: return
  }
  
  private void Dne(int paramInt1, int paramInt2) {
    this.Dne[paramInt1 + paramInt2 * 16] = 1L;
    this.div = true;
  }
  
  public boolean Dne(int paramInt1, int paramInt2, int paramInt3, int paramInt4, int paramInt5) {
    // Byte code:
    //   0: iload_3
    //   1: iconst_4
    //   2: ishl
    //   3: iload_1
    //   4: ior
    //   5: istore #6
    //   7: iload_2
    //   8: aload_0
    //   9: getfield Dne : [I
    //   12: iload #6
    //   14: iaload
    //   15: iconst_1
    //   16: isub
    //   17: if_icmplt -> 30
    //   20: aload_0
    //   21: getfield Dne : [I
    //   24: iload #6
    //   26: sipush #-999
    //   29: iastore
    //   30: aload_0
    //   31: getfield FWm : [I
    //   34: iload #6
    //   36: iaload
    //   37: istore #7
    //   39: aload_0
    //   40: iload_1
    //   41: iload_2
    //   42: iload_3
    //   43: invokevirtual Dne : (III)I
    //   46: istore #8
    //   48: aload_0
    //   49: iload_1
    //   50: iload_2
    //   51: iload_3
    //   52: invokevirtual bzF : (III)I
    //   55: istore #9
    //   57: iload #8
    //   59: iload #4
    //   61: if_icmpne -> 73
    //   64: iload #9
    //   66: iload #5
    //   68: if_icmpne -> 73
    //   71: iconst_0
    //   72: ireturn
    //   73: aload_0
    //   74: getfield Dne : [LcHy;
    //   77: iload_2
    //   78: iconst_4
    //   79: ishr
    //   80: aaload
    //   81: astore #10
    //   83: iconst_0
    //   84: istore #11
    //   86: aload #10
    //   88: ifnonnull -> 152
    //   91: iload #4
    //   93: ifne -> 98
    //   96: iconst_0
    //   97: ireturn
    //   98: aload_0
    //   99: getfield Dne : [LcHy;
    //   102: iload_2
    //   103: iconst_4
    //   104: ishr
    //   105: new cHy
    //   108: dup
    //   109: iload_2
    //   110: iconst_4
    //   111: ishr
    //   112: iconst_4
    //   113: ishl
    //   114: aload_0
    //   115: getfield Dne : LQnq;
    //   118: getfield Dne : LJik;
    //   121: getfield FWm : Z
    //   124: ifne -> 131
    //   127: iconst_1
    //   128: goto -> 132
    //   131: iconst_0
    //   132: invokespecial <init> : (IZ)V
    //   135: dup_x2
    //   136: aastore
    //   137: astore #10
    //   139: iload_2
    //   140: iload #7
    //   142: if_icmplt -> 149
    //   145: iconst_1
    //   146: goto -> 150
    //   149: iconst_0
    //   150: istore #11
    //   152: aload_0
    //   153: getfield Dne : I
    //   156: bipush #16
    //   158: imul
    //   159: iload_1
    //   160: iadd
    //   161: istore #12
    //   163: aload_0
    //   164: getfield FWm : I
    //   167: bipush #16
    //   169: imul
    //   170: iload_3
    //   171: iadd
    //   172: istore #13
    //   174: iload #8
    //   176: ifeq -> 209
    //   179: aload_0
    //   180: getfield Dne : LQnq;
    //   183: getfield aFZ : Z
    //   186: ifne -> 209
    //   189: getstatic zKP.Dne : [LzKP;
    //   192: iload #8
    //   194: aaload
    //   195: aload_0
    //   196: getfield Dne : LQnq;
    //   199: iload #12
    //   201: iload_2
    //   202: iload #13
    //   204: iload #9
    //   206: invokevirtual zGp : (LQnq;IIII)V
    //   209: aload #10
    //   211: iload_1
    //   212: iload_2
    //   213: bipush #15
    //   215: iand
    //   216: iload_3
    //   217: iload #4
    //   219: invokevirtual Dne : (IIII)V
    //   222: iload #8
    //   224: ifeq -> 293
    //   227: aload_0
    //   228: getfield Dne : LQnq;
    //   231: getfield aFZ : Z
    //   234: ifne -> 262
    //   237: getstatic zKP.Dne : [LzKP;
    //   240: iload #8
    //   242: aaload
    //   243: aload_0
    //   244: getfield Dne : LQnq;
    //   247: iload #12
    //   249: iload_2
    //   250: iload #13
    //   252: iload #8
    //   254: iload #9
    //   256: invokevirtual Dne : (LQnq;IIIII)V
    //   259: goto -> 293
    //   262: getstatic zKP.Dne : [LzKP;
    //   265: iload #8
    //   267: aaload
    //   268: instanceof sCQ
    //   271: ifeq -> 293
    //   274: iload #8
    //   276: iload #4
    //   278: if_icmpeq -> 293
    //   281: aload_0
    //   282: getfield Dne : LQnq;
    //   285: iload #12
    //   287: iload_2
    //   288: iload #13
    //   290: invokevirtual bzF : (III)V
    //   293: aload #10
    //   295: iload_1
    //   296: iload_2
    //   297: bipush #15
    //   299: iand
    //   300: iload_3
    //   301: invokevirtual Dne : (III)I
    //   304: iload #4
    //   306: if_icmpeq -> 311
    //   309: iconst_0
    //   310: ireturn
    //   311: aload #10
    //   313: iload_1
    //   314: iload_2
    //   315: bipush #15
    //   317: iand
    //   318: iload_3
    //   319: iload #5
    //   321: invokevirtual FWm : (IIII)V
    //   324: iload #11
    //   326: ifeq -> 336
    //   329: aload_0
    //   330: invokevirtual FWm : ()V
    //   333: goto -> 388
    //   336: getstatic zKP.FWm : [I
    //   339: iload #4
    //   341: sipush #4095
    //   344: iand
    //   345: iaload
    //   346: ifle -> 367
    //   349: iload_2
    //   350: iload #7
    //   352: if_icmplt -> 382
    //   355: aload_0
    //   356: iload_1
    //   357: iload_2
    //   358: iconst_1
    //   359: iadd
    //   360: iload_3
    //   361: invokespecial bzF : (III)V
    //   364: goto -> 382
    //   367: iload_2
    //   368: iload #7
    //   370: iconst_1
    //   371: isub
    //   372: if_icmpne -> 382
    //   375: aload_0
    //   376: iload_1
    //   377: iload_2
    //   378: iload_3
    //   379: invokespecial bzF : (III)V
    //   382: aload_0
    //   383: iload_1
    //   384: iload_3
    //   385: invokespecial Dne : (II)V
    //   388: iload #4
    //   390: ifeq -> 494
    //   393: aload_0
    //   394: getfield Dne : LQnq;
    //   397: getfield aFZ : Z
    //   400: ifne -> 421
    //   403: getstatic zKP.Dne : [LzKP;
    //   406: iload #4
    //   408: aaload
    //   409: aload_0
    //   410: getfield Dne : LQnq;
    //   413: iload #12
    //   415: iload_2
    //   416: iload #13
    //   418: invokevirtual Dne : (LQnq;III)V
    //   421: getstatic zKP.Dne : [LzKP;
    //   424: iload #4
    //   426: aaload
    //   427: instanceof sCQ
    //   430: ifeq -> 530
    //   433: aload_0
    //   434: iload_1
    //   435: iload_2
    //   436: iload_3
    //   437: invokevirtual Dne : (III)LipD;
    //   440: astore #14
    //   442: aload #14
    //   444: ifnonnull -> 481
    //   447: getstatic zKP.Dne : [LzKP;
    //   450: iload #4
    //   452: aaload
    //   453: checkcast sCQ
    //   456: aload_0
    //   457: getfield Dne : LQnq;
    //   460: invokeinterface Dne : (LQnq;)LipD;
    //   465: astore #14
    //   467: aload_0
    //   468: getfield Dne : LQnq;
    //   471: iload #12
    //   473: iload_2
    //   474: iload #13
    //   476: aload #14
    //   478: invokevirtual Dne : (IIILipD;)V
    //   481: aload #14
    //   483: ifnull -> 530
    //   486: aload #14
    //   488: invokevirtual Qnq : ()V
    //   491: goto -> 530
    //   494: iload #8
    //   496: ifle -> 530
    //   499: getstatic zKP.Dne : [LzKP;
    //   502: iload #8
    //   504: aaload
    //   505: instanceof sCQ
    //   508: ifeq -> 530
    //   511: aload_0
    //   512: iload_1
    //   513: iload_2
    //   514: iload_3
    //   515: invokevirtual Dne : (III)LipD;
    //   518: astore #14
    //   520: aload #14
    //   522: ifnull -> 530
    //   525: aload #14
    //   527: invokevirtual Qnq : ()V
    //   530: aload_0
    //   531: iconst_1
    //   532: putfield Qnq : Z
    //   535: iconst_1
    //   536: ireturn
  }
  
  public void bzF() {
    // Byte code:
    //   0: aload_0
    //   1: iconst_1
    //   2: putfield FWm : Z
    //   5: aload_0
    //   6: getfield Dne : LQnq;
    //   9: aload_0
    //   10: getfield Dne : Ljava/util/Map;
    //   13: invokeinterface values : ()Ljava/util/Collection;
    //   18: invokevirtual Dne : (Ljava/util/Collection;)V
    //   21: iconst_0
    //   22: istore_1
    //   23: iload_1
    //   24: aload_0
    //   25: getfield Dne : [Ljava/util/List;
    //   28: arraylength
    //   29: if_icmpge -> 51
    //   32: aload_0
    //   33: getfield Dne : LQnq;
    //   36: aload_0
    //   37: getfield Dne : [Ljava/util/List;
    //   40: iload_1
    //   41: aaload
    //   42: invokevirtual Dne : (Ljava/util/List;)V
    //   45: iinc #1, 1
    //   48: goto -> 23
    //   51: return
  }
  
  public OdI Dne(int paramInt1, int paramInt2, tgc paramtgc) {
    // Byte code:
    //   0: aload_0
    //   1: getfield Dne : [B
    //   4: iload_2
    //   5: iconst_4
    //   6: ishl
    //   7: iload_1
    //   8: ior
    //   9: baload
    //   10: sipush #255
    //   13: iand
    //   14: istore #4
    //   16: iload #4
    //   18: sipush #255
    //   21: if_icmpne -> 70
    //   24: aload_3
    //   25: aload_0
    //   26: getfield Dne : I
    //   29: iconst_4
    //   30: ishl
    //   31: iload_1
    //   32: iadd
    //   33: aload_0
    //   34: getfield FWm : I
    //   37: iconst_4
    //   38: ishl
    //   39: iload_2
    //   40: iadd
    //   41: invokevirtual Dne : (II)LOdI;
    //   44: astore #5
    //   46: aload #5
    //   48: getfield Qnq : I
    //   51: istore #4
    //   53: aload_0
    //   54: getfield Dne : [B
    //   57: iload_2
    //   58: iconst_4
    //   59: ishl
    //   60: iload_1
    //   61: ior
    //   62: iload #4
    //   64: sipush #255
    //   67: iand
    //   68: i2b
    //   69: bastore
    //   70: getstatic OdI.Dne : [LOdI;
    //   73: iload #4
    //   75: aaload
    //   76: ifnonnull -> 85
    //   79: getstatic OdI.FWm : LOdI;
    //   82: goto -> 91
    //   85: getstatic OdI.Dne : [LOdI;
    //   88: iload #4
    //   90: aaload
    //   91: areturn
  }
  
  public int Dne(udO paramudO, int paramInt1, int paramInt2, int paramInt3) {
    // Byte code:
    //   0: aload_0
    //   1: getfield Dne : [LcHy;
    //   4: iload_3
    //   5: iconst_4
    //   6: ishr
    //   7: aaload
    //   8: astore #5
    //   10: aload #5
    //   12: ifnonnull -> 37
    //   15: aload_0
    //   16: iload_2
    //   17: iload_3
    //   18: iload #4
    //   20: invokevirtual Dne : (III)Z
    //   23: ifeq -> 33
    //   26: aload_1
    //   27: getfield Dne : I
    //   30: goto -> 102
    //   33: iconst_0
    //   34: goto -> 102
    //   37: aload_1
    //   38: getstatic udO.Dne : LudO;
    //   41: if_acmpne -> 76
    //   44: aload_0
    //   45: getfield Dne : LQnq;
    //   48: getfield Dne : LJik;
    //   51: getfield FWm : Z
    //   54: ifeq -> 61
    //   57: iconst_0
    //   58: goto -> 102
    //   61: aload #5
    //   63: iload_2
    //   64: iload_3
    //   65: bipush #15
    //   67: iand
    //   68: iload #4
    //   70: invokevirtual bzF : (III)I
    //   73: goto -> 102
    //   76: aload_1
    //   77: getstatic udO.FWm : LudO;
    //   80: if_acmpne -> 98
    //   83: aload #5
    //   85: iload_2
    //   86: iload_3
    //   87: bipush #15
    //   89: iand
    //   90: iload #4
    //   92: invokevirtual Qnq : (III)I
    //   95: goto -> 102
    //   98: aload_1
    //   99: getfield Dne : I
    //   102: ireturn
  }
  
  public void Dne(int paramInt1, int paramInt2, int paramInt3) {
    // Byte code:
    //   0: new EyB
    //   3: dup
    //   4: iload_1
    //   5: iload_2
    //   6: iload_3
    //   7: invokespecial <init> : (III)V
    //   10: astore #4
    //   12: aload_0
    //   13: getfield FWm : Z
    //   16: ifeq -> 45
    //   19: aload_0
    //   20: getfield Dne : Ljava/util/Map;
    //   23: aload #4
    //   25: invokeinterface remove : (Ljava/lang/Object;)Ljava/lang/Object;
    //   30: checkcast ipD
    //   33: astore #5
    //   35: aload #5
    //   37: ifnull -> 45
    //   40: aload #5
    //   42: invokevirtual zGp : ()V
    //   45: return
  }
  
  public void Dne(byte[] paramArrayOfbyte) {
    this.Dne = paramArrayOfbyte;
  }
  
  public cHy[] Dne() {
    return this.Dne;
  }
  
  public qMV(Qnq paramQnq, byte[] paramArrayOfbyte, int paramInt1, int paramInt2) {
    // Byte code:
    //   0: aload_0
    //   1: aload_1
    //   2: iload_3
    //   3: iload #4
    //   5: invokespecial <init> : (LQnq;II)V
    //   8: aload_2
    //   9: arraylength
    //   10: sipush #256
    //   13: idiv
    //   14: istore #5
    //   16: iconst_0
    //   17: istore #6
    //   19: iload #6
    //   21: bipush #16
    //   23: if_icmpge -> 157
    //   26: iconst_0
    //   27: istore #7
    //   29: iload #7
    //   31: bipush #16
    //   33: if_icmpge -> 151
    //   36: iconst_0
    //   37: istore #8
    //   39: iload #8
    //   41: iload #5
    //   43: if_icmpge -> 145
    //   46: aload_2
    //   47: iload #6
    //   49: bipush #11
    //   51: ishl
    //   52: iload #7
    //   54: bipush #7
    //   56: ishl
    //   57: ior
    //   58: iload #8
    //   60: ior
    //   61: baload
    //   62: istore #9
    //   64: iload #9
    //   66: ifeq -> 139
    //   69: iload #8
    //   71: iconst_4
    //   72: ishr
    //   73: istore #10
    //   75: aload_0
    //   76: getfield Dne : [LcHy;
    //   79: iload #10
    //   81: aaload
    //   82: ifnonnull -> 118
    //   85: aload_0
    //   86: getfield Dne : [LcHy;
    //   89: iload #10
    //   91: new cHy
    //   94: dup
    //   95: iload #10
    //   97: iconst_4
    //   98: ishl
    //   99: aload_1
    //   100: getfield Dne : LJik;
    //   103: getfield FWm : Z
    //   106: ifne -> 113
    //   109: iconst_1
    //   110: goto -> 114
    //   113: iconst_0
    //   114: invokespecial <init> : (IZ)V
    //   117: aastore
    //   118: aload_0
    //   119: getfield Dne : [LcHy;
    //   122: iload #10
    //   124: aaload
    //   125: iload #6
    //   127: iload #8
    //   129: bipush #15
    //   131: iand
    //   132: iload #7
    //   134: iload #9
    //   136: invokevirtual Dne : (IIII)V
    //   139: iinc #8, 1
    //   142: goto -> 39
    //   145: iinc #7, 1
    //   148: goto -> 29
    //   151: iinc #6, 1
    //   154: goto -> 19
    //   157: return
  }
  
  public void FWm(sMa paramsMa) {
    Dne(paramsMa, paramsMa.mrb);
  }
  
  public int FWm(int paramInt1, int paramInt2, int paramInt3) {
    return zKP.FWm[Dne(paramInt1, paramInt2, paramInt3)];
  }
  
  public int FWm(int paramInt1, int paramInt2) {
    // Byte code:
    //   0: iload_1
    //   1: iload_2
    //   2: iconst_4
    //   3: ishl
    //   4: ior
    //   5: istore_3
    //   6: aload_0
    //   7: getfield Dne : [I
    //   10: iload_3
    //   11: iaload
    //   12: istore #4
    //   14: iload #4
    //   16: sipush #-999
    //   19: if_icmpne -> 116
    //   22: aload_0
    //   23: invokevirtual Dne : ()I
    //   26: bipush #15
    //   28: iadd
    //   29: istore #5
    //   31: iconst_m1
    //   32: istore #4
    //   34: iload #5
    //   36: ifle -> 108
    //   39: iload #4
    //   41: iconst_m1
    //   42: if_icmpne -> 108
    //   45: aload_0
    //   46: iload_1
    //   47: iload #5
    //   49: iload_2
    //   50: invokevirtual Dne : (III)I
    //   53: istore #6
    //   55: iload #6
    //   57: ifne -> 66
    //   60: getstatic KFd.Dne : LKFd;
    //   63: goto -> 75
    //   66: getstatic zKP.Dne : [LzKP;
    //   69: iload #6
    //   71: aaload
    //   72: getfield Dne : LKFd;
    //   75: astore #7
    //   77: aload #7
    //   79: invokevirtual bzF : ()Z
    //   82: ifne -> 99
    //   85: aload #7
    //   87: invokevirtual Qnq : ()Z
    //   90: ifne -> 99
    //   93: iinc #5, -1
    //   96: goto -> 105
    //   99: iload #5
    //   101: iconst_1
    //   102: iadd
    //   103: istore #4
    //   105: goto -> 34
    //   108: aload_0
    //   109: getfield Dne : [I
    //   112: iload_3
    //   113: iload #4
    //   115: iastore
    //   116: iload #4
    //   118: ireturn
  }
  
  public void Dne(int paramInt1, int paramInt2, int paramInt3, ipD paramipD) {
    // Byte code:
    //   0: new EyB
    //   3: dup
    //   4: iload_1
    //   5: iload_2
    //   6: iload_3
    //   7: invokespecial <init> : (III)V
    //   10: astore #5
    //   12: aload #4
    //   14: aload_0
    //   15: getfield Dne : LQnq;
    //   18: invokevirtual Dne : (LQnq;)V
    //   21: aload #4
    //   23: aload_0
    //   24: getfield Dne : I
    //   27: bipush #16
    //   29: imul
    //   30: iload_1
    //   31: iadd
    //   32: putfield Qnq : I
    //   35: aload #4
    //   37: iload_2
    //   38: putfield aFZ : I
    //   41: aload #4
    //   43: aload_0
    //   44: getfield FWm : I
    //   47: bipush #16
    //   49: imul
    //   50: iload_3
    //   51: iadd
    //   52: putfield zGp : I
    //   55: aload_0
    //   56: iload_1
    //   57: iload_2
    //   58: iload_3
    //   59: invokevirtual Dne : (III)I
    //   62: ifeq -> 132
    //   65: getstatic zKP.Dne : [LzKP;
    //   68: aload_0
    //   69: iload_1
    //   70: iload_2
    //   71: iload_3
    //   72: invokevirtual Dne : (III)I
    //   75: aaload
    //   76: instanceof sCQ
    //   79: ifeq -> 132
    //   82: aload_0
    //   83: getfield Dne : Ljava/util/Map;
    //   86: aload #5
    //   88: invokeinterface containsKey : (Ljava/lang/Object;)Z
    //   93: ifeq -> 113
    //   96: aload_0
    //   97: getfield Dne : Ljava/util/Map;
    //   100: aload #5
    //   102: invokeinterface get : (Ljava/lang/Object;)Ljava/lang/Object;
    //   107: checkcast ipD
    //   110: invokevirtual zGp : ()V
    //   113: aload #4
    //   115: invokevirtual DyG : ()V
    //   118: aload_0
    //   119: getfield Dne : Ljava/util/Map;
    //   122: aload #5
    //   124: aload #4
    //   126: invokeinterface put : (Ljava/lang/Object;Ljava/lang/Object;)Ljava/lang/Object;
    //   131: pop
    //   132: return
  }
  
  public boolean Dne(int paramInt1, int paramInt2, int paramInt3) {
    return (paramInt2 >= this.FWm[paramInt3 << 4 | paramInt1]);
  }
  
  public byte[] Dne() {
    return this.Dne;
  }
  
  public int Dne() {
    // Byte code:
    //   0: aload_0
    //   1: getfield Dne : [LcHy;
    //   4: arraylength
    //   5: iconst_1
    //   6: isub
    //   7: istore_1
    //   8: iload_1
    //   9: iflt -> 37
    //   12: aload_0
    //   13: getfield Dne : [LcHy;
    //   16: iload_1
    //   17: aaload
    //   18: ifnull -> 31
    //   21: aload_0
    //   22: getfield Dne : [LcHy;
    //   25: iload_1
    //   26: aaload
    //   27: invokevirtual Dne : ()I
    //   30: ireturn
    //   31: iinc #1, -1
    //   34: goto -> 8
    //   37: iconst_0
    //   38: ireturn
  }
  
  public int bzF(int paramInt1, int paramInt2, int paramInt3) {
    // Byte code:
    //   0: iload_2
    //   1: iconst_4
    //   2: ishr
    //   3: aload_0
    //   4: getfield Dne : [LcHy;
    //   7: arraylength
    //   8: if_icmplt -> 13
    //   11: iconst_0
    //   12: ireturn
    //   13: aload_0
    //   14: getfield Dne : [LcHy;
    //   17: iload_2
    //   18: iconst_4
    //   19: ishr
    //   20: aaload
    //   21: astore #4
    //   23: aload #4
    //   25: ifnull -> 42
    //   28: aload #4
    //   30: iload_1
    //   31: iload_2
    //   32: bipush #15
    //   34: iand
    //   35: iload_3
    //   36: invokevirtual FWm : (III)I
    //   39: goto -> 43
    //   42: iconst_0
    //   43: ireturn
  }
  
  public Sxs Dne() {
    return new Sxs(this.Dne, this.FWm);
  }
  
  public boolean Dne(int paramInt1, int paramInt2) {
    return (paramInt1 == this.Dne && paramInt2 == this.FWm);
  }
  
  public int Dne(int paramInt1, int paramInt2, int paramInt3) {
    // Byte code:
    //   0: iload_2
    //   1: iconst_4
    //   2: ishr
    //   3: aload_0
    //   4: getfield Dne : [LcHy;
    //   7: arraylength
    //   8: if_icmplt -> 13
    //   11: iconst_0
    //   12: ireturn
    //   13: aload_0
    //   14: getfield Dne : [LcHy;
    //   17: iload_2
    //   18: iconst_4
    //   19: ishr
    //   20: aaload
    //   21: astore #4
    //   23: aload #4
    //   25: ifnull -> 42
    //   28: aload #4
    //   30: iload_1
    //   31: iload_2
    //   32: bipush #15
    //   34: iand
    //   35: iload_3
    //   36: invokevirtual Dne : (III)I
    //   39: goto -> 43
    //   42: iconst_0
    //   43: ireturn
  }
  
  public boolean Dne(int paramInt1, int paramInt2, int paramInt3, int paramInt4) {
    // Byte code:
    //   0: aload_0
    //   1: getfield Dne : [LcHy;
    //   4: iload_2
    //   5: iconst_4
    //   6: ishr
    //   7: aaload
    //   8: astore #5
    //   10: aload #5
    //   12: ifnonnull -> 17
    //   15: iconst_0
    //   16: ireturn
    //   17: aload #5
    //   19: iload_1
    //   20: iload_2
    //   21: bipush #15
    //   23: iand
    //   24: iload_3
    //   25: invokevirtual FWm : (III)I
    //   28: istore #6
    //   30: iload #6
    //   32: iload #4
    //   34: if_icmpne -> 39
    //   37: iconst_0
    //   38: ireturn
    //   39: aload_0
    //   40: iconst_1
    //   41: putfield Qnq : Z
    //   44: aload #5
    //   46: iload_1
    //   47: iload_2
    //   48: bipush #15
    //   50: iand
    //   51: iload_3
    //   52: iload #4
    //   54: invokevirtual FWm : (IIII)V
    //   57: aload #5
    //   59: iload_1
    //   60: iload_2
    //   61: bipush #15
    //   63: iand
    //   64: iload_3
    //   65: invokevirtual Dne : (III)I
    //   68: istore #7
    //   70: iload #7
    //   72: ifle -> 113
    //   75: getstatic zKP.Dne : [LzKP;
    //   78: iload #7
    //   80: aaload
    //   81: instanceof sCQ
    //   84: ifeq -> 113
    //   87: aload_0
    //   88: iload_1
    //   89: iload_2
    //   90: iload_3
    //   91: invokevirtual Dne : (III)LipD;
    //   94: astore #8
    //   96: aload #8
    //   98: ifnull -> 113
    //   101: aload #8
    //   103: invokevirtual Qnq : ()V
    //   106: aload #8
    //   108: iload #4
    //   110: putfield DyG : I
    //   113: iconst_1
    //   114: ireturn
  }
  
  public ipD Dne(int paramInt1, int paramInt2, int paramInt3) {
    // Byte code:
    //   0: new EyB
    //   3: dup
    //   4: iload_1
    //   5: iload_2
    //   6: iload_3
    //   7: invokespecial <init> : (III)V
    //   10: astore #4
    //   12: aload_0
    //   13: getfield Dne : Ljava/util/Map;
    //   16: aload #4
    //   18: invokeinterface get : (Ljava/lang/Object;)Ljava/lang/Object;
    //   23: checkcast ipD
    //   26: astore #5
    //   28: aload #5
    //   30: ifnonnull -> 130
    //   33: aload_0
    //   34: iload_1
    //   35: iload_2
    //   36: iload_3
    //   37: invokevirtual Dne : (III)I
    //   40: istore #6
    //   42: iload #6
    //   44: ifle -> 59
    //   47: getstatic zKP.Dne : [LzKP;
    //   50: iload #6
    //   52: aaload
    //   53: invokevirtual mrb : ()Z
    //   56: ifne -> 61
    //   59: aconst_null
    //   60: areturn
    //   61: aload #5
    //   63: ifnonnull -> 114
    //   66: getstatic zKP.Dne : [LzKP;
    //   69: iload #6
    //   71: aaload
    //   72: checkcast sCQ
    //   75: aload_0
    //   76: getfield Dne : LQnq;
    //   79: invokeinterface Dne : (LQnq;)LipD;
    //   84: astore #5
    //   86: aload_0
    //   87: getfield Dne : LQnq;
    //   90: aload_0
    //   91: getfield Dne : I
    //   94: bipush #16
    //   96: imul
    //   97: iload_1
    //   98: iadd
    //   99: iload_2
    //   100: aload_0
    //   101: getfield FWm : I
    //   104: bipush #16
    //   106: imul
    //   107: iload_3
    //   108: iadd
    //   109: aload #5
    //   111: invokevirtual Dne : (IIILipD;)V
    //   114: aload_0
    //   115: getfield Dne : Ljava/util/Map;
    //   118: aload #4
    //   120: invokeinterface get : (Ljava/lang/Object;)Ljava/lang/Object;
    //   125: checkcast ipD
    //   128: astore #5
    //   130: aload #5
    //   132: ifnull -> 157
    //   135: aload #5
    //   137: invokevirtual aFZ : ()Z
    //   140: ifeq -> 157
    //   143: aload_0
    //   144: getfield Dne : Ljava/util/Map;
    //   147: aload #4
    //   149: invokeinterface remove : (Ljava/lang/Object;)Ljava/lang/Object;
    //   154: pop
    //   155: aconst_null
    //   156: areturn
    //   157: aload #5
    //   159: areturn
  }
  
  private void bzF(int paramInt1, int paramInt2, int paramInt3) {
    // Byte code:
    //   0: aload_0
    //   1: getfield FWm : [I
    //   4: iload_3
    //   5: iconst_4
    //   6: ishl
    //   7: iload_1
    //   8: ior
    //   9: iaload
    //   10: sipush #255
    //   13: iand
    //   14: istore #4
    //   16: iload #4
    //   18: istore #5
    //   20: iload_2
    //   21: iload #4
    //   23: if_icmple -> 29
    //   26: iload_2
    //   27: istore #5
    //   29: iload #5
    //   31: ifle -> 53
    //   34: aload_0
    //   35: iload_1
    //   36: iload #5
    //   38: iconst_1
    //   39: isub
    //   40: iload_3
    //   41: invokevirtual FWm : (III)I
    //   44: ifne -> 53
    //   47: iinc #5, -1
    //   50: goto -> 29
    //   53: iload #5
    //   55: iload #4
    //   57: if_icmpeq -> 505
    //   60: aload_0
    //   61: getfield Dne : LQnq;
    //   64: iload_1
    //   65: aload_0
    //   66: getfield Dne : I
    //   69: bipush #16
    //   71: imul
    //   72: iadd
    //   73: iload_3
    //   74: aload_0
    //   75: getfield FWm : I
    //   78: bipush #16
    //   80: imul
    //   81: iadd
    //   82: iload #5
    //   84: iload #4
    //   86: invokevirtual FWm : (IIII)V
    //   89: aload_0
    //   90: getfield FWm : [I
    //   93: iload_3
    //   94: iconst_4
    //   95: ishl
    //   96: iload_1
    //   97: ior
    //   98: iload #5
    //   100: iastore
    //   101: aload_0
    //   102: getfield Dne : I
    //   105: bipush #16
    //   107: imul
    //   108: iload_1
    //   109: iadd
    //   110: istore #6
    //   112: aload_0
    //   113: getfield FWm : I
    //   116: bipush #16
    //   118: imul
    //   119: iload_3
    //   120: iadd
    //   121: istore #7
    //   123: aload_0
    //   124: getfield Dne : LQnq;
    //   127: getfield Dne : LJik;
    //   130: getfield FWm : Z
    //   133: ifne -> 369
    //   136: iload #5
    //   138: iload #4
    //   140: if_icmpge -> 215
    //   143: iload #5
    //   145: istore #8
    //   147: iload #8
    //   149: iload #4
    //   151: if_icmpge -> 286
    //   154: aload_0
    //   155: getfield Dne : [LcHy;
    //   158: iload #8
    //   160: iconst_4
    //   161: ishr
    //   162: aaload
    //   163: astore #10
    //   165: aload #10
    //   167: ifnull -> 209
    //   170: aload #10
    //   172: iload_1
    //   173: iload #8
    //   175: bipush #15
    //   177: iand
    //   178: iload_3
    //   179: bipush #15
    //   181: invokevirtual bzF : (IIII)V
    //   184: aload_0
    //   185: getfield Dne : LQnq;
    //   188: aload_0
    //   189: getfield Dne : I
    //   192: iconst_4
    //   193: ishl
    //   194: iload_1
    //   195: iadd
    //   196: iload #8
    //   198: aload_0
    //   199: getfield FWm : I
    //   202: iconst_4
    //   203: ishl
    //   204: iload_3
    //   205: iadd
    //   206: invokevirtual FWm : (III)V
    //   209: iinc #8, 1
    //   212: goto -> 147
    //   215: iload #4
    //   217: istore #8
    //   219: iload #8
    //   221: iload #5
    //   223: if_icmpge -> 286
    //   226: aload_0
    //   227: getfield Dne : [LcHy;
    //   230: iload #8
    //   232: iconst_4
    //   233: ishr
    //   234: aaload
    //   235: astore #10
    //   237: aload #10
    //   239: ifnull -> 280
    //   242: aload #10
    //   244: iload_1
    //   245: iload #8
    //   247: bipush #15
    //   249: iand
    //   250: iload_3
    //   251: iconst_0
    //   252: invokevirtual bzF : (IIII)V
    //   255: aload_0
    //   256: getfield Dne : LQnq;
    //   259: aload_0
    //   260: getfield Dne : I
    //   263: iconst_4
    //   264: ishl
    //   265: iload_1
    //   266: iadd
    //   267: iload #8
    //   269: aload_0
    //   270: getfield FWm : I
    //   273: iconst_4
    //   274: ishl
    //   275: iload_3
    //   276: iadd
    //   277: invokevirtual FWm : (III)V
    //   280: iinc #8, 1
    //   283: goto -> 219
    //   286: bipush #15
    //   288: istore #8
    //   290: iload #5
    //   292: ifle -> 369
    //   295: iload #8
    //   297: ifle -> 369
    //   300: iinc #5, -1
    //   303: aload_0
    //   304: iload_1
    //   305: iload #5
    //   307: iload_3
    //   308: invokevirtual FWm : (III)I
    //   311: istore #9
    //   313: iload #9
    //   315: ifne -> 321
    //   318: iconst_1
    //   319: istore #9
    //   321: iload #8
    //   323: iload #9
    //   325: isub
    //   326: istore #8
    //   328: iload #8
    //   330: ifge -> 336
    //   333: iconst_0
    //   334: istore #8
    //   336: aload_0
    //   337: getfield Dne : [LcHy;
    //   340: iload #5
    //   342: iconst_4
    //   343: ishr
    //   344: aaload
    //   345: astore #11
    //   347: aload #11
    //   349: ifnull -> 366
    //   352: aload #11
    //   354: iload_1
    //   355: iload #5
    //   357: bipush #15
    //   359: iand
    //   360: iload_3
    //   361: iload #8
    //   363: invokevirtual bzF : (IIII)V
    //   366: goto -> 290
    //   369: aload_0
    //   370: getfield FWm : [I
    //   373: iload_3
    //   374: iconst_4
    //   375: ishl
    //   376: iload_1
    //   377: ior
    //   378: iaload
    //   379: istore #8
    //   381: iload #4
    //   383: istore #9
    //   385: iload #8
    //   387: istore #10
    //   389: iload #8
    //   391: iload #4
    //   393: if_icmpge -> 404
    //   396: iload #8
    //   398: istore #9
    //   400: iload #4
    //   402: istore #10
    //   404: iload #8
    //   406: aload_0
    //   407: getfield bzF : I
    //   410: if_icmpge -> 419
    //   413: aload_0
    //   414: iload #8
    //   416: putfield bzF : I
    //   419: aload_0
    //   420: getfield Dne : LQnq;
    //   423: getfield Dne : LJik;
    //   426: getfield FWm : Z
    //   429: ifne -> 500
    //   432: aload_0
    //   433: iload #6
    //   435: iconst_1
    //   436: isub
    //   437: iload #7
    //   439: iload #9
    //   441: iload #10
    //   443: invokespecial Dne : (IIII)V
    //   446: aload_0
    //   447: iload #6
    //   449: iconst_1
    //   450: iadd
    //   451: iload #7
    //   453: iload #9
    //   455: iload #10
    //   457: invokespecial Dne : (IIII)V
    //   460: aload_0
    //   461: iload #6
    //   463: iload #7
    //   465: iconst_1
    //   466: isub
    //   467: iload #9
    //   469: iload #10
    //   471: invokespecial Dne : (IIII)V
    //   474: aload_0
    //   475: iload #6
    //   477: iload #7
    //   479: iconst_1
    //   480: iadd
    //   481: iload #9
    //   483: iload #10
    //   485: invokespecial Dne : (IIII)V
    //   488: aload_0
    //   489: iload #6
    //   491: iload #7
    //   493: iload #9
    //   495: iload #10
    //   497: invokespecial Dne : (IIII)V
    //   500: aload_0
    //   501: iconst_1
    //   502: putfield Qnq : Z
    //   505: return
  }
  
  public void DyG() {
    this.Qnq = false;
  }
  
  public int Dne(int paramInt1, int paramInt2) {
    return this.FWm[paramInt2 << 4 | paramInt1];
  }
  
  public int Dne(int paramInt1, int paramInt2, int paramInt3, int paramInt4) {
    // Byte code:
    //   0: aload_0
    //   1: getfield Dne : [LcHy;
    //   4: iload_2
    //   5: iconst_4
    //   6: ishr
    //   7: aaload
    //   8: astore #5
    //   10: aload #5
    //   12: ifnonnull -> 53
    //   15: aload_0
    //   16: getfield Dne : LQnq;
    //   19: getfield Dne : LJik;
    //   22: getfield FWm : Z
    //   25: ifne -> 51
    //   28: iload #4
    //   30: getstatic udO.Dne : LudO;
    //   33: getfield Dne : I
    //   36: if_icmpge -> 51
    //   39: getstatic udO.Dne : LudO;
    //   42: getfield Dne : I
    //   45: iload #4
    //   47: isub
    //   48: goto -> 52
    //   51: iconst_0
    //   52: ireturn
    //   53: aload_0
    //   54: getfield Dne : LQnq;
    //   57: getfield Dne : LJik;
    //   60: getfield FWm : Z
    //   63: ifeq -> 70
    //   66: iconst_0
    //   67: goto -> 81
    //   70: aload #5
    //   72: iload_1
    //   73: iload_2
    //   74: bipush #15
    //   76: iand
    //   77: iload_3
    //   78: invokevirtual bzF : (III)I
    //   81: istore #6
    //   83: iload #6
    //   85: ifle -> 92
    //   88: iconst_1
    //   89: putstatic qMV.Dne : Z
    //   92: iload #6
    //   94: iload #4
    //   96: isub
    //   97: istore #6
    //   99: aload #5
    //   101: iload_1
    //   102: iload_2
    //   103: bipush #15
    //   105: iand
    //   106: iload_3
    //   107: invokevirtual Qnq : (III)I
    //   110: istore #7
    //   112: iload #7
    //   114: iload #6
    //   116: if_icmple -> 123
    //   119: iload #7
    //   121: istore #6
    //   123: iload #6
    //   125: ireturn
  }
  
  public void FWm() {
    // Byte code:
    //   0: aload_0
    //   1: invokevirtual Dne : ()I
    //   4: istore_1
    //   5: aload_0
    //   6: ldc_w 2147483647
    //   9: putfield bzF : I
    //   12: iconst_0
    //   13: istore_2
    //   14: iload_2
    //   15: bipush #16
    //   17: if_icmpge -> 226
    //   20: iconst_0
    //   21: istore_3
    //   22: iload_3
    //   23: bipush #16
    //   25: if_icmpge -> 220
    //   28: aload_0
    //   29: getfield Dne : [I
    //   32: iload_2
    //   33: iload_3
    //   34: iconst_4
    //   35: ishl
    //   36: iadd
    //   37: sipush #-999
    //   40: iastore
    //   41: iload_1
    //   42: bipush #16
    //   44: iadd
    //   45: iconst_1
    //   46: isub
    //   47: istore #4
    //   49: iload #4
    //   51: ifle -> 100
    //   54: aload_0
    //   55: iload_2
    //   56: iload #4
    //   58: iconst_1
    //   59: isub
    //   60: iload_3
    //   61: invokevirtual FWm : (III)I
    //   64: ifne -> 73
    //   67: iinc #4, -1
    //   70: goto -> 49
    //   73: aload_0
    //   74: getfield FWm : [I
    //   77: iload_3
    //   78: iconst_4
    //   79: ishl
    //   80: iload_2
    //   81: ior
    //   82: iload #4
    //   84: iastore
    //   85: iload #4
    //   87: aload_0
    //   88: getfield bzF : I
    //   91: if_icmpge -> 100
    //   94: aload_0
    //   95: iload #4
    //   97: putfield bzF : I
    //   100: aload_0
    //   101: getfield Dne : LQnq;
    //   104: getfield Dne : LJik;
    //   107: getfield FWm : Z
    //   110: ifne -> 211
    //   113: bipush #15
    //   115: istore #4
    //   117: iload_1
    //   118: bipush #16
    //   120: iadd
    //   121: iconst_1
    //   122: isub
    //   123: istore #5
    //   125: iload #4
    //   127: aload_0
    //   128: iload_2
    //   129: iload #5
    //   131: iload_3
    //   132: invokevirtual FWm : (III)I
    //   135: isub
    //   136: istore #4
    //   138: iload #4
    //   140: ifle -> 198
    //   143: aload_0
    //   144: getfield Dne : [LcHy;
    //   147: iload #5
    //   149: iconst_4
    //   150: ishr
    //   151: aaload
    //   152: astore #6
    //   154: aload #6
    //   156: ifnull -> 198
    //   159: aload #6
    //   161: iload_2
    //   162: iload #5
    //   164: bipush #15
    //   166: iand
    //   167: iload_3
    //   168: iload #4
    //   170: invokevirtual bzF : (IIII)V
    //   173: aload_0
    //   174: getfield Dne : LQnq;
    //   177: aload_0
    //   178: getfield Dne : I
    //   181: iconst_4
    //   182: ishl
    //   183: iload_2
    //   184: iadd
    //   185: iload #5
    //   187: aload_0
    //   188: getfield FWm : I
    //   191: iconst_4
    //   192: ishl
    //   193: iload_3
    //   194: iadd
    //   195: invokevirtual FWm : (III)V
    //   198: iinc #5, -1
    //   201: iload #5
    //   203: ifle -> 211
    //   206: iload #4
    //   208: ifgt -> 125
    //   211: iinc #3, 1
    //   214: goto -> 217
    //   217: goto -> 22
    //   220: iinc #2, 1
    //   223: goto -> 14
    //   226: aload_0
    //   227: iconst_1
    //   228: putfield Qnq : Z
    //   231: iconst_0
    //   232: istore_2
    //   233: iload_2
    //   234: bipush #16
    //   236: if_icmpge -> 265
    //   239: iconst_0
    //   240: istore_3
    //   241: iload_3
    //   242: bipush #16
    //   244: if_icmpge -> 259
    //   247: aload_0
    //   248: iload_2
    //   249: iload_3
    //   250: invokespecial Dne : (II)V
    //   253: iinc #3, 1
    //   256: goto -> 241
    //   259: iinc #2, 1
    //   262: goto -> 233
    //   265: return
  }
  
  public void div() {
    // Byte code:
    //   0: iconst_0
    //   1: istore_1
    //   2: iload_1
    //   3: bipush #8
    //   5: if_icmpge -> 413
    //   8: aload_0
    //   9: getfield Qnq : I
    //   12: sipush #4096
    //   15: if_icmplt -> 19
    //   18: return
    //   19: aload_0
    //   20: getfield Qnq : I
    //   23: bipush #16
    //   25: irem
    //   26: istore_2
    //   27: aload_0
    //   28: getfield Qnq : I
    //   31: bipush #16
    //   33: idiv
    //   34: bipush #16
    //   36: irem
    //   37: istore_3
    //   38: aload_0
    //   39: getfield Qnq : I
    //   42: sipush #256
    //   45: idiv
    //   46: istore #4
    //   48: aload_0
    //   49: dup
    //   50: getfield Qnq : I
    //   53: iconst_1
    //   54: iadd
    //   55: putfield Qnq : I
    //   58: aload_0
    //   59: getfield Dne : I
    //   62: iconst_4
    //   63: ishl
    //   64: iload_3
    //   65: iadd
    //   66: istore #5
    //   68: aload_0
    //   69: getfield FWm : I
    //   72: iconst_4
    //   73: ishl
    //   74: iload #4
    //   76: iadd
    //   77: istore #6
    //   79: iconst_0
    //   80: istore #7
    //   82: iload #7
    //   84: bipush #16
    //   86: if_icmpge -> 407
    //   89: iload_2
    //   90: iconst_4
    //   91: ishl
    //   92: iload #7
    //   94: iadd
    //   95: istore #8
    //   97: aload_0
    //   98: getfield Dne : [LcHy;
    //   101: iload_2
    //   102: aaload
    //   103: ifnonnull -> 140
    //   106: iload #7
    //   108: ifeq -> 166
    //   111: iload #7
    //   113: bipush #15
    //   115: if_icmpeq -> 166
    //   118: iload_3
    //   119: ifeq -> 166
    //   122: iload_3
    //   123: bipush #15
    //   125: if_icmpeq -> 166
    //   128: iload #4
    //   130: ifeq -> 166
    //   133: iload #4
    //   135: bipush #15
    //   137: if_icmpeq -> 166
    //   140: aload_0
    //   141: getfield Dne : [LcHy;
    //   144: iload_2
    //   145: aaload
    //   146: ifnull -> 401
    //   149: aload_0
    //   150: getfield Dne : [LcHy;
    //   153: iload_2
    //   154: aaload
    //   155: iload_3
    //   156: iload #7
    //   158: iload #4
    //   160: invokevirtual Dne : (III)I
    //   163: ifne -> 401
    //   166: getstatic zKP.bzF : [I
    //   169: aload_0
    //   170: getfield Dne : LQnq;
    //   173: iload #5
    //   175: iload #8
    //   177: iconst_1
    //   178: isub
    //   179: iload #6
    //   181: invokevirtual Dne : (III)I
    //   184: iaload
    //   185: ifle -> 203
    //   188: aload_0
    //   189: getfield Dne : LQnq;
    //   192: iload #5
    //   194: iload #8
    //   196: iconst_1
    //   197: isub
    //   198: iload #6
    //   200: invokevirtual Qnq : (III)V
    //   203: getstatic zKP.bzF : [I
    //   206: aload_0
    //   207: getfield Dne : LQnq;
    //   210: iload #5
    //   212: iload #8
    //   214: iconst_1
    //   215: iadd
    //   216: iload #6
    //   218: invokevirtual Dne : (III)I
    //   221: iaload
    //   222: ifle -> 240
    //   225: aload_0
    //   226: getfield Dne : LQnq;
    //   229: iload #5
    //   231: iload #8
    //   233: iconst_1
    //   234: iadd
    //   235: iload #6
    //   237: invokevirtual Qnq : (III)V
    //   240: getstatic zKP.bzF : [I
    //   243: aload_0
    //   244: getfield Dne : LQnq;
    //   247: iload #5
    //   249: iconst_1
    //   250: isub
    //   251: iload #8
    //   253: iload #6
    //   255: invokevirtual Dne : (III)I
    //   258: iaload
    //   259: ifle -> 277
    //   262: aload_0
    //   263: getfield Dne : LQnq;
    //   266: iload #5
    //   268: iconst_1
    //   269: isub
    //   270: iload #8
    //   272: iload #6
    //   274: invokevirtual Qnq : (III)V
    //   277: getstatic zKP.bzF : [I
    //   280: aload_0
    //   281: getfield Dne : LQnq;
    //   284: iload #5
    //   286: iconst_1
    //   287: iadd
    //   288: iload #8
    //   290: iload #6
    //   292: invokevirtual Dne : (III)I
    //   295: iaload
    //   296: ifle -> 314
    //   299: aload_0
    //   300: getfield Dne : LQnq;
    //   303: iload #5
    //   305: iconst_1
    //   306: iadd
    //   307: iload #8
    //   309: iload #6
    //   311: invokevirtual Qnq : (III)V
    //   314: getstatic zKP.bzF : [I
    //   317: aload_0
    //   318: getfield Dne : LQnq;
    //   321: iload #5
    //   323: iload #8
    //   325: iload #6
    //   327: iconst_1
    //   328: isub
    //   329: invokevirtual Dne : (III)I
    //   332: iaload
    //   333: ifle -> 351
    //   336: aload_0
    //   337: getfield Dne : LQnq;
    //   340: iload #5
    //   342: iload #8
    //   344: iload #6
    //   346: iconst_1
    //   347: isub
    //   348: invokevirtual Qnq : (III)V
    //   351: getstatic zKP.bzF : [I
    //   354: aload_0
    //   355: getfield Dne : LQnq;
    //   358: iload #5
    //   360: iload #8
    //   362: iload #6
    //   364: iconst_1
    //   365: iadd
    //   366: invokevirtual Dne : (III)I
    //   369: iaload
    //   370: ifle -> 388
    //   373: aload_0
    //   374: getfield Dne : LQnq;
    //   377: iload #5
    //   379: iload #8
    //   381: iload #6
    //   383: iconst_1
    //   384: iadd
    //   385: invokevirtual Qnq : (III)V
    //   388: aload_0
    //   389: getfield Dne : LQnq;
    //   392: iload #5
    //   394: iload #8
    //   396: iload #6
    //   398: invokevirtual Qnq : (III)V
    //   401: iinc #7, 1
    //   404: goto -> 82
    //   407: iinc #1, 1
    //   410: goto -> 2
    //   413: return
  }
  
  public void Dne(ZfC paramZfC1, ZfC paramZfC2, int paramInt1, int paramInt2) {
    if (!this.bzF && paramZfC1.Dne(paramInt1 + 1, paramInt2 + 1) && paramZfC1.Dne(paramInt1, paramInt2 + 1) && paramZfC1.Dne(paramInt1 + 1, paramInt2))
      paramZfC1.Dne(paramZfC2, paramInt1, paramInt2); 
    if (paramZfC1.Dne(paramInt1 - 1, paramInt2) && !(paramZfC1.Dne(paramInt1 - 1, paramInt2)).bzF && paramZfC1.Dne(paramInt1 - 1, paramInt2 + 1) && paramZfC1.Dne(paramInt1, paramInt2 + 1) && paramZfC1.Dne(paramInt1 - 1, paramInt2 + 1))
      paramZfC1.Dne(paramZfC2, paramInt1 - 1, paramInt2); 
    if (paramZfC1.Dne(paramInt1, paramInt2 - 1) && !(paramZfC1.Dne(paramInt1, paramInt2 - 1)).bzF && paramZfC1.Dne(paramInt1 + 1, paramInt2 - 1) && paramZfC1.Dne(paramInt1 + 1, paramInt2 - 1) && paramZfC1.Dne(paramInt1 + 1, paramInt2))
      paramZfC1.Dne(paramZfC2, paramInt1, paramInt2 - 1); 
    if (paramZfC1.Dne(paramInt1 - 1, paramInt2 - 1) && !(paramZfC1.Dne(paramInt1 - 1, paramInt2 - 1)).bzF && paramZfC1.Dne(paramInt1, paramInt2 - 1) && paramZfC1.Dne(paramInt1 - 1, paramInt2))
      paramZfC1.Dne(paramZfC2, paramInt1 - 1, paramInt2 - 1); 
  }
  
  public boolean Dne() {
    return false;
  }
  
  public void Dne(Class paramClass, bSp parambSp, List paramList, pUe parampUe) {
    // Byte code:
    //   0: aload_2
    //   1: getfield FWm : D
    //   4: ldc2_w 2.0
    //   7: dsub
    //   8: ldc2_w 16.0
    //   11: ddiv
    //   12: invokestatic FWm : (D)I
    //   15: istore #5
    //   17: aload_2
    //   18: getfield aFZ : D
    //   21: ldc2_w 2.0
    //   24: dadd
    //   25: ldc2_w 16.0
    //   28: ddiv
    //   29: invokestatic FWm : (D)I
    //   32: istore #6
    //   34: iload #5
    //   36: ifge -> 45
    //   39: iconst_0
    //   40: istore #5
    //   42: goto -> 64
    //   45: iload #5
    //   47: aload_0
    //   48: getfield Dne : [Ljava/util/List;
    //   51: arraylength
    //   52: if_icmplt -> 64
    //   55: aload_0
    //   56: getfield Dne : [Ljava/util/List;
    //   59: arraylength
    //   60: iconst_1
    //   61: isub
    //   62: istore #5
    //   64: iload #6
    //   66: aload_0
    //   67: getfield Dne : [Ljava/util/List;
    //   70: arraylength
    //   71: if_icmplt -> 86
    //   74: aload_0
    //   75: getfield Dne : [Ljava/util/List;
    //   78: arraylength
    //   79: iconst_1
    //   80: isub
    //   81: istore #6
    //   83: goto -> 94
    //   86: iload #6
    //   88: ifge -> 94
    //   91: iconst_0
    //   92: istore #6
    //   94: iload #5
    //   96: istore #7
    //   98: iload #7
    //   100: iload #6
    //   102: if_icmpgt -> 205
    //   105: aload_0
    //   106: getfield Dne : [Ljava/util/List;
    //   109: iload #7
    //   111: aaload
    //   112: astore #8
    //   114: iconst_0
    //   115: istore #9
    //   117: iload #9
    //   119: aload #8
    //   121: invokeinterface size : ()I
    //   126: if_icmpge -> 199
    //   129: aload #8
    //   131: iload #9
    //   133: invokeinterface get : (I)Ljava/lang/Object;
    //   138: checkcast sMa
    //   141: astore #10
    //   143: aload_1
    //   144: aload #10
    //   146: invokevirtual getClass : ()Ljava/lang/Class;
    //   149: invokevirtual isAssignableFrom : (Ljava/lang/Class;)Z
    //   152: ifeq -> 193
    //   155: aload #10
    //   157: getfield Dne : LbSp;
    //   160: aload_2
    //   161: invokevirtual Dne : (LbSp;)Z
    //   164: ifeq -> 193
    //   167: aload #4
    //   169: ifnull -> 184
    //   172: aload #4
    //   174: aload #10
    //   176: invokeinterface Dne : (LsMa;)Z
    //   181: ifeq -> 193
    //   184: aload_3
    //   185: aload #10
    //   187: invokeinterface add : (Ljava/lang/Object;)Z
    //   192: pop
    //   193: iinc #9, 1
    //   196: goto -> 117
    //   199: iinc #7, 1
    //   202: goto -> 98
    //   205: return
  }
  
  public boolean Dne(boolean paramBoolean) {
    // Byte code:
    //   0: iload_1
    //   1: ifeq -> 35
    //   4: aload_0
    //   5: getfield aFZ : Z
    //   8: ifeq -> 26
    //   11: aload_0
    //   12: getfield Dne : LQnq;
    //   15: invokevirtual FWm : ()J
    //   18: aload_0
    //   19: getfield Dne : J
    //   22: lcmp
    //   23: ifne -> 33
    //   26: aload_0
    //   27: getfield Qnq : Z
    //   30: ifeq -> 63
    //   33: iconst_1
    //   34: ireturn
    //   35: aload_0
    //   36: getfield aFZ : Z
    //   39: ifeq -> 63
    //   42: aload_0
    //   43: getfield Dne : LQnq;
    //   46: invokevirtual FWm : ()J
    //   49: aload_0
    //   50: getfield Dne : J
    //   53: ldc2_w 600
    //   56: ladd
    //   57: lcmp
    //   58: iflt -> 63
    //   61: iconst_1
    //   62: ireturn
    //   63: aload_0
    //   64: getfield Qnq : Z
    //   67: ireturn
  }
  
  public void zGp() {
    if (this.div && !((Jik)this.Dne.Dne).FWm)
      IjH(); 
  }
  
  public void Qnq() {
    // Byte code:
    //   0: aload_0
    //   1: iconst_0
    //   2: putfield FWm : Z
    //   5: aload_0
    //   6: getfield Dne : Ljava/util/Map;
    //   9: invokeinterface values : ()Ljava/util/Collection;
    //   14: invokeinterface iterator : ()Ljava/util/Iterator;
    //   19: astore_1
    //   20: aload_1
    //   21: invokeinterface hasNext : ()Z
    //   26: ifeq -> 50
    //   29: aload_1
    //   30: invokeinterface next : ()Ljava/lang/Object;
    //   35: checkcast ipD
    //   38: astore_2
    //   39: aload_0
    //   40: getfield Dne : LQnq;
    //   43: aload_2
    //   44: invokevirtual Dne : (LipD;)V
    //   47: goto -> 20
    //   50: iconst_0
    //   51: istore_2
    //   52: iload_2
    //   53: aload_0
    //   54: getfield Dne : [Ljava/util/List;
    //   57: arraylength
    //   58: if_icmpge -> 80
    //   61: aload_0
    //   62: getfield Dne : LQnq;
    //   65: aload_0
    //   66: getfield Dne : [Ljava/util/List;
    //   69: iload_2
    //   70: aaload
    //   71: invokevirtual FWm : (Ljava/util/List;)V
    //   74: iinc #2, 1
    //   77: goto -> 52
    //   80: return
  }
  
  public void aFZ() {
    this.Qnq = true;
  }
  
  public void Dne(cHy[] paramArrayOfcHy) {
    this.Dne = paramArrayOfcHy;
  }
  
  private void IjH() {
    // Byte code:
    //   0: aload_0
    //   1: getfield Dne : LQnq;
    //   4: getfield Dne : LBkx;
    //   7: ldc_w 'recheckGaps'
    //   10: invokevirtual Dne : (Ljava/lang/String;)V
    //   13: aload_0
    //   14: getfield Dne : LQnq;
    //   17: aload_0
    //   18: getfield Dne : I
    //   21: bipush #16
    //   23: imul
    //   24: bipush #8
    //   26: iadd
    //   27: iconst_0
    //   28: aload_0
    //   29: getfield FWm : I
    //   32: bipush #16
    //   34: imul
    //   35: bipush #8
    //   37: iadd
    //   38: bipush #16
    //   40: invokevirtual Dne : (IIII)Z
    //   43: ifeq -> 281
    //   46: iconst_0
    //   47: istore_1
    //   48: iload_1
    //   49: bipush #16
    //   51: if_icmpge -> 276
    //   54: iconst_0
    //   55: istore_2
    //   56: iload_2
    //   57: bipush #16
    //   59: if_icmpge -> 270
    //   62: aload_0
    //   63: getfield Dne : [Z
    //   66: iload_1
    //   67: iload_2
    //   68: bipush #16
    //   70: imul
    //   71: iadd
    //   72: baload
    //   73: ifeq -> 264
    //   76: aload_0
    //   77: getfield Dne : [Z
    //   80: iload_1
    //   81: iload_2
    //   82: bipush #16
    //   84: imul
    //   85: iadd
    //   86: iconst_0
    //   87: bastore
    //   88: aload_0
    //   89: iload_1
    //   90: iload_2
    //   91: invokevirtual Dne : (II)I
    //   94: istore_3
    //   95: aload_0
    //   96: getfield Dne : I
    //   99: bipush #16
    //   101: imul
    //   102: iload_1
    //   103: iadd
    //   104: istore #4
    //   106: aload_0
    //   107: getfield FWm : I
    //   110: bipush #16
    //   112: imul
    //   113: iload_2
    //   114: iadd
    //   115: istore #5
    //   117: aload_0
    //   118: getfield Dne : LQnq;
    //   121: iload #4
    //   123: iconst_1
    //   124: isub
    //   125: iload #5
    //   127: invokevirtual bzF : (II)I
    //   130: istore #6
    //   132: aload_0
    //   133: getfield Dne : LQnq;
    //   136: iload #4
    //   138: iconst_1
    //   139: iadd
    //   140: iload #5
    //   142: invokevirtual bzF : (II)I
    //   145: istore #7
    //   147: aload_0
    //   148: getfield Dne : LQnq;
    //   151: iload #4
    //   153: iload #5
    //   155: iconst_1
    //   156: isub
    //   157: invokevirtual bzF : (II)I
    //   160: istore #8
    //   162: aload_0
    //   163: getfield Dne : LQnq;
    //   166: iload #4
    //   168: iload #5
    //   170: iconst_1
    //   171: iadd
    //   172: invokevirtual bzF : (II)I
    //   175: istore #9
    //   177: iload #7
    //   179: iload #6
    //   181: if_icmpge -> 188
    //   184: iload #7
    //   186: istore #6
    //   188: iload #8
    //   190: iload #6
    //   192: if_icmpge -> 199
    //   195: iload #8
    //   197: istore #6
    //   199: iload #9
    //   201: iload #6
    //   203: if_icmpge -> 210
    //   206: iload #9
    //   208: istore #6
    //   210: aload_0
    //   211: iload #4
    //   213: iload #5
    //   215: iload #6
    //   217: invokespecial FWm : (III)V
    //   220: aload_0
    //   221: iload #4
    //   223: iconst_1
    //   224: isub
    //   225: iload #5
    //   227: iload_3
    //   228: invokespecial FWm : (III)V
    //   231: aload_0
    //   232: iload #4
    //   234: iconst_1
    //   235: iadd
    //   236: iload #5
    //   238: iload_3
    //   239: invokespecial FWm : (III)V
    //   242: aload_0
    //   243: iload #4
    //   245: iload #5
    //   247: iconst_1
    //   248: isub
    //   249: iload_3
    //   250: invokespecial FWm : (III)V
    //   253: aload_0
    //   254: iload #4
    //   256: iload #5
    //   258: iconst_1
    //   259: iadd
    //   260: iload_3
    //   261: invokespecial FWm : (III)V
    //   264: iinc #2, 1
    //   267: goto -> 56
    //   270: iinc #1, 1
    //   273: goto -> 48
    //   276: aload_0
    //   277: iconst_0
    //   278: putfield div : Z
    //   281: aload_0
    //   282: getfield Dne : LQnq;
    //   285: getfield Dne : LBkx;
    //   288: invokevirtual FWm : ()V
    //   291: return
  }
  
  public void Dne(udO paramudO, int paramInt1, int paramInt2, int paramInt3, int paramInt4) {
    cHy cHy1;
    long l = this.Dne[paramInt2 >> 4];
    if (l == null) {
      cHy1 = this.Dne[paramInt2 >> 4] = new cHy(paramInt2 >> 4 << 4, !((Jik)this.Dne.Dne).FWm);
      FWm();
    } 
    this.Qnq = true;
    if (paramudO == udO.Dne) {
      if (!((Jik)this.Dne.Dne).FWm)
        cHy1.bzF(paramInt1, paramInt2 & 0xF, paramInt3, paramInt4); 
    } else if (paramudO == udO.FWm) {
      cHy1.Qnq(paramInt1, paramInt2 & 0xF, paramInt3, paramInt4);
    } 
  }
  
  public boolean FWm(int paramInt1, int paramInt2) {
    // Byte code:
    //   0: iload_1
    //   1: ifge -> 6
    //   4: iconst_0
    //   5: istore_1
    //   6: iload_2
    //   7: sipush #256
    //   10: if_icmplt -> 17
    //   13: sipush #255
    //   16: istore_2
    //   17: iload_1
    //   18: istore_3
    //   19: iload_3
    //   20: iload_2
    //   21: if_icmpgt -> 55
    //   24: aload_0
    //   25: getfield Dne : [LcHy;
    //   28: iload_3
    //   29: iconst_4
    //   30: ishr
    //   31: aaload
    //   32: astore #4
    //   34: aload #4
    //   36: ifnull -> 49
    //   39: aload #4
    //   41: invokevirtual Dne : ()Z
    //   44: ifne -> 49
    //   47: iconst_0
    //   48: ireturn
    //   49: iinc #3, 16
    //   52: goto -> 19
    //   55: iconst_1
    //   56: ireturn
  }
  
  public void Dne(ipD paramipD) {
    int i = paramipD.Qnq - this.Dne * 16;
    int j = paramipD.aFZ;
    int k = paramipD.zGp - this.FWm * 16;
    Dne(i, j, k, paramipD);
    if (this.FWm)
      this.Dne.bzF.add(paramipD); 
  }
  
  public void Dne(byte[] paramArrayOfbyte, int paramInt1, int paramInt2, boolean paramBoolean) {
    // Byte code:
    //   0: iconst_0
    //   1: istore #5
    //   3: aload_0
    //   4: getfield Dne : LQnq;
    //   7: getfield Dne : LJik;
    //   10: getfield FWm : Z
    //   13: ifne -> 20
    //   16: iconst_1
    //   17: goto -> 21
    //   20: iconst_0
    //   21: istore #6
    //   23: iconst_0
    //   24: istore #7
    //   26: iload #7
    //   28: aload_0
    //   29: getfield Dne : [LcHy;
    //   32: arraylength
    //   33: if_icmpge -> 139
    //   36: iload_2
    //   37: iconst_1
    //   38: iload #7
    //   40: ishl
    //   41: iand
    //   42: ifeq -> 110
    //   45: aload_0
    //   46: getfield Dne : [LcHy;
    //   49: iload #7
    //   51: aaload
    //   52: ifnonnull -> 75
    //   55: aload_0
    //   56: getfield Dne : [LcHy;
    //   59: iload #7
    //   61: new cHy
    //   64: dup
    //   65: iload #7
    //   67: iconst_4
    //   68: ishl
    //   69: iload #6
    //   71: invokespecial <init> : (IZ)V
    //   74: aastore
    //   75: aload_0
    //   76: getfield Dne : [LcHy;
    //   79: iload #7
    //   81: aaload
    //   82: invokevirtual Dne : ()[B
    //   85: astore #8
    //   87: aload_1
    //   88: iload #5
    //   90: aload #8
    //   92: iconst_0
    //   93: aload #8
    //   95: arraylength
    //   96: invokestatic arraycopy : (Ljava/lang/Object;ILjava/lang/Object;II)V
    //   99: iload #5
    //   101: aload #8
    //   103: arraylength
    //   104: iadd
    //   105: istore #5
    //   107: goto -> 133
    //   110: iload #4
    //   112: ifeq -> 133
    //   115: aload_0
    //   116: getfield Dne : [LcHy;
    //   119: iload #7
    //   121: aaload
    //   122: ifnull -> 133
    //   125: aload_0
    //   126: getfield Dne : [LcHy;
    //   129: iload #7
    //   131: aconst_null
    //   132: aastore
    //   133: iinc #7, 1
    //   136: goto -> 26
    //   139: iconst_0
    //   140: istore #7
    //   142: iload #7
    //   144: aload_0
    //   145: getfield Dne : [LcHy;
    //   148: arraylength
    //   149: if_icmpge -> 218
    //   152: iload_2
    //   153: iconst_1
    //   154: iload #7
    //   156: ishl
    //   157: iand
    //   158: ifeq -> 212
    //   161: aload_0
    //   162: getfield Dne : [LcHy;
    //   165: iload #7
    //   167: aaload
    //   168: ifnull -> 212
    //   171: aload_0
    //   172: getfield Dne : [LcHy;
    //   175: iload #7
    //   177: aaload
    //   178: invokevirtual FWm : ()LFYZ;
    //   181: astore #8
    //   183: aload_1
    //   184: iload #5
    //   186: aload #8
    //   188: getfield Dne : [B
    //   191: iconst_0
    //   192: aload #8
    //   194: getfield Dne : [B
    //   197: arraylength
    //   198: invokestatic arraycopy : (Ljava/lang/Object;ILjava/lang/Object;II)V
    //   201: iload #5
    //   203: aload #8
    //   205: getfield Dne : [B
    //   208: arraylength
    //   209: iadd
    //   210: istore #5
    //   212: iinc #7, 1
    //   215: goto -> 142
    //   218: iconst_0
    //   219: istore #7
    //   221: iload #7
    //   223: aload_0
    //   224: getfield Dne : [LcHy;
    //   227: arraylength
    //   228: if_icmpge -> 297
    //   231: iload_2
    //   232: iconst_1
    //   233: iload #7
    //   235: ishl
    //   236: iand
    //   237: ifeq -> 291
    //   240: aload_0
    //   241: getfield Dne : [LcHy;
    //   244: iload #7
    //   246: aaload
    //   247: ifnull -> 291
    //   250: aload_0
    //   251: getfield Dne : [LcHy;
    //   254: iload #7
    //   256: aaload
    //   257: invokevirtual bzF : ()LFYZ;
    //   260: astore #8
    //   262: aload_1
    //   263: iload #5
    //   265: aload #8
    //   267: getfield Dne : [B
    //   270: iconst_0
    //   271: aload #8
    //   273: getfield Dne : [B
    //   276: arraylength
    //   277: invokestatic arraycopy : (Ljava/lang/Object;ILjava/lang/Object;II)V
    //   280: iload #5
    //   282: aload #8
    //   284: getfield Dne : [B
    //   287: arraylength
    //   288: iadd
    //   289: istore #5
    //   291: iinc #7, 1
    //   294: goto -> 221
    //   297: iload #6
    //   299: ifeq -> 381
    //   302: iconst_0
    //   303: istore #7
    //   305: iload #7
    //   307: aload_0
    //   308: getfield Dne : [LcHy;
    //   311: arraylength
    //   312: if_icmpge -> 381
    //   315: iload_2
    //   316: iconst_1
    //   317: iload #7
    //   319: ishl
    //   320: iand
    //   321: ifeq -> 375
    //   324: aload_0
    //   325: getfield Dne : [LcHy;
    //   328: iload #7
    //   330: aaload
    //   331: ifnull -> 375
    //   334: aload_0
    //   335: getfield Dne : [LcHy;
    //   338: iload #7
    //   340: aaload
    //   341: invokevirtual Qnq : ()LFYZ;
    //   344: astore #8
    //   346: aload_1
    //   347: iload #5
    //   349: aload #8
    //   351: getfield Dne : [B
    //   354: iconst_0
    //   355: aload #8
    //   357: getfield Dne : [B
    //   360: arraylength
    //   361: invokestatic arraycopy : (Ljava/lang/Object;ILjava/lang/Object;II)V
    //   364: iload #5
    //   366: aload #8
    //   368: getfield Dne : [B
    //   371: arraylength
    //   372: iadd
    //   373: istore #5
    //   375: iinc #7, 1
    //   378: goto -> 305
    //   381: iconst_0
    //   382: istore #7
    //   384: iload #7
    //   386: aload_0
    //   387: getfield Dne : [LcHy;
    //   390: arraylength
    //   391: if_icmpge -> 527
    //   394: iload_3
    //   395: iconst_1
    //   396: iload #7
    //   398: ishl
    //   399: iand
    //   400: ifeq -> 483
    //   403: aload_0
    //   404: getfield Dne : [LcHy;
    //   407: iload #7
    //   409: aaload
    //   410: ifnonnull -> 422
    //   413: wide iinc #5 2048
    //   419: goto -> 521
    //   422: aload_0
    //   423: getfield Dne : [LcHy;
    //   426: iload #7
    //   428: aaload
    //   429: invokevirtual Dne : ()LFYZ;
    //   432: astore #8
    //   434: aload #8
    //   436: ifnonnull -> 451
    //   439: aload_0
    //   440: getfield Dne : [LcHy;
    //   443: iload #7
    //   445: aaload
    //   446: invokevirtual aFZ : ()LFYZ;
    //   449: astore #8
    //   451: aload_1
    //   452: iload #5
    //   454: aload #8
    //   456: getfield Dne : [B
    //   459: iconst_0
    //   460: aload #8
    //   462: getfield Dne : [B
    //   465: arraylength
    //   466: invokestatic arraycopy : (Ljava/lang/Object;ILjava/lang/Object;II)V
    //   469: iload #5
    //   471: aload #8
    //   473: getfield Dne : [B
    //   476: arraylength
    //   477: iadd
    //   478: istore #5
    //   480: goto -> 521
    //   483: iload #4
    //   485: ifeq -> 521
    //   488: aload_0
    //   489: getfield Dne : [LcHy;
    //   492: iload #7
    //   494: aaload
    //   495: ifnull -> 521
    //   498: aload_0
    //   499: getfield Dne : [LcHy;
    //   502: iload #7
    //   504: aaload
    //   505: invokevirtual Dne : ()LFYZ;
    //   508: ifnull -> 521
    //   511: aload_0
    //   512: getfield Dne : [LcHy;
    //   515: iload #7
    //   517: aaload
    //   518: invokevirtual FWm : ()V
    //   521: iinc #7, 1
    //   524: goto -> 384
    //   527: iload #4
    //   529: ifeq -> 558
    //   532: aload_1
    //   533: iload #5
    //   535: aload_0
    //   536: getfield Dne : [B
    //   539: iconst_0
    //   540: aload_0
    //   541: getfield Dne : [B
    //   544: arraylength
    //   545: invokestatic arraycopy : (Ljava/lang/Object;ILjava/lang/Object;II)V
    //   548: iload #5
    //   550: aload_0
    //   551: getfield Dne : [B
    //   554: arraylength
    //   555: iadd
    //   556: istore #9
    //   558: iconst_0
    //   559: istore #7
    //   561: iload #7
    //   563: aload_0
    //   564: getfield Dne : [LcHy;
    //   567: arraylength
    //   568: if_icmpge -> 606
    //   571: aload_0
    //   572: getfield Dne : [LcHy;
    //   575: iload #7
    //   577: aaload
    //   578: ifnull -> 600
    //   581: iload_2
    //   582: iconst_1
    //   583: iload #7
    //   585: ishl
    //   586: iand
    //   587: ifeq -> 600
    //   590: aload_0
    //   591: getfield Dne : [LcHy;
    //   594: iload #7
    //   596: aaload
    //   597: invokevirtual Dne : ()V
    //   600: iinc #7, 1
    //   603: goto -> 561
    //   606: aload_0
    //   607: invokevirtual Dne : ()V
    //   610: aload_0
    //   611: getfield Dne : Ljava/util/Map;
    //   614: invokeinterface values : ()Ljava/util/Collection;
    //   619: invokeinterface iterator : ()Ljava/util/Iterator;
    //   624: astore #9
    //   626: aload #9
    //   628: invokeinterface hasNext : ()Z
    //   633: ifeq -> 656
    //   636: aload #9
    //   638: invokeinterface next : ()Ljava/lang/Object;
    //   643: checkcast ipD
    //   646: astore #10
    //   648: aload #10
    //   650: invokevirtual Qnq : ()V
    //   653: goto -> 626
    //   656: return
  }
  
  public void Dne(sMa paramsMa) {
    // Byte code:
    //   0: aload_0
    //   1: iconst_1
    //   2: putfield aFZ : Z
    //   5: aload_1
    //   6: getfield div : D
    //   9: ldc2_w 16.0
    //   12: ddiv
    //   13: invokestatic FWm : (D)I
    //   16: istore_2
    //   17: aload_1
    //   18: getfield mrb : D
    //   21: ldc2_w 16.0
    //   24: ddiv
    //   25: invokestatic FWm : (D)I
    //   28: istore_3
    //   29: iload_2
    //   30: aload_0
    //   31: getfield Dne : I
    //   34: if_icmpne -> 45
    //   37: iload_3
    //   38: aload_0
    //   39: getfield FWm : I
    //   42: if_icmpeq -> 80
    //   45: aload_0
    //   46: getfield Dne : LQnq;
    //   49: invokevirtual Dne : ()LdLs;
    //   52: new java/lang/StringBuilder
    //   55: dup
    //   56: invokespecial <init> : ()V
    //   59: ldc_w 'Wrong location! '
    //   62: invokevirtual append : (Ljava/lang/String;)Ljava/lang/StringBuilder;
    //   65: aload_1
    //   66: invokevirtual append : (Ljava/lang/Object;)Ljava/lang/StringBuilder;
    //   69: invokevirtual toString : ()Ljava/lang/String;
    //   72: invokeinterface bzF : (Ljava/lang/String;)V
    //   77: invokestatic dumpStack : ()V
    //   80: aload_1
    //   81: getfield IjH : D
    //   84: ldc2_w 16.0
    //   87: ddiv
    //   88: invokestatic FWm : (D)I
    //   91: istore #4
    //   93: iload #4
    //   95: ifge -> 101
    //   98: iconst_0
    //   99: istore #4
    //   101: iload #4
    //   103: aload_0
    //   104: getfield Dne : [Ljava/util/List;
    //   107: arraylength
    //   108: if_icmplt -> 120
    //   111: aload_0
    //   112: getfield Dne : [Ljava/util/List;
    //   115: arraylength
    //   116: iconst_1
    //   117: isub
    //   118: istore #4
    //   120: aload_1
    //   121: iconst_1
    //   122: putfield trS : Z
    //   125: aload_1
    //   126: aload_0
    //   127: getfield Dne : I
    //   130: putfield IjH : I
    //   133: aload_1
    //   134: iload #4
    //   136: putfield mrb : I
    //   139: aload_1
    //   140: aload_0
    //   141: getfield FWm : I
    //   144: putfield XHL : I
    //   147: aload_0
    //   148: getfield Dne : [Ljava/util/List;
    //   151: iload #4
    //   153: aaload
    //   154: aload_1
    //   155: invokeinterface add : (Ljava/lang/Object;)Z
    //   160: pop
    //   161: return
  }
  
  private void Dne(int paramInt1, int paramInt2, int paramInt3, int paramInt4) {
    // Byte code:
    //   0: iload #4
    //   2: iload_3
    //   3: if_icmple -> 56
    //   6: aload_0
    //   7: getfield Dne : LQnq;
    //   10: iload_1
    //   11: iconst_0
    //   12: iload_2
    //   13: bipush #16
    //   15: invokevirtual Dne : (IIII)Z
    //   18: ifeq -> 56
    //   21: iload_3
    //   22: istore #5
    //   24: iload #5
    //   26: iload #4
    //   28: if_icmpge -> 51
    //   31: aload_0
    //   32: getfield Dne : LQnq;
    //   35: getstatic udO.Dne : LudO;
    //   38: iload_1
    //   39: iload #5
    //   41: iload_2
    //   42: invokevirtual Dne : (LudO;III)V
    //   45: iinc #5, 1
    //   48: goto -> 24
    //   51: aload_0
    //   52: iconst_1
    //   53: putfield Qnq : Z
    //   56: return
  }
}


/* Location:              C:\Users\fract\Downloads\ERROR422.jar!\qMV.class
 * Java compiler version: 8 (52.0)
 * JD-Core Version:       1.1.3
 */