public class QRF extends ZOO {
  FUH Dne;
  
  boolean Dne;
  
  public void FWm() {
    // Byte code:
    //   0: aload_0
    //   1: getfield FWm : LFUH;
    //   4: invokevirtual bzF : ()LFUH;
    //   7: ifnull -> 46
    //   10: aload_0
    //   11: getfield FWm : LFUH;
    //   14: invokevirtual bzF : ()LFUH;
    //   17: instanceof FiG
    //   20: ifeq -> 46
    //   23: aload_0
    //   24: getfield FWm : LFUH;
    //   27: invokevirtual bzF : ()LFUH;
    //   30: checkcast FiG
    //   33: getfield Dne : Luqg;
    //   36: getfield Dne : Z
    //   39: ifeq -> 46
    //   42: aload_0
    //   43: invokespecial FWm : ()V
    //   46: return
  }
  
  public boolean Dne() {
    // Byte code:
    //   0: aload_0
    //   1: aload_0
    //   2: getfield FWm : LFUH;
    //   5: invokevirtual Dne : ()LFUH;
    //   8: iconst_1
    //   9: invokevirtual Dne : (LFUH;Z)Z
    //   12: ireturn
  }
  
  public QRF(FUH paramFUH, boolean paramBoolean) {
    super(paramFUH, 16.0F, false);
    this.Dne = paramBoolean;
    Dne(1);
  }
  
  public boolean FWm() {
    // Byte code:
    //   0: aload_0
    //   1: getfield FWm : LFUH;
    //   4: invokevirtual Dne : ()LFUH;
    //   7: ifnull -> 28
    //   10: aload_0
    //   11: getfield FWm : LFUH;
    //   14: invokevirtual Dne : ()LFUH;
    //   17: aload_0
    //   18: getfield Dne : LFUH;
    //   21: if_acmpeq -> 28
    //   24: iconst_1
    //   25: goto -> 29
    //   28: iconst_0
    //   29: ireturn
  }
  
  public void Dne() {
    // Byte code:
    //   0: aload_0
    //   1: getfield FWm : LFUH;
    //   4: aload_0
    //   5: getfield FWm : LFUH;
    //   8: invokevirtual Dne : ()LFUH;
    //   11: invokevirtual FWm : (LFUH;)V
    //   14: aload_0
    //   15: aload_0
    //   16: getfield FWm : LFUH;
    //   19: invokevirtual Dne : ()LFUH;
    //   22: putfield Dne : LFUH;
    //   25: aload_0
    //   26: getfield Dne : Z
    //   29: ifeq -> 175
    //   32: aload_0
    //   33: getfield FWm : LFUH;
    //   36: getfield Dne : LQnq;
    //   39: aload_0
    //   40: getfield FWm : LFUH;
    //   43: invokevirtual getClass : ()Ljava/lang/Class;
    //   46: invokestatic Dne : ()LzjJ;
    //   49: aload_0
    //   50: getfield FWm : LFUH;
    //   53: getfield div : D
    //   56: aload_0
    //   57: getfield FWm : LFUH;
    //   60: getfield IjH : D
    //   63: aload_0
    //   64: getfield FWm : LFUH;
    //   67: getfield mrb : D
    //   70: aload_0
    //   71: getfield FWm : LFUH;
    //   74: getfield div : D
    //   77: dconst_1
    //   78: dadd
    //   79: aload_0
    //   80: getfield FWm : LFUH;
    //   83: getfield IjH : D
    //   86: dconst_1
    //   87: dadd
    //   88: aload_0
    //   89: getfield FWm : LFUH;
    //   92: getfield mrb : D
    //   95: dconst_1
    //   96: dadd
    //   97: invokevirtual Dne : (DDDDDD)LbSp;
    //   100: aload_0
    //   101: getfield Dne : F
    //   104: f2d
    //   105: ldc2_w 10.0
    //   108: aload_0
    //   109: getfield Dne : F
    //   112: f2d
    //   113: invokevirtual FWm : (DDD)LbSp;
    //   116: invokevirtual Dne : (Ljava/lang/Class;LbSp;)Ljava/util/List;
    //   119: astore_1
    //   120: aload_1
    //   121: invokeinterface iterator : ()Ljava/util/Iterator;
    //   126: astore_2
    //   127: aload_2
    //   128: invokeinterface hasNext : ()Z
    //   133: ifeq -> 175
    //   136: aload_2
    //   137: invokeinterface next : ()Ljava/lang/Object;
    //   142: checkcast FUH
    //   145: astore_3
    //   146: aload_0
    //   147: getfield FWm : LFUH;
    //   150: aload_3
    //   151: if_acmpeq -> 172
    //   154: aload_3
    //   155: invokevirtual bzF : ()LFUH;
    //   158: ifnonnull -> 172
    //   161: aload_3
    //   162: aload_0
    //   163: getfield FWm : LFUH;
    //   166: invokevirtual Dne : ()LFUH;
    //   169: invokevirtual FWm : (LFUH;)V
    //   172: goto -> 127
    //   175: aload_0
    //   176: invokespecial Dne : ()V
    //   179: return
  }
}


/* Location:              C:\Users\fract\Downloads\ERROR422.jar!\QRF.class
 * Java compiler version: 8 (52.0)
 * JD-Core Version:       1.1.3
 */