public class quK extends cMv {
  private double bzF;
  
  private FUH Dne;
  
  private double FWm;
  
  private kSJ Dne;
  
  private double Dne;
  
  private float FWm;
  
  private float Dne;
  
  public void FWm() {
    this.Dne = null;
  }
  
  public boolean FWm() {
    // Byte code:
    //   0: aload_0
    //   1: getfield Dne : LkSJ;
    //   4: invokevirtual Dne : ()LKFZ;
    //   7: invokevirtual bzF : ()Z
    //   10: ifne -> 52
    //   13: aload_0
    //   14: getfield Dne : LFUH;
    //   17: invokevirtual udO : ()Z
    //   20: ifeq -> 52
    //   23: aload_0
    //   24: getfield Dne : LFUH;
    //   27: aload_0
    //   28: getfield Dne : LkSJ;
    //   31: invokevirtual Dne : (LsMa;)D
    //   34: aload_0
    //   35: getfield FWm : F
    //   38: aload_0
    //   39: getfield FWm : F
    //   42: fmul
    //   43: f2d
    //   44: dcmpg
    //   45: ifge -> 52
    //   48: iconst_1
    //   49: goto -> 53
    //   52: iconst_0
    //   53: ireturn
  }
  
  public quK(kSJ paramkSJ, float paramFloat1, float paramFloat2) {
    this.Dne = paramkSJ;
    this.Dne = paramFloat1;
    this.FWm = paramFloat2;
    Dne(1);
  }
  
  public boolean Dne() {
    // Byte code:
    //   0: aload_0
    //   1: aload_0
    //   2: getfield Dne : LkSJ;
    //   5: invokevirtual bzF : ()LFUH;
    //   8: putfield Dne : LFUH;
    //   11: aload_0
    //   12: getfield Dne : LFUH;
    //   15: ifnonnull -> 20
    //   18: iconst_0
    //   19: ireturn
    //   20: aload_0
    //   21: getfield Dne : LFUH;
    //   24: aload_0
    //   25: getfield Dne : LkSJ;
    //   28: invokevirtual Dne : (LsMa;)D
    //   31: aload_0
    //   32: getfield FWm : F
    //   35: aload_0
    //   36: getfield FWm : F
    //   39: fmul
    //   40: f2d
    //   41: dcmpl
    //   42: ifle -> 47
    //   45: iconst_0
    //   46: ireturn
    //   47: aload_0
    //   48: getfield Dne : LkSJ;
    //   51: bipush #16
    //   53: bipush #7
    //   55: aload_0
    //   56: getfield Dne : LkSJ;
    //   59: getfield Dne : LQnq;
    //   62: invokevirtual Dne : ()LziS;
    //   65: aload_0
    //   66: getfield Dne : LFUH;
    //   69: getfield div : D
    //   72: aload_0
    //   73: getfield Dne : LFUH;
    //   76: getfield IjH : D
    //   79: aload_0
    //   80: getfield Dne : LFUH;
    //   83: getfield mrb : D
    //   86: invokevirtual Dne : (DDD)LchN;
    //   89: invokestatic Dne : (LkSJ;IILchN;)LchN;
    //   92: astore_1
    //   93: aload_1
    //   94: ifnonnull -> 99
    //   97: iconst_0
    //   98: ireturn
    //   99: aload_0
    //   100: aload_1
    //   101: getfield Dne : D
    //   104: putfield Dne : D
    //   107: aload_0
    //   108: aload_1
    //   109: getfield FWm : D
    //   112: putfield FWm : D
    //   115: aload_0
    //   116: aload_1
    //   117: getfield bzF : D
    //   120: putfield bzF : D
    //   123: iconst_1
    //   124: ireturn
  }
  
  public void Dne() {
    // Byte code:
    //   0: aload_0
    //   1: getfield Dne : LkSJ;
    //   4: invokevirtual Dne : ()LKFZ;
    //   7: aload_0
    //   8: getfield Dne : D
    //   11: aload_0
    //   12: getfield FWm : D
    //   15: aload_0
    //   16: getfield bzF : D
    //   19: aload_0
    //   20: getfield Dne : F
    //   23: invokevirtual Dne : (DDDF)Z
    //   26: pop
    //   27: return
  }
}


/* Location:              C:\Users\fract\Downloads\ERROR422.jar!\quK.class
 * Java compiler version: 8 (52.0)
 * JD-Core Version:       1.1.3
 */