import net.minecraft.client.Minecraft;

public class RJV {
  private int bzF = -1;
  
  private int Dne;
  
  private final fzy Dne;
  
  private float FWm;
  
  private NMq Dne;
  
  private float Dne;
  
  private int aFZ;
  
  public XHL Dne;
  
  private final Minecraft Dne;
  
  private int FWm = -1;
  
  private boolean Dne = true;
  
  private int Qnq;
  
  public boolean bzF() {
    return true;
  }
  
  public void FWm(FiG paramFiG) {
    paramFiG.mrb = -180.0F;
  }
  
  public MJs Dne(Qnq paramQnq) {
    return new MJs(this.Dne, paramQnq, this.Dne.Dne, this.Dne);
  }
  
  public boolean Dne(FiG paramFiG, Qnq paramQnq, NMq paramNMq) {
    // Byte code:
    //   0: aload_0
    //   1: invokespecial bzF : ()V
    //   4: aload_0
    //   5: getfield Dne : Lfzy;
    //   8: new DtJ
    //   11: dup
    //   12: iconst_m1
    //   13: iconst_m1
    //   14: iconst_m1
    //   15: sipush #255
    //   18: aload_1
    //   19: getfield Dne : LMOS;
    //   22: invokevirtual Dne : ()LNMq;
    //   25: fconst_0
    //   26: fconst_0
    //   27: fconst_0
    //   28: invokespecial <init> : (IIIILNMq;FFF)V
    //   31: invokevirtual FWm : (LNER;)V
    //   34: aload_3
    //   35: getfield Dne : I
    //   38: istore #4
    //   40: aload_3
    //   41: aload_2
    //   42: aload_1
    //   43: invokevirtual Dne : (LQnq;LFiG;)LNMq;
    //   46: astore #5
    //   48: aload #5
    //   50: aload_3
    //   51: if_acmpne -> 71
    //   54: aload #5
    //   56: ifnull -> 69
    //   59: aload #5
    //   61: getfield Dne : I
    //   64: iload #4
    //   66: if_icmpne -> 71
    //   69: iconst_0
    //   70: ireturn
    //   71: aload_1
    //   72: getfield Dne : LMOS;
    //   75: getfield Dne : [LNMq;
    //   78: aload_1
    //   79: getfield Dne : LMOS;
    //   82: getfield Dne : I
    //   85: aload #5
    //   87: aastore
    //   88: aload #5
    //   90: getfield Dne : I
    //   93: ifne -> 112
    //   96: aload_1
    //   97: getfield Dne : LMOS;
    //   100: getfield Dne : [LNMq;
    //   103: aload_1
    //   104: getfield Dne : LMOS;
    //   107: getfield Dne : I
    //   110: aconst_null
    //   111: aastore
    //   112: iconst_1
    //   113: ireturn
  }
  
  public boolean Dne(int paramInt1, int paramInt2, int paramInt3, int paramInt4) {
    // Byte code:
    //   0: aload_0
    //   1: getfield Dne : LXHL;
    //   4: invokevirtual Dne : ()Z
    //   7: ifeq -> 28
    //   10: aload_0
    //   11: getfield Dne : Lnet/minecraft/client/Minecraft;
    //   14: getfield Dne : LMJs;
    //   17: iload_1
    //   18: iload_2
    //   19: iload_3
    //   20: invokevirtual FWm : (III)Z
    //   23: ifne -> 28
    //   26: iconst_0
    //   27: ireturn
    //   28: aload_0
    //   29: getfield Dne : Lnet/minecraft/client/Minecraft;
    //   32: getfield Dne : LVzZ;
    //   35: astore #5
    //   37: getstatic zKP.Dne : [LzKP;
    //   40: aload #5
    //   42: iload_1
    //   43: iload_2
    //   44: iload_3
    //   45: invokevirtual Dne : (III)I
    //   48: aaload
    //   49: astore #6
    //   51: aload #6
    //   53: ifnonnull -> 58
    //   56: iconst_0
    //   57: ireturn
    //   58: aload #5
    //   60: sipush #2001
    //   63: iload_1
    //   64: iload_2
    //   65: iload_3
    //   66: aload #6
    //   68: getfield FWm : I
    //   71: aload #5
    //   73: iload_1
    //   74: iload_2
    //   75: iload_3
    //   76: invokevirtual bzF : (III)I
    //   79: bipush #12
    //   81: ishl
    //   82: iadd
    //   83: invokevirtual Qnq : (IIIII)V
    //   86: aload #5
    //   88: iload_1
    //   89: iload_2
    //   90: iload_3
    //   91: invokevirtual bzF : (III)I
    //   94: istore #7
    //   96: aload #5
    //   98: iload_1
    //   99: iload_2
    //   100: iload_3
    //   101: invokevirtual Qnq : (III)Z
    //   104: istore #8
    //   106: iload #8
    //   108: ifeq -> 123
    //   111: aload #6
    //   113: aload #5
    //   115: iload_1
    //   116: iload_2
    //   117: iload_3
    //   118: iload #7
    //   120: invokevirtual bzF : (LQnq;IIII)V
    //   123: aload_0
    //   124: iconst_m1
    //   125: putfield FWm : I
    //   128: aload_0
    //   129: getfield Dne : LXHL;
    //   132: invokevirtual FWm : ()Z
    //   135: ifne -> 195
    //   138: aload_0
    //   139: getfield Dne : Lnet/minecraft/client/Minecraft;
    //   142: getfield Dne : LMJs;
    //   145: invokevirtual bzF : ()LNMq;
    //   148: astore #9
    //   150: aload #9
    //   152: ifnull -> 195
    //   155: aload #9
    //   157: aload #5
    //   159: aload #6
    //   161: getfield FWm : I
    //   164: iload_1
    //   165: iload_2
    //   166: iload_3
    //   167: aload_0
    //   168: getfield Dne : Lnet/minecraft/client/Minecraft;
    //   171: getfield Dne : LMJs;
    //   174: invokevirtual Dne : (LQnq;IIIILFiG;)V
    //   177: aload #9
    //   179: getfield Dne : I
    //   182: ifne -> 195
    //   185: aload_0
    //   186: getfield Dne : Lnet/minecraft/client/Minecraft;
    //   189: getfield Dne : LMJs;
    //   192: invokevirtual BJH : ()V
    //   195: iload #8
    //   197: ireturn
  }
  
  private void bzF() {
    // Byte code:
    //   0: aload_0
    //   1: getfield Dne : Lnet/minecraft/client/Minecraft;
    //   4: getfield Dne : LMJs;
    //   7: getfield Dne : LMOS;
    //   10: getfield Dne : I
    //   13: istore_1
    //   14: iload_1
    //   15: aload_0
    //   16: getfield aFZ : I
    //   19: if_icmpeq -> 45
    //   22: aload_0
    //   23: iload_1
    //   24: putfield aFZ : I
    //   27: aload_0
    //   28: getfield Dne : Lfzy;
    //   31: new aig
    //   34: dup
    //   35: aload_0
    //   36: getfield aFZ : I
    //   39: invokespecial <init> : (I)V
    //   42: invokevirtual FWm : (LNER;)V
    //   45: return
  }
  
  public void FWm() {
    bzF();
    this.Dne.Dne.bzF();
  }
  
  public boolean Qnq() {
    // Byte code:
    //   0: aload_0
    //   1: getfield Dne : LXHL;
    //   4: invokevirtual FWm : ()Z
    //   7: ifne -> 14
    //   10: iconst_1
    //   11: goto -> 15
    //   14: iconst_0
    //   15: ireturn
  }
  
  public void Dne(NMq paramNMq, int paramInt) {
    // Byte code:
    //   0: aload_0
    //   1: getfield Dne : LXHL;
    //   4: invokevirtual FWm : ()Z
    //   7: ifeq -> 26
    //   10: aload_0
    //   11: getfield Dne : Lfzy;
    //   14: new pRp
    //   17: dup
    //   18: iload_2
    //   19: aload_1
    //   20: invokespecial <init> : (ILNMq;)V
    //   23: invokevirtual FWm : (LNER;)V
    //   26: return
  }
  
  public void Dne(int paramInt1, int paramInt2, int paramInt3, int paramInt4) {
    // Byte code:
    //   0: aload_0
    //   1: getfield Dne : LXHL;
    //   4: invokevirtual Dne : ()Z
    //   7: ifeq -> 26
    //   10: aload_0
    //   11: getfield Dne : Lnet/minecraft/client/Minecraft;
    //   14: getfield Dne : LMJs;
    //   17: iload_1
    //   18: iload_2
    //   19: iload_3
    //   20: invokevirtual FWm : (III)Z
    //   23: ifeq -> 343
    //   26: aload_0
    //   27: getfield Dne : LXHL;
    //   30: invokevirtual FWm : ()Z
    //   33: ifeq -> 77
    //   36: aload_0
    //   37: getfield Dne : Lfzy;
    //   40: new Wbc
    //   43: dup
    //   44: iconst_0
    //   45: iload_1
    //   46: iload_2
    //   47: iload_3
    //   48: iload #4
    //   50: invokespecial <init> : (IIIII)V
    //   53: invokevirtual FWm : (LNER;)V
    //   56: aload_0
    //   57: getfield Dne : Lnet/minecraft/client/Minecraft;
    //   60: aload_0
    //   61: iload_1
    //   62: iload_2
    //   63: iload_3
    //   64: iload #4
    //   66: invokestatic Dne : (Lnet/minecraft/client/Minecraft;LRJV;IIII)V
    //   69: aload_0
    //   70: iconst_5
    //   71: putfield Qnq : I
    //   74: goto -> 343
    //   77: aload_0
    //   78: getfield Dne : Z
    //   81: ifeq -> 94
    //   84: aload_0
    //   85: iload_1
    //   86: iload_2
    //   87: iload_3
    //   88: invokespecial Dne : (III)Z
    //   91: ifne -> 343
    //   94: aload_0
    //   95: getfield Dne : Z
    //   98: ifeq -> 130
    //   101: aload_0
    //   102: getfield Dne : Lfzy;
    //   105: new Wbc
    //   108: dup
    //   109: iconst_1
    //   110: aload_0
    //   111: getfield Dne : I
    //   114: aload_0
    //   115: getfield FWm : I
    //   118: aload_0
    //   119: getfield bzF : I
    //   122: iload #4
    //   124: invokespecial <init> : (IIIII)V
    //   127: invokevirtual FWm : (LNER;)V
    //   130: aload_0
    //   131: getfield Dne : Lfzy;
    //   134: new Wbc
    //   137: dup
    //   138: iconst_0
    //   139: iload_1
    //   140: iload_2
    //   141: iload_3
    //   142: iload #4
    //   144: invokespecial <init> : (IIIII)V
    //   147: invokevirtual FWm : (LNER;)V
    //   150: aload_0
    //   151: getfield Dne : Lnet/minecraft/client/Minecraft;
    //   154: getfield Dne : LVzZ;
    //   157: iload_1
    //   158: iload_2
    //   159: iload_3
    //   160: invokevirtual Dne : (III)I
    //   163: istore #5
    //   165: iload #5
    //   167: ifle -> 205
    //   170: aload_0
    //   171: getfield Dne : F
    //   174: fconst_0
    //   175: fcmpl
    //   176: ifne -> 205
    //   179: getstatic zKP.Dne : [LzKP;
    //   182: iload #5
    //   184: aaload
    //   185: aload_0
    //   186: getfield Dne : Lnet/minecraft/client/Minecraft;
    //   189: getfield Dne : LVzZ;
    //   192: iload_1
    //   193: iload_2
    //   194: iload_3
    //   195: aload_0
    //   196: getfield Dne : Lnet/minecraft/client/Minecraft;
    //   199: getfield Dne : LMJs;
    //   202: invokevirtual Dne : (LQnq;IIILFiG;)V
    //   205: iload #5
    //   207: ifle -> 257
    //   210: getstatic zKP.Dne : [LzKP;
    //   213: iload #5
    //   215: aaload
    //   216: aload_0
    //   217: getfield Dne : Lnet/minecraft/client/Minecraft;
    //   220: getfield Dne : LMJs;
    //   223: aload_0
    //   224: getfield Dne : Lnet/minecraft/client/Minecraft;
    //   227: getfield Dne : LMJs;
    //   230: getfield Dne : LQnq;
    //   233: iload_1
    //   234: iload_2
    //   235: iload_3
    //   236: invokevirtual Dne : (LFiG;LQnq;III)F
    //   239: fconst_1
    //   240: fcmpl
    //   241: iflt -> 257
    //   244: aload_0
    //   245: iload_1
    //   246: iload_2
    //   247: iload_3
    //   248: iload #4
    //   250: invokevirtual Dne : (IIII)Z
    //   253: pop
    //   254: goto -> 343
    //   257: aload_0
    //   258: iconst_1
    //   259: putfield Dne : Z
    //   262: aload_0
    //   263: iload_1
    //   264: putfield Dne : I
    //   267: aload_0
    //   268: iload_2
    //   269: putfield FWm : I
    //   272: aload_0
    //   273: iload_3
    //   274: putfield bzF : I
    //   277: aload_0
    //   278: aload_0
    //   279: getfield Dne : Lnet/minecraft/client/Minecraft;
    //   282: getfield Dne : LMJs;
    //   285: invokevirtual Dne : ()LNMq;
    //   288: putfield Dne : LNMq;
    //   291: aload_0
    //   292: fconst_0
    //   293: putfield Dne : F
    //   296: aload_0
    //   297: fconst_0
    //   298: putfield FWm : F
    //   301: aload_0
    //   302: getfield Dne : Lnet/minecraft/client/Minecraft;
    //   305: getfield Dne : LVzZ;
    //   308: aload_0
    //   309: getfield Dne : Lnet/minecraft/client/Minecraft;
    //   312: getfield Dne : LMJs;
    //   315: getfield aFZ : I
    //   318: aload_0
    //   319: getfield Dne : I
    //   322: aload_0
    //   323: getfield FWm : I
    //   326: aload_0
    //   327: getfield bzF : I
    //   330: aload_0
    //   331: getfield Dne : F
    //   334: ldc 10.0
    //   336: fmul
    //   337: f2i
    //   338: iconst_1
    //   339: isub
    //   340: invokevirtual aFZ : (IIIII)V
    //   343: return
  }
  
  public float Dne() {
    // Byte code:
    //   0: aload_0
    //   1: getfield Dne : LXHL;
    //   4: invokevirtual FWm : ()Z
    //   7: ifeq -> 15
    //   10: ldc 5.0
    //   12: goto -> 17
    //   15: ldc 4.5
    //   17: freturn
  }
  
  public boolean Dne() {
    return false;
  }
  
  private boolean Dne(int paramInt1, int paramInt2, int paramInt3) {
    // Byte code:
    //   0: aload_0
    //   1: getfield Dne : Lnet/minecraft/client/Minecraft;
    //   4: getfield Dne : LMJs;
    //   7: invokevirtual Dne : ()LNMq;
    //   10: astore #4
    //   12: aload_0
    //   13: getfield Dne : LNMq;
    //   16: ifnonnull -> 28
    //   19: aload #4
    //   21: ifnonnull -> 28
    //   24: iconst_1
    //   25: goto -> 29
    //   28: iconst_0
    //   29: istore #5
    //   31: aload_0
    //   32: getfield Dne : LNMq;
    //   35: ifnull -> 100
    //   38: aload #4
    //   40: ifnull -> 100
    //   43: aload #4
    //   45: getfield bzF : I
    //   48: aload_0
    //   49: getfield Dne : LNMq;
    //   52: getfield bzF : I
    //   55: if_icmpne -> 97
    //   58: aload #4
    //   60: aload_0
    //   61: getfield Dne : LNMq;
    //   64: invokestatic Dne : (LNMq;LNMq;)Z
    //   67: ifeq -> 97
    //   70: aload #4
    //   72: invokevirtual FWm : ()Z
    //   75: ifne -> 93
    //   78: aload #4
    //   80: invokevirtual Qnq : ()I
    //   83: aload_0
    //   84: getfield Dne : LNMq;
    //   87: invokevirtual Qnq : ()I
    //   90: if_icmpne -> 97
    //   93: iconst_1
    //   94: goto -> 98
    //   97: iconst_0
    //   98: istore #5
    //   100: iload_1
    //   101: aload_0
    //   102: getfield Dne : I
    //   105: if_icmpne -> 133
    //   108: iload_2
    //   109: aload_0
    //   110: getfield FWm : I
    //   113: if_icmpne -> 133
    //   116: iload_3
    //   117: aload_0
    //   118: getfield bzF : I
    //   121: if_icmpne -> 133
    //   124: iload #5
    //   126: ifeq -> 133
    //   129: iconst_1
    //   130: goto -> 134
    //   133: iconst_0
    //   134: ireturn
  }
  
  public boolean zGp() {
    // Byte code:
    //   0: aload_0
    //   1: getfield Dne : LXHL;
    //   4: invokevirtual FWm : ()Z
    //   7: ireturn
  }
  
  public void Dne() {
    // Byte code:
    //   0: aload_0
    //   1: getfield Dne : Z
    //   4: ifeq -> 35
    //   7: aload_0
    //   8: getfield Dne : Lfzy;
    //   11: new Wbc
    //   14: dup
    //   15: iconst_1
    //   16: aload_0
    //   17: getfield Dne : I
    //   20: aload_0
    //   21: getfield FWm : I
    //   24: aload_0
    //   25: getfield bzF : I
    //   28: iconst_m1
    //   29: invokespecial <init> : (IIIII)V
    //   32: invokevirtual FWm : (LNER;)V
    //   35: aload_0
    //   36: iconst_0
    //   37: putfield Dne : Z
    //   40: aload_0
    //   41: fconst_0
    //   42: putfield Dne : F
    //   45: aload_0
    //   46: getfield Dne : Lnet/minecraft/client/Minecraft;
    //   49: getfield Dne : LVzZ;
    //   52: aload_0
    //   53: getfield Dne : Lnet/minecraft/client/Minecraft;
    //   56: getfield Dne : LMJs;
    //   59: getfield aFZ : I
    //   62: aload_0
    //   63: getfield Dne : I
    //   66: aload_0
    //   67: getfield FWm : I
    //   70: aload_0
    //   71: getfield bzF : I
    //   74: iconst_m1
    //   75: invokevirtual aFZ : (IIIII)V
    //   78: return
  }
  
  public boolean aFZ() {
    // Byte code:
    //   0: aload_0
    //   1: getfield Dne : LXHL;
    //   4: invokevirtual FWm : ()Z
    //   7: ireturn
  }
  
  public void Dne(int paramInt1, int paramInt2) {
    // Byte code:
    //   0: aload_0
    //   1: getfield Dne : Lfzy;
    //   4: new fwI
    //   7: dup
    //   8: iload_1
    //   9: iload_2
    //   10: invokespecial <init> : (II)V
    //   13: invokevirtual FWm : (LNER;)V
    //   16: return
  }
  
  public void Dne(XHL paramXHL) {
    // Byte code:
    //   0: aload_0
    //   1: aload_1
    //   2: putfield Dne : LXHL;
    //   5: aload_0
    //   6: getfield Dne : LXHL;
    //   9: aload_0
    //   10: getfield Dne : Lnet/minecraft/client/Minecraft;
    //   13: getfield Dne : LMJs;
    //   16: getfield Dne : Luqg;
    //   19: invokevirtual Dne : (Luqg;)V
    //   22: return
  }
  
  public static void Dne(Minecraft paramMinecraft, RJV paramRJV, int paramInt1, int paramInt2, int paramInt3, int paramInt4) {
    if (!paramMinecraft.Dne.Dne((FiG)paramMinecraft.Dne, paramInt1, paramInt2, paramInt3, paramInt4))
      paramRJV.Dne(paramInt1, paramInt2, paramInt3, paramInt4); 
  }
  
  public void Dne(NMq paramNMq) {
    // Byte code:
    //   0: aload_0
    //   1: getfield Dne : LXHL;
    //   4: invokevirtual FWm : ()Z
    //   7: ifeq -> 30
    //   10: aload_1
    //   11: ifnull -> 30
    //   14: aload_0
    //   15: getfield Dne : Lfzy;
    //   18: new pRp
    //   21: dup
    //   22: iconst_m1
    //   23: aload_1
    //   24: invokespecial <init> : (ILNMq;)V
    //   27: invokevirtual FWm : (LNER;)V
    //   30: return
  }
  
  public boolean FWm() {
    // Byte code:
    //   0: aload_0
    //   1: getfield Dne : LXHL;
    //   4: invokevirtual bzF : ()Z
    //   7: ireturn
  }
  
  public void Dne(FiG paramFiG) {
    // Byte code:
    //   0: aload_0
    //   1: getfield Dne : LXHL;
    //   4: aload_1
    //   5: getfield Dne : Luqg;
    //   8: invokevirtual Dne : (Luqg;)V
    //   11: return
  }
  
  public void bzF(FiG paramFiG) {
    // Byte code:
    //   0: aload_0
    //   1: invokespecial bzF : ()V
    //   4: aload_0
    //   5: getfield Dne : Lfzy;
    //   8: new Wbc
    //   11: dup
    //   12: iconst_5
    //   13: iconst_0
    //   14: iconst_0
    //   15: iconst_0
    //   16: sipush #255
    //   19: invokespecial <init> : (IIIII)V
    //   22: invokevirtual FWm : (LNER;)V
    //   25: aload_1
    //   26: invokevirtual ZfC : ()V
    //   29: return
  }
  
  public RJV(Minecraft paramMinecraft, fzy paramfzy) {
    this.Dne = null;
    this.Dne = 0.0F;
    this.FWm = 0.0F;
    this.Qnq = 0;
    this.Dne = false;
    this.Dne = XHL.FWm;
    this.aFZ = 0;
    this.Dne = paramMinecraft;
    this.Dne = paramfzy;
  }
  
  public void FWm(int paramInt1, int paramInt2, int paramInt3, int paramInt4) {
    // Byte code:
    //   0: aload_0
    //   1: invokespecial bzF : ()V
    //   4: aload_0
    //   5: getfield Qnq : I
    //   8: ifle -> 24
    //   11: aload_0
    //   12: dup
    //   13: getfield Qnq : I
    //   16: iconst_1
    //   17: isub
    //   18: putfield Qnq : I
    //   21: goto -> 350
    //   24: aload_0
    //   25: getfield Dne : LXHL;
    //   28: invokevirtual FWm : ()Z
    //   31: ifeq -> 75
    //   34: aload_0
    //   35: iconst_5
    //   36: putfield Qnq : I
    //   39: aload_0
    //   40: getfield Dne : Lfzy;
    //   43: new Wbc
    //   46: dup
    //   47: iconst_0
    //   48: iload_1
    //   49: iload_2
    //   50: iload_3
    //   51: iload #4
    //   53: invokespecial <init> : (IIIII)V
    //   56: invokevirtual FWm : (LNER;)V
    //   59: aload_0
    //   60: getfield Dne : Lnet/minecraft/client/Minecraft;
    //   63: aload_0
    //   64: iload_1
    //   65: iload_2
    //   66: iload_3
    //   67: iload #4
    //   69: invokestatic Dne : (Lnet/minecraft/client/Minecraft;LRJV;IIII)V
    //   72: goto -> 350
    //   75: aload_0
    //   76: iload_1
    //   77: iload_2
    //   78: iload_3
    //   79: invokespecial Dne : (III)Z
    //   82: ifeq -> 341
    //   85: aload_0
    //   86: getfield Dne : Lnet/minecraft/client/Minecraft;
    //   89: getfield Dne : LVzZ;
    //   92: iload_1
    //   93: iload_2
    //   94: iload_3
    //   95: invokevirtual Dne : (III)I
    //   98: istore #5
    //   100: iload #5
    //   102: ifne -> 111
    //   105: aload_0
    //   106: iconst_0
    //   107: putfield Dne : Z
    //   110: return
    //   111: getstatic zKP.Dne : [LzKP;
    //   114: iload #5
    //   116: aaload
    //   117: astore #6
    //   119: aload_0
    //   120: dup
    //   121: getfield Dne : F
    //   124: aload #6
    //   126: aload_0
    //   127: getfield Dne : Lnet/minecraft/client/Minecraft;
    //   130: getfield Dne : LMJs;
    //   133: aload_0
    //   134: getfield Dne : Lnet/minecraft/client/Minecraft;
    //   137: getfield Dne : LMJs;
    //   140: getfield Dne : LQnq;
    //   143: iload_1
    //   144: iload_2
    //   145: iload_3
    //   146: invokevirtual Dne : (LFiG;LQnq;III)F
    //   149: fadd
    //   150: putfield Dne : F
    //   153: aload_0
    //   154: getfield FWm : F
    //   157: ldc 4.0
    //   159: frem
    //   160: fconst_0
    //   161: fcmpl
    //   162: ifne -> 227
    //   165: aload #6
    //   167: ifnull -> 227
    //   170: aload_0
    //   171: getfield Dne : Lnet/minecraft/client/Minecraft;
    //   174: getfield Dne : LmKT;
    //   177: aload #6
    //   179: getfield kGO : LPsW;
    //   182: invokevirtual bzF : ()Ljava/lang/String;
    //   185: iload_1
    //   186: i2f
    //   187: ldc 0.5
    //   189: fadd
    //   190: iload_2
    //   191: i2f
    //   192: ldc 0.5
    //   194: fadd
    //   195: iload_3
    //   196: i2f
    //   197: ldc 0.5
    //   199: fadd
    //   200: aload #6
    //   202: getfield kGO : LPsW;
    //   205: invokevirtual Dne : ()F
    //   208: fconst_1
    //   209: fadd
    //   210: ldc 8.0
    //   212: fdiv
    //   213: aload #6
    //   215: getfield kGO : LPsW;
    //   218: invokevirtual FWm : ()F
    //   221: ldc 0.5
    //   223: fmul
    //   224: invokevirtual Dne : (Ljava/lang/String;FFFFF)V
    //   227: aload_0
    //   228: dup
    //   229: getfield FWm : F
    //   232: fconst_1
    //   233: fadd
    //   234: putfield FWm : F
    //   237: aload_0
    //   238: getfield Dne : F
    //   241: fconst_1
    //   242: fcmpl
    //   243: iflt -> 296
    //   246: aload_0
    //   247: iconst_0
    //   248: putfield Dne : Z
    //   251: aload_0
    //   252: getfield Dne : Lfzy;
    //   255: new Wbc
    //   258: dup
    //   259: iconst_2
    //   260: iload_1
    //   261: iload_2
    //   262: iload_3
    //   263: iload #4
    //   265: invokespecial <init> : (IIIII)V
    //   268: invokevirtual FWm : (LNER;)V
    //   271: aload_0
    //   272: iload_1
    //   273: iload_2
    //   274: iload_3
    //   275: iload #4
    //   277: invokevirtual Dne : (IIII)Z
    //   280: pop
    //   281: aload_0
    //   282: fconst_0
    //   283: putfield Dne : F
    //   286: aload_0
    //   287: fconst_0
    //   288: putfield FWm : F
    //   291: aload_0
    //   292: iconst_5
    //   293: putfield Qnq : I
    //   296: aload_0
    //   297: getfield Dne : Lnet/minecraft/client/Minecraft;
    //   300: getfield Dne : LVzZ;
    //   303: aload_0
    //   304: getfield Dne : Lnet/minecraft/client/Minecraft;
    //   307: getfield Dne : LMJs;
    //   310: getfield aFZ : I
    //   313: aload_0
    //   314: getfield Dne : I
    //   317: aload_0
    //   318: getfield FWm : I
    //   321: aload_0
    //   322: getfield bzF : I
    //   325: aload_0
    //   326: getfield Dne : F
    //   329: ldc 10.0
    //   331: fmul
    //   332: f2i
    //   333: iconst_1
    //   334: isub
    //   335: invokevirtual aFZ : (IIIII)V
    //   338: goto -> 350
    //   341: aload_0
    //   342: iload_1
    //   343: iload_2
    //   344: iload_3
    //   345: iload #4
    //   347: invokevirtual Dne : (IIII)V
    //   350: return
  }
  
  public NMq Dne(int paramInt1, int paramInt2, int paramInt3, int paramInt4, FiG paramFiG) {
    // Byte code:
    //   0: aload #5
    //   2: getfield FWm : LPdb;
    //   5: aload #5
    //   7: getfield Dne : LMOS;
    //   10: invokevirtual Dne : (LMOS;)S
    //   13: istore #6
    //   15: aload #5
    //   17: getfield FWm : LPdb;
    //   20: iload_2
    //   21: iload_3
    //   22: iload #4
    //   24: aload #5
    //   26: invokevirtual Dne : (IIILFiG;)LNMq;
    //   29: astore #7
    //   31: aload_0
    //   32: getfield Dne : Lfzy;
    //   35: new mZp
    //   38: dup
    //   39: iload_1
    //   40: iload_2
    //   41: iload_3
    //   42: iload #4
    //   44: aload #7
    //   46: iload #6
    //   48: invokespecial <init> : (IIIILNMq;S)V
    //   51: invokevirtual FWm : (LNER;)V
    //   54: aload #7
    //   56: areturn
  }
  
  public void Dne(FiG paramFiG, sMa paramsMa) {
    // Byte code:
    //   0: aload_0
    //   1: invokespecial bzF : ()V
    //   4: aload_0
    //   5: getfield Dne : Lfzy;
    //   8: new EHr
    //   11: dup
    //   12: aload_1
    //   13: getfield aFZ : I
    //   16: aload_2
    //   17: getfield aFZ : I
    //   20: iconst_1
    //   21: invokespecial <init> : (III)V
    //   24: invokevirtual FWm : (LNER;)V
    //   27: aload_1
    //   28: aload_2
    //   29: invokevirtual IjH : (LsMa;)V
    //   32: return
  }
  
  public boolean Dne(FiG paramFiG, Qnq paramQnq, NMq paramNMq, int paramInt1, int paramInt2, int paramInt3, int paramInt4, chN paramchN) {
    // Byte code:
    //   0: aload_0
    //   1: invokespecial bzF : ()V
    //   4: aload #8
    //   6: getfield Dne : D
    //   9: d2f
    //   10: iload #4
    //   12: i2f
    //   13: fsub
    //   14: fstore #9
    //   16: aload #8
    //   18: getfield FWm : D
    //   21: d2f
    //   22: iload #5
    //   24: i2f
    //   25: fsub
    //   26: fstore #10
    //   28: aload #8
    //   30: getfield bzF : D
    //   33: d2f
    //   34: iload #6
    //   36: i2f
    //   37: fsub
    //   38: fstore #11
    //   40: iconst_0
    //   41: istore #12
    //   43: aload_1
    //   44: invokevirtual aFZ : ()Z
    //   47: ifeq -> 57
    //   50: aload_1
    //   51: invokevirtual Dne : ()LNMq;
    //   54: ifnonnull -> 105
    //   57: aload_2
    //   58: iload #4
    //   60: iload #5
    //   62: iload #6
    //   64: invokevirtual Dne : (III)I
    //   67: istore #13
    //   69: iload #13
    //   71: ifle -> 105
    //   74: getstatic zKP.Dne : [LzKP;
    //   77: iload #13
    //   79: aaload
    //   80: aload_2
    //   81: iload #4
    //   83: iload #5
    //   85: iload #6
    //   87: aload_1
    //   88: iload #7
    //   90: fload #9
    //   92: fload #10
    //   94: fload #11
    //   96: invokevirtual Dne : (LQnq;IIILFiG;IFFF)Z
    //   99: ifeq -> 105
    //   102: iconst_1
    //   103: istore #12
    //   105: iload #12
    //   107: ifne -> 154
    //   110: aload_3
    //   111: ifnull -> 154
    //   114: aload_3
    //   115: invokevirtual Dne : ()LdEr;
    //   118: instanceof tkL
    //   121: ifeq -> 154
    //   124: aload_3
    //   125: invokevirtual Dne : ()LdEr;
    //   128: checkcast tkL
    //   131: astore #14
    //   133: aload #14
    //   135: aload_2
    //   136: iload #4
    //   138: iload #5
    //   140: iload #6
    //   142: iload #7
    //   144: aload_1
    //   145: aload_3
    //   146: invokevirtual Dne : (LQnq;IIIILFiG;LNMq;)Z
    //   149: ifne -> 154
    //   152: iconst_0
    //   153: ireturn
    //   154: aload_0
    //   155: getfield Dne : Lfzy;
    //   158: new DtJ
    //   161: dup
    //   162: iload #4
    //   164: iload #5
    //   166: iload #6
    //   168: iload #7
    //   170: aload_1
    //   171: getfield Dne : LMOS;
    //   174: invokevirtual Dne : ()LNMq;
    //   177: fload #9
    //   179: fload #10
    //   181: fload #11
    //   183: invokespecial <init> : (IIIILNMq;FFF)V
    //   186: invokevirtual FWm : (LNER;)V
    //   189: iload #12
    //   191: ifeq -> 196
    //   194: iconst_1
    //   195: ireturn
    //   196: aload_3
    //   197: ifnonnull -> 202
    //   200: iconst_0
    //   201: ireturn
    //   202: aload_0
    //   203: getfield Dne : LXHL;
    //   206: invokevirtual FWm : ()Z
    //   209: ifeq -> 261
    //   212: aload_3
    //   213: invokevirtual Qnq : ()I
    //   216: istore #13
    //   218: aload_3
    //   219: getfield Dne : I
    //   222: istore #14
    //   224: aload_3
    //   225: aload_1
    //   226: aload_2
    //   227: iload #4
    //   229: iload #5
    //   231: iload #6
    //   233: iload #7
    //   235: fload #9
    //   237: fload #10
    //   239: fload #11
    //   241: invokevirtual Dne : (LFiG;LQnq;IIIIFFF)Z
    //   244: istore #15
    //   246: aload_3
    //   247: iload #13
    //   249: invokevirtual Dne : (I)V
    //   252: aload_3
    //   253: iload #14
    //   255: putfield Dne : I
    //   258: iload #15
    //   260: ireturn
    //   261: aload_3
    //   262: aload_1
    //   263: aload_2
    //   264: iload #4
    //   266: iload #5
    //   268: iload #6
    //   270: iload #7
    //   272: fload #9
    //   274: fload #10
    //   276: fload #11
    //   278: invokevirtual Dne : (LFiG;LQnq;IIIIFFF)Z
    //   281: ireturn
  }
  
  public boolean Dne(FiG paramFiG, sMa paramsMa) {
    // Byte code:
    //   0: aload_0
    //   1: invokespecial bzF : ()V
    //   4: aload_0
    //   5: getfield Dne : Lfzy;
    //   8: new EHr
    //   11: dup
    //   12: aload_1
    //   13: getfield aFZ : I
    //   16: aload_2
    //   17: getfield aFZ : I
    //   20: iconst_0
    //   21: invokespecial <init> : (III)V
    //   24: invokevirtual FWm : (LNER;)V
    //   27: aload_1
    //   28: aload_2
    //   29: invokevirtual aFZ : (LsMa;)Z
    //   32: ireturn
  }
}


/* Location:              C:\Users\fract\Downloads\ERROR422.jar!\RJV.class
 * Java compiler version: 8 (52.0)
 * JD-Core Version:       1.1.3
 */