public class RlP extends cMv {
  private Class Dne;
  
  private float FWm;
  
  private float Dne;
  
  private kSJ Dne;
  
  private wdG Dne;
  
  public final pUe Dne;
  
  private sMa Dne;
  
  private float bzF;
  
  private KFZ Dne = (KFZ)new lKU(this);
  
  static kSJ Dne(RlP paramRlP) {
    return (kSJ)paramRlP.Dne;
  }
  
  public void bzF() {
    if (this.Dne.Dne((sMa)this.Dne) < 49.0D) {
      this.Dne.Dne().Dne(this.FWm);
    } else {
      this.Dne.Dne().Dne(this.Dne);
    } 
  }
  
  public void Dne() {
    this.Dne.Dne((wdG)this.Dne, this.Dne);
  }
  
  public RlP(kSJ paramkSJ, Class paramClass, float paramFloat1, float paramFloat2, float paramFloat3) {
    this.Dne = (KFZ)paramkSJ;
    this.Dne = (KFZ)paramClass;
    this.bzF = paramFloat1;
    this.Dne = paramFloat2;
    this.FWm = paramFloat3;
    this.Dne = paramkSJ.Dne();
    Dne(1);
  }
  
  public boolean FWm() {
    return !this.Dne.bzF();
  }
  
  public void FWm() {
    this.Dne = null;
  }
  
  public boolean Dne() {
    // Byte code:
    //   0: aload_0
    //   1: getfield Dne : Ljava/lang/Class;
    //   4: ldc FiG
    //   6: if_acmpne -> 66
    //   9: aload_0
    //   10: getfield Dne : LkSJ;
    //   13: instanceof BRM
    //   16: ifeq -> 34
    //   19: aload_0
    //   20: getfield Dne : LkSJ;
    //   23: checkcast BRM
    //   26: invokevirtual LVR : ()Z
    //   29: ifeq -> 34
    //   32: iconst_0
    //   33: ireturn
    //   34: aload_0
    //   35: aload_0
    //   36: getfield Dne : LkSJ;
    //   39: getfield Dne : LQnq;
    //   42: aload_0
    //   43: getfield Dne : LkSJ;
    //   46: aload_0
    //   47: getfield bzF : F
    //   50: f2d
    //   51: invokevirtual Dne : (LsMa;D)LFiG;
    //   54: putfield Dne : LsMa;
    //   57: aload_0
    //   58: getfield Dne : LsMa;
    //   61: ifnonnull -> 133
    //   64: iconst_0
    //   65: ireturn
    //   66: aload_0
    //   67: getfield Dne : LkSJ;
    //   70: getfield Dne : LQnq;
    //   73: aload_0
    //   74: getfield Dne : Ljava/lang/Class;
    //   77: aload_0
    //   78: getfield Dne : LkSJ;
    //   81: getfield Dne : LbSp;
    //   84: aload_0
    //   85: getfield bzF : F
    //   88: f2d
    //   89: ldc2_w 3.0
    //   92: aload_0
    //   93: getfield bzF : F
    //   96: f2d
    //   97: invokevirtual FWm : (DDD)LbSp;
    //   100: aload_0
    //   101: getfield Dne : LpUe;
    //   104: invokevirtual Dne : (Ljava/lang/Class;LbSp;LpUe;)Ljava/util/List;
    //   107: astore_1
    //   108: aload_1
    //   109: invokeinterface isEmpty : ()Z
    //   114: ifeq -> 119
    //   117: iconst_0
    //   118: ireturn
    //   119: aload_0
    //   120: aload_1
    //   121: iconst_0
    //   122: invokeinterface get : (I)Ljava/lang/Object;
    //   127: checkcast sMa
    //   130: putfield Dne : LsMa;
    //   133: aload_0
    //   134: getfield Dne : LkSJ;
    //   137: bipush #16
    //   139: bipush #7
    //   141: aload_0
    //   142: getfield Dne : LkSJ;
    //   145: getfield Dne : LQnq;
    //   148: invokevirtual Dne : ()LziS;
    //   151: aload_0
    //   152: getfield Dne : LsMa;
    //   155: getfield div : D
    //   158: aload_0
    //   159: getfield Dne : LsMa;
    //   162: getfield IjH : D
    //   165: aload_0
    //   166: getfield Dne : LsMa;
    //   169: getfield mrb : D
    //   172: invokevirtual Dne : (DDD)LchN;
    //   175: invokestatic FWm : (LkSJ;IILchN;)LchN;
    //   178: astore_1
    //   179: aload_1
    //   180: ifnonnull -> 185
    //   183: iconst_0
    //   184: ireturn
    //   185: aload_0
    //   186: getfield Dne : LsMa;
    //   189: aload_1
    //   190: getfield Dne : D
    //   193: aload_1
    //   194: getfield FWm : D
    //   197: aload_1
    //   198: getfield bzF : D
    //   201: invokevirtual Dne : (DDD)D
    //   204: aload_0
    //   205: getfield Dne : LsMa;
    //   208: aload_0
    //   209: getfield Dne : LkSJ;
    //   212: invokevirtual Dne : (LsMa;)D
    //   215: dcmpg
    //   216: ifge -> 221
    //   219: iconst_0
    //   220: ireturn
    //   221: aload_0
    //   222: aload_0
    //   223: getfield Dne : LKFZ;
    //   226: aload_1
    //   227: getfield Dne : D
    //   230: aload_1
    //   231: getfield FWm : D
    //   234: aload_1
    //   235: getfield bzF : D
    //   238: invokevirtual Dne : (DDD)LwdG;
    //   241: putfield Dne : LwdG;
    //   244: aload_0
    //   245: getfield Dne : LwdG;
    //   248: ifnonnull -> 255
    //   251: iconst_0
    //   252: goto -> 263
    //   255: aload_0
    //   256: getfield Dne : LwdG;
    //   259: aload_1
    //   260: invokevirtual Dne : (LchN;)Z
    //   263: ireturn
  }
}


/* Location:              C:\Users\fract\Downloads\ERROR422.jar!\RlP.class
 * Java compiler version: 8 (52.0)
 * JD-Core Version:       1.1.3
 */