import java.util.Random;

public class rPc extends OdI {
  public int bzF() {
    double d1 = bzF();
    double d2 = FWm();
    return ((bzF.Dne(d1, d2) & 0xFEFEFE) + 5115470) / 2;
  }
  
  public int Qnq() {
    double d1 = bzF();
    double d2 = FWm();
    return ((QFY.Dne(d1, d2) & 0xFEFEFE) + 5115470) / 2;
  }
  
  public gwq Dne(Random paramRandom) {
    return this.Dne;
  }
  
  static {
  
  }
  
  protected rPc(int paramInt) {
    // Byte code:
    //   0: aload_0
    //   1: iload_1
    //   2: invokespecial <init> : (I)V
    //   5: aload_0
    //   6: getfield Dne : LFnk;
    //   9: iconst_2
    //   10: putfield Qnq : I
    //   13: aload_0
    //   14: getfield Dne : LFnk;
    //   17: sipush #-999
    //   20: putfield aFZ : I
    //   23: aload_0
    //   24: getfield Dne : LFnk;
    //   27: iconst_1
    //   28: putfield DyG : I
    //   31: aload_0
    //   32: getfield Dne : LFnk;
    //   35: bipush #8
    //   37: putfield div : I
    //   40: aload_0
    //   41: getfield Dne : LFnk;
    //   44: bipush #10
    //   46: putfield IjH : I
    //   49: aload_0
    //   50: getfield Dne : LFnk;
    //   53: iconst_1
    //   54: putfield kGO : I
    //   57: aload_0
    //   58: getfield Dne : LFnk;
    //   61: iconst_4
    //   62: putfield bzF : I
    //   65: aload_0
    //   66: ldc 14745518
    //   68: putfield bzF : I
    //   71: aload_0
    //   72: getfield Dne : Ljava/util/List;
    //   75: new oIf
    //   78: dup
    //   79: ldc Tgj
    //   81: iconst_1
    //   82: iconst_1
    //   83: iconst_1
    //   84: invokespecial <init> : (Ljava/lang/Class;III)V
    //   87: invokeinterface add : (Ljava/lang/Object;)Z
    //   92: pop
    //   93: return
  }
}


/* Location:              C:\Users\fract\Downloads\ERROR422.jar!\rPc.class
 * Java compiler version: 8 (52.0)
 * JD-Core Version:       1.1.3
 */