public class RZd extends FrK implements yzC {
  static {
  
  }
  
  public void Dne(gnI paramgnI, int paramInt, String paramString, Object... paramVarArgs) {
    // Byte code:
    //   0: iconst_1
    //   1: istore #5
    //   3: aload_1
    //   4: instanceof FgE
    //   7: ifeq -> 32
    //   10: invokestatic Dne : ()LJwh;
    //   13: getfield Dne : [LRAN;
    //   16: iconst_0
    //   17: aaload
    //   18: invokevirtual Dne : ()LaSc;
    //   21: ldc 'commandBlockOutput'
    //   23: invokevirtual Dne : (Ljava/lang/String;)Z
    //   26: ifne -> 32
    //   29: iconst_0
    //   30: istore #5
    //   32: iload #5
    //   34: ifeq -> 173
    //   37: invokestatic Dne : ()LJwh;
    //   40: invokevirtual Dne : ()LdzN;
    //   43: getfield Dne : Ljava/util/List;
    //   46: invokeinterface iterator : ()Ljava/util/Iterator;
    //   51: astore #6
    //   53: aload #6
    //   55: invokeinterface hasNext : ()Z
    //   60: ifeq -> 173
    //   63: aload #6
    //   65: invokeinterface next : ()Ljava/lang/Object;
    //   70: checkcast PJQ
    //   73: astore #7
    //   75: aload #7
    //   77: aload_1
    //   78: if_acmpeq -> 170
    //   81: invokestatic Dne : ()LJwh;
    //   84: invokevirtual Dne : ()LdzN;
    //   87: aload #7
    //   89: getfield aFZ : Ljava/lang/String;
    //   92: invokevirtual FWm : (Ljava/lang/String;)Z
    //   95: ifeq -> 170
    //   98: aload #7
    //   100: new java/lang/StringBuilder
    //   103: dup
    //   104: invokespecial <init> : ()V
    //   107: ldc ''
    //   109: invokevirtual append : (Ljava/lang/String;)Ljava/lang/StringBuilder;
    //   112: getstatic Dne.div : LDne;
    //   115: invokevirtual append : (Ljava/lang/Object;)Ljava/lang/StringBuilder;
    //   118: ldc ''
    //   120: invokevirtual append : (Ljava/lang/String;)Ljava/lang/StringBuilder;
    //   123: getstatic Dne.EyB : LDne;
    //   126: invokevirtual append : (Ljava/lang/Object;)Ljava/lang/StringBuilder;
    //   129: ldc '['
    //   131: invokevirtual append : (Ljava/lang/String;)Ljava/lang/StringBuilder;
    //   134: aload_1
    //   135: invokeinterface a_ : ()Ljava/lang/String;
    //   140: invokevirtual append : (Ljava/lang/String;)Ljava/lang/StringBuilder;
    //   143: ldc ': '
    //   145: invokevirtual append : (Ljava/lang/String;)Ljava/lang/StringBuilder;
    //   148: aload #7
    //   150: aload_3
    //   151: aload #4
    //   153: invokevirtual Dne : (Ljava/lang/String;[Ljava/lang/Object;)Ljava/lang/String;
    //   156: invokevirtual append : (Ljava/lang/String;)Ljava/lang/StringBuilder;
    //   159: ldc ']'
    //   161: invokevirtual append : (Ljava/lang/String;)Ljava/lang/StringBuilder;
    //   164: invokevirtual toString : ()Ljava/lang/String;
    //   167: invokevirtual Dne : (Ljava/lang/String;)V
    //   170: goto -> 53
    //   173: aload_1
    //   174: invokestatic Dne : ()LJwh;
    //   177: if_acmpeq -> 237
    //   180: invokestatic Dne : ()LJwh;
    //   183: invokevirtual Dne : ()LdLs;
    //   186: new java/lang/StringBuilder
    //   189: dup
    //   190: invokespecial <init> : ()V
    //   193: ldc '['
    //   195: invokevirtual append : (Ljava/lang/String;)Ljava/lang/StringBuilder;
    //   198: aload_1
    //   199: invokeinterface a_ : ()Ljava/lang/String;
    //   204: invokevirtual append : (Ljava/lang/String;)Ljava/lang/StringBuilder;
    //   207: ldc ': '
    //   209: invokevirtual append : (Ljava/lang/String;)Ljava/lang/StringBuilder;
    //   212: invokestatic Dne : ()LJwh;
    //   215: aload_3
    //   216: aload #4
    //   218: invokevirtual Dne : (Ljava/lang/String;[Ljava/lang/Object;)Ljava/lang/String;
    //   221: invokevirtual append : (Ljava/lang/String;)Ljava/lang/StringBuilder;
    //   224: ldc ']'
    //   226: invokevirtual append : (Ljava/lang/String;)Ljava/lang/StringBuilder;
    //   229: invokevirtual toString : ()Ljava/lang/String;
    //   232: invokeinterface Dne : (Ljava/lang/String;)V
    //   237: iload_2
    //   238: iconst_1
    //   239: iand
    //   240: iconst_1
    //   241: if_icmpeq -> 259
    //   244: aload_1
    //   245: aload_1
    //   246: aload_3
    //   247: aload #4
    //   249: invokeinterface Dne : (Ljava/lang/String;[Ljava/lang/Object;)Ljava/lang/String;
    //   254: invokeinterface Dne : (Ljava/lang/String;)V
    //   259: return
  }
  
  public RZd() {
    Dne(new jXy());
    Dne(new Sxo());
    Dne(new rWl());
    Dne(new kSP());
    Dne(new UBB());
    Dne(new ePu());
    Dne(new twP());
    Dne(new iEq());
    Dne(new CEb());
    Dne(new Wuv());
    Dne(new dNY());
    Dne(new PpL());
    Dne(new LiD());
    Dne(new IlF());
    Dne(new giz());
    Dne(new UPH());
    Dne(new etD());
    Dne(new fTH());
    Dne(new IYH());
    Dne(new lpz());
    Dne(new duB());
    Dne(new alz());
    Dne(new FwH());
    if (Jwh.Dne().Qnq()) {
      Dne(new khp());
      Dne(new GjN());
      Dne(new HJG());
      Dne(new ZyT());
      Dne(new jNM());
      Dne(new auk());
      Dne(new tqk());
      Dne(new DgO());
      Dne(new lOW());
      Dne(new OCt());
      Dne(new jFR());
      Dne(new FxW());
      Dne(new lzJ());
      Dne(new STA());
    } else {
      Dne(new IWv());
    } 
    xZE.Dne(this);
  }
}


/* Location:              C:\Users\fract\Downloads\ERROR422.jar!\RZd.class
 * Java compiler version: 8 (52.0)
 * JD-Core Version:       1.1.3
 */