public class SET extends cMv {
  private yQQ Dne;
  
  private kSJ Dne;
  
  public boolean Dne() {
    // Byte code:
    //   0: aload_0
    //   1: getfield Dne : LkSJ;
    //   4: getfield Dne : LQnq;
    //   7: invokevirtual Dne : ()Z
    //   10: ifeq -> 15
    //   13: iconst_0
    //   14: ireturn
    //   15: aload_0
    //   16: getfield Dne : LkSJ;
    //   19: getfield Dne : LQnq;
    //   22: getfield Dne : LPrX;
    //   25: aload_0
    //   26: getfield Dne : LkSJ;
    //   29: getfield div : D
    //   32: invokestatic FWm : (D)I
    //   35: aload_0
    //   36: getfield Dne : LkSJ;
    //   39: getfield IjH : D
    //   42: invokestatic FWm : (D)I
    //   45: aload_0
    //   46: getfield Dne : LkSJ;
    //   49: getfield mrb : D
    //   52: invokestatic FWm : (D)I
    //   55: bipush #16
    //   57: invokevirtual Dne : (IIII)LuQr;
    //   60: astore_1
    //   61: aload_1
    //   62: ifnonnull -> 67
    //   65: iconst_0
    //   66: ireturn
    //   67: aload_0
    //   68: aload_1
    //   69: aload_0
    //   70: getfield Dne : LkSJ;
    //   73: getfield div : D
    //   76: invokestatic FWm : (D)I
    //   79: aload_0
    //   80: getfield Dne : LkSJ;
    //   83: getfield IjH : D
    //   86: invokestatic FWm : (D)I
    //   89: aload_0
    //   90: getfield Dne : LkSJ;
    //   93: getfield mrb : D
    //   96: invokestatic FWm : (D)I
    //   99: invokevirtual Dne : (III)LyQQ;
    //   102: putfield Dne : LyQQ;
    //   105: aload_0
    //   106: getfield Dne : LyQQ;
    //   109: ifnonnull -> 116
    //   112: iconst_0
    //   113: goto -> 166
    //   116: aload_0
    //   117: getfield Dne : LyQQ;
    //   120: aload_0
    //   121: getfield Dne : LkSJ;
    //   124: getfield div : D
    //   127: invokestatic FWm : (D)I
    //   130: aload_0
    //   131: getfield Dne : LkSJ;
    //   134: getfield IjH : D
    //   137: invokestatic FWm : (D)I
    //   140: aload_0
    //   141: getfield Dne : LkSJ;
    //   144: getfield mrb : D
    //   147: invokestatic FWm : (D)I
    //   150: invokevirtual FWm : (III)I
    //   153: i2d
    //   154: ldc2_w 2.25
    //   157: dcmpg
    //   158: ifge -> 165
    //   161: iconst_1
    //   162: goto -> 166
    //   165: iconst_0
    //   166: ireturn
  }
  
  public void bzF() {
    this.Dne.FWm();
  }
  
  public SET(kSJ paramkSJ) {
    this.Dne = paramkSJ;
  }
  
  public void FWm() {
    this.Dne.Dne().FWm(true);
    this.Dne.Dne().bzF(true);
    this.Dne = null;
  }
  
  public boolean FWm() {
    // Byte code:
    //   0: aload_0
    //   1: getfield Dne : LkSJ;
    //   4: getfield Dne : LQnq;
    //   7: invokevirtual Dne : ()Z
    //   10: ifeq -> 17
    //   13: iconst_0
    //   14: goto -> 62
    //   17: aload_0
    //   18: getfield Dne : LyQQ;
    //   21: getfield Dne : Z
    //   24: ifne -> 61
    //   27: aload_0
    //   28: getfield Dne : LyQQ;
    //   31: aload_0
    //   32: getfield Dne : LkSJ;
    //   35: getfield div : D
    //   38: invokestatic FWm : (D)I
    //   41: aload_0
    //   42: getfield Dne : LkSJ;
    //   45: getfield mrb : D
    //   48: invokestatic FWm : (D)I
    //   51: invokevirtual Dne : (II)Z
    //   54: ifeq -> 61
    //   57: iconst_1
    //   58: goto -> 62
    //   61: iconst_0
    //   62: ireturn
  }
  
  public void Dne() {
    this.Dne.Dne().FWm(false);
    this.Dne.Dne().bzF(false);
  }
}


/* Location:              C:\Users\fract\Downloads\ERROR422.jar!\SET.class
 * Java compiler version: 8 (52.0)
 * JD-Core Version:       1.1.3
 */