import java.util.Random;
import java.util.UUID;

public abstract class sMa {
  public int ooe;
  
  public String Dne;
  
  public double trS;
  
  private static int Dne = false;
  
  public boolean XHL;
  
  public double Qnq;
  
  public float XHL;
  
  public int kGO;
  
  public int div;
  
  public double Zpi;
  
  public sMa FWm;
  
  private UUID Dne;
  
  public double zGp;
  
  public double div;
  
  public float FfS;
  
  public boolean qLR;
  
  public double kGO;
  
  public boolean kGO;
  
  protected boolean udO;
  
  public float EyB;
  
  public float udO;
  
  private int FWm;
  
  public final bSp Dne;
  
  public boolean bzF;
  
  private double FWm;
  
  public sMa Dne;
  
  public int Zpi;
  
  public String FWm;
  
  public Qnq Dne;
  
  public float ceE;
  
  public int mrb;
  
  protected int ATE;
  
  public boolean zGp;
  
  public double mrb;
  
  public boolean Zpi;
  
  public boolean aFZ;
  
  public int qLR;
  
  public boolean trS;
  
  public boolean DyG;
  
  public float kGO;
  
  public int aFZ;
  
  protected boolean Vxn;
  
  protected boolean mrb;
  
  public float Zpi;
  
  public int DyG;
  
  protected Random Dne;
  
  private boolean Dne;
  
  protected int trS;
  
  public double ooe;
  
  protected luM Dne;
  
  public int udO;
  
  public int IjH;
  
  public float trS;
  
  public float ATE;
  
  public boolean IjH;
  
  public double XHL;
  
  public float mrb;
  
  public boolean ATE;
  
  public double udO;
  
  public bfY Dne;
  
  public float Vxn;
  
  public int XHL;
  
  public float qLR;
  
  public double DyG;
  
  private int bzF;
  
  public int zGp;
  
  public float ooe;
  
  protected boolean ooe;
  
  private double Dne;
  
  public double IjH;
  
  public boolean div;
  
  private boolean FWm;
  
  public float OdI;
  
  public boolean Qnq;
  
  public double aFZ;
  
  public boolean ceE() {
    return Dne(4);
  }
  
  public int zGp() {
    return 0;
  }
  
  public JiM Dne(int paramInt1, int paramInt2, float paramFloat) {
    return Dne(new NMq(paramInt1, paramInt2, 0), paramFloat);
  }
  
  public double Dne(double paramDouble1, double paramDouble2, double paramDouble3) {
    double d1 = this.div - paramDouble1;
    double d2 = this.IjH - paramDouble2;
    double d3 = this.mrb - paramDouble3;
    return d1 * d1 + d2 * d2 + d3 * d3;
  }
  
  public boolean Zpi() {
    return this.udO;
  }
  
  public void FWm(float paramFloat) {}
  
  protected void ceE() {
    if (!this.ooe) {
      Dne(zBn.bzF, 4);
      aFZ(15);
    } 
  }
  
  public float Dne() {
    return this.trS / 2.0F;
  }
  
  public String Dne() {
    String str = Klb.Dne(this);
    if (str == null)
      str = "generic"; 
    return KGL.Dne("entity." + str + ".name");
  }
  
  public double Dne(sMa paramsMa) {
    double d1 = this.div - paramsMa.div;
    double d2 = this.IjH - paramsMa.IjH;
    double d3 = this.mrb - paramsMa.mrb;
    return d1 * d1 + d2 * d2 + d3 * d3;
  }
  
  public void Dne() {
    Vxn();
  }
  
  public boolean ATE() {
    return Dne(3);
  }
  
  public void DyG(int paramInt) {
    // Byte code:
    //   0: aload_0
    //   1: getfield Dne : LluM;
    //   4: iconst_1
    //   5: iload_1
    //   6: i2s
    //   7: invokestatic valueOf : (S)Ljava/lang/Short;
    //   10: invokevirtual FWm : (ILjava/lang/Object;)V
    //   13: return
  }
  
  public boolean udO() {
    return (this.Zpi == 0.0F);
  }
  
  public boolean zGp() {
    // Byte code:
    //   0: aload_0
    //   1: getfield Dne : LQnq;
    //   4: aload_0
    //   5: getfield Dne : LbSp;
    //   8: dconst_0
    //   9: ldc2_w -0.4000000059604645
    //   12: dconst_0
    //   13: invokevirtual FWm : (DDD)LbSp;
    //   16: ldc2_w 0.001
    //   19: ldc2_w 0.001
    //   22: ldc2_w 0.001
    //   25: invokevirtual aFZ : (DDD)LbSp;
    //   28: getstatic KFd.div : LKFd;
    //   31: aload_0
    //   32: invokevirtual Dne : (LbSp;LKFd;LsMa;)Z
    //   35: ifeq -> 373
    //   38: aload_0
    //   39: getfield udO : Z
    //   42: ifne -> 355
    //   45: aload_0
    //   46: getfield Dne : Z
    //   49: ifne -> 355
    //   52: aload_0
    //   53: getfield XHL : D
    //   56: aload_0
    //   57: getfield XHL : D
    //   60: dmul
    //   61: ldc2_w 0.20000000298023224
    //   64: dmul
    //   65: aload_0
    //   66: getfield Zpi : D
    //   69: aload_0
    //   70: getfield Zpi : D
    //   73: dmul
    //   74: dadd
    //   75: aload_0
    //   76: getfield kGO : D
    //   79: aload_0
    //   80: getfield kGO : D
    //   83: dmul
    //   84: ldc2_w 0.20000000298023224
    //   87: dmul
    //   88: dadd
    //   89: invokestatic Dne : (D)F
    //   92: ldc 0.2
    //   94: fmul
    //   95: fstore_1
    //   96: fload_1
    //   97: fconst_1
    //   98: fcmpl
    //   99: ifle -> 104
    //   102: fconst_1
    //   103: fstore_1
    //   104: aload_0
    //   105: ldc 'liquid.splash'
    //   107: fload_1
    //   108: fconst_1
    //   109: aload_0
    //   110: getfield Dne : Ljava/util/Random;
    //   113: invokevirtual nextFloat : ()F
    //   116: aload_0
    //   117: getfield Dne : Ljava/util/Random;
    //   120: invokevirtual nextFloat : ()F
    //   123: fsub
    //   124: ldc 0.4
    //   126: fmul
    //   127: fadd
    //   128: invokevirtual Dne : (Ljava/lang/String;FF)V
    //   131: aload_0
    //   132: getfield Dne : LbSp;
    //   135: getfield FWm : D
    //   138: invokestatic FWm : (D)I
    //   141: i2f
    //   142: fstore_2
    //   143: iconst_0
    //   144: istore_3
    //   145: iload_3
    //   146: i2f
    //   147: fconst_1
    //   148: aload_0
    //   149: getfield ooe : F
    //   152: ldc 20.0
    //   154: fmul
    //   155: fadd
    //   156: fcmpg
    //   157: ifge -> 255
    //   160: aload_0
    //   161: getfield Dne : Ljava/util/Random;
    //   164: invokevirtual nextFloat : ()F
    //   167: fconst_2
    //   168: fmul
    //   169: fconst_1
    //   170: fsub
    //   171: aload_0
    //   172: getfield ooe : F
    //   175: fmul
    //   176: fstore #4
    //   178: aload_0
    //   179: getfield Dne : Ljava/util/Random;
    //   182: invokevirtual nextFloat : ()F
    //   185: fconst_2
    //   186: fmul
    //   187: fconst_1
    //   188: fsub
    //   189: aload_0
    //   190: getfield ooe : F
    //   193: fmul
    //   194: fstore #5
    //   196: aload_0
    //   197: getfield Dne : LQnq;
    //   200: ldc 'bubble'
    //   202: aload_0
    //   203: getfield div : D
    //   206: fload #4
    //   208: f2d
    //   209: dadd
    //   210: fload_2
    //   211: fconst_1
    //   212: fadd
    //   213: f2d
    //   214: aload_0
    //   215: getfield mrb : D
    //   218: fload #5
    //   220: f2d
    //   221: dadd
    //   222: aload_0
    //   223: getfield XHL : D
    //   226: aload_0
    //   227: getfield Zpi : D
    //   230: aload_0
    //   231: getfield Dne : Ljava/util/Random;
    //   234: invokevirtual nextFloat : ()F
    //   237: ldc 0.2
    //   239: fmul
    //   240: f2d
    //   241: dsub
    //   242: aload_0
    //   243: getfield kGO : D
    //   246: invokevirtual Dne : (Ljava/lang/String;DDDDDD)V
    //   249: iinc #3, 1
    //   252: goto -> 145
    //   255: iconst_0
    //   256: istore_3
    //   257: iload_3
    //   258: i2f
    //   259: fconst_1
    //   260: aload_0
    //   261: getfield ooe : F
    //   264: ldc 20.0
    //   266: fmul
    //   267: fadd
    //   268: fcmpg
    //   269: ifge -> 355
    //   272: aload_0
    //   273: getfield Dne : Ljava/util/Random;
    //   276: invokevirtual nextFloat : ()F
    //   279: fconst_2
    //   280: fmul
    //   281: fconst_1
    //   282: fsub
    //   283: aload_0
    //   284: getfield ooe : F
    //   287: fmul
    //   288: fstore #4
    //   290: aload_0
    //   291: getfield Dne : Ljava/util/Random;
    //   294: invokevirtual nextFloat : ()F
    //   297: fconst_2
    //   298: fmul
    //   299: fconst_1
    //   300: fsub
    //   301: aload_0
    //   302: getfield ooe : F
    //   305: fmul
    //   306: fstore #5
    //   308: aload_0
    //   309: getfield Dne : LQnq;
    //   312: ldc 'splash'
    //   314: aload_0
    //   315: getfield div : D
    //   318: fload #4
    //   320: f2d
    //   321: dadd
    //   322: fload_2
    //   323: fconst_1
    //   324: fadd
    //   325: f2d
    //   326: aload_0
    //   327: getfield mrb : D
    //   330: fload #5
    //   332: f2d
    //   333: dadd
    //   334: aload_0
    //   335: getfield XHL : D
    //   338: aload_0
    //   339: getfield Zpi : D
    //   342: aload_0
    //   343: getfield kGO : D
    //   346: invokevirtual Dne : (Ljava/lang/String;DDDDDD)V
    //   349: iinc #3, 1
    //   352: goto -> 257
    //   355: aload_0
    //   356: fconst_0
    //   357: putfield ceE : F
    //   360: aload_0
    //   361: iconst_1
    //   362: putfield udO : Z
    //   365: aload_0
    //   366: iconst_0
    //   367: putfield bzF : I
    //   370: goto -> 378
    //   373: aload_0
    //   374: iconst_0
    //   375: putfield udO : Z
    //   378: aload_0
    //   379: getfield udO : Z
    //   382: ireturn
  }
  
  public boolean a_(FiG paramFiG) {
    return false;
  }
  
  public float c_() {
    return 0.0F;
  }
  
  public boolean Dne(WkD paramWkD) {
    String str = Qnq();
    if (this.Zpi == 0.0F && str != null) {
      paramWkD.Dne("id", str);
      bzF(paramWkD);
      return true;
    } 
    return false;
  }
  
  protected mbZ Dne(float... paramVarArgs) {
    mbZ mbZ = new mbZ();
    float[] arrayOfFloat = paramVarArgs;
    int i = paramVarArgs.length;
    for (byte b = 0; b < i; b++) {
      float f = arrayOfFloat[b];
      mbZ.Dne(new nOv((String)null, f));
    } 
    return mbZ;
  }
  
  public void Dne(double paramDouble1, double paramDouble2, double paramDouble3, float paramFloat1, float paramFloat2) {
    this.aFZ = this.div = paramDouble1;
    this.zGp = this.IjH = paramDouble2;
    this.DyG = this.mrb = paramDouble3;
    this.Zpi = this.mrb = paramFloat1;
    this.kGO = this.XHL = paramFloat2;
    this.EyB = 0.0F;
    double d = (this.Zpi - paramFloat1);
    if (d < -180.0D)
      this.Zpi += 360.0F; 
    if (d >= 180.0D)
      this.Zpi -= 360.0F; 
    bzF(this.div, this.IjH, this.mrb);
    FWm(paramFloat1, paramFloat2);
  }
  
  public int div() {
    // Byte code:
    //   0: aload_0
    //   1: getfield Dne : LluM;
    //   4: iconst_1
    //   5: invokevirtual Dne : (I)S
    //   8: ireturn
  }
  
  public void bzF(boolean paramBoolean) {
    Dne(1, paramBoolean);
  }
  
  public void Qnq(sMa paramsMa) {
    if (paramsMa.Dne != this && paramsMa.FWm != this) {
      double d1 = paramsMa.div - this.div;
      double d2 = paramsMa.mrb - this.mrb;
      double d3 = geR.Dne(d1, d2);
      if (d3 >= 0.009999999776482582D) {
        d3 = geR.Dne(d3);
        d1 /= d3;
        d2 /= d3;
        double d = 1.0D / d3;
        if (d > 1.0D)
          d = 1.0D; 
        d1 *= d;
        d2 *= d;
        d1 *= 0.05000000074505806D;
        d2 *= 0.05000000074505806D;
        d1 *= (1.0F - this.OdI);
        d2 *= (1.0F - this.OdI);
        Qnq(-d1, 0.0D, -d2);
        paramsMa.Qnq(d1, 0.0D, d2);
      } 
    } 
  }
  
  public sMa[] Dne() {
    return null;
  }
  
  public JiM Dne(int paramInt1, int paramInt2) {
    return Dne(paramInt1, paramInt2, 0.0F);
  }
  
  public boolean Dne(zBn paramzBn, int paramInt) {
    if (EyB())
      return false; 
    oIf();
    return false;
  }
  
  public String bzF() {
    return null;
  }
  
  public int DyG() {
    return 900;
  }
  
  public void a_(FiG paramFiG) {}
  
  public void bzF(float paramFloat1, float paramFloat2) {
    int i = this.XHL;
    float f = this.mrb;
    this.mrb = (float)(this.mrb + paramFloat1 * 0.15D);
    this.XHL = (float)(this.XHL - paramFloat2 * 0.15D);
    if (this.XHL < -90.0F)
      this.XHL = -90.0F; 
    if (this.XHL > 90.0F)
      this.XHL = 90.0F; 
    this.kGO += this.XHL - i;
    this.Zpi += this.mrb - f;
  }
  
  public bSp Dne() {
    return null;
  }
  
  public void FWm(sMa paramsMa, int paramInt) {}
  
  public int Dne(float paramFloat) {
    // Byte code:
    //   0: aload_0
    //   1: getfield div : D
    //   4: invokestatic FWm : (D)I
    //   7: istore_2
    //   8: aload_0
    //   9: getfield mrb : D
    //   12: invokestatic FWm : (D)I
    //   15: istore_3
    //   16: aload_0
    //   17: getfield Dne : LQnq;
    //   20: iload_2
    //   21: iconst_0
    //   22: iload_3
    //   23: invokevirtual bzF : (III)Z
    //   26: ifeq -> 81
    //   29: aload_0
    //   30: getfield Dne : LbSp;
    //   33: getfield aFZ : D
    //   36: aload_0
    //   37: getfield Dne : LbSp;
    //   40: getfield FWm : D
    //   43: dsub
    //   44: ldc2_w 0.66
    //   47: dmul
    //   48: dstore #4
    //   50: aload_0
    //   51: getfield IjH : D
    //   54: aload_0
    //   55: getfield udO : F
    //   58: f2d
    //   59: dsub
    //   60: dload #4
    //   62: dadd
    //   63: invokestatic FWm : (D)I
    //   66: istore #6
    //   68: aload_0
    //   69: getfield Dne : LQnq;
    //   72: iload_2
    //   73: iload #6
    //   75: iload_3
    //   76: iconst_0
    //   77: invokevirtual Dne : (IIII)I
    //   80: ireturn
    //   81: iconst_0
    //   82: ireturn
  }
  
  public boolean aFZ() {
    return Dne(1);
  }
  
  public void g_() {
    this.Zpi = true;
  }
  
  public void Dne(FUH paramFUH) {}
  
  public double FWm(double paramDouble1, double paramDouble2, double paramDouble3) {
    double d1 = this.div - paramDouble1;
    double d2 = this.IjH - paramDouble2;
    double d3 = this.mrb - paramDouble3;
    return geR.Dne(d1 * d1 + d2 * d2 + d3 * d3);
  }
  
  public void gnI() {}
  
  public void bzF(sMa paramsMa) {
    this.Dne = 0.0D;
    this.FWm = 0.0D;
    if (paramsMa == null) {
      if (this.FWm != null) {
        FWm(this.FWm.div, this.FWm.Dne.FWm + this.FWm.trS, this.FWm.mrb, this.mrb, this.XHL);
        this.FWm.Dne = null;
      } 
      this.FWm = null;
    } else {
      if (this.FWm != null)
        this.FWm.Dne = null; 
      this.FWm = paramsMa;
      paramsMa.Dne = this;
    } 
  }
  
  public void FWm(float paramFloat1, float paramFloat2, float paramFloat3) {
    float f = paramFloat1 * paramFloat1 + paramFloat2 * paramFloat2;
    if (f >= 1.0E-4F) {
      f = geR.bzF(f);
      if (f < 1.0F)
        f = 1.0F; 
      f = paramFloat3 / f;
      paramFloat1 *= f;
      paramFloat2 *= f;
      float f1 = geR.Dne(this.mrb * 3.1415927F / 180.0F);
      float f2 = geR.FWm(this.mrb * 3.1415927F / 180.0F);
      this.XHL += (paramFloat1 * f2 - paramFloat2 * f1);
      this.kGO += (paramFloat2 * f2 + paramFloat1 * f1);
    } 
  }
  
  public void FWm(double paramDouble1, double paramDouble2, double paramDouble3, float paramFloat1, float paramFloat2) {
    this.aFZ = this.div = paramDouble1;
    (this.div = paramDouble1).udO = this;
    this.ooe = this.zGp = this.IjH = paramDouble2 + this.udO;
    this.DyG = this.mrb = paramDouble3;
    (this.mrb = paramDouble3).trS = this;
    this.mrb = paramFloat1;
    this.XHL = paramFloat2;
    bzF(this.div, this.IjH, this.mrb);
  }
  
  public void zGp(sMa paramsMa) {
    FWm(paramsMa.div, paramsMa.IjH, paramsMa.mrb, paramsMa.mrb, paramsMa.XHL);
  }
  
  public void aFZ(double paramDouble1, double paramDouble2, double paramDouble3) {
    this.XHL = paramDouble1;
    this.Zpi = paramDouble2;
    this.kGO = paramDouble3;
  }
  
  public void mrb() {}
  
  protected void Dne(double paramDouble, boolean paramBoolean) {
    if (paramBoolean) {
      if (this.ceE > 0.0F) {
        Dne(this.ceE);
        this.ceE = 0.0F;
      } 
    } else if (paramDouble < 0.0D) {
      this.ceE = (float)(this.ceE - paramDouble);
    } 
  }
  
  public boolean FfS() {
    return false;
  }
  
  public void Dne(String paramString, float paramFloat1, float paramFloat2) {
    // Byte code:
    //   0: aload_0
    //   1: getfield Dne : LQnq;
    //   4: aload_0
    //   5: aload_1
    //   6: fload_2
    //   7: fload_3
    //   8: invokevirtual Dne : (LsMa;Ljava/lang/String;FF)V
    //   11: return
  }
  
  public String aFZ() {
    return Dne();
  }
  
  public boolean FWm(sMa paramsMa) {
    return false;
  }
  
  public final boolean mrb() {
    return this.ooe;
  }
  
  public void Dne(xIh paramxIh) {
    zGp(5);
    this.bzF++;
    if (this.bzF == 0)
      aFZ(8); 
  }
  
  protected mbZ Dne(double... paramVarArgs) {
    mbZ mbZ = new mbZ();
    double[] arrayOfDouble = paramVarArgs;
    int i = paramVarArgs.length;
    for (byte b = 0; b < i; b++) {
      double d = arrayOfDouble[b];
      mbZ.Dne(new kJU((String)null, d));
    } 
    return mbZ;
  }
  
  public sMa(Qnq paramQnq) {
    // Byte code:
    //   0: aload_0
    //   1: invokespecial <init> : ()V
    //   4: aload_0
    //   5: getstatic sMa.Dne : I
    //   8: dup
    //   9: iconst_1
    //   10: iadd
    //   11: putstatic sMa.Dne : I
    //   14: putfield aFZ : I
    //   17: aload_0
    //   18: dconst_1
    //   19: putfield Qnq : D
    //   22: aload_0
    //   23: iconst_0
    //   24: putfield bzF : Z
    //   27: aload_0
    //   28: dconst_0
    //   29: dconst_0
    //   30: dconst_0
    //   31: dconst_0
    //   32: dconst_0
    //   33: dconst_0
    //   34: invokestatic Dne : (DDDDDD)LbSp;
    //   37: putfield Dne : LbSp;
    //   40: aload_0
    //   41: iconst_0
    //   42: putfield aFZ : Z
    //   45: aload_0
    //   46: iconst_0
    //   47: putfield div : Z
    //   50: aload_0
    //   51: iconst_0
    //   52: putfield IjH : Z
    //   55: aload_0
    //   56: iconst_1
    //   57: putfield XHL : Z
    //   60: aload_0
    //   61: iconst_0
    //   62: putfield Zpi : Z
    //   65: aload_0
    //   66: fconst_0
    //   67: putfield udO : F
    //   70: aload_0
    //   71: ldc_w 0.6
    //   74: putfield ooe : F
    //   77: aload_0
    //   78: ldc_w 1.8
    //   81: putfield trS : F
    //   84: aload_0
    //   85: fconst_0
    //   86: putfield qLR : F
    //   89: aload_0
    //   90: fconst_0
    //   91: putfield ATE : F
    //   94: aload_0
    //   95: fconst_0
    //   96: putfield Vxn : F
    //   99: aload_0
    //   100: fconst_0
    //   101: putfield ceE : F
    //   104: aload_0
    //   105: iconst_1
    //   106: putfield FWm : I
    //   109: aload_0
    //   110: fconst_0
    //   111: putfield EyB : F
    //   114: aload_0
    //   115: fconst_0
    //   116: putfield FfS : F
    //   119: aload_0
    //   120: iconst_0
    //   121: putfield kGO : Z
    //   124: aload_0
    //   125: fconst_0
    //   126: putfield OdI : F
    //   129: aload_0
    //   130: new java/util/Random
    //   133: dup
    //   134: invokespecial <init> : ()V
    //   137: putfield Dne : Ljava/util/Random;
    //   140: aload_0
    //   141: iconst_0
    //   142: putfield zGp : I
    //   145: aload_0
    //   146: iconst_1
    //   147: putfield DyG : I
    //   150: aload_0
    //   151: iconst_0
    //   152: putfield bzF : I
    //   155: aload_0
    //   156: iconst_0
    //   157: putfield udO : Z
    //   160: aload_0
    //   161: iconst_0
    //   162: putfield div : I
    //   165: aload_0
    //   166: iconst_1
    //   167: putfield Dne : Z
    //   170: aload_0
    //   171: iconst_0
    //   172: putfield ooe : Z
    //   175: aload_0
    //   176: new luM
    //   179: dup
    //   180: invokespecial <init> : ()V
    //   183: putfield Dne : LluM;
    //   186: aload_0
    //   187: iconst_0
    //   188: putfield trS : Z
    //   191: aload_0
    //   192: iconst_0
    //   193: putfield ATE : I
    //   196: aload_0
    //   197: iconst_0
    //   198: putfield FWm : Z
    //   201: aload_0
    //   202: invokestatic randomUUID : ()Ljava/util/UUID;
    //   205: putfield Dne : Ljava/util/UUID;
    //   208: aload_0
    //   209: getstatic bfY.FWm : LbfY;
    //   212: putfield Dne : LbfY;
    //   215: aload_0
    //   216: aload_1
    //   217: putfield Dne : LQnq;
    //   220: aload_0
    //   221: dconst_0
    //   222: dconst_0
    //   223: dconst_0
    //   224: invokevirtual bzF : (DDD)V
    //   227: aload_1
    //   228: ifnull -> 242
    //   231: aload_0
    //   232: aload_1
    //   233: getfield Dne : LJik;
    //   236: getfield Dne : I
    //   239: putfield qLR : I
    //   242: aload_0
    //   243: getfield Dne : LluM;
    //   246: iconst_0
    //   247: iconst_0
    //   248: invokestatic valueOf : (B)Ljava/lang/Byte;
    //   251: invokevirtual Dne : (ILjava/lang/Object;)V
    //   254: aload_0
    //   255: getfield Dne : LluM;
    //   258: iconst_1
    //   259: sipush #300
    //   262: invokestatic valueOf : (S)Ljava/lang/Short;
    //   265: invokevirtual Dne : (ILjava/lang/Object;)V
    //   268: aload_0
    //   269: invokevirtual FWm : ()V
    //   272: return
  }
  
  public void Dne(Noo paramNoo) {
    paramNoo.Dne("Entity Type", new LWx(this));
    paramNoo.Dne("Entity ID", Integer.valueOf(this.aFZ));
    paramNoo.Dne("Entity Name", new jdt(this));
    paramNoo.Dne("Entity's Exact location", String.format("%.2f, %.2f, %.2f", new Object[] { Double.valueOf(this.div), Double.valueOf(this.IjH), Double.valueOf(this.mrb) }));
    paramNoo.Dne("Entity's Block location", Noo.Dne(geR.FWm(this.div), geR.FWm(this.IjH), geR.FWm(this.mrb)));
    paramNoo.Dne("Entity's Momentum", String.format("%.2f, %.2f, %.2f", new Object[] { Double.valueOf(this.XHL), Double.valueOf(this.Zpi), Double.valueOf(this.kGO) }));
  }
  
  public NMq[] Dne() {
    return null;
  }
  
  public void bzF(double paramDouble1, double paramDouble2, double paramDouble3) {
    // Byte code:
    //   0: aload_0
    //   1: dload_1
    //   2: putfield div : D
    //   5: aload_0
    //   6: dload_3
    //   7: putfield IjH : D
    //   10: aload_0
    //   11: dload #5
    //   13: putfield mrb : D
    //   16: aload_0
    //   17: getfield ooe : F
    //   20: fconst_2
    //   21: fdiv
    //   22: fstore #7
    //   24: aload_0
    //   25: getfield trS : F
    //   28: fstore #8
    //   30: aload_0
    //   31: getfield Dne : LbSp;
    //   34: dload_1
    //   35: fload #7
    //   37: f2d
    //   38: dsub
    //   39: dload_3
    //   40: aload_0
    //   41: getfield udO : F
    //   44: f2d
    //   45: dsub
    //   46: aload_0
    //   47: getfield EyB : F
    //   50: f2d
    //   51: dadd
    //   52: dload #5
    //   54: fload #7
    //   56: f2d
    //   57: dsub
    //   58: dload_1
    //   59: fload #7
    //   61: f2d
    //   62: dadd
    //   63: dload_3
    //   64: aload_0
    //   65: getfield udO : F
    //   68: f2d
    //   69: dsub
    //   70: aload_0
    //   71: getfield EyB : F
    //   74: f2d
    //   75: dadd
    //   76: fload #8
    //   78: f2d
    //   79: dadd
    //   80: dload #5
    //   82: fload #7
    //   84: f2d
    //   85: dadd
    //   86: invokevirtual FWm : (DDDDDD)LbSp;
    //   89: pop
    //   90: return
  }
  
  public void Dne(byte paramByte) {}
  
  public boolean FWm(double paramDouble1, double paramDouble2, double paramDouble3) {
    // Byte code:
    //   0: aload_0
    //   1: getfield Dne : LbSp;
    //   4: dload_1
    //   5: dload_3
    //   6: dload #5
    //   8: invokevirtual bzF : (DDD)LbSp;
    //   11: astore #7
    //   13: aload_0
    //   14: getfield Dne : LQnq;
    //   17: aload_0
    //   18: aload #7
    //   20: invokevirtual Dne : (LsMa;LbSp;)Ljava/util/List;
    //   23: astore #8
    //   25: aload #8
    //   27: invokeinterface isEmpty : ()Z
    //   32: ifne -> 39
    //   35: iconst_0
    //   36: goto -> 56
    //   39: aload_0
    //   40: getfield Dne : LQnq;
    //   43: aload #7
    //   45: invokevirtual bzF : (LbSp;)Z
    //   48: ifne -> 55
    //   51: iconst_1
    //   52: goto -> 56
    //   55: iconst_0
    //   56: ireturn
  }
  
  public void EyB() {
    this.bzF = 0;
  }
  
  public JiM Dne(NMq paramNMq, float paramFloat) {
    // Byte code:
    //   0: new JiM
    //   3: dup
    //   4: aload_0
    //   5: getfield Dne : LQnq;
    //   8: aload_0
    //   9: getfield div : D
    //   12: aload_0
    //   13: getfield IjH : D
    //   16: fload_2
    //   17: f2d
    //   18: dadd
    //   19: aload_0
    //   20: getfield mrb : D
    //   23: aload_1
    //   24: invokespecial <init> : (LQnq;DDDLNMq;)V
    //   27: astore_3
    //   28: aload_3
    //   29: bipush #10
    //   31: putfield FWm : I
    //   34: aload_0
    //   35: getfield Dne : LQnq;
    //   38: aload_3
    //   39: invokevirtual FWm : (LsMa;)Z
    //   42: pop
    //   43: aload_3
    //   44: areturn
  }
  
  public void Vxn() {
    // Byte code:
    //   0: aload_0
    //   1: getfield Dne : LQnq;
    //   4: getfield Dne : LBkx;
    //   7: ldc_w 'entityBaseTick'
    //   10: invokevirtual Dne : (Ljava/lang/String;)V
    //   13: aload_0
    //   14: getfield FWm : LsMa;
    //   17: ifnull -> 35
    //   20: aload_0
    //   21: getfield FWm : LsMa;
    //   24: getfield Zpi : Z
    //   27: ifeq -> 35
    //   30: aload_0
    //   31: aconst_null
    //   32: putfield FWm : LsMa;
    //   35: aload_0
    //   36: aload_0
    //   37: getfield ATE : F
    //   40: putfield qLR : F
    //   43: aload_0
    //   44: aload_0
    //   45: getfield div : D
    //   48: putfield aFZ : D
    //   51: aload_0
    //   52: aload_0
    //   53: getfield IjH : D
    //   56: putfield zGp : D
    //   59: aload_0
    //   60: aload_0
    //   61: getfield mrb : D
    //   64: putfield DyG : D
    //   67: aload_0
    //   68: aload_0
    //   69: getfield XHL : F
    //   72: putfield kGO : F
    //   75: aload_0
    //   76: aload_0
    //   77: getfield mrb : F
    //   80: putfield Zpi : F
    //   83: aload_0
    //   84: getfield Dne : LQnq;
    //   87: getfield aFZ : Z
    //   90: ifne -> 271
    //   93: aload_0
    //   94: getfield Dne : LQnq;
    //   97: instanceof RAN
    //   100: ifeq -> 271
    //   103: aload_0
    //   104: getfield Dne : LQnq;
    //   107: getfield Dne : LBkx;
    //   110: ldc_w 'portal'
    //   113: invokevirtual Dne : (Ljava/lang/String;)V
    //   116: aload_0
    //   117: getfield Dne : LQnq;
    //   120: checkcast RAN
    //   123: invokevirtual Dne : ()LJwh;
    //   126: astore_2
    //   127: aload_0
    //   128: invokevirtual zGp : ()I
    //   131: istore_1
    //   132: aload_0
    //   133: getfield Vxn : Z
    //   136: ifeq -> 215
    //   139: aload_2
    //   140: invokevirtual div : ()Z
    //   143: ifeq -> 244
    //   146: aload_0
    //   147: getfield FWm : LsMa;
    //   150: ifnonnull -> 207
    //   153: aload_0
    //   154: dup
    //   155: getfield trS : I
    //   158: dup_x1
    //   159: iconst_1
    //   160: iadd
    //   161: putfield trS : I
    //   164: iload_1
    //   165: if_icmplt -> 207
    //   168: aload_0
    //   169: iload_1
    //   170: putfield trS : I
    //   173: aload_0
    //   174: aload_0
    //   175: invokevirtual DyG : ()I
    //   178: putfield ooe : I
    //   181: aload_0
    //   182: getfield Dne : LQnq;
    //   185: getfield Dne : LJik;
    //   188: getfield Dne : I
    //   191: iconst_m1
    //   192: if_icmpne -> 200
    //   195: iconst_0
    //   196: istore_3
    //   197: goto -> 202
    //   200: iconst_m1
    //   201: istore_3
    //   202: aload_0
    //   203: iload_3
    //   204: invokevirtual Qnq : (I)V
    //   207: aload_0
    //   208: iconst_0
    //   209: putfield Vxn : Z
    //   212: goto -> 244
    //   215: aload_0
    //   216: getfield trS : I
    //   219: ifle -> 232
    //   222: aload_0
    //   223: dup
    //   224: getfield trS : I
    //   227: iconst_4
    //   228: isub
    //   229: putfield trS : I
    //   232: aload_0
    //   233: getfield trS : I
    //   236: ifge -> 244
    //   239: aload_0
    //   240: iconst_0
    //   241: putfield trS : I
    //   244: aload_0
    //   245: getfield ooe : I
    //   248: ifle -> 261
    //   251: aload_0
    //   252: dup
    //   253: getfield ooe : I
    //   256: iconst_1
    //   257: isub
    //   258: putfield ooe : I
    //   261: aload_0
    //   262: getfield Dne : LQnq;
    //   265: getfield Dne : LBkx;
    //   268: invokevirtual FWm : ()V
    //   271: aload_0
    //   272: invokevirtual ATE : ()Z
    //   275: ifeq -> 461
    //   278: aload_0
    //   279: invokevirtual Zpi : ()Z
    //   282: ifne -> 461
    //   285: aload_0
    //   286: getfield div : D
    //   289: invokestatic FWm : (D)I
    //   292: istore_2
    //   293: aload_0
    //   294: getfield IjH : D
    //   297: ldc2_w 0.20000000298023224
    //   300: dsub
    //   301: aload_0
    //   302: getfield udO : F
    //   305: f2d
    //   306: dsub
    //   307: invokestatic FWm : (D)I
    //   310: istore_1
    //   311: aload_0
    //   312: getfield mrb : D
    //   315: invokestatic FWm : (D)I
    //   318: istore_3
    //   319: aload_0
    //   320: getfield Dne : LQnq;
    //   323: iload_2
    //   324: iload_1
    //   325: iload_3
    //   326: invokevirtual Dne : (III)I
    //   329: istore #4
    //   331: iload #4
    //   333: ifle -> 461
    //   336: aload_0
    //   337: getfield Dne : LQnq;
    //   340: new java/lang/StringBuilder
    //   343: dup
    //   344: invokespecial <init> : ()V
    //   347: ldc_w 'tilecrack_'
    //   350: invokevirtual append : (Ljava/lang/String;)Ljava/lang/StringBuilder;
    //   353: iload #4
    //   355: invokevirtual append : (I)Ljava/lang/StringBuilder;
    //   358: ldc_w '_'
    //   361: invokevirtual append : (Ljava/lang/String;)Ljava/lang/StringBuilder;
    //   364: aload_0
    //   365: getfield Dne : LQnq;
    //   368: iload_2
    //   369: iload_1
    //   370: iload_3
    //   371: invokevirtual bzF : (III)I
    //   374: invokevirtual append : (I)Ljava/lang/StringBuilder;
    //   377: invokevirtual toString : ()Ljava/lang/String;
    //   380: aload_0
    //   381: getfield div : D
    //   384: aload_0
    //   385: getfield Dne : Ljava/util/Random;
    //   388: invokevirtual nextFloat : ()F
    //   391: f2d
    //   392: ldc2_w 0.5
    //   395: dsub
    //   396: aload_0
    //   397: getfield ooe : F
    //   400: f2d
    //   401: dmul
    //   402: dadd
    //   403: aload_0
    //   404: getfield Dne : LbSp;
    //   407: getfield FWm : D
    //   410: ldc2_w 0.1
    //   413: dadd
    //   414: aload_0
    //   415: getfield mrb : D
    //   418: aload_0
    //   419: getfield Dne : Ljava/util/Random;
    //   422: invokevirtual nextFloat : ()F
    //   425: f2d
    //   426: ldc2_w 0.5
    //   429: dsub
    //   430: aload_0
    //   431: getfield ooe : F
    //   434: f2d
    //   435: dmul
    //   436: dadd
    //   437: aload_0
    //   438: getfield XHL : D
    //   441: dneg
    //   442: ldc2_w 4.0
    //   445: dmul
    //   446: ldc2_w 1.5
    //   449: aload_0
    //   450: getfield kGO : D
    //   453: dneg
    //   454: ldc2_w 4.0
    //   457: dmul
    //   458: invokevirtual Dne : (Ljava/lang/String;DDDDDD)V
    //   461: aload_0
    //   462: invokevirtual zGp : ()Z
    //   465: pop
    //   466: aload_0
    //   467: getfield Dne : LQnq;
    //   470: getfield aFZ : Z
    //   473: ifeq -> 484
    //   476: aload_0
    //   477: iconst_0
    //   478: putfield bzF : I
    //   481: goto -> 552
    //   484: aload_0
    //   485: getfield bzF : I
    //   488: ifle -> 552
    //   491: aload_0
    //   492: getfield ooe : Z
    //   495: ifeq -> 523
    //   498: aload_0
    //   499: dup
    //   500: getfield bzF : I
    //   503: iconst_4
    //   504: isub
    //   505: putfield bzF : I
    //   508: aload_0
    //   509: getfield bzF : I
    //   512: ifge -> 552
    //   515: aload_0
    //   516: iconst_0
    //   517: putfield bzF : I
    //   520: goto -> 552
    //   523: aload_0
    //   524: getfield bzF : I
    //   527: bipush #20
    //   529: irem
    //   530: ifne -> 542
    //   533: aload_0
    //   534: getstatic zBn.FWm : LzBn;
    //   537: iconst_1
    //   538: invokevirtual Dne : (LzBn;I)Z
    //   541: pop
    //   542: aload_0
    //   543: dup
    //   544: getfield bzF : I
    //   547: iconst_1
    //   548: isub
    //   549: putfield bzF : I
    //   552: aload_0
    //   553: invokevirtual DyG : ()Z
    //   556: ifeq -> 575
    //   559: aload_0
    //   560: invokevirtual ceE : ()V
    //   563: aload_0
    //   564: dup
    //   565: getfield ceE : F
    //   568: ldc_w 0.5
    //   571: fmul
    //   572: putfield ceE : F
    //   575: aload_0
    //   576: getfield IjH : D
    //   579: ldc2_w -64.0
    //   582: dcmpg
    //   583: ifge -> 586
    //   586: aload_0
    //   587: getfield Dne : LQnq;
    //   590: getfield aFZ : Z
    //   593: ifne -> 630
    //   596: aload_0
    //   597: iconst_0
    //   598: aload_0
    //   599: getfield bzF : I
    //   602: ifle -> 609
    //   605: iconst_1
    //   606: goto -> 610
    //   609: iconst_0
    //   610: invokevirtual Dne : (IZ)V
    //   613: aload_0
    //   614: iconst_2
    //   615: aload_0
    //   616: getfield FWm : LsMa;
    //   619: ifnull -> 626
    //   622: iconst_1
    //   623: goto -> 627
    //   626: iconst_0
    //   627: invokevirtual Dne : (IZ)V
    //   630: aload_0
    //   631: iconst_0
    //   632: putfield Dne : Z
    //   635: aload_0
    //   636: getfield Dne : LQnq;
    //   639: getfield Dne : LBkx;
    //   642: invokevirtual FWm : ()V
    //   645: return
  }
  
  protected abstract void Dne(WkD paramWkD);
  
  public void aFZ(int paramInt) {
    int i = paramInt * 20;
    i = oAi.Dne(this, i);
    if (this.bzF < i)
      this.bzF = i; 
  }
  
  public boolean Dne(chN paramchN) {
    double d1 = this.div - paramchN.Dne;
    double d2 = this.IjH - paramchN.FWm;
    double d3 = this.mrb - paramchN.bzF;
    double d4 = d1 * d1 + d2 * d2 + d3 * d3;
    return Dne(d4);
  }
  
  public String toString() {
    // Byte code:
    //   0: ldc_w '%s['%s'/%d, l='%s', x=%.2f, y=%.2f, z=%.2f]'
    //   3: bipush #7
    //   5: anewarray java/lang/Object
    //   8: dup
    //   9: iconst_0
    //   10: aload_0
    //   11: invokevirtual getClass : ()Ljava/lang/Class;
    //   14: invokevirtual getSimpleName : ()Ljava/lang/String;
    //   17: aastore
    //   18: dup
    //   19: iconst_1
    //   20: aload_0
    //   21: invokevirtual Dne : ()Ljava/lang/String;
    //   24: aastore
    //   25: dup
    //   26: iconst_2
    //   27: aload_0
    //   28: getfield aFZ : I
    //   31: invokestatic valueOf : (I)Ljava/lang/Integer;
    //   34: aastore
    //   35: dup
    //   36: iconst_3
    //   37: aload_0
    //   38: getfield Dne : LQnq;
    //   41: ifnonnull -> 50
    //   44: ldc_w '~NULL~'
    //   47: goto -> 60
    //   50: aload_0
    //   51: getfield Dne : LQnq;
    //   54: invokevirtual Dne : ()LxoY;
    //   57: invokevirtual Dne : ()Ljava/lang/String;
    //   60: aastore
    //   61: dup
    //   62: iconst_4
    //   63: aload_0
    //   64: getfield div : D
    //   67: invokestatic valueOf : (D)Ljava/lang/Double;
    //   70: aastore
    //   71: dup
    //   72: iconst_5
    //   73: aload_0
    //   74: getfield IjH : D
    //   77: invokestatic valueOf : (D)Ljava/lang/Double;
    //   80: aastore
    //   81: dup
    //   82: bipush #6
    //   84: aload_0
    //   85: getfield mrb : D
    //   88: invokestatic valueOf : (D)Ljava/lang/Double;
    //   91: aastore
    //   92: invokestatic format : (Ljava/lang/String;[Ljava/lang/Object;)Ljava/lang/String;
    //   95: areturn
  }
  
  public int hashCode() {
    return this.aFZ;
  }
  
  public void a_(int paramInt, NMq paramNMq) {}
  
  protected void ATE() {
    // Byte code:
    //   0: aload_0
    //   1: getfield Dne : LQnq;
    //   4: ifnull -> 88
    //   7: aload_0
    //   8: getfield IjH : D
    //   11: dconst_0
    //   12: dcmpl
    //   13: ifle -> 68
    //   16: aload_0
    //   17: aload_0
    //   18: getfield div : D
    //   21: aload_0
    //   22: getfield IjH : D
    //   25: aload_0
    //   26: getfield mrb : D
    //   29: invokevirtual bzF : (DDD)V
    //   32: aload_0
    //   33: getfield Dne : LQnq;
    //   36: aload_0
    //   37: aload_0
    //   38: getfield Dne : LbSp;
    //   41: invokevirtual Dne : (LsMa;LbSp;)Ljava/util/List;
    //   44: invokeinterface isEmpty : ()Z
    //   49: ifeq -> 55
    //   52: goto -> 68
    //   55: aload_0
    //   56: dup
    //   57: getfield IjH : D
    //   60: dconst_1
    //   61: dadd
    //   62: putfield IjH : D
    //   65: goto -> 7
    //   68: aload_0
    //   69: aload_0
    //   70: aload_0
    //   71: dconst_0
    //   72: dup2_x1
    //   73: putfield kGO : D
    //   76: dup2_x1
    //   77: putfield Zpi : D
    //   80: putfield XHL : D
    //   83: aload_0
    //   84: fconst_0
    //   85: putfield XHL : F
    //   88: return
  }
  
  public boolean XHL() {
    // Byte code:
    //   0: aload_0
    //   1: getfield udO : Z
    //   4: ifne -> 75
    //   7: aload_0
    //   8: getfield Dne : LQnq;
    //   11: aload_0
    //   12: getfield div : D
    //   15: invokestatic FWm : (D)I
    //   18: aload_0
    //   19: getfield IjH : D
    //   22: invokestatic FWm : (D)I
    //   25: aload_0
    //   26: getfield mrb : D
    //   29: invokestatic FWm : (D)I
    //   32: invokevirtual udO : (III)Z
    //   35: ifne -> 75
    //   38: aload_0
    //   39: getfield Dne : LQnq;
    //   42: aload_0
    //   43: getfield div : D
    //   46: invokestatic FWm : (D)I
    //   49: aload_0
    //   50: getfield IjH : D
    //   53: aload_0
    //   54: getfield trS : F
    //   57: f2d
    //   58: dadd
    //   59: invokestatic FWm : (D)I
    //   62: aload_0
    //   63: getfield mrb : D
    //   66: invokestatic FWm : (D)I
    //   69: invokevirtual udO : (III)Z
    //   72: ifeq -> 79
    //   75: iconst_1
    //   76: goto -> 80
    //   79: iconst_0
    //   80: ireturn
  }
  
  public void aFZ(sMa paramsMa) {
    // Byte code:
    //   0: aload_0
    //   1: getfield div : D
    //   4: dstore_2
    //   5: aload_0
    //   6: getfield IjH : D
    //   9: dstore #4
    //   11: aload_0
    //   12: getfield mrb : D
    //   15: dstore #6
    //   17: aload_1
    //   18: ifnull -> 47
    //   21: aload_1
    //   22: getfield div : D
    //   25: dstore_2
    //   26: aload_1
    //   27: getfield Dne : LbSp;
    //   30: getfield FWm : D
    //   33: aload_1
    //   34: getfield trS : F
    //   37: f2d
    //   38: dadd
    //   39: dstore #4
    //   41: aload_1
    //   42: getfield mrb : D
    //   45: dstore #6
    //   47: ldc2_w -1.5
    //   50: dstore #8
    //   52: dload #8
    //   54: ldc2_w 2.0
    //   57: dcmpg
    //   58: ifge -> 280
    //   61: ldc2_w -1.5
    //   64: dstore #10
    //   66: dload #10
    //   68: ldc2_w 2.0
    //   71: dcmpg
    //   72: ifge -> 271
    //   75: dload #8
    //   77: dconst_0
    //   78: dcmpl
    //   79: ifne -> 89
    //   82: dload #10
    //   84: dconst_0
    //   85: dcmpl
    //   86: ifeq -> 262
    //   89: aload_0
    //   90: getfield div : D
    //   93: dload #8
    //   95: dadd
    //   96: d2i
    //   97: istore #12
    //   99: aload_0
    //   100: getfield mrb : D
    //   103: dload #10
    //   105: dadd
    //   106: d2i
    //   107: istore #13
    //   109: aload_0
    //   110: getfield Dne : LbSp;
    //   113: dload #8
    //   115: dconst_1
    //   116: dload #10
    //   118: invokevirtual bzF : (DDD)LbSp;
    //   121: astore #14
    //   123: aload_0
    //   124: getfield Dne : LQnq;
    //   127: aload #14
    //   129: invokevirtual Dne : (LbSp;)Ljava/util/List;
    //   132: invokeinterface isEmpty : ()Z
    //   137: ifeq -> 262
    //   140: aload_0
    //   141: getfield Dne : LQnq;
    //   144: iload #12
    //   146: aload_0
    //   147: getfield IjH : D
    //   150: d2i
    //   151: iload #13
    //   153: invokevirtual IjH : (III)Z
    //   156: ifeq -> 192
    //   159: aload_0
    //   160: aload_0
    //   161: getfield div : D
    //   164: dload #8
    //   166: dadd
    //   167: aload_0
    //   168: getfield IjH : D
    //   171: dconst_1
    //   172: dadd
    //   173: aload_0
    //   174: getfield mrb : D
    //   177: dload #10
    //   179: dadd
    //   180: aload_0
    //   181: getfield mrb : F
    //   184: aload_0
    //   185: getfield XHL : F
    //   188: invokevirtual FWm : (DDDFF)V
    //   191: return
    //   192: aload_0
    //   193: getfield Dne : LQnq;
    //   196: iload #12
    //   198: aload_0
    //   199: getfield IjH : D
    //   202: d2i
    //   203: iconst_1
    //   204: isub
    //   205: iload #13
    //   207: invokevirtual IjH : (III)Z
    //   210: ifne -> 237
    //   213: aload_0
    //   214: getfield Dne : LQnq;
    //   217: iload #12
    //   219: aload_0
    //   220: getfield IjH : D
    //   223: d2i
    //   224: iconst_1
    //   225: isub
    //   226: iload #13
    //   228: invokevirtual Dne : (III)LKFd;
    //   231: getstatic KFd.div : LKFd;
    //   234: if_acmpne -> 262
    //   237: aload_0
    //   238: getfield div : D
    //   241: dload #8
    //   243: dadd
    //   244: dstore_2
    //   245: aload_0
    //   246: getfield IjH : D
    //   249: dconst_1
    //   250: dadd
    //   251: dstore #4
    //   253: aload_0
    //   254: getfield mrb : D
    //   257: dload #10
    //   259: dadd
    //   260: dstore #6
    //   262: dload #10
    //   264: dconst_1
    //   265: dadd
    //   266: dstore #10
    //   268: goto -> 66
    //   271: dload #8
    //   273: dconst_1
    //   274: dadd
    //   275: dstore #8
    //   277: goto -> 52
    //   280: aload_0
    //   281: dload_2
    //   282: dload #4
    //   284: dload #6
    //   286: aload_0
    //   287: getfield mrb : F
    //   290: aload_0
    //   291: getfield XHL : F
    //   294: invokevirtual FWm : (DDDFF)V
    //   297: return
  }
  
  public boolean Dne() {
    return false;
  }
  
  public void Qnq(boolean paramBoolean) {
    Dne(5, paramBoolean);
  }
  
  public void Qnq(double paramDouble1, double paramDouble2, double paramDouble3) {
    this.XHL += paramDouble1;
    this.Zpi += paramDouble2;
    this.kGO += paramDouble3;
    this.ATE = true;
  }
  
  public void tgc() {
    this.mrb = true;
    this.ceE = 0.0F;
  }
  
  public boolean Dne(sMa paramsMa) {
    return (this == paramsMa);
  }
  
  public boolean kGO() {
    return false;
  }
  
  protected final String Qnq() {
    return Klb.Dne(this);
  }
  
  protected void FWm(float paramFloat1, float paramFloat2) {
    this.mrb = paramFloat1 % 360.0F;
    this.XHL = paramFloat2 % 360.0F;
  }
  
  public boolean Dne(KFd paramKFd) {
    // Byte code:
    //   0: aload_0
    //   1: getfield IjH : D
    //   4: aload_0
    //   5: invokevirtual c_ : ()F
    //   8: f2d
    //   9: dadd
    //   10: dstore_2
    //   11: aload_0
    //   12: getfield div : D
    //   15: invokestatic FWm : (D)I
    //   18: istore #4
    //   20: dload_2
    //   21: invokestatic FWm : (D)I
    //   24: i2f
    //   25: invokestatic Dne : (F)I
    //   28: istore #5
    //   30: aload_0
    //   31: getfield mrb : D
    //   34: invokestatic FWm : (D)I
    //   37: istore #6
    //   39: aload_0
    //   40: getfield Dne : LQnq;
    //   43: iload #4
    //   45: iload #5
    //   47: iload #6
    //   49: invokevirtual Dne : (III)I
    //   52: istore #7
    //   54: iload #7
    //   56: ifeq -> 118
    //   59: getstatic zKP.Dne : [LzKP;
    //   62: iload #7
    //   64: aaload
    //   65: getfield Dne : LKFd;
    //   68: aload_1
    //   69: if_acmpne -> 118
    //   72: aload_0
    //   73: getfield Dne : LQnq;
    //   76: iload #4
    //   78: iload #5
    //   80: iload #6
    //   82: invokevirtual bzF : (III)I
    //   85: invokestatic Dne : (I)F
    //   88: ldc_w 0.11111111
    //   91: fsub
    //   92: fstore #8
    //   94: iload #5
    //   96: iconst_1
    //   97: iadd
    //   98: i2f
    //   99: fload #8
    //   101: fsub
    //   102: fstore #9
    //   104: dload_2
    //   105: fload #9
    //   107: f2d
    //   108: dcmpg
    //   109: ifge -> 116
    //   112: iconst_1
    //   113: goto -> 117
    //   116: iconst_0
    //   117: ireturn
    //   118: iconst_0
    //   119: ireturn
  }
  
  protected void oIf() {
    this.IjH = true;
  }
  
  protected abstract void FWm(WkD paramWkD);
  
  protected boolean Dne(int paramInt) {
    // Byte code:
    //   0: aload_0
    //   1: getfield Dne : LluM;
    //   4: iconst_0
    //   5: invokevirtual Dne : (I)B
    //   8: iconst_1
    //   9: iload_1
    //   10: ishl
    //   11: iand
    //   12: ifeq -> 19
    //   15: iconst_1
    //   16: goto -> 20
    //   19: iconst_0
    //   20: ireturn
  }
  
  protected boolean FWm() {
    return true;
  }
  
  protected void Dne(int paramInt1, int paramInt2, int paramInt3, int paramInt4) {
    // Byte code:
    //   0: getstatic zKP.Dne : [LzKP;
    //   3: iload #4
    //   5: aaload
    //   6: getfield kGO : LPsW;
    //   9: astore #5
    //   11: aload_0
    //   12: getfield Dne : LQnq;
    //   15: iload_1
    //   16: iload_2
    //   17: iconst_1
    //   18: iadd
    //   19: iload_3
    //   20: invokevirtual Dne : (III)I
    //   23: getstatic zKP.EwP : LzKP;
    //   26: getfield FWm : I
    //   29: if_icmpne -> 66
    //   32: getstatic zKP.EwP : LzKP;
    //   35: getfield kGO : LPsW;
    //   38: astore #5
    //   40: aload_0
    //   41: aload #5
    //   43: invokevirtual bzF : ()Ljava/lang/String;
    //   46: aload #5
    //   48: invokevirtual Dne : ()F
    //   51: ldc_w 0.15
    //   54: fmul
    //   55: aload #5
    //   57: invokevirtual FWm : ()F
    //   60: invokevirtual Dne : (Ljava/lang/String;FF)V
    //   63: goto -> 104
    //   66: getstatic zKP.Dne : [LzKP;
    //   69: iload #4
    //   71: aaload
    //   72: getfield Dne : LKFd;
    //   75: invokevirtual Qnq : ()Z
    //   78: ifne -> 104
    //   81: aload_0
    //   82: aload #5
    //   84: invokevirtual bzF : ()Ljava/lang/String;
    //   87: aload #5
    //   89: invokevirtual Dne : ()F
    //   92: ldc_w 0.15
    //   95: fmul
    //   96: aload #5
    //   98: invokevirtual FWm : ()F
    //   101: invokevirtual Dne : (Ljava/lang/String;FF)V
    //   104: return
  }
  
  public double Qnq() {
    return this.udO;
  }
  
  public boolean equals(Object paramObject) {
    return (paramObject instanceof sMa) ? ((((sMa)paramObject).aFZ == this.aFZ)) : false;
  }
  
  public float Dne(float paramFloat) {
    // Byte code:
    //   0: aload_0
    //   1: getfield div : D
    //   4: invokestatic FWm : (D)I
    //   7: istore_2
    //   8: aload_0
    //   9: getfield mrb : D
    //   12: invokestatic FWm : (D)I
    //   15: istore_3
    //   16: aload_0
    //   17: getfield Dne : LQnq;
    //   20: iload_2
    //   21: iconst_0
    //   22: iload_3
    //   23: invokevirtual bzF : (III)Z
    //   26: ifeq -> 80
    //   29: aload_0
    //   30: getfield Dne : LbSp;
    //   33: getfield aFZ : D
    //   36: aload_0
    //   37: getfield Dne : LbSp;
    //   40: getfield FWm : D
    //   43: dsub
    //   44: ldc2_w 0.66
    //   47: dmul
    //   48: dstore #4
    //   50: aload_0
    //   51: getfield IjH : D
    //   54: aload_0
    //   55: getfield udO : F
    //   58: f2d
    //   59: dsub
    //   60: dload #4
    //   62: dadd
    //   63: invokestatic FWm : (D)I
    //   66: istore #6
    //   68: aload_0
    //   69: getfield Dne : LQnq;
    //   72: iload_2
    //   73: iload #6
    //   75: iload_3
    //   76: invokevirtual Dne : (III)F
    //   79: freturn
    //   80: fconst_0
    //   81: freturn
  }
  
  protected boolean Dne(double paramDouble1, double paramDouble2, double paramDouble3) {
    // Byte code:
    //   0: dload_1
    //   1: invokestatic FWm : (D)I
    //   4: istore #7
    //   6: dload_3
    //   7: invokestatic FWm : (D)I
    //   10: istore #8
    //   12: dload #5
    //   14: invokestatic FWm : (D)I
    //   17: istore #9
    //   19: dload_1
    //   20: iload #7
    //   22: i2d
    //   23: dsub
    //   24: dstore #10
    //   26: dload_3
    //   27: iload #8
    //   29: i2d
    //   30: dsub
    //   31: dstore #12
    //   33: dload #5
    //   35: iload #9
    //   37: i2d
    //   38: dsub
    //   39: dstore #14
    //   41: aload_0
    //   42: getfield Dne : LQnq;
    //   45: aload_0
    //   46: getfield Dne : LbSp;
    //   49: invokevirtual Dne : (LbSp;)Ljava/util/List;
    //   52: astore #16
    //   54: aload #16
    //   56: invokeinterface isEmpty : ()Z
    //   61: ifeq -> 82
    //   64: aload_0
    //   65: getfield Dne : LQnq;
    //   68: iload #7
    //   70: iload #8
    //   72: iload #9
    //   74: invokevirtual div : (III)Z
    //   77: ifne -> 82
    //   80: iconst_0
    //   81: ireturn
    //   82: aload_0
    //   83: getfield Dne : LQnq;
    //   86: iload #7
    //   88: iconst_1
    //   89: isub
    //   90: iload #8
    //   92: iload #9
    //   94: invokevirtual div : (III)Z
    //   97: ifne -> 104
    //   100: iconst_1
    //   101: goto -> 105
    //   104: iconst_0
    //   105: istore #17
    //   107: aload_0
    //   108: getfield Dne : LQnq;
    //   111: iload #7
    //   113: iconst_1
    //   114: iadd
    //   115: iload #8
    //   117: iload #9
    //   119: invokevirtual div : (III)Z
    //   122: ifne -> 129
    //   125: iconst_1
    //   126: goto -> 130
    //   129: iconst_0
    //   130: istore #18
    //   132: aload_0
    //   133: getfield Dne : LQnq;
    //   136: iload #7
    //   138: iload #8
    //   140: iconst_1
    //   141: isub
    //   142: iload #9
    //   144: invokevirtual div : (III)Z
    //   147: ifne -> 154
    //   150: iconst_1
    //   151: goto -> 155
    //   154: iconst_0
    //   155: istore #19
    //   157: aload_0
    //   158: getfield Dne : LQnq;
    //   161: iload #7
    //   163: iload #8
    //   165: iconst_1
    //   166: iadd
    //   167: iload #9
    //   169: invokevirtual div : (III)Z
    //   172: ifne -> 179
    //   175: iconst_1
    //   176: goto -> 180
    //   179: iconst_0
    //   180: istore #20
    //   182: aload_0
    //   183: getfield Dne : LQnq;
    //   186: iload #7
    //   188: iload #8
    //   190: iload #9
    //   192: iconst_1
    //   193: isub
    //   194: invokevirtual div : (III)Z
    //   197: ifne -> 204
    //   200: iconst_1
    //   201: goto -> 205
    //   204: iconst_0
    //   205: istore #21
    //   207: aload_0
    //   208: getfield Dne : LQnq;
    //   211: iload #7
    //   213: iload #8
    //   215: iload #9
    //   217: iconst_1
    //   218: iadd
    //   219: invokevirtual div : (III)Z
    //   222: ifne -> 229
    //   225: iconst_1
    //   226: goto -> 230
    //   229: iconst_0
    //   230: istore #22
    //   232: iconst_3
    //   233: istore #23
    //   235: ldc2_w 9999.0
    //   238: dstore #24
    //   240: iload #17
    //   242: ifeq -> 260
    //   245: dload #10
    //   247: dload #24
    //   249: dcmpg
    //   250: ifge -> 260
    //   253: dload #10
    //   255: dstore #24
    //   257: iconst_0
    //   258: istore #23
    //   260: iload #18
    //   262: ifeq -> 284
    //   265: dconst_1
    //   266: dload #10
    //   268: dsub
    //   269: dload #24
    //   271: dcmpg
    //   272: ifge -> 284
    //   275: dconst_1
    //   276: dload #10
    //   278: dsub
    //   279: dstore #24
    //   281: iconst_1
    //   282: istore #23
    //   284: iload #20
    //   286: ifeq -> 308
    //   289: dconst_1
    //   290: dload #12
    //   292: dsub
    //   293: dload #24
    //   295: dcmpg
    //   296: ifge -> 308
    //   299: dconst_1
    //   300: dload #12
    //   302: dsub
    //   303: dstore #24
    //   305: iconst_3
    //   306: istore #23
    //   308: iload #21
    //   310: ifeq -> 328
    //   313: dload #14
    //   315: dload #24
    //   317: dcmpg
    //   318: ifge -> 328
    //   321: dload #14
    //   323: dstore #24
    //   325: iconst_4
    //   326: istore #23
    //   328: iload #22
    //   330: ifeq -> 352
    //   333: dconst_1
    //   334: dload #14
    //   336: dsub
    //   337: dload #24
    //   339: dcmpg
    //   340: ifge -> 352
    //   343: dconst_1
    //   344: dload #14
    //   346: dsub
    //   347: dstore #24
    //   349: iconst_5
    //   350: istore #23
    //   352: aload_0
    //   353: getfield Dne : Ljava/util/Random;
    //   356: invokevirtual nextFloat : ()F
    //   359: ldc 0.2
    //   361: fmul
    //   362: ldc_w 0.1
    //   365: fadd
    //   366: fstore #26
    //   368: iload #23
    //   370: ifne -> 381
    //   373: aload_0
    //   374: fload #26
    //   376: fneg
    //   377: f2d
    //   378: putfield XHL : D
    //   381: iload #23
    //   383: iconst_1
    //   384: if_icmpne -> 394
    //   387: aload_0
    //   388: fload #26
    //   390: f2d
    //   391: putfield XHL : D
    //   394: iload #23
    //   396: iconst_2
    //   397: if_icmpne -> 408
    //   400: aload_0
    //   401: fload #26
    //   403: fneg
    //   404: f2d
    //   405: putfield Zpi : D
    //   408: iload #23
    //   410: iconst_3
    //   411: if_icmpne -> 421
    //   414: aload_0
    //   415: fload #26
    //   417: f2d
    //   418: putfield Zpi : D
    //   421: iload #23
    //   423: iconst_4
    //   424: if_icmpne -> 435
    //   427: aload_0
    //   428: fload #26
    //   430: fneg
    //   431: f2d
    //   432: putfield kGO : D
    //   435: iload #23
    //   437: iconst_5
    //   438: if_icmpne -> 448
    //   441: aload_0
    //   442: fload #26
    //   444: f2d
    //   445: putfield kGO : D
    //   448: iconst_1
    //   449: ireturn
  }
  
  public float Dne(sMa paramsMa) {
    float f1 = (float)(this.div - paramsMa.div);
    float f2 = (float)(this.IjH - paramsMa.IjH);
    float f3 = (float)(this.mrb - paramsMa.mrb);
    return geR.bzF(f1 * f1 + f2 * f2 + f3 * f3);
  }
  
  protected void FfS() {
    g_();
  }
  
  public void Dne(double paramDouble1, double paramDouble2, double paramDouble3) {
    // Byte code:
    //   0: aload_0
    //   1: getfield kGO : Z
    //   4: ifeq -> 91
    //   7: aload_0
    //   8: getfield Dne : LbSp;
    //   11: dload_1
    //   12: dload_3
    //   13: dload #5
    //   15: invokevirtual Qnq : (DDD)LbSp;
    //   18: pop
    //   19: aload_0
    //   20: aload_0
    //   21: getfield Dne : LbSp;
    //   24: getfield Dne : D
    //   27: aload_0
    //   28: getfield Dne : LbSp;
    //   31: getfield Qnq : D
    //   34: dadd
    //   35: ldc2_w 2.0
    //   38: ddiv
    //   39: putfield div : D
    //   42: aload_0
    //   43: aload_0
    //   44: getfield Dne : LbSp;
    //   47: getfield FWm : D
    //   50: aload_0
    //   51: getfield udO : F
    //   54: f2d
    //   55: dadd
    //   56: aload_0
    //   57: getfield EyB : F
    //   60: f2d
    //   61: dsub
    //   62: putfield IjH : D
    //   65: aload_0
    //   66: aload_0
    //   67: getfield Dne : LbSp;
    //   70: getfield bzF : D
    //   73: aload_0
    //   74: getfield Dne : LbSp;
    //   77: getfield zGp : D
    //   80: dadd
    //   81: ldc2_w 2.0
    //   84: ddiv
    //   85: putfield mrb : D
    //   88: goto -> 2046
    //   91: aload_0
    //   92: getfield Dne : LQnq;
    //   95: getfield Dne : LBkx;
    //   98: ldc_w 'move'
    //   101: invokevirtual Dne : (Ljava/lang/String;)V
    //   104: aload_0
    //   105: dup
    //   106: getfield EyB : F
    //   109: ldc 0.4
    //   111: fmul
    //   112: putfield EyB : F
    //   115: aload_0
    //   116: getfield div : D
    //   119: dstore #7
    //   121: aload_0
    //   122: getfield IjH : D
    //   125: dstore #9
    //   127: aload_0
    //   128: getfield mrb : D
    //   131: dstore #11
    //   133: aload_0
    //   134: getfield mrb : Z
    //   137: ifeq -> 180
    //   140: aload_0
    //   141: iconst_0
    //   142: putfield mrb : Z
    //   145: dload_1
    //   146: ldc2_w 0.25
    //   149: dmul
    //   150: dstore_1
    //   151: dload_3
    //   152: ldc2_w 0.05000000074505806
    //   155: dmul
    //   156: dstore_3
    //   157: dload #5
    //   159: ldc2_w 0.25
    //   162: dmul
    //   163: dstore #5
    //   165: aload_0
    //   166: dconst_0
    //   167: putfield XHL : D
    //   170: aload_0
    //   171: dconst_0
    //   172: putfield Zpi : D
    //   175: aload_0
    //   176: dconst_0
    //   177: putfield kGO : D
    //   180: dload_1
    //   181: dstore #13
    //   183: dload_3
    //   184: dstore #15
    //   186: dload #5
    //   188: dstore #17
    //   190: aload_0
    //   191: getfield Dne : LbSp;
    //   194: invokevirtual Dne : ()LbSp;
    //   197: astore #19
    //   199: aload_0
    //   200: getfield aFZ : Z
    //   203: ifeq -> 224
    //   206: aload_0
    //   207: invokevirtual aFZ : ()Z
    //   210: ifeq -> 224
    //   213: aload_0
    //   214: instanceof FiG
    //   217: ifeq -> 224
    //   220: iconst_1
    //   221: goto -> 225
    //   224: iconst_0
    //   225: istore #20
    //   227: iload #20
    //   229: ifeq -> 544
    //   232: ldc2_w 0.05
    //   235: dstore #21
    //   237: dload_1
    //   238: dconst_0
    //   239: dcmpl
    //   240: ifeq -> 316
    //   243: aload_0
    //   244: getfield Dne : LQnq;
    //   247: aload_0
    //   248: aload_0
    //   249: getfield Dne : LbSp;
    //   252: dload_1
    //   253: ldc2_w -1.0
    //   256: dconst_0
    //   257: invokevirtual bzF : (DDD)LbSp;
    //   260: invokevirtual Dne : (LsMa;LbSp;)Ljava/util/List;
    //   263: invokeinterface isEmpty : ()Z
    //   268: ifeq -> 316
    //   271: dload_1
    //   272: dload #21
    //   274: dcmpg
    //   275: ifge -> 291
    //   278: dload_1
    //   279: dload #21
    //   281: dneg
    //   282: dcmpl
    //   283: iflt -> 291
    //   286: dconst_0
    //   287: dstore_1
    //   288: goto -> 310
    //   291: dload_1
    //   292: dconst_0
    //   293: dcmpl
    //   294: ifle -> 305
    //   297: dload_1
    //   298: dload #21
    //   300: dsub
    //   301: dstore_1
    //   302: goto -> 310
    //   305: dload_1
    //   306: dload #21
    //   308: dadd
    //   309: dstore_1
    //   310: dload_1
    //   311: dstore #13
    //   313: goto -> 237
    //   316: dload #5
    //   318: dconst_0
    //   319: dcmpl
    //   320: ifeq -> 406
    //   323: aload_0
    //   324: getfield Dne : LQnq;
    //   327: aload_0
    //   328: aload_0
    //   329: getfield Dne : LbSp;
    //   332: dconst_0
    //   333: ldc2_w -1.0
    //   336: dload #5
    //   338: invokevirtual bzF : (DDD)LbSp;
    //   341: invokevirtual Dne : (LsMa;LbSp;)Ljava/util/List;
    //   344: invokeinterface isEmpty : ()Z
    //   349: ifeq -> 406
    //   352: dload #5
    //   354: dload #21
    //   356: dcmpg
    //   357: ifge -> 375
    //   360: dload #5
    //   362: dload #21
    //   364: dneg
    //   365: dcmpl
    //   366: iflt -> 375
    //   369: dconst_0
    //   370: dstore #5
    //   372: goto -> 399
    //   375: dload #5
    //   377: dconst_0
    //   378: dcmpl
    //   379: ifle -> 392
    //   382: dload #5
    //   384: dload #21
    //   386: dsub
    //   387: dstore #5
    //   389: goto -> 399
    //   392: dload #5
    //   394: dload #21
    //   396: dadd
    //   397: dstore #5
    //   399: dload #5
    //   401: dstore #17
    //   403: goto -> 316
    //   406: dload_1
    //   407: dconst_0
    //   408: dcmpl
    //   409: ifeq -> 544
    //   412: dload #5
    //   414: dconst_0
    //   415: dcmpl
    //   416: ifeq -> 544
    //   419: aload_0
    //   420: getfield Dne : LQnq;
    //   423: aload_0
    //   424: aload_0
    //   425: getfield Dne : LbSp;
    //   428: dload_1
    //   429: ldc2_w -1.0
    //   432: dload #5
    //   434: invokevirtual bzF : (DDD)LbSp;
    //   437: invokevirtual Dne : (LsMa;LbSp;)Ljava/util/List;
    //   440: invokeinterface isEmpty : ()Z
    //   445: ifeq -> 544
    //   448: dload_1
    //   449: dload #21
    //   451: dcmpg
    //   452: ifge -> 468
    //   455: dload_1
    //   456: dload #21
    //   458: dneg
    //   459: dcmpl
    //   460: iflt -> 468
    //   463: dconst_0
    //   464: dstore_1
    //   465: goto -> 487
    //   468: dload_1
    //   469: dconst_0
    //   470: dcmpl
    //   471: ifle -> 482
    //   474: dload_1
    //   475: dload #21
    //   477: dsub
    //   478: dstore_1
    //   479: goto -> 487
    //   482: dload_1
    //   483: dload #21
    //   485: dadd
    //   486: dstore_1
    //   487: dload #5
    //   489: dload #21
    //   491: dcmpg
    //   492: ifge -> 510
    //   495: dload #5
    //   497: dload #21
    //   499: dneg
    //   500: dcmpl
    //   501: iflt -> 510
    //   504: dconst_0
    //   505: dstore #5
    //   507: goto -> 534
    //   510: dload #5
    //   512: dconst_0
    //   513: dcmpl
    //   514: ifle -> 527
    //   517: dload #5
    //   519: dload #21
    //   521: dsub
    //   522: dstore #5
    //   524: goto -> 534
    //   527: dload #5
    //   529: dload #21
    //   531: dadd
    //   532: dstore #5
    //   534: dload_1
    //   535: dstore #13
    //   537: dload #5
    //   539: dstore #17
    //   541: goto -> 406
    //   544: aload_0
    //   545: getfield Dne : LQnq;
    //   548: aload_0
    //   549: aload_0
    //   550: getfield Dne : LbSp;
    //   553: dload_1
    //   554: dload_3
    //   555: dload #5
    //   557: invokevirtual Dne : (DDD)LbSp;
    //   560: invokevirtual Dne : (LsMa;LbSp;)Ljava/util/List;
    //   563: astore #21
    //   565: iconst_0
    //   566: istore #22
    //   568: iload #22
    //   570: aload #21
    //   572: invokeinterface size : ()I
    //   577: if_icmpge -> 607
    //   580: aload #21
    //   582: iload #22
    //   584: invokeinterface get : (I)Ljava/lang/Object;
    //   589: checkcast bSp
    //   592: aload_0
    //   593: getfield Dne : LbSp;
    //   596: dload_3
    //   597: invokevirtual FWm : (LbSp;D)D
    //   600: dstore_3
    //   601: iinc #22, 1
    //   604: goto -> 568
    //   607: aload_0
    //   608: getfield Dne : LbSp;
    //   611: dconst_0
    //   612: dload_3
    //   613: dconst_0
    //   614: invokevirtual Qnq : (DDD)LbSp;
    //   617: pop
    //   618: aload_0
    //   619: getfield XHL : Z
    //   622: ifne -> 639
    //   625: dload #15
    //   627: dload_3
    //   628: dcmpl
    //   629: ifeq -> 639
    //   632: dconst_0
    //   633: dstore #5
    //   635: dconst_0
    //   636: dstore_3
    //   637: dconst_0
    //   638: dstore_1
    //   639: aload_0
    //   640: getfield aFZ : Z
    //   643: ifne -> 660
    //   646: dload #15
    //   648: dload_3
    //   649: dcmpl
    //   650: ifeq -> 664
    //   653: dload #15
    //   655: dconst_0
    //   656: dcmpg
    //   657: ifge -> 664
    //   660: iconst_1
    //   661: goto -> 665
    //   664: iconst_0
    //   665: istore #22
    //   667: iconst_0
    //   668: istore #23
    //   670: iload #23
    //   672: aload #21
    //   674: invokeinterface size : ()I
    //   679: if_icmpge -> 709
    //   682: aload #21
    //   684: iload #23
    //   686: invokeinterface get : (I)Ljava/lang/Object;
    //   691: checkcast bSp
    //   694: aload_0
    //   695: getfield Dne : LbSp;
    //   698: dload_1
    //   699: invokevirtual Dne : (LbSp;D)D
    //   702: dstore_1
    //   703: iinc #23, 1
    //   706: goto -> 670
    //   709: aload_0
    //   710: getfield Dne : LbSp;
    //   713: dload_1
    //   714: dconst_0
    //   715: dconst_0
    //   716: invokevirtual Qnq : (DDD)LbSp;
    //   719: pop
    //   720: aload_0
    //   721: getfield XHL : Z
    //   724: ifne -> 741
    //   727: dload #13
    //   729: dload_1
    //   730: dcmpl
    //   731: ifeq -> 741
    //   734: dconst_0
    //   735: dstore #5
    //   737: dconst_0
    //   738: dstore_3
    //   739: dconst_0
    //   740: dstore_1
    //   741: iconst_0
    //   742: istore #23
    //   744: iload #23
    //   746: aload #21
    //   748: invokeinterface size : ()I
    //   753: if_icmpge -> 785
    //   756: aload #21
    //   758: iload #23
    //   760: invokeinterface get : (I)Ljava/lang/Object;
    //   765: checkcast bSp
    //   768: aload_0
    //   769: getfield Dne : LbSp;
    //   772: dload #5
    //   774: invokevirtual bzF : (LbSp;D)D
    //   777: dstore #5
    //   779: iinc #23, 1
    //   782: goto -> 744
    //   785: aload_0
    //   786: getfield Dne : LbSp;
    //   789: dconst_0
    //   790: dconst_0
    //   791: dload #5
    //   793: invokevirtual Qnq : (DDD)LbSp;
    //   796: pop
    //   797: aload_0
    //   798: getfield XHL : Z
    //   801: ifne -> 819
    //   804: dload #17
    //   806: dload #5
    //   808: dcmpl
    //   809: ifeq -> 819
    //   812: dconst_0
    //   813: dstore #5
    //   815: dconst_0
    //   816: dstore_3
    //   817: dconst_0
    //   818: dstore_1
    //   819: aload_0
    //   820: getfield FfS : F
    //   823: fconst_0
    //   824: fcmpl
    //   825: ifle -> 1280
    //   828: iload #22
    //   830: ifeq -> 1280
    //   833: iload #20
    //   835: ifne -> 849
    //   838: aload_0
    //   839: getfield EyB : F
    //   842: ldc_w 0.05
    //   845: fcmpg
    //   846: ifge -> 1280
    //   849: dload #13
    //   851: dload_1
    //   852: dcmpl
    //   853: ifne -> 864
    //   856: dload #17
    //   858: dload #5
    //   860: dcmpl
    //   861: ifeq -> 1280
    //   864: dload_1
    //   865: dstore #29
    //   867: dload_3
    //   868: dstore #24
    //   870: dload #5
    //   872: dstore #26
    //   874: dload #13
    //   876: dstore_1
    //   877: aload_0
    //   878: getfield FfS : F
    //   881: f2d
    //   882: dstore_3
    //   883: dload #17
    //   885: dstore #5
    //   887: aload_0
    //   888: getfield Dne : LbSp;
    //   891: invokevirtual Dne : ()LbSp;
    //   894: astore #31
    //   896: aload_0
    //   897: getfield Dne : LbSp;
    //   900: aload #19
    //   902: invokevirtual Dne : (LbSp;)V
    //   905: aload_0
    //   906: getfield Dne : LQnq;
    //   909: aload_0
    //   910: aload_0
    //   911: getfield Dne : LbSp;
    //   914: dload #13
    //   916: dload_3
    //   917: dload #17
    //   919: invokevirtual Dne : (DDD)LbSp;
    //   922: invokevirtual Dne : (LsMa;LbSp;)Ljava/util/List;
    //   925: astore #21
    //   927: iconst_0
    //   928: istore #28
    //   930: iload #28
    //   932: aload #21
    //   934: invokeinterface size : ()I
    //   939: if_icmpge -> 969
    //   942: aload #21
    //   944: iload #28
    //   946: invokeinterface get : (I)Ljava/lang/Object;
    //   951: checkcast bSp
    //   954: aload_0
    //   955: getfield Dne : LbSp;
    //   958: dload_3
    //   959: invokevirtual FWm : (LbSp;D)D
    //   962: dstore_3
    //   963: iinc #28, 1
    //   966: goto -> 930
    //   969: aload_0
    //   970: getfield Dne : LbSp;
    //   973: dconst_0
    //   974: dload_3
    //   975: dconst_0
    //   976: invokevirtual Qnq : (DDD)LbSp;
    //   979: pop
    //   980: aload_0
    //   981: getfield XHL : Z
    //   984: ifne -> 1001
    //   987: dload #15
    //   989: dload_3
    //   990: dcmpl
    //   991: ifeq -> 1001
    //   994: dconst_0
    //   995: dstore #5
    //   997: dconst_0
    //   998: dstore_3
    //   999: dconst_0
    //   1000: dstore_1
    //   1001: iconst_0
    //   1002: istore #28
    //   1004: iload #28
    //   1006: aload #21
    //   1008: invokeinterface size : ()I
    //   1013: if_icmpge -> 1043
    //   1016: aload #21
    //   1018: iload #28
    //   1020: invokeinterface get : (I)Ljava/lang/Object;
    //   1025: checkcast bSp
    //   1028: aload_0
    //   1029: getfield Dne : LbSp;
    //   1032: dload_1
    //   1033: invokevirtual Dne : (LbSp;D)D
    //   1036: dstore_1
    //   1037: iinc #28, 1
    //   1040: goto -> 1004
    //   1043: aload_0
    //   1044: getfield Dne : LbSp;
    //   1047: dload_1
    //   1048: dconst_0
    //   1049: dconst_0
    //   1050: invokevirtual Qnq : (DDD)LbSp;
    //   1053: pop
    //   1054: aload_0
    //   1055: getfield XHL : Z
    //   1058: ifne -> 1075
    //   1061: dload #13
    //   1063: dload_1
    //   1064: dcmpl
    //   1065: ifeq -> 1075
    //   1068: dconst_0
    //   1069: dstore #5
    //   1071: dconst_0
    //   1072: dstore_3
    //   1073: dconst_0
    //   1074: dstore_1
    //   1075: iconst_0
    //   1076: istore #28
    //   1078: iload #28
    //   1080: aload #21
    //   1082: invokeinterface size : ()I
    //   1087: if_icmpge -> 1119
    //   1090: aload #21
    //   1092: iload #28
    //   1094: invokeinterface get : (I)Ljava/lang/Object;
    //   1099: checkcast bSp
    //   1102: aload_0
    //   1103: getfield Dne : LbSp;
    //   1106: dload #5
    //   1108: invokevirtual bzF : (LbSp;D)D
    //   1111: dstore #5
    //   1113: iinc #28, 1
    //   1116: goto -> 1078
    //   1119: aload_0
    //   1120: getfield Dne : LbSp;
    //   1123: dconst_0
    //   1124: dconst_0
    //   1125: dload #5
    //   1127: invokevirtual Qnq : (DDD)LbSp;
    //   1130: pop
    //   1131: aload_0
    //   1132: getfield XHL : Z
    //   1135: ifne -> 1153
    //   1138: dload #17
    //   1140: dload #5
    //   1142: dcmpl
    //   1143: ifeq -> 1153
    //   1146: dconst_0
    //   1147: dstore #5
    //   1149: dconst_0
    //   1150: dstore_3
    //   1151: dconst_0
    //   1152: dstore_1
    //   1153: aload_0
    //   1154: getfield XHL : Z
    //   1157: ifne -> 1177
    //   1160: dload #15
    //   1162: dload_3
    //   1163: dcmpl
    //   1164: ifeq -> 1177
    //   1167: dconst_0
    //   1168: dstore #5
    //   1170: dconst_0
    //   1171: dstore_3
    //   1172: dconst_0
    //   1173: dstore_1
    //   1174: goto -> 1237
    //   1177: aload_0
    //   1178: getfield FfS : F
    //   1181: fneg
    //   1182: f2d
    //   1183: dstore_3
    //   1184: iconst_0
    //   1185: istore #28
    //   1187: iload #28
    //   1189: aload #21
    //   1191: invokeinterface size : ()I
    //   1196: if_icmpge -> 1226
    //   1199: aload #21
    //   1201: iload #28
    //   1203: invokeinterface get : (I)Ljava/lang/Object;
    //   1208: checkcast bSp
    //   1211: aload_0
    //   1212: getfield Dne : LbSp;
    //   1215: dload_3
    //   1216: invokevirtual FWm : (LbSp;D)D
    //   1219: dstore_3
    //   1220: iinc #28, 1
    //   1223: goto -> 1187
    //   1226: aload_0
    //   1227: getfield Dne : LbSp;
    //   1230: dconst_0
    //   1231: dload_3
    //   1232: dconst_0
    //   1233: invokevirtual Qnq : (DDD)LbSp;
    //   1236: pop
    //   1237: dload #29
    //   1239: dload #29
    //   1241: dmul
    //   1242: dload #26
    //   1244: dload #26
    //   1246: dmul
    //   1247: dadd
    //   1248: dload_1
    //   1249: dload_1
    //   1250: dmul
    //   1251: dload #5
    //   1253: dload #5
    //   1255: dmul
    //   1256: dadd
    //   1257: dcmpl
    //   1258: iflt -> 1280
    //   1261: dload #29
    //   1263: dstore_1
    //   1264: dload #24
    //   1266: dstore_3
    //   1267: dload #26
    //   1269: dstore #5
    //   1271: aload_0
    //   1272: getfield Dne : LbSp;
    //   1275: aload #31
    //   1277: invokevirtual Dne : (LbSp;)V
    //   1280: aload_0
    //   1281: getfield Dne : LQnq;
    //   1284: getfield Dne : LBkx;
    //   1287: invokevirtual FWm : ()V
    //   1290: aload_0
    //   1291: getfield Dne : LQnq;
    //   1294: getfield Dne : LBkx;
    //   1297: ldc_w 'rest'
    //   1300: invokevirtual Dne : (Ljava/lang/String;)V
    //   1303: aload_0
    //   1304: aload_0
    //   1305: getfield Dne : LbSp;
    //   1308: getfield Dne : D
    //   1311: aload_0
    //   1312: getfield Dne : LbSp;
    //   1315: getfield Qnq : D
    //   1318: dadd
    //   1319: ldc2_w 2.0
    //   1322: ddiv
    //   1323: putfield div : D
    //   1326: aload_0
    //   1327: aload_0
    //   1328: getfield Dne : LbSp;
    //   1331: getfield FWm : D
    //   1334: aload_0
    //   1335: getfield udO : F
    //   1338: f2d
    //   1339: dadd
    //   1340: aload_0
    //   1341: getfield EyB : F
    //   1344: f2d
    //   1345: dsub
    //   1346: putfield IjH : D
    //   1349: aload_0
    //   1350: aload_0
    //   1351: getfield Dne : LbSp;
    //   1354: getfield bzF : D
    //   1357: aload_0
    //   1358: getfield Dne : LbSp;
    //   1361: getfield zGp : D
    //   1364: dadd
    //   1365: ldc2_w 2.0
    //   1368: ddiv
    //   1369: putfield mrb : D
    //   1372: aload_0
    //   1373: dload #13
    //   1375: dload_1
    //   1376: dcmpl
    //   1377: ifne -> 1388
    //   1380: dload #17
    //   1382: dload #5
    //   1384: dcmpl
    //   1385: ifeq -> 1392
    //   1388: iconst_1
    //   1389: goto -> 1393
    //   1392: iconst_0
    //   1393: putfield zGp : Z
    //   1396: aload_0
    //   1397: dload #15
    //   1399: dload_3
    //   1400: dcmpl
    //   1401: ifeq -> 1408
    //   1404: iconst_1
    //   1405: goto -> 1409
    //   1408: iconst_0
    //   1409: putfield DyG : Z
    //   1412: aload_0
    //   1413: dload #15
    //   1415: dload_3
    //   1416: dcmpl
    //   1417: ifeq -> 1431
    //   1420: dload #15
    //   1422: dconst_0
    //   1423: dcmpg
    //   1424: ifge -> 1431
    //   1427: iconst_1
    //   1428: goto -> 1432
    //   1431: iconst_0
    //   1432: putfield aFZ : Z
    //   1435: aload_0
    //   1436: aload_0
    //   1437: getfield zGp : Z
    //   1440: ifne -> 1450
    //   1443: aload_0
    //   1444: getfield DyG : Z
    //   1447: ifeq -> 1454
    //   1450: iconst_1
    //   1451: goto -> 1455
    //   1454: iconst_0
    //   1455: putfield div : Z
    //   1458: aload_0
    //   1459: dload_3
    //   1460: aload_0
    //   1461: getfield aFZ : Z
    //   1464: invokevirtual Dne : (DZ)V
    //   1467: dload #13
    //   1469: dload_1
    //   1470: dcmpl
    //   1471: ifeq -> 1479
    //   1474: aload_0
    //   1475: dconst_0
    //   1476: putfield XHL : D
    //   1479: dload #15
    //   1481: dload_3
    //   1482: dcmpl
    //   1483: ifeq -> 1491
    //   1486: aload_0
    //   1487: dconst_0
    //   1488: putfield Zpi : D
    //   1491: dload #17
    //   1493: dload #5
    //   1495: dcmpl
    //   1496: ifeq -> 1504
    //   1499: aload_0
    //   1500: dconst_0
    //   1501: putfield kGO : D
    //   1504: aload_0
    //   1505: getfield div : D
    //   1508: dload #7
    //   1510: dsub
    //   1511: dstore #29
    //   1513: aload_0
    //   1514: getfield IjH : D
    //   1517: dload #9
    //   1519: dsub
    //   1520: dstore #24
    //   1522: aload_0
    //   1523: getfield mrb : D
    //   1526: dload #11
    //   1528: dsub
    //   1529: dstore #26
    //   1531: aload_0
    //   1532: invokevirtual FWm : ()Z
    //   1535: ifeq -> 1895
    //   1538: iload #20
    //   1540: ifne -> 1895
    //   1543: aload_0
    //   1544: getfield FWm : LsMa;
    //   1547: ifnonnull -> 1895
    //   1550: aload_0
    //   1551: getfield div : D
    //   1554: invokestatic FWm : (D)I
    //   1557: istore #31
    //   1559: aload_0
    //   1560: getfield IjH : D
    //   1563: ldc2_w 0.20000000298023224
    //   1566: dsub
    //   1567: aload_0
    //   1568: getfield udO : F
    //   1571: f2d
    //   1572: dsub
    //   1573: invokestatic FWm : (D)I
    //   1576: istore #28
    //   1578: aload_0
    //   1579: getfield mrb : D
    //   1582: invokestatic FWm : (D)I
    //   1585: istore #32
    //   1587: aload_0
    //   1588: getfield Dne : LQnq;
    //   1591: iload #31
    //   1593: iload #28
    //   1595: iload #32
    //   1597: invokevirtual Dne : (III)I
    //   1600: istore #33
    //   1602: iload #33
    //   1604: ifne -> 1662
    //   1607: aload_0
    //   1608: getfield Dne : LQnq;
    //   1611: iload #31
    //   1613: iload #28
    //   1615: iconst_1
    //   1616: isub
    //   1617: iload #32
    //   1619: invokevirtual FWm : (III)I
    //   1622: istore #34
    //   1624: iload #34
    //   1626: bipush #11
    //   1628: if_icmpeq -> 1645
    //   1631: iload #34
    //   1633: bipush #32
    //   1635: if_icmpeq -> 1645
    //   1638: iload #34
    //   1640: bipush #21
    //   1642: if_icmpne -> 1662
    //   1645: aload_0
    //   1646: getfield Dne : LQnq;
    //   1649: iload #31
    //   1651: iload #28
    //   1653: iconst_1
    //   1654: isub
    //   1655: iload #32
    //   1657: invokevirtual Dne : (III)I
    //   1660: istore #33
    //   1662: iload #33
    //   1664: getstatic zKP.ZfC : LzKP;
    //   1667: getfield FWm : I
    //   1670: if_icmpeq -> 1676
    //   1673: dconst_0
    //   1674: dstore #24
    //   1676: aload_0
    //   1677: aload_0
    //   1678: getfield ATE : F
    //   1681: f2d
    //   1682: dload #29
    //   1684: dload #29
    //   1686: dmul
    //   1687: dload #26
    //   1689: dload #26
    //   1691: dmul
    //   1692: dadd
    //   1693: invokestatic Dne : (D)F
    //   1696: f2d
    //   1697: ldc2_w 0.6
    //   1700: dmul
    //   1701: dadd
    //   1702: d2f
    //   1703: putfield ATE : F
    //   1706: aload_0
    //   1707: aload_0
    //   1708: getfield Vxn : F
    //   1711: f2d
    //   1712: dload #29
    //   1714: dload #29
    //   1716: dmul
    //   1717: dload #24
    //   1719: dload #24
    //   1721: dmul
    //   1722: dadd
    //   1723: dload #26
    //   1725: dload #26
    //   1727: dmul
    //   1728: dadd
    //   1729: invokestatic Dne : (D)F
    //   1732: f2d
    //   1733: ldc2_w 0.6
    //   1736: dmul
    //   1737: dadd
    //   1738: d2f
    //   1739: putfield Vxn : F
    //   1742: aload_0
    //   1743: getfield Vxn : F
    //   1746: aload_0
    //   1747: getfield FWm : I
    //   1750: i2f
    //   1751: fcmpl
    //   1752: ifle -> 1895
    //   1755: iload #33
    //   1757: ifle -> 1895
    //   1760: aload_0
    //   1761: aload_0
    //   1762: getfield Vxn : F
    //   1765: f2i
    //   1766: iconst_1
    //   1767: iadd
    //   1768: putfield FWm : I
    //   1771: aload_0
    //   1772: invokevirtual Zpi : ()Z
    //   1775: ifeq -> 1863
    //   1778: aload_0
    //   1779: getfield XHL : D
    //   1782: aload_0
    //   1783: getfield XHL : D
    //   1786: dmul
    //   1787: ldc2_w 0.20000000298023224
    //   1790: dmul
    //   1791: aload_0
    //   1792: getfield Zpi : D
    //   1795: aload_0
    //   1796: getfield Zpi : D
    //   1799: dmul
    //   1800: dadd
    //   1801: aload_0
    //   1802: getfield kGO : D
    //   1805: aload_0
    //   1806: getfield kGO : D
    //   1809: dmul
    //   1810: ldc2_w 0.20000000298023224
    //   1813: dmul
    //   1814: dadd
    //   1815: invokestatic Dne : (D)F
    //   1818: ldc_w 0.35
    //   1821: fmul
    //   1822: fstore #34
    //   1824: fload #34
    //   1826: fconst_1
    //   1827: fcmpl
    //   1828: ifle -> 1834
    //   1831: fconst_1
    //   1832: fstore #34
    //   1834: aload_0
    //   1835: ldc_w 'liquid.swim'
    //   1838: fload #34
    //   1840: fconst_1
    //   1841: aload_0
    //   1842: getfield Dne : Ljava/util/Random;
    //   1845: invokevirtual nextFloat : ()F
    //   1848: aload_0
    //   1849: getfield Dne : Ljava/util/Random;
    //   1852: invokevirtual nextFloat : ()F
    //   1855: fsub
    //   1856: ldc 0.4
    //   1858: fmul
    //   1859: fadd
    //   1860: invokevirtual Dne : (Ljava/lang/String;FF)V
    //   1863: aload_0
    //   1864: iload #31
    //   1866: iload #28
    //   1868: iload #32
    //   1870: iload #33
    //   1872: invokevirtual Dne : (IIII)V
    //   1875: getstatic zKP.Dne : [LzKP;
    //   1878: iload #33
    //   1880: aaload
    //   1881: aload_0
    //   1882: getfield Dne : LQnq;
    //   1885: iload #31
    //   1887: iload #28
    //   1889: iload #32
    //   1891: aload_0
    //   1892: invokevirtual FWm : (LQnq;IIILsMa;)V
    //   1895: aload_0
    //   1896: invokevirtual OdI : ()V
    //   1899: aload_0
    //   1900: invokevirtual XHL : ()Z
    //   1903: istore #31
    //   1905: aload_0
    //   1906: getfield Dne : LQnq;
    //   1909: aload_0
    //   1910: getfield Dne : LbSp;
    //   1913: ldc2_w 0.001
    //   1916: ldc2_w 0.001
    //   1919: ldc2_w 0.001
    //   1922: invokevirtual aFZ : (DDD)LbSp;
    //   1925: invokevirtual Qnq : (LbSp;)Z
    //   1928: ifeq -> 1967
    //   1931: aload_0
    //   1932: iconst_1
    //   1933: invokevirtual zGp : (I)V
    //   1936: iload #31
    //   1938: ifne -> 1983
    //   1941: aload_0
    //   1942: dup
    //   1943: getfield bzF : I
    //   1946: iconst_1
    //   1947: iadd
    //   1948: putfield bzF : I
    //   1951: aload_0
    //   1952: getfield bzF : I
    //   1955: ifne -> 1983
    //   1958: aload_0
    //   1959: bipush #8
    //   1961: invokevirtual aFZ : (I)V
    //   1964: goto -> 1983
    //   1967: aload_0
    //   1968: getfield bzF : I
    //   1971: ifgt -> 1983
    //   1974: aload_0
    //   1975: aload_0
    //   1976: getfield DyG : I
    //   1979: ineg
    //   1980: putfield bzF : I
    //   1983: iload #31
    //   1985: ifeq -> 2036
    //   1988: aload_0
    //   1989: getfield bzF : I
    //   1992: ifle -> 2036
    //   1995: aload_0
    //   1996: ldc_w 'random.fizz'
    //   1999: ldc_w 0.7
    //   2002: ldc_w 1.6
    //   2005: aload_0
    //   2006: getfield Dne : Ljava/util/Random;
    //   2009: invokevirtual nextFloat : ()F
    //   2012: aload_0
    //   2013: getfield Dne : Ljava/util/Random;
    //   2016: invokevirtual nextFloat : ()F
    //   2019: fsub
    //   2020: ldc 0.4
    //   2022: fmul
    //   2023: fadd
    //   2024: invokevirtual Dne : (Ljava/lang/String;FF)V
    //   2027: aload_0
    //   2028: aload_0
    //   2029: getfield DyG : I
    //   2032: ineg
    //   2033: putfield bzF : I
    //   2036: aload_0
    //   2037: getfield Dne : LQnq;
    //   2040: getfield Dne : LBkx;
    //   2043: invokevirtual FWm : ()V
    //   2046: return
  }
  
  public void Fnk() {
    if (this.ooe) {
      this.ooe = DyG();
    } else {
      double d1 = this.aFZ - this.div;
      double d2 = this.DyG - this.mrb;
      if (this.Dne.aFZ == null && this.Vxn == 0.0F)
        this.ATE = zxJ.Dne(d1, d2); 
      this.Vxn = true;
    } 
  }
  
  public chN Dne() {
    return null;
  }
  
  protected void Dne(float paramFloat1, float paramFloat2) {
    if (paramFloat1 != this.ooe || paramFloat2 != this.trS) {
      this.ooe = paramFloat1;
      this.trS = paramFloat2;
      this.Dne.Qnq = this.Dne.Dne + this.ooe;
      this.Dne.zGp = this.Dne.bzF + this.ooe;
      this.Dne.aFZ = this.Dne.FWm + this.trS;
    } 
    float f = paramFloat1 % 2.0F;
    if (f < 0.375D) {
      this.Dne = bfY.Dne;
    } else if (f < 0.75D) {
      this.Dne = bfY.FWm;
    } else if (f < 1.0D) {
      this.Dne = bfY.bzF;
    } else if (f < 1.375D) {
      this.Dne = bfY.Qnq;
    } else if (f < 1.75D) {
      this.Dne = bfY.aFZ;
    } else {
      this.Dne = bfY.zGp;
    } 
  }
  
  public double aFZ() {
    return this.trS * 0.75D;
  }
  
  public float Dne(yTR paramyTR, Qnq paramQnq, int paramInt1, int paramInt2, int paramInt3, zKP paramzKP) {
    return paramzKP.Dne(this);
  }
  
  public int IjH() {
    return this.ATE;
  }
  
  public boolean OdI() {
    return trS();
  }
  
  public float Qnq() {
    return 0.1F;
  }
  
  protected void Dne(float paramFloat) {
    // Byte code:
    //   0: aload_0
    //   1: getfield Dne : LsMa;
    //   4: ifnull -> 15
    //   7: aload_0
    //   8: getfield Dne : LsMa;
    //   11: fload_1
    //   12: invokevirtual Dne : (F)V
    //   15: return
  }
  
  public void Qnq(WkD paramWkD) {
    try {
      mbZ mbZ1 = paramWkD.Dne("Pos");
      mbZ mbZ2 = paramWkD.Dne("Motion");
      mbZ mbZ3 = paramWkD.Dne("Rotation");
      this.XHL = ((kJU)mbZ2.FWm(0)).Dne;
      this.Zpi = ((kJU)mbZ2.FWm(1)).Dne;
      this.kGO = ((kJU)mbZ2.FWm(2)).Dne;
      if (Math.abs(this.XHL) > 10.0D)
        this.XHL = 0.0D; 
      if (Math.abs(this.Zpi) > 10.0D)
        this.Zpi = 0.0D; 
      if (Math.abs(this.kGO) > 10.0D)
        this.kGO = 0.0D; 
      this.udO = this.div = ((kJU)mbZ1.FWm(0)).Dne;
      (this.div = ((kJU)mbZ1.FWm(0)).Dne).aFZ = this;
      this.zGp = this.ooe = this.IjH = ((kJU)mbZ1.FWm(1)).Dne;
      this.trS = this.mrb = ((kJU)mbZ1.FWm(2)).Dne;
      (this.mrb = ((kJU)mbZ1.FWm(2)).Dne).DyG = this;
      this.Zpi = this.mrb = ((nOv)mbZ3.FWm(0)).Dne;
      this.kGO = this.XHL = ((nOv)mbZ3.FWm(1)).Dne;
      this.ceE = paramWkD.Dne("FallDistance");
      this.bzF = paramWkD.Dne("Fire");
      DyG(paramWkD.Dne("Air"));
      this.aFZ = paramWkD.FWm("OnGround");
      this.qLR = paramWkD.Dne("Dimension");
      this.FWm = paramWkD.FWm("Invulnerable");
      this.ooe = paramWkD.Dne("PortalCooldown");
      if (paramWkD.Dne("UUIDMost") && paramWkD.Dne("UUIDLeast"))
        this.Dne = new UUID(paramWkD.Dne("UUIDMost"), paramWkD.Dne("UUIDLeast")); 
      bzF(this.div, this.IjH, this.mrb);
      FWm(this.mrb, this.XHL);
      FWm(paramWkD);
    } catch (Throwable throwable) {
      McM mcM = McM.Dne(throwable, "Loading entity NBT");
      Noo noo = mcM.Dne("Entity being loaded");
      Dne(noo);
      throw new kaJ(mcM);
    } 
  }
  
  public int FWm() {
    return 3;
  }
  
  public void vSL() {
    // Byte code:
    //   0: aload_0
    //   1: getfield FWm : LsMa;
    //   4: getfield Zpi : Z
    //   7: ifeq -> 18
    //   10: aload_0
    //   11: aconst_null
    //   12: putfield FWm : LsMa;
    //   15: goto -> 324
    //   18: aload_0
    //   19: dconst_0
    //   20: putfield XHL : D
    //   23: aload_0
    //   24: dconst_0
    //   25: putfield Zpi : D
    //   28: aload_0
    //   29: dconst_0
    //   30: putfield kGO : D
    //   33: aload_0
    //   34: invokevirtual Dne : ()V
    //   37: aload_0
    //   38: getfield FWm : LsMa;
    //   41: ifnull -> 324
    //   44: aload_0
    //   45: getfield FWm : LsMa;
    //   48: invokevirtual RPx : ()V
    //   51: aload_0
    //   52: dup
    //   53: getfield FWm : D
    //   56: aload_0
    //   57: getfield FWm : LsMa;
    //   60: getfield mrb : F
    //   63: aload_0
    //   64: getfield FWm : LsMa;
    //   67: getfield Zpi : F
    //   70: fsub
    //   71: f2d
    //   72: dadd
    //   73: putfield FWm : D
    //   76: aload_0
    //   77: dup
    //   78: getfield Dne : D
    //   81: aload_0
    //   82: getfield FWm : LsMa;
    //   85: getfield XHL : F
    //   88: aload_0
    //   89: getfield FWm : LsMa;
    //   92: getfield kGO : F
    //   95: fsub
    //   96: f2d
    //   97: dadd
    //   98: putfield Dne : D
    //   101: aload_0
    //   102: getfield FWm : D
    //   105: ldc2_w 180.0
    //   108: dcmpl
    //   109: iflt -> 127
    //   112: aload_0
    //   113: dup
    //   114: getfield FWm : D
    //   117: ldc2_w 360.0
    //   120: dsub
    //   121: putfield FWm : D
    //   124: goto -> 101
    //   127: aload_0
    //   128: getfield FWm : D
    //   131: ldc2_w -180.0
    //   134: dcmpg
    //   135: ifge -> 153
    //   138: aload_0
    //   139: dup
    //   140: getfield FWm : D
    //   143: ldc2_w 360.0
    //   146: dadd
    //   147: putfield FWm : D
    //   150: goto -> 127
    //   153: aload_0
    //   154: getfield Dne : D
    //   157: ldc2_w 180.0
    //   160: dcmpl
    //   161: iflt -> 179
    //   164: aload_0
    //   165: dup
    //   166: getfield Dne : D
    //   169: ldc2_w 360.0
    //   172: dsub
    //   173: putfield Dne : D
    //   176: goto -> 153
    //   179: aload_0
    //   180: getfield Dne : D
    //   183: ldc2_w -180.0
    //   186: dcmpg
    //   187: ifge -> 205
    //   190: aload_0
    //   191: dup
    //   192: getfield Dne : D
    //   195: ldc2_w 360.0
    //   198: dadd
    //   199: putfield Dne : D
    //   202: goto -> 179
    //   205: aload_0
    //   206: getfield FWm : D
    //   209: ldc2_w 0.5
    //   212: dmul
    //   213: dstore_1
    //   214: aload_0
    //   215: getfield Dne : D
    //   218: ldc2_w 0.5
    //   221: dmul
    //   222: dstore_3
    //   223: ldc_w 10.0
    //   226: fstore #5
    //   228: dload_1
    //   229: fload #5
    //   231: f2d
    //   232: dcmpl
    //   233: ifle -> 240
    //   236: fload #5
    //   238: f2d
    //   239: dstore_1
    //   240: dload_1
    //   241: fload #5
    //   243: fneg
    //   244: f2d
    //   245: dcmpg
    //   246: ifge -> 254
    //   249: fload #5
    //   251: fneg
    //   252: f2d
    //   253: dstore_1
    //   254: dload_3
    //   255: fload #5
    //   257: f2d
    //   258: dcmpl
    //   259: ifle -> 266
    //   262: fload #5
    //   264: f2d
    //   265: dstore_3
    //   266: dload_3
    //   267: fload #5
    //   269: fneg
    //   270: f2d
    //   271: dcmpg
    //   272: ifge -> 280
    //   275: fload #5
    //   277: fneg
    //   278: f2d
    //   279: dstore_3
    //   280: aload_0
    //   281: dup
    //   282: getfield FWm : D
    //   285: dload_1
    //   286: dsub
    //   287: putfield FWm : D
    //   290: aload_0
    //   291: dup
    //   292: getfield Dne : D
    //   295: dload_3
    //   296: dsub
    //   297: putfield Dne : D
    //   300: aload_0
    //   301: aload_0
    //   302: getfield mrb : F
    //   305: f2d
    //   306: dload_1
    //   307: dadd
    //   308: d2f
    //   309: putfield mrb : F
    //   312: aload_0
    //   313: aload_0
    //   314: getfield XHL : F
    //   317: f2d
    //   318: dload_3
    //   319: dadd
    //   320: d2f
    //   321: putfield XHL : F
    //   324: return
  }
  
  public void Dne(double paramDouble1, double paramDouble2, double paramDouble3, float paramFloat1, float paramFloat2, int paramInt) {
    // Byte code:
    //   0: aload_0
    //   1: dload_1
    //   2: dload_3
    //   3: dload #5
    //   5: invokevirtual bzF : (DDD)V
    //   8: aload_0
    //   9: fload #7
    //   11: fload #8
    //   13: invokevirtual FWm : (FF)V
    //   16: aload_0
    //   17: getfield Dne : LQnq;
    //   20: aload_0
    //   21: aload_0
    //   22: getfield Dne : LbSp;
    //   25: ldc2_w 0.03125
    //   28: dconst_0
    //   29: ldc2_w 0.03125
    //   32: invokevirtual aFZ : (DDD)LbSp;
    //   35: invokevirtual Dne : (LsMa;LbSp;)Ljava/util/List;
    //   38: astore #10
    //   40: aload #10
    //   42: invokeinterface isEmpty : ()Z
    //   47: ifne -> 127
    //   50: dconst_0
    //   51: dstore #11
    //   53: iconst_0
    //   54: istore #13
    //   56: iload #13
    //   58: aload #10
    //   60: invokeinterface size : ()I
    //   65: if_icmpge -> 106
    //   68: aload #10
    //   70: iload #13
    //   72: invokeinterface get : (I)Ljava/lang/Object;
    //   77: checkcast bSp
    //   80: astore #14
    //   82: aload #14
    //   84: getfield aFZ : D
    //   87: dload #11
    //   89: dcmpl
    //   90: ifle -> 100
    //   93: aload #14
    //   95: getfield aFZ : D
    //   98: dstore #11
    //   100: iinc #13, 1
    //   103: goto -> 56
    //   106: dload_3
    //   107: dload #11
    //   109: aload_0
    //   110: getfield Dne : LbSp;
    //   113: getfield FWm : D
    //   116: dsub
    //   117: dadd
    //   118: dstore_3
    //   119: aload_0
    //   120: dload_1
    //   121: dload_3
    //   122: dload #5
    //   124: invokevirtual bzF : (DDD)V
    //   127: return
  }
  
  public boolean Dne(double paramDouble) {
    // Byte code:
    //   0: aload_0
    //   1: getfield Dne : LbSp;
    //   4: invokevirtual Dne : ()D
    //   7: dstore_3
    //   8: dload_3
    //   9: ldc2_w 64.0
    //   12: aload_0
    //   13: getfield Qnq : D
    //   16: dmul
    //   17: dmul
    //   18: dstore_3
    //   19: dload_1
    //   20: dload_3
    //   21: dload_3
    //   22: dmul
    //   23: dcmpg
    //   24: ifge -> 31
    //   27: iconst_1
    //   28: goto -> 32
    //   31: iconst_0
    //   32: ireturn
  }
  
  public boolean trS() {
    return (this.bzF > 0 || Dne(0));
  }
  
  public boolean FWm(FiG paramFiG) {
    return Vxn();
  }
  
  public boolean Vxn() {
    return Dne(5);
  }
  
  public boolean oIf() {
    return true;
  }
  
  public luM Dne() {
    return this.Dne;
  }
  
  protected abstract void FWm();
  
  public boolean DyG() {
    // Byte code:
    //   0: aload_0
    //   1: getfield Dne : LQnq;
    //   4: aload_0
    //   5: getfield Dne : LbSp;
    //   8: ldc2_w -0.10000000149011612
    //   11: ldc2_w -0.4000000059604645
    //   14: ldc2_w -0.10000000149011612
    //   17: invokevirtual FWm : (DDD)LbSp;
    //   20: getstatic KFd.IjH : LKFd;
    //   23: invokevirtual Dne : (LbSp;LKFd;)Z
    //   26: ireturn
  }
  
  public boolean bzF() {
    return true;
  }
  
  protected void OdI() {
    // Byte code:
    //   0: aload_0
    //   1: getfield Dne : LbSp;
    //   4: getfield Dne : D
    //   7: ldc2_w 0.001
    //   10: dadd
    //   11: invokestatic FWm : (D)I
    //   14: istore_1
    //   15: aload_0
    //   16: getfield Dne : LbSp;
    //   19: getfield FWm : D
    //   22: ldc2_w 0.001
    //   25: dadd
    //   26: invokestatic FWm : (D)I
    //   29: istore_2
    //   30: aload_0
    //   31: getfield Dne : LbSp;
    //   34: getfield bzF : D
    //   37: ldc2_w 0.001
    //   40: dadd
    //   41: invokestatic FWm : (D)I
    //   44: istore_3
    //   45: aload_0
    //   46: getfield Dne : LbSp;
    //   49: getfield Qnq : D
    //   52: ldc2_w 0.001
    //   55: dsub
    //   56: invokestatic FWm : (D)I
    //   59: istore #4
    //   61: aload_0
    //   62: getfield Dne : LbSp;
    //   65: getfield aFZ : D
    //   68: ldc2_w 0.001
    //   71: dsub
    //   72: invokestatic FWm : (D)I
    //   75: istore #5
    //   77: aload_0
    //   78: getfield Dne : LbSp;
    //   81: getfield zGp : D
    //   84: ldc2_w 0.001
    //   87: dsub
    //   88: invokestatic FWm : (D)I
    //   91: istore #6
    //   93: aload_0
    //   94: getfield Dne : LQnq;
    //   97: iload_1
    //   98: iload_2
    //   99: iload_3
    //   100: iload #4
    //   102: iload #5
    //   104: iload #6
    //   106: invokevirtual Dne : (IIIIII)Z
    //   109: ifeq -> 200
    //   112: iload_1
    //   113: istore #7
    //   115: iload #7
    //   117: iload #4
    //   119: if_icmpgt -> 200
    //   122: iload_2
    //   123: istore #8
    //   125: iload #8
    //   127: iload #5
    //   129: if_icmpgt -> 194
    //   132: iload_3
    //   133: istore #9
    //   135: iload #9
    //   137: iload #6
    //   139: if_icmpgt -> 188
    //   142: aload_0
    //   143: getfield Dne : LQnq;
    //   146: iload #7
    //   148: iload #8
    //   150: iload #9
    //   152: invokevirtual Dne : (III)I
    //   155: istore #10
    //   157: iload #10
    //   159: ifle -> 182
    //   162: getstatic zKP.Dne : [LzKP;
    //   165: iload #10
    //   167: aaload
    //   168: aload_0
    //   169: getfield Dne : LQnq;
    //   172: iload #7
    //   174: iload #8
    //   176: iload #9
    //   178: aload_0
    //   179: invokevirtual Dne : (LQnq;IIILsMa;)V
    //   182: iinc #9, 1
    //   185: goto -> 135
    //   188: iinc #8, 1
    //   191: goto -> 125
    //   194: iinc #7, 1
    //   197: goto -> 115
    //   200: return
  }
  
  protected void zGp(int paramInt) {
    if (!this.ooe)
      Dne((zBn)zBn.Dne, paramInt); 
  }
  
  public void a_(boolean paramBoolean) {
    Dne(3, paramBoolean);
  }
  
  public void bzF(WkD paramWkD) {
    // Byte code:
    //   0: aload_1
    //   1: ldc_w 'Pos'
    //   4: aload_0
    //   5: iconst_3
    //   6: newarray double
    //   8: dup
    //   9: iconst_0
    //   10: aload_0
    //   11: getfield div : D
    //   14: dastore
    //   15: dup
    //   16: iconst_1
    //   17: aload_0
    //   18: getfield IjH : D
    //   21: aload_0
    //   22: getfield EyB : F
    //   25: f2d
    //   26: dadd
    //   27: dastore
    //   28: dup
    //   29: iconst_2
    //   30: aload_0
    //   31: getfield mrb : D
    //   34: dastore
    //   35: invokevirtual Dne : ([D)LmbZ;
    //   38: invokevirtual Dne : (Ljava/lang/String;LoNe;)V
    //   41: aload_1
    //   42: ldc_w 'Motion'
    //   45: aload_0
    //   46: iconst_3
    //   47: newarray double
    //   49: dup
    //   50: iconst_0
    //   51: aload_0
    //   52: getfield XHL : D
    //   55: dastore
    //   56: dup
    //   57: iconst_1
    //   58: aload_0
    //   59: getfield Zpi : D
    //   62: dastore
    //   63: dup
    //   64: iconst_2
    //   65: aload_0
    //   66: getfield kGO : D
    //   69: dastore
    //   70: invokevirtual Dne : ([D)LmbZ;
    //   73: invokevirtual Dne : (Ljava/lang/String;LoNe;)V
    //   76: aload_1
    //   77: ldc_w 'Rotation'
    //   80: aload_0
    //   81: iconst_2
    //   82: newarray float
    //   84: dup
    //   85: iconst_0
    //   86: aload_0
    //   87: getfield mrb : F
    //   90: fastore
    //   91: dup
    //   92: iconst_1
    //   93: aload_0
    //   94: getfield XHL : F
    //   97: fastore
    //   98: invokevirtual Dne : ([F)LmbZ;
    //   101: invokevirtual Dne : (Ljava/lang/String;LoNe;)V
    //   104: aload_1
    //   105: ldc_w 'FallDistance'
    //   108: aload_0
    //   109: getfield ceE : F
    //   112: invokevirtual Dne : (Ljava/lang/String;F)V
    //   115: aload_1
    //   116: ldc_w 'Fire'
    //   119: aload_0
    //   120: getfield bzF : I
    //   123: i2s
    //   124: invokevirtual Dne : (Ljava/lang/String;S)V
    //   127: aload_1
    //   128: ldc_w 'Air'
    //   131: aload_0
    //   132: invokevirtual div : ()I
    //   135: i2s
    //   136: invokevirtual Dne : (Ljava/lang/String;S)V
    //   139: aload_1
    //   140: ldc_w 'OnGround'
    //   143: aload_0
    //   144: getfield aFZ : Z
    //   147: invokevirtual Dne : (Ljava/lang/String;Z)V
    //   150: aload_1
    //   151: ldc_w 'Dimension'
    //   154: aload_0
    //   155: getfield qLR : I
    //   158: invokevirtual Dne : (Ljava/lang/String;I)V
    //   161: aload_1
    //   162: ldc_w 'Invulnerable'
    //   165: aload_0
    //   166: getfield FWm : Z
    //   169: invokevirtual Dne : (Ljava/lang/String;Z)V
    //   172: aload_1
    //   173: ldc_w 'PortalCooldown'
    //   176: aload_0
    //   177: getfield ooe : I
    //   180: invokevirtual Dne : (Ljava/lang/String;I)V
    //   183: aload_1
    //   184: ldc_w 'UUIDMost'
    //   187: aload_0
    //   188: getfield Dne : Ljava/util/UUID;
    //   191: invokevirtual getMostSignificantBits : ()J
    //   194: invokevirtual Dne : (Ljava/lang/String;J)V
    //   197: aload_1
    //   198: ldc_w 'UUIDLeast'
    //   201: aload_0
    //   202: getfield Dne : Ljava/util/UUID;
    //   205: invokevirtual getLeastSignificantBits : ()J
    //   208: invokevirtual Dne : (Ljava/lang/String;J)V
    //   211: aload_0
    //   212: aload_1
    //   213: invokevirtual Dne : (LWkD;)V
    //   216: aload_0
    //   217: getfield FWm : LsMa;
    //   220: ifnull -> 253
    //   223: new WkD
    //   226: dup
    //   227: ldc_w 'Riding'
    //   230: invokespecial <init> : (Ljava/lang/String;)V
    //   233: astore_2
    //   234: aload_0
    //   235: getfield FWm : LsMa;
    //   238: aload_2
    //   239: invokevirtual Dne : (LWkD;)Z
    //   242: ifeq -> 253
    //   245: aload_1
    //   246: ldc_w 'Riding'
    //   249: aload_2
    //   250: invokevirtual Dne : (Ljava/lang/String;LoNe;)V
    //   253: goto -> 289
    //   256: astore_2
    //   257: aload_2
    //   258: ldc_w 'Saving entity NBT'
    //   261: invokestatic Dne : (Ljava/lang/Throwable;Ljava/lang/String;)LMcM;
    //   264: astore_3
    //   265: aload_3
    //   266: ldc_w 'Entity being saved'
    //   269: invokevirtual Dne : (Ljava/lang/String;)LNoo;
    //   272: astore #4
    //   274: aload_0
    //   275: aload #4
    //   277: invokevirtual Dne : (LNoo;)V
    //   280: new kaJ
    //   283: dup
    //   284: aload_3
    //   285: invokespecial <init> : (LMcM;)V
    //   288: athrow
    //   289: return
    // Exception table:
    //   from	to	target	type
    //   0	253	256	java/lang/Throwable
  }
  
  public void aFZ(boolean paramBoolean) {
    Dne(4, paramBoolean);
  }
  
  public boolean EyB() {
    return this.FWm;
  }
  
  protected void Dne(int paramInt, boolean paramBoolean) {
    // Byte code:
    //   0: aload_0
    //   1: getfield Dne : LluM;
    //   4: iconst_0
    //   5: invokevirtual Dne : (I)B
    //   8: istore_3
    //   9: iload_2
    //   10: ifeq -> 33
    //   13: aload_0
    //   14: getfield Dne : LluM;
    //   17: iconst_0
    //   18: iload_3
    //   19: iconst_1
    //   20: iload_1
    //   21: ishl
    //   22: ior
    //   23: i2b
    //   24: invokestatic valueOf : (B)Ljava/lang/Byte;
    //   27: invokevirtual FWm : (ILjava/lang/Object;)V
    //   30: goto -> 52
    //   33: aload_0
    //   34: getfield Dne : LluM;
    //   37: iconst_0
    //   38: iload_3
    //   39: iconst_1
    //   40: iload_1
    //   41: ishl
    //   42: iconst_m1
    //   43: ixor
    //   44: iand
    //   45: i2b
    //   46: invokestatic valueOf : (B)Ljava/lang/Byte;
    //   49: invokevirtual FWm : (ILjava/lang/Object;)V
    //   52: return
  }
  
  public void Dne(Qnq paramQnq) {
    this.Dne = paramQnq;
  }
  
  public boolean FWm(WkD paramWkD) {
    String str = Qnq();
    if (this.Zpi == 0.0F && str != null && this.Dne == null) {
      paramWkD.Dne("id", str);
      bzF(paramWkD);
      return true;
    } 
    return false;
  }
  
  public void RPx() {
    // Byte code:
    //   0: aload_0
    //   1: getfield Dne : LsMa;
    //   4: ifnull -> 108
    //   7: aload_0
    //   8: getfield Dne : LsMa;
    //   11: instanceof FiG
    //   14: ifeq -> 30
    //   17: aload_0
    //   18: getfield Dne : LsMa;
    //   21: checkcast FiG
    //   24: invokevirtual b_ : ()Z
    //   27: ifne -> 76
    //   30: aload_0
    //   31: getfield Dne : LsMa;
    //   34: aload_0
    //   35: getfield udO : D
    //   38: putfield udO : D
    //   41: aload_0
    //   42: getfield Dne : LsMa;
    //   45: aload_0
    //   46: getfield ooe : D
    //   49: aload_0
    //   50: invokevirtual aFZ : ()D
    //   53: dadd
    //   54: aload_0
    //   55: getfield Dne : LsMa;
    //   58: invokevirtual Qnq : ()D
    //   61: dadd
    //   62: putfield ooe : D
    //   65: aload_0
    //   66: getfield Dne : LsMa;
    //   69: aload_0
    //   70: getfield trS : D
    //   73: putfield trS : D
    //   76: aload_0
    //   77: getfield Dne : LsMa;
    //   80: aload_0
    //   81: getfield div : D
    //   84: aload_0
    //   85: getfield IjH : D
    //   88: aload_0
    //   89: invokevirtual aFZ : ()D
    //   92: dadd
    //   93: aload_0
    //   94: getfield Dne : LsMa;
    //   97: invokevirtual Qnq : ()D
    //   100: dadd
    //   101: aload_0
    //   102: getfield mrb : D
    //   105: invokevirtual bzF : (DDD)V
    //   108: return
  }
  
  public boolean qLR() {
    return (this.FWm != null || Dne(2));
  }
  
  public void Dne(sMa paramsMa, boolean paramBoolean) {
    WkD wkD = new WkD();
    paramsMa.bzF(wkD);
    Qnq(wkD);
    this.ooe = paramsMa.ooe;
    this.ATE = paramsMa.ATE;
  }
  
  public boolean Dne(yTR paramyTR, Qnq paramQnq, int paramInt1, int paramInt2, int paramInt3, int paramInt4, float paramFloat) {
    return true;
  }
  
  public void Qnq(int paramInt) {
    // Byte code:
    //   0: aload_0
    //   1: getfield Dne : LQnq;
    //   4: getfield aFZ : Z
    //   7: ifne -> 176
    //   10: aload_0
    //   11: getfield Zpi : Z
    //   14: ifne -> 176
    //   17: aload_0
    //   18: getfield Dne : LQnq;
    //   21: getfield Dne : LBkx;
    //   24: ldc_w 'changeDimension'
    //   27: invokevirtual Dne : (Ljava/lang/String;)V
    //   30: invokestatic Dne : ()LJwh;
    //   33: astore_2
    //   34: aload_0
    //   35: getfield qLR : I
    //   38: istore_3
    //   39: aload_2
    //   40: iload_3
    //   41: invokevirtual Dne : (I)LRAN;
    //   44: astore #4
    //   46: aload_2
    //   47: iload_1
    //   48: invokevirtual Dne : (I)LRAN;
    //   51: astore #5
    //   53: aload_0
    //   54: iload_1
    //   55: putfield qLR : I
    //   58: aload_0
    //   59: getfield Dne : LQnq;
    //   62: aload_0
    //   63: invokevirtual bzF : (LsMa;)V
    //   66: aload_0
    //   67: iconst_0
    //   68: putfield Zpi : Z
    //   71: aload_0
    //   72: getfield Dne : LQnq;
    //   75: getfield Dne : LBkx;
    //   78: ldc_w 'reposition'
    //   81: invokevirtual Dne : (Ljava/lang/String;)V
    //   84: aload_2
    //   85: invokevirtual Dne : ()LdzN;
    //   88: aload_0
    //   89: iload_3
    //   90: aload #4
    //   92: aload #5
    //   94: invokevirtual Dne : (LsMa;ILRAN;LRAN;)V
    //   97: aload_0
    //   98: getfield Dne : LQnq;
    //   101: getfield Dne : LBkx;
    //   104: ldc_w 'reloading'
    //   107: invokevirtual FWm : (Ljava/lang/String;)V
    //   110: aload_0
    //   111: invokestatic Dne : (LsMa;)Ljava/lang/String;
    //   114: aload #5
    //   116: invokestatic Dne : (Ljava/lang/String;LQnq;)LsMa;
    //   119: astore #6
    //   121: aload #6
    //   123: ifnull -> 141
    //   126: aload #6
    //   128: aload_0
    //   129: iconst_1
    //   130: invokevirtual Dne : (LsMa;Z)V
    //   133: aload #5
    //   135: aload #6
    //   137: invokevirtual FWm : (LsMa;)Z
    //   140: pop
    //   141: aload_0
    //   142: iconst_1
    //   143: putfield Zpi : Z
    //   146: aload_0
    //   147: getfield Dne : LQnq;
    //   150: getfield Dne : LBkx;
    //   153: invokevirtual FWm : ()V
    //   156: aload #4
    //   158: invokevirtual udO : ()V
    //   161: aload #5
    //   163: invokevirtual udO : ()V
    //   166: aload_0
    //   167: getfield Dne : LQnq;
    //   170: getfield Dne : LBkx;
    //   173: invokevirtual FWm : ()V
    //   176: return
  }
  
  public float aFZ() {
    return 0.0F;
  }
  
  public boolean ooe() {
    // Byte code:
    //   0: iconst_0
    //   1: istore_1
    //   2: iload_1
    //   3: bipush #8
    //   5: if_icmpge -> 131
    //   8: iload_1
    //   9: iconst_0
    //   10: ishr
    //   11: iconst_2
    //   12: irem
    //   13: i2f
    //   14: ldc_w 0.5
    //   17: fsub
    //   18: aload_0
    //   19: getfield ooe : F
    //   22: fmul
    //   23: ldc_w 0.8
    //   26: fmul
    //   27: fstore_2
    //   28: iload_1
    //   29: iconst_1
    //   30: ishr
    //   31: iconst_2
    //   32: irem
    //   33: i2f
    //   34: ldc_w 0.5
    //   37: fsub
    //   38: ldc_w 0.1
    //   41: fmul
    //   42: fstore_3
    //   43: iload_1
    //   44: iconst_2
    //   45: ishr
    //   46: iconst_2
    //   47: irem
    //   48: i2f
    //   49: ldc_w 0.5
    //   52: fsub
    //   53: aload_0
    //   54: getfield ooe : F
    //   57: fmul
    //   58: ldc_w 0.8
    //   61: fmul
    //   62: fstore #4
    //   64: aload_0
    //   65: getfield div : D
    //   68: fload_2
    //   69: f2d
    //   70: dadd
    //   71: invokestatic FWm : (D)I
    //   74: istore #5
    //   76: aload_0
    //   77: getfield IjH : D
    //   80: aload_0
    //   81: invokevirtual c_ : ()F
    //   84: f2d
    //   85: dadd
    //   86: fload_3
    //   87: f2d
    //   88: dadd
    //   89: invokestatic FWm : (D)I
    //   92: istore #6
    //   94: aload_0
    //   95: getfield mrb : D
    //   98: fload #4
    //   100: f2d
    //   101: dadd
    //   102: invokestatic FWm : (D)I
    //   105: istore #7
    //   107: aload_0
    //   108: getfield Dne : LQnq;
    //   111: iload #5
    //   113: iload #6
    //   115: iload #7
    //   117: invokevirtual DyG : (III)Z
    //   120: ifeq -> 125
    //   123: iconst_1
    //   124: ireturn
    //   125: iinc #1, 1
    //   128: goto -> 2
    //   131: iconst_0
    //   132: ireturn
  }
  
  public bSp Dne(sMa paramsMa) {
    return null;
  }
}


/* Location:              C:\Users\fract\Downloads\ERROR422.jar!\sMa.class
 * Java compiler version: 8 (52.0)
 * JD-Core Version:       1.1.3
 */