public class TCA extends VHz {
  protected void Dne(wHH paramwHH) {
    // Byte code:
    //   0: aload_1
    //   1: getfield Dne : LsMa;
    //   4: ifnull -> 24
    //   7: aload_1
    //   8: getfield Dne : LsMa;
    //   11: aload_0
    //   12: aload_0
    //   13: invokevirtual Dne : ()LFUH;
    //   16: invokestatic Dne : (LsMa;LsMa;)LzBn;
    //   19: iconst_0
    //   20: invokevirtual Dne : (LzBn;I)Z
    //   23: pop
    //   24: aload_0
    //   25: getfield Dne : LQnq;
    //   28: getfield aFZ : Z
    //   31: ifne -> 181
    //   34: aload_0
    //   35: getfield Dne : Ljava/util/Random;
    //   38: bipush #8
    //   40: invokevirtual nextInt : (I)I
    //   43: ifne -> 181
    //   46: iconst_1
    //   47: istore_2
    //   48: aload_0
    //   49: getfield Dne : Ljava/util/Random;
    //   52: bipush #32
    //   54: invokevirtual nextInt : (I)I
    //   57: ifne -> 62
    //   60: iconst_4
    //   61: istore_2
    //   62: bipush #10
    //   64: invokestatic Dne : (I)I
    //   67: ifne -> 115
    //   70: new zTy
    //   73: dup
    //   74: aload_0
    //   75: getfield Dne : LQnq;
    //   78: invokespecial <init> : (LQnq;)V
    //   81: astore_3
    //   82: aload_3
    //   83: aload_0
    //   84: getfield div : D
    //   87: aload_0
    //   88: getfield IjH : D
    //   91: aload_0
    //   92: getfield mrb : D
    //   95: aload_0
    //   96: getfield mrb : F
    //   99: fconst_0
    //   100: invokevirtual FWm : (DDDFF)V
    //   103: aload_0
    //   104: getfield Dne : LQnq;
    //   107: aload_3
    //   108: invokevirtual FWm : (LsMa;)Z
    //   111: pop
    //   112: goto -> 181
    //   115: iconst_0
    //   116: istore_3
    //   117: iload_3
    //   118: iload_2
    //   119: if_icmpge -> 181
    //   122: new GRq
    //   125: dup
    //   126: aload_0
    //   127: getfield Dne : LQnq;
    //   130: invokespecial <init> : (LQnq;)V
    //   133: astore #4
    //   135: aload #4
    //   137: sipush #-24000
    //   140: invokevirtual FWm : (I)V
    //   143: aload #4
    //   145: aload_0
    //   146: getfield div : D
    //   149: aload_0
    //   150: getfield IjH : D
    //   153: aload_0
    //   154: getfield mrb : D
    //   157: aload_0
    //   158: getfield mrb : F
    //   161: fconst_0
    //   162: invokevirtual FWm : (DDDFF)V
    //   165: aload_0
    //   166: getfield Dne : LQnq;
    //   169: aload #4
    //   171: invokevirtual FWm : (LsMa;)Z
    //   174: pop
    //   175: iinc #3, 1
    //   178: goto -> 117
    //   181: iconst_0
    //   182: istore_2
    //   183: iload_2
    //   184: bipush #8
    //   186: if_icmpge -> 219
    //   189: aload_0
    //   190: getfield Dne : LQnq;
    //   193: ldc 'snowballpoof'
    //   195: aload_0
    //   196: getfield div : D
    //   199: aload_0
    //   200: getfield IjH : D
    //   203: aload_0
    //   204: getfield mrb : D
    //   207: dconst_0
    //   208: dconst_0
    //   209: dconst_0
    //   210: invokevirtual Dne : (Ljava/lang/String;DDDDDD)V
    //   213: iinc #2, 1
    //   216: goto -> 183
    //   219: aload_0
    //   220: getfield Dne : LQnq;
    //   223: getfield aFZ : Z
    //   226: ifne -> 233
    //   229: aload_0
    //   230: invokevirtual g_ : ()V
    //   233: return
  }
  
  public TCA(Qnq paramQnq, FUH paramFUH) {
    super(paramQnq, paramFUH);
  }
  
  public TCA(Qnq paramQnq, double paramDouble1, double paramDouble2, double paramDouble3) {
    super(paramQnq, paramDouble1, paramDouble2, paramDouble3);
  }
  
  public TCA(Qnq paramQnq) {
    super(paramQnq);
  }
  
  static {
  
  }
}


/* Location:              C:\Users\fract\Downloads\ERROR422.jar!\TCA.class
 * Java compiler version: 8 (52.0)
 * JD-Core Version:       1.1.3
 */