public class TKg extends Jik {
  public boolean FWm(int paramInt1, int paramInt2) {
    return true;
  }
  
  public float Dne(long paramLong, float paramFloat) {
    return 0.0F;
  }
  
  public ZfC Dne() {
    // Byte code:
    //   0: new Zlx
    //   3: dup
    //   4: aload_0
    //   5: getfield Dne : LQnq;
    //   8: aload_0
    //   9: getfield Dne : LQnq;
    //   12: invokevirtual Dne : ()J
    //   15: invokespecial <init> : (LQnq;J)V
    //   18: areturn
  }
  
  public boolean bzF() {
    return false;
  }
  
  public void FWm() {
    this.Dne = new yMz(OdI.mrb, 0.5F, 0.0F);
    this.Dne = 1;
    this.FWm = true;
  }
  
  public chN Dne(float paramFloat1, float paramFloat2) {
    // Byte code:
    //   0: ldc 10518688
    //   2: istore_3
    //   3: fload_1
    //   4: ldc 3.1415927
    //   6: fmul
    //   7: fconst_2
    //   8: fmul
    //   9: invokestatic FWm : (F)F
    //   12: fconst_2
    //   13: fmul
    //   14: ldc 0.5
    //   16: fadd
    //   17: fstore #4
    //   19: fload #4
    //   21: fconst_0
    //   22: fcmpg
    //   23: ifge -> 29
    //   26: fconst_0
    //   27: fstore #4
    //   29: fload #4
    //   31: fconst_1
    //   32: fcmpl
    //   33: ifle -> 39
    //   36: fconst_1
    //   37: fstore #4
    //   39: iload_3
    //   40: bipush #16
    //   42: ishr
    //   43: sipush #255
    //   46: iand
    //   47: i2f
    //   48: ldc 255.0
    //   50: fdiv
    //   51: fstore #5
    //   53: iload_3
    //   54: bipush #8
    //   56: ishr
    //   57: sipush #255
    //   60: iand
    //   61: i2f
    //   62: ldc 255.0
    //   64: fdiv
    //   65: fstore #6
    //   67: iload_3
    //   68: sipush #255
    //   71: iand
    //   72: i2f
    //   73: ldc 255.0
    //   75: fdiv
    //   76: fstore #7
    //   78: fload #5
    //   80: fload #4
    //   82: fconst_0
    //   83: fmul
    //   84: ldc 0.15
    //   86: fadd
    //   87: fmul
    //   88: fstore #5
    //   90: fload #6
    //   92: fload #4
    //   94: fconst_0
    //   95: fmul
    //   96: ldc 0.15
    //   98: fadd
    //   99: fmul
    //   100: fstore #6
    //   102: fload #7
    //   104: fload #4
    //   106: fconst_0
    //   107: fmul
    //   108: ldc 0.15
    //   110: fadd
    //   111: fmul
    //   112: fstore #7
    //   114: aload_0
    //   115: getfield Dne : LQnq;
    //   118: invokevirtual Dne : ()LziS;
    //   121: fload #5
    //   123: f2d
    //   124: fload #6
    //   126: f2d
    //   127: fload #7
    //   129: f2d
    //   130: invokevirtual Dne : (DDD)LchN;
    //   133: areturn
  }
  
  public boolean Dne() {
    return false;
  }
  
  public float Dne() {
    return 8.0F;
  }
  
  static {
  
  }
  
  public boolean Dne(int paramInt1, int paramInt2) {
    // Byte code:
    //   0: aload_0
    //   1: getfield Dne : LQnq;
    //   4: iload_1
    //   5: iload_2
    //   6: invokevirtual Dne : (II)I
    //   9: istore_3
    //   10: iload_3
    //   11: ifne -> 18
    //   14: iconst_0
    //   15: goto -> 29
    //   18: getstatic zKP.Dne : [LzKP;
    //   21: iload_3
    //   22: aaload
    //   23: getfield Dne : LKFd;
    //   26: invokevirtual bzF : ()Z
    //   29: ireturn
  }
  
  public float[] Dne(float paramFloat1, float paramFloat2) {
    return null;
  }
  
  public boolean FWm() {
    return false;
  }
  
  public int Dne() {
    return 50;
  }
  
  public iSh Dne() {
    return new iSh(100, 50, 0);
  }
  
  public String Dne() {
    return "The End";
  }
}


/* Location:              C:\Users\fract\Downloads\ERROR422.jar!\TKg.class
 * Java compiler version: 8 (52.0)
 * JD-Core Version:       1.1.3
 */