public class uVe extends dEr {
  private final CNI Dne;
  
  private int Dne;
  
  public boolean Dne(zKP paramzKP) {
    return (paramzKP.FWm == zKP.vSL.FWm);
  }
  
  public boolean Dne(NMq paramNMq, Qnq paramQnq, int paramInt1, int paramInt2, int paramInt3, int paramInt4, FUH paramFUH) {
    if (zKP.Dne[paramInt1].Dne(paramQnq, paramInt2, paramInt3, paramInt4) != 0.0D)
      paramNMq.Dne(2, paramFUH); 
    return true;
  }
  
  public boolean Dne(NMq paramNMq, FUH paramFUH1, FUH paramFUH2) {
    paramNMq.Dne(1, paramFUH2);
    return true;
  }
  
  public boolean FWm() {
    return true;
  }
  
  public NMq Dne(NMq paramNMq, Qnq paramQnq, FiG paramFiG) {
    paramFiG.Dne(paramNMq, a_(paramNMq));
    return paramNMq;
  }
  
  public int FWm() {
    // Byte code:
    //   0: aload_0
    //   1: getfield Dne : LCNI;
    //   4: invokevirtual FWm : ()I
    //   7: ireturn
  }
  
  public uVe(int paramInt, CNI paramCNI) {
    super(paramInt);
    this.Dne = paramCNI;
    this.aFZ = 1;
    FWm(paramCNI.Dne());
    Dne(JcN.IjH);
    this.Dne = 4 + paramCNI.FWm();
  }
  
  public int Dne() {
    // Byte code:
    //   0: aload_0
    //   1: getfield Dne : LCNI;
    //   4: invokevirtual Qnq : ()I
    //   7: ireturn
  }
  
  public int a_(NMq paramNMq) {
    return 72000;
  }
  
  public String Dne() {
    // Byte code:
    //   0: aload_0
    //   1: getfield Dne : LCNI;
    //   4: invokevirtual toString : ()Ljava/lang/String;
    //   7: areturn
  }
  
  public float Dne(NMq paramNMq, zKP paramzKP) {
    if (paramzKP.FWm == zKP.vSL.FWm)
      return 15.0F; 
    dNT dNT = paramzKP.Dne;
    return (dNT != KFd.XHL && dNT != KFd.Zpi && dNT != KFd.EyB && dNT != KFd.mrb && dNT != KFd.Fnk) ? 1.0F : 1.5F;
  }
  
  public een Dne(NMq paramNMq) {
    return een.Qnq;
  }
  
  public boolean Dne(NMq paramNMq1, NMq paramNMq2) {
    // Byte code:
    //   0: aload_0
    //   1: getfield Dne : LCNI;
    //   4: invokevirtual aFZ : ()I
    //   7: aload_2
    //   8: getfield bzF : I
    //   11: if_icmpne -> 18
    //   14: iconst_1
    //   15: goto -> 24
    //   18: aload_0
    //   19: aload_1
    //   20: aload_2
    //   21: invokespecial Dne : (LNMq;LNMq;)Z
    //   24: ireturn
  }
  
  public int Dne(sMa paramsMa) {
    return this.Dne;
  }
}


/* Location:              C:\Users\fract\Downloads\ERROR422.jar\\uVe.class
 * Java compiler version: 8 (52.0)
 * JD-Core Version:       1.1.3
 */