public class VQx extends cMv {
  private final float Dne;
  
  private final kQo Dne;
  
  private int bzF = 0;
  
  private int Qnq = 0;
  
  private int zGp = 0;
  
  private int aFZ = 0;
  
  private int Dne = 0;
  
  private int FWm = 0;
  
  private boolean bzF() {
    // Byte code:
    //   0: aload_0
    //   1: getfield Dne : LkQo;
    //   4: getfield IjH : D
    //   7: d2i
    //   8: istore_1
    //   9: ldc2_w 2.147483647E9
    //   12: dstore_2
    //   13: aload_0
    //   14: getfield Dne : LkQo;
    //   17: getfield div : D
    //   20: d2i
    //   21: bipush #8
    //   23: isub
    //   24: istore #4
    //   26: iload #4
    //   28: i2d
    //   29: aload_0
    //   30: getfield Dne : LkQo;
    //   33: getfield div : D
    //   36: ldc2_w 8.0
    //   39: dadd
    //   40: dcmpg
    //   41: ifge -> 170
    //   44: aload_0
    //   45: getfield Dne : LkQo;
    //   48: getfield mrb : D
    //   51: d2i
    //   52: bipush #8
    //   54: isub
    //   55: istore #5
    //   57: iload #5
    //   59: i2d
    //   60: aload_0
    //   61: getfield Dne : LkQo;
    //   64: getfield mrb : D
    //   67: ldc2_w 8.0
    //   70: dadd
    //   71: dcmpg
    //   72: ifge -> 164
    //   75: aload_0
    //   76: aload_0
    //   77: getfield Dne : LkQo;
    //   80: getfield Dne : LQnq;
    //   83: iload #4
    //   85: iload_1
    //   86: iload #5
    //   88: invokespecial Dne : (LQnq;III)Z
    //   91: ifeq -> 158
    //   94: aload_0
    //   95: getfield Dne : LkQo;
    //   98: getfield Dne : LQnq;
    //   101: iload #4
    //   103: iload_1
    //   104: iconst_1
    //   105: iadd
    //   106: iload #5
    //   108: invokevirtual Dne : (III)Z
    //   111: ifeq -> 158
    //   114: aload_0
    //   115: getfield Dne : LkQo;
    //   118: iload #4
    //   120: i2d
    //   121: iload_1
    //   122: i2d
    //   123: iload #5
    //   125: i2d
    //   126: invokevirtual Dne : (DDD)D
    //   129: dstore #6
    //   131: dload #6
    //   133: dload_2
    //   134: dcmpg
    //   135: ifge -> 158
    //   138: aload_0
    //   139: iload #4
    //   141: putfield Qnq : I
    //   144: aload_0
    //   145: iload_1
    //   146: putfield aFZ : I
    //   149: aload_0
    //   150: iload #5
    //   152: putfield zGp : I
    //   155: dload #6
    //   157: dstore_2
    //   158: iinc #5, 1
    //   161: goto -> 57
    //   164: iinc #4, 1
    //   167: goto -> 26
    //   170: dload_2
    //   171: ldc2_w 2.147483647E9
    //   174: dcmpg
    //   175: ifge -> 182
    //   178: iconst_1
    //   179: goto -> 183
    //   182: iconst_0
    //   183: ireturn
  }
  
  public void Dne() {
    // Byte code:
    //   0: aload_0
    //   1: getfield Dne : LkQo;
    //   4: invokevirtual Dne : ()LKFZ;
    //   7: aload_0
    //   8: getfield Qnq : I
    //   11: i2f
    //   12: f2d
    //   13: ldc2_w 0.5
    //   16: dadd
    //   17: aload_0
    //   18: getfield aFZ : I
    //   21: iconst_1
    //   22: iadd
    //   23: i2d
    //   24: aload_0
    //   25: getfield zGp : I
    //   28: i2f
    //   29: f2d
    //   30: ldc2_w 0.5
    //   33: dadd
    //   34: aload_0
    //   35: getfield Dne : F
    //   38: invokevirtual Dne : (DDDF)Z
    //   41: pop
    //   42: aload_0
    //   43: iconst_0
    //   44: putfield Dne : I
    //   47: aload_0
    //   48: iconst_0
    //   49: putfield FWm : I
    //   52: aload_0
    //   53: aload_0
    //   54: getfield Dne : LkQo;
    //   57: invokevirtual Dne : ()Ljava/util/Random;
    //   60: aload_0
    //   61: getfield Dne : LkQo;
    //   64: invokevirtual Dne : ()Ljava/util/Random;
    //   67: sipush #1200
    //   70: invokevirtual nextInt : (I)I
    //   73: sipush #1200
    //   76: iadd
    //   77: invokevirtual nextInt : (I)I
    //   80: sipush #1200
    //   83: iadd
    //   84: putfield bzF : I
    //   87: aload_0
    //   88: getfield Dne : LkQo;
    //   91: invokevirtual Dne : ()LHAo;
    //   94: iconst_0
    //   95: invokevirtual Dne : (Z)V
    //   98: return
  }
  
  public void FWm() {
    // Byte code:
    //   0: aload_0
    //   1: getfield Dne : LkQo;
    //   4: iconst_0
    //   5: invokevirtual XHL : (Z)V
    //   8: return
  }
  
  public boolean Dne() {
    // Byte code:
    //   0: aload_0
    //   1: getfield Dne : LkQo;
    //   4: invokevirtual LVR : ()Z
    //   7: ifeq -> 48
    //   10: aload_0
    //   11: getfield Dne : LkQo;
    //   14: invokevirtual ICU : ()Z
    //   17: ifne -> 48
    //   20: aload_0
    //   21: getfield Dne : LkQo;
    //   24: invokevirtual Dne : ()Ljava/util/Random;
    //   27: invokevirtual nextDouble : ()D
    //   30: ldc2_w 0.006500000134110451
    //   33: dcmpg
    //   34: ifgt -> 48
    //   37: aload_0
    //   38: invokespecial bzF : ()Z
    //   41: ifeq -> 48
    //   44: iconst_1
    //   45: goto -> 49
    //   48: iconst_0
    //   49: ireturn
  }
  
  public void bzF() {
    // Byte code:
    //   0: aload_0
    //   1: dup
    //   2: getfield Dne : I
    //   5: iconst_1
    //   6: iadd
    //   7: putfield Dne : I
    //   10: aload_0
    //   11: getfield Dne : LkQo;
    //   14: invokevirtual Dne : ()LHAo;
    //   17: iconst_0
    //   18: invokevirtual Dne : (Z)V
    //   21: aload_0
    //   22: getfield Dne : LkQo;
    //   25: aload_0
    //   26: getfield Qnq : I
    //   29: i2d
    //   30: aload_0
    //   31: getfield aFZ : I
    //   34: iconst_1
    //   35: iadd
    //   36: i2d
    //   37: aload_0
    //   38: getfield zGp : I
    //   41: i2d
    //   42: invokevirtual Dne : (DDD)D
    //   45: dconst_1
    //   46: dcmpl
    //   47: ifle -> 113
    //   50: aload_0
    //   51: getfield Dne : LkQo;
    //   54: iconst_0
    //   55: invokevirtual XHL : (Z)V
    //   58: aload_0
    //   59: getfield Dne : LkQo;
    //   62: invokevirtual Dne : ()LKFZ;
    //   65: aload_0
    //   66: getfield Qnq : I
    //   69: i2f
    //   70: f2d
    //   71: ldc2_w 0.5
    //   74: dadd
    //   75: aload_0
    //   76: getfield aFZ : I
    //   79: iconst_1
    //   80: iadd
    //   81: i2d
    //   82: aload_0
    //   83: getfield zGp : I
    //   86: i2f
    //   87: f2d
    //   88: ldc2_w 0.5
    //   91: dadd
    //   92: aload_0
    //   93: getfield Dne : F
    //   96: invokevirtual Dne : (DDDF)Z
    //   99: pop
    //   100: aload_0
    //   101: dup
    //   102: getfield FWm : I
    //   105: iconst_1
    //   106: iadd
    //   107: putfield FWm : I
    //   110: goto -> 144
    //   113: aload_0
    //   114: getfield Dne : LkQo;
    //   117: invokevirtual ICU : ()Z
    //   120: ifne -> 134
    //   123: aload_0
    //   124: getfield Dne : LkQo;
    //   127: iconst_1
    //   128: invokevirtual XHL : (Z)V
    //   131: goto -> 144
    //   134: aload_0
    //   135: dup
    //   136: getfield FWm : I
    //   139: iconst_1
    //   140: isub
    //   141: putfield FWm : I
    //   144: return
  }
  
  private boolean Dne(Qnq paramQnq, int paramInt1, int paramInt2, int paramInt3) {
    int i = paramQnq.Dne(paramInt1, paramInt2, paramInt3);
    int j = paramQnq.bzF(paramInt1, paramInt2, paramInt3);
    if (i == ((gHK)zKP.Dne).FWm) {
      GON gON = (GON)paramQnq.Dne(paramInt1, paramInt2, paramInt3);
      if (gON.Dne < 1)
        return true; 
    } else {
      if (i == zKP.qrB.FWm)
        return true; 
      if (i == zKP.FfS.FWm && !rTW.Dne(j))
        return true; 
    } 
    return false;
  }
  
  public VQx(kQo paramkQo, float paramFloat) {
    this.Dne = paramkQo;
    this.Dne = paramFloat;
    Dne(5);
  }
  
  public boolean FWm() {
    return (this.Dne <= this.bzF && this.FWm <= 60 && Dne((Qnq)this.Dne.Dne, this.Qnq, this.aFZ, this.zGp));
  }
}


/* Location:              C:\Users\fract\Downloads\ERROR422.jar!\VQx.class
 * Java compiler version: 8 (52.0)
 * JD-Core Version:       1.1.3
 */