public class vSE implements IjH {
  private RAN Dne;
  
  private Jwh Dne;
  
  public void FWm(int paramInt1, int paramInt2, int paramInt3) {}
  
  public vSE(Jwh paramJwh, RAN paramRAN) {
    this.Dne = paramJwh;
    this.Dne = (Jwh)paramRAN;
  }
  
  public void Dne(String paramString, int paramInt1, int paramInt2, int paramInt3) {}
  
  public void Dne(int paramInt1, int paramInt2, int paramInt3) {
    this.Dne.Dne().Dne(paramInt1, paramInt2, paramInt3);
  }
  
  public void Dne(FiG paramFiG, int paramInt1, int paramInt2, int paramInt3, int paramInt4, int paramInt5) {
    this.Dne.Dne().Dne(paramFiG, paramInt2, paramInt3, paramInt4, 64.0D, ((Jik)((RAN)this.Dne).Dne).Dne, new wwJ(paramInt1, paramInt2, paramInt3, paramInt4, paramInt5, false));
  }
  
  public void Dne(String paramString, double paramDouble1, double paramDouble2, double paramDouble3, float paramFloat1, float paramFloat2) {
    this.Dne.Dne().Dne(paramDouble1, paramDouble2, paramDouble3, (paramFloat1 > 1.0F) ? (16.0F * paramFloat1) : 16.0D, ((Jik)((RAN)this.Dne).Dne).Dne, new AQV(paramString, paramDouble1, paramDouble2, paramDouble3, paramFloat1, paramFloat2));
  }
  
  public void Dne(FiG paramFiG, String paramString, double paramDouble1, double paramDouble2, double paramDouble3, float paramFloat1, float paramFloat2) {
    this.Dne.Dne().Dne(paramFiG, paramDouble1, paramDouble2, paramDouble3, (paramFloat1 > 1.0F) ? (16.0F * paramFloat1) : 16.0D, ((Jik)((RAN)this.Dne).Dne).Dne, new AQV(paramString, paramDouble1, paramDouble2, paramDouble3, paramFloat1, paramFloat2));
  }
  
  public void Dne(int paramInt1, int paramInt2, int paramInt3, int paramInt4, int paramInt5, int paramInt6) {}
  
  public void FWm(sMa paramsMa) {
    this.Dne.Dne().FWm(paramsMa);
  }
  
  public void Dne(sMa paramsMa) {
    this.Dne.Dne().Dne(paramsMa);
  }
  
  public void FWm(int paramInt1, int paramInt2, int paramInt3, int paramInt4, int paramInt5) {
    // Byte code:
    //   0: aload_0
    //   1: getfield Dne : LJwh;
    //   4: invokevirtual Dne : ()LdzN;
    //   7: getfield Dne : Ljava/util/List;
    //   10: invokeinterface iterator : ()Ljava/util/Iterator;
    //   15: astore #6
    //   17: aload #6
    //   19: invokeinterface hasNext : ()Z
    //   24: ifeq -> 145
    //   27: aload #6
    //   29: invokeinterface next : ()Ljava/lang/Object;
    //   34: checkcast PJQ
    //   37: astore #7
    //   39: aload #7
    //   41: ifnull -> 142
    //   44: aload #7
    //   46: getfield Dne : LQnq;
    //   49: aload_0
    //   50: getfield Dne : LRAN;
    //   53: if_acmpne -> 142
    //   56: aload #7
    //   58: getfield aFZ : I
    //   61: iload_1
    //   62: if_icmpeq -> 142
    //   65: iload_2
    //   66: i2d
    //   67: aload #7
    //   69: getfield div : D
    //   72: dsub
    //   73: dstore #8
    //   75: iload_3
    //   76: i2d
    //   77: aload #7
    //   79: getfield IjH : D
    //   82: dsub
    //   83: dstore #10
    //   85: iload #4
    //   87: i2d
    //   88: aload #7
    //   90: getfield mrb : D
    //   93: dsub
    //   94: dstore #12
    //   96: dload #8
    //   98: dload #8
    //   100: dmul
    //   101: dload #10
    //   103: dload #10
    //   105: dmul
    //   106: dadd
    //   107: dload #12
    //   109: dload #12
    //   111: dmul
    //   112: dadd
    //   113: ldc2_w 1024.0
    //   116: dcmpg
    //   117: ifge -> 142
    //   120: aload #7
    //   122: getfield Dne : LTnv;
    //   125: new bEj
    //   128: dup
    //   129: iload_1
    //   130: iload_2
    //   131: iload_3
    //   132: iload #4
    //   134: iload #5
    //   136: invokespecial <init> : (IIIII)V
    //   139: invokevirtual Dne : (LNER;)V
    //   142: goto -> 17
    //   145: return
  }
  
  public void Dne(String paramString, double paramDouble1, double paramDouble2, double paramDouble3, double paramDouble4, double paramDouble5, double paramDouble6) {}
  
  public void Dne(int paramInt1, int paramInt2, int paramInt3, int paramInt4, int paramInt5) {
    this.Dne.Dne().Dne(new wwJ(paramInt1, paramInt2, paramInt3, paramInt4, paramInt5, true));
  }
}


/* Location:              C:\Users\fract\Downloads\ERROR422.jar!\vSE.class
 * Java compiler version: 8 (52.0)
 * JD-Core Version:       1.1.3
 */