final class vYb extends tip {
  private final tip Dne = new tip();
  
  public NMq FWm(Cwq paramCwq, NMq paramNMq) {
    // Byte code:
    //   0: aload_1
    //   1: invokeinterface Qnq : ()I
    //   6: invokestatic Dne : (I)LHQH;
    //   9: astore_3
    //   10: aload_1
    //   11: invokeinterface Dne : ()LQnq;
    //   16: astore #4
    //   18: aload_1
    //   19: invokeinterface Dne : ()D
    //   24: aload_3
    //   25: invokevirtual Dne : ()I
    //   28: i2f
    //   29: ldc 1.125
    //   31: fmul
    //   32: f2d
    //   33: dadd
    //   34: dstore #5
    //   36: aload_1
    //   37: invokeinterface FWm : ()D
    //   42: aload_3
    //   43: invokevirtual FWm : ()I
    //   46: i2f
    //   47: ldc 1.125
    //   49: fmul
    //   50: f2d
    //   51: dadd
    //   52: dstore #7
    //   54: aload_1
    //   55: invokeinterface bzF : ()D
    //   60: aload_3
    //   61: invokevirtual bzF : ()I
    //   64: i2f
    //   65: ldc 1.125
    //   67: fmul
    //   68: f2d
    //   69: dadd
    //   70: dstore #9
    //   72: aload_1
    //   73: invokeinterface Dne : ()I
    //   78: aload_3
    //   79: invokevirtual Dne : ()I
    //   82: iadd
    //   83: istore #11
    //   85: aload_1
    //   86: invokeinterface FWm : ()I
    //   91: aload_3
    //   92: invokevirtual FWm : ()I
    //   95: iadd
    //   96: istore #12
    //   98: aload_1
    //   99: invokeinterface bzF : ()I
    //   104: aload_3
    //   105: invokevirtual bzF : ()I
    //   108: iadd
    //   109: istore #13
    //   111: aload #4
    //   113: iload #11
    //   115: iload #12
    //   117: iload #13
    //   119: invokevirtual Dne : (III)LKFd;
    //   122: astore #14
    //   124: getstatic KFd.div : LKFd;
    //   127: aload #14
    //   129: invokevirtual equals : (Ljava/lang/Object;)Z
    //   132: ifeq -> 141
    //   135: dconst_1
    //   136: dstore #15
    //   138: goto -> 187
    //   141: getstatic KFd.Dne : LKFd;
    //   144: aload #14
    //   146: invokevirtual equals : (Ljava/lang/Object;)Z
    //   149: ifeq -> 174
    //   152: getstatic KFd.div : LKFd;
    //   155: aload #4
    //   157: iload #11
    //   159: iload #12
    //   161: iconst_1
    //   162: isub
    //   163: iload #13
    //   165: invokevirtual Dne : (III)LKFd;
    //   168: invokevirtual equals : (Ljava/lang/Object;)Z
    //   171: ifne -> 184
    //   174: aload_0
    //   175: getfield Dne : Ltip;
    //   178: aload_1
    //   179: aload_2
    //   180: invokevirtual Dne : (LCwq;LNMq;)LNMq;
    //   183: areturn
    //   184: dconst_0
    //   185: dstore #15
    //   187: new iMX
    //   190: dup
    //   191: aload #4
    //   193: dload #5
    //   195: dload #7
    //   197: dload #15
    //   199: dadd
    //   200: dload #9
    //   202: invokespecial <init> : (LQnq;DDD)V
    //   205: astore #17
    //   207: aload #4
    //   209: aload #17
    //   211: invokevirtual FWm : (LsMa;)Z
    //   214: pop
    //   215: aload_2
    //   216: iconst_1
    //   217: invokevirtual Dne : (I)LNMq;
    //   220: pop
    //   221: aload_2
    //   222: areturn
  }
  
  protected void Dne(Cwq paramCwq) {
    paramCwq.Dne().Qnq(1000, paramCwq.Dne(), paramCwq.FWm(), paramCwq.bzF(), 0);
  }
}


/* Location:              C:\Users\fract\Downloads\ERROR422.jar!\vYb.class
 * Java compiler version: 8 (52.0)
 * JD-Core Version:       1.1.3
 */