public class wao extends tkl implements vjn {
  protected int kGO() {
    return dEr.iNQ.Qnq;
  }
  
  public int Dne() {
    return 4;
  }
  
  public wao(Qnq paramQnq) {
    // Byte code:
    //   0: aload_0
    //   1: aload_1
    //   2: invokespecial <init> : (LQnq;)V
    //   5: aload_0
    //   6: ldc '/mob/snowman.png'
    //   8: putfield bzF : Ljava/lang/String;
    //   11: aload_0
    //   12: ldc 0.4
    //   14: ldc 1.8
    //   16: invokevirtual Dne : (FF)V
    //   19: aload_0
    //   20: invokevirtual Dne : ()LKFZ;
    //   23: iconst_1
    //   24: invokevirtual Dne : (Z)V
    //   27: aload_0
    //   28: getfield Dne : LOKo;
    //   31: iconst_1
    //   32: new Auu
    //   35: dup
    //   36: aload_0
    //   37: ldc 0.25
    //   39: bipush #20
    //   41: ldc 10.0
    //   43: invokespecial <init> : (Lvjn;FIF)V
    //   46: invokevirtual Dne : (ILcMv;)V
    //   49: aload_0
    //   50: getfield Dne : LOKo;
    //   53: iconst_2
    //   54: new IBw
    //   57: dup
    //   58: aload_0
    //   59: ldc 0.2
    //   61: invokespecial <init> : (LkSJ;F)V
    //   64: invokevirtual Dne : (ILcMv;)V
    //   67: aload_0
    //   68: getfield Dne : LOKo;
    //   71: iconst_3
    //   72: new yws
    //   75: dup
    //   76: aload_0
    //   77: ldc FiG
    //   79: ldc 6.0
    //   81: invokespecial <init> : (LFUH;Ljava/lang/Class;F)V
    //   84: invokevirtual Dne : (ILcMv;)V
    //   87: aload_0
    //   88: getfield Dne : LOKo;
    //   91: iconst_4
    //   92: new cHg
    //   95: dup
    //   96: aload_0
    //   97: invokespecial <init> : (LFUH;)V
    //   100: invokevirtual Dne : (ILcMv;)V
    //   103: aload_0
    //   104: getfield FWm : LOKo;
    //   107: iconst_1
    //   108: new AmF
    //   111: dup
    //   112: aload_0
    //   113: ldc FUH
    //   115: ldc 16.0
    //   117: iconst_0
    //   118: iconst_1
    //   119: iconst_0
    //   120: getstatic ZFz.Dne : LpUe;
    //   123: invokespecial <init> : (LFUH;Ljava/lang/Class;FIZZLpUe;)V
    //   126: invokevirtual Dne : (ILcMv;)V
    //   129: return
  }
  
  public boolean tgc() {
    return true;
  }
  
  public void Dne(FUH paramFUH, float paramFloat) {
    // Byte code:
    //   0: new KXX
    //   3: dup
    //   4: aload_0
    //   5: getfield Dne : LQnq;
    //   8: aload_0
    //   9: invokespecial <init> : (LQnq;LFUH;)V
    //   12: astore_3
    //   13: aload_1
    //   14: getfield div : D
    //   17: aload_0
    //   18: getfield div : D
    //   21: dsub
    //   22: dstore #4
    //   24: aload_1
    //   25: getfield IjH : D
    //   28: aload_1
    //   29: invokevirtual c_ : ()F
    //   32: f2d
    //   33: dadd
    //   34: ldc2_w 1.100000023841858
    //   37: dsub
    //   38: aload_3
    //   39: getfield IjH : D
    //   42: dsub
    //   43: dstore #6
    //   45: aload_1
    //   46: getfield mrb : D
    //   49: aload_0
    //   50: getfield mrb : D
    //   53: dsub
    //   54: dstore #8
    //   56: dload #4
    //   58: dload #4
    //   60: dmul
    //   61: dload #8
    //   63: dload #8
    //   65: dmul
    //   66: dadd
    //   67: invokestatic Dne : (D)F
    //   70: ldc 0.2
    //   72: fmul
    //   73: fstore #10
    //   75: aload_3
    //   76: dload #4
    //   78: dload #6
    //   80: fload #10
    //   82: f2d
    //   83: dadd
    //   84: dload #8
    //   86: ldc 1.6
    //   88: ldc 12.0
    //   90: invokevirtual bzF : (DDDFF)V
    //   93: aload_0
    //   94: ldc 'random.bow'
    //   96: fconst_1
    //   97: fconst_1
    //   98: aload_0
    //   99: invokevirtual Dne : ()Ljava/util/Random;
    //   102: invokevirtual nextFloat : ()F
    //   105: ldc 0.4
    //   107: fmul
    //   108: ldc 0.8
    //   110: fadd
    //   111: fdiv
    //   112: invokevirtual Dne : (Ljava/lang/String;FF)V
    //   115: aload_0
    //   116: getfield Dne : LQnq;
    //   119: aload_3
    //   120: invokevirtual FWm : (LsMa;)Z
    //   123: pop
    //   124: return
  }
  
  static {
  
  }
  
  public void IjH() {
    // Byte code:
    //   0: aload_0
    //   1: invokespecial IjH : ()V
    //   4: aload_0
    //   5: invokevirtual XHL : ()Z
    //   8: ifeq -> 20
    //   11: aload_0
    //   12: getstatic zBn.aFZ : LzBn;
    //   15: iconst_1
    //   16: invokevirtual Dne : (LzBn;I)Z
    //   19: pop
    //   20: aload_0
    //   21: getfield div : D
    //   24: invokestatic FWm : (D)I
    //   27: istore_1
    //   28: aload_0
    //   29: getfield mrb : D
    //   32: invokestatic FWm : (D)I
    //   35: istore_2
    //   36: aload_0
    //   37: getfield Dne : LQnq;
    //   40: iload_1
    //   41: iload_2
    //   42: invokevirtual Dne : (II)LOdI;
    //   45: invokevirtual bzF : ()F
    //   48: fconst_1
    //   49: fcmpl
    //   50: ifle -> 62
    //   53: aload_0
    //   54: getstatic zBn.FWm : LzBn;
    //   57: iconst_1
    //   58: invokevirtual Dne : (LzBn;I)Z
    //   61: pop
    //   62: iconst_0
    //   63: istore_1
    //   64: iload_1
    //   65: iconst_4
    //   66: if_icmpge -> 196
    //   69: aload_0
    //   70: getfield div : D
    //   73: iload_1
    //   74: iconst_2
    //   75: irem
    //   76: iconst_2
    //   77: imul
    //   78: iconst_1
    //   79: isub
    //   80: i2f
    //   81: ldc 0.25
    //   83: fmul
    //   84: f2d
    //   85: dadd
    //   86: invokestatic FWm : (D)I
    //   89: istore_2
    //   90: aload_0
    //   91: getfield IjH : D
    //   94: invokestatic FWm : (D)I
    //   97: istore_3
    //   98: aload_0
    //   99: getfield mrb : D
    //   102: iload_1
    //   103: iconst_2
    //   104: idiv
    //   105: iconst_2
    //   106: irem
    //   107: iconst_2
    //   108: imul
    //   109: iconst_1
    //   110: isub
    //   111: i2f
    //   112: ldc 0.25
    //   114: fmul
    //   115: f2d
    //   116: dadd
    //   117: invokestatic FWm : (D)I
    //   120: istore #4
    //   122: aload_0
    //   123: getfield Dne : LQnq;
    //   126: iload_2
    //   127: iload_3
    //   128: iload #4
    //   130: invokevirtual Dne : (III)I
    //   133: ifne -> 190
    //   136: aload_0
    //   137: getfield Dne : LQnq;
    //   140: iload_2
    //   141: iload #4
    //   143: invokevirtual Dne : (II)LOdI;
    //   146: invokevirtual bzF : ()F
    //   149: ldc 0.8
    //   151: fcmpg
    //   152: ifge -> 190
    //   155: getstatic zKP.EwP : LzKP;
    //   158: aload_0
    //   159: getfield Dne : LQnq;
    //   162: iload_2
    //   163: iload_3
    //   164: iload #4
    //   166: invokevirtual Dne : (LQnq;III)Z
    //   169: ifeq -> 190
    //   172: aload_0
    //   173: getfield Dne : LQnq;
    //   176: iload_2
    //   177: iload_3
    //   178: iload #4
    //   180: getstatic zKP.EwP : LzKP;
    //   183: getfield FWm : I
    //   186: invokevirtual FWm : (IIII)Z
    //   189: pop
    //   190: iinc #1, 1
    //   193: goto -> 64
    //   196: return
  }
  
  protected void Dne(boolean paramBoolean, int paramInt) {
    // Byte code:
    //   0: aload_0
    //   1: getfield Dne : Ljava/util/Random;
    //   4: bipush #16
    //   6: invokevirtual nextInt : (I)I
    //   9: istore_3
    //   10: iconst_0
    //   11: istore #4
    //   13: iload #4
    //   15: iload_3
    //   16: if_icmpge -> 37
    //   19: aload_0
    //   20: getstatic dEr.iNQ : LdEr;
    //   23: getfield Qnq : I
    //   26: iconst_1
    //   27: invokevirtual Dne : (II)LJiM;
    //   30: pop
    //   31: iinc #4, 1
    //   34: goto -> 13
    //   37: return
  }
}


/* Location:              C:\Users\fract\Downloads\ERROR422.jar!\wao.class
 * Java compiler version: 8 (52.0)
 * JD-Core Version:       1.1.3
 */