class wDe extends ghN {
  int[] Dne;
  
  Object[] Dne;
  
  float[][] Dne = (float[][])null;
  
  static int Dne = 0;
  
  int[] FWm;
  
  void Dne(Lth paramLth, Object paramObject, qbC paramqbC) {
    ajq ajq = (ajq)paramObject;
    if (ajq.Dne > true) {
      paramqbC.Dne(1, 1);
      paramqbC.Dne(ajq.Dne - 1, 4);
    } else {
      paramqbC.Dne(0, 1);
    } 
    if (ajq.FWm > 0) {
      paramqbC.Dne(1, 1);
      paramqbC.Dne(ajq.FWm - 1, 8);
      for (byte b1 = 0; b1 < ajq.FWm; b1++) {
        paramqbC.Dne(ajq.zGp[b1], xHL.FWm(paramLth.FWm));
        paramqbC.Dne(ajq.DyG[b1], xHL.FWm(paramLth.FWm));
      } 
    } else {
      paramqbC.Dne(0, 1);
    } 
    paramqbC.Dne(0, 2);
    if (ajq.Dne > true)
      for (byte b1 = 0; b1 < paramLth.FWm; b1++)
        paramqbC.Dne(ajq.Dne[b1], 4);  
    for (byte b = 0; b < ajq.Dne; b++) {
      paramqbC.Dne(ajq.FWm[b], 8);
      paramqbC.Dne(ajq.bzF[b], 8);
      paramqbC.Dne(ajq.Qnq[b], 8);
    } 
  }
  
  synchronized int Dne(MOU paramMOU, Object paramObject) {
    // Byte code:
    //   0: aload_1
    //   1: getfield Dne : LAOl;
    //   4: astore_3
    //   5: aload_3
    //   6: getfield Dne : LLth;
    //   9: astore #4
    //   11: aload_2
    //   12: checkcast ZPy
    //   15: astore #5
    //   17: aload #5
    //   19: getfield Dne : Lajq;
    //   22: astore #6
    //   24: aload #5
    //   26: getfield Dne : LXEH;
    //   29: astore #7
    //   31: aload_1
    //   32: aload #4
    //   34: getfield Dne : [I
    //   37: aload_1
    //   38: getfield FWm : I
    //   41: iaload
    //   42: dup_x1
    //   43: putfield Qnq : I
    //   46: istore #8
    //   48: aload_3
    //   49: getfield Dne : [[[[[F
    //   52: aload_1
    //   53: getfield FWm : I
    //   56: aaload
    //   57: aload_1
    //   58: getfield Dne : I
    //   61: aaload
    //   62: aload_1
    //   63: getfield bzF : I
    //   66: aaload
    //   67: aload #7
    //   69: getfield FWm : I
    //   72: aaload
    //   73: astore #9
    //   75: aload_0
    //   76: getfield Dne : [[F
    //   79: ifnull -> 95
    //   82: aload_0
    //   83: getfield Dne : [[F
    //   86: arraylength
    //   87: aload #4
    //   89: getfield FWm : I
    //   92: if_icmpge -> 141
    //   95: aload_0
    //   96: aload #4
    //   98: getfield FWm : I
    //   101: anewarray [F
    //   104: putfield Dne : [[F
    //   107: aload_0
    //   108: aload #4
    //   110: getfield FWm : I
    //   113: newarray int
    //   115: putfield FWm : [I
    //   118: aload_0
    //   119: aload #4
    //   121: getfield FWm : I
    //   124: newarray int
    //   126: putfield Dne : [I
    //   129: aload_0
    //   130: aload #4
    //   132: getfield FWm : I
    //   135: anewarray java/lang/Object
    //   138: putfield Dne : [Ljava/lang/Object;
    //   141: iconst_0
    //   142: istore #10
    //   144: iload #10
    //   146: aload #4
    //   148: getfield FWm : I
    //   151: if_icmpge -> 266
    //   154: aload_1
    //   155: getfield Dne : [[F
    //   158: iload #10
    //   160: aaload
    //   161: astore #11
    //   163: aload #6
    //   165: getfield Dne : [I
    //   168: iload #10
    //   170: iaload
    //   171: istore #12
    //   173: aload_0
    //   174: getfield Dne : [Ljava/lang/Object;
    //   177: iload #10
    //   179: aload #5
    //   181: getfield Dne : [LWoN;
    //   184: iload #12
    //   186: aaload
    //   187: aload_1
    //   188: aload #5
    //   190: getfield FWm : [Ljava/lang/Object;
    //   193: iload #12
    //   195: aaload
    //   196: aload_0
    //   197: getfield Dne : [Ljava/lang/Object;
    //   200: iload #10
    //   202: aaload
    //   203: invokevirtual Dne : (LMOU;Ljava/lang/Object;Ljava/lang/Object;)Ljava/lang/Object;
    //   206: aastore
    //   207: aload_0
    //   208: getfield Dne : [Ljava/lang/Object;
    //   211: iload #10
    //   213: aaload
    //   214: ifnull -> 228
    //   217: aload_0
    //   218: getfield FWm : [I
    //   221: iload #10
    //   223: iconst_1
    //   224: iastore
    //   225: goto -> 236
    //   228: aload_0
    //   229: getfield FWm : [I
    //   232: iload #10
    //   234: iconst_0
    //   235: iastore
    //   236: iconst_0
    //   237: istore #13
    //   239: iload #13
    //   241: iload #8
    //   243: iconst_2
    //   244: idiv
    //   245: if_icmpge -> 260
    //   248: aload #11
    //   250: iload #13
    //   252: fconst_0
    //   253: fastore
    //   254: iinc #13, 1
    //   257: goto -> 239
    //   260: iinc #10, 1
    //   263: goto -> 144
    //   266: iconst_0
    //   267: istore #10
    //   269: iload #10
    //   271: aload #6
    //   273: getfield FWm : I
    //   276: if_icmpge -> 345
    //   279: aload_0
    //   280: getfield FWm : [I
    //   283: aload #6
    //   285: getfield zGp : [I
    //   288: iload #10
    //   290: iaload
    //   291: iaload
    //   292: ifne -> 311
    //   295: aload_0
    //   296: getfield FWm : [I
    //   299: aload #6
    //   301: getfield DyG : [I
    //   304: iload #10
    //   306: iaload
    //   307: iaload
    //   308: ifeq -> 339
    //   311: aload_0
    //   312: getfield FWm : [I
    //   315: aload #6
    //   317: getfield zGp : [I
    //   320: iload #10
    //   322: iaload
    //   323: iconst_1
    //   324: iastore
    //   325: aload_0
    //   326: getfield FWm : [I
    //   329: aload #6
    //   331: getfield DyG : [I
    //   334: iload #10
    //   336: iaload
    //   337: iconst_1
    //   338: iastore
    //   339: iinc #10, 1
    //   342: goto -> 269
    //   345: iconst_0
    //   346: istore #10
    //   348: iload #10
    //   350: aload #6
    //   352: getfield Dne : I
    //   355: if_icmpge -> 476
    //   358: iconst_0
    //   359: istore #11
    //   361: iconst_0
    //   362: istore #12
    //   364: iload #12
    //   366: aload #4
    //   368: getfield FWm : I
    //   371: if_icmpge -> 439
    //   374: aload #6
    //   376: getfield Dne : [I
    //   379: iload #12
    //   381: iaload
    //   382: iload #10
    //   384: if_icmpne -> 433
    //   387: aload_0
    //   388: getfield FWm : [I
    //   391: iload #12
    //   393: iaload
    //   394: ifeq -> 408
    //   397: aload_0
    //   398: getfield Dne : [I
    //   401: iload #11
    //   403: iconst_1
    //   404: iastore
    //   405: goto -> 416
    //   408: aload_0
    //   409: getfield Dne : [I
    //   412: iload #11
    //   414: iconst_0
    //   415: iastore
    //   416: aload_0
    //   417: getfield Dne : [[F
    //   420: iload #11
    //   422: iinc #11, 1
    //   425: aload_1
    //   426: getfield Dne : [[F
    //   429: iload #12
    //   431: aaload
    //   432: aastore
    //   433: iinc #12, 1
    //   436: goto -> 364
    //   439: aload #5
    //   441: getfield Dne : [LbFq;
    //   444: iload #10
    //   446: aaload
    //   447: aload_1
    //   448: aload #5
    //   450: getfield Qnq : [Ljava/lang/Object;
    //   453: iload #10
    //   455: aaload
    //   456: aload_0
    //   457: getfield Dne : [[F
    //   460: aload_0
    //   461: getfield Dne : [I
    //   464: iload #11
    //   466: invokevirtual Dne : (LMOU;Ljava/lang/Object;[[F[II)I
    //   469: pop
    //   470: iinc #10, 1
    //   473: goto -> 348
    //   476: aload #6
    //   478: getfield FWm : I
    //   481: iconst_1
    //   482: isub
    //   483: istore #10
    //   485: iload #10
    //   487: iflt -> 656
    //   490: aload_1
    //   491: getfield Dne : [[F
    //   494: aload #6
    //   496: getfield zGp : [I
    //   499: iload #10
    //   501: iaload
    //   502: aaload
    //   503: astore #11
    //   505: aload_1
    //   506: getfield Dne : [[F
    //   509: aload #6
    //   511: getfield DyG : [I
    //   514: iload #10
    //   516: iaload
    //   517: aaload
    //   518: astore #12
    //   520: iconst_0
    //   521: istore #13
    //   523: iload #13
    //   525: iload #8
    //   527: iconst_2
    //   528: idiv
    //   529: if_icmpge -> 650
    //   532: aload #11
    //   534: iload #13
    //   536: faload
    //   537: fstore #14
    //   539: aload #12
    //   541: iload #13
    //   543: faload
    //   544: fstore #15
    //   546: fload #14
    //   548: fconst_0
    //   549: fcmpl
    //   550: ifle -> 600
    //   553: fload #15
    //   555: fconst_0
    //   556: fcmpl
    //   557: ifle -> 580
    //   560: aload #11
    //   562: iload #13
    //   564: fload #14
    //   566: fastore
    //   567: aload #12
    //   569: iload #13
    //   571: fload #14
    //   573: fload #15
    //   575: fsub
    //   576: fastore
    //   577: goto -> 644
    //   580: aload #12
    //   582: iload #13
    //   584: fload #14
    //   586: fastore
    //   587: aload #11
    //   589: iload #13
    //   591: fload #14
    //   593: fload #15
    //   595: fadd
    //   596: fastore
    //   597: goto -> 644
    //   600: fload #15
    //   602: fconst_0
    //   603: fcmpl
    //   604: ifle -> 627
    //   607: aload #11
    //   609: iload #13
    //   611: fload #14
    //   613: fastore
    //   614: aload #12
    //   616: iload #13
    //   618: fload #14
    //   620: fload #15
    //   622: fadd
    //   623: fastore
    //   624: goto -> 644
    //   627: aload #12
    //   629: iload #13
    //   631: fload #14
    //   633: fastore
    //   634: aload #11
    //   636: iload #13
    //   638: fload #14
    //   640: fload #15
    //   642: fsub
    //   643: fastore
    //   644: iinc #13, 1
    //   647: goto -> 523
    //   650: iinc #10, -1
    //   653: goto -> 485
    //   656: iconst_0
    //   657: istore #10
    //   659: iload #10
    //   661: aload #4
    //   663: getfield FWm : I
    //   666: if_icmpge -> 724
    //   669: aload_1
    //   670: getfield Dne : [[F
    //   673: iload #10
    //   675: aaload
    //   676: astore #11
    //   678: aload #6
    //   680: getfield Dne : [I
    //   683: iload #10
    //   685: iaload
    //   686: istore #12
    //   688: aload #5
    //   690: getfield Dne : [LWoN;
    //   693: iload #12
    //   695: aaload
    //   696: aload_1
    //   697: aload #5
    //   699: getfield FWm : [Ljava/lang/Object;
    //   702: iload #12
    //   704: aaload
    //   705: aload_0
    //   706: getfield Dne : [Ljava/lang/Object;
    //   709: iload #10
    //   711: aaload
    //   712: aload #11
    //   714: invokevirtual Dne : (LMOU;Ljava/lang/Object;Ljava/lang/Object;[F)I
    //   717: pop
    //   718: iinc #10, 1
    //   721: goto -> 659
    //   724: iconst_0
    //   725: istore #10
    //   727: iload #10
    //   729: aload #4
    //   731: getfield FWm : I
    //   734: if_icmpge -> 773
    //   737: aload_1
    //   738: getfield Dne : [[F
    //   741: iload #10
    //   743: aaload
    //   744: astore #11
    //   746: aload_3
    //   747: getfield Dne : [[Ljava/lang/Object;
    //   750: aload_1
    //   751: getfield FWm : I
    //   754: aaload
    //   755: iconst_0
    //   756: aaload
    //   757: checkcast Sti
    //   760: aload #11
    //   762: aload #11
    //   764: invokevirtual FWm : ([F[F)V
    //   767: iinc #10, 1
    //   770: goto -> 727
    //   773: iconst_0
    //   774: istore #10
    //   776: iload #10
    //   778: aload #4
    //   780: getfield FWm : I
    //   783: if_icmpge -> 865
    //   786: aload_1
    //   787: getfield Dne : [[F
    //   790: iload #10
    //   792: aaload
    //   793: astore #11
    //   795: aload_0
    //   796: getfield FWm : [I
    //   799: iload #10
    //   801: iaload
    //   802: ifeq -> 837
    //   805: iconst_0
    //   806: istore #12
    //   808: iload #12
    //   810: iload #8
    //   812: if_icmpge -> 834
    //   815: aload #11
    //   817: iload #12
    //   819: dup2
    //   820: faload
    //   821: aload #9
    //   823: iload #12
    //   825: faload
    //   826: fmul
    //   827: fastore
    //   828: iinc #12, 1
    //   831: goto -> 808
    //   834: goto -> 859
    //   837: iconst_0
    //   838: istore #12
    //   840: iload #12
    //   842: iload #8
    //   844: if_icmpge -> 859
    //   847: aload #11
    //   849: iload #12
    //   851: fconst_0
    //   852: fastore
    //   853: iinc #12, 1
    //   856: goto -> 840
    //   859: iinc #10, 1
    //   862: goto -> 776
    //   865: iconst_0
    //   866: ireturn
  }
  
  void Dne(Object paramObject) {}
  
  wDe() {
    this.Dne = null;
    this.FWm = null;
    this.Dne = null;
  }
  
  Object Dne(AOl paramAOl, XEH paramXEH, Object paramObject) {
    int i = paramAOl.Dne;
    ZPy zPy = new ZPy(this);
    float[][] arrayOfFloat = zPy.Dne = (float[][])paramObject;
    zPy.Dne = (float[][])paramXEH;
    zPy.Dne = (float[][])new Object[((ajq)arrayOfFloat).Dne];
    zPy.FWm = new Object[((ajq)arrayOfFloat).Dne];
    zPy.Qnq = new Object[((ajq)arrayOfFloat).Dne];
    zPy.Dne = (float[][])new qxf[((ajq)arrayOfFloat).Dne];
    zPy.Dne = (float[][])new WoN[((ajq)arrayOfFloat).Dne];
    zPy.Dne = (float[][])new bFq[((ajq)arrayOfFloat).Dne];
    for (byte b = 0; b < ((ajq)arrayOfFloat).Dne; b++) {
      int j = ((ajq)arrayOfFloat).FWm[b];
      int k = ((ajq)arrayOfFloat).bzF[b];
      int m = ((ajq)arrayOfFloat).Qnq[b];
      zPy.Dne[b] = (float[])qxf.Dne[i.bzF[j]];
      zPy.Dne[b] = (float[])zPy.Dne[b].Dne(paramAOl, paramXEH, i.FWm[j]);
      zPy.Dne[b] = (float[])WoN.Dne[i.Qnq[k]];
      zPy.FWm[b] = zPy.Dne[b].Dne(paramAOl, paramXEH, i.bzF[k]);
      zPy.Dne[b] = (float[])bFq.Dne[i.aFZ[m]];
      zPy.Qnq[b] = zPy.Dne[b].Dne(paramAOl, paramXEH, i.Qnq[m]);
    } 
    if (i.kGO == 0 || paramAOl.bzF != 0);
    zPy.Dne = (float[][])i.FWm;
    return zPy;
  }
  
  Object Dne(Lth paramLth, qbC paramqbC) {
    // Byte code:
    //   0: new ajq
    //   3: dup
    //   4: aload_0
    //   5: invokespecial <init> : (LwDe;)V
    //   8: astore_3
    //   9: aload_2
    //   10: iconst_1
    //   11: invokevirtual FWm : (I)I
    //   14: ifeq -> 31
    //   17: aload_3
    //   18: aload_2
    //   19: iconst_4
    //   20: invokevirtual FWm : (I)I
    //   23: iconst_1
    //   24: iadd
    //   25: putfield Dne : I
    //   28: goto -> 36
    //   31: aload_3
    //   32: iconst_1
    //   33: putfield Dne : I
    //   36: aload_2
    //   37: iconst_1
    //   38: invokevirtual FWm : (I)I
    //   41: ifeq -> 157
    //   44: aload_3
    //   45: aload_2
    //   46: bipush #8
    //   48: invokevirtual FWm : (I)I
    //   51: iconst_1
    //   52: iadd
    //   53: putfield FWm : I
    //   56: iconst_0
    //   57: istore #4
    //   59: iload #4
    //   61: aload_3
    //   62: getfield FWm : I
    //   65: if_icmpge -> 157
    //   68: aload_3
    //   69: getfield zGp : [I
    //   72: iload #4
    //   74: aload_2
    //   75: aload_1
    //   76: getfield FWm : I
    //   79: invokestatic FWm : (I)I
    //   82: invokevirtual FWm : (I)I
    //   85: dup_x2
    //   86: iastore
    //   87: istore #5
    //   89: aload_3
    //   90: getfield DyG : [I
    //   93: iload #4
    //   95: aload_2
    //   96: aload_1
    //   97: getfield FWm : I
    //   100: invokestatic FWm : (I)I
    //   103: invokevirtual FWm : (I)I
    //   106: dup_x2
    //   107: iastore
    //   108: istore #6
    //   110: iload #5
    //   112: iflt -> 145
    //   115: iload #6
    //   117: iflt -> 145
    //   120: iload #5
    //   122: iload #6
    //   124: if_icmpeq -> 145
    //   127: iload #5
    //   129: aload_1
    //   130: getfield FWm : I
    //   133: if_icmpge -> 145
    //   136: iload #6
    //   138: aload_1
    //   139: getfield FWm : I
    //   142: if_icmplt -> 151
    //   145: aload_3
    //   146: invokevirtual Dne : ()V
    //   149: aconst_null
    //   150: areturn
    //   151: iinc #4, 1
    //   154: goto -> 59
    //   157: aload_2
    //   158: iconst_2
    //   159: invokevirtual FWm : (I)I
    //   162: ifle -> 171
    //   165: aload_3
    //   166: invokevirtual Dne : ()V
    //   169: aconst_null
    //   170: areturn
    //   171: aload_3
    //   172: getfield Dne : I
    //   175: iconst_1
    //   176: if_icmple -> 229
    //   179: iconst_0
    //   180: istore #4
    //   182: iload #4
    //   184: aload_1
    //   185: getfield FWm : I
    //   188: if_icmpge -> 229
    //   191: aload_3
    //   192: getfield Dne : [I
    //   195: iload #4
    //   197: aload_2
    //   198: iconst_4
    //   199: invokevirtual FWm : (I)I
    //   202: iastore
    //   203: aload_3
    //   204: getfield Dne : [I
    //   207: iload #4
    //   209: iaload
    //   210: aload_3
    //   211: getfield Dne : I
    //   214: if_icmplt -> 223
    //   217: aload_3
    //   218: invokevirtual Dne : ()V
    //   221: aconst_null
    //   222: areturn
    //   223: iinc #4, 1
    //   226: goto -> 182
    //   229: iconst_0
    //   230: istore #4
    //   232: iload #4
    //   234: aload_3
    //   235: getfield Dne : I
    //   238: if_icmpge -> 346
    //   241: aload_3
    //   242: getfield FWm : [I
    //   245: iload #4
    //   247: aload_2
    //   248: bipush #8
    //   250: invokevirtual FWm : (I)I
    //   253: iastore
    //   254: aload_3
    //   255: getfield FWm : [I
    //   258: iload #4
    //   260: iaload
    //   261: aload_1
    //   262: getfield IjH : I
    //   265: if_icmplt -> 274
    //   268: aload_3
    //   269: invokevirtual Dne : ()V
    //   272: aconst_null
    //   273: areturn
    //   274: aload_3
    //   275: getfield bzF : [I
    //   278: iload #4
    //   280: aload_2
    //   281: bipush #8
    //   283: invokevirtual FWm : (I)I
    //   286: iastore
    //   287: aload_3
    //   288: getfield bzF : [I
    //   291: iload #4
    //   293: iaload
    //   294: aload_1
    //   295: getfield mrb : I
    //   298: if_icmplt -> 307
    //   301: aload_3
    //   302: invokevirtual Dne : ()V
    //   305: aconst_null
    //   306: areturn
    //   307: aload_3
    //   308: getfield Qnq : [I
    //   311: iload #4
    //   313: aload_2
    //   314: bipush #8
    //   316: invokevirtual FWm : (I)I
    //   319: iastore
    //   320: aload_3
    //   321: getfield Qnq : [I
    //   324: iload #4
    //   326: iaload
    //   327: aload_1
    //   328: getfield XHL : I
    //   331: if_icmplt -> 340
    //   334: aload_3
    //   335: invokevirtual Dne : ()V
    //   338: aconst_null
    //   339: areturn
    //   340: iinc #4, 1
    //   343: goto -> 232
    //   346: aload_3
    //   347: areturn
  }
  
  void FWm(Object paramObject) {}
}


/* Location:              C:\Users\fract\Downloads\ERROR422.jar!\wDe.class
 * Java compiler version: 5 (49.0)
 * JD-Core Version:       1.1.3
 */