public class wEm extends onZ {
  private final MqS FWm;
  
  private FiG Dne;
  
  private int Dne;
  
  public boolean Dne(NMq paramNMq) {
    return false;
  }
  
  public void Dne(FiG paramFiG, NMq paramNMq) {
    // Byte code:
    //   0: aload_0
    //   1: aload_2
    //   2: invokevirtual FWm : (LNMq;)V
    //   5: iconst_0
    //   6: istore_3
    //   7: iload_3
    //   8: aload_0
    //   9: getfield FWm : LMqS;
    //   12: invokeinterface Qnq : ()I
    //   17: if_icmpge -> 149
    //   20: aload_0
    //   21: getfield FWm : LMqS;
    //   24: iload_3
    //   25: invokeinterface Dne : (I)LNMq;
    //   30: astore #4
    //   32: aload #4
    //   34: ifnull -> 143
    //   37: aload_0
    //   38: getfield FWm : LMqS;
    //   41: iload_3
    //   42: iconst_1
    //   43: invokeinterface Dne : (II)LNMq;
    //   48: pop
    //   49: aload #4
    //   51: invokevirtual Dne : ()LdEr;
    //   54: invokevirtual IjH : ()Z
    //   57: ifeq -> 143
    //   60: new NMq
    //   63: dup
    //   64: aload #4
    //   66: invokevirtual Dne : ()LdEr;
    //   69: invokevirtual FWm : ()LdEr;
    //   72: invokespecial <init> : (LdEr;)V
    //   75: astore #5
    //   77: aload #4
    //   79: invokevirtual Dne : ()LdEr;
    //   82: aload #4
    //   84: invokevirtual bzF : (LNMq;)Z
    //   87: ifeq -> 105
    //   90: aload_0
    //   91: getfield Dne : LFiG;
    //   94: getfield Dne : LMOS;
    //   97: aload #5
    //   99: invokevirtual Dne : (LNMq;)Z
    //   102: ifne -> 143
    //   105: aload_0
    //   106: getfield FWm : LMqS;
    //   109: iload_3
    //   110: invokeinterface Dne : (I)LNMq;
    //   115: ifnonnull -> 133
    //   118: aload_0
    //   119: getfield FWm : LMqS;
    //   122: iload_3
    //   123: aload #5
    //   125: invokeinterface Dne : (ILNMq;)V
    //   130: goto -> 143
    //   133: aload_0
    //   134: getfield Dne : LFiG;
    //   137: aload #5
    //   139: invokevirtual Dne : (LNMq;)LJiM;
    //   142: pop
    //   143: iinc #3, 1
    //   146: goto -> 7
    //   149: return
  }
  
  protected void Dne(NMq paramNMq, int paramInt) {
    this.Dne += paramInt;
    FWm(paramNMq);
  }
  
  public wEm(FiG paramFiG, MqS paramMqS1, MqS paramMqS2, int paramInt1, int paramInt2, int paramInt3) {
    super(paramMqS2, paramInt1, paramInt2, paramInt3);
    this.Dne = paramFiG;
    this.FWm = paramMqS1;
  }
  
  public NMq Dne(int paramInt) {
    if (Dne())
      this.Dne += Math.min(paramInt, (Dne()).Dne); 
    return super.Dne(paramInt);
  }
  
  protected void FWm(NMq paramNMq) {
    // Byte code:
    //   0: aload_1
    //   1: aload_0
    //   2: getfield Dne : LFiG;
    //   5: getfield Dne : LQnq;
    //   8: aload_0
    //   9: getfield Dne : LFiG;
    //   12: aload_0
    //   13: getfield Dne : I
    //   16: invokevirtual Dne : (LQnq;LFiG;I)V
    //   19: aload_0
    //   20: iconst_0
    //   21: putfield Dne : I
    //   24: aload_1
    //   25: getfield bzF : I
    //   28: getstatic zKP.mlD : LzKP;
    //   31: getfield FWm : I
    //   34: if_icmpne -> 51
    //   37: aload_0
    //   38: getfield Dne : LFiG;
    //   41: getstatic qlg.bzF : LAuk;
    //   44: iconst_1
    //   45: invokevirtual Dne : (LRLC;I)V
    //   48: goto -> 291
    //   51: aload_1
    //   52: getfield bzF : I
    //   55: getstatic dEr.udO : LdEr;
    //   58: getfield Qnq : I
    //   61: if_icmpne -> 78
    //   64: aload_0
    //   65: getfield Dne : LFiG;
    //   68: getstatic qlg.Qnq : LAuk;
    //   71: iconst_1
    //   72: invokevirtual Dne : (LRLC;I)V
    //   75: goto -> 291
    //   78: aload_1
    //   79: getfield bzF : I
    //   82: getstatic zKP.haP : LzKP;
    //   85: getfield FWm : I
    //   88: if_icmpne -> 105
    //   91: aload_0
    //   92: getfield Dne : LFiG;
    //   95: getstatic qlg.aFZ : LAuk;
    //   98: iconst_1
    //   99: invokevirtual Dne : (LRLC;I)V
    //   102: goto -> 291
    //   105: aload_1
    //   106: getfield bzF : I
    //   109: getstatic dEr.Wwe : LdEr;
    //   112: getfield Qnq : I
    //   115: if_icmpne -> 132
    //   118: aload_0
    //   119: getfield Dne : LFiG;
    //   122: getstatic qlg.DyG : LAuk;
    //   125: iconst_1
    //   126: invokevirtual Dne : (LRLC;I)V
    //   129: goto -> 291
    //   132: aload_1
    //   133: getfield bzF : I
    //   136: getstatic dEr.rPc : LdEr;
    //   139: getfield Qnq : I
    //   142: if_icmpne -> 159
    //   145: aload_0
    //   146: getfield Dne : LFiG;
    //   149: getstatic qlg.div : LAuk;
    //   152: iconst_1
    //   153: invokevirtual Dne : (LRLC;I)V
    //   156: goto -> 291
    //   159: aload_1
    //   160: getfield bzF : I
    //   163: getstatic dEr.iXU : LdEr;
    //   166: getfield Qnq : I
    //   169: if_icmpne -> 186
    //   172: aload_0
    //   173: getfield Dne : LFiG;
    //   176: getstatic qlg.IjH : LAuk;
    //   179: iconst_1
    //   180: invokevirtual Dne : (LRLC;I)V
    //   183: goto -> 291
    //   186: aload_1
    //   187: getfield bzF : I
    //   190: getstatic dEr.ATE : LdEr;
    //   193: getfield Qnq : I
    //   196: if_icmpne -> 213
    //   199: aload_0
    //   200: getfield Dne : LFiG;
    //   203: getstatic qlg.mrb : LAuk;
    //   206: iconst_1
    //   207: invokevirtual Dne : (LRLC;I)V
    //   210: goto -> 291
    //   213: aload_1
    //   214: getfield bzF : I
    //   217: getstatic dEr.Zpi : LdEr;
    //   220: getfield Qnq : I
    //   223: if_icmpne -> 240
    //   226: aload_0
    //   227: getfield Dne : LFiG;
    //   230: getstatic qlg.kGO : LAuk;
    //   233: iconst_1
    //   234: invokevirtual Dne : (LRLC;I)V
    //   237: goto -> 291
    //   240: aload_1
    //   241: getfield bzF : I
    //   244: getstatic zKP.KkE : LzKP;
    //   247: getfield FWm : I
    //   250: if_icmpne -> 267
    //   253: aload_0
    //   254: getfield Dne : LFiG;
    //   257: getstatic qlg.vSL : LAuk;
    //   260: iconst_1
    //   261: invokevirtual Dne : (LRLC;I)V
    //   264: goto -> 291
    //   267: aload_1
    //   268: getfield bzF : I
    //   271: getstatic zKP.AgF : LzKP;
    //   274: getfield FWm : I
    //   277: if_icmpne -> 291
    //   280: aload_0
    //   281: getfield Dne : LFiG;
    //   284: getstatic qlg.Fnk : LAuk;
    //   287: iconst_1
    //   288: invokevirtual Dne : (LRLC;I)V
    //   291: return
  }
}


/* Location:              C:\Users\fract\Downloads\ERROR422.jar!\wEm.class
 * Java compiler version: 8 (52.0)
 * JD-Core Version:       1.1.3
 */