public class wHH {
  public gks Dne;
  
  public sMa Dne;
  
  public int bzF;
  
  public int FWm;
  
  public int Dne;
  
  public int Qnq;
  
  public chN Dne = (chN)gks.Dne;
  
  public wHH(sMa paramsMa) {
    // Byte code:
    //   0: aload_0
    //   1: invokespecial <init> : ()V
    //   4: aload_0
    //   5: getstatic gks.FWm : Lgks;
    //   8: putfield Dne : Lgks;
    //   11: aload_0
    //   12: aload_1
    //   13: putfield Dne : LsMa;
    //   16: aload_0
    //   17: aload_1
    //   18: getfield Dne : LQnq;
    //   21: invokevirtual Dne : ()LziS;
    //   24: aload_1
    //   25: getfield div : D
    //   28: aload_1
    //   29: getfield IjH : D
    //   32: aload_1
    //   33: getfield mrb : D
    //   36: invokevirtual Dne : (DDD)LchN;
    //   39: putfield Dne : LchN;
    //   42: return
  }
  
  public wHH(int paramInt1, int paramInt2, int paramInt3, int paramInt4, chN paramchN) {
    this.Dne = paramInt1;
    this.FWm = paramInt2;
    this.bzF = paramInt3;
    this.Qnq = paramInt4;
    this.Dne = paramchN.FWm.Dne(paramchN.Dne, paramchN.FWm, paramchN.bzF);
  }
}


/* Location:              C:\Users\fract\Downloads\ERROR422.jar!\wHH.class
 * Java compiler version: 8 (52.0)
 * JD-Core Version:       1.1.3
 */