class WRa extends Thread {
  final Qyp Dne;
  
  public void run() {
    // Byte code:
    //   0: getstatic Qyp.Dne : Ljava/util/concurrent/atomic/AtomicInteger;
    //   3: invokevirtual getAndIncrement : ()I
    //   6: pop
    //   7: aload_0
    //   8: getfield Dne : LQyp;
    //   11: invokestatic Dne : (LQyp;)Z
    //   14: ifeq -> 50
    //   17: aload_0
    //   18: getfield Dne : LQyp;
    //   21: invokestatic FWm : (LQyp;)Z
    //   24: ifne -> 50
    //   27: aload_0
    //   28: getfield Dne : LQyp;
    //   31: invokestatic bzF : (LQyp;)Z
    //   34: ifne -> 27
    //   37: ldc2_w 2
    //   40: invokestatic sleep : (J)V
    //   43: goto -> 27
    //   46: astore_1
    //   47: goto -> 27
    //   50: getstatic Qyp.Dne : Ljava/util/concurrent/atomic/AtomicInteger;
    //   53: invokevirtual getAndDecrement : ()I
    //   56: pop
    //   57: goto -> 70
    //   60: astore_2
    //   61: getstatic Qyp.Dne : Ljava/util/concurrent/atomic/AtomicInteger;
    //   64: invokevirtual getAndDecrement : ()I
    //   67: pop
    //   68: aload_2
    //   69: athrow
    //   70: return
    // Exception table:
    //   from	to	target	type
    //   7	50	60	finally
    //   37	43	46	java/lang/InterruptedException
  }
  
  WRa(Qyp paramQyp, String paramString) {
    super(paramString);
    this.Dne = paramQyp;
  }
}


/* Location:              C:\Users\fract\Downloads\ERROR422.jar!\WRa.class
 * Java compiler version: 8 (52.0)
 * JD-Core Version:       1.1.3
 */