import java.util.List;

public class WSC extends FUH implements eKx, sQM {
  public Dur Qnq;
  
  public double FWm;
  
  public int FWm;
  
  public double[][] Dne;
  
  public Dur DyG;
  
  public boolean Dne;
  
  public int Dne;
  
  public Dur[] Dne;
  
  public float Dne;
  
  public Dur Dne;
  
  public Dur zGp;
  
  private sMa bzF;
  
  public double Dne;
  
  public Dur aFZ;
  
  public float FWm;
  
  public Ndk Dne = (Ndk)new double[64][3];
  
  public double EyB;
  
  public boolean FWm;
  
  public Dur FWm;
  
  public Dur bzF;
  
  protected boolean FWm(zBn paramzBn, int paramInt) {
    return super.Dne(paramzBn, paramInt);
  }
  
  private float Dne(double paramDouble) {
    return (float)geR.Dne(paramDouble);
  }
  
  public boolean kGO() {
    return false;
  }
  
  public Qnq Dne() {
    return (Qnq)this.Dne;
  }
  
  protected String DyG() {
    return "mob.enderdragon.hit";
  }
  
  private void zGp() {
    // Byte code:
    //   0: aload_0
    //   1: iconst_0
    //   2: putfield Dne : Z
    //   5: aload_0
    //   6: getfield Dne : Ljava/util/Random;
    //   9: iconst_2
    //   10: invokevirtual nextInt : (I)I
    //   13: ifne -> 72
    //   16: aload_0
    //   17: getfield Dne : LQnq;
    //   20: getfield Qnq : Ljava/util/List;
    //   23: invokeinterface isEmpty : ()Z
    //   28: ifne -> 72
    //   31: aload_0
    //   32: aload_0
    //   33: getfield Dne : LQnq;
    //   36: getfield Qnq : Ljava/util/List;
    //   39: aload_0
    //   40: getfield Dne : Ljava/util/Random;
    //   43: aload_0
    //   44: getfield Dne : LQnq;
    //   47: getfield Qnq : Ljava/util/List;
    //   50: invokeinterface size : ()I
    //   55: invokevirtual nextInt : (I)I
    //   58: invokeinterface get : (I)Ljava/lang/Object;
    //   63: checkcast sMa
    //   66: putfield bzF : LsMa;
    //   69: goto -> 217
    //   72: iconst_0
    //   73: istore_1
    //   74: aload_0
    //   75: dconst_0
    //   76: putfield Dne : D
    //   79: aload_0
    //   80: ldc 70.0
    //   82: aload_0
    //   83: getfield Dne : Ljava/util/Random;
    //   86: invokevirtual nextFloat : ()F
    //   89: ldc 50.0
    //   91: fmul
    //   92: fadd
    //   93: f2d
    //   94: putfield FWm : D
    //   97: aload_0
    //   98: dconst_0
    //   99: putfield EyB : D
    //   102: aload_0
    //   103: dup
    //   104: getfield Dne : D
    //   107: aload_0
    //   108: getfield Dne : Ljava/util/Random;
    //   111: invokevirtual nextFloat : ()F
    //   114: ldc 120.0
    //   116: fmul
    //   117: ldc 60.0
    //   119: fsub
    //   120: f2d
    //   121: dadd
    //   122: putfield Dne : D
    //   125: aload_0
    //   126: dup
    //   127: getfield EyB : D
    //   130: aload_0
    //   131: getfield Dne : Ljava/util/Random;
    //   134: invokevirtual nextFloat : ()F
    //   137: ldc 120.0
    //   139: fmul
    //   140: ldc 60.0
    //   142: fsub
    //   143: f2d
    //   144: dadd
    //   145: putfield EyB : D
    //   148: aload_0
    //   149: getfield div : D
    //   152: aload_0
    //   153: getfield Dne : D
    //   156: dsub
    //   157: dstore_2
    //   158: aload_0
    //   159: getfield IjH : D
    //   162: aload_0
    //   163: getfield FWm : D
    //   166: dsub
    //   167: dstore #4
    //   169: aload_0
    //   170: getfield mrb : D
    //   173: aload_0
    //   174: getfield EyB : D
    //   177: dsub
    //   178: dstore #6
    //   180: dload_2
    //   181: dload_2
    //   182: dmul
    //   183: dload #4
    //   185: dload #4
    //   187: dmul
    //   188: dadd
    //   189: dload #6
    //   191: dload #6
    //   193: dmul
    //   194: dadd
    //   195: ldc2_w 100.0
    //   198: dcmpl
    //   199: ifle -> 206
    //   202: iconst_1
    //   203: goto -> 207
    //   206: iconst_0
    //   207: istore_1
    //   208: iload_1
    //   209: ifeq -> 74
    //   212: aload_0
    //   213: aconst_null
    //   214: putfield bzF : LsMa;
    //   217: return
  }
  
  public int c_() {
    return this.Dne.Dne(16);
  }
  
  public WSC(Qnq paramQnq) {
    super(paramQnq);
    this.Dne = -1;
    this.Dne = 0.0F;
    this.FWm = 0.0F;
    this.Dne = false;
    this.FWm = false;
    this.FWm = false;
    this.Dne = null;
    this.Dne = (Ndk)new Dur[] { (Dur)(this.Dne = (Ndk)new Dur(this, "head", 6.0F, 6.0F)), this.FWm = new Dur(this, "body", 8.0F, 8.0F), this.bzF = new Dur(this, "tail", 4.0F, 4.0F), this.Qnq = new Dur(this, "tail", 4.0F, 4.0F), this.aFZ = new Dur(this, "tail", 4.0F, 4.0F), this.zGp = new Dur(this, "wing", 4.0F, 4.0F), this.DyG = new Dur(this, "wing", 4.0F, 4.0F) };
    bzF(Dne());
    this.bzF = (Dur)"/mob/enderdragon/ender.png";
    Dne(16.0F, 8.0F);
    this.kGO = true;
    this.ooe = true;
    this.FWm = 100.0D;
    this.qLR = true;
  }
  
  protected String zGp() {
    return "mob.enderdragon.growl";
  }
  
  private void Qnq() {
    if (this.Dne != null)
      if (this.Dne.Zpi != 0.0F) {
        if (((Qnq)this.Dne).aFZ == null)
          Dne((Dur)this.Dne, zBn.Dne((yTR)null), 10); 
        this.Dne = null;
      } else if (this.zGp % 10 == 0 && XHL() < Dne()) {
        bzF(XHL() + 1);
      }  
    if (this.Dne.nextInt(10) == 0) {
      float f = 32.0F;
      List list = this.Dne.Dne(Ndk.class, this.Dne.FWm(f, f, f));
      Ndk ndk = null;
      double d = Double.MAX_VALUE;
      for (Ndk ndk1 : list) {
        double d1 = ndk1.Dne(this);
        if (d1 < d) {
          d = d1;
          ndk = ndk1;
        } 
      } 
      this.Dne = ndk;
    } 
  }
  
  private void Dne(List paramList) {
    double d1 = (((bSp)this.FWm.Dne).Dne + ((bSp)this.FWm.Dne).Qnq) / 2.0D;
    double d2 = (((bSp)this.FWm.Dne).bzF + ((bSp)this.FWm.Dne).zGp) / 2.0D;
    for (sMa sMa1 : paramList) {
      if (sMa1 instanceof FUH) {
        double d3 = sMa1.div - d1;
        double d4 = sMa1.mrb - d2;
        double d5 = d3 * d3 + d4 * d4;
        sMa1.Qnq(d3 / d5 * 4.0D, 0.20000000298023224D, d4 / d5 * 4.0D);
      } 
    } 
  }
  
  public boolean Dne(zBn paramzBn, int paramInt) {
    return false;
  }
  
  private void Dne(int paramInt1, int paramInt2) {
    byte b1 = 64;
    aQq.Dne = true;
    byte b2 = 4;
    for (int i = b1 - 1; i <= b1 + 32; i++) {
      for (int j = paramInt1 - b2; j <= paramInt1 + b2; j++) {
        for (int k = paramInt2 - b2; k <= paramInt2 + b2; k++) {
          double d1 = (j - paramInt1);
          double d2 = (k - paramInt2);
          double d3 = d1 * d1 + d2 * d2;
          if (d3 <= (b2 - 0.5D) * (b2 - 0.5D))
            if (i < b1) {
              if (d3 <= ((b2 - 1) - 0.5D) * ((b2 - 1) - 0.5D))
                this.Dne.FWm(j, i, k, zKP.zGp.FWm); 
            } else if (i > b1) {
              this.Dne.FWm(j, i, k, 0);
            } else if (d3 > ((b2 - 1) - 0.5D) * ((b2 - 1) - 0.5D)) {
              this.Dne.FWm(j, i, k, zKP.zGp.FWm);
            } else {
              this.Dne.FWm(j, i, k, zKP.EYV.FWm);
            }  
        } 
      } 
    } 
    this.Dne.FWm(paramInt1, b1 + 0, paramInt2, zKP.zGp.FWm);
    this.Dne.FWm(paramInt1, b1 + 1, paramInt2, zKP.zGp.FWm);
    this.Dne.FWm(paramInt1, b1 + 2, paramInt2, zKP.zGp.FWm);
    this.Dne.FWm(paramInt1 - 1, b1 + 2, paramInt2, zKP.Wwe.FWm);
    this.Dne.FWm(paramInt1 + 1, b1 + 2, paramInt2, zKP.Wwe.FWm);
    this.Dne.FWm(paramInt1, b1 + 2, paramInt2 - 1, zKP.Wwe.FWm);
    this.Dne.FWm(paramInt1, b1 + 2, paramInt2 + 1, zKP.Wwe.FWm);
    this.Dne.FWm(paramInt1, b1 + 3, paramInt2, zKP.zGp.FWm);
    this.Dne.FWm(paramInt1, b1 + 4, paramInt2, zKP.sJS.FWm);
    aQq.Dne = false;
  }
  
  private boolean Dne(bSp parambSp) {
    int i = geR.FWm(parambSp.Dne);
    int j = geR.FWm(parambSp.FWm);
    int k = geR.FWm(parambSp.bzF);
    int m = geR.FWm(parambSp.Qnq);
    int n = geR.FWm(parambSp.aFZ);
    int i1 = geR.FWm(parambSp.zGp);
    boolean bool1 = false;
    boolean bool2 = false;
    for (int i2 = i; i2 <= m; i2++) {
      for (int i3 = j; i3 <= n; i3++) {
        for (int i4 = k; i4 <= i1; i4++) {
          int i5 = this.Dne.Dne(i2, i3, i4);
          if (i5 != 0)
            if (i5 != zKP.cot.FWm && i5 != zKP.dNY.FWm && i5 != zKP.zGp.FWm && this.Dne.Dne().Dne("mobGriefing")) {
              bool2 = (this.Dne.Qnq(i2, i3, i4) || bool2) ? true : false;
            } else {
              bool1 = true;
            }  
        } 
      } 
    } 
    if (bool2) {
      double d1 = parambSp.Dne + (parambSp.Qnq - parambSp.Dne) * this.Dne.nextFloat();
      double d2 = parambSp.FWm + (parambSp.aFZ - parambSp.FWm) * this.Dne.nextFloat();
      double d3 = parambSp.bzF + (parambSp.zGp - parambSp.bzF) * this.Dne.nextFloat();
      this.Dne.Dne("largeexplode", d1, d2, d3, 0.0D, 0.0D, 0.0D);
    } 
    return bool1;
  }
  
  public boolean Dne(Dur paramDur, zBn paramzBn, int paramInt) {
    if (paramDur != this.Dne)
      paramInt = paramInt / 4 + 1; 
    float f1 = this.mrb * 3.1415927F / 180.0F;
    float f2 = geR.Dne(f1);
    float f3 = geR.FWm(f1);
    this.Dne = this.div + (f2 * 5.0F) + ((this.Dne.nextFloat() - 0.5F) * 2.0F);
    this.FWm = this.IjH + (this.Dne.nextFloat() * 3.0F) + 1.0D;
    this.EyB = this.mrb - (f3 * 5.0F) + ((this.Dne.nextFloat() - 0.5F) * 2.0F);
    this.bzF = null;
    if (paramzBn.FWm() instanceof FiG || paramzBn.FWm())
      FWm(paramzBn, paramInt); 
    return true;
  }
  
  public sMa[] Dne() {
    return (sMa[])this.Dne;
  }
  
  private void FWm(List<sMa> paramList) {
    for (byte b = 0; b < paramList.size(); b++) {
      sMa sMa1 = paramList.get(b);
      if (sMa1 instanceof FUH)
        sMa1.Dne(zBn.Dne(this), 10); 
    } 
  }
  
  public void IjH() {
    if (((Qnq)this.Dne).aFZ == null) {
      this.Dne.FWm(16, Integer.valueOf(this.Vxn));
    } else {
      float f1 = geR.FWm(this.FWm * 3.1415927F * 2.0F);
      float f2 = geR.FWm(this.Dne * 3.1415927F * 2.0F);
      if (f2 <= -0.3F && f1 >= -0.3F)
        this.Dne.Dne(this.div, this.IjH, this.mrb, "mob.enderdragon.wings", 5.0F, 0.8F + this.Dne.nextFloat() * 0.3F, false); 
    } 
    this.Dne = (Ndk)this.FWm;
    if (this.Vxn <= 0) {
      float f1 = (this.Dne.nextFloat() - 0.5F) * 8.0F;
      float f2 = (this.Dne.nextFloat() - 0.5F) * 4.0F;
      float f3 = (this.Dne.nextFloat() - 0.5F) * 8.0F;
      this.Dne.Dne("largeexplode", this.div + f1, this.IjH + 2.0D + f2, this.mrb + f3, 0.0D, 0.0D, 0.0D);
    } else {
      Qnq();
      float f1 = 0.2F / (geR.Dne(this.XHL * this.XHL + this.kGO * this.kGO) * 10.0F + 1.0F);
      f1 *= (float)Math.pow(2.0D, this.Zpi);
      if (this.FWm != null) {
        this.FWm += f1 * 0.5F;
      } else {
        this.FWm += f1;
      } 
      this.mrb = geR.aFZ(this.mrb);
      if (this.Dne < null)
        for (byte b1 = 0; b1 < this.Dne.length; b1++) {
          this.Dne[b1][0] = this.mrb;
          this.Dne[b1][1] = this.IjH;
        }  
      if (++this.Dne == this.Dne.length)
        this.Dne = false; 
      this.Dne[this.Dne][0] = this.mrb;
      this.Dne[this.Dne][1] = this.IjH;
      if (((Qnq)this.Dne).aFZ != null) {
        if (this.yMz > 0) {
          double d4 = this.div + (this.bzF - this.div) / this.yMz;
          double d1 = this.IjH + (this.qLR - this.IjH) / this.yMz;
          double d2 = this.mrb + (this.ATE - this.mrb) / this.yMz;
          double d3 = geR.Dne(this.Vxn - this.mrb);
          this.mrb = (float)(this.mrb + d3 / this.yMz);
          this.XHL = (float)(this.XHL + (this.ceE - this.XHL) / this.yMz);
          this.yMz--;
          bzF(d4, d1, d2);
          FWm(this.mrb, this.XHL);
        } 
      } else {
        double d4 = this.Dne - this.div;
        double d1 = this.FWm - this.IjH;
        double d2 = this.EyB - this.mrb;
        double d3 = d4 * d4 + d1 * d1 + d2 * d2;
        if (this.bzF != null) {
          this.Dne = this.bzF.div;
          this.EyB = this.bzF.mrb;
          double d8 = this.Dne - this.div;
          double d9 = this.EyB - this.mrb;
          double d10 = Math.sqrt(d8 * d8 + d9 * d9);
          double d11 = 0.4000000059604645D + d10 / 80.0D - 1.0D;
          if (d11 > 10.0D)
            d11 = 10.0D; 
          this.FWm = this.bzF.Dne.FWm + d11;
        } else {
          this.Dne += this.Dne.nextGaussian() * 2.0D;
          this.EyB += this.Dne.nextGaussian() * 2.0D;
        } 
        if (this.Dne != null || d3 < 100.0D || d3 > 22500.0D || this.zGp != null || this.DyG != null)
          zGp(); 
        d1 /= geR.Dne(d4 * d4 + d2 * d2);
        float f10 = 0.6F;
        if (d1 < -f10)
          d1 = -f10; 
        if (d1 > f10)
          d1 = f10; 
        this.Zpi += d1 * 0.10000000149011612D;
        this.mrb = geR.aFZ(this.mrb);
        double d5 = 180.0D - Math.atan2(d4, d2) * 180.0D / Math.PI;
        double d6 = geR.Dne(d5 - this.mrb);
        if (d6 > 50.0D)
          d6 = 50.0D; 
        if (d6 < -50.0D)
          d6 = -50.0D; 
        chN chN1 = this.Dne.Dne().Dne(this.Dne - this.div, this.FWm - this.IjH, this.EyB - this.mrb).Dne();
        chN chN2 = this.Dne.Dne().Dne(geR.Dne(this.mrb * 3.1415927F / 180.0F), this.Zpi, -geR.FWm(this.mrb * 3.1415927F / 180.0F)).Dne();
        float f11 = (float)(chN2.Dne(chN1) + 0.5D) / 1.5F;
        if (f11 < 0.0F)
          f11 = 0.0F; 
        this.BJH *= 0.8F;
        float f12 = geR.Dne(this.XHL * this.XHL + this.kGO * this.kGO) * 1.0F + 1.0F;
        double d7 = Math.sqrt(this.XHL * this.XHL + this.kGO * this.kGO) * 1.0D + 1.0D;
        if (d7 > 40.0D)
          d7 = 40.0D; 
        this.BJH = (float)(this.BJH + d6 * 0.699999988079071D / d7 / f12);
        this.mrb += this.BJH * 0.1F;
        float f13 = (float)(2.0D / (d7 + 1.0D));
        float f14 = 0.06F;
        FWm(0.0F, -1.0F, f14 * (f11 * f13 + 1.0F - f13));
        if (this.FWm != null) {
          Dne(this.XHL * 0.800000011920929D, this.Zpi * 0.800000011920929D, this.kGO * 0.800000011920929D);
        } else {
          Dne(this.XHL, this.Zpi, this.kGO);
        } 
        chN chN3 = this.Dne.Dne().Dne(this.XHL, this.Zpi, this.kGO).Dne();
        float f15 = (float)(chN3.Dne(chN2) + 1.0D) / 2.0F;
        f15 = 0.8F + 0.15F * f15;
        this.XHL *= f15;
        this.kGO *= f15;
        this.Zpi *= 0.9100000262260437D;
      } 
      this.IjH = this.mrb;
      ((Dur)this.Dne).ooe = ((Dur)this.Dne).trS = 3.0F;
      this.bzF.ooe = this.bzF.trS = 2.0F;
      this.Qnq.ooe = this.Qnq.trS = 2.0F;
      this.aFZ.ooe = this.aFZ.trS = 2.0F;
      this.FWm.trS = 3.0F;
      this.FWm.ooe = 5.0F;
      this.zGp.trS = 2.0F;
      this.zGp.ooe = 4.0F;
      this.DyG.trS = 3.0F;
      this.DyG.ooe = 4.0F;
      float f2 = (float)(Dne(5, 1.0F)[1] - Dne(10, 1.0F)[1]) * 10.0F / 180.0F * 3.1415927F;
      float f3 = geR.FWm(f2);
      float f5 = -geR.Dne(f2);
      float f6 = this.mrb * 3.1415927F / 180.0F;
      float f7 = geR.Dne(f6);
      float f8 = geR.FWm(f6);
      this.FWm.Dne();
      this.FWm.FWm(this.div + (f7 * 0.5F), this.IjH, this.mrb - (f8 * 0.5F), 0.0F, 0.0F);
      this.zGp.Dne();
      this.zGp.FWm(this.div + (f8 * 4.5F), this.IjH + 2.0D, this.mrb + (f7 * 4.5F), 0.0F, 0.0F);
      this.DyG.Dne();
      this.DyG.FWm(this.div - (f8 * 4.5F), this.IjH + 2.0D, this.mrb - (f7 * 4.5F), 0.0F, 0.0F);
      if (((Qnq)this.Dne).aFZ == null && this.OdI == 0) {
        Dne(this.Dne.FWm(this, this.zGp.Dne.FWm(4.0D, 2.0D, 4.0D).Qnq(0.0D, -2.0D, 0.0D)));
        Dne(this.Dne.FWm(this, this.DyG.Dne.FWm(4.0D, 2.0D, 4.0D).Qnq(0.0D, -2.0D, 0.0D)));
        FWm(this.Dne.FWm(this, ((Dur)this.Dne).Dne.FWm(1.0D, 1.0D, 1.0D)));
      } 
      double[] arrayOfDouble1 = Dne(5, 1.0F);
      double[] arrayOfDouble2 = Dne(0, 1.0F);
      float f4 = geR.Dne(this.mrb * 3.1415927F / 180.0F - this.BJH * 0.01F);
      float f9 = geR.FWm(this.mrb * 3.1415927F / 180.0F - this.BJH * 0.01F);
      this.Dne.Dne();
      this.Dne.FWm(this.div + (f4 * 5.5F * f3), this.IjH + (arrayOfDouble2[1] - arrayOfDouble1[1]) * 1.0D + (f5 * 5.5F), this.mrb - (f9 * 5.5F * f3), 0.0F, 0.0F);
      for (byte b = 0; b < 3; b++) {
        Dur dur = null;
        if (b == 0)
          dur = this.bzF; 
        if (b == 1)
          dur = this.Qnq; 
        if (b == 2)
          dur = this.aFZ; 
        double[] arrayOfDouble = Dne(12 + b * 2, 1.0F);
        float f10 = this.mrb * 3.1415927F / 180.0F + Dne(arrayOfDouble[0] - arrayOfDouble1[0]) * 3.1415927F / 180.0F * 1.0F;
        float f11 = geR.Dne(f10);
        float f12 = geR.FWm(f10);
        float f13 = 1.5F;
        float f14 = (b + 1) * 2.0F;
        dur.Dne();
        dur.FWm(this.div - ((f7 * f13 + f11 * f14) * f3), this.IjH + (arrayOfDouble[1] - arrayOfDouble1[1]) * 1.0D - ((f14 + f13) * f5) + 1.5D, this.mrb + ((f8 * f13 + f12 * f14) * f3), 0.0F, 0.0F);
      } 
      if (((Qnq)this.Dne).aFZ == null)
        this.FWm = Dne((bSp)((Dur)this.Dne).Dne) | Dne((bSp)this.FWm.Dne); 
    } 
  }
  
  public int Dne() {
    return 200;
  }
  
  protected void ZgS() {}
  
  protected void cot() {
    this.FWm++;
    if (this.FWm >= '´' && this.FWm <= 'È') {
      float f1 = (this.Dne.nextFloat() - 0.5F) * 8.0F;
      float f2 = (this.Dne.nextFloat() - 0.5F) * 4.0F;
      float f3 = (this.Dne.nextFloat() - 0.5F) * 8.0F;
      this.Dne.Dne("hugeexplosion", this.div + f1, this.IjH + 2.0D + f2, this.mrb + f3, 0.0D, 0.0D, 0.0D);
    } 
    if (((Qnq)this.Dne).aFZ == null) {
      if (this.FWm > '' && this.FWm % 5 == 0) {
        int i = 1000;
        while (i > 0) {
          int j = alg.Dne(i);
          i -= j;
          this.Dne.FWm(new alg((Qnq)this.Dne, this.div, this.IjH, this.mrb, j));
        } 
      } 
      if (this.FWm == true)
        this.Dne.bzF(1018, (int)this.div, (int)this.IjH, (int)this.mrb, 0); 
    } 
    Dne(0.0D, 0.10000000149011612D, 0.0D);
    this.IjH = this.mrb += 20.0F;
    if (this.FWm == 'È' && ((Qnq)this.Dne).aFZ == null) {
      int i = 2000;
      while (i > 0) {
        int j = alg.Dne(i);
        i -= j;
        this.Dne.FWm(new alg((Qnq)this.Dne, this.div, this.IjH, this.mrb, j));
      } 
      Dne(geR.FWm(this.div), geR.FWm(this.mrb));
      g_();
    } 
  }
  
  protected void FWm() {
    super.FWm();
    this.Dne.Dne(16, new Integer(Dne()));
  }
  
  protected float div() {
    return 5.0F;
  }
  
  public double[] Dne(int paramInt, float paramFloat) {
    if (this.Vxn <= 0)
      paramFloat = 0.0F; 
    paramFloat = 1.0F - paramFloat;
    int i = this.Dne - paramInt * 1 & 0x3F;
    int j = this.Dne - paramInt * 1 - 1 & 0x3F;
    double[] arrayOfDouble = new double[3];
    Ndk ndk = this.Dne[i][0];
    double d = geR.Dne(this.Dne[j][0] - ndk);
    arrayOfDouble[0] = ndk + d * paramFloat;
    ndk = this.Dne[i][1];
    d = this.Dne[j][1] - ndk;
    arrayOfDouble[1] = ndk + d * paramFloat;
    arrayOfDouble[2] = this.Dne[i][2] + (this.Dne[j][2] - this.Dne[i][2]) * paramFloat;
    return arrayOfDouble;
  }
}


/* Location:              C:\Users\fract\Downloads\ERROR422.jar!\WSC.class
 * Java compiler version: 8 (52.0)
 * JD-Core Version:       1.1.3
 */