public class Wwe extends OdI {
  public Wwe(int paramInt) {
    // Byte code:
    //   0: aload_0
    //   1: iload_1
    //   2: invokespecial <init> : (I)V
    //   5: aload_0
    //   6: getfield Dne : Ljava/util/List;
    //   9: invokeinterface clear : ()V
    //   14: aload_0
    //   15: getfield FWm : Ljava/util/List;
    //   18: invokeinterface clear : ()V
    //   23: aload_0
    //   24: getfield bzF : Ljava/util/List;
    //   27: invokeinterface clear : ()V
    //   32: aload_0
    //   33: getfield Qnq : Ljava/util/List;
    //   36: invokeinterface clear : ()V
    //   41: aload_0
    //   42: getfield Dne : Ljava/util/List;
    //   45: new oIf
    //   48: dup
    //   49: ldc VAd
    //   51: bipush #50
    //   53: iconst_4
    //   54: iconst_4
    //   55: invokespecial <init> : (Ljava/lang/Class;III)V
    //   58: invokeinterface add : (Ljava/lang/Object;)Z
    //   63: pop
    //   64: aload_0
    //   65: getfield Dne : Ljava/util/List;
    //   68: new oIf
    //   71: dup
    //   72: ldc eBi
    //   74: bipush #100
    //   76: iconst_4
    //   77: iconst_4
    //   78: invokespecial <init> : (Ljava/lang/Class;III)V
    //   81: invokeinterface add : (Ljava/lang/Object;)Z
    //   86: pop
    //   87: aload_0
    //   88: getfield Dne : Ljava/util/List;
    //   91: new oIf
    //   94: dup
    //   95: ldc WDT
    //   97: iconst_1
    //   98: iconst_4
    //   99: iconst_4
    //   100: invokespecial <init> : (Ljava/lang/Class;III)V
    //   103: invokeinterface add : (Ljava/lang/Object;)Z
    //   108: pop
    //   109: return
  }
  
  static {
  
  }
}


/* Location:              C:\Users\fract\Downloads\ERROR422.jar!\Wwe.class
 * Java compiler version: 8 (52.0)
 * JD-Core Version:       1.1.3
 */