import java.io.DataInputStream;
import java.io.DataOutputStream;
import java.io.IOException;
import java.net.InetSocketAddress;
import java.net.Socket;
import java.util.Collections;
import java.util.List;
import net.minecraft.client.Minecraft;
import org.lwjgl.input.Keyboard;
import org.lwjgl.opengl.GL11;

public class wWl extends qVZ {
  private static final Object Dne;
  
  private qVZ Dne;
  
  private TIk Dne;
  
  private boolean bzF;
  
  private zXv Dne;
  
  private ukD Dne;
  
  private volatile int aFZ;
  
  private int zGp = 0;
  
  private String Dne;
  
  private int Qnq = -1;
  
  private static int Dne = false;
  
  private Pee Dne;
  
  private Pee bzF;
  
  private Pee FWm;
  
  private Long Dne = null;
  
  private List FWm = Collections.emptyList();
  
  static Minecraft Qnq(wWl paramwWl) {
    return (Minecraft)paramwWl.Dne;
  }
  
  static msA Dne(wWl paramwWl) {
    return (msA)paramwWl.Dne;
  }
  
  public void FWm() {
    Keyboard.enableRepeatEvents(false);
  }
  
  private void Dne(int paramInt) {
    if (paramInt >= 0 && paramInt < this.FWm.size()) {
      muh muh = this.FWm.get(paramInt);
      this.Dne.FWm();
      blc blc = new blc((Minecraft)this.Dne, this, new OQj(this, muh));
      blc.zGp();
      this.Dne.Dne(blc);
    } 
  }
  
  private void Qnq(int paramInt1, int paramInt2, int paramInt3, int paramInt4) {
    ((Minecraft)this.Dne).Dne.Dne("/gui/gui.png");
    GL11.glColor4f(1.0F, 1.0F, 1.0F, 1.0F);
    GL11.glPushMatrix();
    GL11.glScalef(0.5F, 0.5F, 0.5F);
    FWm(paramInt1 * 2, paramInt2 * 2, 207, 0, 16, 15);
    GL11.glPopMatrix();
    if (paramInt3 >= paramInt1 && paramInt3 <= paramInt1 + 9 && paramInt4 >= paramInt2 && paramInt4 <= paramInt2 + 9)
      this.Dne = (Long)"Open World"; 
  }
  
  private void FWm(int paramInt1, int paramInt2, int paramInt3, int paramInt4, int paramInt5) {
    if (this.zGp % 20 < 10) {
      ((Minecraft)this.Dne).Dne.Dne("/gui/gui.png");
      GL11.glColor4f(1.0F, 1.0F, 1.0F, 1.0F);
      GL11.glPushMatrix();
      GL11.glScalef(0.5F, 0.5F, 0.5F);
      FWm(paramInt1 * 2, paramInt2 * 2, 207, 0, 16, 15);
      GL11.glPopMatrix();
    } 
    if (paramInt3 >= paramInt1 && paramInt3 <= paramInt1 + 9 && paramInt4 >= paramInt2 && paramInt4 <= paramInt2 + 9)
      if (paramInt5 == 0) {
        this.Dne = (Long)"Expires in < a day";
      } else {
        this.Dne = (Long)("Expires in " + paramInt5 + ((paramInt5 > 1) ? (Long)" days" : (Long)" day"));
      }  
  }
  
  static void Dne(wWl paramwWl, int paramInt1, int paramInt2, int paramInt3, int paramInt4, int paramInt5) {
    paramwWl.FWm(paramInt1, paramInt2, paramInt3, paramInt4, paramInt5);
  }
  
  static int FWm(wWl paramwWl, int paramInt) {
    return paramwWl.Qnq = paramInt;
  }
  
  static int bzF() {
    return Dne--;
  }
  
  private muh Dne(long paramLong) {
    mNp mNp = new mNp((vwN)((Minecraft)this.Dne).Dne);
    try {
      return mNp.Dne(paramLong);
    } catch (lUu lUu) {
    
    } catch (IOException iOException) {}
    return null;
  }
  
  static int Dne() {
    return Dne;
  }
  
  static msA FWm(wWl paramwWl) {
    return (msA)paramwWl.Dne;
  }
  
  static void Dne(wWl paramwWl, int paramInt) {
    paramwWl.Dne(paramInt);
  }
  
  static Minecraft zGp(wWl paramwWl) {
    return (Minecraft)paramwWl.Dne;
  }
  
  static msA Qnq(wWl paramwWl) {
    return (msA)paramwWl.Dne;
  }
  
  protected void Dne(char paramChar, int paramInt) {
    if (paramInt == 59) {
      ((fZI)((Minecraft)this.Dne).Dne).udO = (((fZI)((Minecraft)this.Dne).Dne).udO == null) ? 1 : 0;
      ((Minecraft)this.Dne).Dne.FWm();
    } else if (paramChar == '\r') {
      Dne(this.Dne.get(2));
    } else {
      super.Dne(paramChar, paramInt);
    } 
  }
  
  static String Dne(wWl paramwWl, String paramString) {
    return (String)(paramwWl.Dne = (Long)paramString);
  }
  
  static Pee Dne(wWl paramwWl) {
    return (Pee)paramwWl.Dne;
  }
  
  static msA DyG(wWl paramwWl) {
    return (msA)paramwWl.Dne;
  }
  
  static msA aFZ(wWl paramwWl) {
    return (msA)paramwWl.Dne;
  }
  
  static {
    Dne = (Long)new Object();
  }
  
  static List Dne(wWl paramwWl) {
    return paramwWl.FWm;
  }
  
  static Pee FWm(wWl paramwWl) {
    return paramwWl.bzF;
  }
  
  private void aFZ(int paramInt1, int paramInt2, int paramInt3, int paramInt4) {
    ((Minecraft)this.Dne).Dne.Dne("/gui/gui.png");
    GL11.glColor4f(1.0F, 1.0F, 1.0F, 1.0F);
    GL11.glPushMatrix();
    GL11.glScalef(0.5F, 0.5F, 0.5F);
    FWm(paramInt1 * 2, paramInt2 * 2, 223, 0, 16, 15);
    GL11.glPopMatrix();
    if (paramInt3 >= paramInt1 && paramInt3 <= paramInt1 + 9 && paramInt4 >= paramInt2 && paramInt4 <= paramInt2 + 9)
      this.Dne = (Long)"Closed World"; 
  }
  
  static Minecraft Dne(wWl paramwWl) {
    return (Minecraft)paramwWl.Dne;
  }
  
  public void zGp() {
    // Byte code:
    //   0: invokestatic Dne : ()Lirb;
    //   3: astore_1
    //   4: aload_0
    //   5: getfield Dne : Ljava/util/List;
    //   8: aload_0
    //   9: new Pee
    //   12: dup
    //   13: iconst_1
    //   14: aload_0
    //   15: getfield FWm : I
    //   18: iconst_2
    //   19: idiv
    //   20: sipush #154
    //   23: isub
    //   24: aload_0
    //   25: getfield bzF : I
    //   28: bipush #52
    //   30: isub
    //   31: bipush #100
    //   33: bipush #20
    //   35: aload_1
    //   36: ldc 'mco.selectServer.select'
    //   38: invokevirtual Dne : (Ljava/lang/String;)Ljava/lang/String;
    //   41: invokespecial <init> : (IIIIILjava/lang/String;)V
    //   44: dup_x1
    //   45: putfield bzF : LPee;
    //   48: invokeinterface add : (Ljava/lang/Object;)Z
    //   53: pop
    //   54: aload_0
    //   55: getfield Dne : Ljava/util/List;
    //   58: aload_0
    //   59: new Pee
    //   62: dup
    //   63: iconst_2
    //   64: aload_0
    //   65: getfield FWm : I
    //   68: iconst_2
    //   69: idiv
    //   70: bipush #48
    //   72: isub
    //   73: aload_0
    //   74: getfield bzF : I
    //   77: bipush #52
    //   79: isub
    //   80: bipush #100
    //   82: bipush #20
    //   84: aload_1
    //   85: ldc 'mco.selectServer.create'
    //   87: invokevirtual Dne : (Ljava/lang/String;)Ljava/lang/String;
    //   90: invokespecial <init> : (IIIIILjava/lang/String;)V
    //   93: dup_x1
    //   94: putfield FWm : LPee;
    //   97: invokeinterface add : (Ljava/lang/Object;)Z
    //   102: pop
    //   103: aload_0
    //   104: getfield Dne : Ljava/util/List;
    //   107: aload_0
    //   108: new Pee
    //   111: dup
    //   112: iconst_3
    //   113: aload_0
    //   114: getfield FWm : I
    //   117: iconst_2
    //   118: idiv
    //   119: bipush #58
    //   121: iadd
    //   122: aload_0
    //   123: getfield bzF : I
    //   126: bipush #52
    //   128: isub
    //   129: bipush #100
    //   131: bipush #20
    //   133: aload_1
    //   134: ldc 'mco.selectServer.configure'
    //   136: invokevirtual Dne : (Ljava/lang/String;)Ljava/lang/String;
    //   139: invokespecial <init> : (IIIIILjava/lang/String;)V
    //   142: dup_x1
    //   143: putfield Dne : LPee;
    //   146: invokeinterface add : (Ljava/lang/Object;)Z
    //   151: pop
    //   152: aload_0
    //   153: getfield Dne : Ljava/util/List;
    //   156: aload_0
    //   157: new zXv
    //   160: dup
    //   161: iconst_4
    //   162: aload_0
    //   163: getfield FWm : I
    //   166: iconst_2
    //   167: idiv
    //   168: sipush #154
    //   171: isub
    //   172: aload_0
    //   173: getfield bzF : I
    //   176: bipush #28
    //   178: isub
    //   179: sipush #154
    //   182: bipush #20
    //   184: aload_1
    //   185: ldc 'mco.selectServer.moreinfo'
    //   187: invokevirtual Dne : (Ljava/lang/String;)Ljava/lang/String;
    //   190: invokespecial <init> : (IIIIILjava/lang/String;)V
    //   193: dup_x1
    //   194: putfield Dne : LzXv;
    //   197: invokeinterface add : (Ljava/lang/Object;)Z
    //   202: pop
    //   203: aload_0
    //   204: getfield Dne : Ljava/util/List;
    //   207: new Pee
    //   210: dup
    //   211: iconst_0
    //   212: aload_0
    //   213: getfield FWm : I
    //   216: iconst_2
    //   217: idiv
    //   218: bipush #6
    //   220: iadd
    //   221: aload_0
    //   222: getfield bzF : I
    //   225: bipush #28
    //   227: isub
    //   228: sipush #153
    //   231: bipush #20
    //   233: aload_1
    //   234: ldc 'gui.cancel'
    //   236: invokevirtual Dne : (Ljava/lang/String;)Ljava/lang/String;
    //   239: invokespecial <init> : (IIIIILjava/lang/String;)V
    //   242: invokeinterface add : (Ljava/lang/Object;)Z
    //   247: pop
    //   248: aload_0
    //   249: getfield Qnq : I
    //   252: iflt -> 273
    //   255: aload_0
    //   256: getfield Qnq : I
    //   259: aload_0
    //   260: getfield Dne : LTIk;
    //   263: invokevirtual Dne : ()I
    //   266: if_icmpge -> 273
    //   269: iconst_1
    //   270: goto -> 274
    //   273: iconst_0
    //   274: istore_2
    //   275: aload_0
    //   276: getfield bzF : LPee;
    //   279: iload_2
    //   280: ifeq -> 336
    //   283: aload_0
    //   284: getfield FWm : Ljava/util/List;
    //   287: aload_0
    //   288: getfield Qnq : I
    //   291: invokeinterface get : (I)Ljava/lang/Object;
    //   296: checkcast muh
    //   299: getfield bzF : Ljava/lang/String;
    //   302: ldc 'OPEN'
    //   304: invokevirtual equals : (Ljava/lang/Object;)Z
    //   307: ifeq -> 336
    //   310: aload_0
    //   311: getfield FWm : Ljava/util/List;
    //   314: aload_0
    //   315: getfield Qnq : I
    //   318: invokeinterface get : (I)Ljava/lang/Object;
    //   323: checkcast muh
    //   326: getfield Dne : Z
    //   329: ifne -> 336
    //   332: iconst_1
    //   333: goto -> 337
    //   336: iconst_0
    //   337: putfield Dne : Z
    //   340: aload_0
    //   341: getfield Dne : LPee;
    //   344: iload_2
    //   345: ifeq -> 387
    //   348: aload_0
    //   349: getfield Dne : Lnet/minecraft/client/Minecraft;
    //   352: getfield Dne : LvwN;
    //   355: getfield Dne : Ljava/lang/String;
    //   358: aload_0
    //   359: getfield FWm : Ljava/util/List;
    //   362: aload_0
    //   363: getfield Qnq : I
    //   366: invokeinterface get : (I)Ljava/lang/Object;
    //   371: checkcast muh
    //   374: getfield Qnq : Ljava/lang/String;
    //   377: invokevirtual equals : (Ljava/lang/Object;)Z
    //   380: ifeq -> 387
    //   383: iconst_1
    //   384: goto -> 388
    //   387: iconst_0
    //   388: putfield Dne : Z
    //   391: aload_0
    //   392: getfield FWm : LPee;
    //   395: aload_0
    //   396: getfield aFZ : I
    //   399: ifle -> 406
    //   402: iconst_1
    //   403: goto -> 407
    //   406: iconst_0
    //   407: putfield Dne : Z
    //   410: return
  }
  
  static msA zGp(wWl paramwWl) {
    return (msA)paramwWl.Dne;
  }
  
  static Minecraft FWm(wWl paramwWl) {
    return (Minecraft)paramwWl.Dne;
  }
  
  public void bzF() {
    super.bzF();
    this.zGp++;
    if (this.Dne.Dne()) {
      List list = this.Dne.Dne();
      for (muh muh : list) {
        for (muh muh1 : this.FWm) {
          if (muh.Dne == muh1.Dne) {
            muh.Dne(muh1);
            if (this.Dne != null && this.Dne.longValue() == muh.Dne) {
              this.Dne = null;
              muh.FWm = 0L;
            } 
          } 
        } 
      } 
      this.FWm = list;
      this.Dne.Dne();
    } 
    ((Pee)this.FWm).Dne = (this.aFZ > 0) ? 1 : 0;
  }
  
  static void Dne(wWl paramwWl, int paramInt1, int paramInt2, int paramInt3, int paramInt4) {
    paramwWl.bzF(paramInt1, paramInt2, paramInt3, paramInt4);
  }
  
  static int FWm() {
    return Dne++;
  }
  
  public void Dne(long paramLong) {
    this.Qnq = -1;
    this.Dne = Long.valueOf(paramLong);
  }
  
  static Minecraft aFZ(wWl paramwWl) {
    return (Minecraft)paramwWl.Dne;
  }
  
  static int Dne(wWl paramwWl) {
    return paramwWl.Qnq;
  }
  
  static Minecraft bzF(wWl paramwWl) {
    return (Minecraft)paramwWl.Dne;
  }
  
  private void bzF(int paramInt1, int paramInt2, int paramInt3, int paramInt4) {
    ((Minecraft)this.Dne).Dne.Dne("/gui/gui.png");
    GL11.glColor4f(1.0F, 1.0F, 1.0F, 1.0F);
    GL11.glPushMatrix();
    GL11.glScalef(0.5F, 0.5F, 0.5F);
    FWm(paramInt1 * 2, paramInt2 * 2, 191, 0, 16, 15);
    GL11.glPopMatrix();
    if (paramInt3 >= paramInt1 && paramInt3 <= paramInt1 + 9 && paramInt4 >= paramInt2 && paramInt4 <= paramInt2 + 9)
      this.Dne = (Long)"Expired World"; 
  }
  
  static int Dne(wWl paramwWl, int paramInt) {
    return paramwWl.aFZ = paramInt;
  }
  
  public void Dne(int paramInt1, int paramInt2, float paramFloat) {
    this.Dne = null;
    irb irb = irb.Dne();
    aFZ();
    this.Dne.Dne(paramInt1, paramInt2, paramFloat);
    Dne((msA)this.Dne, irb.Dne("mco.title"), this.FWm / 2, 20, 16777215);
    super.Dne(paramInt1, paramInt2, paramFloat);
    if (this.Dne != null)
      Dne((String)this.Dne, paramInt1, paramInt2); 
  }
  
  public void Dne() {
    Keyboard.enableRepeatEvents(true);
    this.Dne.clear();
    this.Dne = (Long)new ukD((vwN)((Minecraft)this.Dne).Dne);
    if (this.bzF == null) {
      this.bzF = true;
      this.Dne = (Long)new TIk(this);
    } else {
      this.Dne.Dne(this.FWm, this.bzF, 32, this.bzF - 64);
    } 
    (new nwv(this)).start();
    zGp();
  }
  
  protected void Dne(Pee paramPee) {
    if (paramPee.Dne != null)
      if (paramPee.aFZ == 1) {
        Dne(this.Qnq);
      } else if (paramPee.aFZ == 3) {
        List<muh> list = this.Dne.Dne();
        if (this.Qnq < list.size()) {
          muh muh1 = list.get(this.Qnq);
          muh muh2 = Dne(muh1.Dne);
          if (muh2 != null) {
            this.Dne.FWm();
            this.Dne.Dne(new JFs(this, muh2));
          } 
        } 
      } else if (paramPee.aFZ == 0) {
        this.Dne.FWm();
        this.Dne.Dne((qVZ)this.Dne);
      } else if (paramPee.aFZ == 2) {
        this.Dne.FWm();
        this.Dne.Dne(new LKa(this));
      } else if (paramPee.aFZ == 4) {
        this.Dne.Dne("http://realms.minecraft.net/");
      } else {
        this.Dne.Dne(paramPee);
      }  
  }
  
  protected void Dne(String paramString, int paramInt1, int paramInt2) {
    if (paramString != null) {
      int i = paramInt1 + 12;
      int j = paramInt2 - 12;
      int k = this.Dne.Dne(paramString);
      Dne(i - 3, j - 3, i + k + 3, j + 8 + 3, -1073741824, -1073741824);
      this.Dne.Dne(paramString, i, j, -1);
    } 
  }
  
  private void Dne(muh parammuh) {
    if (parammuh.DyG.equals(""))
      parammuh.DyG = Dne.div + "" + Character.MIN_VALUE; 
    parammuh.FWm = 61L;
    Qyv qyv = Qyv.Dne(parammuh.aFZ);
    Socket socket = null;
    DataInputStream dataInputStream = null;
    DataOutputStream dataOutputStream = null;
    try {
      socket = new Socket();
      socket.setSoTimeout(3000);
      socket.setTcpNoDelay(true);
      socket.setTrafficClass(18);
      socket.connect(new InetSocketAddress(qyv.Dne(), qyv.Dne()), 3000);
      dataInputStream = new DataInputStream(socket.getInputStream());
      dataOutputStream = new DataOutputStream(socket.getOutputStream());
      dataOutputStream.write(254);
      dataOutputStream.write(1);
      if (dataInputStream.read() != 255)
        throw new IOException("Bad message"); 
      String str = NER.Dne(dataInputStream, 256);
      char[] arrayOfChar = str.toCharArray();
      int i;
      for (i = 0; i < arrayOfChar.length; i++) {
        if (arrayOfChar[i] != 'ยง' && arrayOfChar[i] != '\000' && BAQ.Dne.indexOf(arrayOfChar[i]) < 0)
          arrayOfChar[i] = '?'; 
      } 
      str = new String(arrayOfChar);
      if (str.startsWith("ยง") && str.length() > 1) {
        String[] arrayOfString = str.substring(1).split("\000");
        if (geR.Dne(arrayOfString[0], 0) == 1) {
          parammuh.FWm = geR.Dne(arrayOfString[1], parammuh.FWm);
          parammuh.zGp = arrayOfString[2];
          i = geR.Dne(arrayOfString[4], 0);
          int j = geR.Dne(arrayOfString[5], 0);
          if (i >= 0 && j >= 0) {
            parammuh.DyG = Dne.div + "" + i;
          } else {
            parammuh.DyG = "" + Dne.IjH + "???";
          } 
        } else {
          parammuh.zGp = "???";
          parammuh.FWm = 62L;
          parammuh.DyG = "" + Dne.IjH + "???";
        } 
      } else {
        String[] arrayOfString = str.split("ยง");
        str = arrayOfString[0];
        i = -1;
        int j = -1;
        try {
          i = Integer.parseInt(arrayOfString[1]);
          j = Integer.parseInt(arrayOfString[2]);
        } catch (Exception exception) {}
        parammuh.FWm = Dne.div + str;
        if (i >= 0 && j > 0) {
          parammuh.DyG = Dne.div + "" + i;
        } else {
          parammuh.DyG = "" + Dne.IjH + "???";
        } 
        parammuh.zGp = "1.3";
        parammuh.FWm = 60L;
      } 
    } finally {
      try {
        if (dataInputStream != null)
          dataInputStream.close(); 
      } catch (Throwable throwable) {}
      try {
        if (dataOutputStream != null)
          dataOutputStream.close(); 
      } catch (Throwable throwable) {}
      try {
        if (socket != null)
          socket.close(); 
      } catch (Throwable throwable) {}
    } 
  }
  
  static void Dne(wWl paramwWl, muh parammuh) {
    paramwWl.Dne(parammuh);
  }
  
  static msA bzF(wWl paramwWl) {
    return (msA)paramwWl.Dne;
  }
  
  static void bzF(wWl paramwWl, int paramInt1, int paramInt2, int paramInt3, int paramInt4) {
    paramwWl.Qnq(paramInt1, paramInt2, paramInt3, paramInt4);
  }
  
  static Object Dne() {
    return Dne;
  }
  
  static void FWm(wWl paramwWl, int paramInt1, int paramInt2, int paramInt3, int paramInt4) {
    paramwWl.aFZ(paramInt1, paramInt2, paramInt3, paramInt4);
  }
  
  public wWl(qVZ paramqVZ) {
    this.Dne = (Long)paramqVZ;
  }
}


/* Location:              C:\Users\fract\Downloads\ERROR422.jar!\wWl.class
 * Java compiler version: 8 (52.0)
 * JD-Core Version:       1.1.3
 */