public class xIh extends orI {
  private int FWm;
  
  public long Dne;
  
  private int Dne;
  
  public boolean Dne(chN paramchN) {
    return (this.Dne >= 0);
  }
  
  public void Dne() {
    // Byte code:
    //   0: aload_0
    //   1: invokespecial Dne : ()V
    //   4: aload_0
    //   5: getfield Dne : I
    //   8: iconst_2
    //   9: if_icmpne -> 83
    //   12: aload_0
    //   13: getfield Dne : LQnq;
    //   16: aload_0
    //   17: getfield div : D
    //   20: aload_0
    //   21: getfield IjH : D
    //   24: aload_0
    //   25: getfield mrb : D
    //   28: ldc 'ambient.weather.thunder'
    //   30: ldc 10000.0
    //   32: ldc 0.8
    //   34: aload_0
    //   35: getfield Dne : Ljava/util/Random;
    //   38: invokevirtual nextFloat : ()F
    //   41: ldc 0.2
    //   43: fmul
    //   44: fadd
    //   45: invokevirtual Dne : (DDDLjava/lang/String;FF)V
    //   48: aload_0
    //   49: getfield Dne : LQnq;
    //   52: aload_0
    //   53: getfield div : D
    //   56: aload_0
    //   57: getfield IjH : D
    //   60: aload_0
    //   61: getfield mrb : D
    //   64: ldc 'random.explode'
    //   66: fconst_2
    //   67: ldc 0.5
    //   69: aload_0
    //   70: getfield Dne : Ljava/util/Random;
    //   73: invokevirtual nextFloat : ()F
    //   76: ldc 0.2
    //   78: fmul
    //   79: fadd
    //   80: invokevirtual Dne : (DDDLjava/lang/String;FF)V
    //   83: aload_0
    //   84: dup
    //   85: getfield Dne : I
    //   88: iconst_1
    //   89: isub
    //   90: putfield Dne : I
    //   93: aload_0
    //   94: getfield Dne : I
    //   97: ifge -> 270
    //   100: aload_0
    //   101: getfield FWm : I
    //   104: ifne -> 114
    //   107: aload_0
    //   108: invokevirtual g_ : ()V
    //   111: goto -> 270
    //   114: aload_0
    //   115: getfield Dne : I
    //   118: aload_0
    //   119: getfield Dne : Ljava/util/Random;
    //   122: bipush #10
    //   124: invokevirtual nextInt : (I)I
    //   127: ineg
    //   128: if_icmpge -> 270
    //   131: aload_0
    //   132: dup
    //   133: getfield FWm : I
    //   136: iconst_1
    //   137: isub
    //   138: putfield FWm : I
    //   141: aload_0
    //   142: iconst_1
    //   143: putfield Dne : I
    //   146: aload_0
    //   147: aload_0
    //   148: getfield Dne : Ljava/util/Random;
    //   151: invokevirtual nextLong : ()J
    //   154: putfield Dne : J
    //   157: aload_0
    //   158: getfield Dne : LQnq;
    //   161: getfield aFZ : Z
    //   164: ifne -> 270
    //   167: aload_0
    //   168: getfield Dne : LQnq;
    //   171: aload_0
    //   172: getfield div : D
    //   175: invokestatic FWm : (D)I
    //   178: aload_0
    //   179: getfield IjH : D
    //   182: invokestatic FWm : (D)I
    //   185: aload_0
    //   186: getfield mrb : D
    //   189: invokestatic FWm : (D)I
    //   192: bipush #10
    //   194: invokevirtual Dne : (IIII)Z
    //   197: ifeq -> 270
    //   200: aload_0
    //   201: getfield div : D
    //   204: invokestatic FWm : (D)I
    //   207: istore_1
    //   208: aload_0
    //   209: getfield IjH : D
    //   212: invokestatic FWm : (D)I
    //   215: istore_2
    //   216: aload_0
    //   217: getfield mrb : D
    //   220: invokestatic FWm : (D)I
    //   223: istore_3
    //   224: aload_0
    //   225: getfield Dne : LQnq;
    //   228: iload_1
    //   229: iload_2
    //   230: iload_3
    //   231: invokevirtual Dne : (III)I
    //   234: ifne -> 270
    //   237: getstatic zKP.Dne : Liqp;
    //   240: aload_0
    //   241: getfield Dne : LQnq;
    //   244: iload_1
    //   245: iload_2
    //   246: iload_3
    //   247: invokevirtual Dne : (LQnq;III)Z
    //   250: ifeq -> 270
    //   253: aload_0
    //   254: getfield Dne : LQnq;
    //   257: iload_1
    //   258: iload_2
    //   259: iload_3
    //   260: getstatic zKP.Dne : Liqp;
    //   263: getfield FWm : I
    //   266: invokevirtual FWm : (IIII)Z
    //   269: pop
    //   270: aload_0
    //   271: getfield Dne : I
    //   274: iflt -> 396
    //   277: aload_0
    //   278: getfield Dne : LQnq;
    //   281: getfield aFZ : Z
    //   284: ifeq -> 298
    //   287: aload_0
    //   288: getfield Dne : LQnq;
    //   291: iconst_2
    //   292: putfield Qnq : I
    //   295: goto -> 396
    //   298: ldc2_w 3.0
    //   301: dstore_1
    //   302: aload_0
    //   303: getfield Dne : LQnq;
    //   306: aload_0
    //   307: invokestatic Dne : ()LzjJ;
    //   310: aload_0
    //   311: getfield div : D
    //   314: dload_1
    //   315: dsub
    //   316: aload_0
    //   317: getfield IjH : D
    //   320: dload_1
    //   321: dsub
    //   322: aload_0
    //   323: getfield mrb : D
    //   326: dload_1
    //   327: dsub
    //   328: aload_0
    //   329: getfield div : D
    //   332: dload_1
    //   333: dadd
    //   334: aload_0
    //   335: getfield IjH : D
    //   338: ldc2_w 6.0
    //   341: dadd
    //   342: dload_1
    //   343: dadd
    //   344: aload_0
    //   345: getfield mrb : D
    //   348: dload_1
    //   349: dadd
    //   350: invokevirtual Dne : (DDDDDD)LbSp;
    //   353: invokevirtual FWm : (LsMa;LbSp;)Ljava/util/List;
    //   356: astore_3
    //   357: iconst_0
    //   358: istore #4
    //   360: iload #4
    //   362: aload_3
    //   363: invokeinterface size : ()I
    //   368: if_icmpge -> 396
    //   371: aload_3
    //   372: iload #4
    //   374: invokeinterface get : (I)Ljava/lang/Object;
    //   379: checkcast sMa
    //   382: astore #5
    //   384: aload #5
    //   386: aload_0
    //   387: invokevirtual Dne : (LxIh;)V
    //   390: iinc #4, 1
    //   393: goto -> 360
    //   396: return
  }
  
  protected void FWm(WkD paramWkD) {}
  
  protected void Dne(WkD paramWkD) {}
  
  protected void FWm() {}
  
  public xIh(Qnq paramQnq, double paramDouble1, double paramDouble2, double paramDouble3) {
    // Byte code:
    //   0: aload_0
    //   1: aload_1
    //   2: invokespecial <init> : (LQnq;)V
    //   5: aload_0
    //   6: lconst_0
    //   7: putfield Dne : J
    //   10: aload_0
    //   11: dload_2
    //   12: dload #4
    //   14: dload #6
    //   16: fconst_0
    //   17: fconst_0
    //   18: invokevirtual FWm : (DDDFF)V
    //   21: aload_0
    //   22: iconst_2
    //   23: putfield Dne : I
    //   26: aload_0
    //   27: aload_0
    //   28: getfield Dne : Ljava/util/Random;
    //   31: invokevirtual nextLong : ()J
    //   34: putfield Dne : J
    //   37: aload_0
    //   38: aload_0
    //   39: getfield Dne : Ljava/util/Random;
    //   42: iconst_3
    //   43: invokevirtual nextInt : (I)I
    //   46: iconst_1
    //   47: iadd
    //   48: putfield FWm : I
    //   51: aload_1
    //   52: getfield aFZ : Z
    //   55: ifne -> 269
    //   58: aload_1
    //   59: getfield aFZ : I
    //   62: iconst_2
    //   63: if_icmplt -> 269
    //   66: aload_1
    //   67: dload_2
    //   68: invokestatic FWm : (D)I
    //   71: dload #4
    //   73: invokestatic FWm : (D)I
    //   76: dload #6
    //   78: invokestatic FWm : (D)I
    //   81: bipush #10
    //   83: invokevirtual Dne : (IIII)Z
    //   86: ifeq -> 269
    //   89: dload_2
    //   90: invokestatic FWm : (D)I
    //   93: istore #8
    //   95: dload #4
    //   97: invokestatic FWm : (D)I
    //   100: istore #9
    //   102: dload #6
    //   104: invokestatic FWm : (D)I
    //   107: istore #10
    //   109: aload_1
    //   110: iload #8
    //   112: iload #9
    //   114: iload #10
    //   116: invokevirtual Dne : (III)I
    //   119: ifne -> 155
    //   122: getstatic zKP.Dne : Liqp;
    //   125: aload_1
    //   126: iload #8
    //   128: iload #9
    //   130: iload #10
    //   132: invokevirtual Dne : (LQnq;III)Z
    //   135: ifeq -> 155
    //   138: aload_1
    //   139: iload #8
    //   141: iload #9
    //   143: iload #10
    //   145: getstatic zKP.Dne : Liqp;
    //   148: getfield FWm : I
    //   151: invokevirtual FWm : (IIII)Z
    //   154: pop
    //   155: iconst_0
    //   156: istore #8
    //   158: iload #8
    //   160: iconst_4
    //   161: if_icmpge -> 269
    //   164: dload_2
    //   165: invokestatic FWm : (D)I
    //   168: aload_0
    //   169: getfield Dne : Ljava/util/Random;
    //   172: iconst_3
    //   173: invokevirtual nextInt : (I)I
    //   176: iadd
    //   177: iconst_1
    //   178: isub
    //   179: istore #9
    //   181: dload #4
    //   183: invokestatic FWm : (D)I
    //   186: aload_0
    //   187: getfield Dne : Ljava/util/Random;
    //   190: iconst_3
    //   191: invokevirtual nextInt : (I)I
    //   194: iadd
    //   195: iconst_1
    //   196: isub
    //   197: istore #10
    //   199: dload #6
    //   201: invokestatic FWm : (D)I
    //   204: aload_0
    //   205: getfield Dne : Ljava/util/Random;
    //   208: iconst_3
    //   209: invokevirtual nextInt : (I)I
    //   212: iadd
    //   213: iconst_1
    //   214: isub
    //   215: istore #11
    //   217: aload_1
    //   218: iload #9
    //   220: iload #10
    //   222: iload #11
    //   224: invokevirtual Dne : (III)I
    //   227: ifne -> 263
    //   230: getstatic zKP.Dne : Liqp;
    //   233: aload_1
    //   234: iload #9
    //   236: iload #10
    //   238: iload #11
    //   240: invokevirtual Dne : (LQnq;III)Z
    //   243: ifeq -> 263
    //   246: aload_1
    //   247: iload #9
    //   249: iload #10
    //   251: iload #11
    //   253: getstatic zKP.Dne : Liqp;
    //   256: getfield FWm : I
    //   259: invokevirtual FWm : (IIII)Z
    //   262: pop
    //   263: iinc #8, 1
    //   266: goto -> 158
    //   269: return
  }
}


/* Location:              C:\Users\fract\Downloads\ERROR422.jar!\xIh.class
 * Java compiler version: 8 (52.0)
 * JD-Core Version:       1.1.3
 */