public class XjO extends Jik {
  protected void Dne() {
    float f = 0.1F;
    for (byte b = 0; b <= 15; b++) {
      float f1 = 1.0F - b / 15.0F;
      this.Dne[b] = (1.0F - f1) / (f1 * 3.0F + 1.0F) * (1.0F - f) + f;
    } 
  }
  
  public boolean Dne(int paramInt1, int paramInt2) {
    return false;
  }
  
  public boolean FWm() {
    return false;
  }
  
  public float Dne(long paramLong, float paramFloat) {
    return 0.5F;
  }
  
  public boolean FWm(int paramInt1, int paramInt2) {
    return true;
  }
  
  public void FWm() {
    this.Dne = new yMz(OdI.IjH, 1.0F, 0.0F);
    this.Dne = 1;
    this.FWm = true;
    this.Dne = -1;
  }
  
  public ZfC Dne() {
    // Byte code:
    //   0: new aJO
    //   3: dup
    //   4: aload_0
    //   5: getfield Dne : LQnq;
    //   8: aload_0
    //   9: getfield Dne : LQnq;
    //   12: invokevirtual Dne : ()J
    //   15: invokespecial <init> : (LQnq;J)V
    //   18: areturn
  }
  
  public boolean Dne() {
    return false;
  }
  
  static {
  
  }
  
  public String Dne() {
    return "Nether";
  }
  
  public chN Dne(float paramFloat1, float paramFloat2) {
    // Byte code:
    //   0: aload_0
    //   1: getfield Dne : LQnq;
    //   4: invokevirtual Dne : ()LziS;
    //   7: ldc2_w 0.20000000298023224
    //   10: ldc2_w 0.029999999329447746
    //   13: ldc2_w 0.029999999329447746
    //   16: invokevirtual Dne : (DDD)LchN;
    //   19: areturn
  }
}


/* Location:              C:\Users\fract\Downloads\ERROR422.jar!\XjO.class
 * Java compiler version: 8 (52.0)
 * JD-Core Version:       1.1.3
 */