public class XSK implements Cwq {
  private final Qnq Dne;
  
  private final int bzF;
  
  private final int FWm;
  
  private final int Dne;
  
  public Qnq Dne() {
    return this.Dne;
  }
  
  public int Dne() {
    return this.Dne;
  }
  
  public XSK(Qnq paramQnq, int paramInt1, int paramInt2, int paramInt3) {
    this.Dne = paramQnq;
    this.Dne = paramInt1;
    this.FWm = paramInt2;
    this.bzF = paramInt3;
  }
  
  public int Qnq() {
    // Byte code:
    //   0: aload_0
    //   1: getfield Dne : LQnq;
    //   4: aload_0
    //   5: getfield Dne : I
    //   8: aload_0
    //   9: getfield FWm : I
    //   12: aload_0
    //   13: getfield bzF : I
    //   16: invokevirtual bzF : (III)I
    //   19: ireturn
  }
  
  public int FWm() {
    return this.FWm;
  }
  
  public double FWm() {
    return this.FWm + 0.5D;
  }
  
  public ipD Dne() {
    // Byte code:
    //   0: aload_0
    //   1: getfield Dne : LQnq;
    //   4: aload_0
    //   5: getfield Dne : I
    //   8: aload_0
    //   9: getfield FWm : I
    //   12: aload_0
    //   13: getfield bzF : I
    //   16: invokevirtual Dne : (III)LipD;
    //   19: areturn
  }
  
  public double Dne() {
    return this.Dne + 0.5D;
  }
  
  public int bzF() {
    return this.bzF;
  }
  
  public double bzF() {
    return this.bzF + 0.5D;
  }
}


/* Location:              C:\Users\fract\Downloads\ERROR422.jar!\XSK.class
 * Java compiler version: 8 (52.0)
 * JD-Core Version:       1.1.3
 */