public class Xxe extends DIk {
  public float IYC;
  
  private float JLG;
  
  public float xXN;
  
  private float YHU;
  
  public float bzF;
  
  public float aFZ;
  
  private float CZC;
  
  private float exS;
  
  public float zGp;
  
  private float iNQ;
  
  public float FWm;
  
  private float LoG;
  
  public float Qnq;
  
  public float Dne;
  
  public int Dne() {
    return 10;
  }
  
  public Xxe(Qnq paramQnq) {
    // Byte code:
    //   0: aload_0
    //   1: aload_1
    //   2: invokespecial <init> : (LQnq;)V
    //   5: aload_0
    //   6: fconst_0
    //   7: putfield Dne : F
    //   10: aload_0
    //   11: fconst_0
    //   12: putfield FWm : F
    //   15: aload_0
    //   16: fconst_0
    //   17: putfield bzF : F
    //   20: aload_0
    //   21: fconst_0
    //   22: putfield Qnq : F
    //   25: aload_0
    //   26: fconst_0
    //   27: putfield aFZ : F
    //   30: aload_0
    //   31: fconst_0
    //   32: putfield zGp : F
    //   35: aload_0
    //   36: fconst_0
    //   37: putfield xXN : F
    //   40: aload_0
    //   41: fconst_0
    //   42: putfield IYC : F
    //   45: aload_0
    //   46: fconst_0
    //   47: putfield YHU : F
    //   50: aload_0
    //   51: fconst_0
    //   52: putfield JLG : F
    //   55: aload_0
    //   56: fconst_0
    //   57: putfield exS : F
    //   60: aload_0
    //   61: fconst_0
    //   62: putfield iNQ : F
    //   65: aload_0
    //   66: fconst_0
    //   67: putfield CZC : F
    //   70: aload_0
    //   71: fconst_0
    //   72: putfield LoG : F
    //   75: aload_0
    //   76: ldc '/mob/squid.png'
    //   78: putfield bzF : Ljava/lang/String;
    //   81: aload_0
    //   82: ldc 0.95
    //   84: ldc 0.95
    //   86: invokevirtual Dne : (FF)V
    //   89: aload_0
    //   90: fconst_1
    //   91: aload_0
    //   92: getfield Dne : Ljava/util/Random;
    //   95: invokevirtual nextFloat : ()F
    //   98: fconst_1
    //   99: fadd
    //   100: fdiv
    //   101: ldc 0.2
    //   103: fmul
    //   104: putfield JLG : F
    //   107: return
  }
  
  public boolean cot() {
    return (this.IjH > 45.0D && this.IjH < 63.0D && super.cot());
  }
  
  public void Qnq(float paramFloat1, float paramFloat2) {
    Dne(this.XHL, this.Zpi, this.kGO);
  }
  
  protected String DyG() {
    return null;
  }
  
  protected void Dne(boolean paramBoolean, int paramInt) {
    // Byte code:
    //   0: aload_0
    //   1: getfield Dne : Ljava/util/Random;
    //   4: iconst_3
    //   5: iload_2
    //   6: iadd
    //   7: invokevirtual nextInt : (I)I
    //   10: iconst_1
    //   11: iadd
    //   12: istore_3
    //   13: iconst_0
    //   14: istore #4
    //   16: iload #4
    //   18: iload_3
    //   19: if_icmpge -> 46
    //   22: aload_0
    //   23: new NMq
    //   26: dup
    //   27: getstatic dEr.edi : LdEr;
    //   30: iconst_1
    //   31: iconst_0
    //   32: invokespecial <init> : (LdEr;II)V
    //   35: fconst_0
    //   36: invokevirtual Dne : (LNMq;F)LJiM;
    //   39: pop
    //   40: iinc #4, 1
    //   43: goto -> 16
    //   46: return
  }
  
  protected String div() {
    return null;
  }
  
  public void IjH() {
    // Byte code:
    //   0: aload_0
    //   1: invokespecial IjH : ()V
    //   4: aload_0
    //   5: aload_0
    //   6: getfield Dne : F
    //   9: putfield FWm : F
    //   12: aload_0
    //   13: aload_0
    //   14: getfield bzF : F
    //   17: putfield Qnq : F
    //   20: aload_0
    //   21: aload_0
    //   22: getfield aFZ : F
    //   25: putfield zGp : F
    //   28: aload_0
    //   29: aload_0
    //   30: getfield xXN : F
    //   33: putfield IYC : F
    //   36: aload_0
    //   37: dup
    //   38: getfield aFZ : F
    //   41: aload_0
    //   42: getfield JLG : F
    //   45: fadd
    //   46: putfield aFZ : F
    //   49: aload_0
    //   50: getfield aFZ : F
    //   53: ldc 6.2831855
    //   55: fcmpl
    //   56: ifle -> 100
    //   59: aload_0
    //   60: dup
    //   61: getfield aFZ : F
    //   64: ldc 6.2831855
    //   66: fsub
    //   67: putfield aFZ : F
    //   70: aload_0
    //   71: getfield Dne : Ljava/util/Random;
    //   74: bipush #10
    //   76: invokevirtual nextInt : (I)I
    //   79: ifne -> 100
    //   82: aload_0
    //   83: fconst_1
    //   84: aload_0
    //   85: getfield Dne : Ljava/util/Random;
    //   88: invokevirtual nextFloat : ()F
    //   91: fconst_1
    //   92: fadd
    //   93: fdiv
    //   94: ldc 0.2
    //   96: fmul
    //   97: putfield JLG : F
    //   100: aload_0
    //   101: invokevirtual Zpi : ()Z
    //   104: ifeq -> 382
    //   107: aload_0
    //   108: getfield aFZ : F
    //   111: ldc 3.1415927
    //   113: fcmpg
    //   114: ifge -> 180
    //   117: aload_0
    //   118: getfield aFZ : F
    //   121: ldc 3.1415927
    //   123: fdiv
    //   124: fstore_1
    //   125: aload_0
    //   126: fload_1
    //   127: fload_1
    //   128: fmul
    //   129: ldc 3.1415927
    //   131: fmul
    //   132: invokestatic Dne : (F)F
    //   135: ldc 3.1415927
    //   137: fmul
    //   138: ldc 0.25
    //   140: fmul
    //   141: putfield xXN : F
    //   144: fload_1
    //   145: f2d
    //   146: ldc2_w 0.75
    //   149: dcmpl
    //   150: ifle -> 166
    //   153: aload_0
    //   154: fconst_1
    //   155: putfield YHU : F
    //   158: aload_0
    //   159: fconst_1
    //   160: putfield exS : F
    //   163: goto -> 207
    //   166: aload_0
    //   167: dup
    //   168: getfield exS : F
    //   171: ldc 0.8
    //   173: fmul
    //   174: putfield exS : F
    //   177: goto -> 207
    //   180: aload_0
    //   181: fconst_0
    //   182: putfield xXN : F
    //   185: aload_0
    //   186: dup
    //   187: getfield YHU : F
    //   190: ldc 0.9
    //   192: fmul
    //   193: putfield YHU : F
    //   196: aload_0
    //   197: dup
    //   198: getfield exS : F
    //   201: ldc 0.99
    //   203: fmul
    //   204: putfield exS : F
    //   207: aload_0
    //   208: getfield Dne : LQnq;
    //   211: getfield aFZ : Z
    //   214: ifne -> 259
    //   217: aload_0
    //   218: aload_0
    //   219: getfield iNQ : F
    //   222: aload_0
    //   223: getfield YHU : F
    //   226: fmul
    //   227: f2d
    //   228: putfield XHL : D
    //   231: aload_0
    //   232: aload_0
    //   233: getfield CZC : F
    //   236: aload_0
    //   237: getfield YHU : F
    //   240: fmul
    //   241: f2d
    //   242: putfield Zpi : D
    //   245: aload_0
    //   246: aload_0
    //   247: getfield LoG : F
    //   250: aload_0
    //   251: getfield YHU : F
    //   254: fmul
    //   255: f2d
    //   256: putfield kGO : D
    //   259: aload_0
    //   260: getfield XHL : D
    //   263: aload_0
    //   264: getfield XHL : D
    //   267: dmul
    //   268: aload_0
    //   269: getfield kGO : D
    //   272: aload_0
    //   273: getfield kGO : D
    //   276: dmul
    //   277: dadd
    //   278: invokestatic Dne : (D)F
    //   281: fstore_1
    //   282: aload_0
    //   283: dup
    //   284: getfield IjH : F
    //   287: aload_0
    //   288: getfield XHL : D
    //   291: aload_0
    //   292: getfield kGO : D
    //   295: invokestatic atan2 : (DD)D
    //   298: d2f
    //   299: fneg
    //   300: ldc 180.0
    //   302: fmul
    //   303: ldc 3.1415927
    //   305: fdiv
    //   306: aload_0
    //   307: getfield IjH : F
    //   310: fsub
    //   311: ldc 0.1
    //   313: fmul
    //   314: fadd
    //   315: putfield IjH : F
    //   318: aload_0
    //   319: aload_0
    //   320: getfield IjH : F
    //   323: putfield mrb : F
    //   326: aload_0
    //   327: dup
    //   328: getfield bzF : F
    //   331: ldc 3.1415927
    //   333: aload_0
    //   334: getfield exS : F
    //   337: fmul
    //   338: ldc 1.5
    //   340: fmul
    //   341: fadd
    //   342: putfield bzF : F
    //   345: aload_0
    //   346: dup
    //   347: getfield Dne : F
    //   350: fload_1
    //   351: f2d
    //   352: aload_0
    //   353: getfield Zpi : D
    //   356: invokestatic atan2 : (DD)D
    //   359: d2f
    //   360: fneg
    //   361: ldc 180.0
    //   363: fmul
    //   364: ldc 3.1415927
    //   366: fdiv
    //   367: aload_0
    //   368: getfield Dne : F
    //   371: fsub
    //   372: ldc 0.1
    //   374: fmul
    //   375: fadd
    //   376: putfield Dne : F
    //   379: goto -> 469
    //   382: aload_0
    //   383: aload_0
    //   384: getfield aFZ : F
    //   387: invokestatic Dne : (F)F
    //   390: invokestatic Qnq : (F)F
    //   393: ldc 3.1415927
    //   395: fmul
    //   396: ldc 0.25
    //   398: fmul
    //   399: putfield xXN : F
    //   402: aload_0
    //   403: getfield Dne : LQnq;
    //   406: getfield aFZ : Z
    //   409: ifne -> 446
    //   412: aload_0
    //   413: dconst_0
    //   414: putfield XHL : D
    //   417: aload_0
    //   418: dup
    //   419: getfield Zpi : D
    //   422: ldc2_w 0.08
    //   425: dsub
    //   426: putfield Zpi : D
    //   429: aload_0
    //   430: dup
    //   431: getfield Zpi : D
    //   434: ldc2_w 0.9800000190734863
    //   437: dmul
    //   438: putfield Zpi : D
    //   441: aload_0
    //   442: dconst_0
    //   443: putfield kGO : D
    //   446: aload_0
    //   447: aload_0
    //   448: getfield Dne : F
    //   451: f2d
    //   452: ldc -90.0
    //   454: aload_0
    //   455: getfield Dne : F
    //   458: fsub
    //   459: f2d
    //   460: ldc2_w 0.02
    //   463: dmul
    //   464: dadd
    //   465: d2f
    //   466: putfield Dne : F
    //   469: return
  }
  
  protected float div() {
    return 0.4F;
  }
  
  protected String zGp() {
    return null;
  }
  
  public boolean Zpi() {
    // Byte code:
    //   0: aload_0
    //   1: getfield Dne : LQnq;
    //   4: aload_0
    //   5: getfield Dne : LbSp;
    //   8: dconst_0
    //   9: ldc2_w -0.6000000238418579
    //   12: dconst_0
    //   13: invokevirtual FWm : (DDD)LbSp;
    //   16: getstatic KFd.div : LKFd;
    //   19: aload_0
    //   20: invokevirtual Dne : (LbSp;LKFd;LsMa;)Z
    //   23: ireturn
  }
  
  protected int kGO() {
    return 0;
  }
  
  protected void div() {
    // Byte code:
    //   0: aload_0
    //   1: dup
    //   2: getfield Wwe : I
    //   5: iconst_1
    //   6: iadd
    //   7: putfield Wwe : I
    //   10: aload_0
    //   11: getfield Wwe : I
    //   14: bipush #100
    //   16: if_icmple -> 37
    //   19: aload_0
    //   20: aload_0
    //   21: aload_0
    //   22: fconst_0
    //   23: dup_x1
    //   24: putfield LoG : F
    //   27: dup_x1
    //   28: putfield CZC : F
    //   31: putfield iNQ : F
    //   34: goto -> 135
    //   37: aload_0
    //   38: getfield Dne : Ljava/util/Random;
    //   41: bipush #50
    //   43: invokevirtual nextInt : (I)I
    //   46: ifeq -> 83
    //   49: aload_0
    //   50: getfield udO : Z
    //   53: ifeq -> 83
    //   56: aload_0
    //   57: getfield iNQ : F
    //   60: fconst_0
    //   61: fcmpl
    //   62: ifne -> 135
    //   65: aload_0
    //   66: getfield CZC : F
    //   69: fconst_0
    //   70: fcmpl
    //   71: ifne -> 135
    //   74: aload_0
    //   75: getfield LoG : F
    //   78: fconst_0
    //   79: fcmpl
    //   80: ifne -> 135
    //   83: aload_0
    //   84: getfield Dne : Ljava/util/Random;
    //   87: invokevirtual nextFloat : ()F
    //   90: ldc 3.1415927
    //   92: fmul
    //   93: fconst_2
    //   94: fmul
    //   95: fstore_1
    //   96: aload_0
    //   97: fload_1
    //   98: invokestatic FWm : (F)F
    //   101: ldc 0.2
    //   103: fmul
    //   104: putfield iNQ : F
    //   107: aload_0
    //   108: ldc -0.1
    //   110: aload_0
    //   111: getfield Dne : Ljava/util/Random;
    //   114: invokevirtual nextFloat : ()F
    //   117: ldc 0.2
    //   119: fmul
    //   120: fadd
    //   121: putfield CZC : F
    //   124: aload_0
    //   125: fload_1
    //   126: invokestatic Dne : (F)F
    //   129: ldc 0.2
    //   131: fmul
    //   132: putfield LoG : F
    //   135: aload_0
    //   136: invokevirtual ZgS : ()V
    //   139: return
  }
}


/* Location:              C:\Users\fract\Downloads\ERROR422.jar!\Xxe.class
 * Java compiler version: 8 (52.0)
 * JD-Core Version:       1.1.3
 */