import java.util.Collection;
import java.util.HashMap;
import java.util.Iterator;
import java.util.List;

public class yDZ {
  public static final String Zpi;
  
  public static final String zGp;
  
  private static final HashMap bzF;
  
  public static final String DyG;
  
  public static final String Qnq;
  
  public static final String aFZ;
  
  public static final String Dne;
  
  private static final HashMap FWm;
  
  public static final String mrb;
  
  public static final String FWm;
  
  public static final String XHL;
  
  public static final String bzF;
  
  private static final HashMap Dne;
  
  public static final String div;
  
  public static final String IjH;
  
  private static final String[] Dne;
  
  static {
    // Byte code:
    //   0: ldc '+0-1-2-3&4-4+13'
    //   2: putstatic yDZ.bzF : Ljava/lang/String;
    //   5: aconst_null
    //   6: putstatic yDZ.Dne : Ljava/lang/String;
    //   9: new java/util/HashMap
    //   12: dup
    //   13: invokespecial <init> : ()V
    //   16: putstatic yDZ.Dne : Ljava/util/HashMap;
    //   19: new java/util/HashMap
    //   22: dup
    //   23: invokespecial <init> : ()V
    //   26: putstatic yDZ.FWm : Ljava/util/HashMap;
    //   29: getstatic yDZ.Dne : Ljava/util/HashMap;
    //   32: getstatic SXd.XHL : LSXd;
    //   35: invokevirtual Dne : ()I
    //   38: invokestatic valueOf : (I)Ljava/lang/Integer;
    //   41: ldc '0 & !1 & !2 & !3 & 0+6'
    //   43: invokevirtual put : (Ljava/lang/Object;Ljava/lang/Object;)Ljava/lang/Object;
    //   46: pop
    //   47: ldc '-0+1-2-3&4-4+13'
    //   49: putstatic yDZ.FWm : Ljava/lang/String;
    //   52: getstatic yDZ.Dne : Ljava/util/HashMap;
    //   55: getstatic SXd.FWm : LSXd;
    //   58: invokevirtual Dne : ()I
    //   61: invokestatic valueOf : (I)Ljava/lang/Integer;
    //   64: ldc '!0 & 1 & !2 & !3 & 1+6'
    //   66: invokevirtual put : (Ljava/lang/Object;Ljava/lang/Object;)Ljava/lang/Object;
    //   69: pop
    //   70: ldc '+0+1-2-3&4-4+13'
    //   72: putstatic yDZ.div : Ljava/lang/String;
    //   75: getstatic yDZ.Dne : Ljava/util/HashMap;
    //   78: getstatic SXd.kGO : LSXd;
    //   81: invokevirtual Dne : ()I
    //   84: invokestatic valueOf : (I)Ljava/lang/Integer;
    //   87: ldc '0 & 1 & !2 & !3 & 0+6'
    //   89: invokevirtual put : (Ljava/lang/Object;Ljava/lang/Object;)Ljava/lang/Object;
    //   92: pop
    //   93: ldc '+0-1+2-3&4-4+13'
    //   95: putstatic yDZ.zGp : Ljava/lang/String;
    //   98: getstatic yDZ.Dne : Ljava/util/HashMap;
    //   101: getstatic SXd.DyG : LSXd;
    //   104: invokevirtual Dne : ()I
    //   107: invokestatic valueOf : (I)Ljava/lang/Integer;
    //   110: ldc '0 & !1 & 2 & !3'
    //   112: invokevirtual put : (Ljava/lang/Object;Ljava/lang/Object;)Ljava/lang/Object;
    //   115: pop
    //   116: ldc '-0-1+2-3&4-4+13'
    //   118: putstatic yDZ.Qnq : Ljava/lang/String;
    //   121: getstatic yDZ.Dne : Ljava/util/HashMap;
    //   124: getstatic SXd.ceE : LSXd;
    //   127: invokevirtual Dne : ()I
    //   130: invokestatic valueOf : (I)Ljava/lang/Integer;
    //   133: ldc '!0 & !1 & 2 & !3 & 2+6'
    //   135: invokevirtual put : (Ljava/lang/Object;Ljava/lang/Object;)Ljava/lang/Object;
    //   138: pop
    //   139: ldc '-0+3-4+13'
    //   141: putstatic yDZ.aFZ : Ljava/lang/String;
    //   144: getstatic yDZ.Dne : Ljava/util/HashMap;
    //   147: getstatic SXd.Vxn : LSXd;
    //   150: invokevirtual Dne : ()I
    //   153: invokestatic valueOf : (I)Ljava/lang/Integer;
    //   156: ldc '!0 & !1 & !2 & 3 & 3+6'
    //   158: invokevirtual put : (Ljava/lang/Object;Ljava/lang/Object;)Ljava/lang/Object;
    //   161: pop
    //   162: getstatic yDZ.Dne : Ljava/util/HashMap;
    //   165: getstatic SXd.div : LSXd;
    //   168: invokevirtual Dne : ()I
    //   171: invokestatic valueOf : (I)Ljava/lang/Integer;
    //   174: ldc '!0 & !1 & 2 & 3'
    //   176: invokevirtual put : (Ljava/lang/Object;Ljava/lang/Object;)Ljava/lang/Object;
    //   179: pop
    //   180: getstatic yDZ.Dne : Ljava/util/HashMap;
    //   183: getstatic SXd.bzF : LSXd;
    //   186: invokevirtual Dne : ()I
    //   189: invokestatic valueOf : (I)Ljava/lang/Integer;
    //   192: ldc '!0 & 1 & !2 & 3 & 3+6'
    //   194: invokevirtual put : (Ljava/lang/Object;Ljava/lang/Object;)Ljava/lang/Object;
    //   197: pop
    //   198: ldc '+0-1-2+3&4-4+13'
    //   200: putstatic yDZ.DyG : Ljava/lang/String;
    //   203: getstatic yDZ.Dne : Ljava/util/HashMap;
    //   206: getstatic SXd.zGp : LSXd;
    //   209: invokevirtual Dne : ()I
    //   212: invokestatic valueOf : (I)Ljava/lang/Integer;
    //   215: ldc '0 & !1 & !2 & 3 & 3+6'
    //   217: invokevirtual put : (Ljava/lang/Object;Ljava/lang/Object;)Ljava/lang/Object;
    //   220: pop
    //   221: ldc '-0+1+2-3+13&4-4'
    //   223: putstatic yDZ.Zpi : Ljava/lang/String;
    //   226: getstatic yDZ.Dne : Ljava/util/HashMap;
    //   229: getstatic SXd.qLR : LSXd;
    //   232: invokevirtual Dne : ()I
    //   235: invokestatic valueOf : (I)Ljava/lang/Integer;
    //   238: ldc '!0 & 1 & 2 & !3 & 2+6'
    //   240: invokevirtual put : (Ljava/lang/Object;Ljava/lang/Object;)Ljava/lang/Object;
    //   243: pop
    //   244: getstatic yDZ.Dne : Ljava/util/HashMap;
    //   247: getstatic SXd.ooe : LSXd;
    //   250: invokevirtual Dne : ()I
    //   253: invokestatic valueOf : (I)Ljava/lang/Integer;
    //   256: ldc '!0 & 1 & 2 & 3 & 2+6'
    //   258: invokevirtual put : (Ljava/lang/Object;Ljava/lang/Object;)Ljava/lang/Object;
    //   261: pop
    //   262: ldc '+5-6-7'
    //   264: putstatic yDZ.mrb : Ljava/lang/String;
    //   267: getstatic yDZ.FWm : Ljava/util/HashMap;
    //   270: getstatic SXd.FWm : LSXd;
    //   273: invokevirtual Dne : ()I
    //   276: invokestatic valueOf : (I)Ljava/lang/Integer;
    //   279: ldc '5'
    //   281: invokevirtual put : (Ljava/lang/Object;Ljava/lang/Object;)Ljava/lang/Object;
    //   284: pop
    //   285: getstatic yDZ.FWm : Ljava/util/HashMap;
    //   288: getstatic SXd.Qnq : LSXd;
    //   291: invokevirtual Dne : ()I
    //   294: invokestatic valueOf : (I)Ljava/lang/Integer;
    //   297: ldc '5'
    //   299: invokevirtual put : (Ljava/lang/Object;Ljava/lang/Object;)Ljava/lang/Object;
    //   302: pop
    //   303: getstatic yDZ.FWm : Ljava/util/HashMap;
    //   306: getstatic SXd.zGp : LSXd;
    //   309: invokevirtual Dne : ()I
    //   312: invokestatic valueOf : (I)Ljava/lang/Integer;
    //   315: ldc '5'
    //   317: invokevirtual put : (Ljava/lang/Object;Ljava/lang/Object;)Ljava/lang/Object;
    //   320: pop
    //   321: getstatic yDZ.FWm : Ljava/util/HashMap;
    //   324: getstatic SXd.XHL : LSXd;
    //   327: invokevirtual Dne : ()I
    //   330: invokestatic valueOf : (I)Ljava/lang/Integer;
    //   333: ldc '5'
    //   335: invokevirtual put : (Ljava/lang/Object;Ljava/lang/Object;)Ljava/lang/Object;
    //   338: pop
    //   339: getstatic yDZ.FWm : Ljava/util/HashMap;
    //   342: getstatic SXd.div : LSXd;
    //   345: invokevirtual Dne : ()I
    //   348: invokestatic valueOf : (I)Ljava/lang/Integer;
    //   351: ldc '5'
    //   353: invokevirtual put : (Ljava/lang/Object;Ljava/lang/Object;)Ljava/lang/Object;
    //   356: pop
    //   357: getstatic yDZ.FWm : Ljava/util/HashMap;
    //   360: getstatic SXd.DyG : LSXd;
    //   363: invokevirtual Dne : ()I
    //   366: invokestatic valueOf : (I)Ljava/lang/Integer;
    //   369: ldc '5'
    //   371: invokevirtual put : (Ljava/lang/Object;Ljava/lang/Object;)Ljava/lang/Object;
    //   374: pop
    //   375: getstatic yDZ.FWm : Ljava/util/HashMap;
    //   378: getstatic SXd.Zpi : LSXd;
    //   381: invokevirtual Dne : ()I
    //   384: invokestatic valueOf : (I)Ljava/lang/Integer;
    //   387: ldc '5'
    //   389: invokevirtual put : (Ljava/lang/Object;Ljava/lang/Object;)Ljava/lang/Object;
    //   392: pop
    //   393: getstatic yDZ.FWm : Ljava/util/HashMap;
    //   396: getstatic SXd.ceE : LSXd;
    //   399: invokevirtual Dne : ()I
    //   402: invokestatic valueOf : (I)Ljava/lang/Integer;
    //   405: ldc '5'
    //   407: invokevirtual put : (Ljava/lang/Object;Ljava/lang/Object;)Ljava/lang/Object;
    //   410: pop
    //   411: ldc '-5+6-7'
    //   413: putstatic yDZ.IjH : Ljava/lang/String;
    //   416: ldc '+14&13-13'
    //   418: putstatic yDZ.XHL : Ljava/lang/String;
    //   421: new java/util/HashMap
    //   424: dup
    //   425: invokespecial <init> : ()V
    //   428: putstatic yDZ.bzF : Ljava/util/HashMap;
    //   431: bipush #32
    //   433: anewarray java/lang/String
    //   436: dup
    //   437: iconst_0
    //   438: ldc 'potion.prefix.mundane'
    //   440: aastore
    //   441: dup
    //   442: iconst_1
    //   443: ldc 'potion.prefix.uninteresting'
    //   445: aastore
    //   446: dup
    //   447: iconst_2
    //   448: ldc 'potion.prefix.bland'
    //   450: aastore
    //   451: dup
    //   452: iconst_3
    //   453: ldc 'potion.prefix.clear'
    //   455: aastore
    //   456: dup
    //   457: iconst_4
    //   458: ldc 'potion.prefix.milky'
    //   460: aastore
    //   461: dup
    //   462: iconst_5
    //   463: ldc 'potion.prefix.diffuse'
    //   465: aastore
    //   466: dup
    //   467: bipush #6
    //   469: ldc 'potion.prefix.artless'
    //   471: aastore
    //   472: dup
    //   473: bipush #7
    //   475: ldc 'potion.prefix.thin'
    //   477: aastore
    //   478: dup
    //   479: bipush #8
    //   481: ldc 'potion.prefix.awkward'
    //   483: aastore
    //   484: dup
    //   485: bipush #9
    //   487: ldc 'potion.prefix.flat'
    //   489: aastore
    //   490: dup
    //   491: bipush #10
    //   493: ldc 'potion.prefix.bulky'
    //   495: aastore
    //   496: dup
    //   497: bipush #11
    //   499: ldc 'potion.prefix.bungling'
    //   501: aastore
    //   502: dup
    //   503: bipush #12
    //   505: ldc 'potion.prefix.buttered'
    //   507: aastore
    //   508: dup
    //   509: bipush #13
    //   511: ldc 'potion.prefix.smooth'
    //   513: aastore
    //   514: dup
    //   515: bipush #14
    //   517: ldc 'potion.prefix.suave'
    //   519: aastore
    //   520: dup
    //   521: bipush #15
    //   523: ldc 'potion.prefix.debonair'
    //   525: aastore
    //   526: dup
    //   527: bipush #16
    //   529: ldc 'potion.prefix.thick'
    //   531: aastore
    //   532: dup
    //   533: bipush #17
    //   535: ldc 'potion.prefix.elegant'
    //   537: aastore
    //   538: dup
    //   539: bipush #18
    //   541: ldc 'potion.prefix.fancy'
    //   543: aastore
    //   544: dup
    //   545: bipush #19
    //   547: ldc 'potion.prefix.charming'
    //   549: aastore
    //   550: dup
    //   551: bipush #20
    //   553: ldc 'potion.prefix.dashing'
    //   555: aastore
    //   556: dup
    //   557: bipush #21
    //   559: ldc 'potion.prefix.refined'
    //   561: aastore
    //   562: dup
    //   563: bipush #22
    //   565: ldc 'potion.prefix.cordial'
    //   567: aastore
    //   568: dup
    //   569: bipush #23
    //   571: ldc 'potion.prefix.sparkling'
    //   573: aastore
    //   574: dup
    //   575: bipush #24
    //   577: ldc 'potion.prefix.potent'
    //   579: aastore
    //   580: dup
    //   581: bipush #25
    //   583: ldc 'potion.prefix.foul'
    //   585: aastore
    //   586: dup
    //   587: bipush #26
    //   589: ldc 'potion.prefix.odorless'
    //   591: aastore
    //   592: dup
    //   593: bipush #27
    //   595: ldc 'potion.prefix.rank'
    //   597: aastore
    //   598: dup
    //   599: bipush #28
    //   601: ldc 'potion.prefix.harsh'
    //   603: aastore
    //   604: dup
    //   605: bipush #29
    //   607: ldc 'potion.prefix.acrid'
    //   609: aastore
    //   610: dup
    //   611: bipush #30
    //   613: ldc 'potion.prefix.gross'
    //   615: aastore
    //   616: dup
    //   617: bipush #31
    //   619: ldc 'potion.prefix.stinky'
    //   621: aastore
    //   622: putstatic yDZ.Dne : [Ljava/lang/String;
    //   625: return
  }
  
  private static int Dne(int paramInt1, int paramInt2) {
    return Dne(paramInt1, paramInt2) ? 1 : 0;
  }
  
  public static int Dne(int paramInt, String paramString) {
    byte b1 = 0;
    int i = paramString.length();
    boolean bool1 = false;
    boolean bool2 = false;
    boolean bool3 = false;
    boolean bool4 = false;
    int j = 0;
    for (byte b2 = b1; b2 < i; b2++) {
      char c = paramString.charAt(b2);
      if (c >= '0' && c <= '9') {
        j *= 10;
        j += c - 48;
        bool1 = true;
      } else if (c == '!') {
        if (bool1) {
          paramInt = Dne(paramInt, j, bool3, bool2, bool4);
          bool4 = false;
          bool2 = false;
          bool3 = false;
          bool1 = false;
          j = 0;
        } 
        bool2 = true;
      } else if (c == '-') {
        if (bool1) {
          paramInt = Dne(paramInt, j, bool3, bool2, bool4);
          bool4 = false;
          bool2 = false;
          bool3 = false;
          bool1 = false;
          j = 0;
        } 
        bool3 = true;
      } else if (c == '+') {
        if (bool1) {
          paramInt = Dne(paramInt, j, bool3, bool2, bool4);
          bool4 = false;
          bool2 = false;
          bool3 = false;
          bool1 = false;
          j = 0;
        } 
      } else if (c == '&') {
        if (bool1) {
          paramInt = Dne(paramInt, j, bool3, bool2, bool4);
          bool4 = false;
          bool2 = false;
          bool3 = false;
          bool1 = false;
          j = 0;
        } 
        bool4 = true;
      } 
    } 
    if (bool1)
      paramInt = Dne(paramInt, j, bool3, bool2, bool4); 
    return paramInt & 0x7FFF;
  }
  
  public static String Dne(int paramInt) {
    int i = Dne(paramInt);
    return Dne[i];
  }
  
  public static int Dne(int paramInt) {
    return Dne(paramInt, 5, 4, 3, 2, 1);
  }
  
  public static int Dne(int paramInt, boolean paramBoolean) {
    if (!paramBoolean) {
      if (bzF.containsKey(Integer.valueOf(paramInt)))
        return ((Integer)bzF.get(Integer.valueOf(paramInt))).intValue(); 
      int i = Dne(Dne(paramInt, false));
      bzF.put(Integer.valueOf(paramInt), Integer.valueOf(i));
      return i;
    } 
    return Dne(Dne(paramInt, paramBoolean));
  }
  
  public static boolean Dne(Collection paramCollection) {
    Iterator<NAx> iterator = paramCollection.iterator();
    while (true) {
      if (!iterator.hasNext())
        return true; 
      NAx nAx = iterator.next();
      if (!nAx.FWm())
        return false; 
    } 
  }
  
  public static List Dne(int paramInt, boolean paramBoolean) {
    // Byte code:
    //   0: aconst_null
    //   1: astore_2
    //   2: getstatic SXd.Dne : [LSXd;
    //   5: astore_3
    //   6: aload_3
    //   7: arraylength
    //   8: istore #4
    //   10: iconst_0
    //   11: istore #5
    //   13: iload #5
    //   15: iload #4
    //   17: if_icmpge -> 270
    //   20: aload_3
    //   21: iload #5
    //   23: aaload
    //   24: astore #6
    //   26: aload #6
    //   28: ifnull -> 264
    //   31: aload #6
    //   33: invokevirtual Qnq : ()Z
    //   36: ifeq -> 43
    //   39: iload_1
    //   40: ifeq -> 264
    //   43: getstatic yDZ.Dne : Ljava/util/HashMap;
    //   46: aload #6
    //   48: invokevirtual Dne : ()I
    //   51: invokestatic valueOf : (I)Ljava/lang/Integer;
    //   54: invokevirtual get : (Ljava/lang/Object;)Ljava/lang/Object;
    //   57: checkcast java/lang/String
    //   60: astore #7
    //   62: aload #7
    //   64: ifnull -> 264
    //   67: aload #7
    //   69: iconst_0
    //   70: aload #7
    //   72: invokevirtual length : ()I
    //   75: iload_0
    //   76: invokestatic Dne : (Ljava/lang/String;III)I
    //   79: istore #8
    //   81: iload #8
    //   83: ifle -> 264
    //   86: iconst_0
    //   87: istore #9
    //   89: getstatic yDZ.FWm : Ljava/util/HashMap;
    //   92: aload #6
    //   94: invokevirtual Dne : ()I
    //   97: invokestatic valueOf : (I)Ljava/lang/Integer;
    //   100: invokevirtual get : (Ljava/lang/Object;)Ljava/lang/Object;
    //   103: checkcast java/lang/String
    //   106: astore #10
    //   108: aload #10
    //   110: ifnull -> 135
    //   113: aload #10
    //   115: iconst_0
    //   116: aload #10
    //   118: invokevirtual length : ()I
    //   121: iload_0
    //   122: invokestatic Dne : (Ljava/lang/String;III)I
    //   125: istore #9
    //   127: iload #9
    //   129: ifge -> 135
    //   132: iconst_0
    //   133: istore #9
    //   135: aload #6
    //   137: invokevirtual Dne : ()Z
    //   140: ifeq -> 149
    //   143: iconst_1
    //   144: istore #8
    //   146: goto -> 213
    //   149: sipush #1200
    //   152: iload #8
    //   154: iconst_3
    //   155: imul
    //   156: iload #8
    //   158: iconst_1
    //   159: isub
    //   160: iconst_2
    //   161: imul
    //   162: iadd
    //   163: imul
    //   164: istore #8
    //   166: iload #8
    //   168: iload #9
    //   170: ishr
    //   171: istore #8
    //   173: iload #8
    //   175: i2d
    //   176: aload #6
    //   178: invokevirtual Dne : ()D
    //   181: dmul
    //   182: invokestatic round : (D)J
    //   185: l2i
    //   186: istore #8
    //   188: iload_0
    //   189: sipush #16384
    //   192: iand
    //   193: ifeq -> 213
    //   196: iload #8
    //   198: i2d
    //   199: ldc2_w 0.75
    //   202: dmul
    //   203: ldc2_w 0.5
    //   206: dadd
    //   207: invokestatic round : (D)J
    //   210: l2i
    //   211: istore #8
    //   213: aload_2
    //   214: ifnonnull -> 225
    //   217: new java/util/ArrayList
    //   220: dup
    //   221: invokespecial <init> : ()V
    //   224: astore_2
    //   225: new NAx
    //   228: dup
    //   229: aload #6
    //   231: invokevirtual Dne : ()I
    //   234: iload #8
    //   236: iload #9
    //   238: invokespecial <init> : (III)V
    //   241: astore #11
    //   243: iload_0
    //   244: sipush #16384
    //   247: iand
    //   248: ifeq -> 257
    //   251: aload #11
    //   253: iconst_1
    //   254: invokevirtual Dne : (Z)V
    //   257: aload_2
    //   258: aload #11
    //   260: invokevirtual add : (Ljava/lang/Object;)Z
    //   263: pop
    //   264: iinc #5, 1
    //   267: goto -> 13
    //   270: aload_2
    //   271: areturn
  }
  
  public static int Dne(Collection paramCollection) {
    int i = 3694022;
    if (paramCollection != null && !paramCollection.isEmpty()) {
      float f1 = 0.0F;
      float f2 = 0.0F;
      float f3 = 0.0F;
      float f4 = 0.0F;
      for (NAx nAx : paramCollection) {
        int j = SXd.Dne[nAx.Dne()].bzF();
        for (byte b = 0; b <= nAx.bzF(); b++) {
          f1 += (j >> 16 & 0xFF) / 255.0F;
          f2 += (j >> 8 & 0xFF) / 255.0F;
          f3 += (j >> 0 & 0xFF) / 255.0F;
          f4++;
        } 
      } 
      f1 = f1 / f4 * 255.0F;
      f2 = f2 / f4 * 255.0F;
      f3 = f3 / f4 * 255.0F;
      return (int)f1 << 16 | (int)f2 << 8 | (int)f3;
    } 
    return i;
  }
  
  private static int Dne(boolean paramBoolean1, boolean paramBoolean2, boolean paramBoolean3, int paramInt1, int paramInt2, int paramInt3, int paramInt4) {
    int i = 0;
    if (paramBoolean1) {
      i = FWm(paramInt4, paramInt2);
    } else if (paramInt1 != -1) {
      if (paramInt1 == 0 && FWm(paramInt4) == paramInt2) {
        i = 1;
      } else if (paramInt1 == 1 && FWm(paramInt4) > paramInt2) {
        i = 1;
      } else if (paramInt1 == 2 && FWm(paramInt4) < paramInt2) {
        i = 1;
      } 
    } else {
      i = Dne(paramInt4, paramInt2);
    } 
    if (paramBoolean2)
      i *= paramInt3; 
    if (paramBoolean3)
      i *= -1; 
    return i;
  }
  
  private static int FWm(int paramInt) {
    byte b;
    for (b = 0; paramInt > 0; b++)
      paramInt &= paramInt - 1; 
    return b;
  }
  
  private static int Dne(String paramString, int paramInt1, int paramInt2, int paramInt3) {
    if (paramInt1 < paramString.length() && paramInt2 >= 0 && paramInt1 < paramInt2) {
      int i = paramString.indexOf('|', paramInt1);
      if (i >= 0 && i < paramInt2) {
        int i2 = Dne(paramString, paramInt1, i - 1, paramInt3);
        if (i2 > 0)
          return i2; 
        int i3 = Dne(paramString, i + 1, paramInt2, paramInt3);
        return (i3 > 0) ? i3 : 0;
      } 
      int j = paramString.indexOf('&', paramInt1);
      if (j >= 0 && j < paramInt2) {
        int i2 = Dne(paramString, paramInt1, j - 1, paramInt3);
        if (i2 <= 0)
          return 0; 
        int i3 = Dne(paramString, j + 1, paramInt2, paramInt3);
        return (i3 <= 0) ? 0 : ((i2 > i3) ? i2 : i3);
      } 
      boolean bool1 = false;
      boolean bool2 = false;
      boolean bool3 = false;
      boolean bool4 = false;
      boolean bool5 = false;
      byte b = -1;
      int k = 0;
      int m = 0;
      int n = 0;
      for (int i1 = paramInt1; i1 < paramInt2; i1++) {
        char c = paramString.charAt(i1);
        if (c >= '0' && c <= '9') {
          if (bool1) {
            m = c - 48;
            bool2 = true;
          } else {
            k *= 10;
            k += c - 48;
            bool3 = true;
          } 
        } else if (c == '*') {
          bool1 = true;
        } else if (c == '!') {
          if (bool3) {
            n += Dne(bool4, bool2, bool5, b, k, m, paramInt3);
            bool4 = false;
            bool5 = false;
            bool1 = false;
            bool2 = false;
            bool3 = false;
            m = 0;
            k = 0;
            b = -1;
          } 
          bool4 = true;
        } else if (c == '-') {
          if (bool3) {
            n += Dne(bool4, bool2, bool5, b, k, m, paramInt3);
            bool4 = false;
            bool5 = false;
            bool1 = false;
            bool2 = false;
            bool3 = false;
            m = 0;
            k = 0;
            b = -1;
          } 
          bool5 = true;
        } else if (c != '=' && c != '<' && c != '>') {
          if (c == '+' && bool3) {
            n += Dne(bool4, bool2, bool5, b, k, m, paramInt3);
            bool4 = false;
            bool5 = false;
            bool1 = false;
            bool2 = false;
            bool3 = false;
            m = 0;
            k = 0;
            b = -1;
          } 
        } else {
          if (bool3) {
            n += Dne(bool4, bool2, bool5, b, k, m, paramInt3);
            bool4 = false;
            bool5 = false;
            bool1 = false;
            bool2 = false;
            bool3 = false;
            m = 0;
            k = 0;
            b = -1;
          } 
          if (c == '=') {
            b = 0;
          } else if (c == '<') {
            b = 2;
          } else if (c == '>') {
            b = 1;
          } 
        } 
      } 
      if (bool3)
        n += Dne(bool4, bool2, bool5, b, k, m, paramInt3); 
      return n;
    } 
    return 0;
  }
  
  private static int Dne(int paramInt1, int paramInt2, boolean paramBoolean1, boolean paramBoolean2, boolean paramBoolean3) {
    if (paramBoolean3) {
      if (!Dne(paramInt1, paramInt2))
        return 0; 
    } else if (paramBoolean1) {
      paramInt1 &= 1 << paramInt2 ^ 0xFFFFFFFF;
    } else if (paramBoolean2) {
      if ((paramInt1 & 1 << paramInt2) == 0) {
        paramInt1 |= 1 << paramInt2;
      } else {
        paramInt1 &= 1 << paramInt2 ^ 0xFFFFFFFF;
      } 
    } else {
      paramInt1 |= 1 << paramInt2;
    } 
    return paramInt1;
  }
  
  public static int Dne(int paramInt1, int paramInt2, int paramInt3, int paramInt4, int paramInt5, int paramInt6) {
    return (Dne(paramInt1, paramInt2) ? 16 : 0) | (Dne(paramInt1, paramInt3) ? 8 : 0) | (Dne(paramInt1, paramInt4) ? 4 : 0) | (Dne(paramInt1, paramInt5) ? 2 : 0) | (Dne(paramInt1, paramInt6) ? 1 : 0);
  }
  
  private static int FWm(int paramInt1, int paramInt2) {
    return Dne(paramInt1, paramInt2) ? 0 : 1;
  }
  
  public static boolean Dne(int paramInt1, int paramInt2) {
    return ((paramInt1 & 1 << paramInt2) != 0);
  }
}


/* Location:              C:\Users\fract\Downloads\ERROR422.jar!\yDZ.class
 * Java compiler version: 8 (52.0)
 * JD-Core Version:       1.1.3
 */