public class yrf {
  public static yrf Dne = new yrf();
  
  private GON Dne;
  
  private RPI Dne = (RPI)new GON();
  
  public yrf() {
    this.Dne = new RPI();
  }
  
  public void Dne(zKP paramzKP, int paramInt, float paramFloat) {
    // Byte code:
    //   0: aload_1
    //   1: getfield FWm : I
    //   4: getstatic zKP.wns : LzKP;
    //   7: getfield FWm : I
    //   10: if_icmpne -> 30
    //   13: getstatic XWr.Dne : LXWr;
    //   16: aload_0
    //   17: getfield Dne : LRPI;
    //   20: dconst_0
    //   21: dconst_0
    //   22: dconst_0
    //   23: fconst_0
    //   24: invokevirtual Dne : (LipD;DDDF)V
    //   27: goto -> 44
    //   30: getstatic XWr.Dne : LXWr;
    //   33: aload_0
    //   34: getfield Dne : LGON;
    //   37: dconst_0
    //   38: dconst_0
    //   39: dconst_0
    //   40: fconst_0
    //   41: invokevirtual Dne : (LipD;DDDF)V
    //   44: return
  }
}


/* Location:              C:\Users\fract\Downloads\ERROR422.jar!\yrf.class
 * Java compiler version: 8 (52.0)
 * JD-Core Version:       1.1.3
 */