public class yws extends cMv {
  private Class Dne;
  
  private int Dne;
  
  private FUH Dne;
  
  private float Dne;
  
  private float FWm;
  
  protected sMa Dne;
  
  public void Dne() {
    this.Dne = 40 + this.Dne.Dne().nextInt(40);
  }
  
  public void FWm() {
    this.Dne = null;
  }
  
  public void bzF() {
    this.Dne.Dne().Dne(this.Dne.div, this.Dne.IjH + this.Dne.c_(), this.Dne.mrb, 10.0F, this.Dne.udO());
    this.Dne--;
  }
  
  public yws(FUH paramFUH, Class paramClass, float paramFloat1, float paramFloat2) {
    this.Dne = paramFUH;
    this.Dne = (sMa)paramClass;
    this.Dne = paramFloat1;
    this.FWm = paramFloat2;
    Dne(2);
  }
  
  public boolean FWm() {
    return !this.Dne.udO() ? false : ((this.Dne.Dne(this.Dne) > (this.Dne * this.Dne)) ? false : ((this.Dne > null)));
  }
  
  public yws(FUH paramFUH, Class paramClass, float paramFloat) {
    this.Dne = paramFUH;
    this.Dne = (sMa)paramClass;
    this.Dne = paramFloat;
    this.FWm = 0.02F;
    Dne(2);
  }
  
  public boolean Dne() {
    // Byte code:
    //   0: aload_0
    //   1: getfield Dne : LFUH;
    //   4: invokevirtual Dne : ()Ljava/util/Random;
    //   7: invokevirtual nextFloat : ()F
    //   10: aload_0
    //   11: getfield FWm : F
    //   14: fcmpl
    //   15: iflt -> 20
    //   18: iconst_0
    //   19: ireturn
    //   20: aload_0
    //   21: getfield Dne : Ljava/lang/Class;
    //   24: ldc FiG
    //   26: if_acmpne -> 55
    //   29: aload_0
    //   30: aload_0
    //   31: getfield Dne : LFUH;
    //   34: getfield Dne : LQnq;
    //   37: aload_0
    //   38: getfield Dne : LFUH;
    //   41: aload_0
    //   42: getfield Dne : F
    //   45: f2d
    //   46: invokevirtual Dne : (LsMa;D)LFiG;
    //   49: putfield Dne : LsMa;
    //   52: goto -> 100
    //   55: aload_0
    //   56: aload_0
    //   57: getfield Dne : LFUH;
    //   60: getfield Dne : LQnq;
    //   63: aload_0
    //   64: getfield Dne : Ljava/lang/Class;
    //   67: aload_0
    //   68: getfield Dne : LFUH;
    //   71: getfield Dne : LbSp;
    //   74: aload_0
    //   75: getfield Dne : F
    //   78: f2d
    //   79: ldc2_w 3.0
    //   82: aload_0
    //   83: getfield Dne : F
    //   86: f2d
    //   87: invokevirtual FWm : (DDD)LbSp;
    //   90: aload_0
    //   91: getfield Dne : LFUH;
    //   94: invokevirtual Dne : (Ljava/lang/Class;LbSp;LsMa;)LsMa;
    //   97: putfield Dne : LsMa;
    //   100: aload_0
    //   101: getfield Dne : LsMa;
    //   104: ifnull -> 111
    //   107: iconst_1
    //   108: goto -> 112
    //   111: iconst_0
    //   112: ireturn
  }
}


/* Location:              C:\Users\fract\Downloads\ERROR422.jar!\yws.class
 * Java compiler version: 8 (52.0)
 * JD-Core Version:       1.1.3
 */