public class ZFJ extends LHi {
  public float Dne(int paramInt1, int paramInt2, int paramInt3) {
    // Byte code:
    //   0: aload_0
    //   1: getfield Dne : LQnq;
    //   4: iload_1
    //   5: iload_2
    //   6: iload_3
    //   7: invokevirtual Dne : (III)F
    //   10: ldc 0.5
    //   12: fsub
    //   13: freturn
  }
  
  static {
  
  }
  
  public ZFJ(Qnq paramQnq) {
    super(paramQnq);
    this.udO *= 6.0F;
    Dne(this.ooe * 6.0F, this.trS * 6.0F);
  }
  
  public int Dne() {
    return 100;
  }
  
  public int Dne(sMa paramsMa) {
    return 50;
  }
}


/* Location:              C:\Users\fract\Downloads\ERROR422.jar!\ZFJ.class
 * Java compiler version: 8 (52.0)
 * JD-Core Version:       1.1.3
 */