public class ZgS extends OdI {
  static {
  
  }
  
  public ZgS(int paramInt) {
    // Byte code:
    //   0: aload_0
    //   1: iload_1
    //   2: invokespecial <init> : (I)V
    //   5: aload_0
    //   6: getfield Dne : LFnk;
    //   9: bipush #-100
    //   11: putfield Qnq : I
    //   14: aload_0
    //   15: getfield Dne : LFnk;
    //   18: bipush #-100
    //   20: putfield aFZ : I
    //   23: aload_0
    //   24: getfield Dne : LFnk;
    //   27: bipush #-100
    //   29: putfield zGp : I
    //   32: aload_0
    //   33: getfield Dne : LFnk;
    //   36: iconst_1
    //   37: putfield div : I
    //   40: aload_0
    //   41: getfield Dne : LFnk;
    //   44: iconst_1
    //   45: putfield udO : I
    //   48: aload_0
    //   49: getstatic zKP.Dne : LUyU;
    //   52: getfield FWm : I
    //   55: i2b
    //   56: putfield Dne : B
    //   59: aload_0
    //   60: getfield Dne : Ljava/util/List;
    //   63: invokeinterface clear : ()V
    //   68: aload_0
    //   69: getfield FWm : Ljava/util/List;
    //   72: invokeinterface clear : ()V
    //   77: aload_0
    //   78: getfield bzF : Ljava/util/List;
    //   81: invokeinterface clear : ()V
    //   86: aload_0
    //   87: getfield FWm : Ljava/util/List;
    //   90: new oIf
    //   93: dup
    //   94: ldc Ahh
    //   96: bipush #8
    //   98: iconst_4
    //   99: bipush #8
    //   101: invokespecial <init> : (Ljava/lang/Class;III)V
    //   104: invokeinterface add : (Ljava/lang/Object;)Z
    //   109: pop
    //   110: return
  }
}


/* Location:              C:\Users\fract\Downloads\ERROR422.jar!\ZgS.class
 * Java compiler version: 8 (52.0)
 * JD-Core Version:       1.1.3
 */