public class ZkF extends ZOO {
  CDE Dne;
  
  FUH Dne;
  
  public boolean Dne() {
    // Byte code:
    //   0: aload_0
    //   1: getfield Dne : LCDE;
    //   4: invokevirtual Dne : ()LuQr;
    //   7: astore_1
    //   8: aload_1
    //   9: ifnonnull -> 14
    //   12: iconst_0
    //   13: ireturn
    //   14: aload_0
    //   15: aload_1
    //   16: aload_0
    //   17: getfield Dne : LCDE;
    //   20: invokevirtual Dne : (LFUH;)LFUH;
    //   23: putfield Dne : LFUH;
    //   26: aload_0
    //   27: aload_0
    //   28: getfield Dne : LFUH;
    //   31: iconst_0
    //   32: invokevirtual Dne : (LFUH;Z)Z
    //   35: ifne -> 77
    //   38: aload_0
    //   39: getfield FWm : LFUH;
    //   42: invokevirtual Dne : ()Ljava/util/Random;
    //   45: bipush #20
    //   47: invokevirtual nextInt : (I)I
    //   50: ifne -> 75
    //   53: aload_0
    //   54: aload_1
    //   55: aload_0
    //   56: getfield Dne : LCDE;
    //   59: invokevirtual Dne : (LFUH;)LFiG;
    //   62: putfield Dne : LFUH;
    //   65: aload_0
    //   66: aload_0
    //   67: getfield Dne : LFUH;
    //   70: iconst_0
    //   71: invokevirtual Dne : (LFUH;Z)Z
    //   74: ireturn
    //   75: iconst_0
    //   76: ireturn
    //   77: iconst_1
    //   78: ireturn
  }
  
  public ZkF(CDE paramCDE) {
    super(paramCDE, 16.0F, false, true);
    this.Dne = paramCDE;
    Dne(1);
  }
  
  public void Dne() {
    this.Dne.FWm(this.Dne);
    super.Dne();
  }
}


/* Location:              C:\Users\fract\Downloads\ERROR422.jar!\ZkF.class
 * Java compiler version: 8 (52.0)
 * JD-Core Version:       1.1.3
 */