public class zMx extends sMa {
  private int Dne;
  
  private int FWm;
  
  public boolean bzF() {
    return false;
  }
  
  public void Dne(byte paramByte) {
    // Byte code:
    //   0: iload_1
    //   1: bipush #17
    //   3: if_icmpne -> 81
    //   6: aload_0
    //   7: getfield Dne : LQnq;
    //   10: getfield aFZ : Z
    //   13: ifeq -> 81
    //   16: aload_0
    //   17: getfield Dne : LluM;
    //   20: bipush #8
    //   22: invokevirtual Dne : (I)LNMq;
    //   25: astore_2
    //   26: aconst_null
    //   27: astore_3
    //   28: aload_2
    //   29: ifnull -> 49
    //   32: aload_2
    //   33: invokevirtual aFZ : ()Z
    //   36: ifeq -> 49
    //   39: aload_2
    //   40: invokevirtual Dne : ()LWkD;
    //   43: ldc 'Fireworks'
    //   45: invokevirtual Dne : (Ljava/lang/String;)LWkD;
    //   48: astore_3
    //   49: aload_0
    //   50: getfield Dne : LQnq;
    //   53: aload_0
    //   54: getfield div : D
    //   57: aload_0
    //   58: getfield IjH : D
    //   61: aload_0
    //   62: getfield mrb : D
    //   65: aload_0
    //   66: getfield XHL : D
    //   69: aload_0
    //   70: getfield Zpi : D
    //   73: aload_0
    //   74: getfield kGO : D
    //   77: aload_3
    //   78: invokevirtual Dne : (DDDDDDLWkD;)V
    //   81: aload_0
    //   82: iload_1
    //   83: invokespecial Dne : (B)V
    //   86: return
  }
  
  public void FWm(WkD paramWkD) {
    // Byte code:
    //   0: aload_0
    //   1: aload_1
    //   2: ldc 'Life'
    //   4: invokevirtual Dne : (Ljava/lang/String;)I
    //   7: putfield Dne : I
    //   10: aload_0
    //   11: aload_1
    //   12: ldc 'LifeTime'
    //   14: invokevirtual Dne : (Ljava/lang/String;)I
    //   17: putfield FWm : I
    //   20: aload_1
    //   21: ldc 'FireworksItem'
    //   23: invokevirtual Dne : (Ljava/lang/String;)LWkD;
    //   26: astore_2
    //   27: aload_2
    //   28: ifnull -> 50
    //   31: aload_2
    //   32: invokestatic Dne : (LWkD;)LNMq;
    //   35: astore_3
    //   36: aload_3
    //   37: ifnull -> 50
    //   40: aload_0
    //   41: getfield Dne : LluM;
    //   44: bipush #8
    //   46: aload_3
    //   47: invokevirtual FWm : (ILjava/lang/Object;)V
    //   50: return
  }
  
  public boolean Dne(double paramDouble) {
    return (paramDouble < 4096.0D);
  }
  
  public float Dne(float paramFloat) {
    return super.Dne(paramFloat);
  }
  
  public int Dne(float paramFloat) {
    return super.Dne(paramFloat);
  }
  
  public void Dne() {
    // Byte code:
    //   0: aload_0
    //   1: aload_0
    //   2: getfield div : D
    //   5: putfield udO : D
    //   8: aload_0
    //   9: aload_0
    //   10: getfield IjH : D
    //   13: putfield ooe : D
    //   16: aload_0
    //   17: aload_0
    //   18: getfield mrb : D
    //   21: putfield trS : D
    //   24: aload_0
    //   25: invokespecial Dne : ()V
    //   28: aload_0
    //   29: dup
    //   30: getfield XHL : D
    //   33: ldc2_w 1.15
    //   36: dmul
    //   37: putfield XHL : D
    //   40: aload_0
    //   41: dup
    //   42: getfield kGO : D
    //   45: ldc2_w 1.15
    //   48: dmul
    //   49: putfield kGO : D
    //   52: aload_0
    //   53: dup
    //   54: getfield Zpi : D
    //   57: ldc2_w 0.04
    //   60: dadd
    //   61: putfield Zpi : D
    //   64: aload_0
    //   65: aload_0
    //   66: getfield XHL : D
    //   69: aload_0
    //   70: getfield Zpi : D
    //   73: aload_0
    //   74: getfield kGO : D
    //   77: invokevirtual Dne : (DDD)V
    //   80: aload_0
    //   81: getfield XHL : D
    //   84: aload_0
    //   85: getfield XHL : D
    //   88: dmul
    //   89: aload_0
    //   90: getfield kGO : D
    //   93: aload_0
    //   94: getfield kGO : D
    //   97: dmul
    //   98: dadd
    //   99: invokestatic Dne : (D)F
    //   102: fstore_1
    //   103: aload_0
    //   104: aload_0
    //   105: getfield XHL : D
    //   108: aload_0
    //   109: getfield kGO : D
    //   112: invokestatic atan2 : (DD)D
    //   115: ldc2_w 180.0
    //   118: dmul
    //   119: ldc2_w 3.141592653589793
    //   122: ddiv
    //   123: d2f
    //   124: putfield mrb : F
    //   127: aload_0
    //   128: aload_0
    //   129: getfield Zpi : D
    //   132: fload_1
    //   133: f2d
    //   134: invokestatic atan2 : (DD)D
    //   137: ldc2_w 180.0
    //   140: dmul
    //   141: ldc2_w 3.141592653589793
    //   144: ddiv
    //   145: d2f
    //   146: putfield XHL : F
    //   149: aload_0
    //   150: getfield XHL : F
    //   153: aload_0
    //   154: getfield kGO : F
    //   157: fsub
    //   158: ldc -180.0
    //   160: fcmpg
    //   161: ifge -> 178
    //   164: aload_0
    //   165: dup
    //   166: getfield kGO : F
    //   169: ldc 360.0
    //   171: fsub
    //   172: putfield kGO : F
    //   175: goto -> 149
    //   178: aload_0
    //   179: getfield XHL : F
    //   182: aload_0
    //   183: getfield kGO : F
    //   186: fsub
    //   187: ldc 180.0
    //   189: fcmpl
    //   190: iflt -> 207
    //   193: aload_0
    //   194: dup
    //   195: getfield kGO : F
    //   198: ldc 360.0
    //   200: fadd
    //   201: putfield kGO : F
    //   204: goto -> 178
    //   207: aload_0
    //   208: getfield mrb : F
    //   211: aload_0
    //   212: getfield Zpi : F
    //   215: fsub
    //   216: ldc -180.0
    //   218: fcmpg
    //   219: ifge -> 236
    //   222: aload_0
    //   223: dup
    //   224: getfield Zpi : F
    //   227: ldc 360.0
    //   229: fsub
    //   230: putfield Zpi : F
    //   233: goto -> 207
    //   236: aload_0
    //   237: getfield mrb : F
    //   240: aload_0
    //   241: getfield Zpi : F
    //   244: fsub
    //   245: ldc 180.0
    //   247: fcmpl
    //   248: iflt -> 265
    //   251: aload_0
    //   252: dup
    //   253: getfield Zpi : F
    //   256: ldc 360.0
    //   258: fadd
    //   259: putfield Zpi : F
    //   262: goto -> 236
    //   265: aload_0
    //   266: aload_0
    //   267: getfield kGO : F
    //   270: aload_0
    //   271: getfield XHL : F
    //   274: aload_0
    //   275: getfield kGO : F
    //   278: fsub
    //   279: ldc 0.2
    //   281: fmul
    //   282: fadd
    //   283: putfield XHL : F
    //   286: aload_0
    //   287: aload_0
    //   288: getfield Zpi : F
    //   291: aload_0
    //   292: getfield mrb : F
    //   295: aload_0
    //   296: getfield Zpi : F
    //   299: fsub
    //   300: ldc 0.2
    //   302: fmul
    //   303: fadd
    //   304: putfield mrb : F
    //   307: aload_0
    //   308: getfield Dne : I
    //   311: ifne -> 327
    //   314: aload_0
    //   315: getfield Dne : LQnq;
    //   318: aload_0
    //   319: ldc 'fireworks.launch'
    //   321: ldc 3.0
    //   323: fconst_1
    //   324: invokevirtual Dne : (LsMa;Ljava/lang/String;FF)V
    //   327: aload_0
    //   328: dup
    //   329: getfield Dne : I
    //   332: iconst_1
    //   333: iadd
    //   334: putfield Dne : I
    //   337: aload_0
    //   338: getfield Dne : LQnq;
    //   341: getfield aFZ : Z
    //   344: ifeq -> 413
    //   347: aload_0
    //   348: getfield Dne : I
    //   351: iconst_2
    //   352: irem
    //   353: iconst_2
    //   354: if_icmpge -> 413
    //   357: aload_0
    //   358: getfield Dne : LQnq;
    //   361: ldc 'fireworksSpark'
    //   363: aload_0
    //   364: getfield div : D
    //   367: aload_0
    //   368: getfield IjH : D
    //   371: ldc2_w 0.3
    //   374: dsub
    //   375: aload_0
    //   376: getfield mrb : D
    //   379: aload_0
    //   380: getfield Dne : Ljava/util/Random;
    //   383: invokevirtual nextGaussian : ()D
    //   386: ldc2_w 0.05
    //   389: dmul
    //   390: aload_0
    //   391: getfield Zpi : D
    //   394: dneg
    //   395: ldc2_w 0.5
    //   398: dmul
    //   399: aload_0
    //   400: getfield Dne : Ljava/util/Random;
    //   403: invokevirtual nextGaussian : ()D
    //   406: ldc2_w 0.05
    //   409: dmul
    //   410: invokevirtual Dne : (Ljava/lang/String;DDDDDD)V
    //   413: aload_0
    //   414: getfield Dne : LQnq;
    //   417: getfield aFZ : Z
    //   420: ifne -> 448
    //   423: aload_0
    //   424: getfield Dne : I
    //   427: aload_0
    //   428: getfield FWm : I
    //   431: if_icmple -> 448
    //   434: aload_0
    //   435: getfield Dne : LQnq;
    //   438: aload_0
    //   439: bipush #17
    //   441: invokevirtual Dne : (LsMa;B)V
    //   444: aload_0
    //   445: invokevirtual g_ : ()V
    //   448: return
  }
  
  public void aFZ(double paramDouble1, double paramDouble2, double paramDouble3) {
    this.XHL = paramDouble1;
    this.Zpi = paramDouble2;
    this.kGO = paramDouble3;
    if (this.kGO == 0.0F && this.Zpi == 0.0F) {
      float f = geR.Dne(paramDouble1 * paramDouble1 + paramDouble3 * paramDouble3);
      this.Zpi = this.mrb = (float)(Math.atan2(paramDouble1, paramDouble3) * 180.0D / Math.PI);
      this.kGO = this.XHL = (float)(Math.atan2(paramDouble2, f) * 180.0D / Math.PI);
    } 
  }
  
  public zMx(Qnq paramQnq) {
    super(paramQnq);
    Dne(0.25F, 0.25F);
  }
  
  public float Dne() {
    return 0.0F;
  }
  
  public zMx(Qnq paramQnq, double paramDouble1, double paramDouble2, double paramDouble3, NMq paramNMq) {
    // Byte code:
    //   0: aload_0
    //   1: aload_1
    //   2: invokespecial <init> : (LQnq;)V
    //   5: aload_0
    //   6: iconst_0
    //   7: putfield Dne : I
    //   10: aload_0
    //   11: ldc 0.25
    //   13: ldc 0.25
    //   15: invokevirtual Dne : (FF)V
    //   18: aload_0
    //   19: dload_2
    //   20: dload #4
    //   22: dload #6
    //   24: invokevirtual bzF : (DDD)V
    //   27: aload_0
    //   28: fconst_0
    //   29: putfield udO : F
    //   32: iconst_1
    //   33: istore #9
    //   35: aload #8
    //   37: ifnull -> 92
    //   40: aload #8
    //   42: invokevirtual aFZ : ()Z
    //   45: ifeq -> 92
    //   48: aload_0
    //   49: getfield Dne : LluM;
    //   52: bipush #8
    //   54: aload #8
    //   56: invokevirtual FWm : (ILjava/lang/Object;)V
    //   59: aload #8
    //   61: invokevirtual Dne : ()LWkD;
    //   64: astore #10
    //   66: aload #10
    //   68: ldc 'Fireworks'
    //   70: invokevirtual Dne : (Ljava/lang/String;)LWkD;
    //   73: astore #11
    //   75: aload #11
    //   77: ifnull -> 92
    //   80: iload #9
    //   82: aload #11
    //   84: ldc 'Flight'
    //   86: invokevirtual Dne : (Ljava/lang/String;)B
    //   89: iadd
    //   90: istore #9
    //   92: aload_0
    //   93: aload_0
    //   94: getfield Dne : Ljava/util/Random;
    //   97: invokevirtual nextGaussian : ()D
    //   100: ldc2_w 0.001
    //   103: dmul
    //   104: putfield XHL : D
    //   107: aload_0
    //   108: aload_0
    //   109: getfield Dne : Ljava/util/Random;
    //   112: invokevirtual nextGaussian : ()D
    //   115: ldc2_w 0.001
    //   118: dmul
    //   119: putfield kGO : D
    //   122: aload_0
    //   123: ldc2_w 0.05
    //   126: putfield Zpi : D
    //   129: aload_0
    //   130: bipush #10
    //   132: iload #9
    //   134: imul
    //   135: aload_0
    //   136: getfield Dne : Ljava/util/Random;
    //   139: bipush #6
    //   141: invokevirtual nextInt : (I)I
    //   144: iadd
    //   145: aload_0
    //   146: getfield Dne : Ljava/util/Random;
    //   149: bipush #7
    //   151: invokevirtual nextInt : (I)I
    //   154: iadd
    //   155: putfield FWm : I
    //   158: return
  }
  
  public void Dne(WkD paramWkD) {
    // Byte code:
    //   0: aload_1
    //   1: ldc 'Life'
    //   3: aload_0
    //   4: getfield Dne : I
    //   7: invokevirtual Dne : (Ljava/lang/String;I)V
    //   10: aload_1
    //   11: ldc 'LifeTime'
    //   13: aload_0
    //   14: getfield FWm : I
    //   17: invokevirtual Dne : (Ljava/lang/String;I)V
    //   20: aload_0
    //   21: getfield Dne : LluM;
    //   24: bipush #8
    //   26: invokevirtual Dne : (I)LNMq;
    //   29: astore_2
    //   30: aload_2
    //   31: ifnull -> 55
    //   34: new WkD
    //   37: dup
    //   38: invokespecial <init> : ()V
    //   41: astore_3
    //   42: aload_2
    //   43: aload_3
    //   44: invokevirtual Dne : (LWkD;)LWkD;
    //   47: pop
    //   48: aload_1
    //   49: ldc 'FireworksItem'
    //   51: aload_3
    //   52: invokevirtual Dne : (Ljava/lang/String;LWkD;)V
    //   55: return
  }
  
  protected void FWm() {
    // Byte code:
    //   0: aload_0
    //   1: getfield Dne : LluM;
    //   4: bipush #8
    //   6: iconst_5
    //   7: invokevirtual Dne : (II)V
    //   10: return
  }
}


/* Location:              C:\Users\fract\Downloads\ERROR422.jar!\zMx.class
 * Java compiler version: 8 (52.0)
 * JD-Core Version:       1.1.3
 */