public class znX extends cMv {
  int Dne;
  
  Qnq Dne;
  
  private HzK FWm;
  
  private HzK Dne;
  
  float Dne = false;
  
  public znX(HzK paramHzK, float paramFloat) {
    this.Dne = paramHzK;
    this.Dne = paramHzK.Dne;
    this.Dne = paramFloat;
    Dne(3);
  }
  
  public void bzF() {
    // Byte code:
    //   0: aload_0
    //   1: getfield Dne : LHzK;
    //   4: invokevirtual Dne : ()LbvU;
    //   7: aload_0
    //   8: getfield FWm : LHzK;
    //   11: ldc 10.0
    //   13: aload_0
    //   14: getfield Dne : LHzK;
    //   17: invokevirtual udO : ()I
    //   20: i2f
    //   21: invokevirtual Dne : (LsMa;FF)V
    //   24: aload_0
    //   25: getfield Dne : LHzK;
    //   28: invokevirtual Dne : ()LKFZ;
    //   31: aload_0
    //   32: getfield FWm : LHzK;
    //   35: aload_0
    //   36: getfield Dne : F
    //   39: invokevirtual Dne : (LFUH;F)Z
    //   42: pop
    //   43: aload_0
    //   44: dup
    //   45: getfield Dne : I
    //   48: iconst_1
    //   49: iadd
    //   50: putfield Dne : I
    //   53: aload_0
    //   54: getfield Dne : I
    //   57: bipush #60
    //   59: if_icmplt -> 84
    //   62: aload_0
    //   63: getfield Dne : LHzK;
    //   66: aload_0
    //   67: getfield FWm : LHzK;
    //   70: invokevirtual Dne : (LsMa;)D
    //   73: ldc2_w 9.0
    //   76: dcmpg
    //   77: ifge -> 84
    //   80: aload_0
    //   81: invokespecial Qnq : ()V
    //   84: return
  }
  
  private void Qnq() {
    // Byte code:
    //   0: aload_0
    //   1: getfield Dne : LHzK;
    //   4: aload_0
    //   5: getfield FWm : LHzK;
    //   8: invokevirtual Dne : (LAzh;)LAzh;
    //   11: astore_1
    //   12: aload_1
    //   13: ifnull -> 297
    //   16: aload_0
    //   17: getfield Dne : LHzK;
    //   20: sipush #6000
    //   23: invokevirtual FWm : (I)V
    //   26: aload_0
    //   27: getfield FWm : LHzK;
    //   30: sipush #6000
    //   33: invokevirtual FWm : (I)V
    //   36: aload_0
    //   37: getfield Dne : LHzK;
    //   40: invokevirtual Qnq : ()V
    //   43: aload_0
    //   44: getfield FWm : LHzK;
    //   47: invokevirtual Qnq : ()V
    //   50: aload_1
    //   51: sipush #-24000
    //   54: invokevirtual FWm : (I)V
    //   57: aload_1
    //   58: aload_0
    //   59: getfield Dne : LHzK;
    //   62: getfield div : D
    //   65: aload_0
    //   66: getfield Dne : LHzK;
    //   69: getfield IjH : D
    //   72: aload_0
    //   73: getfield Dne : LHzK;
    //   76: getfield mrb : D
    //   79: fconst_0
    //   80: fconst_0
    //   81: invokevirtual FWm : (DDDFF)V
    //   84: aload_0
    //   85: getfield Dne : LQnq;
    //   88: aload_1
    //   89: invokevirtual FWm : (LsMa;)Z
    //   92: pop
    //   93: aload_0
    //   94: getfield Dne : LHzK;
    //   97: invokevirtual Dne : ()Ljava/util/Random;
    //   100: astore_2
    //   101: iconst_0
    //   102: istore_3
    //   103: iload_3
    //   104: bipush #7
    //   106: if_icmpge -> 249
    //   109: aload_2
    //   110: invokevirtual nextGaussian : ()D
    //   113: ldc2_w 0.02
    //   116: dmul
    //   117: dstore #4
    //   119: aload_2
    //   120: invokevirtual nextGaussian : ()D
    //   123: ldc2_w 0.02
    //   126: dmul
    //   127: dstore #6
    //   129: aload_2
    //   130: invokevirtual nextGaussian : ()D
    //   133: ldc2_w 0.02
    //   136: dmul
    //   137: dstore #8
    //   139: aload_0
    //   140: getfield Dne : LQnq;
    //   143: ldc 'heart'
    //   145: aload_0
    //   146: getfield Dne : LHzK;
    //   149: getfield div : D
    //   152: aload_2
    //   153: invokevirtual nextFloat : ()F
    //   156: aload_0
    //   157: getfield Dne : LHzK;
    //   160: getfield ooe : F
    //   163: fmul
    //   164: fconst_2
    //   165: fmul
    //   166: f2d
    //   167: dadd
    //   168: aload_0
    //   169: getfield Dne : LHzK;
    //   172: getfield ooe : F
    //   175: f2d
    //   176: dsub
    //   177: aload_0
    //   178: getfield Dne : LHzK;
    //   181: getfield IjH : D
    //   184: ldc2_w 0.5
    //   187: dadd
    //   188: aload_2
    //   189: invokevirtual nextFloat : ()F
    //   192: aload_0
    //   193: getfield Dne : LHzK;
    //   196: getfield trS : F
    //   199: fmul
    //   200: f2d
    //   201: dadd
    //   202: aload_0
    //   203: getfield Dne : LHzK;
    //   206: getfield mrb : D
    //   209: aload_2
    //   210: invokevirtual nextFloat : ()F
    //   213: aload_0
    //   214: getfield Dne : LHzK;
    //   217: getfield ooe : F
    //   220: fmul
    //   221: fconst_2
    //   222: fmul
    //   223: f2d
    //   224: dadd
    //   225: aload_0
    //   226: getfield Dne : LHzK;
    //   229: getfield ooe : F
    //   232: f2d
    //   233: dsub
    //   234: dload #4
    //   236: dload #6
    //   238: dload #8
    //   240: invokevirtual Dne : (Ljava/lang/String;DDDDDD)V
    //   243: iinc #3, 1
    //   246: goto -> 103
    //   249: aload_0
    //   250: getfield Dne : LQnq;
    //   253: new alg
    //   256: dup
    //   257: aload_0
    //   258: getfield Dne : LQnq;
    //   261: aload_0
    //   262: getfield Dne : LHzK;
    //   265: getfield div : D
    //   268: aload_0
    //   269: getfield Dne : LHzK;
    //   272: getfield IjH : D
    //   275: aload_0
    //   276: getfield Dne : LHzK;
    //   279: getfield mrb : D
    //   282: aload_2
    //   283: bipush #7
    //   285: invokevirtual nextInt : (I)I
    //   288: iconst_1
    //   289: iadd
    //   290: invokespecial <init> : (LQnq;DDDI)V
    //   293: invokevirtual FWm : (LsMa;)Z
    //   296: pop
    //   297: return
  }
  
  public boolean Dne() {
    // Byte code:
    //   0: aload_0
    //   1: getfield Dne : LHzK;
    //   4: invokevirtual ZfC : ()Z
    //   7: ifne -> 12
    //   10: iconst_0
    //   11: ireturn
    //   12: aload_0
    //   13: aload_0
    //   14: invokespecial Dne : ()LHzK;
    //   17: putfield FWm : LHzK;
    //   20: aload_0
    //   21: getfield FWm : LHzK;
    //   24: ifnull -> 31
    //   27: iconst_1
    //   28: goto -> 32
    //   31: iconst_0
    //   32: ireturn
  }
  
  private HzK Dne() {
    // Byte code:
    //   0: ldc 8.0
    //   2: fstore_1
    //   3: aload_0
    //   4: getfield Dne : LQnq;
    //   7: aload_0
    //   8: getfield Dne : LHzK;
    //   11: invokevirtual getClass : ()Ljava/lang/Class;
    //   14: aload_0
    //   15: getfield Dne : LHzK;
    //   18: getfield Dne : LbSp;
    //   21: fload_1
    //   22: f2d
    //   23: fload_1
    //   24: f2d
    //   25: fload_1
    //   26: f2d
    //   27: invokevirtual FWm : (DDD)LbSp;
    //   30: invokevirtual Dne : (Ljava/lang/Class;LbSp;)Ljava/util/List;
    //   33: astore_2
    //   34: ldc2_w 1.7976931348623157E308
    //   37: dstore_3
    //   38: aconst_null
    //   39: astore #5
    //   41: aload_2
    //   42: invokeinterface iterator : ()Ljava/util/Iterator;
    //   47: astore #6
    //   49: aload #6
    //   51: invokeinterface hasNext : ()Z
    //   56: ifeq -> 114
    //   59: aload #6
    //   61: invokeinterface next : ()Ljava/lang/Object;
    //   66: checkcast HzK
    //   69: astore #7
    //   71: aload_0
    //   72: getfield Dne : LHzK;
    //   75: aload #7
    //   77: invokevirtual Dne : (LHzK;)Z
    //   80: ifeq -> 111
    //   83: aload_0
    //   84: getfield Dne : LHzK;
    //   87: aload #7
    //   89: invokevirtual Dne : (LsMa;)D
    //   92: dload_3
    //   93: dcmpg
    //   94: ifge -> 111
    //   97: aload #7
    //   99: astore #5
    //   101: aload_0
    //   102: getfield Dne : LHzK;
    //   105: aload #7
    //   107: invokevirtual Dne : (LsMa;)D
    //   110: dstore_3
    //   111: goto -> 49
    //   114: aload #5
    //   116: areturn
  }
  
  public void FWm() {
    this.FWm = null;
    this.Dne = false;
  }
  
  public boolean FWm() {
    return (this.FWm.udO() && this.FWm.ZfC() && this.Dne < 60);
  }
}


/* Location:              C:\Users\fract\Downloads\ERROR422.jar!\znX.class
 * Java compiler version: 8 (52.0)
 * JD-Core Version:       1.1.3
 */