public class zPr extends SmS {
  private int Qnq;
  
  private int aFZ = -1;
  
  public boolean FWm() {
    // Byte code:
    //   0: aload_0
    //   1: getfield Dne : LFUH;
    //   4: aload_0
    //   5: getfield Dne : I
    //   8: i2d
    //   9: aload_0
    //   10: getfield FWm : I
    //   13: i2d
    //   14: aload_0
    //   15: getfield bzF : I
    //   18: i2d
    //   19: invokevirtual Dne : (DDD)D
    //   22: dstore_1
    //   23: aload_0
    //   24: getfield Qnq : I
    //   27: sipush #240
    //   30: if_icmpgt -> 74
    //   33: aload_0
    //   34: getfield Dne : Loqu;
    //   37: aload_0
    //   38: getfield Dne : LFUH;
    //   41: getfield Dne : LQnq;
    //   44: aload_0
    //   45: getfield Dne : I
    //   48: aload_0
    //   49: getfield FWm : I
    //   52: aload_0
    //   53: getfield bzF : I
    //   56: invokevirtual FWm : (LZpi;III)Z
    //   59: ifne -> 74
    //   62: dload_1
    //   63: ldc2_w 4.0
    //   66: dcmpg
    //   67: ifge -> 74
    //   70: iconst_1
    //   71: goto -> 75
    //   74: iconst_0
    //   75: ireturn
  }
  
  public zPr(FUH paramFUH) {
    super(paramFUH);
  }
  
  public void bzF() {
    // Byte code:
    //   0: aload_0
    //   1: invokespecial bzF : ()V
    //   4: aload_0
    //   5: getfield Dne : LFUH;
    //   8: invokevirtual Dne : ()Ljava/util/Random;
    //   11: bipush #20
    //   13: invokevirtual nextInt : (I)I
    //   16: ifne -> 45
    //   19: aload_0
    //   20: getfield Dne : LFUH;
    //   23: getfield Dne : LQnq;
    //   26: sipush #1010
    //   29: aload_0
    //   30: getfield Dne : I
    //   33: aload_0
    //   34: getfield FWm : I
    //   37: aload_0
    //   38: getfield bzF : I
    //   41: iconst_0
    //   42: invokevirtual Qnq : (IIIII)V
    //   45: aload_0
    //   46: dup
    //   47: getfield Qnq : I
    //   50: iconst_1
    //   51: iadd
    //   52: putfield Qnq : I
    //   55: aload_0
    //   56: getfield Qnq : I
    //   59: i2f
    //   60: ldc 240.0
    //   62: fdiv
    //   63: ldc 10.0
    //   65: fmul
    //   66: f2i
    //   67: istore_1
    //   68: iload_1
    //   69: aload_0
    //   70: getfield aFZ : I
    //   73: if_icmpeq -> 111
    //   76: aload_0
    //   77: getfield Dne : LFUH;
    //   80: getfield Dne : LQnq;
    //   83: aload_0
    //   84: getfield Dne : LFUH;
    //   87: getfield aFZ : I
    //   90: aload_0
    //   91: getfield Dne : I
    //   94: aload_0
    //   95: getfield FWm : I
    //   98: aload_0
    //   99: getfield bzF : I
    //   102: iload_1
    //   103: invokevirtual aFZ : (IIIII)V
    //   106: aload_0
    //   107: iload_1
    //   108: putfield aFZ : I
    //   111: aload_0
    //   112: getfield Qnq : I
    //   115: sipush #240
    //   118: if_icmpne -> 216
    //   121: aload_0
    //   122: getfield Dne : LFUH;
    //   125: getfield Dne : LQnq;
    //   128: getfield aFZ : I
    //   131: iconst_3
    //   132: if_icmpne -> 216
    //   135: aload_0
    //   136: getfield Dne : LFUH;
    //   139: getfield Dne : LQnq;
    //   142: aload_0
    //   143: getfield Dne : I
    //   146: aload_0
    //   147: getfield FWm : I
    //   150: aload_0
    //   151: getfield bzF : I
    //   154: invokevirtual Qnq : (III)Z
    //   157: pop
    //   158: aload_0
    //   159: getfield Dne : LFUH;
    //   162: getfield Dne : LQnq;
    //   165: sipush #1012
    //   168: aload_0
    //   169: getfield Dne : I
    //   172: aload_0
    //   173: getfield FWm : I
    //   176: aload_0
    //   177: getfield bzF : I
    //   180: iconst_0
    //   181: invokevirtual Qnq : (IIIII)V
    //   184: aload_0
    //   185: getfield Dne : LFUH;
    //   188: getfield Dne : LQnq;
    //   191: sipush #2001
    //   194: aload_0
    //   195: getfield Dne : I
    //   198: aload_0
    //   199: getfield FWm : I
    //   202: aload_0
    //   203: getfield bzF : I
    //   206: aload_0
    //   207: getfield Dne : Loqu;
    //   210: getfield FWm : I
    //   213: invokevirtual Qnq : (IIIII)V
    //   216: return
  }
  
  public boolean Dne() {
    // Byte code:
    //   0: aload_0
    //   1: invokespecial Dne : ()Z
    //   4: ifne -> 11
    //   7: iconst_0
    //   8: goto -> 67
    //   11: aload_0
    //   12: getfield Dne : LFUH;
    //   15: getfield Dne : LQnq;
    //   18: invokevirtual Dne : ()LaSc;
    //   21: ldc 'mobGriefing'
    //   23: invokevirtual Dne : (Ljava/lang/String;)Z
    //   26: ifne -> 33
    //   29: iconst_0
    //   30: goto -> 67
    //   33: aload_0
    //   34: getfield Dne : Loqu;
    //   37: aload_0
    //   38: getfield Dne : LFUH;
    //   41: getfield Dne : LQnq;
    //   44: aload_0
    //   45: getfield Dne : I
    //   48: aload_0
    //   49: getfield FWm : I
    //   52: aload_0
    //   53: getfield bzF : I
    //   56: invokevirtual FWm : (LZpi;III)Z
    //   59: ifne -> 66
    //   62: iconst_1
    //   63: goto -> 67
    //   66: iconst_0
    //   67: ireturn
  }
  
  public void Dne() {
    super.Dne();
    this.Qnq = 0;
  }
  
  public void FWm() {
    // Byte code:
    //   0: aload_0
    //   1: invokespecial FWm : ()V
    //   4: aload_0
    //   5: getfield Dne : LFUH;
    //   8: getfield Dne : LQnq;
    //   11: aload_0
    //   12: getfield Dne : LFUH;
    //   15: getfield aFZ : I
    //   18: aload_0
    //   19: getfield Dne : I
    //   22: aload_0
    //   23: getfield FWm : I
    //   26: aload_0
    //   27: getfield bzF : I
    //   30: iconst_m1
    //   31: invokevirtual aFZ : (IIIII)V
    //   34: return
  }
}


/* Location:              C:\Users\fract\Downloads\ERROR422.jar!\zPr.class
 * Java compiler version: 8 (52.0)
 * JD-Core Version:       1.1.3
 */