import net.minecraft.client.Minecraft;

public class zSv extends qVZ {
  private static final ONk[] FWm;
  
  private static final ONk[] Dne = new ONk[] { ONk.ATE, ONk.Vxn, ONk.ceE, ONk.EyB, ONk.FfS, ONk.tgc, ONk.AgF, ONk.yMz, ONk.qXo };
  
  private final fZI Dne;
  
  private int Dne;
  
  private String Dne;
  
  private String FWm;
  
  private final qVZ Dne = false;
  
  public void Dne(int paramInt1, int paramInt2, float paramFloat) {
    aFZ();
    Dne((msA)this.Dne, (String)this.Dne, this.FWm / 2, 20, 16777215);
    Dne((msA)this.Dne, this.FWm, this.FWm / 2, this.Dne + 7, 16777215);
    super.Dne(paramInt1, paramInt2, paramFloat);
  }
  
  public void Dne() {
    // Byte code:
    //   0: invokestatic Dne : ()Lirb;
    //   3: astore_1
    //   4: iconst_0
    //   5: istore_2
    //   6: aload_0
    //   7: aload_1
    //   8: ldc 'options.chat.title'
    //   10: invokevirtual Dne : (Ljava/lang/String;)Ljava/lang/String;
    //   13: putfield Dne : Ljava/lang/String;
    //   16: aload_0
    //   17: aload_1
    //   18: ldc 'options.multiplayer.title'
    //   20: invokevirtual Dne : (Ljava/lang/String;)Ljava/lang/String;
    //   23: putfield FWm : Ljava/lang/String;
    //   26: getstatic zSv.Dne : [LONk;
    //   29: astore_3
    //   30: aload_3
    //   31: arraylength
    //   32: istore #4
    //   34: iconst_0
    //   35: istore #5
    //   37: iload #5
    //   39: iload #4
    //   41: if_icmpge -> 209
    //   44: aload_3
    //   45: iload #5
    //   47: aaload
    //   48: astore #6
    //   50: aload #6
    //   52: invokevirtual Dne : ()Z
    //   55: ifeq -> 135
    //   58: aload_0
    //   59: getfield Dne : Ljava/util/List;
    //   62: new bsO
    //   65: dup
    //   66: aload #6
    //   68: invokevirtual Dne : ()I
    //   71: aload_0
    //   72: getfield FWm : I
    //   75: iconst_2
    //   76: idiv
    //   77: sipush #155
    //   80: isub
    //   81: iload_2
    //   82: iconst_2
    //   83: irem
    //   84: sipush #160
    //   87: imul
    //   88: iadd
    //   89: aload_0
    //   90: getfield bzF : I
    //   93: bipush #6
    //   95: idiv
    //   96: bipush #24
    //   98: iload_2
    //   99: iconst_1
    //   100: ishr
    //   101: imul
    //   102: iadd
    //   103: aload #6
    //   105: aload_0
    //   106: getfield Dne : LfZI;
    //   109: aload #6
    //   111: invokevirtual Dne : (LONk;)Ljava/lang/String;
    //   114: aload_0
    //   115: getfield Dne : LfZI;
    //   118: aload #6
    //   120: invokevirtual Dne : (LONk;)F
    //   123: invokespecial <init> : (IIILONk;Ljava/lang/String;F)V
    //   126: invokeinterface add : (Ljava/lang/Object;)Z
    //   131: pop
    //   132: goto -> 200
    //   135: aload_0
    //   136: getfield Dne : Ljava/util/List;
    //   139: new Cpw
    //   142: dup
    //   143: aload #6
    //   145: invokevirtual Dne : ()I
    //   148: aload_0
    //   149: getfield FWm : I
    //   152: iconst_2
    //   153: idiv
    //   154: sipush #155
    //   157: isub
    //   158: iload_2
    //   159: iconst_2
    //   160: irem
    //   161: sipush #160
    //   164: imul
    //   165: iadd
    //   166: aload_0
    //   167: getfield bzF : I
    //   170: bipush #6
    //   172: idiv
    //   173: bipush #24
    //   175: iload_2
    //   176: iconst_1
    //   177: ishr
    //   178: imul
    //   179: iadd
    //   180: aload #6
    //   182: aload_0
    //   183: getfield Dne : LfZI;
    //   186: aload #6
    //   188: invokevirtual Dne : (LONk;)Ljava/lang/String;
    //   191: invokespecial <init> : (IIILONk;Ljava/lang/String;)V
    //   194: invokeinterface add : (Ljava/lang/Object;)Z
    //   199: pop
    //   200: iinc #2, 1
    //   203: iinc #5, 1
    //   206: goto -> 37
    //   209: iload_2
    //   210: iconst_2
    //   211: irem
    //   212: iconst_1
    //   213: if_icmpne -> 219
    //   216: iinc #2, 1
    //   219: aload_0
    //   220: aload_0
    //   221: getfield bzF : I
    //   224: bipush #6
    //   226: idiv
    //   227: bipush #24
    //   229: iload_2
    //   230: iconst_1
    //   231: ishr
    //   232: imul
    //   233: iadd
    //   234: putfield Dne : I
    //   237: iinc #2, 2
    //   240: getstatic zSv.FWm : [LONk;
    //   243: astore_3
    //   244: aload_3
    //   245: arraylength
    //   246: istore #4
    //   248: iconst_0
    //   249: istore #5
    //   251: iload #5
    //   253: iload #4
    //   255: if_icmpge -> 423
    //   258: aload_3
    //   259: iload #5
    //   261: aaload
    //   262: astore #6
    //   264: aload #6
    //   266: invokevirtual Dne : ()Z
    //   269: ifeq -> 349
    //   272: aload_0
    //   273: getfield Dne : Ljava/util/List;
    //   276: new bsO
    //   279: dup
    //   280: aload #6
    //   282: invokevirtual Dne : ()I
    //   285: aload_0
    //   286: getfield FWm : I
    //   289: iconst_2
    //   290: idiv
    //   291: sipush #155
    //   294: isub
    //   295: iload_2
    //   296: iconst_2
    //   297: irem
    //   298: sipush #160
    //   301: imul
    //   302: iadd
    //   303: aload_0
    //   304: getfield bzF : I
    //   307: bipush #6
    //   309: idiv
    //   310: bipush #24
    //   312: iload_2
    //   313: iconst_1
    //   314: ishr
    //   315: imul
    //   316: iadd
    //   317: aload #6
    //   319: aload_0
    //   320: getfield Dne : LfZI;
    //   323: aload #6
    //   325: invokevirtual Dne : (LONk;)Ljava/lang/String;
    //   328: aload_0
    //   329: getfield Dne : LfZI;
    //   332: aload #6
    //   334: invokevirtual Dne : (LONk;)F
    //   337: invokespecial <init> : (IIILONk;Ljava/lang/String;F)V
    //   340: invokeinterface add : (Ljava/lang/Object;)Z
    //   345: pop
    //   346: goto -> 414
    //   349: aload_0
    //   350: getfield Dne : Ljava/util/List;
    //   353: new Cpw
    //   356: dup
    //   357: aload #6
    //   359: invokevirtual Dne : ()I
    //   362: aload_0
    //   363: getfield FWm : I
    //   366: iconst_2
    //   367: idiv
    //   368: sipush #155
    //   371: isub
    //   372: iload_2
    //   373: iconst_2
    //   374: irem
    //   375: sipush #160
    //   378: imul
    //   379: iadd
    //   380: aload_0
    //   381: getfield bzF : I
    //   384: bipush #6
    //   386: idiv
    //   387: bipush #24
    //   389: iload_2
    //   390: iconst_1
    //   391: ishr
    //   392: imul
    //   393: iadd
    //   394: aload #6
    //   396: aload_0
    //   397: getfield Dne : LfZI;
    //   400: aload #6
    //   402: invokevirtual Dne : (LONk;)Ljava/lang/String;
    //   405: invokespecial <init> : (IIILONk;Ljava/lang/String;)V
    //   408: invokeinterface add : (Ljava/lang/Object;)Z
    //   413: pop
    //   414: iinc #2, 1
    //   417: iinc #5, 1
    //   420: goto -> 251
    //   423: aload_0
    //   424: getfield Dne : Ljava/util/List;
    //   427: new Pee
    //   430: dup
    //   431: sipush #200
    //   434: aload_0
    //   435: getfield FWm : I
    //   438: iconst_2
    //   439: idiv
    //   440: bipush #100
    //   442: isub
    //   443: aload_0
    //   444: getfield bzF : I
    //   447: bipush #6
    //   449: idiv
    //   450: sipush #168
    //   453: iadd
    //   454: aload_1
    //   455: ldc 'gui.done'
    //   457: invokevirtual Dne : (Ljava/lang/String;)Ljava/lang/String;
    //   460: invokespecial <init> : (IIILjava/lang/String;)V
    //   463: invokeinterface add : (Ljava/lang/Object;)Z
    //   468: pop
    //   469: return
  }
  
  protected void Dne(Pee paramPee) {
    if (paramPee.Dne != null) {
      if (paramPee.aFZ < 100 && paramPee instanceof Cpw) {
        this.Dne.Dne(((Cpw)paramPee).Dne(), 1);
        paramPee.Dne = this.Dne.Dne(ONk.Dne(paramPee.aFZ));
      } 
      if (paramPee.aFZ == 200) {
        ((Minecraft)this.Dne).Dne.FWm();
        this.Dne.Dne(this.Dne);
      } 
    } 
  }
  
  public zSv(qVZ paramqVZ, fZI paramfZI) {
    this.Dne = paramqVZ;
    this.Dne = (qVZ)paramfZI;
  }
  
  static {
    FWm = (String)new ONk[] { ONk.Fnk };
  }
}


/* Location:              C:\Users\fract\Downloads\ERROR422.jar!\zSv.class
 * Java compiler version: 8 (52.0)
 * JD-Core Version:       1.1.3
 */