public class ZWx extends cMv {
  private double FWm;
  
  private double bzF;
  
  private float Dne;
  
  private double Dne;
  
  private kSJ Dne;
  
  public boolean Dne() {
    // Byte code:
    //   0: aload_0
    //   1: getfield Dne : LkSJ;
    //   4: invokevirtual vSL : ()Z
    //   7: ifeq -> 12
    //   10: iconst_0
    //   11: ireturn
    //   12: aload_0
    //   13: getfield Dne : LkSJ;
    //   16: invokevirtual FWm : ()LiSh;
    //   19: astore_1
    //   20: aload_0
    //   21: getfield Dne : LkSJ;
    //   24: bipush #16
    //   26: bipush #7
    //   28: aload_0
    //   29: getfield Dne : LkSJ;
    //   32: getfield Dne : LQnq;
    //   35: invokevirtual Dne : ()LziS;
    //   38: aload_1
    //   39: getfield Dne : I
    //   42: i2d
    //   43: aload_1
    //   44: getfield FWm : I
    //   47: i2d
    //   48: aload_1
    //   49: getfield bzF : I
    //   52: i2d
    //   53: invokevirtual Dne : (DDD)LchN;
    //   56: invokestatic Dne : (LkSJ;IILchN;)LchN;
    //   59: astore_2
    //   60: aload_2
    //   61: ifnonnull -> 66
    //   64: iconst_0
    //   65: ireturn
    //   66: aload_0
    //   67: aload_2
    //   68: getfield Dne : D
    //   71: putfield Dne : D
    //   74: aload_0
    //   75: aload_2
    //   76: getfield FWm : D
    //   79: putfield FWm : D
    //   82: aload_0
    //   83: aload_2
    //   84: getfield bzF : D
    //   87: putfield bzF : D
    //   90: iconst_1
    //   91: ireturn
  }
  
  public ZWx(kSJ paramkSJ, float paramFloat) {
    this.Dne = paramkSJ;
    this.Dne = paramFloat;
    Dne(1);
  }
  
  public boolean FWm() {
    return !this.Dne.Dne().bzF();
  }
  
  public void Dne() {
    this.Dne.Dne().Dne(this.Dne, this.FWm, this.bzF, this.Dne);
  }
}


/* Location:              C:\Users\fract\Downloads\ERROR422.jar!\ZWx.class
 * Java compiler version: 8 (52.0)
 * JD-Core Version:       1.1.3
 */