import java.util.List;
import net.minecraft.client.Minecraft;
import org.lwjgl.opengl.GL11;

public class ZyA extends qVZ {
  private static eKj Dne = new eKj();
  
  protected String Dne;
  
  private FkP Dne;
  
  private LAz Dne;
  
  protected qVZ Dne;
  
  private eiw Dne;
  
  private kmt Dne;
  
  private LSv Dne = (LSv)"Select world";
  
  private void bzF(int paramInt1, int paramInt2, int paramInt3) {
    Dne(paramInt1 + 1, paramInt2 + 1);
    GL11.glEnable(32826);
    Cit.bzF();
    Dne.Dne((msA)this.Dne, ((Minecraft)this.Dne).Dne, new NMq(paramInt3, 1, 0), paramInt1 + 2, paramInt2 + 2);
    Cit.Dne();
    GL11.glDisable(32826);
  }
  
  static msA mrb(ZyA paramZyA) {
    return (msA)paramZyA.Dne;
  }
  
  protected void Dne(Pee paramPee) {
    if (paramPee.Dne != null)
      if (paramPee.aFZ == 0) {
        this.Dne.Dne((qVZ)this.Dne);
      } else if (paramPee.aFZ == 1) {
        this.Dne = this.Dne;
      } else if (paramPee.aFZ == 3) {
        this.Dne = this.Dne;
      } else if (paramPee.aFZ == 2) {
        this.Dne = this.Dne;
      } else {
        this.Dne.Dne(paramPee);
      }  
  }
  
  static msA aFZ(ZyA paramZyA) {
    return (msA)paramZyA.Dne;
  }
  
  static msA Qnq(ZyA paramZyA) {
    return (msA)paramZyA.Dne;
  }
  
  static Minecraft FWm(ZyA paramZyA) {
    return (Minecraft)paramZyA.Dne;
  }
  
  public void Dne(int paramInt1, int paramInt2, float paramFloat) {
    this.Dne.Dne(paramInt1, paramInt2, paramFloat);
    Dne((msA)this.Dne, (String)this.Dne, this.FWm / 2, 20, 16777215);
    super.Dne(paramInt1, paramInt2, paramFloat);
  }
  
  static Minecraft bzF(ZyA paramZyA) {
    return (Minecraft)paramZyA.Dne;
  }
  
  static void Dne(ZyA paramZyA, int paramInt1, int paramInt2, int paramInt3, int paramInt4, int paramInt5, int paramInt6) {
    paramZyA.Dne(paramInt1, paramInt2, paramInt3, paramInt4, paramInt5, paramInt6);
  }
  
  static msA XHL(ZyA paramZyA) {
    return (msA)paramZyA.Dne;
  }
  
  static msA bzF(ZyA paramZyA) {
    return (msA)paramZyA.Dne;
  }
  
  static msA IjH(ZyA paramZyA) {
    return (msA)paramZyA.Dne;
  }
  
  public ZyA(qVZ paramqVZ, FkP paramFkP) {
    this.Dne = null;
    this.Dne = (LSv)paramqVZ;
    this.Dne = (LSv)paramFkP;
  }
  
  private void Dne(int paramInt1, int paramInt2) {
    bzF(paramInt1, paramInt2, 0, 0);
  }
  
  static msA zGp(ZyA paramZyA) {
    return (msA)paramZyA.Dne;
  }
  
  static FkP Dne(ZyA paramZyA) {
    return (FkP)paramZyA.Dne;
  }
  
  static msA DyG(ZyA paramZyA) {
    return (msA)paramZyA.Dne;
  }
  
  public void zGp() {
    irb irb = irb.Dne();
    this.Dne.add(new Pee(0, this.FWm / 2 + 4, this.bzF - 28, 150, 20, irb.Dne("gui.done")));
    this.Dne.add(new Pee(1, this.FWm / 2 - 154, this.bzF - 52, 100, 20, irb.Dne("stat.generalButton")));
    Pee pee1;
    this.Dne.add(pee1 = new Pee(2, this.FWm / 2 - 46, this.bzF - 52, 100, 20, irb.Dne("stat.blocksButton")));
    Pee pee2;
    this.Dne.add(pee2 = new Pee(3, this.FWm / 2 + 62, this.bzF - 52, 100, 20, irb.Dne("stat.itemsButton")));
    if (this.Dne.Dne() == 0)
      pee1.Dne = Character.MIN_VALUE; 
    if (this.Dne.Dne() == 0)
      pee2.Dne = Character.MIN_VALUE; 
  }
  
  static Minecraft Dne(ZyA paramZyA) {
    return (Minecraft)paramZyA.Dne;
  }
  
  private void bzF(int paramInt1, int paramInt2, int paramInt3, int paramInt4) {
    // Byte code:
    //   0: fconst_1
    //   1: fconst_1
    //   2: fconst_1
    //   3: fconst_1
    //   4: invokestatic glColor4f : (FFFF)V
    //   7: aload_0
    //   8: getfield Dne : Lnet/minecraft/client/Minecraft;
    //   11: getfield Dne : LSnh;
    //   14: ldc '/gui/slot.png'
    //   16: invokevirtual Dne : (Ljava/lang/String;)V
    //   19: getstatic WAR.Dne : LWAR;
    //   22: astore #5
    //   24: aload #5
    //   26: invokevirtual Dne : ()V
    //   29: aload #5
    //   31: iload_1
    //   32: iconst_0
    //   33: iadd
    //   34: i2d
    //   35: iload_2
    //   36: bipush #18
    //   38: iadd
    //   39: i2d
    //   40: aload_0
    //   41: getfield FWm : F
    //   44: f2d
    //   45: iload_3
    //   46: iconst_0
    //   47: iadd
    //   48: i2f
    //   49: ldc 0.0078125
    //   51: fmul
    //   52: f2d
    //   53: iload #4
    //   55: bipush #18
    //   57: iadd
    //   58: i2f
    //   59: ldc 0.0078125
    //   61: fmul
    //   62: f2d
    //   63: invokevirtual Dne : (DDDDD)V
    //   66: aload #5
    //   68: iload_1
    //   69: bipush #18
    //   71: iadd
    //   72: i2d
    //   73: iload_2
    //   74: bipush #18
    //   76: iadd
    //   77: i2d
    //   78: aload_0
    //   79: getfield FWm : F
    //   82: f2d
    //   83: iload_3
    //   84: bipush #18
    //   86: iadd
    //   87: i2f
    //   88: ldc 0.0078125
    //   90: fmul
    //   91: f2d
    //   92: iload #4
    //   94: bipush #18
    //   96: iadd
    //   97: i2f
    //   98: ldc 0.0078125
    //   100: fmul
    //   101: f2d
    //   102: invokevirtual Dne : (DDDDD)V
    //   105: aload #5
    //   107: iload_1
    //   108: bipush #18
    //   110: iadd
    //   111: i2d
    //   112: iload_2
    //   113: iconst_0
    //   114: iadd
    //   115: i2d
    //   116: aload_0
    //   117: getfield FWm : F
    //   120: f2d
    //   121: iload_3
    //   122: bipush #18
    //   124: iadd
    //   125: i2f
    //   126: ldc 0.0078125
    //   128: fmul
    //   129: f2d
    //   130: iload #4
    //   132: iconst_0
    //   133: iadd
    //   134: i2f
    //   135: ldc 0.0078125
    //   137: fmul
    //   138: f2d
    //   139: invokevirtual Dne : (DDDDD)V
    //   142: aload #5
    //   144: iload_1
    //   145: iconst_0
    //   146: iadd
    //   147: i2d
    //   148: iload_2
    //   149: iconst_0
    //   150: iadd
    //   151: i2d
    //   152: aload_0
    //   153: getfield FWm : F
    //   156: f2d
    //   157: iload_3
    //   158: iconst_0
    //   159: iadd
    //   160: i2f
    //   161: ldc 0.0078125
    //   163: fmul
    //   164: f2d
    //   165: iload #4
    //   167: iconst_0
    //   168: iadd
    //   169: i2f
    //   170: ldc 0.0078125
    //   172: fmul
    //   173: f2d
    //   174: invokevirtual Dne : (DDDDD)V
    //   177: aload #5
    //   179: invokevirtual Dne : ()I
    //   182: pop
    //   183: return
  }
  
  static void Dne(ZyA paramZyA, int paramInt1, int paramInt2, int paramInt3) {
    paramZyA.bzF(paramInt1, paramInt2, paramInt3);
  }
  
  static void FWm(ZyA paramZyA, int paramInt1, int paramInt2, int paramInt3, int paramInt4, int paramInt5, int paramInt6) {
    paramZyA.Dne(paramInt1, paramInt2, paramInt3, paramInt4, paramInt5, paramInt6);
  }
  
  public void Dne() {
    this.Dne = (LSv)KGL.Dne("gui.stats");
    this.Dne = new kmt(this);
    this.Dne.Dne((List)this.Dne, 1, 1);
    this.Dne = new LAz(this);
    this.Dne.Dne((List)this.Dne, 1, 1);
    this.Dne = new eiw(this);
    this.Dne.Dne((List)this.Dne, 1, 1);
    this.Dne = this.Dne;
    zGp();
  }
  
  static void Dne(ZyA paramZyA, int paramInt1, int paramInt2, int paramInt3, int paramInt4) {
    paramZyA.bzF(paramInt1, paramInt2, paramInt3, paramInt4);
  }
  
  static msA Dne(ZyA paramZyA) {
    return (msA)paramZyA.Dne;
  }
  
  static msA div(ZyA paramZyA) {
    return (msA)paramZyA.Dne;
  }
  
  static msA FWm(ZyA paramZyA) {
    return (msA)paramZyA.Dne;
  }
}


/* Location:              C:\Users\fract\Downloads\ERROR422.jar!\ZyA.class
 * Java compiler version: 8 (52.0)
 * JD-Core Version:       1.1.3
 */